Workbook
Name prov_cd: 'SELECT PROVINCE'!$B$1
Name province_codes: 'SELECT PROVINCE'!$B$6:$B$16
Name rate_table: 'SELECT PROVINCE'!$B$6:$C$16

Sheet 26MY_CIV5D_DATA
B1: 1 | C1: 2 | D1: 3 | E1: 4 | F1: 5 | G1: 6 | H1: 23 | I1: 24 | J1: 25 | K1: 26 | L1: 27 | M1: 28 | N1: 29 | O1: 30 | P1: 31 | Q1: 32 | R1: 33 | S1: 34 | T1: 35 | U1: 36 | V1: 37
B2: Model Name | C2: Civic Hatch & Type R | D2: Civic à Hayon & Type R | W2: Yes | X2: Yes | Y2: Yes | Z2: Yes | AA2: Yes | AB2: Yes | AC2: Yes | AD2: Yes | AE2: Yes
B3: Model Year | C3: 2026 | W3: No | X3: No | Y3: No | Z3: No | AA3: No | AB3: No | AC3: No | AD3: No | AE3: No
B4: Publication Date | C4: 46142 | D4: yyyy/mm/dd | M4: * if it's "N/A" or "S" do not show on trim | W4: NEW | X4: NEW | Y4: NEW | Z4: NEW | AA4: NEW | AB4: NEW | AC4: NEW | AD4: NEW | AE4: NEW
M5: Trim Application* | W5: N/A
B6: PARTS | C6: HAC | L6: =prov_cd -> YT | P6: SPORT | Q6: SPORT Hybride | S6: Sport Touring Hybride | T6: Type R | W6: Images | AG6: Wheels | AH6: Charging | AI6: Featured | AJ6: Included | AK6: Accessories
B7: Part Number / Kit Part Number | C7: Part Number | D7: Item Name English | E7: Item Name French | F7: Description English | G7: Description French | H7: FRT | I7: Residual-ized $ | J7: Dealer Net | K7: List Price | L7: Install Price | P7: SPORT | Q7: SPORT Hybrid | S7: Sport Touring Hybrid | T7: Type R | U7: Comments English | V7: Comments French | W7: SiteCore | X7: Overlay 1 | Y7: Overlay 2 | Z7: Overlay 3 | AA7: Overlay 4 | AB7: Overlay 5 | AC7: Overlay 6 | AD7: Overlay 7 | AE7: Overlay 8 | AF7: Display Order | AK7: Safety & Exterior Protection | AL7: Winter Season | AM7: Exterior & Interior Utility | AN7: Interior Styling | AO7: Exterior Styling | AP7: Misc-ellaneous | AR7: Dependancies | AS7: Exclusions
B8: 25CIV-ENK-WTPK | C8: 25CIV-ENK-WTPK | D8: 16” Enkei M52 Wheels & Michelin X-ICE Snow Tire Package | E8: Ensemble de roues Enkei M52 de 16 po et de pneus Michelin X-ICE Snow | F8: These attractive & custom Enkei M52 wheels are hub centric and compatible with your factory lug nuts. Compliment these wheels with the Michelin X-ICE Snow tires for the ultimate traction & style during our Canadian winters. | G8: Ces attrayantes et distinctives roues Enkei M52 sont centrées sur le moyeu et compatibles avec les écrous de roue d’origine de votre véhicule. Jumelez ces roues aux pneus Michelin X ICE Snow pour un style et une adhérence convenant parfaitement à nos hivers canadiens. | H8: 1.2 | J8: =J12+J30 -> 1596.56 | K8: =K12+K30 -> 2028 | L8: =K8+(H8*VLOOKUP(prov_cd,rate_table,2,FALSE)) -> 2245.2 | P8: • | Q8: N/A | S8: N/A | T8: N/A | U8: Priced as a set of 4 wheels. | V8: Prix établi pour ensemble de 4 pneus. | W8: Yes | AF8: 6 | AG8: • | AI8: • | AL8: •
B9: 25CIV-STL-WTPK | C9: 25CIV-STL-WTPK | D9: 16” Winter Steel Wheels & Michelin X-ICE Snow Tire Package | E9: Ensemble de roues d’hiver de 16 po en acier et de pneus Michelin X-ICE Snow | F9: Steel wheels offer great value and allow you to save your factory wheels from our harsh Canadian winters. Compliment these wheels with the Michelin X-ICE Snow tires for the ultimate traction & style during our Canadian winters. | G9: Des roues en acier offrent un excellent rapport qualité-prix et vous permettent de préserver les roues d’origine de votre véhicule de nos rigoureux hivers canadiens. Jumelez ces roues aux pneus Michelin X ICE Snow pour un une adhérence optimale lors de nos hivers canadiens. | H9: 1.2 | J9: =J12+J29 -> 1150.4 | K9: =K12+K29 -> 1522.72 | L9: =K9+(H9*VLOOKUP(prov_cd,rate_table,2,FALSE)) -> 1739.92 | P9: • | Q9: N/A | S9: N/A | T9: N/A | U9: Priced as a set of 4 wheels. | V9: Prix établi pour ensemble de 4 pneus. | W9: Yes | AF9: 7 | AG9: • | AI9: • | AL9: •
B10: 480-670-6545-SP or 480-670-6545-GB | C10: N/A only used for app chart | D10: 16" Enkei M52 Wheels - Silver or Gloss Black
B11: 480-670-6545-SP ou 480-670-6545-GB | C11: N/A only used for app chart | E11: Roues Enkei M52 de 16 po - argent ou noir brillant
B12: 34417 | C12: N/A only used for app chart | D12: Michelin X-ICE Snow Tires - 215/55/16 | E12: Pneus Michelin X-ICE Snow - 215/55/16 | J12: =VLOOKUP(B12,'[1]MASTER PART LIST'!$B:$C,2,FALSE)*4 -> 832.56 | K12: =VLOOKUP(B12,'[1]MASTER PART LIST'!$B:$D,3,FALSE)*4 -> 1000
B13: 25CIV5-ARO-PK | C13: =B14 -> 25CIV-5AR-NH883 | D13: Aero Kit | E13: Ensemble Aero | F13: Enhance the styling of your Civic Hatch with the Aero Kit. Includes body coloured front underbody spoiler and HPD Tailgate Spoiler. All packaged together with a 10% discount. | G13: Améliorez le style de votre Civic Hatch avec le Kit Aero. Comprend un déflecteur de bas de caisse avant de couleur assortie à la carrosserie et déflecteur de hayon HPD. Le tout est offert sous forme d’ensemble avec un rabais de 10 %. | H13: =H14 -> 2.2 | J13: =J14 -> 660.6 | K13: =K14 -> 1101.6 | L13: =K13+(H13*VLOOKUP(prov_cd,rate_table,2,FALSE)) -> 1499.8 | P13: • | Q13: • | S13: • | T13: N/A | U13: 10% Discount Applied. Includes body coloured front underbody spoiler and tailgate spoiler. | V13: Rabais de 10 % appliqué. Comprend déflecteur de bas de caisse avant de la couleur de la carrosserie et un becquet de hayon. | W13: Yes | AF13: 5 | AI13: • | AO13: • | AS13: Front Underbody Spoiler - 08F01-T20-130A Tailgate Spoiler, HPD - 08F02-T47-130
A14: need | B14: 25CIV-5AR-NH883 | D14: Platinum White Pearl (NH-883P) | E14: Blanc platine nacré (NH-883P) | H14: =H49+H70 -> 2.2 | J14: =(J49+J70)*0.9 -> 660.6 | K14: =(K49+K70)*0.9 -> 1101.6 | L14: =K14+(H14*VLOOKUP(prov_cd,rate_table,2,FALSE)) -> 1499.8 | P14: • | Q14: • | S14: • | T14: N/A
A15: need | B15: 25CIV-5AR-NH932 | D15: Solar Reflection Silver (NH-932M) | E15: Refl et solaire argent métallisé (NH-932M) | H15: =H50+H71 -> 2.2 | J15: =(J50+J71)*0.9 -> 660.6 | K15: =(K50+K71)*0.9 -> 1101.6 | L15: =K15+(H15*VLOOKUP(prov_cd,rate_table,2,FALSE)) -> 1499.8 | P15: • | Q15: • | S15: • | T15: N/A
A16: need | B16: 25CIV-5AR-NH904 | D16: Meteoroid Gray Pearl (NH-904M) | E16: Gris météore nacré (NH-904M) | H16: =H51+H72 -> 2.2 | J16: =(J51+J72)*0.9 -> 660.6 | K16: =(K51+K72)*0.9 -> 1101.6 | L16: =K16+(H16*VLOOKUP(prov_cd,rate_table,2,FALSE)) -> 1499.8 | P16: N/A | Q16: • | S16: N/A | T16: N/A
A17: need | B17: 25CIV-5AR-NH912 | D17: Urban Grey Pearl (NH-912P) | E17: Gris urbain nacré (NH-912P) | H17: =H137+H139 -> 2.2 | J17: =(J137+J139)*0.9 -> 660.6 | K17: =(K137+K139)*0.9 -> 1101.6 | L17: =K17+(H17*VLOOKUP(prov_cd,rate_table,2,FALSE)) -> 1499.8 | P17: N/A | Q17: N/A | S17: • | T17: N/A
A18: need | B18: 25CIV-5AR-NH731 | D18: Crystal Black Pearl (NH-731P) | E18: Noir cristal nacré (NH-731P) | H18: =H52+H73 -> 2.2 | J18: =(J52+J73)*0.9 -> 660.6 | K18: =(K52+K73)*0.9 -> 1101.6 | L18: =K18+(H18*VLOOKUP(prov_cd,rate_table,2,FALSE)) -> 1499.8 | P18: • | Q18: • | S18: • | T18: N/A
A19: need | B19: 25CIV-5AR-R513 | D19: Rallye Red (R-513) | E19: Rouge rallye (R-513) | H19: =H53+H74 -> 2.2 | J19: =(J53+J74)*0.9 -> 660.6 | K19: =(K53+K74)*0.9 -> 1101.6 | L19: =K19+(H19*VLOOKUP(prov_cd,rate_table,2,FALSE)) -> 1499.8 | P19: N/A | Q19: • | S19: • | T19: N/A
A20: need | B20: 25CIV-5AR-B637 | D20: Boost Blue Pearl (B-637P) | E20: Bleu turbo nacré (B-637P) | H20: =H138+H75 -> 2.2 | J20: =(J54+J75)*0.9 -> 660.6 | K20: =(K54+K75)*0.9 -> 1101.6 | L20: =K20+(H20*VLOOKUP(prov_cd,rate_table,2,FALSE)) -> 1499.8 | P20: N/A | Q20: N/A | S20: • | T20: N/A
B21: 22CIV-COLD-PK20 | C21: 22CIV-COLD-PK20 | D21: Cold Weather Package - 2.0L | E21: Ensemble de temps froid - 2,0 L | F21: Package includes: Engine Block Heater and Auto Battery Charger/Maintainer. Packaged together with a 5% discount. | G21: L’ensemble inclut : Chauffe-moteur et chargeur/mainteneur automatique de batterie de 12 V Optimate. Offerts en ensemble avec une remise de 5 %. | H21: =H86+H88 -> 1.4 | J21: =(J86+J88)*0.95 -> 230.85 | K21: =(K86+K88)*0.95 -> 384.75 | L21: =K21+(H21*VLOOKUP(prov_cd,rate_table,2,FALSE)) -> 638.15 | P21: • | Q21: • | S21: • | T21: N/A | U21: 5% Discount Applied. | V21: Rabais de 5 % appliqué. | W21: Yes | AF21: 9 | AI21: • | AL21: • | AS21: Engine Block Heater - 2.0L - 08T44-SNA-302 Optimate 12V Auto Battery Charger/Maintainer - 31670-BMS-004H
B22: 23CIV-COLD-TR | C22: 23CIV-COLD-TR | D22: Cold Weather Package - Type R | E22: Ensemble de temps froid - Type R | F22: Package includes: Engine Block Heater and Auto Battery Charger/Maintainer. Packaged together with a 5% discount. | G22: L’ensemble inclut : Chauffe-moteur et chargeur/mainteneur automatique de batterie de 12 V Optimate. Offerts en ensemble avec une remise de 5 %. | H22: =H102+H88 -> 1.4 | J22: =(J102+J88)*0.95 -> 278.35 | K22: =(K102+K88)*0.95 -> 464.55 | L22: =K22+(H22*VLOOKUP(prov_cd,rate_table,2,FALSE)) -> 717.95 | P22: N/A | Q22: N/A | S22: N/A | T22: • | U22: 5% Discount Applied. | V22: Rabais de 5 % appliqué. | AK22: • | AS22: Engine Block Heater Type R - 08T44-TGH-300 Optimate 12V Auto Battery Charger/Maintainer - 31670-BMS-004H
B23: 25CIV5D-PRO-PET | C23: =B23 -> 25CIV5D-PRO-PET | D23: Protection Package - Petrol | E23: Ensemble de protection - Petrol | F23: Package includes: All-Season Floor Mats, Rear Splash Guards, and Trunk Tray. | G23: L’ensemble inclut : Tapis toutes saisons, garde-boue arrière, et plateau de coffre. | H23: =H79+H84+H47 -> 0.6 | J23: =(J79+J84+J47)*0.9 -> 297 | K23: =K79+K84+K47 -> 550 | L23: =K23+(H23*VLOOKUP(prov_cd,rate_table,2,FALSE)) -> 658.6 | P23: • | Q23: N/A | S23: N/A | T23: N/A | W23: Yes | AF23: 2 | AI23: • | AM23: • | AS23: Floor Mats - All-Season - 08P17-T20-110 Trunk Tray - 08U45-T47-100B Rear Splash Guards - 08P09-T47-300
B24: 25CIV5-PRO-HYB | C24: 25CIV5-PRO-HYB | D24: Protection Package - Hybrid | E24: Ensemble de protection - Hybrid | F24: Package includes: All-Season Floor Mats, Rear Splash Guards, and Trunk Tray. | G24: L’ensemble inclut : Tapis toutes saisons, garde-boue arrière, et plateau de coffre. | H24: =H80+H84+H47 -> 0.6 | J24: =(J80+J84+J47)*0.9 -> 297 | K24: =K80+K84+K47 -> 550 | L24: =K24+(H24*VLOOKUP(prov_cd,rate_table,2,FALSE)) -> 658.6 | P24: N/A | Q24: • | S24: • | T24: N/A | W24: Yes | AF24: 3 | AI24: • | AM24: • | AS24: Floor Mats Hybrid - All-Season - 08P17-T20-110A Trunk Tray - 08U45-T47-100 Rear Splash Guards - 08P09-T47-300
B25: 23TYPER-PROPK | C25: =B25 -> 23TYPER-PROPK | D25: Protection Package - Type R | E25: Ensemble de protection - Type R | F25: Package includes: All-Season Floor Mats, and Cargo Tray. | G25: L’ensemble inclut : Tapis toutes saisons et plateau de coffre. | H25: =(H79+H108) -> 0.2 | J25: =(J79+J108)*0.9 -> 245.7 | K25: =(K79+K108) -> 455 | L25: =K25+(H25*VLOOKUP(prov_cd,rate_table,2,FALSE)) -> 491.2 | P25: N/A | Q25: N/A | S25: N/A | T25: • | AF25: 4 | AI25: • | AS25: Floor Mats All-Season Type R - 08P17-T20-110 Cargo Tray Type R - 08U45-T60-100
B26: 25CIV5-PRO-FLM | C26: 25CIV5-PRO-FLM | D26: Protection Package - Film | E26: Ensemble de protection - Film | F26: Package includes: Door Edge and Door Sill Protection Films, and Rear Bumper Applique. | G26: L’ensemble inclut : Pellicule pour rebord de portière, pellicule de protection de seuil de portière, et pellicule pour pare-chocs arrière. | H26: =H46+H41+H78 -> 1 | J26: =(J46+J41+J78)*0.9 -> 205.2 | K26: =(K46+K41+K78)*0.9 -> 330.3 | L26: =K26+(H26*VLOOKUP(prov_cd,rate_table,2,FALSE)) -> 511.3 | P26: N/A | Q26: N/A | S26: N/A | T26: N/A | U26: 10% Discount Applied. Cannot be installed with Door Edge Guards | V26: Rabais de 10 % appliqué. Ne peut être installé simultanément avec protecteurs de bordure de porte. | W26: Yes | AF26: 8 | AI26: • | AK26: • | AS26: Door Edge Film - 08P20-T20-100A Door Sill Protection Film - 08P04-T20-100 08P01-T47-100 Rear Bumper Protector
B27: 26TYPER-RACE | C27: =B27 -> 26TYPER-RACE | D27: Racing Package - Type R | E27: Ensemble de course – Type R | F27: Package includes: Carbon Fiber Wing Spoiler, Alcantara Steering Wheel and Red Leather Shift Knob | G27: L'ensemble comprend un aileron arrière en fibre de carbone, un volant en Alcantara et un pommeau de levier de vitesse gainé de cuir rouge. | H27: =H105+H109+H110 -> 1 | J27: =J105+J109+J110 -> 3928 | K27: =K105+K109+K110 -> 6431 | L27: =K27+(H27*VLOOKUP(prov_cd,rate_table,2,FALSE)) -> 6612 | P27: N/A | Q27: N/A | S27: N/A | T27: • | AF27: 1 | AI27: •
A29: no image | B29: 42700-TBA-A12 | C29: 42700-TBA-A12 | D29: 16” Winter Steel Wheels | E29: Roues d’hiver de 16 po en acier | F29: Steel wheels offer great value and allow you to save your factory wheels from our harsh Canadian winters. Price listed excludes winter tires and installation. Set of 4. | G29: Des roues en acier offrent un excellent rapport qualité-prix et vous permettent de préserver les roues d’origine de votre véhicule de nos rigoureux hivers canadiens. Le prix indiqué exclut les pneus d'hiver et l'installation. Ensemble de quatre. | H29: 1.6 | J29: =VLOOKUP(B29,'[1]MASTER PART LIST'!$B:$C,2,FALSE)*4 -> 317.84 | K29: =VLOOKUP(B29,'[1]MASTER PART LIST'!$B:$D,3,FALSE)*4 -> 522.72 | L29: =K29+(H29*VLOOKUP(prov_cd,rate_table,2,FALSE)) -> 812.32 | P29: • | Q29: N/A | S29: N/A | T29: N/A | U29: Priced as a set of 4 wheels. Tires sold separately. | V29: Prix pour un ensemble de 4 roues. Pneus vendus séparément. | AF29: 12 | AG29: • | AK29: •
B30: 480-670-6545GB | C30: 480-670-6545GB | D30: 16" Enkei M52 Wheel - Gloss Black | E30: Jantes Enkei M52 de 16 po noir lustré | F30: Look great all year round with a custom set of attractive winter alloy wheels. Designed & Approved for your Honda, these attractive and strong Enkei alloy wheels are compatible with your factory lug nuts & feature a unique hub centric design. Priced as a set of 4 wheels. Tires sold separately. | G30: Vous aurez fière allure tout au long de l'année avec un ensemble personnalisé de jantes en alliage pour l'hiver. Conçues et approuvées pour votre Honda, ces jantes en alliage Enkei robustes et attrayantes sont compatibles avec vos écrous de roue d'origine et présentent une conception unique centrée sur le moyeu. Prix pour un jeu de 4 jantes. Pneus vendus séparément. | H30: 1.6 | J30: =VLOOKUP(B30,'[1]MASTER PART LIST'!$B:$C,2,FALSE)*4 -> 764 | K30: =VLOOKUP(B30,'[1]MASTER PART LIST'!$B:$D,3,FALSE)*4 -> 1028 | L30: =K30+(H30*VLOOKUP(prov_cd,rate_table,2,FALSE)) -> 1317.6 | P30: T | Q30: N/A | S30: N/A | T30: N/A | U30: Priced as a set of 4 wheels. Tires sold separately. | V30: Prix pour un ensemble de 4 roues. Pneus vendus séparément. | W30: Yes | AF30: 13 | AG30: • | AK30: •
B31: 480-670-6545SP | C31: 480-670-6545SP | D31: 16" Enkei M52 Wheel - Silver | E31: Jantes Enkei M52 de 16 po argent | F31: Look great all year round with a custom set of attractive winter alloy wheels. Designed & Approved for your Honda, these attractive and strong Enkei alloy wheels are compatible with your factory lug nuts & feature a unique hub centric design. Priced as a set of 4 wheels. Tires sold separately. | G31: Vous aurez fière allure tout au long de l'année avec un ensemble personnalisé de jantes en alliage pour l'hiver. Conçues et approuvées pour votre Honda, ces jantes en alliage Enkei robustes et attrayantes sont compatibles avec vos écrous de roue d'origine et présentent une conception unique centrée sur le moyeu. Prix pour un jeu de 4 jantes. Pneus vendus séparément. | H31: 1.6 | J31: =VLOOKUP(B31,'[1]MASTER PART LIST'!$B:$C,2,FALSE)*4 -> 764 | K31: =VLOOKUP(B31,'[1]MASTER PART LIST'!$B:$D,3,FALSE)*4 -> 1028 | L31: =K31+(H31*VLOOKUP(prov_cd,rate_table,2,FALSE)) -> 1317.6 | P31: T | Q31: N/A | S31: N/A | T31: N/A | U31: Priced as a set of 4 wheels. Tires sold separately. | V31: Prix pour un ensemble de 4 roues. Pneus vendus séparément. | W31: Yes | AF31: 14 | AG31: • | AK31: •
B32: 509-775-6545BH | C32: 509-775-6545BH | D32: 17" Enkei Draco Wheel, Gloss Black | E32: Jantes Enkei de 17 po noir lustré | F32: Look great all year round with a custom set of attractive winter alloy wheels. Designed & Approved for your Honda, these attractive and strong Enkei alloy wheels are compatible with your factory lug nuts & feature a unique hub centric design. Priced as a set of 4 wheels. Tires sold separately. | G32: Vous aurez fière allure tout au long de l'année avec un ensemble personnalisé de jantes en alliage pour l'hiver. Conçues et approuvées pour votre Honda, ces jantes en alliage Enkei robustes et attrayantes sont compatibles avec vos écrous de roue d'origine et présentent une conception unique centrée sur le moyeu. Prix pour un jeu de 4 jantes. Pneus vendus séparément. | H32: 1.6 | J32: =VLOOKUP(B32,'[1]MASTER PART LIST'!$B:$C,2,FALSE)*4 -> 856 | K32: =VLOOKUP(B32,'[1]MASTER PART LIST'!$B:$D,3,FALSE)*4 -> 1148 | L32: =K32+(H32*VLOOKUP(prov_cd,rate_table,2,FALSE)) -> 1437.6 | P32: T | Q32: N/A | S32: N/A | T32: N/A | U32: Priced as a set of 4 wheels. Tires sold separately. | V32: Prix pour un ensemble de 4 roues. Pneus vendus séparément. | W32: Yes | AF32: 15 | AG32: •
B33: 509-775-6545SH | C33: 509-775-6545SH | D33: 17" Enkei Draco Wheel, Silver | E33: Jantes Enkei de 17 po argent | F33: Look great all year round with a custom set of attractive winter alloy wheels. Designed & Approved for your Honda, these attractive and strong Enkei alloy wheels are compatible with your factory lug nuts & feature a unique hub centric design. Priced as a set of 4 wheels. Tires sold separately. | G33: Vous aurez fière allure tout au long de l'année avec un ensemble personnalisé de jantes en alliage pour l'hiver. Conçues et approuvées pour votre Honda, ces jantes en alliage Enkei robustes et attrayantes sont compatibles avec vos écrous de roue d'origine et présentent une conception unique centrée sur le moyeu. Prix pour un jeu de 4 jantes. Pneus vendus séparément. | H33: 1.6 | J33: =VLOOKUP(B33,'[1]MASTER PART LIST'!$B:$C,2,FALSE)*4 -> 856 | K33: =VLOOKUP(B33,'[1]MASTER PART LIST'!$B:$D,3,FALSE)*4 -> 1148 | L33: =K33+(H33*VLOOKUP(prov_cd,rate_table,2,FALSE)) -> 1437.6 | P33: T | Q33: N/A | S33: N/A | T33: N/A | U33: Priced as a set of 4 wheels. Tires sold separately. | V33: Prix pour un ensemble de 4 roues. Pneus vendus séparément. | W33: Yes | AF33: 16 | AG33: •
B34: 08W18-T20-100 | C34: 08W18-T20-100 | D34: 18" Alloy Wheel - Black | E34: Jantes de 18 pouces noir | F34: Attract even more attention with these stunning 18" Alloy Wheels structurally matched to the original vehicle design so that handling remains undisturbed. Priced as a set of 4. Recommended tires sold separately. | G34: Attirez encore plus l’attention avec ces superbes jantes de 18 pouces dont la structure est adaptée à la conception originale du véhicule afin que la maniabilité reste inchangée. Prix pour ensemble de 4. Pneus recommandés vendus séparément | H34: 1.6 | J34: =VLOOKUP(B34,'[1]MASTER PART LIST'!$B:$C,2,FALSE)*4 -> 2316 | K34: =VLOOKUP(B34,'[1]MASTER PART LIST'!$B:$D,3,FALSE)*4 -> 3564 | L34: =K34+(H34*VLOOKUP(prov_cd,rate_table,2,FALSE)) -> 3853.6 | P34: E | Q34: E | S34: E | T34: N/A | U34: Priced as a set of 4 wheels. Tires sold separately. | V34: Prix pour un ensemble de 4 roues. Pneus vendus séparément. | W34: Yes | X34: No | Y34: No | Z34: No | AF34: 10 | AG34: •
B35: 08W19-T60-100 | C35: =B35 -> 08W19-T60-100 | D35: 19" Light Weight Alloy Wheel | E35: Jantes de 19 pouces | F35: Stronger, lighter, and visually distinct, these Alloy Wheels are everything you want rolled into an impressive presentation. 5.29 pounds lighter than OEM wheels. Distinct Shark Gray metallic-finish, laser-etched logo | G35: Plus résistantes, plus légères et visuellement distinctes, ces jantes en alliage ont tout ce que vous recherchez, réunies dans une présentation impressionnante.. Pèsent moins de 5,29 livres que les roues d’origine. Fini gris requin métallisé distinct, logo gravé au laser. | H35: 1.6 | J35: =VLOOKUP(B35,'[1]MASTER PART LIST'!$B:$C,2,FALSE)*4 -> 4664 | K35: =VLOOKUP(B35,'[1]MASTER PART LIST'!$B:$D,3,FALSE)*4 -> 6664 | L35: =K35+(H35*VLOOKUP(prov_cd,rate_table,2,FALSE)) -> 6953.6 | P35: N/A | Q35: N/A | S35: N/A | T35: E | U35: Priced as a set of 4 wheels. Tires sold separately. Laser-etched logo & shark gray metallic finish | V35: Prix pour un ensemble de 4 roues. Pneus vendus séparément. | AF35: 11 | AG35: •
A36: ** needs to be added to WEB** | B36: 08W42-TG7-301A | C36: 08W42-TG7-301A | D36: Wheel Locks - Black (Type R) | E36: Écrous de roue antivols - Noirs (Type R) | F36: A great way to help ensure that your wheels stay on your vehicle where they belong. | G36: Un excellent moyen de vous assurer que les roues demeurent sur votre véhicule là où elles devraient se trouver. | H36: 0.2 | J36: =VLOOKUP(B36,'[1]MASTER PART LIST'!$B:$C,2,FALSE) -> 88 | K36: =VLOOKUP(B36,'[1]MASTER PART LIST'!$B:$D,3,FALSE) -> 147 | L36: =K36+(H36*VLOOKUP(prov_cd,rate_table,2,FALSE)) -> 183.2 | P36: N/A | Q36: N/A | S36: N/A | T36: • | AF36: 17 | AK36: •
B37: 08W42-TK4-301 | C37: 08W42-TK4-301 | D37: Wheel Locks - Chrome (Type R) | E37: Écrous de roue antivols - Chromés (Type R) | F37: A great way to help ensure that your wheels stay on your vehicle where they belong. Chrome-plated triple-nickel finish for a brilliant shine and corrosion prevention | G37: Un excellent moyen de vous assurer que les roues demeurent sur votre véhicule, où elles devraient se trouver. La finition chromée triple nickel procure un éclat brillant et une prévention contre la corrosion. | H37: 0.2 | J37: =VLOOKUP(B37,'[1]MASTER PART LIST'!$B:$C,2,FALSE) -> 94 | K37: =VLOOKUP(B37,'[1]MASTER PART LIST'!$B:$D,3,FALSE) -> 157 | L37: =K37+(H37*VLOOKUP(prov_cd,rate_table,2,FALSE)) -> 193.2 | P37: N/A | Q37: N/A | S37: N/A | T37: • | AF37: 18 | AK37: •
B38: 08W42-S2A-101 | C38: 08W42-S2A-101 | D38: Wheel Locks - Black | E38: Écrous de roue antivols - Noirs | F38: A great way to help ensure that your wheels stay on your vehicle where they belong. Functions like a regular lug nut, but requires a special key tool for installation and removal. Hardened-steel construction is durable and theft-resistant. | G38: Un excellent moyen de vous assurer que les roues demeurent sur votre véhicule, là où elles devraient se trouver. S’utilisent comme des écrous réguliers, mais nécessitent un outil spécial pour l’installation et le retrait. Fabriqués en acier trempé, ils sont durables et antivol. | H38: 0.2 | J38: =VLOOKUP(B38,'[1]MASTER PART LIST'!$B:$C,2,FALSE) -> 61 | K38: =VLOOKUP(B38,'[1]MASTER PART LIST'!$B:$D,3,FALSE) -> 102 | L38: =K38+(H38*VLOOKUP(prov_cd,rate_table,2,FALSE)) -> 138.2 | P38: • | Q38: • | S38: • | T38: N/A | W38: Yes | AF38: 19 | AK38: • | AS38: 08W42-SCV-302 Wheel Locks - Chrome
B39: 08W42-SCV-302 | C39: 08W42-SCV-302 | D39: Wheel Locks - Chrome | E39: Écrous de roue antivols - Chromés | F39: A great way to help ensure that your wheels stay on your vehicle where they belong. Chrome-plated triple-nickel finish for a brilliant shine and corrosion prevention | G39: Un excellent moyen de vous assurer que les roues demeurent sur votre véhicule, où elles devraient se trouver. La finition chromée triple nickel procure un éclat brillant et une prévention contre la corrosion. | H39: 0.2 | J39: =VLOOKUP(B39,'[1]MASTER PART LIST'!$B:$C,2,FALSE) -> 54 | K39: =VLOOKUP(B39,'[1]MASTER PART LIST'!$B:$D,3,FALSE) -> 90 | L39: =K39+(H39*VLOOKUP(prov_cd,rate_table,2,FALSE)) -> 126.2 | P39: • | Q39: • | S39: • | T39: N/A | W39: Yes | AF39: 20 | AK39: • | AS39: 08W42-S2A-101 Wheel Locks - Black
B40: 08W42-TGG-100 | C40: 08W42-TGG-101 | D40: Wheel Lug Nuts - Black | E40: Écrous de roue - Noir | F40: Create a different look with a set of black lug nuts. Each package has a quantity of 4 lugs. | G40: Créez un aspect différent grâce à cet ensemble d’écrous de roue noirs qui complète les roues en alliage du véhicule. Chaque paquet contient 4 écrous de roue. | H40: 0.2 | J40: =VLOOKUP(B40,'[1]MASTER PART LIST'!$B:$C,2,FALSE) -> 57 | K40: =VLOOKUP(B40,'[1]MASTER PART LIST'!$B:$D,3,FALSE) -> 91 | L40: =K40+(H40*VLOOKUP(prov_cd,rate_table,2,FALSE)) -> 127.2 | P40: • | Q40: • | S40: • | T40: N/A | U40: Includes: 1 set (i.e. 4 lug nuts). A complete install requires 5 sets (i.e. 20 lug nuts) for 4 wheels. | V40: Inclut 4 écrous de roue en 1 jeu. L'installation complète nécessite 5 jeux pour 4 roues (20 écrous de roue). | W40: Yes | AF40: 21 | AO40: •
B41: 08P20-T20-100A | C41: 08P20-T20-100A | D41: Door Edge Film | E41: Pellicule pour rebord de portière | F41: Help protect against unsightly nicks and scrapes around your door edges. | G41: La pellicule aide à protéger les surfaces des rebords de portières contre des égratignures et éraflures inesthétiques. | H41: 0.5 | J41: =VLOOKUP(B41,'[1]MASTER PART LIST'!$B:$C,2,FALSE) -> 67 | K41: =VLOOKUP(B41,'[1]MASTER PART LIST'!$B:$D,3,FALSE) -> 112 | L41: =K41+(H41*VLOOKUP(prov_cd,rate_table,2,FALSE)) -> 202.5 | P41: • | Q41: • | S41: • | T41: N/A | U41: Cannot be installed with Door Edge Guards | V41: Ne peut être installé simultanément avec protecteurs de bordure de porte. | W41: Yes | AF41: 48 | AK41: • | AS41: 25CIV5-PRO-FLM Protection Package - Film 08P20-T20-130 Door Edge Guards
B42: 08R04-T47-100A | C42: 08R04-T47-100A | D42: Door Visors - Black | E42: Déflecteurs de portières - noir | F42: A great way to enjoy some fresh air even when the weather may not be ideal. | G42: Une excellente façon de profiter de l’air frais même lorsque la météo n’est pas au rendez-vous. | H42: 0.5 | J42: =VLOOKUP(B42,'[1]MASTER PART LIST'!$B:$C,2,FALSE) -> 207 | K42: =VLOOKUP(B42,'[1]MASTER PART LIST'!$B:$D,3,FALSE) -> 345 | L42: =K42+(H42*VLOOKUP(prov_cd,rate_table,2,FALSE)) -> 435.5 | P42: • | Q42: • | S42: • | T42: • | W42: Yes | AF42: 28 | AM42: •
B43: 08F20-T47-100E | C43: =B43 -> 08F20-T47-100E | D43: Black Emblem H-Mark | E43: Emblèmes « H » noirs | F43: If attention to detail is important to you then you’re sure to love the look of the Black H-Mark emblems. Includes front and rear emblems | G43: Si l’attention aux détails est importante pour vous, alors vous aimerez certainement l’allure des emblèmes « H » noirs. Comprend les emblèmes avant et arrière. | H43: 0.7 | J43: =VLOOKUP(B43,'[1]MASTER PART LIST'!$B:$C,2,FALSE) -> 86 | K43: =VLOOKUP(B43,'[1]MASTER PART LIST'!$B:$D,3,FALSE) -> 123 | L43: =K43+(H43*VLOOKUP(prov_cd,rate_table,2,FALSE)) -> 249.7 | P43: • | Q43: • | S43: • | T43: N/A | U43: Front and Rear H-Mark Logo. | V43: Logo H-Mark à l'avant et à l'arrière. | W43: Yes | X43: N/A | Y43: N/A | Z43: No | AO43: • | AS43: 25CIV5-MBM-SPT Black Emblem Set - SPORT 25CIV5-MBM-SPHY Black Emblem Set - Sport Hybrid
B44: 08P47-T20-300 | C44: 08P47-T20-300 | D44: Hood Protector | E44: Protecteur de capot | F44: The Hood Protector redirects dirt, insects, and minor road debris to help keep the windshield clean and protect the hood’s finish. | G44: Le protecteur de capot redirige la saleté, les insectes et les petits débris de la route pour aider à garder votre pare-brise propre et à protéger le fini du capot. | H44: 0.6 | J44: =VLOOKUP(B44,'[1]MASTER PART LIST'!$B:$C,2,FALSE) -> 221 | K44: =VLOOKUP(B44,'[1]MASTER PART LIST'!$B:$D,3,FALSE) -> 368 | L44: =K44+(H44*VLOOKUP(prov_cd,rate_table,2,FALSE)) -> 476.6 | P44: • | Q44: • | S44: • | T44: N/A | W44: Yes | AF44: 69 | AM44: •
B45: 08R01-T20-300 | C45: 08R01-T20-300 | D45: Moonroof Visor | E45: Déflecteur de toit ouvrant | F45: The Moonroof Visor helps reduce wind noise and glare for a more comfortable and enjoyable driving experience. | G45: Le déflecteur de toit contribue à réduire le bruit du vent et l'éblouissement pour une expérience de conduite plus confortable et plus agréable. | H45: 0.3 | J45: =VLOOKUP(B45,'[1]MASTER PART LIST'!$B:$C,2,FALSE) -> 174 | K45: =VLOOKUP(B45,'[1]MASTER PART LIST'!$B:$D,3,FALSE) -> 290 | L45: =K45+(H45*VLOOKUP(prov_cd,rate_table,2,FALSE)) -> 344.3 | P45: • | Q45: • | S45: • | T45: N/A | W45: Yes | AF45: 29 | AM45: •
B46: 08P01-T47-100 | C46: 08P01-T47-100 | D46: Rear Bumper Protector | E46: Protection de pare-chocs arrière | F46: The Rear Bumper Protector enhances your exterior while helping to prevent scratches when loading and unloading. Constructed of brushed stainless steel. Tested for extreme temperatures. | G46: Le déflecteur de hayon donne une allure encore plus sportive et unique au style aérodynamique de la Civic. Couleur assortie aux spécifications de la couleur d’origine pour une apparence personnalisée. Fait de résine ABS moulée par injection offrant de la durabilité et un ajustement parfait. Matériel d’installation conçu et fabriqué spécialement pour chaque véhicule. Les emblèmes de couleur noir lustré sont disponibles comme accessoires séparés. | H46: 0.1 | J46: =VLOOKUP(B46,'[1]MASTER PART LIST'!$B:$C,2,FALSE) -> 58 | K46: =VLOOKUP(B46,'[1]MASTER PART LIST'!$B:$D,3,FALSE) -> 83 | L46: =K46+(H46*VLOOKUP(prov_cd,rate_table,2,FALSE)) -> 101.1 | P46: • | Q46: • | S46: • | T46: N/A | W46: Yes | AF46: 50 | AM46: • | AS46: 25CIV5-PRO-FLM Protection Package - Film
B47: 08P09-T47-300 | C47: 08P09-T47-300 | D47: Splash Guards - Rear | E47: Garde-boue arrière | F47: Rear Splash Guards are a nice finishing touch. They give your Civic a great look and help protect your paint from chips and stains. Custom-fitted in wheelwells to blend in with vehicle design. No-drill installation helps protect against corrosion. Superior strength and durability in nearly any weather condition. | G47: Les garde-boue arrière ajoutent une touche finale soignée. Les garde-boue procurent une belle apparence à votre Civic à hayon et contribuent à protéger la peinture contre les éclats et les taches. Ils s’ajustent sur mesure dans les passages de roue pour s’agencer au design du véhicule. L’installation sans perçage aide à protéger contre la corrosion. Résistance et durabilité supérieures dans presque toutes les conditions météorologiques. | H47: 0.4 | J47: =VLOOKUP(B47,'[1]MASTER PART LIST'!$B:$C,2,FALSE) -> 63 | K47: =VLOOKUP(B47,'[1]MASTER PART LIST'!$B:$D,3,FALSE) -> 105 | L47: =K47+(H47*VLOOKUP(prov_cd,rate_table,2,FALSE)) -> 177.4 | P47: • | Q47: • | S47: • | T47: N/A | W47: Yes | AF47: 70 | AM47: • | AS47: 25CIV5D-PRO-PET Protection Package - Petrol 25CIV5-PRO-HYB Protection Package - Hybrid
B48: 08F01-T20-XXXX | C48: 08F01-T20-130A | D48: Front Underbody Spoiler | E48: Déflecteur de bas de caisse avant | F48: Turn heads with accentuated aerodynamic styling created by the Rear Underbody Spoiler. It adds a sleek, sporty, low-profile custom look. Complete the look with the addition of the side and rear underbody spoilers - sold separately. | G48: Faites tourner les têtes avec ce déflecteur de bas de caisse avant qui donne un style aérodynamique accentué. Il procure une touche personnalisée élégante qui confère une allure sportive et un profil abaissé. . Complétez l’apparence en ajoutant des déflecteurs de bas de caisse latéraux et arrière (vendus séparément). | H48: =H49 -> 1 | J48: =J49 -> 262 | K48: =K49 -> 437 | L48: =K48+(H48*VLOOKUP(prov_cd,rate_table,2,FALSE)) -> 618 | P48: • | Q48: • | S48: • | T48: N/A | W48: Yes | AF48: 25 | AO48: • | AS48: 25CIV-5AR-NH883 Aero Kit
B49: 08F01-T20-130A | C49: N/A | D49: Platinum White Pearl (NH-883P) | E49: Blanc platine nacré (NH-883P) | H49: 1 | J49: =VLOOKUP(B49,'[1]MASTER PART LIST'!$B:$C,2,FALSE) -> 262 | K49: =VLOOKUP(B49,'[1]MASTER PART LIST'!$B:$D,3,FALSE) -> 437 | L49: =K49+(H49*VLOOKUP(prov_cd,rate_table,2,FALSE)) -> 618 | P49: • | Q49: • | S49: • | T49: N/A | W49: Yes
B50: 08F01-T20-1Z0A | C50: N/A | D50: Solar Reflection Silver (NH-932M) | E50: Refl et solaire argent métallisé (NH-932M) | H50: 1 | J50: =VLOOKUP(B50,'[1]MASTER PART LIST'!$B:$C,2,FALSE) -> 262 | K50: =VLOOKUP(B50,'[1]MASTER PART LIST'!$B:$D,3,FALSE) -> 437 | L50: =K50+(H50*VLOOKUP(prov_cd,rate_table,2,FALSE)) -> 618 | P50: • | Q50: • | S50: • | T50: N/A | W50: Yes
B51: 08F01-T20-170A | C51: N/A | D51: Meteoroid Gray Pearl (NH-904M) | E51: Gris météore nacré (NH-904M) | H51: 1 | J51: =VLOOKUP(B51,'[1]MASTER PART LIST'!$B:$C,2,FALSE) -> 262 | K51: =VLOOKUP(B51,'[1]MASTER PART LIST'!$B:$D,3,FALSE) -> 437 | L51: =K51+(H51*VLOOKUP(prov_cd,rate_table,2,FALSE)) -> 618 | P51: N/A | Q51: • | S51: N/A | T51: N/A | W51: Yes
B52: 08F01-T20-180A | C52: N/A | D52: Crystal Black Pearl (NH-731P) | E52: Noir cristal nacré (NH-731P) | H52: 1 | J52: =VLOOKUP(B52,'[1]MASTER PART LIST'!$B:$C,2,FALSE) -> 262 | K52: =VLOOKUP(B52,'[1]MASTER PART LIST'!$B:$D,3,FALSE) -> 437 | L52: =K52+(H52*VLOOKUP(prov_cd,rate_table,2,FALSE)) -> 618 | P52: • | Q52: • | S52: • | T52: N/A | W52: Yes
B53: 08F01-T20-190A | C53: N/A | D53: Rallye Red (R-513) | E53: Rouge rallye (R-513) | H53: 1 | J53: =VLOOKUP(B53,'[1]MASTER PART LIST'!$B:$C,2,FALSE) -> 262 | K53: =VLOOKUP(B53,'[1]MASTER PART LIST'!$B:$D,3,FALSE) -> 437 | L53: =K53+(H53*VLOOKUP(prov_cd,rate_table,2,FALSE)) -> 618 | P53: N/A | Q53: • | S53: • | T53: N/A | W53: Yes
B54: 08F01-T20-1U0A | C54: N/A | D54: Boost Blue Pearl (B-637P) | E54: Bleu turbo nacré (B-637P) | H54: 1 | J54: =VLOOKUP(B54,'[1]MASTER PART LIST'!$B:$C,2,FALSE) -> 262 | K54: =VLOOKUP(B54,'[1]MASTER PART LIST'!$B:$D,3,FALSE) -> 437 | L54: =K54+(H54*VLOOKUP(prov_cd,rate_table,2,FALSE)) -> 618 | P54: N/A | Q54: N/A | S54: • | T54: N/A | W54: Yes
B55: 08P05-T20-XXXX | C55: 08P05-T20-130 | D55: Body Side Moulding | E55: Moulure latérale | F55: Body Side Moulding accentuates the styling of the Civic and is ideally positioned where the side panel extends out the most, in order to help protect against door dings and scratches. | G55: Non seulement la moulure latérale accentue le style du Civic, son positionnement est idéal à l’endroit où les panneaux latéraux sont le plus en saillie, contribuant à protéger les portières des bosselures et des égratignures. | H55: =H58 -> 0.4 | J55: =J56 -> 215 | K55: =K56 -> 358 | L55: =K55+(H55*VLOOKUP(prov_cd,rate_table,2,FALSE)) -> 430.4 | P55: • | Q55: • | S55: • | T55: N/A | W55: Yes | AF55: 30 | AK55: •
B56: 08P05-T20-130 | C56: N/A | D56: Platinum White Pearl (NH-883P) | E56: Blanc platine nacré (NH-883P) | H56: 0.4 | J56: =VLOOKUP(B56,'[1]MASTER PART LIST'!$B:$C,2,FALSE) -> 215 | K56: =VLOOKUP(B56,'[1]MASTER PART LIST'!$B:$D,3,FALSE) -> 358 | L56: =K56+(H56*VLOOKUP(prov_cd,rate_table,2,FALSE)) -> 430.4 | P56: • | Q56: • | S56: • | T56: N/A | W56: Yes
B57: 08P05-T20-1Z0 | C57: N/A | D57: Solar Reflection Silver (NH-932M) | E57: Refl et solaire argent métallisé (NH-932M) | H57: 0.4 | J57: =VLOOKUP(B57,'[1]MASTER PART LIST'!$B:$C,2,FALSE) -> 215 | K57: =VLOOKUP(B57,'[1]MASTER PART LIST'!$B:$D,3,FALSE) -> 358 | L57: =K57+(H57*VLOOKUP(prov_cd,rate_table,2,FALSE)) -> 430.4 | P57: • | Q57: N/A | S57: N/A | T57: N/A | W57: Yes
B58: 08P05-T20-170 | C58: N/A | D58: Meteoroid Gray Pearl (NH-904M) | E58: Gris météore nacré (NH-904M) | H58: 0.4 | J58: =VLOOKUP(B58,'[1]MASTER PART LIST'!$B:$C,2,FALSE) -> 215 | K58: =VLOOKUP(B58,'[1]MASTER PART LIST'!$B:$D,3,FALSE) -> 358 | L58: =K58+(H58*VLOOKUP(prov_cd,rate_table,2,FALSE)) -> 430.4 | P58: N/A | Q58: • | S58: N/A | T58: N/A | W58: Yes
B59: 08P05-T20-180 | C59: N/A | D59: Crystal Black Pearl (NH-731P) | E59: Noir cristal nacré (NH-731P) | H59: 0.4 | J59: =VLOOKUP(B59,'[1]MASTER PART LIST'!$B:$C,2,FALSE) -> 215 | K59: =VLOOKUP(B59,'[1]MASTER PART LIST'!$B:$D,3,FALSE) -> 358 | L59: =K59+(H59*VLOOKUP(prov_cd,rate_table,2,FALSE)) -> 430.4 | P59: • | Q59: • | S59: • | T59: N/A | W59: Yes
B60: 08P05-T20-190 | C60: N/A | D60: Rallye Red (R-513) | E60: Rouge rallye (R-513) | H60: 0.4 | J60: =VLOOKUP(B60,'[1]MASTER PART LIST'!$B:$C,2,FALSE) -> 215 | K60: =VLOOKUP(B60,'[1]MASTER PART LIST'!$B:$D,3,FALSE) -> 358 | L60: =K60+(H60*VLOOKUP(prov_cd,rate_table,2,FALSE)) -> 430.4 | P60: N/A | Q60: • | S60: • | T60: N/A | W60: Yes
B61: 08P05-T20-1U0 | C61: N/A | D61: Boost Blue Pearl (B-637P) | E61: Bleu turbo nacré (B-637P) | H61: 0.4 | J61: =VLOOKUP(B61,'[1]MASTER PART LIST'!$B:$C,2,FALSE) -> 215 | K61: =VLOOKUP(B61,'[1]MASTER PART LIST'!$B:$D,3,FALSE) -> 358 | L61: =K61+(H61*VLOOKUP(prov_cd,rate_table,2,FALSE)) -> 430.4 | P61: N/A | Q61: N/A | S61: • | T61: N/A | W61: Yes
B62: 08P20-T20-XXXX | C62: 08P20-T20-130 | D62: Door Edge Guards | E62: Protecteurs de bordure de porte | F62: Door Edge Guards help protect your doors from nicks and scrapes that can be expensive to repair. | G62: Les protecteurs de rebords de portières aident à protéger les portières de votre véhicule contre les égratignures et éraflures dont la réparation serait coûteuse. | H62: =H65 -> 0.4 | J62: =J63 -> 140 | K62: =K63 -> 200 | L62: =K62+(H62*VLOOKUP(prov_cd,rate_table,2,FALSE)) -> 272.4 | P62: • | Q62: • | S62: • | T62: N/A | U62: Cannot be installed with Door Edge Film | V62: Ne peut être installé simultanément avec pellicule pour rebord de portière | W62: Yes | AF62: 52 | AK62: • | AS62: Door Sill Protection Film - 08P04-T20-100 08P20-T20-100A Door Edge Film
B63: 08P20-T20-130 | C63: N/A | D63: Platinum White Pearl (NH-883P) | E63: Blanc platine nacré (NH-883P) | H63: 0.4 | J63: =VLOOKUP(B63,'[1]MASTER PART LIST'!$B:$C,2,FALSE) -> 140 | K63: =VLOOKUP(B63,'[1]MASTER PART LIST'!$B:$D,3,FALSE) -> 200 | L63: =K63+(H63*VLOOKUP(prov_cd,rate_table,2,FALSE)) -> 272.4 | P63: • | Q63: • | S63: • | T63: N/A | W63: Yes
B64: 08P20-T20-1Z0 | C64: N/A | D64: Solar Reflection Silver (NH-932M) | E64: Refl et solaire argent métallisé (NH-932M) | H64: 0.4 | J64: =VLOOKUP(B64,'[1]MASTER PART LIST'!$B:$C,2,FALSE) -> 140 | K64: =VLOOKUP(B64,'[1]MASTER PART LIST'!$B:$D,3,FALSE) -> 200 | L64: =K64+(H64*VLOOKUP(prov_cd,rate_table,2,FALSE)) -> 272.4 | P64: • | Q64: N/A | S64: N/A | T64: N/A | W64: Yes
B65: 08P20-T20-170 | C65: N/A | D65: Meteoroid Gray Pearl (NH-904M) | E65: Gris météore nacré (NH-904M) | H65: 0.4 | J65: =VLOOKUP(B65,'[1]MASTER PART LIST'!$B:$C,2,FALSE) -> 115 | K65: =VLOOKUP(B65,'[1]MASTER PART LIST'!$B:$D,3,FALSE) -> 195 | L65: =K65+(H65*VLOOKUP(prov_cd,rate_table,2,FALSE)) -> 267.4 | P65: N/A | Q65: • | S65: N/A | T65: N/A | W65: Yes
B66: 08P20-T20-180 | C66: N/A | D66: Crystal Black Pearl (NH-731P) | E66: Noir cristal nacré (NH-731P) | H66: 0.4 | J66: =VLOOKUP(B66,'[1]MASTER PART LIST'!$B:$C,2,FALSE) -> 140 | K66: =VLOOKUP(B66,'[1]MASTER PART LIST'!$B:$D,3,FALSE) -> 200 | L66: =K66+(H66*VLOOKUP(prov_cd,rate_table,2,FALSE)) -> 272.4 | P66: • | Q66: • | S66: • | T66: N/A | W66: Yes
B67: 08P20-T20-190 | C67: N/A | D67: Rallye Red (R-513) | E67: Rouge rallye (R-513) | H67: 0.4 | J67: =VLOOKUP(B67,'[1]MASTER PART LIST'!$B:$C,2,FALSE) -> 140 | K67: =VLOOKUP(B67,'[1]MASTER PART LIST'!$B:$D,3,FALSE) -> 200 | L67: =K67+(H67*VLOOKUP(prov_cd,rate_table,2,FALSE)) -> 272.4 | P67: N/A | Q67: • | S67: • | T67: N/A | W67: Yes
B68: 08P20-T20-1U0 | C68: N/A | D68: Boost Blue Pearl (B-637P) | E68: Bleu turbo nacré (B-637P) | H68: 0.4 | J68: =VLOOKUP(B67,'[1]MASTER PART LIST'!$B:$C,2,FALSE) -> 140 | K68: =VLOOKUP(B67,'[1]MASTER PART LIST'!$B:$D,3,FALSE) -> 200 | L68: =K68+(H68*VLOOKUP(prov_cd,rate_table,2,FALSE)) -> 272.4 | P68: N/A | Q68: N/A | S68: • | T68: N/A | W68: Yes
B69: 08F02-T47-XXX | C69: 08F02-T47-130 | D69: Tailgate Spoiler, HPD | E69: Déflecteur de hayon - HPD | F69: The Tailgate Spoiler complements the aerodynamic styling of the Civic for an even sportier, unique look. Color-matched to original color specifications for a custom-finished look. Injection-molded ABS for durability and a perfect fit. Installation hardware designed and engineered specially for each vehicle. Gloss Black Emblems available as a separate accessory. | G69: Le déflecteur de hayon donne une allure encore plus sportive et unique au style aérodynamique de la Civic. Couleur assortie aux spécifications de la couleur d’origine pour une apparence personnalisée. Fait de résine ABS moulée par injection offrant de la durabilité et un ajustement parfait. Matériel d’installation conçu et fabriqué spécialement pour chaque véhicule. Les emblèmes de couleur noir lustré sont disponibles comme accessoires séparés. | H69: =H70 -> 1.2 | J69: =J70 -> 472 | K69: =K70 -> 787 | L69: =K69+(H69*VLOOKUP(prov_cd,rate_table,2,FALSE)) -> 1004.2 | P69: • | Q69: • | S69: • | T69: N/A | W69: Yes | AF69: 26 | AO69: • | AS69: 25CIV-5AR-NH883 Aero Kit
B70: 08F02-T47-130 | C70: N/A | D70: Platinum White Pearl (NH-883P) | E70: Blanc platine nacré (NH-883P) | H70: 1.2 | J70: =VLOOKUP(B70,'[1]MASTER PART LIST'!$B:$C,2,FALSE) -> 472 | K70: =VLOOKUP(B70,'[1]MASTER PART LIST'!$B:$D,3,FALSE) -> 787 | L70: =K70+(H70*VLOOKUP(prov_cd,rate_table,2,FALSE)) -> 1004.2 | P70: • | Q70: • | S70: • | T70: N/A | W70: Yes
B71: 08F02-T47-1Z0 | C71: N/A | D71: Solar Reflection Silver (NH-932M) | E71: Refl et solaire argent métallisé (NH-932M) | H71: 1.2 | J71: =VLOOKUP(B71,'[1]MASTER PART LIST'!$B:$C,2,FALSE) -> 472 | K71: =VLOOKUP(B71,'[1]MASTER PART LIST'!$B:$D,3,FALSE) -> 787 | L71: =K71+(H71*VLOOKUP(prov_cd,rate_table,2,FALSE)) -> 1004.2 | P71: • | Q71: N/A | S71: N/A | T71: N/A | W71: Yes
B72: 08F02-T47-170 | C72: N/A | D72: Meteriod Gray Pearl (NH-904M) | E72: Gris météore nacré (NH-904M) | H72: 1.2 | J72: =VLOOKUP(B72,'[1]MASTER PART LIST'!$B:$C,2,FALSE) -> 472 | K72: =VLOOKUP(B72,'[1]MASTER PART LIST'!$B:$D,3,FALSE) -> 787 | L72: =K72+(H72*VLOOKUP(prov_cd,rate_table,2,FALSE)) -> 1004.2 | P72: N/A | Q72: • | S72: N/A | T72: N/A | W72: Yes
B73: 08F02-T47-180 | C73: N/A | D73: Crystal Black Pearl (NH-731P) | E73: Noir cristal nacré (NH-731P) | H73: 1.2 | J73: =VLOOKUP(B73,'[1]MASTER PART LIST'!$B:$C,2,FALSE) -> 472 | K73: =VLOOKUP(B73,'[1]MASTER PART LIST'!$B:$D,3,FALSE) -> 787 | L73: =K73+(H73*VLOOKUP(prov_cd,rate_table,2,FALSE)) -> 1004.2 | P73: • | Q73: • | S73: • | T73: N/A | W73: Yes
B74: 08F02-T47-190 | C74: N/A | D74: Rallye Red (R-513) | E74: Rouge rallye (R-513) | H74: 1.2 | J74: =VLOOKUP(B74,'[1]MASTER PART LIST'!$B:$C,2,FALSE) -> 472 | K74: =VLOOKUP(B74,'[1]MASTER PART LIST'!$B:$D,3,FALSE) -> 787 | L74: =K74+(H74*VLOOKUP(prov_cd,rate_table,2,FALSE)) -> 1004.2 | P74: N/A | Q74: • | S74: • | T74: N/A | W74: Yes
B75: 08F02-T47-1U0 | C75: N/A | D75: Boost Blue Pearl (B-637P) | E75: Bleu turbo nacré (B-637P) | H75: 1.2 | J75: =VLOOKUP(B75,'[1]MASTER PART LIST'!$B:$C,2,FALSE) -> 472 | K75: =VLOOKUP(B75,'[1]MASTER PART LIST'!$B:$D,3,FALSE) -> 787 | L75: =K75+(H75*VLOOKUP(prov_cd,rate_table,2,FALSE)) -> 1004.2 | P75: N/A | Q75: N/A | S75: • | T75: N/A | W75: Yes
B76: 08U25-S3Y-305 | C76: 08U25-S3Y-305 | D76: Ashtray | E76: Cendrier de type porte-gobelet | F76: Front seat passengers can enjoy the added convenience of an ashtray. | G76: Les passagers avant apprécieront la commodité d'un cendrier. | H76: 0 | J76: =VLOOKUP(B76,'[1]MASTER PART LIST'!$B:$C,2,FALSE) -> 40.01 | K76: =VLOOKUP(B76,'[1]MASTER PART LIST'!$B:$D,3,FALSE) -> 66.69 | L76: =K76+(H76*VLOOKUP(prov_cd,rate_table,2,FALSE)) -> 66.69 | P76: • | Q76: • | S76: • | T76: • | W76: Yes | X76: N/A | Y76: N/A | Z76: N/A | AA76: N/A | AB76: N/A | AC76: N/A | AD76: N/A | AE76: N/A | AF76: 250 | AM76: •
B77: 08L96-T47-100 | C77: 08L96-T47-100 | D77: Cargo Net | E77: Filet de retenue | F77: The Cargo Net helps keep your grocery bags upright and holds most loose items securely in place. | G77: Le filet d'arrimage contribue à garder vos sacs d’épicerie à la verticale et garde en place la plupart des articles en toute sécurité. | H77: 0.4 | J77: =VLOOKUP(B77,'[1]MASTER PART LIST'!$B:$C,2,FALSE) -> 56 | K77: =VLOOKUP(B77,'[1]MASTER PART LIST'!$B:$D,3,FALSE) -> 80 | L77: =K77+(H77*VLOOKUP(prov_cd,rate_table,2,FALSE)) -> 152.4 | P77: • | Q77: • | S77: • | T77: • | W77: Yes | X77: N/A | Y77: N/A | Z77: N/A | AA77: N/A | AB77: N/A | AC77: N/A | AD77: N/A | AE77: N/A | AF77: 47 | AM77: •
B78: 08P04-T20-100 | C78: 08P04-T20-100 | D78: Door Sill Protection Film | E78: Pellicule de protection de seuil de portière | F78: The Door Sill Protection Film helps provide the lower door lining with protection from scuffing. Includes front and rear films. Includes front and rear films. | G78: La pellicule de protection de seuil de portière aide à protéger des éraflures la garniture inférieure de portière. Comprend les pellicules avant et arrière. | H78: 0.4 | J78: =VLOOKUP(B78,'[1]MASTER PART LIST'!$B:$C,2,FALSE) -> 103 | K78: =VLOOKUP(B78,'[1]MASTER PART LIST'!$B:$D,3,FALSE) -> 172 | L78: =K78+(H78*VLOOKUP(prov_cd,rate_table,2,FALSE)) -> 244.4 | P78: • | Q78: • | S78: • | T78: N/A | W78: Yes | X78: N/A | Y78: N/A | Z78: N/A | AA78: N/A | AB78: N/A | AC78: N/A | AD78: N/A | AE78: N/A | AF78: 51 | AK78: • | AS78: Door Edge Guards - 08P20-T20-130 25CIV5-PRO-FLM Protection Package - Film
B79: 08P17-T20-110 | C79: 08P17-T20-110 | D79: Floor Mats - All-Season | E79: Tapis toutes saisons | F79: The extended sidewalls of the High Wall All-Season Floor Mats add extra protection to shield your original carpets from the wear and tear of everyday driving. | G79: Les hautes parois des tapis toutes saisons offrent une protection accrue de la moquette d’origine contre l’usure et la détérioration dues à la conduite quotidienne. | H79: 0.1 | J79: =VLOOKUP(B79,'[1]MASTER PART LIST'!$B:$C,2,FALSE) -> 149 | K79: =VLOOKUP(B79,'[1]MASTER PART LIST'!$B:$D,3,FALSE) -> 248 | L79: =K79+(H79*VLOOKUP(prov_cd,rate_table,2,FALSE)) -> 266.1 | P79: • | Q79: N/A | S79: N/A | T79: • | U79: Includes Front and Rear. | V79: Inclut avant et arrière. | W79: Yes | X79: N/A | Y79: N/A | Z79: N/A | AA79: N/A | AB79: N/A | AC79: N/A | AD79: N/A | AE79: N/A | AF79: 34 | AM79: • | AS79: 25CIV5D-PRO-PET Protection Package - Petrol
B80: 08P17-T20-110A | C80: 08P17-T20-110A | D80: Floor Mats Hybrid - All-Season | E80: Tapis toutes saisons - Hybrid | F80: The extended sidewalls of the High Wall All-Season Floor Mats add extra protection to shield your original carpets from the wear and tear of everyday driving. | G80: Les hautes parois des tapis toutes saisons offrent une protection accrue de la moquette d’origine contre l’usure et la détérioration dues à la conduite quotidienne. | H80: 0.1 | J80: =VLOOKUP(B80,'[1]MASTER PART LIST'!$B:$C,2,FALSE) -> 149 | K80: =VLOOKUP(B80,'[1]MASTER PART LIST'!$B:$D,3,FALSE) -> 248 | L80: =K80+(H80*VLOOKUP(prov_cd,rate_table,2,FALSE)) -> 266.1 | P80: N/A | Q80: • | S80: • | T80: N/A | U80: Includes Front and Rear. | V80: Inclut avant et arrière. | W80: Yes | X80: N/A | Y80: N/A | Z80: N/A | AA80: N/A | AB80: N/A | AC80: N/A | AD80: N/A | AE80: N/A | AF80: 35 | AM80: • | AS80: 25CIV5-PRO-HYB Protection Package - Hybrid
B81: 08P15-T20-110 | C81: 08P15-T20-110 | D81: Carpet Floor Mats - Contoured High-Wall | E81: Tapis à hautes parois profilées | F81: Contoured High-Wall Carpet Floor Mats offer protection, durability and easy cleaning, all while maintaining the feeling of carpeting underfoot. These floor mats are designed with surrounding walls that corral dirt and debris for simplified cleaning and are contoured specifically for a perfect fit. | G81: Les tapis en moquette à hautes parois profilées offrent protection, durabilité et facilité de nettoyage, tout en conservant la sensation de la moquette sous les pieds. Ces tapis sont conçus avec des parois qui retiennent la saleté et les débris pour un nettoyage plus facile et sont spécialement profilés pour un ajustement parfait. | H81: 0.1 | J81: =VLOOKUP(B81,'[1]MASTER PART LIST'!$B:$C,2,FALSE) -> 238 | K81: =VLOOKUP(B81,'[1]MASTER PART LIST'!$B:$D,3,FALSE) -> 397 | L81: =K81+(H81*VLOOKUP(prov_cd,rate_table,2,FALSE)) -> 415.1 | P81: • | Q81: • | S81: • | T81: N/A | U81: Includes Front and Rear. | V81: Inclut avant et arrière. | W81: Yes | X81: N/A | Y81: N/A | Z81: N/A | AA81: N/A | AB81: N/A | AC81: N/A | AD81: N/A | AE81: N/A | AF81: 39 | AN81: •
B82: 08R13-T47-100 | C82: 08R13-T47-100 | D82: Rear Passenger Window Shade | E82: Pare-soleil pour glaces latérales arrière | F82: The Rear Passenger Window Shade provides added comfort for your rear seated passengers by shielding them from the sun’s heat and glare. Includes left and right side shade. | G82: Les pare-soleil pour glaces latérales arrière offrent un confort accru pour vos passagers arrière, en fournissant une protection contre l’éblouissement et la chaleur du soleil. Inclut le côté gauche et droit. | H82: 0.5 | J82: =VLOOKUP(B82,'[1]MASTER PART LIST'!$B:$C,2,FALSE) -> 209 | K82: =VLOOKUP(B82,'[1]MASTER PART LIST'!$B:$D,3,FALSE) -> 322 | L82: =K82+(H82*VLOOKUP(prov_cd,rate_table,2,FALSE)) -> 412.5 | P82: • | Q82: • | S82: • | T82: • | U82: Includes Left and Right Side. | V82: Inclut le côté gauche et droit. | W82: Yes | X82: N/A | Y82: N/A | Z82: N/A | AA82: N/A | AB82: N/A | AC82: N/A | AD82: N/A | AE82: N/A | AF82: 43 | AM82: •
B83: 08U45-T47-100 | C83: =B83 -> 08U45-T47-100 | D83: Cargo Tray | E83: Plateau de coffre | F83: The Cargo Tray helps protect the floor in the rear storage area from accidental spills that can happen during sharp turns and quick stops. The high-quality molded plastic is rugged, durable, and cleans easily with mild soap and water. The Cargo Try perfectly matches the interior contours of your Civic. The molded-in ribs and texture give added rigidity and strength and its raised sides give added protection. | G83: Il arrive souvent que les objets que vous transportez dans votre coffre se renversent, laissent des taches ou abîment la moquette d’origine, faisant du plateau de coffre un investissement judicieux. | H83: 0.1 | J83: =VLOOKUP(B83,'[1]MASTER PART LIST'!$B:$C,2,FALSE) -> 118 | K83: =VLOOKUP(B83,'[1]MASTER PART LIST'!$B:$D,3,FALSE) -> 197 | L83: =K83+(H83*VLOOKUP(prov_cd,rate_table,2,FALSE)) -> 215.1 | P83: • | Q83: N/A | S83: N/A | T83: N/A | W83: Yes | X83: N/A | Y83: N/A | Z83: N/A | AA83: N/A | AB83: N/A | AC83: N/A | AD83: N/A | AE83: N/A | AF83: 36 | AM83: • | AS83: 25CIV5D-PRO-PET Protection Package - Petrol
A84: update Post Feb 1 | B84: 08U45-T47-100B | C84: =B84 -> 08U45-T47-100B | D84: Cargo Tray | E84: Plateau de coffre | F84: The Cargo Tray helps protect the floor in the rear storage area from accidental spills that can happen during sharp turns and quick stops. The high-quality molded plastic is rugged, durable, and cleans easily with mild soap and water. The Cargo Try perfectly matches the interior contours of your Civic. The molded-in ribs and texture give added rigidity and strength and its raised sides give added protection. | G84: Il arrive souvent que les objets que vous transportez dans votre coffre se renversent, laissent des taches ou abîment la moquette d’origine, faisant du plateau de coffre un investissement judicieux. | H84: 0.1 | J84: =VLOOKUP(B84,'[1]MASTER PART LIST'!$B:$C,2,FALSE) -> 118 | K84: =VLOOKUP(B84,'[1]MASTER PART LIST'!$B:$D,3,FALSE) -> 197 | L84: =K84+(H84*VLOOKUP(prov_cd,rate_table,2,FALSE)) -> 215.1 | P84: N/A | Q84: • | S84: • | T84: N/A | W84: Yes | X84: N/A | Y84: N/A | Z84: N/A | AA84: N/A | AB84: N/A | AC84: N/A | AD84: N/A | AE84: N/A | AF84: 37 | AM84: • | AS84: 25CIV5-PRO-HYB Protection Package - Hybrid
B85: 08U45-T20-300A | C85: 08U45-T20-300A | D85: Cargo Tray Dividers | E85: Séparateurs de plateau de coffre | F85: Small items will stay right where you put them, neat and organized, with these easy-to-use Cargo Tray Dividers. | G85: Les petits articles resteront là où vous les avez rangés, ordonnés et bien organisés, grâce à ces séparateurs de plateau de coffre faciles à utiliser. | H85: 0.1 | J85: =VLOOKUP(B85,'[1]MASTER PART LIST'!$B:$C,2,FALSE) -> 77 | K85: =VLOOKUP(B85,'[1]MASTER PART LIST'!$B:$D,3,FALSE) -> 128 | L85: =K85+(H85*VLOOKUP(prov_cd,rate_table,2,FALSE)) -> 146.1 | P85: • | Q85: • | S85: • | T85: • | U85: Dividers Only. | V85: Séparateurs seulement. | W85: Yes | X85: N/A | Y85: N/A | Z85: N/A | AA85: N/A | AB85: N/A | AC85: N/A | AD85: N/A | AE85: N/A | AF85: 41 | AM85: • | AR85: Cargo Tray - 08U45-T47-100
B86: 08T44-SNA-302 | C86: 08T44-SNA-302 | D86: Engine Block Heater - 2.0L | E86: Chauffe-moteur - 2,0 L | F86: Don't let the cold Canadian winters stop you from enjoying your new car. The addition of the Engine Block Heater will help ensure a smooth start even on the coldest days. | G86: Ne laissez pas nos hivers froids vous priver du plaisir de votre voiture. L'ajout du chauffe-bloc aidera à assurer le démarrage de votre voiture, même aux températures les plus basses. | H86: 1.4 | J86: =VLOOKUP(B86,'[1]MASTER PART LIST'!$B:$C,2,FALSE) -> 149 | K86: =VLOOKUP(B86,'[1]MASTER PART LIST'!$B:$D,3,FALSE) -> 248 | L86: =K86+(H86*VLOOKUP(prov_cd,rate_table,2,FALSE)) -> 501.4 | P86: • | Q86: • | S86: • | T86: N/A | W86: Yes | X86: N/A | Y86: N/A | Z86: N/A | AA86: N/A | AB86: N/A | AC86: N/A | AD86: N/A | AE86: N/A | AF86: 53 | AL86: • | AS86: 22CIV-COLD-PK20 Cold Weather Package - 2.0L
B87: 08E12-T20-100B | C87: 08E12-T20-100B | D87: Illuminated Door Sill Trim | E87: Garniture de seuil de portière illuminée | F87: The Illuminated Door Sill Trim dresses up the interior while helping protect the lower door sill from scuff marks. Includes front and rear trims. Front illumination only. | G87: La garniture de seuil de portière illuminée rend l’habitacle plus attrayant tout en protégeant le seuil de portière des éraflures. Comprend les garnitures avant et arrière. Éclairage avant seulement. | H87: 1.1 | J87: =VLOOKUP(B87,'[1]MASTER PART LIST'!$B:$C,2,FALSE) -> 256 | K87: =VLOOKUP(B87,'[1]MASTER PART LIST'!$B:$D,3,FALSE) -> 427 | L87: =K87+(H87*VLOOKUP(prov_cd,rate_table,2,FALSE)) -> 626.1 | P87: • | Q87: • | S87: • | T87: N/A | U87: Includes Front and Rear trims. Front illumination Only. | V87: Inclut avant et arrière garniture. Éclairage avant seulement. | W87: Yes | X87: N/A | Y87: N/A | Z87: N/A | AA87: N/A | AB87: N/A | AC87: N/A | AD87: N/A | AE87: N/A | AF87: 32 | AN87: •
B88: 31670-BMS-004H | C88: 31670-BMS-004H | D88: Optimate 12V Auto Battery Charger/Maintainer | E88: Chargeur/mainteneur de batterie automobile 12 V Optimate | F88: Extended battery life by charging/maintaining a Honda battery to ideal charge levels. | G88: Vie prolongée de la batterie Honda en maintenant la charge au niveau ideal. | H88: 0 | J88: =VLOOKUP(B88,'[1]MASTER PART LIST'!$B:$C,2,FALSE) -> 94 | K88: =VLOOKUP(B88,'[1]MASTER PART LIST'!$B:$D,3,FALSE) -> 157 | L88: =K88+(H88*VLOOKUP(prov_cd,rate_table,2,FALSE)) -> 157 | P88: • | Q88: • | S88: • | T88: • | W88: Yes | X88: N/A | Y88: N/A | Z88: N/A | AA88: N/A | AB88: N/A | AC88: N/A | AD88: N/A | AE88: N/A | AF88: 55 | AL88: • | AS88: 22CIV-COLD-PK20 Cold Weather Package - 2.0L 23CIV-COLD-TR Cold Weather Package - Type R
B89: 31670-BMS-LEAD | C89: N/A App Chart reference | D89: Battery Lead | E89: Câble de batterie | H89: 0 | J89: =VLOOKUP(B89,'[1]MASTER PART LIST'!$B:$C,2,FALSE) -> 20 | K89: =VLOOKUP(B89,'[1]MASTER PART LIST'!$B:$D,3,FALSE) -> 28 | L89: =K89+(H89*VLOOKUP(prov_cd,rate_table,2,FALSE)) -> 28 | P89: • | Q89: • | S89: • | T89: • | W89: Yes
B90: 08P30-T47-100 | C90: 08P30-T47-100 | D90: Seat Back Protector | E90: Protection de dossier du siège | F90: The Seat Back Protector protects the back of the seat when it's folded down to load longer items. Made of high-quality molded plastic for maximum durability. Cleans easily with mild soap and water. Textured surface helps to prevent items from shifting and sliding. | G90: Le protecteur de dossier des sièges protège le dossier des sièges lorsqu'ils sont rabattus pour charger des articles plus longs. Fait de plastique moulé de haute qualité offrant une durabilité maximale. Se nettoie facilement à l'aide de savon doux et d'eau. La surface texturée aide à empêcher les articles de bouger et de glisser. | H90: 0.2 | J90: =VLOOKUP(B90,'[1]MASTER PART LIST'!$B:$C,2,FALSE) -> 157 | K90: =VLOOKUP(B90,'[1]MASTER PART LIST'!$B:$D,3,FALSE) -> 224 | L90: =K90+(H90*VLOOKUP(prov_cd,rate_table,2,FALSE)) -> 260.2 | P90: • | Q90: • | S90: • | T90: • | W90: Yes | X90: N/A | Y90: N/A | Z90: N/A | AA90: N/A | AB90: N/A | AC90: N/A | AD90: N/A | AE90: N/A | AF90: 42 | AM90: •
B91: 08LXX-E09-XXXX | C91: N/A only used for app chart | D91: Roof Attachments | E91: Accessoires de toit
B92: 08L02-T47-300 | C92: =B92 -> 08L02-T47-300 | D92: Roof Rack | E92: Porte-bagages de toit | F92: With the Roof Rack, you can securely haul items on your Civic. You’ll help prevent damage to your vehicle’s interior, while providing more comfort to those seated inside. 154 lb maximum load capacity. Moonroof operation is unaffected. Rack can be removed when not in use. Rack covers included in kit for use when Roof Rack is removed. | G92: Avec le porte-bagages de toit, vous pouvez transporter des objets en toute sécurité sur votre Civic. Vous éviterez ainsi des dommages à l’intérieur de votre véhicule, tout en offrant plus de confort aux passagers à l’intérieur. Capacité de charge maximale de 154 lb. L’utilisation du toit ouvrant n’est pas affectée. Le porte-bagages peut être retiré lorsqu’il n’est pas utilisé. Les housses de porte-bagages incluses dans l’ensemble peuvent être utilisées lorsque le porte-bagages de toit est retiré. | H92: 0.4 | J92: =VLOOKUP(B92,'[1]MASTER PART LIST'!$B:$C,2,FALSE) -> 498 | K92: =VLOOKUP(B92,'[1]MASTER PART LIST'!$B:$D,3,FALSE) -> 830 | L92: =K92+(H92*VLOOKUP(prov_cd,rate_table,2,FALSE)) -> 902.4 | P92: • | Q92: • | S92: • | T92: • | W92: Yes | AF92: 60 | AM92: •
B93: 08L20-E09-300A | C93: =B93 -> 08L20-E09-300A | D93: Roof Box - Midsize | E93: Boîte de toit - moyenne | F93: Keep your golf clubs, snowboards, skis, and other gear protected and out of the elements in the Midsize Roof Box. Impact and UV-resistant. 16 cu.ft. of lockable storage space - length 74 in, width 36 in, height 16.5 in. 110lbs max load capacity. Dual-side opening for easy access. Requires Roof Rack Crossbars. | G93: Cette boîte de toit aux lignes aérodynamiques est conçue pour garder vos objets précieux au sec et à l'abri des regards indiscrets, lors de vos sorties de plein air. Porte-bagages de toit requis. Longueur : 193 cm, largeur : 84 cm, hauteur : 40 cm (76 po x 33 po x 15,6 po); capacité de charge maximale : 50 kg (110 lb) | H93: 0.2 | J93: =VLOOKUP(B93,'[1]MASTER PART LIST'!$B:$C,2,FALSE) -> 898 | K93: =VLOOKUP(B93,'[1]MASTER PART LIST'!$B:$D,3,FALSE) -> 1497 | L93: =K93+(H93*VLOOKUP(prov_cd,rate_table,2,FALSE)) -> 1533.2 | P93: • | Q93: • | S93: • | T93: • | W93: Yes | AF93: 66 | AM93: • | AR93: Roof Rack - 08L02-T47-300
B94: 08L20-E09-300B | C94: =B94 -> 08L20-E09-300B | D94: Roof Box - Short | E94: Boîte de toit - courte | F94: You can always use more storage space on a road trip, and the Short Roof Box provides just that. 13 cu. ft. of lockable storage space - length 65in, width 34.5 in, height 16in. 110lbs max load capacity. Dual-side opening for easy access. Requires Roof Rack Crossbars. | G94: Vous pouvez toujours profiter de plus d'espace pour un voyage et la boîte de toit courte vous offre la solution. Espace de rangement se verrouillant à clé de 13 pi2 - longueur de 65 po, largeur de 34,5 po, hauteur de 16 po. Capacité de charge maximale de 110 lb. Ouverture sur les deux côtés pour faciliter l'accès. Les traverses de toit sont requises. | H94: 0.2 | J94: =VLOOKUP(B94,'[1]MASTER PART LIST'!$B:$C,2,FALSE) -> 820 | K94: =VLOOKUP(B94,'[1]MASTER PART LIST'!$B:$D,3,FALSE) -> 1367 | L94: =K94+(H94*VLOOKUP(prov_cd,rate_table,2,FALSE)) -> 1403.2 | P94: • | Q94: • | S94: • | T94: • | W94: Yes | AF94: 67 | AM94: • | AR94: Roof Rack - 08L02-T47-300
B95: 08L07-E09-101 | C95: =B95 -> 08L07-E09-101 | D95: Roof Bike Attachment - Frame Mount | E95: Support à vélo vertical pour porte-bagages de toit | F95: This Roof Bike Attachment lets you securely transport your bicycle and keep it safely out of the way. (Roof Rails and Cross Bars required, one bicycle per attachment) | G95: Le porte-bicyclette pour le toit vous permet, en toute sécurité, de transporter votre vélo bien à l'abri des autres bagages. (Deux porte-bicyclette représentés. Barres transversales pour galerie de toit et galerie de toit requises.) | H95: 0.6 | J95: =VLOOKUP(B95,'[1]MASTER PART LIST'!$B:$C,2,FALSE) -> 393 | K95: =VLOOKUP(B95,'[1]MASTER PART LIST'!$B:$D,3,FALSE) -> 561 | L95: =K95+(H95*VLOOKUP(prov_cd,rate_table,2,FALSE)) -> 669.6 | P95: • | Q95: • | S95: • | T95: • | U95: Only one (1) bike attachment allowed on the Roof Rack. Roof Rack required. | V95: Un (1) seul porte-vélo permis sur le porte-bagages de toit. Porte-bagages de toit requis. | W95: Yes | AF95: 62 | AM95: • | AR95: Roof Rack - 08L02-T47-300
B96: 08L09-E09-101 | C96: =B96 -> 08L09-E09-101 | D96: Roof Kayak Attachment | E96: Galerie de toit, fixation pour kayak | F96: Handle kayaks up to 36 in wide and weighing up to 75 lbs. Easy loading with the pivoting, felt-lined rear saddles that help glide and center your kayak. Two independent pivoting saddles conform to a limitless range of hull shapes. Requires Roof Rack Crossbars. | G96: Permet de transporter des kayaks jusqu’à 36 po de large et dont le poids peut atteindre 75 lb. Chargement facile à l'aide des selles arrière pivotantes à revêtement feutré qui aident à guider et centrer votre kayak. Deux selles pivotantes et indépendantes s'adaptent à une gamme infinie de formes de coque. Les traverses de toit sont requises. | H96: 0.2 | J96: =VLOOKUP(B96,'[1]MASTER PART LIST'!$B:$C,2,FALSE) -> 442 | K96: =VLOOKUP(B96,'[1]MASTER PART LIST'!$B:$D,3,FALSE) -> 737 | L96: =K96+(H96*VLOOKUP(prov_cd,rate_table,2,FALSE)) -> 773.2 | P96: • | Q96: • | S96: • | T96: • | W96: Yes | AF96: 65 | AM96: • | AR96: Roof Rack - 08L02-T47-300
B97: 08L03-E09-300C | C97: =B97 -> 08L03-E09-300C | D97: Roof Ski/Snowboard Attachment | E97: Galerie de toit, Fixation pour skis/planche à neige | F97: The handy Ski Attachment keeps your skis and snowboards outside so your interior stays clean and dry. Requires Crossbar. | G97: La fixation pratique pour skis permet de transporter ceux-ci à l’extérieur du véhicule, pour que l’habitacle demeure propre et sec. Barres transversales requises. | H97: 0.2 | J97: =VLOOKUP(B97,'[1]MASTER PART LIST'!$B:$C,2,FALSE) -> 426 | K97: =VLOOKUP(B97,'[1]MASTER PART LIST'!$B:$D,3,FALSE) -> 710 | L97: =K97+(H97*VLOOKUP(prov_cd,rate_table,2,FALSE)) -> 746.2 | P97: • | Q97: • | S97: • | T97: • | W97: Yes | AF97: 63 | AM97: • | AR97: Roof Rack - 08L02-T47-300
B98: 08L05-E09-100 | C98: =B98 -> 08L05-E09-100 | D98: Roof Surfboard Attachment | E98: Galerie de toit, Fixation pour planche de surf | F98: The telescoping design allows a custom fit for boards up to 34 in wide. Handles two boards with maximum stability. Soft, weather-resistant padding and strong, durable load straps with adjustable padding protect boards from strap abrasion. Requires Roof Rack Crossbars. | G98: La conception télescopique offre un ajustement personnalisé pour les planches dont la largeur peut atteindre 34 po. Permet de transporter deux planches avec un maximum de stabilité. Rembourrage souple et résistant aux intempéries et sangles résistantes et durables avec rembourrage réglable protégeant les planches contre l'abrasion causée par les sangles. Les traverses de toit sont requises. | H98: 0.2 | J98: =VLOOKUP(B98,'[1]MASTER PART LIST'!$B:$C,2,FALSE) -> 213 | K98: =VLOOKUP(B98,'[1]MASTER PART LIST'!$B:$D,3,FALSE) -> 355 | L98: =K98+(H98*VLOOKUP(prov_cd,rate_table,2,FALSE)) -> 391.2 | P98: • | Q98: • | S98: • | T98: • | W98: Yes | AF98: 64 | AM98: • | AR98: Roof Rack - 08L02-T47-300
B99: 08L20-E09-300C | C99: 08L20-E09-101C5D | D99: =D100 -> Roof Basket | E99: =E100 -> Panier de toit | F99: =F100 -> Honda has you covered with a low-profile Roof Basket that’ll hold up to 150 lbs. Its tapered side walls make loading easier and wind fairing directs airflow over your cargo. The Roof Basket is rated up to 150 lbs. However, the combined weight of the Roof Basket and load cannot exceed 154 lbs. Depending on applied model the roof basket requires roof carrier or roof rails and crossbars. | G99: =G100 -> Honda propose un panier de toit à profil bas qui peut contenir jusqu’à 150 lb. Les parois latérales inclinées facilitent le chargement. Le carénage permet le déplacement de l’air au-dessus de votre chargement. Le panier de toit peut contenir jusqu’à 150 lb. Cependant, le poids combiné du panier de toit et de la charge ne doit pas dépasser 154 lb. Selon le modèle sur lequel il est utilisé, le panier de toit requiert un porte-bagages, ou des longerons de toit et des barres transversales. | H99: =H100+H101 -> 0.4 | J99: =J100 -> 586 | K99: =K100 -> 977 | L99: =K99+(H99*VLOOKUP(prov_cd,rate_table,2,FALSE)) -> 1049.4 | P99: =P100 -> • | Q99: =Q100 -> • | S99: =S100 -> • | T99: • | U99: =U100 -> Roof Basket Attachment Kit (hardware) and Roof Rack required. | V99: =V100 -> Ensemble de fixation de panier de toit (nécessaire de montage) et porte-bagages de toit requis. | W99: Yes | AF99: 61 | AM99: • | AR99: Roof Rack - 08L02-T47-300
B100: 08L20-E09-101C | C100: app chart only | D100: Roof Basket | E100: Panier de toit | F100: Honda has you covered with a low-profile Roof Basket that’ll hold up to 150 lbs. Its tapered side walls make loading easier and wind fairing directs airflow over your cargo. The Roof Basket is rated up to 150 lbs. However, the combined weight of the Roof Basket and load cannot exceed 154 lbs. Depending on applied model the roof basket requires roof carrier or roof rails and crossbars. | G100: Honda propose un panier de toit à profil bas qui peut contenir jusqu’à 150 lb. Les parois latérales inclinées facilitent le chargement. Le carénage permet le déplacement de l’air au-dessus de votre chargement. Le panier de toit peut contenir jusqu’à 150 lb. Cependant, le poids combiné du panier de toit et de la charge ne doit pas dépasser 154 lb. Selon le modèle sur lequel il est utilisé, le panier de toit requiert un porte-bagages, ou des longerons de toit et des barres transversales. | H100: 0.4 | J100: =VLOOKUP(B100,'[1]MASTER PART LIST'!$B:$C,2,FALSE) -> 586 | K100: =VLOOKUP(B100,'[1]MASTER PART LIST'!$B:$D,3,FALSE) -> 977 | L100: =K100+(H100*VLOOKUP(prov_cd,rate_table,2,FALSE)) -> 1049.4 | P100: • | Q100: • | S100: • | T100: • | U100: Roof Basket Attachment Kit (hardware) and Roof Rack required. | V100: Ensemble de fixation de panier de toit (nécessaire de montage) et porte-bagages de toit requis. | W100: Yes
B101: 08L20-E09-100D | C101: app chart only | D101: Roof Basket Attachment Kit | E101: Ensemble de fixation de panier de toit | J101: =VLOOKUP(B101,'[1]MASTER PART LIST'!$B:$C,2,FALSE) -> 17 | K101: =VLOOKUP(B101,'[1]MASTER PART LIST'!$B:$D,3,FALSE) -> 28 | L101: =K101+(H101*VLOOKUP(prov_cd,rate_table,2,FALSE)) -> 28 | P101: • | Q101: • | S101: • | T101: • | W101: Yes | AL101: •
...

Sheet SELECT PROVINCE
A1: Select Province: Choissisez votre province: | B1: YT
B4: Current Labor Rates
B5: Taux de main d'oeuvre en cours
B6: AB | C6: 171
B7: BC | C7: 181
B8: MB | C8: 164
B9: NB | C9: 142
B10: NL | C10: 142
B11: NS | C11: 142
B12: ON | C12: 160 | F12: =prov_cd -> YT
B13: PEI | C13: 134
B14: QC | C14: 152
B15: SK | C15: 164
B16: YT | C16: 181
B18: Publication Date / Date de publication: | C18: ='26MY_CIV5D_DATA'!$C$4 -> 46142
A23: All published prices, trim specifications, and availability are subject to change without prior notice.
A24: Tout prix, spécifications de versions et disponibilté d'accessoires publiés sont sujets à changer sans pré-avis.

Sheet 26MY_CIV5D_APP_EN
B2: Honda Internal | C2: Honda Accessories
C3: Model Name | D3: ='26MY_CIV5D_DATA'!C2 -> Civic Hatch & Type R
C4: Model Year | D4: ='26MY_CIV5D_DATA'!$C$3 -> 2026
C5: S = Standard (accessory comes standard on this trim)
C6: T = Tire Size Change (the size of the accessory wheel is smaller/larger than the OE Wheel. Customer will require new tires to fit these wheels.)
C7: E = Exchange Standard Equipment (the size of the accessory wheel is the same size as the OE wheel and therefore they can use the OE tire.)
C8: N/A = Not Applicable (accessory cannot be applied to this trim)
H10: Province
C11: 1.0 Packages and Kits | H11: =prov_cd -> YT
C12: Description | D12: Part Number | E12: Dealer Net | F12: List Price | G12: FRT | H12: Installed Price | I12: Application | Q12: Comments
I13: ='26MY_CIV5D_DATA'!M$7 -> 0 | J13: ='26MY_CIV5D_DATA'!N$7 -> 0 | K13: ='26MY_CIV5D_DATA'!O$7 -> 0 | L13: ='26MY_CIV5D_DATA'!P$7 -> SPORT | M13: ='26MY_CIV5D_DATA'!Q$7 -> SPORT Hybrid | N13: ='26MY_CIV5D_DATA'!R$7 -> 0 | O13: ='26MY_CIV5D_DATA'!S$7 -> Sport Touring Hybrid | P13: ='26MY_CIV5D_DATA'!T$7 -> Type R
B14: 26TYPER-RACE | C14: =VLOOKUP(B14,'26MY_CIV5D_DATA'!B:AS,3,FALSE) -> Racing Package - Type R | D14: =B14 -> 26TYPER-RACE | E14: =VLOOKUP(B14,'26MY_CIV5D_DATA'!B:AS,9,FALSE) -> 3928 | F14: =VLOOKUP(B14,'26MY_CIV5D_DATA'!B:AS,10,FALSE) -> 6431 | G14: =VLOOKUP(B14,'26MY_CIV5D_DATA'!B:AS,7,FALSE) -> 1 | H14: =VLOOKUP(B14,'26MY_CIV5D_DATA'!B:AS,11,FALSE) -> 6612 | I14: =VLOOKUP(B14,'26MY_CIV5D_DATA'!B:AS,12,FALSE) -> 0 | J14: =VLOOKUP(B14,'26MY_CIV5D_DATA'!B:AS,13,FALSE) -> 0 | K14: =VLOOKUP($B14,'26MY_CIV5D_DATA'!$B:$AS,14,FALSE) -> 0 | L14: =VLOOKUP(B14,'26MY_CIV5D_DATA'!B:AS,15,FALSE) -> N/A | M14: =VLOOKUP(B14,'26MY_CIV5D_DATA'!B:AS,16,FALSE) -> N/A | N14: =VLOOKUP($B14,'26MY_CIV5D_DATA'!$B:$AS,17,FALSE) -> 0 | O14: =VLOOKUP(B14,'26MY_CIV5D_DATA'!B:AS,18,FALSE) -> N/A | P14: =VLOOKUP(B14,'26MY_CIV5D_DATA'!B:AS,19,FALSE) -> • | Q14: =IF(VLOOKUP(B14,'26MY_CIV5D_DATA'!B:AS,20,FALSE)="","",VLOOKUP(B14,'26MY_CIV5D_DATA'!B:AS,20,FALSE))
B15: 08F02-T60-100 | C15: =VLOOKUP(B15,'26MY_CIV5D_DATA'!B:AS,3,FALSE) -> Carbon Fiber Wing Spoiler - Type R | D15: =B15 -> 08F02-T60-100
B16: 08U97-T60-110 | C16: =VLOOKUP(B16,'26MY_CIV5D_DATA'!B:AS,3,FALSE) -> Steering Wheel, Alcantara - Type R | D16: =B16 -> 08U97-T60-110
B17: 08U92-T60-110 | C17: =VLOOKUP(B17,'26MY_CIV5D_DATA'!B:AS,3,FALSE) -> Shift Knob - Type R | D17: =B17 -> 08U92-T60-110
B19: 25CIV-ENK-WTPK | C19: =VLOOKUP(B19,'26MY_CIV5D_DATA'!B:AS,3,FALSE) -> 16” Enkei M52 Wheels & Michelin X-ICE Snow Tire Package | E19: =VLOOKUP(B19,'26MY_CIV5D_DATA'!B:AS,9,FALSE) -> 1596.56 | F19: =VLOOKUP(B19,'26MY_CIV5D_DATA'!B:AS,10,FALSE) -> 2028 | G19: =VLOOKUP(B19,'26MY_CIV5D_DATA'!B:AS,7,FALSE) -> 1.2 | H19: =VLOOKUP(B19,'26MY_CIV5D_DATA'!B:AS,11,FALSE) -> 2245.2 | I19: =VLOOKUP(B19,'26MY_CIV5D_DATA'!B:AS,12,FALSE) -> 0 | J19: =VLOOKUP(B19,'26MY_CIV5D_DATA'!B:AS,13,FALSE) -> 0 | K19: =VLOOKUP($B19,'26MY_CIV5D_DATA'!$B:$AS,14,FALSE) -> 0 | L19: =VLOOKUP(B19,'26MY_CIV5D_DATA'!B:AS,15,FALSE) -> • | M19: =VLOOKUP(B19,'26MY_CIV5D_DATA'!B:AS,16,FALSE) -> N/A | N19: =VLOOKUP($B19,'26MY_CIV5D_DATA'!$B:$AS,17,FALSE) -> 0 | O19: =VLOOKUP(B19,'26MY_CIV5D_DATA'!B:AS,18,FALSE) -> N/A | P19: =VLOOKUP(B19,'26MY_CIV5D_DATA'!B:AS,19,FALSE) -> N/A | Q19: =IF(VLOOKUP(B19,'26MY_CIV5D_DATA'!B:AS,20,FALSE)="","",VLOOKUP(B19,'26MY_CIV5D_DATA'!B:AS,20,FALSE)) -> Priced as a set of 4 wheels.
B20: 480-670-6545-SP or 480-670-6545-GB | C20: =VLOOKUP(B20,'26MY_CIV5D_DATA'!B:AS,3,FALSE) -> 16" Enkei M52 Wheels - Silver or Gloss Black | D20: =B20 -> 480-670-6545-SP or 480-670-6545-GB
B21: 34417 | C21: =VLOOKUP(B21,'26MY_CIV5D_DATA'!B:AS,3,FALSE) -> Michelin X-ICE Snow Tires - 215/55/16 | D21: =B21 -> 34417
B23: 25CIV-STL-WTPK | C23: =VLOOKUP(B23,'26MY_CIV5D_DATA'!B:AS,3,FALSE) -> 16” Winter Steel Wheels & Michelin X-ICE Snow Tire Package | E23: =VLOOKUP(B23,'26MY_CIV5D_DATA'!B:AS,9,FALSE) -> 1150.4 | F23: =VLOOKUP(B23,'26MY_CIV5D_DATA'!B:AS,10,FALSE) -> 1522.72 | G23: =VLOOKUP(B23,'26MY_CIV5D_DATA'!B:AS,7,FALSE) -> 1.2 | H23: =VLOOKUP(B23,'26MY_CIV5D_DATA'!B:AS,11,FALSE) -> 1739.92 | I23: =VLOOKUP(B23,'26MY_CIV5D_DATA'!B:AS,12,FALSE) -> 0 | J23: =VLOOKUP(B23,'26MY_CIV5D_DATA'!B:AS,13,FALSE) -> 0 | K23: =VLOOKUP($B23,'26MY_CIV5D_DATA'!$B:$AS,14,FALSE) -> 0 | L23: =VLOOKUP(B23,'26MY_CIV5D_DATA'!B:AS,15,FALSE) -> • | M23: =VLOOKUP(B23,'26MY_CIV5D_DATA'!B:AS,16,FALSE) -> N/A | N23: =VLOOKUP($B23,'26MY_CIV5D_DATA'!$B:$AS,17,FALSE) -> 0 | O23: =VLOOKUP(B23,'26MY_CIV5D_DATA'!B:AS,18,FALSE) -> N/A | P23: =VLOOKUP(B23,'26MY_CIV5D_DATA'!B:AS,19,FALSE) -> N/A | Q23: =IF(VLOOKUP(B23,'26MY_CIV5D_DATA'!B:AS,20,FALSE)="","",VLOOKUP(B23,'26MY_CIV5D_DATA'!B:AS,20,FALSE)) -> Priced as a set of 4 wheels.
B24: 42700-TBA-A12 | C24: =VLOOKUP(B24,'26MY_CIV5D_DATA'!B:AS,3,FALSE) -> 16” Winter Steel Wheels | D24: =B24 -> 42700-TBA-A12
B25: 34417 | C25: =VLOOKUP(B25,'26MY_CIV5D_DATA'!B:AS,3,FALSE) -> Michelin X-ICE Snow Tires - 215/55/16 | D25: =B25 -> 34417
B27: 25CIV5-ARO-PK | C27: =VLOOKUP(B27,'26MY_CIV5D_DATA'!B:AS,3,FALSE) -> Aero Kit | E27: =VLOOKUP(B27,'26MY_CIV5D_DATA'!B:AS,9,FALSE) -> 660.6 | F27: =VLOOKUP(B27,'26MY_CIV5D_DATA'!B:AS,10,FALSE) -> 1101.6 | G27: =VLOOKUP(B27,'26MY_CIV5D_DATA'!B:AS,7,FALSE) -> 2.2 | H27: =VLOOKUP(B27,'26MY_CIV5D_DATA'!B:AS,11,FALSE) -> 1499.8 | I27: =VLOOKUP(B27,'26MY_CIV5D_DATA'!B:AS,12,FALSE) -> 0 | J27: =VLOOKUP(B27,'26MY_CIV5D_DATA'!B:AS,13,FALSE) -> 0 | K27: =VLOOKUP($B27,'26MY_CIV5D_DATA'!$B:$AS,14,FALSE) -> 0 | L27: =VLOOKUP(B27,'26MY_CIV5D_DATA'!B:AS,15,FALSE) -> • | M27: =VLOOKUP(B27,'26MY_CIV5D_DATA'!B:AS,16,FALSE) -> • | N27: =VLOOKUP($B27,'26MY_CIV5D_DATA'!$B:$AS,17,FALSE) -> 0 | O27: =VLOOKUP(B27,'26MY_CIV5D_DATA'!B:AS,18,FALSE) -> • | P27: =VLOOKUP(B27,'26MY_CIV5D_DATA'!B:AS,19,FALSE) -> N/A | Q27: =IF(VLOOKUP(B27,'26MY_CIV5D_DATA'!B:AS,20,FALSE)="","",VLOOKUP(B27,'26MY_CIV5D_DATA'!B:AS,20,FALSE)) -> 10% Discount Applied. Includes body coloured front underbody spoiler and tailgate spoiler.
B28: 25CIV-5AR-NH883 | C28: =VLOOKUP(B28,'26MY_CIV5D_DATA'!B:AS,3,FALSE) -> Platinum White Pearl (NH-883P) | D28: =B28 -> 25CIV-5AR-NH883
B29: 25CIV-5AR-NH932 | C29: =VLOOKUP(B29,'26MY_CIV5D_DATA'!B:AS,3,FALSE) -> Solar Reflection Silver (NH-932M) | D29: =B29 -> 25CIV-5AR-NH932
B30: 25CIV-5AR-NH904 | C30: =VLOOKUP(B30,'26MY_CIV5D_DATA'!B:AS,3,FALSE) -> Meteoroid Gray Pearl (NH-904M) | D30: =B30 -> 25CIV-5AR-NH904
B31: 25CIV-5AR-NH912 | C31: =VLOOKUP(B31,'26MY_CIV5D_DATA'!B:AS,3,FALSE) -> Urban Grey Pearl (NH-912P) | D31: =B31 -> 25CIV-5AR-NH912
B32: 25CIV-5AR-NH731 | C32: =VLOOKUP(B32,'26MY_CIV5D_DATA'!B:AS,3,FALSE) -> Crystal Black Pearl (NH-731P) | D32: =B32 -> 25CIV-5AR-NH731
B33: 25CIV-5AR-R513 | C33: =VLOOKUP(B33,'26MY_CIV5D_DATA'!B:AS,3,FALSE) -> Rallye Red (R-513) | D33: =B33 -> 25CIV-5AR-R513
B34: 25CIV-5AR-B637 | C34: =VLOOKUP(B34,'26MY_CIV5D_DATA'!B:AS,3,FALSE) -> Boost Blue Pearl (B-637P) | D34: =B34 -> 25CIV-5AR-B637
B36: 22CIV-COLD-PK20 | C36: =VLOOKUP(B36,'26MY_CIV5D_DATA'!B:AS,3,FALSE) -> Cold Weather Package - 2.0L | D36: =B36 -> 22CIV-COLD-PK20 | E36: =VLOOKUP(B36,'26MY_CIV5D_DATA'!B:AS,9,FALSE) -> 230.85 | F36: =VLOOKUP(B36,'26MY_CIV5D_DATA'!B:AS,10,FALSE) -> 384.75 | G36: =VLOOKUP(B36,'26MY_CIV5D_DATA'!B:AS,7,FALSE) -> 1.4 | H36: =VLOOKUP(B36,'26MY_CIV5D_DATA'!B:AS,11,FALSE) -> 638.15 | I36: =VLOOKUP(B36,'26MY_CIV5D_DATA'!B:AS,12,FALSE) -> 0 | J36: =VLOOKUP(B36,'26MY_CIV5D_DATA'!B:AS,13,FALSE) -> 0 | K36: =VLOOKUP($B36,'26MY_CIV5D_DATA'!$B:$AS,14,FALSE) -> 0 | L36: =VLOOKUP(B36,'26MY_CIV5D_DATA'!B:AS,15,FALSE) -> • | M36: =VLOOKUP(B36,'26MY_CIV5D_DATA'!B:AS,16,FALSE) -> • | N36: =VLOOKUP($B36,'26MY_CIV5D_DATA'!$B:$AS,17,FALSE) -> 0 | O36: =VLOOKUP(B36,'26MY_CIV5D_DATA'!B:AS,18,FALSE) -> • | P36: =VLOOKUP(B36,'26MY_CIV5D_DATA'!B:AS,19,FALSE) -> N/A | Q36: =IF(VLOOKUP(B36,'26MY_CIV5D_DATA'!B:AS,20,FALSE)="","",VLOOKUP(B36,'26MY_CIV5D_DATA'!B:AS,20,FALSE)) -> 5% Discount Applied.
B37: 08T44-SNA-302 | C37: =VLOOKUP(B37,'26MY_CIV5D_DATA'!B:AS,3,FALSE) -> Engine Block Heater - 2.0L | D37: =B37 -> 08T44-SNA-302
B38: 31670-BMS-004H | C38: =VLOOKUP(B38,'26MY_CIV5D_DATA'!B:AS,3,FALSE) -> Optimate 12V Auto Battery Charger/Maintainer | D38: =B38 -> 31670-BMS-004H
B40: 23CIV-COLD-TR | C40: =VLOOKUP(B40,'26MY_CIV5D_DATA'!B:AS,3,FALSE) -> Cold Weather Package - Type R | D40: =B40 -> 23CIV-COLD-TR | E40: =VLOOKUP(B40,'26MY_CIV5D_DATA'!B:AS,9,FALSE) -> 278.35 | F40: =VLOOKUP(B40,'26MY_CIV5D_DATA'!B:AS,10,FALSE) -> 464.55 | G40: =VLOOKUP(B40,'26MY_CIV5D_DATA'!B:AS,7,FALSE) -> 1.4 | H40: =VLOOKUP(B40,'26MY_CIV5D_DATA'!B:AS,11,FALSE) -> 717.95 | I40: =VLOOKUP(B40,'26MY_CIV5D_DATA'!B:AS,12,FALSE) -> 0 | J40: =VLOOKUP(B40,'26MY_CIV5D_DATA'!B:AS,13,FALSE) -> 0 | K40: =VLOOKUP($B40,'26MY_CIV5D_DATA'!$B:$AS,14,FALSE) -> 0 | L40: =VLOOKUP(B40,'26MY_CIV5D_DATA'!B:AS,15,FALSE) -> N/A | M40: =VLOOKUP(B40,'26MY_CIV5D_DATA'!B:AS,16,FALSE) -> N/A | N40: =VLOOKUP($B40,'26MY_CIV5D_DATA'!$B:$AS,17,FALSE) -> 0 | O40: =VLOOKUP(B40,'26MY_CIV5D_DATA'!B:AS,18,FALSE) -> N/A | P40: =VLOOKUP(B40,'26MY_CIV5D_DATA'!B:AS,19,FALSE) -> • | Q40: =IF(VLOOKUP(B40,'26MY_CIV5D_DATA'!B:AS,20,FALSE)="","",VLOOKUP(B40,'26MY_CIV5D_DATA'!B:AS,20,FALSE)) -> 5% Discount Applied.
B41: 08T44-TGH-300 | C41: =VLOOKUP(B41,'26MY_CIV5D_DATA'!B:AS,3,FALSE) -> Engine Block Heater - Type R | D41: =B41 -> 08T44-TGH-300
B42: 31670-BMS-004H | C42: =VLOOKUP(B42,'26MY_CIV5D_DATA'!B:AS,3,FALSE) -> Optimate 12V Auto Battery Charger/Maintainer | D42: =B42 -> 31670-BMS-004H
B44: 25CIV5D-PRO-PET | C44: =VLOOKUP(B44,'26MY_CIV5D_DATA'!B:AS,3,FALSE) -> Protection Package - Petrol | D44: =B44 -> 25CIV5D-PRO-PET | E44: =VLOOKUP(B44,'26MY_CIV5D_DATA'!B:AS,9,FALSE) -> 297 | F44: =VLOOKUP(B44,'26MY_CIV5D_DATA'!B:AS,10,FALSE) -> 550 | G44: =VLOOKUP(B44,'26MY_CIV5D_DATA'!B:AS,7,FALSE) -> 0.6 | H44: =VLOOKUP(B44,'26MY_CIV5D_DATA'!B:AS,11,FALSE) -> 658.6 | I44: =VLOOKUP(B44,'26MY_CIV5D_DATA'!B:AS,12,FALSE) -> 0 | J44: =VLOOKUP(B44,'26MY_CIV5D_DATA'!B:AS,13,FALSE) -> 0 | K44: =VLOOKUP($B44,'26MY_CIV5D_DATA'!$B:$AS,14,FALSE) -> 0 | L44: =VLOOKUP(B44,'26MY_CIV5D_DATA'!B:AS,15,FALSE) -> • | M44: =VLOOKUP(B44,'26MY_CIV5D_DATA'!B:AS,16,FALSE) -> N/A | N44: =VLOOKUP($B44,'26MY_CIV5D_DATA'!$B:$AS,17,FALSE) -> 0 | O44: =VLOOKUP(B44,'26MY_CIV5D_DATA'!B:AS,18,FALSE) -> N/A | P44: =VLOOKUP(B44,'26MY_CIV5D_DATA'!B:AS,19,FALSE) -> N/A | Q44: =IF(VLOOKUP(B44,'26MY_CIV5D_DATA'!B:AS,20,FALSE)="","",VLOOKUP(B44,'26MY_CIV5D_DATA'!B:AS,20,FALSE))
B45: 08P17-T20-110 | C45: =VLOOKUP(B45,'26MY_CIV5D_DATA'!B:AS,3,FALSE) -> Floor Mats - All-Season | D45: =B45 -> 08P17-T20-110
B46: 08U45-T47-100B | C46: =VLOOKUP(B46,'26MY_CIV5D_DATA'!B:AS,3,FALSE) -> Cargo Tray | D46: =B46 -> 08U45-T47-100B
B47: 08P09-T47-300 | C47: =VLOOKUP(B47,'26MY_CIV5D_DATA'!B:AS,3,FALSE) -> Splash Guards - Rear | D47: =B47 -> 08P09-T47-300
B49: 25CIV5-PRO-HYB | C49: =VLOOKUP(B49,'26MY_CIV5D_DATA'!B:AS,3,FALSE) -> Protection Package - Hybrid | D49: =B49 -> 25CIV5-PRO-HYB | E49: =VLOOKUP(B49,'26MY_CIV5D_DATA'!B:AS,9,FALSE) -> 297 | F49: =VLOOKUP(B49,'26MY_CIV5D_DATA'!B:AS,10,FALSE) -> 550 | G49: =VLOOKUP(B49,'26MY_CIV5D_DATA'!B:AS,7,FALSE) -> 0.6 | H49: 602 | I49: =VLOOKUP(B49,'26MY_CIV5D_DATA'!B:AS,12,FALSE) -> 0 | J49: =VLOOKUP(B49,'26MY_CIV5D_DATA'!B:AS,13,FALSE) -> 0 | K49: =VLOOKUP($B49,'26MY_CIV5D_DATA'!$B:$AS,14,FALSE) -> 0 | L49: =VLOOKUP(B49,'26MY_CIV5D_DATA'!B:AS,15,FALSE) -> N/A | M49: =VLOOKUP(B49,'26MY_CIV5D_DATA'!B:AS,16,FALSE) -> • | N49: =VLOOKUP($B49,'26MY_CIV5D_DATA'!$B:$AS,17,FALSE) -> 0 | O49: =VLOOKUP(B49,'26MY_CIV5D_DATA'!B:AS,18,FALSE) -> • | P49: =VLOOKUP(B49,'26MY_CIV5D_DATA'!B:AS,19,FALSE) -> N/A | Q49: =IF(VLOOKUP(B49,'26MY_CIV5D_DATA'!B:AS,20,FALSE)="","",VLOOKUP(B49,'26MY_CIV5D_DATA'!B:AS,20,FALSE))
B50: 08P17-T20-110A | C50: =VLOOKUP(B50,'26MY_CIV5D_DATA'!B:AS,3,FALSE) -> Floor Mats Hybrid - All-Season | D50: =B50 -> 08P17-T20-110A
B51: 08U45-T47-100B | C51: =VLOOKUP(B51,'26MY_CIV5D_DATA'!B:AS,3,FALSE) -> Cargo Tray | D51: =B51 -> 08U45-T47-100B
B52: 08P09-T47-300 | C52: =VLOOKUP(B52,'26MY_CIV5D_DATA'!B:AS,3,FALSE) -> Splash Guards - Rear | D52: =B52 -> 08P09-T47-300
B54: 23TYPER-PROPK | C54: =VLOOKUP(B54,'26MY_CIV5D_DATA'!B:AS,3,FALSE) -> Protection Package - Type R | D54: =B54 -> 23TYPER-PROPK | E54: =VLOOKUP(B54,'26MY_CIV5D_DATA'!B:AS,9,FALSE) -> 245.7 | F54: =VLOOKUP(B54,'26MY_CIV5D_DATA'!B:AS,10,FALSE) -> 455 | G54: =VLOOKUP(B54,'26MY_CIV5D_DATA'!B:AS,7,FALSE) -> 0.2 | H54: 602 | I54: =VLOOKUP(B54,'26MY_CIV5D_DATA'!B:AS,12,FALSE) -> 0 | J54: =VLOOKUP(B54,'26MY_CIV5D_DATA'!B:AS,13,FALSE) -> 0 | K54: =VLOOKUP($B54,'26MY_CIV5D_DATA'!$B:$AS,14,FALSE) -> 0 | L54: =VLOOKUP(B54,'26MY_CIV5D_DATA'!B:AS,15,FALSE) -> N/A | M54: =VLOOKUP(B54,'26MY_CIV5D_DATA'!B:AS,16,FALSE) -> N/A | N54: =VLOOKUP($B54,'26MY_CIV5D_DATA'!$B:$AS,17,FALSE) -> 0 | O54: =VLOOKUP(B54,'26MY_CIV5D_DATA'!B:AS,18,FALSE) -> N/A | P54: =VLOOKUP(B54,'26MY_CIV5D_DATA'!B:AS,19,FALSE) -> • | Q54: =IF(VLOOKUP(B54,'26MY_CIV5D_DATA'!B:AS,20,FALSE)="","",VLOOKUP(B54,'26MY_CIV5D_DATA'!B:AS,20,FALSE))
B55: 08P17-T20-110 | C55: =VLOOKUP(B55,'26MY_CIV5D_DATA'!B:AS,3,FALSE) -> Floor Mats - All-Season | D55: =B55 -> 08P17-T20-110
B56: 08U45-T60-100 | C56: =VLOOKUP(B56,'26MY_CIV5D_DATA'!B:AS,3,FALSE) -> Cargo Tray - Type R | D56: =B56 -> 08U45-T60-100
C58: 2.0 Wheels and Wheel Accessories
C59: Description | D59: Part Number | E59: Dealer Net | F59: List Price | G59: FRT | H59: Installed Price | I59: Application | Q59: Comments
I60: ='26MY_CIV5D_DATA'!M$7 -> 0 | J60: ='26MY_CIV5D_DATA'!N$7 -> 0 | K60: ='26MY_CIV5D_DATA'!O$7 -> 0 | L60: ='26MY_CIV5D_DATA'!P$7 -> SPORT | M60: ='26MY_CIV5D_DATA'!Q$7 -> SPORT Hybrid | N60: ='26MY_CIV5D_DATA'!R$7 -> 0 | O60: ='26MY_CIV5D_DATA'!S$7 -> Sport Touring Hybrid | P60: ='26MY_CIV5D_DATA'!T$7 -> Type R
B61: 42700-TBA-A12 | C61: =VLOOKUP(B61,'26MY_CIV5D_DATA'!B:AS,3,FALSE) -> 16” Winter Steel Wheels | D61: =B61 -> 42700-TBA-A12 | E61: =VLOOKUP(B61,'26MY_CIV5D_DATA'!B:AS,9,FALSE) -> 317.84 | F61: =VLOOKUP(B61,'26MY_CIV5D_DATA'!B:AS,10,FALSE) -> 522.72 | G61: =VLOOKUP(B61,'26MY_CIV5D_DATA'!B:AS,7,FALSE) -> 1.6 | H61: =VLOOKUP(B61,'26MY_CIV5D_DATA'!B:AS,11,FALSE) -> 812.32 | I61: =VLOOKUP(B61,'26MY_CIV5D_DATA'!B:AS,12,FALSE) -> 0 | J61: =VLOOKUP(B61,'26MY_CIV5D_DATA'!B:AS,13,FALSE) -> 0 | K61: =VLOOKUP($B61,'26MY_CIV5D_DATA'!$B:$AS,14,FALSE) -> 0 | L61: =VLOOKUP(B61,'26MY_CIV5D_DATA'!B:AS,15,FALSE) -> • | M61: =VLOOKUP(B61,'26MY_CIV5D_DATA'!B:AS,16,FALSE) -> N/A | N61: =VLOOKUP($B61,'26MY_CIV5D_DATA'!$B:$AS,17,FALSE) -> 0 | O61: =VLOOKUP(B61,'26MY_CIV5D_DATA'!B:AS,18,FALSE) -> N/A | P61: =VLOOKUP(B61,'26MY_CIV5D_DATA'!B:AS,19,FALSE) -> N/A | Q61: =IF(VLOOKUP(B61,'26MY_CIV5D_DATA'!B:AS,20,FALSE)="","",VLOOKUP(B61,'26MY_CIV5D_DATA'!B:AS,20,FALSE)) -> Priced as a set of 4 wheels. Tires sold separately.
B62: 480-670-6545GB | C62: =VLOOKUP(B62,'26MY_CIV5D_DATA'!B:AS,3,FALSE) -> 16" Enkei M52 Wheel - Gloss Black | D62: =B62 -> 480-670-6545GB | E62: =VLOOKUP(B62,'26MY_CIV5D_DATA'!B:AS,9,FALSE) -> 764 | F62: =VLOOKUP(B62,'26MY_CIV5D_DATA'!B:AS,10,FALSE) -> 1028 | G62: =VLOOKUP(B62,'26MY_CIV5D_DATA'!B:AS,7,FALSE) -> 1.6 | H62: =VLOOKUP(B62,'26MY_CIV5D_DATA'!B:AS,11,FALSE) -> 1317.6 | I62: =VLOOKUP(B62,'26MY_CIV5D_DATA'!B:AS,12,FALSE) -> 0 | J62: =VLOOKUP(B62,'26MY_CIV5D_DATA'!B:AS,13,FALSE) -> 0 | K62: =VLOOKUP($B62,'26MY_CIV5D_DATA'!$B:$AS,14,FALSE) -> 0 | L62: =VLOOKUP(B62,'26MY_CIV5D_DATA'!B:AS,15,FALSE) -> T | M62: =VLOOKUP(B62,'26MY_CIV5D_DATA'!B:AS,16,FALSE) -> N/A | N62: =VLOOKUP($B62,'26MY_CIV5D_DATA'!$B:$AS,17,FALSE) -> 0 | O62: =VLOOKUP(B62,'26MY_CIV5D_DATA'!B:AS,18,FALSE) -> N/A | P62: =VLOOKUP(B62,'26MY_CIV5D_DATA'!B:AS,19,FALSE) -> N/A | Q62: =IF(VLOOKUP(B62,'26MY_CIV5D_DATA'!B:AS,20,FALSE)="","",VLOOKUP(B62,'26MY_CIV5D_DATA'!B:AS,20,FALSE)) -> Priced as a set of 4 wheels. Tires sold separately.
B63: 480-670-6545SP | C63: =VLOOKUP(B63,'26MY_CIV5D_DATA'!B:AS,3,FALSE) -> 16" Enkei M52 Wheel - Silver | D63: =B63 -> 480-670-6545SP | E63: =VLOOKUP(B63,'26MY_CIV5D_DATA'!B:AS,9,FALSE) -> 764 | F63: =VLOOKUP(B63,'26MY_CIV5D_DATA'!B:AS,10,FALSE) -> 1028 | G63: =VLOOKUP(B63,'26MY_CIV5D_DATA'!B:AS,7,FALSE) -> 1.6 | H63: =VLOOKUP(B63,'26MY_CIV5D_DATA'!B:AS,11,FALSE) -> 1317.6 | I63: =VLOOKUP(B63,'26MY_CIV5D_DATA'!B:AS,12,FALSE) -> 0 | J63: =VLOOKUP(B63,'26MY_CIV5D_DATA'!B:AS,13,FALSE) -> 0 | K63: =VLOOKUP($B63,'26MY_CIV5D_DATA'!$B:$AS,14,FALSE) -> 0 | L63: =VLOOKUP(B63,'26MY_CIV5D_DATA'!B:AS,15,FALSE) -> T | M63: =VLOOKUP(B63,'26MY_CIV5D_DATA'!B:AS,16,FALSE) -> N/A | N63: =VLOOKUP($B63,'26MY_CIV5D_DATA'!$B:$AS,17,FALSE) -> 0 | O63: =VLOOKUP(B63,'26MY_CIV5D_DATA'!B:AS,18,FALSE) -> N/A | P63: =VLOOKUP(B63,'26MY_CIV5D_DATA'!B:AS,19,FALSE) -> N/A | Q63: =IF(VLOOKUP(B63,'26MY_CIV5D_DATA'!B:AS,20,FALSE)="","",VLOOKUP(B63,'26MY_CIV5D_DATA'!B:AS,20,FALSE)) -> Priced as a set of 4 wheels. Tires sold separately.
B64: 509-775-6545BH | C64: =VLOOKUP(B64,'26MY_CIV5D_DATA'!B:AS,3,FALSE) -> 17" Enkei Draco Wheel, Gloss Black | D64: =B64 -> 509-775-6545BH | E64: =VLOOKUP(B64,'26MY_CIV5D_DATA'!B:AS,9,FALSE) -> 856 | F64: =VLOOKUP(B64,'26MY_CIV5D_DATA'!B:AS,10,FALSE) -> 1148 | G64: =VLOOKUP(B64,'26MY_CIV5D_DATA'!B:AS,7,FALSE) -> 1.6 | H64: =VLOOKUP(B64,'26MY_CIV5D_DATA'!B:AS,11,FALSE) -> 1437.6 | I64: =VLOOKUP(B64,'26MY_CIV5D_DATA'!B:AS,12,FALSE) -> 0 | J64: =VLOOKUP(B64,'26MY_CIV5D_DATA'!B:AS,13,FALSE) -> 0 | K64: =VLOOKUP($B64,'26MY_CIV5D_DATA'!$B:$AS,14,FALSE) -> 0 | L64: =VLOOKUP(B64,'26MY_CIV5D_DATA'!B:AS,15,FALSE) -> T | M64: =VLOOKUP(B64,'26MY_CIV5D_DATA'!B:AS,16,FALSE) -> N/A | N64: =VLOOKUP($B64,'26MY_CIV5D_DATA'!$B:$AS,17,FALSE) -> 0 | O64: =VLOOKUP(B64,'26MY_CIV5D_DATA'!B:AS,18,FALSE) -> N/A | P64: =VLOOKUP(B64,'26MY_CIV5D_DATA'!B:AS,19,FALSE) -> N/A | Q64: =IF(VLOOKUP(B64,'26MY_CIV5D_DATA'!B:AS,20,FALSE)="","",VLOOKUP(B64,'26MY_CIV5D_DATA'!B:AS,20,FALSE)) -> Priced as a set of 4 wheels. Tires sold separately.
B65: 509-775-6545SH | C65: =VLOOKUP(B65,'26MY_CIV5D_DATA'!B:AS,3,FALSE) -> 17" Enkei Draco Wheel, Silver | D65: =B65 -> 509-775-6545SH | E65: =VLOOKUP(B65,'26MY_CIV5D_DATA'!B:AS,9,FALSE) -> 856 | F65: =VLOOKUP(B65,'26MY_CIV5D_DATA'!B:AS,10,FALSE) -> 1148 | G65: =VLOOKUP(B65,'26MY_CIV5D_DATA'!B:AS,7,FALSE) -> 1.6 | H65: =VLOOKUP(B65,'26MY_CIV5D_DATA'!B:AS,11,FALSE) -> 1437.6 | I65: =VLOOKUP(B65,'26MY_CIV5D_DATA'!B:AS,12,FALSE) -> 0 | J65: =VLOOKUP(B65,'26MY_CIV5D_DATA'!B:AS,13,FALSE) -> 0 | K65: =VLOOKUP($B65,'26MY_CIV5D_DATA'!$B:$AS,14,FALSE) -> 0 | L65: =VLOOKUP(B65,'26MY_CIV5D_DATA'!B:AS,15,FALSE) -> T | M65: =VLOOKUP(B65,'26MY_CIV5D_DATA'!B:AS,16,FALSE) -> N/A | N65: =VLOOKUP($B65,'26MY_CIV5D_DATA'!$B:$AS,17,FALSE) -> 0 | O65: =VLOOKUP(B65,'26MY_CIV5D_DATA'!B:AS,18,FALSE) -> N/A | P65: =VLOOKUP(B65,'26MY_CIV5D_DATA'!B:AS,19,FALSE) -> N/A | Q65: =IF(VLOOKUP(B65,'26MY_CIV5D_DATA'!B:AS,20,FALSE)="","",VLOOKUP(B65,'26MY_CIV5D_DATA'!B:AS,20,FALSE)) -> Priced as a set of 4 wheels. Tires sold separately.
B66: 08W18-T20-100 | C66: =VLOOKUP(B66,'26MY_CIV5D_DATA'!B:AS,3,FALSE) -> 18" Alloy Wheel - Black | D66: =B66 -> 08W18-T20-100 | E66: =VLOOKUP(B66,'26MY_CIV5D_DATA'!B:AS,9,FALSE) -> 2316 | F66: =VLOOKUP(B66,'26MY_CIV5D_DATA'!B:AS,10,FALSE) -> 3564 | G66: =VLOOKUP(B66,'26MY_CIV5D_DATA'!B:AS,7,FALSE) -> 1.6 | H66: =VLOOKUP(B66,'26MY_CIV5D_DATA'!B:AS,11,FALSE) -> 3853.6 | I66: =VLOOKUP(B66,'26MY_CIV5D_DATA'!B:AS,12,FALSE) -> 0 | J66: =VLOOKUP(B66,'26MY_CIV5D_DATA'!B:AS,13,FALSE) -> 0 | K66: =VLOOKUP($B66,'26MY_CIV5D_DATA'!$B:$AS,14,FALSE) -> 0 | L66: =VLOOKUP(B66,'26MY_CIV5D_DATA'!B:AS,15,FALSE) -> E | M66: =VLOOKUP(B66,'26MY_CIV5D_DATA'!B:AS,16,FALSE) -> E | N66: =VLOOKUP($B66,'26MY_CIV5D_DATA'!$B:$AS,17,FALSE) -> 0 | O66: =VLOOKUP(B66,'26MY_CIV5D_DATA'!B:AS,18,FALSE) -> E | P66: =VLOOKUP(B66,'26MY_CIV5D_DATA'!B:AS,19,FALSE) -> N/A | Q66: =IF(VLOOKUP(B66,'26MY_CIV5D_DATA'!B:AS,20,FALSE)="","",VLOOKUP(B66,'26MY_CIV5D_DATA'!B:AS,20,FALSE)) -> Priced as a set of 4 wheels. Tires sold separately.
B67: 08W19-T60-100 | C67: =VLOOKUP(B67,'26MY_CIV5D_DATA'!B:AS,3,FALSE) -> 19" Light Weight Alloy Wheel | D67: =B67 -> 08W19-T60-100 | E67: =VLOOKUP(B67,'26MY_CIV5D_DATA'!B:AS,9,FALSE) -> 4664 | F67: =VLOOKUP(B67,'26MY_CIV5D_DATA'!B:AS,10,FALSE) -> 6664 | G67: =VLOOKUP(B67,'26MY_CIV5D_DATA'!B:AS,7,FALSE) -> 1.6 | H67: =VLOOKUP(B67,'26MY_CIV5D_DATA'!B:AS,11,FALSE) -> 6953.6 | I67: =VLOOKUP(B67,'26MY_CIV5D_DATA'!B:AS,12,FALSE) -> 0 | J67: =VLOOKUP(B67,'26MY_CIV5D_DATA'!B:AS,13,FALSE) -> 0 | K67: =VLOOKUP($B67,'26MY_CIV5D_DATA'!$B:$AS,14,FALSE) -> 0 | L67: =VLOOKUP(B67,'26MY_CIV5D_DATA'!B:AS,15,FALSE) -> N/A | M67: =VLOOKUP(B67,'26MY_CIV5D_DATA'!B:AS,16,FALSE) -> N/A | N67: =VLOOKUP($B67,'26MY_CIV5D_DATA'!$B:$AS,17,FALSE) -> 0 | O67: =VLOOKUP(B67,'26MY_CIV5D_DATA'!B:AS,18,FALSE) -> N/A | P67: =VLOOKUP(B67,'26MY_CIV5D_DATA'!B:AS,19,FALSE) -> E | Q67: =IF(VLOOKUP(B67,'26MY_CIV5D_DATA'!B:AS,20,FALSE)="","",VLOOKUP(B67,'26MY_CIV5D_DATA'!B:AS,20,FALSE)) -> Priced as a set of 4 wheels. Tires sold separately. Laser-etched logo & shark gray metallic finish
B68: 08W42-S2A-101 | C68: =VLOOKUP(B68,'26MY_CIV5D_DATA'!B:AS,3,FALSE) -> Wheel Locks - Black | D68: =B68 -> 08W42-S2A-101 | E68: =VLOOKUP(B68,'26MY_CIV5D_DATA'!B:AS,9,FALSE) -> 61 | F68: =VLOOKUP(B68,'26MY_CIV5D_DATA'!B:AS,10,FALSE) -> 102 | G68: =VLOOKUP(B68,'26MY_CIV5D_DATA'!B:AS,7,FALSE) -> 0.2 | H68: =VLOOKUP(B68,'26MY_CIV5D_DATA'!B:AS,11,FALSE) -> 138.2 | I68: =VLOOKUP(B68,'26MY_CIV5D_DATA'!B:AS,12,FALSE) -> 0 | J68: =VLOOKUP(B68,'26MY_CIV5D_DATA'!B:AS,13,FALSE) -> 0 | K68: =VLOOKUP($B68,'26MY_CIV5D_DATA'!$B:$AS,14,FALSE) -> 0 | L68: =VLOOKUP(B68,'26MY_CIV5D_DATA'!B:AS,15,FALSE) -> • | M68: =VLOOKUP(B68,'26MY_CIV5D_DATA'!B:AS,16,FALSE) -> • | N68: =VLOOKUP($B68,'26MY_CIV5D_DATA'!$B:$AS,17,FALSE) -> 0 | O68: =VLOOKUP(B68,'26MY_CIV5D_DATA'!B:AS,18,FALSE) -> • | P68: =VLOOKUP(B68,'26MY_CIV5D_DATA'!B:AS,19,FALSE) -> N/A | Q68: =IF(VLOOKUP(B68,'26MY_CIV5D_DATA'!B:AS,20,FALSE)="","",VLOOKUP(B68,'26MY_CIV5D_DATA'!B:AS,20,FALSE))
B69: 08W42-SCV-302 | C69: =VLOOKUP(B69,'26MY_CIV5D_DATA'!B:AS,3,FALSE) -> Wheel Locks - Chrome | D69: =B69 -> 08W42-SCV-302 | E69: =VLOOKUP(B69,'26MY_CIV5D_DATA'!B:AS,9,FALSE) -> 54 | F69: =VLOOKUP(B69,'26MY_CIV5D_DATA'!B:AS,10,FALSE) -> 90 | G69: =VLOOKUP(B69,'26MY_CIV5D_DATA'!B:AS,7,FALSE) -> 0.2 | H69: =VLOOKUP(B69,'26MY_CIV5D_DATA'!B:AS,11,FALSE) -> 126.2 | I69: =VLOOKUP(B69,'26MY_CIV5D_DATA'!B:AS,12,FALSE) -> 0 | J69: =VLOOKUP(B69,'26MY_CIV5D_DATA'!B:AS,13,FALSE) -> 0 | K69: =VLOOKUP($B69,'26MY_CIV5D_DATA'!$B:$AS,14,FALSE) -> 0 | L69: =VLOOKUP(B69,'26MY_CIV5D_DATA'!B:AS,15,FALSE) -> • | M69: =VLOOKUP(B69,'26MY_CIV5D_DATA'!B:AS,16,FALSE) -> • | N69: =VLOOKUP($B69,'26MY_CIV5D_DATA'!$B:$AS,17,FALSE) -> 0 | O69: =VLOOKUP(B69,'26MY_CIV5D_DATA'!B:AS,18,FALSE) -> • | P69: =VLOOKUP(B69,'26MY_CIV5D_DATA'!B:AS,19,FALSE) -> N/A | Q69: =IF(VLOOKUP(B69,'26MY_CIV5D_DATA'!B:AS,20,FALSE)="","",VLOOKUP(B69,'26MY_CIV5D_DATA'!B:AS,20,FALSE))
B70: 08W42-TG7-301A | C70: =VLOOKUP(B70,'26MY_CIV5D_DATA'!B:AS,3,FALSE) -> Wheel Locks - Black (Type R) | D70: =B70 -> 08W42-TG7-301A | E70: =VLOOKUP(B70,'26MY_CIV5D_DATA'!B:AS,9,FALSE) -> 88 | F70: =VLOOKUP(B70,'26MY_CIV5D_DATA'!B:AS,10,FALSE) -> 147 | G70: =VLOOKUP(B70,'26MY_CIV5D_DATA'!B:AS,7,FALSE) -> 0.2 | H70: =VLOOKUP(B70,'26MY_CIV5D_DATA'!B:AS,11,FALSE) -> 183.2 | I70: =VLOOKUP(B70,'26MY_CIV5D_DATA'!B:AS,12,FALSE) -> 0 | J70: =VLOOKUP(B70,'26MY_CIV5D_DATA'!B:AS,13,FALSE) -> 0 | K70: =VLOOKUP($B70,'26MY_CIV5D_DATA'!$B:$AS,14,FALSE) -> 0 | L70: =VLOOKUP(B70,'26MY_CIV5D_DATA'!B:AS,15,FALSE) -> N/A | M70: =VLOOKUP(B70,'26MY_CIV5D_DATA'!B:AS,16,FALSE) -> N/A | N70: =VLOOKUP($B70,'26MY_CIV5D_DATA'!$B:$AS,17,FALSE) -> 0 | O70: =VLOOKUP(B70,'26MY_CIV5D_DATA'!B:AS,18,FALSE) -> N/A | P70: =VLOOKUP(B70,'26MY_CIV5D_DATA'!B:AS,19,FALSE) -> • | Q70: =IF(VLOOKUP(B70,'26MY_CIV5D_DATA'!B:AS,20,FALSE)="","",VLOOKUP(B70,'26MY_CIV5D_DATA'!B:AS,20,FALSE))
B71: 08W42-TK4-301 | C71: =VLOOKUP(B71,'26MY_CIV5D_DATA'!B:AS,3,FALSE) -> Wheel Locks - Chrome (Type R) | D71: =B71 -> 08W42-TK4-301 | E71: =VLOOKUP(B71,'26MY_CIV5D_DATA'!B:AS,9,FALSE) -> 94 | F71: =VLOOKUP(B71,'26MY_CIV5D_DATA'!B:AS,10,FALSE) -> 157 | G71: =VLOOKUP(B71,'26MY_CIV5D_DATA'!B:AS,7,FALSE) -> 0.2 | H71: =VLOOKUP(B71,'26MY_CIV5D_DATA'!B:AS,11,FALSE) -> 193.2 | I71: =VLOOKUP(B71,'26MY_CIV5D_DATA'!B:AS,12,FALSE) -> 0 | J71: =VLOOKUP(B71,'26MY_CIV5D_DATA'!B:AS,13,FALSE) -> 0 | K71: =VLOOKUP($B71,'26MY_CIV5D_DATA'!$B:$AS,14,FALSE) -> 0 | L71: =VLOOKUP(B71,'26MY_CIV5D_DATA'!B:AS,15,FALSE) -> N/A | M71: =VLOOKUP(B71,'26MY_CIV5D_DATA'!B:AS,16,FALSE) -> N/A | N71: =VLOOKUP($B71,'26MY_CIV5D_DATA'!$B:$AS,17,FALSE) -> 0 | O71: =VLOOKUP(B71,'26MY_CIV5D_DATA'!B:AS,18,FALSE) -> N/A | P71: =VLOOKUP(B71,'26MY_CIV5D_DATA'!B:AS,19,FALSE) -> • | Q71: =IF(VLOOKUP(B71,'26MY_CIV5D_DATA'!B:AS,20,FALSE)="","",VLOOKUP(B71,'26MY_CIV5D_DATA'!B:AS,20,FALSE))
B72: 08W42-TGG-100 | C72: =VLOOKUP(B72,'26MY_CIV5D_DATA'!B:AS,3,FALSE) -> Wheel Lug Nuts - Black | D72: =B72 -> 08W42-TGG-100 | E72: =VLOOKUP(B72,'26MY_CIV5D_DATA'!B:AS,9,FALSE) -> 57 | F72: =VLOOKUP(B72,'26MY_CIV5D_DATA'!B:AS,10,FALSE) -> 91 | G72: =VLOOKUP(B72,'26MY_CIV5D_DATA'!B:AS,7,FALSE) -> 0.2 | H72: =VLOOKUP(B72,'26MY_CIV5D_DATA'!B:AS,11,FALSE) -> 127.2 | I72: =VLOOKUP(B72,'26MY_CIV5D_DATA'!B:AS,12,FALSE) -> 0 | J72: =VLOOKUP(B72,'26MY_CIV5D_DATA'!B:AS,13,FALSE) -> 0 | K72: =VLOOKUP($B72,'26MY_CIV5D_DATA'!$B:$AS,14,FALSE) -> 0 | L72: =VLOOKUP(B72,'26MY_CIV5D_DATA'!B:AS,15,FALSE) -> • | M72: =VLOOKUP(B72,'26MY_CIV5D_DATA'!B:AS,16,FALSE) -> • | N72: =VLOOKUP($B72,'26MY_CIV5D_DATA'!$B:$AS,17,FALSE) -> 0 | O72: =VLOOKUP(B72,'26MY_CIV5D_DATA'!B:AS,18,FALSE) -> • | P72: =VLOOKUP(B72,'26MY_CIV5D_DATA'!B:AS,19,FALSE) -> N/A | Q72: =IF(VLOOKUP(B72,'26MY_CIV5D_DATA'!B:AS,20,FALSE)="","",VLOOKUP(B72,'26MY_CIV5D_DATA'!B:AS,20,FALSE)) -> Includes: 1 set (i.e. 4 lug nuts). A complete install requires 5 sets (i.e. 20 lug nuts) for 4 wheels.
C74: 3.0 Exterior
C75: Description | D75: Part Number | E75: Dealer Net | F75: List Price | G75: FRT | H75: Installed Price | I75: Application | Q75: Comments
I76: ='26MY_CIV5D_DATA'!M$7 -> 0 | J76: ='26MY_CIV5D_DATA'!N$7 -> 0 | K76: ='26MY_CIV5D_DATA'!O$7 -> 0 | L76: ='26MY_CIV5D_DATA'!P$7 -> SPORT | M76: ='26MY_CIV5D_DATA'!Q$7 -> SPORT Hybrid | N76: ='26MY_CIV5D_DATA'!R$7 -> 0 | O76: ='26MY_CIV5D_DATA'!S$7 -> Sport Touring Hybrid | P76: ='26MY_CIV5D_DATA'!T$7 -> Type R
B77: 08F20-T47-100E | C77: =VLOOKUP(B77,'26MY_CIV5D_DATA'!B:AS,3,FALSE) -> Black Emblem H-Mark | D77: =B77 -> 08F20-T47-100E | E77: =VLOOKUP(B77,'26MY_CIV5D_DATA'!B:AS,9,FALSE) -> 86 | F77: =VLOOKUP(B77,'26MY_CIV5D_DATA'!B:AS,10,FALSE) -> 123 | G77: =VLOOKUP(B77,'26MY_CIV5D_DATA'!B:AS,7,FALSE) -> 0.7 | H77: =VLOOKUP(B77,'26MY_CIV5D_DATA'!B:AS,11,FALSE) -> 249.7 | I77: =VLOOKUP(B77,'26MY_CIV5D_DATA'!B:AS,12,FALSE) -> 0 | J77: =VLOOKUP(B77,'26MY_CIV5D_DATA'!B:AS,13,FALSE) -> 0 | K77: =VLOOKUP($B77,'26MY_CIV5D_DATA'!$B:$AS,14,FALSE) -> 0 | L77: =VLOOKUP(B77,'26MY_CIV5D_DATA'!B:AS,15,FALSE) -> • | M77: =VLOOKUP(B77,'26MY_CIV5D_DATA'!B:AS,16,FALSE) -> • | N77: =VLOOKUP($B77,'26MY_CIV5D_DATA'!$B:$AS,17,FALSE) -> 0 | O77: =VLOOKUP(B77,'26MY_CIV5D_DATA'!B:AS,18,FALSE) -> • | P77: =VLOOKUP(B77,'26MY_CIV5D_DATA'!B:AS,19,FALSE) -> N/A | Q77: =IF(VLOOKUP(B77,'26MY_CIV5D_DATA'!B:AS,20,FALSE)="","",VLOOKUP(B77,'26MY_CIV5D_DATA'!B:AS,20,FALSE)) -> Front and Rear H-Mark Logo.
B78: 08P47-T20-300 | C78: =VLOOKUP(B78,'26MY_CIV5D_DATA'!B:AS,3,FALSE) -> Hood Protector | D78: =B78 -> 08P47-T20-300 | E78: =VLOOKUP(B78,'26MY_CIV5D_DATA'!B:AS,9,FALSE) -> 221 | F78: =VLOOKUP(B78,'26MY_CIV5D_DATA'!B:AS,10,FALSE) -> 368 | G78: =VLOOKUP(B78,'26MY_CIV5D_DATA'!B:AS,7,FALSE) -> 0.6 | H78: =VLOOKUP(B78,'26MY_CIV5D_DATA'!B:AS,11,FALSE) -> 476.6 | I78: =VLOOKUP(B78,'26MY_CIV5D_DATA'!B:AS,12,FALSE) -> 0 | J78: =VLOOKUP(B78,'26MY_CIV5D_DATA'!B:AS,13,FALSE) -> 0 | K78: =VLOOKUP($B78,'26MY_CIV5D_DATA'!$B:$AS,14,FALSE) -> 0 | L78: =VLOOKUP(B78,'26MY_CIV5D_DATA'!B:AS,15,FALSE) -> • | M78: =VLOOKUP(B78,'26MY_CIV5D_DATA'!B:AS,16,FALSE) -> • | N78: =VLOOKUP($B78,'26MY_CIV5D_DATA'!$B:$AS,17,FALSE) -> 0 | O78: =VLOOKUP(B78,'26MY_CIV5D_DATA'!B:AS,18,FALSE) -> • | P78: =VLOOKUP(B78,'26MY_CIV5D_DATA'!B:AS,19,FALSE) -> N/A | Q78: =IF(VLOOKUP(B78,'26MY_CIV5D_DATA'!B:AS,20,FALSE)="","",VLOOKUP(B78,'26MY_CIV5D_DATA'!B:AS,20,FALSE))
B79: 08R04-T47-100A | C79: =VLOOKUP(B79,'26MY_CIV5D_DATA'!B:AS,3,FALSE) -> Door Visors - Black | D79: =B79 -> 08R04-T47-100A | E79: =VLOOKUP(B79,'26MY_CIV5D_DATA'!B:AS,9,FALSE) -> 207 | F79: =VLOOKUP(B79,'26MY_CIV5D_DATA'!B:AS,10,FALSE) -> 345 | G79: =VLOOKUP(B79,'26MY_CIV5D_DATA'!B:AS,7,FALSE) -> 0.5 | H79: =VLOOKUP(B79,'26MY_CIV5D_DATA'!B:AS,11,FALSE) -> 435.5 | I79: =VLOOKUP(B79,'26MY_CIV5D_DATA'!B:AS,12,FALSE) -> 0 | J79: =VLOOKUP(B79,'26MY_CIV5D_DATA'!B:AS,13,FALSE) -> 0 | K79: =VLOOKUP($B79,'26MY_CIV5D_DATA'!$B:$AS,14,FALSE) -> 0 | L79: =VLOOKUP(B79,'26MY_CIV5D_DATA'!B:AS,15,FALSE) -> • | M79: =VLOOKUP(B79,'26MY_CIV5D_DATA'!B:AS,16,FALSE) -> • | N79: =VLOOKUP($B79,'26MY_CIV5D_DATA'!$B:$AS,17,FALSE) -> 0 | O79: =VLOOKUP(B79,'26MY_CIV5D_DATA'!B:AS,18,FALSE) -> • | P79: =VLOOKUP(B79,'26MY_CIV5D_DATA'!B:AS,19,FALSE) -> • | Q79: =IF(VLOOKUP(B79,'26MY_CIV5D_DATA'!B:AS,20,FALSE)="","",VLOOKUP(B79,'26MY_CIV5D_DATA'!B:AS,20,FALSE))
B80: 08P09-T47-300 | C80: =VLOOKUP(B80,'26MY_CIV5D_DATA'!B:AS,3,FALSE) -> Splash Guards - Rear | D80: =B80 -> 08P09-T47-300 | E80: =VLOOKUP(B80,'26MY_CIV5D_DATA'!B:AS,9,FALSE) -> 63 | F80: =VLOOKUP(B80,'26MY_CIV5D_DATA'!B:AS,10,FALSE) -> 105 | G80: =VLOOKUP(B80,'26MY_CIV5D_DATA'!B:AS,7,FALSE) -> 0.4 | H80: =VLOOKUP(B80,'26MY_CIV5D_DATA'!B:AS,11,FALSE) -> 177.4 | I80: =VLOOKUP(B80,'26MY_CIV5D_DATA'!B:AS,12,FALSE) -> 0 | J80: =VLOOKUP(B80,'26MY_CIV5D_DATA'!B:AS,13,FALSE) -> 0 | K80: =VLOOKUP($B80,'26MY_CIV5D_DATA'!$B:$AS,14,FALSE) -> 0 | L80: =VLOOKUP(B80,'26MY_CIV5D_DATA'!B:AS,15,FALSE) -> • | M80: =VLOOKUP(B80,'26MY_CIV5D_DATA'!B:AS,16,FALSE) -> • | N80: =VLOOKUP($B80,'26MY_CIV5D_DATA'!$B:$AS,17,FALSE) -> 0 | O80: =VLOOKUP(B80,'26MY_CIV5D_DATA'!B:AS,18,FALSE) -> • | P80: =VLOOKUP(B80,'26MY_CIV5D_DATA'!B:AS,19,FALSE) -> N/A | Q80: =IF(VLOOKUP(B80,'26MY_CIV5D_DATA'!B:AS,20,FALSE)="","",VLOOKUP(B80,'26MY_CIV5D_DATA'!B:AS,20,FALSE))
B81: 08R01-T20-300 | C81: =VLOOKUP(B81,'26MY_CIV5D_DATA'!B:AS,3,FALSE) -> Moonroof Visor | D81: =B81 -> 08R01-T20-300 | E81: =VLOOKUP(B81,'26MY_CIV5D_DATA'!B:AS,9,FALSE) -> 174 | F81: =VLOOKUP(B81,'26MY_CIV5D_DATA'!B:AS,10,FALSE) -> 290 | G81: =VLOOKUP(B81,'26MY_CIV5D_DATA'!B:AS,7,FALSE) -> 0.3 | H81: =VLOOKUP(B81,'26MY_CIV5D_DATA'!B:AS,11,FALSE) -> 344.3 | I81: =VLOOKUP(B81,'26MY_CIV5D_DATA'!B:AS,12,FALSE) -> 0 | J81: =VLOOKUP(B81,'26MY_CIV5D_DATA'!B:AS,13,FALSE) -> 0 | K81: =VLOOKUP($B81,'26MY_CIV5D_DATA'!$B:$AS,14,FALSE) -> 0 | L81: =VLOOKUP(B81,'26MY_CIV5D_DATA'!B:AS,15,FALSE) -> • | M81: =VLOOKUP(B81,'26MY_CIV5D_DATA'!B:AS,16,FALSE) -> • | N81: =VLOOKUP($B81,'26MY_CIV5D_DATA'!$B:$AS,17,FALSE) -> 0 | O81: =VLOOKUP(B81,'26MY_CIV5D_DATA'!B:AS,18,FALSE) -> • | P81: =VLOOKUP(B81,'26MY_CIV5D_DATA'!B:AS,19,FALSE) -> N/A | Q81: =IF(VLOOKUP(B81,'26MY_CIV5D_DATA'!B:AS,20,FALSE)="","",VLOOKUP(B81,'26MY_CIV5D_DATA'!B:AS,20,FALSE))
B82: 08P01-T47-100 | C82: =VLOOKUP(B82,'26MY_CIV5D_DATA'!B:AS,3,FALSE) -> Rear Bumper Protector | D82: =B82 -> 08P01-T47-100 | E82: =VLOOKUP(B82,'26MY_CIV5D_DATA'!B:AS,9,FALSE) -> 58 | F82: =VLOOKUP(B82,'26MY_CIV5D_DATA'!B:AS,10,FALSE) -> 83 | G82: =VLOOKUP(B82,'26MY_CIV5D_DATA'!B:AS,7,FALSE) -> 0.1 | H82: =VLOOKUP(B82,'26MY_CIV5D_DATA'!B:AS,11,FALSE) -> 101.1 | I82: =VLOOKUP(B82,'26MY_CIV5D_DATA'!B:AS,12,FALSE) -> 0 | J82: =VLOOKUP(B82,'26MY_CIV5D_DATA'!B:AS,13,FALSE) -> 0 | K82: =VLOOKUP($B82,'26MY_CIV5D_DATA'!$B:$AS,14,FALSE) -> 0 | L82: =VLOOKUP(B82,'26MY_CIV5D_DATA'!B:AS,15,FALSE) -> • | M82: =VLOOKUP(B82,'26MY_CIV5D_DATA'!B:AS,16,FALSE) -> • | N82: =VLOOKUP($B82,'26MY_CIV5D_DATA'!$B:$AS,17,FALSE) -> 0 | O82: =VLOOKUP(B82,'26MY_CIV5D_DATA'!B:AS,18,FALSE) -> • | P82: =VLOOKUP(B82,'26MY_CIV5D_DATA'!B:AS,19,FALSE) -> N/A | Q82: =IF(VLOOKUP(B82,'26MY_CIV5D_DATA'!B:AS,20,FALSE)="","",VLOOKUP(B82,'26MY_CIV5D_DATA'!B:AS,20,FALSE))
B83: 08P20-T20-100A | C83: =VLOOKUP(B83,'26MY_CIV5D_DATA'!B:AS,3,FALSE) -> Door Edge Film | D83: =B83 -> 08P20-T20-100A | E83: =VLOOKUP(B83,'26MY_CIV5D_DATA'!B:AS,9,FALSE) -> 67 | F83: =VLOOKUP(B83,'26MY_CIV5D_DATA'!B:AS,10,FALSE) -> 112 | G83: =VLOOKUP(B83,'26MY_CIV5D_DATA'!B:AS,7,FALSE) -> 0.5 | H83: =VLOOKUP(B83,'26MY_CIV5D_DATA'!B:AS,11,FALSE) -> 202.5 | I83: =VLOOKUP(B83,'26MY_CIV5D_DATA'!B:AS,12,FALSE) -> 0 | J83: =VLOOKUP(B83,'26MY_CIV5D_DATA'!B:AS,13,FALSE) -> 0 | K83: =VLOOKUP($B83,'26MY_CIV5D_DATA'!$B:$AS,14,FALSE) -> 0 | L83: =VLOOKUP(B83,'26MY_CIV5D_DATA'!B:AS,15,FALSE) -> • | M83: =VLOOKUP(B83,'26MY_CIV5D_DATA'!B:AS,16,FALSE) -> • | N83: =VLOOKUP($B83,'26MY_CIV5D_DATA'!$B:$AS,17,FALSE) -> 0 | O83: =VLOOKUP(B83,'26MY_CIV5D_DATA'!B:AS,18,FALSE) -> • | P83: =VLOOKUP(B83,'26MY_CIV5D_DATA'!B:AS,19,FALSE) -> N/A | Q83: =IF(VLOOKUP(B83,'26MY_CIV5D_DATA'!B:AS,20,FALSE)="","",VLOOKUP(B83,'26MY_CIV5D_DATA'!B:AS,20,FALSE)) -> Cannot be installed with Door Edge Guards
B84: 08P48-T60-100 | C84: =VLOOKUP(B84,'26MY_CIV5D_DATA'!B:AS,3,FALSE) -> Film Protection Kit - Type R | D84: =B84 -> 08P48-T60-100 | E84: =VLOOKUP(B84,'26MY_CIV5D_DATA'!B:AS,9,FALSE) -> 169 | F84: =VLOOKUP(B84,'26MY_CIV5D_DATA'!B:AS,10,FALSE) -> 282 | G84: =VLOOKUP(B84,'26MY_CIV5D_DATA'!B:AS,7,FALSE) -> 1 | H84: =VLOOKUP(B84,'26MY_CIV5D_DATA'!B:AS,11,FALSE) -> 463 | I84: =VLOOKUP(B84,'26MY_CIV5D_DATA'!B:AS,12,FALSE) -> 0 | J84: =VLOOKUP(B84,'26MY_CIV5D_DATA'!B:AS,13,FALSE) -> 0 | K84: =VLOOKUP($B84,'26MY_CIV5D_DATA'!$B:$AS,14,FALSE) -> 0 | L84: =VLOOKUP(B84,'26MY_CIV5D_DATA'!B:AS,15,FALSE) -> N/A | M84: =VLOOKUP(B84,'26MY_CIV5D_DATA'!B:AS,16,FALSE) -> N/A | N84: =VLOOKUP($B84,'26MY_CIV5D_DATA'!$B:$AS,17,FALSE) -> 0 | O84: =VLOOKUP(B84,'26MY_CIV5D_DATA'!B:AS,18,FALSE) -> N/A | P84: =VLOOKUP(B84,'26MY_CIV5D_DATA'!B:AS,19,FALSE) -> • | Q84: =IF(VLOOKUP(B84,'26MY_CIV5D_DATA'!B:AS,20,FALSE)="","",VLOOKUP(B84,'26MY_CIV5D_DATA'!B:AS,20,FALSE)) -> Includes Door Edge Film, Door Handle Film & Rear Bumper Applique
B85: 08F02-T60-100 | C85: =VLOOKUP(B85,'26MY_CIV5D_DATA'!B:AS,3,FALSE) -> Carbon Fiber Wing Spoiler - Type R | D85: =B85 -> 08F02-T60-100 | E85: =VLOOKUP(B85,'26MY_CIV5D_DATA'!B:AS,9,FALSE) -> 3022 | F85: =VLOOKUP(B85,'26MY_CIV5D_DATA'!B:AS,10,FALSE) -> 5037 | G85: =VLOOKUP(B85,'26MY_CIV5D_DATA'!B:AS,7,FALSE) -> 0.2 | H85: =VLOOKUP(B85,'26MY_CIV5D_DATA'!B:AS,11,FALSE) -> 5073.2 | I85: =VLOOKUP(B85,'26MY_CIV5D_DATA'!B:AS,12,FALSE) -> 0 | J85: =VLOOKUP(B85,'26MY_CIV5D_DATA'!B:AS,13,FALSE) -> 0 | K85: =VLOOKUP($B85,'26MY_CIV5D_DATA'!$B:$AS,14,FALSE) -> 0 | L85: =VLOOKUP(B85,'26MY_CIV5D_DATA'!B:AS,15,FALSE) -> N/A | M85: =VLOOKUP(B85,'26MY_CIV5D_DATA'!B:AS,16,FALSE) -> N/A | N85: =VLOOKUP($B85,'26MY_CIV5D_DATA'!$B:$AS,17,FALSE) -> 0 | O85: =VLOOKUP(B85,'26MY_CIV5D_DATA'!B:AS,18,FALSE) -> N/A | P85: =VLOOKUP(B85,'26MY_CIV5D_DATA'!B:AS,19,FALSE) -> • | Q85: =IF(VLOOKUP(B85,'26MY_CIV5D_DATA'!B:AS,20,FALSE)="","",VLOOKUP(B85,'26MY_CIV5D_DATA'!B:AS,20,FALSE)) -> 1.6lbs lighter than standard. Red weaved Carbon Fiber.
B86: 08P34-T60-100 | C86: =VLOOKUP(B86,'26MY_CIV5D_DATA'!B:AS,3,FALSE) -> Car Cover - Type R | D86: =B86 -> 08P34-T60-100 | E86: =VLOOKUP(B86,'26MY_CIV5D_DATA'!B:AS,9,FALSE) -> 450 | F86: =VLOOKUP(B86,'26MY_CIV5D_DATA'!B:AS,10,FALSE) -> 750 | G86: =VLOOKUP(B86,'26MY_CIV5D_DATA'!B:AS,7,FALSE) -> 0 | H86: =VLOOKUP(B86,'26MY_CIV5D_DATA'!B:AS,11,FALSE) -> 750 | I86: =VLOOKUP(B86,'26MY_CIV5D_DATA'!B:AS,12,FALSE) -> 0 | J86: =VLOOKUP(B86,'26MY_CIV5D_DATA'!B:AS,13,FALSE) -> 0 | K86: =VLOOKUP($B86,'26MY_CIV5D_DATA'!$B:$AS,14,FALSE) -> 0 | L86: =VLOOKUP(B86,'26MY_CIV5D_DATA'!B:AS,15,FALSE) -> N/A | M86: =VLOOKUP(B86,'26MY_CIV5D_DATA'!B:AS,16,FALSE) -> N/A | N86: =VLOOKUP($B86,'26MY_CIV5D_DATA'!$B:$AS,17,FALSE) -> 0 | O86: =VLOOKUP(B86,'26MY_CIV5D_DATA'!B:AS,18,FALSE) -> N/A | P86: =VLOOKUP(B86,'26MY_CIV5D_DATA'!B:AS,19,FALSE) -> • | Q86: =IF(VLOOKUP(B86,'26MY_CIV5D_DATA'!B:AS,20,FALSE)="","",VLOOKUP(B86,'26MY_CIV5D_DATA'!B:AS,20,FALSE)) -> Suitable for both indoor and outdoor use.
B87: 08L02-T47-300 | C87: =VLOOKUP(B87,'26MY_CIV5D_DATA'!B:AS,3,FALSE) -> Roof Rack | D87: =B87 -> 08L02-T47-300 | E87: =VLOOKUP(B87,'26MY_CIV5D_DATA'!B:AS,9,FALSE) -> 498 | F87: =VLOOKUP(B87,'26MY_CIV5D_DATA'!B:AS,10,FALSE) -> 830 | G87: =VLOOKUP(B87,'26MY_CIV5D_DATA'!B:AS,7,FALSE) -> 0.4 | H87: =VLOOKUP(B87,'26MY_CIV5D_DATA'!B:AS,11,FALSE) -> 902.4 | I87: =VLOOKUP(B87,'26MY_CIV5D_DATA'!B:AS,12,FALSE) -> 0 | J87: =VLOOKUP(B87,'26MY_CIV5D_DATA'!B:AS,13,FALSE) -> 0 | K87: =VLOOKUP($B87,'26MY_CIV5D_DATA'!$B:$AS,14,FALSE) -> 0 | L87: =VLOOKUP(B87,'26MY_CIV5D_DATA'!B:AS,15,FALSE) -> • | M87: =VLOOKUP(B87,'26MY_CIV5D_DATA'!B:AS,16,FALSE) -> • | N87: =VLOOKUP($B87,'26MY_CIV5D_DATA'!$B:$AS,17,FALSE) -> 0 | O87: =VLOOKUP(B87,'26MY_CIV5D_DATA'!B:AS,18,FALSE) -> • | P87: =VLOOKUP(B87,'26MY_CIV5D_DATA'!B:AS,19,FALSE) -> • | Q87: =IF(VLOOKUP(B87,'26MY_CIV5D_DATA'!B:AS,20,FALSE)="","",VLOOKUP(B87,'26MY_CIV5D_DATA'!B:AS,20,FALSE))
B88: 08LXX-E09-XXXX | C88: =VLOOKUP(B88,'26MY_CIV5D_DATA'!B:AS,3,FALSE) -> Roof Attachments
B89: 08L20-E09-300A | C89: =VLOOKUP(B89,'26MY_CIV5D_DATA'!B:AS,3,FALSE) -> Roof Box - Midsize | D89: =B89 -> 08L20-E09-300A | E89: =VLOOKUP(B89,'26MY_CIV5D_DATA'!B:AS,9,FALSE) -> 898 | F89: =VLOOKUP(B89,'26MY_CIV5D_DATA'!B:AS,10,FALSE) -> 1497 | G89: =VLOOKUP(B89,'26MY_CIV5D_DATA'!B:AS,7,FALSE) -> 0.2 | H89: =VLOOKUP(B89,'26MY_CIV5D_DATA'!B:AS,11,FALSE) -> 1533.2 | I89: =VLOOKUP(B89,'26MY_CIV5D_DATA'!B:AS,12,FALSE) -> 0 | J89: =VLOOKUP(B89,'26MY_CIV5D_DATA'!B:AS,13,FALSE) -> 0 | K89: =VLOOKUP($B89,'26MY_CIV5D_DATA'!$B:$AS,14,FALSE) -> 0 | L89: =VLOOKUP(B89,'26MY_CIV5D_DATA'!B:AS,15,FALSE) -> • | M89: =VLOOKUP(B89,'26MY_CIV5D_DATA'!B:AS,16,FALSE) -> • | N89: =VLOOKUP($B89,'26MY_CIV5D_DATA'!$B:$AS,17,FALSE) -> 0 | O89: =VLOOKUP(B89,'26MY_CIV5D_DATA'!B:AS,18,FALSE) -> • | P89: =VLOOKUP(B89,'26MY_CIV5D_DATA'!B:AS,19,FALSE) -> • | Q89: =IF(VLOOKUP(B89,'26MY_CIV5D_DATA'!B:AS,20,FALSE)="","",VLOOKUP(B89,'26MY_CIV5D_DATA'!B:AS,20,FALSE))
B90: 08L20-E09-300B | C90: =VLOOKUP(B90,'26MY_CIV5D_DATA'!B:AS,3,FALSE) -> Roof Box - Short | D90: =B90 -> 08L20-E09-300B | E90: =VLOOKUP(B90,'26MY_CIV5D_DATA'!B:AS,9,FALSE) -> 820 | F90: =VLOOKUP(B90,'26MY_CIV5D_DATA'!B:AS,10,FALSE) -> 1367 | G90: =VLOOKUP(B90,'26MY_CIV5D_DATA'!B:AS,7,FALSE) -> 0.2 | H90: =VLOOKUP(B90,'26MY_CIV5D_DATA'!B:AS,11,FALSE) -> 1403.2 | I90: =VLOOKUP(B90,'26MY_CIV5D_DATA'!B:AS,12,FALSE) -> 0 | J90: =VLOOKUP(B90,'26MY_CIV5D_DATA'!B:AS,13,FALSE) -> 0 | K90: =VLOOKUP($B90,'26MY_CIV5D_DATA'!$B:$AS,14,FALSE) -> 0 | L90: =VLOOKUP(B90,'26MY_CIV5D_DATA'!B:AS,15,FALSE) -> • | M90: =VLOOKUP(B90,'26MY_CIV5D_DATA'!B:AS,16,FALSE) -> • | N90: =VLOOKUP($B90,'26MY_CIV5D_DATA'!$B:$AS,17,FALSE) -> 0 | O90: =VLOOKUP(B90,'26MY_CIV5D_DATA'!B:AS,18,FALSE) -> • | P90: =VLOOKUP(B90,'26MY_CIV5D_DATA'!B:AS,19,FALSE) -> • | Q90: =IF(VLOOKUP(B90,'26MY_CIV5D_DATA'!B:AS,20,FALSE)="","",VLOOKUP(B90,'26MY_CIV5D_DATA'!B:AS,20,FALSE))
B91: 08L09-E09-101 | C91: =VLOOKUP(B91,'26MY_CIV5D_DATA'!B:AS,3,FALSE) -> Roof Kayak Attachment | D91: =B91 -> 08L09-E09-101 | E91: =VLOOKUP(B91,'26MY_CIV5D_DATA'!B:AS,9,FALSE) -> 442 | F91: =VLOOKUP(B91,'26MY_CIV5D_DATA'!B:AS,10,FALSE) -> 737 | G91: =VLOOKUP(B91,'26MY_CIV5D_DATA'!B:AS,7,FALSE) -> 0.2 | H91: =VLOOKUP(B91,'26MY_CIV5D_DATA'!B:AS,11,FALSE) -> 773.2 | I91: =VLOOKUP(B91,'26MY_CIV5D_DATA'!B:AS,12,FALSE) -> 0 | J91: =VLOOKUP(B91,'26MY_CIV5D_DATA'!B:AS,13,FALSE) -> 0 | K91: =VLOOKUP($B91,'26MY_CIV5D_DATA'!$B:$AS,14,FALSE) -> 0 | L91: =VLOOKUP(B91,'26MY_CIV5D_DATA'!B:AS,15,FALSE) -> • | M91: =VLOOKUP(B91,'26MY_CIV5D_DATA'!B:AS,16,FALSE) -> • | N91: =VLOOKUP($B91,'26MY_CIV5D_DATA'!$B:$AS,17,FALSE) -> 0 | O91: =VLOOKUP(B91,'26MY_CIV5D_DATA'!B:AS,18,FALSE) -> • | P91: =VLOOKUP(B91,'26MY_CIV5D_DATA'!B:AS,19,FALSE) -> • | Q91: =IF(VLOOKUP(B91,'26MY_CIV5D_DATA'!B:AS,20,FALSE)="","",VLOOKUP(B91,'26MY_CIV5D_DATA'!B:AS,20,FALSE))
B92: 08L03-E09-300C | C92: =VLOOKUP(B92,'26MY_CIV5D_DATA'!B:AS,3,FALSE) -> Roof Ski/Snowboard Attachment | D92: =B92 -> 08L03-E09-300C | E92: =VLOOKUP(B92,'26MY_CIV5D_DATA'!B:AS,9,FALSE) -> 426 | F92: =VLOOKUP(B92,'26MY_CIV5D_DATA'!B:AS,10,FALSE) -> 710 | G92: =VLOOKUP(B92,'26MY_CIV5D_DATA'!B:AS,7,FALSE) -> 0.2 | H92: =VLOOKUP(B92,'26MY_CIV5D_DATA'!B:AS,11,FALSE) -> 746.2 | I92: =VLOOKUP(B92,'26MY_CIV5D_DATA'!B:AS,12,FALSE) -> 0 | J92: =VLOOKUP(B92,'26MY_CIV5D_DATA'!B:AS,13,FALSE) -> 0 | K92: =VLOOKUP($B92,'26MY_CIV5D_DATA'!$B:$AS,14,FALSE) -> 0 | L92: =VLOOKUP(B92,'26MY_CIV5D_DATA'!B:AS,15,FALSE) -> • | M92: =VLOOKUP(B92,'26MY_CIV5D_DATA'!B:AS,16,FALSE) -> • | N92: =VLOOKUP($B92,'26MY_CIV5D_DATA'!$B:$AS,17,FALSE) -> 0 | O92: =VLOOKUP(B92,'26MY_CIV5D_DATA'!B:AS,18,FALSE) -> • | P92: =VLOOKUP(B92,'26MY_CIV5D_DATA'!B:AS,19,FALSE) -> • | Q92: =IF(VLOOKUP(B92,'26MY_CIV5D_DATA'!B:AS,20,FALSE)="","",VLOOKUP(B92,'26MY_CIV5D_DATA'!B:AS,20,FALSE))
B93: 08L05-E09-100 | C93: =VLOOKUP(B93,'26MY_CIV5D_DATA'!B:AS,3,FALSE) -> Roof Surfboard Attachment | D93: =B93 -> 08L05-E09-100 | E93: =VLOOKUP(B93,'26MY_CIV5D_DATA'!B:AS,9,FALSE) -> 213 | F93: =VLOOKUP(B93,'26MY_CIV5D_DATA'!B:AS,10,FALSE) -> 355 | G93: =VLOOKUP(B93,'26MY_CIV5D_DATA'!B:AS,7,FALSE) -> 0.2 | H93: =VLOOKUP(B93,'26MY_CIV5D_DATA'!B:AS,11,FALSE) -> 391.2 | I93: =VLOOKUP(B93,'26MY_CIV5D_DATA'!B:AS,12,FALSE) -> 0 | J93: =VLOOKUP(B93,'26MY_CIV5D_DATA'!B:AS,13,FALSE) -> 0 | K93: =VLOOKUP($B93,'26MY_CIV5D_DATA'!$B:$AS,14,FALSE) -> 0 | L93: =VLOOKUP(B93,'26MY_CIV5D_DATA'!B:AS,15,FALSE) -> • | M93: =VLOOKUP(B93,'26MY_CIV5D_DATA'!B:AS,16,FALSE) -> • | N93: =VLOOKUP($B93,'26MY_CIV5D_DATA'!$B:$AS,17,FALSE) -> 0 | O93: =VLOOKUP(B93,'26MY_CIV5D_DATA'!B:AS,18,FALSE) -> • | P93: =VLOOKUP(B93,'26MY_CIV5D_DATA'!B:AS,19,FALSE) -> • | Q93: =IF(VLOOKUP(B93,'26MY_CIV5D_DATA'!B:AS,20,FALSE)="","",VLOOKUP(B93,'26MY_CIV5D_DATA'!B:AS,20,FALSE))
B94: 08L07-E09-101 | C94: =VLOOKUP(B94,'26MY_CIV5D_DATA'!B:AS,3,FALSE) -> Roof Bike Attachment - Frame Mount | D94: =B94 -> 08L07-E09-101 | E94: =VLOOKUP(B94,'26MY_CIV5D_DATA'!B:AS,9,FALSE) -> 393 | F94: =VLOOKUP(B94,'26MY_CIV5D_DATA'!B:AS,10,FALSE) -> 561 | G94: =VLOOKUP(B94,'26MY_CIV5D_DATA'!B:AS,7,FALSE) -> 0.6 | H94: =VLOOKUP(B94,'26MY_CIV5D_DATA'!B:AS,11,FALSE) -> 669.6 | I94: =VLOOKUP(B94,'26MY_CIV5D_DATA'!B:AS,12,FALSE) -> 0 | J94: =VLOOKUP(B94,'26MY_CIV5D_DATA'!B:AS,13,FALSE) -> 0 | K94: =VLOOKUP($B94,'26MY_CIV5D_DATA'!$B:$AS,14,FALSE) -> 0 | L94: =VLOOKUP(B94,'26MY_CIV5D_DATA'!B:AS,15,FALSE) -> • | M94: =VLOOKUP(B94,'26MY_CIV5D_DATA'!B:AS,16,FALSE) -> • | N94: =VLOOKUP($B94,'26MY_CIV5D_DATA'!$B:$AS,17,FALSE) -> 0 | O94: =VLOOKUP(B94,'26MY_CIV5D_DATA'!B:AS,18,FALSE) -> • | P94: =VLOOKUP(B94,'26MY_CIV5D_DATA'!B:AS,19,FALSE) -> • | Q94: =IF(VLOOKUP(B94,'26MY_CIV5D_DATA'!B:AS,20,FALSE)="","",VLOOKUP(B94,'26MY_CIV5D_DATA'!B:AS,20,FALSE)) -> Only one (1) bike attachment allowed on the Roof Rack. Roof Rack required.
B95: 08L20-E09-101C | C95: =VLOOKUP(B95,'26MY_CIV5D_DATA'!B:AS,3,FALSE) -> Roof Basket | D95: =B95 -> 08L20-E09-101C | E95: =VLOOKUP(B95,'26MY_CIV5D_DATA'!B:AS,9,FALSE) -> 586 | F95: =VLOOKUP(B95,'26MY_CIV5D_DATA'!B:AS,10,FALSE) -> 977 | G95: =VLOOKUP(B95,'26MY_CIV5D_DATA'!B:AS,7,FALSE) -> 0.4 | H95: =VLOOKUP(B95,'26MY_CIV5D_DATA'!B:AS,11,FALSE) -> 1049.4 | I95: =VLOOKUP(B95,'26MY_CIV5D_DATA'!B:AS,12,FALSE) -> 0 | J95: =VLOOKUP(B95,'26MY_CIV5D_DATA'!B:AS,13,FALSE) -> 0 | K95: =VLOOKUP($B95,'26MY_CIV5D_DATA'!$B:$AS,14,FALSE) -> 0 | L95: =VLOOKUP(B95,'26MY_CIV5D_DATA'!B:AS,15,FALSE) -> • | M95: =VLOOKUP(B95,'26MY_CIV5D_DATA'!B:AS,16,FALSE) -> • | N95: =VLOOKUP($B95,'26MY_CIV5D_DATA'!$B:$AS,17,FALSE) -> 0 | O95: =VLOOKUP(B95,'26MY_CIV5D_DATA'!B:AS,18,FALSE) -> • | P95: =VLOOKUP(B95,'26MY_CIV5D_DATA'!B:AS,19,FALSE) -> • | Q95: =IF(VLOOKUP(B95,'26MY_CIV5D_DATA'!B:AS,20,FALSE)="","",VLOOKUP(B95,'26MY_CIV5D_DATA'!B:AS,20,FALSE)) -> Roof Basket Attachment Kit (hardware) and Roof Rack required.
B96: 08L20-E09-100D | C96: =VLOOKUP(B96,'26MY_CIV5D_DATA'!B:AS,3,FALSE) -> Roof Basket Attachment Kit | D96: =B96 -> 08L20-E09-100D | E96: =VLOOKUP(B96,'26MY_CIV5D_DATA'!B:AS,9,FALSE) -> 17 | F96: =VLOOKUP(B96,'26MY_CIV5D_DATA'!B:AS,10,FALSE) -> 28 | G96: =VLOOKUP(B96,'26MY_CIV5D_DATA'!B:AS,7,FALSE) -> 0 | H96: =VLOOKUP(B96,'26MY_CIV5D_DATA'!B:AS,11,FALSE) -> 28 | I96: =VLOOKUP(B96,'26MY_CIV5D_DATA'!B:AS,12,FALSE) -> 0 | J96: =VLOOKUP(B96,'26MY_CIV5D_DATA'!B:AS,13,FALSE) -> 0 | K96: =VLOOKUP($B96,'26MY_CIV5D_DATA'!$B:$AS,14,FALSE) -> 0 | L96: =VLOOKUP(B96,'26MY_CIV5D_DATA'!B:AS,15,FALSE) -> • | M96: =VLOOKUP(B96,'26MY_CIV5D_DATA'!B:AS,16,FALSE) -> • | N96: =VLOOKUP($B96,'26MY_CIV5D_DATA'!$B:$AS,17,FALSE) -> 0 | O96: =VLOOKUP(B96,'26MY_CIV5D_DATA'!B:AS,18,FALSE) -> • | P96: =VLOOKUP(B96,'26MY_CIV5D_DATA'!B:AS,19,FALSE) -> •
B97: 08F01-T20-XXXX | C97: =VLOOKUP(B97,'26MY_CIV5D_DATA'!B:AS,3,FALSE) -> Front Underbody Spoiler
B98: 08F01-T20-130A | C98: =VLOOKUP(B98,'26MY_CIV5D_DATA'!B:AS,3,FALSE) -> Platinum White Pearl (NH-883P) | D98: =B98 -> 08F01-T20-130A | E98: =VLOOKUP(B98,'26MY_CIV5D_DATA'!B:AS,9,FALSE) -> 262 | F98: =VLOOKUP(B98,'26MY_CIV5D_DATA'!B:AS,10,FALSE) -> 437 | G98: =VLOOKUP(B98,'26MY_CIV5D_DATA'!B:AS,7,FALSE) -> 1 | H98: =VLOOKUP(B98,'26MY_CIV5D_DATA'!B:AS,11,FALSE) -> 618 | I98: =VLOOKUP(B98,'26MY_CIV5D_DATA'!B:AS,12,FALSE) -> 0 | J98: =VLOOKUP(B98,'26MY_CIV5D_DATA'!B:AS,13,FALSE) -> 0 | K98: =VLOOKUP($B98,'26MY_CIV5D_DATA'!$B:$AS,14,FALSE) -> 0 | L98: =VLOOKUP(B98,'26MY_CIV5D_DATA'!B:AS,15,FALSE) -> • | M98: =VLOOKUP(B98,'26MY_CIV5D_DATA'!B:AS,16,FALSE) -> • | N98: =VLOOKUP($B98,'26MY_CIV5D_DATA'!$B:$AS,17,FALSE) -> 0 | O98: =VLOOKUP(B98,'26MY_CIV5D_DATA'!B:AS,18,FALSE) -> • | P98: =VLOOKUP(B98,'26MY_CIV5D_DATA'!B:AS,19,FALSE) -> N/A | Q98: =IF(VLOOKUP(B98,'26MY_CIV5D_DATA'!B:AS,20,FALSE)="","",VLOOKUP(B98,'26MY_CIV5D_DATA'!B:AS,20,FALSE))
B99: 08F01-T20-1Z0A | C99: =VLOOKUP(B99,'26MY_CIV5D_DATA'!B:AS,3,FALSE) -> Solar Reflection Silver (NH-932M) | D99: =B99 -> 08F01-T20-1Z0A | E99: =VLOOKUP(B99,'26MY_CIV5D_DATA'!B:AS,9,FALSE) -> 262 | F99: =VLOOKUP(B99,'26MY_CIV5D_DATA'!B:AS,10,FALSE) -> 437 | G99: =VLOOKUP(B99,'26MY_CIV5D_DATA'!B:AS,7,FALSE) -> 1 | H99: =VLOOKUP(B99,'26MY_CIV5D_DATA'!B:AS,11,FALSE) -> 618 | I99: =VLOOKUP(B99,'26MY_CIV5D_DATA'!B:AS,12,FALSE) -> 0 | J99: =VLOOKUP(B99,'26MY_CIV5D_DATA'!B:AS,13,FALSE) -> 0 | K99: =VLOOKUP($B99,'26MY_CIV5D_DATA'!$B:$AS,14,FALSE) -> 0 | L99: =VLOOKUP(B99,'26MY_CIV5D_DATA'!B:AS,15,FALSE) -> • | M99: =VLOOKUP(B99,'26MY_CIV5D_DATA'!B:AS,16,FALSE) -> • | N99: =VLOOKUP($B99,'26MY_CIV5D_DATA'!$B:$AS,17,FALSE) -> 0 | O99: =VLOOKUP(B99,'26MY_CIV5D_DATA'!B:AS,18,FALSE) -> • | P99: =VLOOKUP(B99,'26MY_CIV5D_DATA'!B:AS,19,FALSE) -> N/A
B100: 08F01-T20-170A | C100: =VLOOKUP(B100,'26MY_CIV5D_DATA'!B:AS,3,FALSE) -> Meteoroid Gray Pearl (NH-904M) | D100: =B100 -> 08F01-T20-170A | E100: =VLOOKUP(B100,'26MY_CIV5D_DATA'!B:AS,9,FALSE) -> 262 | F100: =VLOOKUP(B100,'26MY_CIV5D_DATA'!B:AS,10,FALSE) -> 437 | G100: =VLOOKUP(B100,'26MY_CIV5D_DATA'!B:AS,7,FALSE) -> 1 | H100: =VLOOKUP(B100,'26MY_CIV5D_DATA'!B:AS,11,FALSE) -> 618 | I100: =VLOOKUP(B100,'26MY_CIV5D_DATA'!B:AS,12,FALSE) -> 0 | J100: =VLOOKUP(B100,'26MY_CIV5D_DATA'!B:AS,13,FALSE) -> 0 | K100: =VLOOKUP($B100,'26MY_CIV5D_DATA'!$B:$AS,14,FALSE) -> 0 | L100: =VLOOKUP(B100,'26MY_CIV5D_DATA'!B:AS,15,FALSE) -> N/A | M100: =VLOOKUP(B100,'26MY_CIV5D_DATA'!B:AS,16,FALSE) -> • | N100: =VLOOKUP($B100,'26MY_CIV5D_DATA'!$B:$AS,17,FALSE) -> 0 | O100: =VLOOKUP(B100,'26MY_CIV5D_DATA'!B:AS,18,FALSE) -> N/A | P100: =VLOOKUP(B100,'26MY_CIV5D_DATA'!B:AS,19,FALSE) -> N/A
B101: 08F01-T20-180A | C101: =VLOOKUP(B101,'26MY_CIV5D_DATA'!B:AS,3,FALSE) -> Crystal Black Pearl (NH-731P) | D101: =B101 -> 08F01-T20-180A | E101: =VLOOKUP(B101,'26MY_CIV5D_DATA'!B:AS,9,FALSE) -> 262 | F101: =VLOOKUP(B101,'26MY_CIV5D_DATA'!B:AS,10,FALSE) -> 437 | G101: =VLOOKUP(B101,'26MY_CIV5D_DATA'!B:AS,7,FALSE) -> 1 | H101: =VLOOKUP(B101,'26MY_CIV5D_DATA'!B:AS,11,FALSE) -> 618 | I101: =VLOOKUP(B101,'26MY_CIV5D_DATA'!B:AS,12,FALSE) -> 0 | J101: =VLOOKUP(B101,'26MY_CIV5D_DATA'!B:AS,13,FALSE) -> 0 | K101: =VLOOKUP($B101,'26MY_CIV5D_DATA'!$B:$AS,14,FALSE) -> 0 | L101: =VLOOKUP(B101,'26MY_CIV5D_DATA'!B:AS,15,FALSE) -> • | M101: =VLOOKUP(B101,'26MY_CIV5D_DATA'!B:AS,16,FALSE) -> • | N101: =VLOOKUP($B101,'26MY_CIV5D_DATA'!$B:$AS,17,FALSE) -> 0 | O101: =VLOOKUP(B101,'26MY_CIV5D_DATA'!B:AS,18,FALSE) -> • | P101: =VLOOKUP(B101,'26MY_CIV5D_DATA'!B:AS,19,FALSE) -> N/A
B102: 08F01-T20-190A | C102: =VLOOKUP(B102,'26MY_CIV5D_DATA'!B:AS,3,FALSE) -> Rallye Red (R-513) | D102: =B102 -> 08F01-T20-190A | E102: =VLOOKUP(B102,'26MY_CIV5D_DATA'!B:AS,9,FALSE) -> 262 | F102: =VLOOKUP(B102,'26MY_CIV5D_DATA'!B:AS,10,FALSE) -> 437 | G102: =VLOOKUP(B102,'26MY_CIV5D_DATA'!B:AS,7,FALSE) -> 1 | H102: =VLOOKUP(B102,'26MY_CIV5D_DATA'!B:AS,11,FALSE) -> 618 | I102: =VLOOKUP(B102,'26MY_CIV5D_DATA'!B:AS,12,FALSE) -> 0 | J102: =VLOOKUP(B102,'26MY_CIV5D_DATA'!B:AS,13,FALSE) -> 0 | K102: =VLOOKUP($B102,'26MY_CIV5D_DATA'!$B:$AS,14,FALSE) -> 0 | L102: =VLOOKUP(B102,'26MY_CIV5D_DATA'!B:AS,15,FALSE) -> N/A | M102: =VLOOKUP(B102,'26MY_CIV5D_DATA'!B:AS,16,FALSE) -> • | N102: =VLOOKUP($B102,'26MY_CIV5D_DATA'!$B:$AS,17,FALSE) -> 0 | O102: =VLOOKUP(B102,'26MY_CIV5D_DATA'!B:AS,18,FALSE) -> • | P102: =VLOOKUP(B102,'26MY_CIV5D_DATA'!B:AS,19,FALSE) -> N/A
B103: 08F01-T20-1U0A | C103: =VLOOKUP(B103,'26MY_CIV5D_DATA'!B:AS,3,FALSE) -> Boost Blue Pearl (B-637P) | D103: =B103 -> 08F01-T20-1U0A | E103: =VLOOKUP(B103,'26MY_CIV5D_DATA'!B:AS,9,FALSE) -> 262 | F103: =VLOOKUP(B103,'26MY_CIV5D_DATA'!B:AS,10,FALSE) -> 437 | G103: =VLOOKUP(B103,'26MY_CIV5D_DATA'!B:AS,7,FALSE) -> 1 | H103: =VLOOKUP(B103,'26MY_CIV5D_DATA'!B:AS,11,FALSE) -> 618 | I103: =VLOOKUP(B103,'26MY_CIV5D_DATA'!B:AS,12,FALSE) -> 0 | J103: =VLOOKUP(B103,'26MY_CIV5D_DATA'!B:AS,13,FALSE) -> 0 | K103: =VLOOKUP($B103,'26MY_CIV5D_DATA'!$B:$AS,14,FALSE) -> 0 | L103: =VLOOKUP(B103,'26MY_CIV5D_DATA'!B:AS,15,FALSE) -> N/A | M103: =VLOOKUP(B103,'26MY_CIV5D_DATA'!B:AS,16,FALSE) -> N/A | N103: =VLOOKUP($B103,'26MY_CIV5D_DATA'!$B:$AS,17,FALSE) -> 0 | O103: =VLOOKUP(B103,'26MY_CIV5D_DATA'!B:AS,18,FALSE) -> • | P103: =VLOOKUP(B103,'26MY_CIV5D_DATA'!B:AS,19,FALSE) -> N/A
B104: 08F02-T47-XXX | C104: =VLOOKUP(B104,'26MY_CIV5D_DATA'!B:AS,3,FALSE) -> Tailgate Spoiler, HPD
B105: 08F02-T47-130 | C105: =VLOOKUP(B105,'26MY_CIV5D_DATA'!B:AS,3,FALSE) -> Platinum White Pearl (NH-883P) | D105: =B105 -> 08F02-T47-130 | E105: =VLOOKUP(B105,'26MY_CIV5D_DATA'!B:AS,9,FALSE) -> 472 | F105: =VLOOKUP(B105,'26MY_CIV5D_DATA'!B:AS,10,FALSE) -> 787 | G105: =VLOOKUP(B105,'26MY_CIV5D_DATA'!B:AS,7,FALSE) -> 1.2 | H105: =VLOOKUP(B105,'26MY_CIV5D_DATA'!B:AS,11,FALSE) -> 1004.2 | I105: =VLOOKUP(B105,'26MY_CIV5D_DATA'!B:AS,12,FALSE) -> 0 | J105: =VLOOKUP(B105,'26MY_CIV5D_DATA'!B:AS,13,FALSE) -> 0 | K105: =VLOOKUP($B105,'26MY_CIV5D_DATA'!$B:$AS,14,FALSE) -> 0 | L105: =VLOOKUP(B105,'26MY_CIV5D_DATA'!B:AS,15,FALSE) -> • | M105: =VLOOKUP(B105,'26MY_CIV5D_DATA'!B:AS,16,FALSE) -> • | N105: =VLOOKUP($B105,'26MY_CIV5D_DATA'!$B:$AS,17,FALSE) -> 0 | O105: =VLOOKUP(B105,'26MY_CIV5D_DATA'!B:AS,18,FALSE) -> • | P105: =VLOOKUP(B105,'26MY_CIV5D_DATA'!B:AS,19,FALSE) -> N/A | Q105: =IF(VLOOKUP(B105,'26MY_CIV5D_DATA'!B:AS,20,FALSE)="","",VLOOKUP(B105,'26MY_CIV5D_DATA'!B:AS,20,FALSE))
B106: 08F02-T47-1Z0 | C106: =VLOOKUP(B106,'26MY_CIV5D_DATA'!B:AS,3,FALSE) -> Solar Reflection Silver (NH-932M) | D106: =B106 -> 08F02-T47-1Z0 | E106: =VLOOKUP(B106,'26MY_CIV5D_DATA'!B:AS,9,FALSE) -> 472 | F106: =VLOOKUP(B106,'26MY_CIV5D_DATA'!B:AS,10,FALSE) -> 787 | G106: =VLOOKUP(B106,'26MY_CIV5D_DATA'!B:AS,7,FALSE) -> 1.2 | H106: =VLOOKUP(B106,'26MY_CIV5D_DATA'!B:AS,11,FALSE) -> 1004.2 | I106: =VLOOKUP(B106,'26MY_CIV5D_DATA'!B:AS,12,FALSE) -> 0 | J106: =VLOOKUP(B106,'26MY_CIV5D_DATA'!B:AS,13,FALSE) -> 0 | K106: =VLOOKUP($B106,'26MY_CIV5D_DATA'!$B:$AS,14,FALSE) -> 0 | L106: =VLOOKUP(B106,'26MY_CIV5D_DATA'!B:AS,15,FALSE) -> • | M106: =VLOOKUP(B106,'26MY_CIV5D_DATA'!B:AS,16,FALSE) -> N/A | N106: =VLOOKUP($B106,'26MY_CIV5D_DATA'!$B:$AS,17,FALSE) -> 0 | O106: =VLOOKUP(B106,'26MY_CIV5D_DATA'!B:AS,18,FALSE) -> N/A | P106: =VLOOKUP(B106,'26MY_CIV5D_DATA'!B:AS,19,FALSE) -> N/A
B107: 08F02-T47-170 | C107: =VLOOKUP(B107,'26MY_CIV5D_DATA'!B:AS,3,FALSE) -> Meteriod Gray Pearl (NH-904M) | D107: =B107 -> 08F02-T47-170 | E107: =VLOOKUP(B107,'26MY_CIV5D_DATA'!B:AS,9,FALSE) -> 472 | F107: =VLOOKUP(B107,'26MY_CIV5D_DATA'!B:AS,10,FALSE) -> 787 | G107: =VLOOKUP(B107,'26MY_CIV5D_DATA'!B:AS,7,FALSE) -> 1.2 | H107: =VLOOKUP(B107,'26MY_CIV5D_DATA'!B:AS,11,FALSE) -> 1004.2 | I107: =VLOOKUP(B107,'26MY_CIV5D_DATA'!B:AS,12,FALSE) -> 0 | J107: =VLOOKUP(B107,'26MY_CIV5D_DATA'!B:AS,13,FALSE) -> 0 | K107: =VLOOKUP($B107,'26MY_CIV5D_DATA'!$B:$AS,14,FALSE) -> 0 | L107: =VLOOKUP(B107,'26MY_CIV5D_DATA'!B:AS,15,FALSE) -> N/A | M107: =VLOOKUP(B107,'26MY_CIV5D_DATA'!B:AS,16,FALSE) -> • | N107: =VLOOKUP($B107,'26MY_CIV5D_DATA'!$B:$AS,17,FALSE) -> 0 | O107: =VLOOKUP(B107,'26MY_CIV5D_DATA'!B:AS,18,FALSE) -> N/A | P107: =VLOOKUP(B107,'26MY_CIV5D_DATA'!B:AS,19,FALSE) -> N/A
B108: 08F02-T47-180 | C108: =VLOOKUP(B108,'26MY_CIV5D_DATA'!B:AS,3,FALSE) -> Crystal Black Pearl (NH-731P) | D108: =B108 -> 08F02-T47-180 | E108: =VLOOKUP(B108,'26MY_CIV5D_DATA'!B:AS,9,FALSE) -> 472 | F108: =VLOOKUP(B108,'26MY_CIV5D_DATA'!B:AS,10,FALSE) -> 787 | G108: =VLOOKUP(B108,'26MY_CIV5D_DATA'!B:AS,7,FALSE) -> 1.2 | H108: =VLOOKUP(B108,'26MY_CIV5D_DATA'!B:AS,11,FALSE) -> 1004.2 | I108: =VLOOKUP(B108,'26MY_CIV5D_DATA'!B:AS,12,FALSE) -> 0 | J108: =VLOOKUP(B108,'26MY_CIV5D_DATA'!B:AS,13,FALSE) -> 0 | K108: =VLOOKUP($B108,'26MY_CIV5D_DATA'!$B:$AS,14,FALSE) -> 0 | L108: =VLOOKUP(B108,'26MY_CIV5D_DATA'!B:AS,15,FALSE) -> • | M108: =VLOOKUP(B108,'26MY_CIV5D_DATA'!B:AS,16,FALSE) -> • | N108: =VLOOKUP($B108,'26MY_CIV5D_DATA'!$B:$AS,17,FALSE) -> 0 | O108: =VLOOKUP(B108,'26MY_CIV5D_DATA'!B:AS,18,FALSE) -> • | P108: =VLOOKUP(B108,'26MY_CIV5D_DATA'!B:AS,19,FALSE) -> N/A
B109: 08F02-T47-190 | C109: =VLOOKUP(B109,'26MY_CIV5D_DATA'!B:AS,3,FALSE) -> Rallye Red (R-513) | D109: =B109 -> 08F02-T47-190 | E109: =VLOOKUP(B109,'26MY_CIV5D_DATA'!B:AS,9,FALSE) -> 472 | F109: =VLOOKUP(B109,'26MY_CIV5D_DATA'!B:AS,10,FALSE) -> 787 | G109: =VLOOKUP(B109,'26MY_CIV5D_DATA'!B:AS,7,FALSE) -> 1.2 | H109: =VLOOKUP(B109,'26MY_CIV5D_DATA'!B:AS,11,FALSE) -> 1004.2 | I109: =VLOOKUP(B109,'26MY_CIV5D_DATA'!B:AS,12,FALSE) -> 0 | J109: =VLOOKUP(B109,'26MY_CIV5D_DATA'!B:AS,13,FALSE) -> 0 | K109: =VLOOKUP($B109,'26MY_CIV5D_DATA'!$B:$AS,14,FALSE) -> 0 | L109: =VLOOKUP(B109,'26MY_CIV5D_DATA'!B:AS,15,FALSE) -> N/A | M109: =VLOOKUP(B109,'26MY_CIV5D_DATA'!B:AS,16,FALSE) -> • | N109: =VLOOKUP($B109,'26MY_CIV5D_DATA'!$B:$AS,17,FALSE) -> 0 | O109: =VLOOKUP(B109,'26MY_CIV5D_DATA'!B:AS,18,FALSE) -> • | P109: =VLOOKUP(B109,'26MY_CIV5D_DATA'!B:AS,19,FALSE) -> N/A
B110: 08F02-T47-1U0 | C110: =VLOOKUP(B110,'26MY_CIV5D_DATA'!B:AS,3,FALSE) -> Boost Blue Pearl (B-637P) | D110: =B110 -> 08F02-T47-1U0 | E110: =VLOOKUP(B110,'26MY_CIV5D_DATA'!B:AS,9,FALSE) -> 472 | F110: =VLOOKUP(B110,'26MY_CIV5D_DATA'!B:AS,10,FALSE) -> 787 | G110: =VLOOKUP(B110,'26MY_CIV5D_DATA'!B:AS,7,FALSE) -> 1.2 | H110: =VLOOKUP(B110,'26MY_CIV5D_DATA'!B:AS,11,FALSE) -> 1004.2 | I110: =VLOOKUP(B110,'26MY_CIV5D_DATA'!B:AS,12,FALSE) -> 0 | J110: =VLOOKUP(B110,'26MY_CIV5D_DATA'!B:AS,13,FALSE) -> 0 | K110: =VLOOKUP($B110,'26MY_CIV5D_DATA'!$B:$AS,14,FALSE) -> 0 | L110: =VLOOKUP(B110,'26MY_CIV5D_DATA'!B:AS,15,FALSE) -> N/A | M110: =VLOOKUP(B110,'26MY_CIV5D_DATA'!B:AS,16,FALSE) -> N/A | N110: =VLOOKUP($B110,'26MY_CIV5D_DATA'!$B:$AS,17,FALSE) -> 0 | O110: =VLOOKUP(B110,'26MY_CIV5D_DATA'!B:AS,18,FALSE) -> • | P110: =VLOOKUP(B110,'26MY_CIV5D_DATA'!B:AS,19,FALSE) -> N/A
B111: 08P05-T20-XXXX | C111: =VLOOKUP(B111,'26MY_CIV5D_DATA'!B:AS,3,FALSE) -> Body Side Moulding
B112: 08P05-T20-130 | C112: =VLOOKUP(B112,'26MY_CIV5D_DATA'!B:AS,3,FALSE) -> Platinum White Pearl (NH-883P) | D112: =B112 -> 08P05-T20-130 | E112: =VLOOKUP(B112,'26MY_CIV5D_DATA'!B:AS,9,FALSE) -> 215 | F112: =VLOOKUP(B112,'26MY_CIV5D_DATA'!B:AS,10,FALSE) -> 358 | G112: =VLOOKUP(B112,'26MY_CIV5D_DATA'!B:AS,7,FALSE) -> 0.4 | H112: =VLOOKUP(B112,'26MY_CIV5D_DATA'!B:AS,11,FALSE) -> 430.4 | I112: =VLOOKUP(B112,'26MY_CIV5D_DATA'!B:AS,12,FALSE) -> 0 | J112: =VLOOKUP(B112,'26MY_CIV5D_DATA'!B:AS,13,FALSE) -> 0 | K112: =VLOOKUP($B112,'26MY_CIV5D_DATA'!$B:$AS,14,FALSE) -> 0 | L112: =VLOOKUP(B112,'26MY_CIV5D_DATA'!B:AS,15,FALSE) -> • | M112: =VLOOKUP(B112,'26MY_CIV5D_DATA'!B:AS,16,FALSE) -> • | N112: =VLOOKUP($B112,'26MY_CIV5D_DATA'!$B:$AS,17,FALSE) -> 0 | O112: =VLOOKUP(B112,'26MY_CIV5D_DATA'!B:AS,18,FALSE) -> • | P112: =VLOOKUP(B112,'26MY_CIV5D_DATA'!B:AS,19,FALSE) -> N/A | Q112: =IF(VLOOKUP(B112,'26MY_CIV5D_DATA'!B:AS,20,FALSE)="","",VLOOKUP(B112,'26MY_CIV5D_DATA'!B:AS,20,FALSE))
...

Sheet 26MY_CIV5D_APP_FR
B2: Honda Internal | C2: Accessoires Honda
C3: Nom du modèle | D3: ='26MY_CIV5D_DATA'!$D$2 -> Civic à Hayon & Type R
C4: Année modèle | D4: ='26MY_CIV5D_DATA'!$C$3 -> 2026
C5: S = De série (accessoire de série sur cette version).
C6: T = Taille des pneus (la taille de la jante accessoire diffère de la jante d’origine. Le client aura besoin de nouveaux pneus pour ces jantes).
C7: E = Échange d’équipement de série (la taille de la jante accessoire est la même que celle de la jante d’origine. Le client peut utiliser les pneus d’origine).
C8: N/A = Sans objet (l’accessoire ne peut être utilisé pour cette version).
H10: Province
C11: 1.0 Groupes et ensembles | H11: =prov_cd -> YT
C12: La description | D12: Numéro de pièce | E12: Prix net | F12: Prix de liste | G12: T.F.F. | H12: Prix installé | I12: Application | Q12: Commentaires
I13: ='26MY_CIV5D_DATA'!M$6 -> 0 | J13: ='26MY_CIV5D_DATA'!N$6 -> 0 | K13: ='26MY_CIV5D_DATA'!O$6 -> 0 | L13: ='26MY_CIV5D_DATA'!P$6 -> SPORT | M13: ='26MY_CIV5D_DATA'!Q$6 -> SPORT Hybride | N13: ='26MY_CIV5D_DATA'!R$6 -> 0 | O13: ='26MY_CIV5D_DATA'!S$6 -> Sport Touring Hybride | P13: ='26MY_CIV5D_DATA'!T$6 -> Type R
B14: 26TYPER-RACE | C14: =VLOOKUP(B14,'26MY_CIV5D_DATA'!B:AS,4,FALSE) -> Ensemble de course – Type R | D14: =B14 -> 26TYPER-RACE | E14: =VLOOKUP(B14,'26MY_CIV5D_DATA'!B:AS,9,FALSE) -> 3928 | F14: =VLOOKUP(B14,'26MY_CIV5D_DATA'!B:AS,10,FALSE) -> 6431 | G14: =VLOOKUP(B14,'26MY_CIV5D_DATA'!B:AS,7,FALSE) -> 1 | H14: =VLOOKUP(B14,'26MY_CIV5D_DATA'!B:AS,11,FALSE) -> 6612 | I14: =VLOOKUP(B14,'26MY_CIV5D_DATA'!B:AS,12,FALSE) -> 0 | J14: =VLOOKUP(B14,'26MY_CIV5D_DATA'!B:AS,13,FALSE) -> 0 | K14: =VLOOKUP($B14,'26MY_CIV5D_DATA'!$B:$AS,14,FALSE) -> 0 | L14: =VLOOKUP(B14,'26MY_CIV5D_DATA'!B:AS,15,FALSE) -> N/A | M14: =VLOOKUP(B14,'26MY_CIV5D_DATA'!B:AS,16,FALSE) -> N/A | N14: =VLOOKUP($B14,'26MY_CIV5D_DATA'!$B:$AS,17,FALSE) -> 0 | O14: =VLOOKUP(B14,'26MY_CIV5D_DATA'!B:AS,18,FALSE) -> N/A | P14: =VLOOKUP(B14,'26MY_CIV5D_DATA'!B:AS,19,FALSE) -> • | Q14: =IF(VLOOKUP(B14,'26MY_CIV5D_DATA'!B:AS,21,FALSE)="","",VLOOKUP(B14,'26MY_CIV5D_DATA'!B:AS,21,FALSE))
B15: 08F02-T60-100 | C15: =VLOOKUP(B15,'26MY_CIV5D_DATA'!B:AS,4,FALSE) -> Becquet de hayon en fibre de carbone - Type R | D15: =B15 -> 08F02-T60-100
B16: 08U97-T60-110 | C16: =VLOOKUP(B16,'26MY_CIV5D_DATA'!B:AS,4,FALSE) -> Volant en Alcantara pour Type R | D16: =B16 -> 08U97-T60-110
B17: 08U92-T60-110 | C17: =VLOOKUP(B17,'26MY_CIV5D_DATA'!B:AS,4,FALSE) -> Pommeau de levier de vitesse gainé de cuir rouge | D17: =B17 -> 08U92-T60-110
B19: 25CIV-ENK-WTPK | C19: =VLOOKUP(B19,'26MY_CIV5D_DATA'!B:AS,4,FALSE) -> Ensemble de roues Enkei M52 de 16 po et de pneus Michelin X-ICE Snow | E19: =VLOOKUP(B19,'26MY_CIV5D_DATA'!B:AS,9,FALSE) -> 1596.56 | F19: =VLOOKUP(B19,'26MY_CIV5D_DATA'!B:AS,10,FALSE) -> 2028 | G19: =VLOOKUP(B19,'26MY_CIV5D_DATA'!B:AS,7,FALSE) -> 1.2 | H19: =VLOOKUP(B19,'26MY_CIV5D_DATA'!B:AS,11,FALSE) -> 2245.2 | I19: =VLOOKUP(B19,'26MY_CIV5D_DATA'!B:AS,12,FALSE) -> 0 | J19: =VLOOKUP(B19,'26MY_CIV5D_DATA'!B:AS,13,FALSE) -> 0 | K19: =VLOOKUP($B19,'26MY_CIV5D_DATA'!$B:$AS,14,FALSE) -> 0 | L19: =VLOOKUP(B19,'26MY_CIV5D_DATA'!B:AS,15,FALSE) -> • | M19: =VLOOKUP(B19,'26MY_CIV5D_DATA'!B:AS,16,FALSE) -> N/A | N19: =VLOOKUP($B19,'26MY_CIV5D_DATA'!$B:$AS,17,FALSE) -> 0 | O19: =VLOOKUP(B19,'26MY_CIV5D_DATA'!B:AS,18,FALSE) -> N/A | P19: =VLOOKUP(B19,'26MY_CIV5D_DATA'!B:AS,19,FALSE) -> N/A | Q19: =IF(VLOOKUP(B19,'26MY_CIV5D_DATA'!B:AS,21,FALSE)="","",VLOOKUP(B19,'26MY_CIV5D_DATA'!B:AS,21,FALSE)) -> Prix établi pour ensemble de 4 pneus.
B20: 480-670-6545-SP ou 480-670-6545-GB | C20: =VLOOKUP(B20,'26MY_CIV5D_DATA'!B:AS,4,FALSE) -> Roues Enkei M52 de 16 po - argent ou noir brillant | D20: =B20 -> 480-670-6545-SP ou 480-670-6545-GB
B21: 34417 | C21: =VLOOKUP(B21,'26MY_CIV5D_DATA'!B:AS,4,FALSE) -> Pneus Michelin X-ICE Snow - 215/55/16 | D21: =B21 -> 34417
B23: 25CIV-STL-WTPK | C23: =VLOOKUP(B23,'26MY_CIV5D_DATA'!B:AS,4,FALSE) -> Ensemble de roues d’hiver de 16 po en acier et de pneus Michelin X-ICE Snow | E23: =VLOOKUP(B23,'26MY_CIV5D_DATA'!B:AS,9,FALSE) -> 1150.4 | F23: =VLOOKUP(B23,'26MY_CIV5D_DATA'!B:AS,10,FALSE) -> 1522.72 | G23: =VLOOKUP(B23,'26MY_CIV5D_DATA'!B:AS,7,FALSE) -> 1.2 | H23: =VLOOKUP(B23,'26MY_CIV5D_DATA'!B:AS,11,FALSE) -> 1739.92 | I23: =VLOOKUP(B23,'26MY_CIV5D_DATA'!B:AS,12,FALSE) -> 0 | J23: =VLOOKUP(B23,'26MY_CIV5D_DATA'!B:AS,13,FALSE) -> 0 | K23: =VLOOKUP($B23,'26MY_CIV5D_DATA'!$B:$AS,14,FALSE) -> 0 | L23: =VLOOKUP(B23,'26MY_CIV5D_DATA'!B:AS,15,FALSE) -> • | M23: =VLOOKUP(B23,'26MY_CIV5D_DATA'!B:AS,16,FALSE) -> N/A | N23: =VLOOKUP($B23,'26MY_CIV5D_DATA'!$B:$AS,17,FALSE) -> 0 | O23: =VLOOKUP(B23,'26MY_CIV5D_DATA'!B:AS,18,FALSE) -> N/A | P23: =VLOOKUP(B23,'26MY_CIV5D_DATA'!B:AS,19,FALSE) -> N/A | Q23: =IF(VLOOKUP(B23,'26MY_CIV5D_DATA'!B:AS,21,FALSE)="","",VLOOKUP(B23,'26MY_CIV5D_DATA'!B:AS,21,FALSE)) -> Prix établi pour ensemble de 4 pneus.
B24: 42700-TBA-A12 | C24: =VLOOKUP(B24,'26MY_CIV5D_DATA'!B:AS,4,FALSE) -> Roues d’hiver de 16 po en acier | D24: =B24 -> 42700-TBA-A12
B25: 34417 | C25: =VLOOKUP(B25,'26MY_CIV5D_DATA'!B:AS,4,FALSE) -> Pneus Michelin X-ICE Snow - 215/55/16 | D25: =B25 -> 34417
B27: 25CIV5-ARO-PK | C27: =VLOOKUP(B27,'26MY_CIV5D_DATA'!B:AS,4,FALSE) -> Ensemble Aero | E27: =VLOOKUP(B27,'26MY_CIV5D_DATA'!B:AS,9,FALSE) -> 660.6 | F27: =VLOOKUP(B27,'26MY_CIV5D_DATA'!B:AS,10,FALSE) -> 1101.6 | G27: =VLOOKUP(B27,'26MY_CIV5D_DATA'!B:AS,7,FALSE) -> 2.2 | H27: =VLOOKUP(B27,'26MY_CIV5D_DATA'!B:AS,11,FALSE) -> 1499.8 | I27: =VLOOKUP(B27,'26MY_CIV5D_DATA'!B:AS,12,FALSE) -> 0 | J27: =VLOOKUP(B27,'26MY_CIV5D_DATA'!B:AS,13,FALSE) -> 0 | K27: =VLOOKUP($B27,'26MY_CIV5D_DATA'!$B:$AS,14,FALSE) -> 0 | L27: =VLOOKUP(B27,'26MY_CIV5D_DATA'!B:AS,15,FALSE) -> • | M27: =VLOOKUP(B27,'26MY_CIV5D_DATA'!B:AS,16,FALSE) -> • | N27: =VLOOKUP($B27,'26MY_CIV5D_DATA'!$B:$AS,17,FALSE) -> 0 | O27: =VLOOKUP(B27,'26MY_CIV5D_DATA'!B:AS,18,FALSE) -> • | P27: =VLOOKUP(B27,'26MY_CIV5D_DATA'!B:AS,19,FALSE) -> N/A | Q27: =IF(VLOOKUP(B27,'26MY_CIV5D_DATA'!B:AS,21,FALSE)="","",VLOOKUP(B27,'26MY_CIV5D_DATA'!B:AS,21,FALSE)) -> Rabais de 10 % appliqué. Comprend déflecteur de bas de caisse avant de la couleur de la carrosserie et un becquet de hayon.
B28: 25CIV-5AR-NH883 | C28: =VLOOKUP(B28,'26MY_CIV5D_DATA'!B:AS,4,FALSE) -> Blanc platine nacré (NH-883P) | D28: =B28 -> 25CIV-5AR-NH883
B29: 25CIV-5AR-NH932 | C29: =VLOOKUP(B29,'26MY_CIV5D_DATA'!B:AS,4,FALSE) -> Refl et solaire argent métallisé (NH-932M) | D29: =B29 -> 25CIV-5AR-NH932
B30: 25CIV-5AR-NH904 | C30: =VLOOKUP(B30,'26MY_CIV5D_DATA'!B:AS,4,FALSE) -> Gris météore nacré (NH-904M) | D30: =B30 -> 25CIV-5AR-NH904
B31: 25CIV-5AR-NH912 | C31: =VLOOKUP(B31,'26MY_CIV5D_DATA'!B:AS,4,FALSE) -> Gris urbain nacré (NH-912P) | D31: =B31 -> 25CIV-5AR-NH912
B32: 25CIV-5AR-NH731 | C32: =VLOOKUP(B32,'26MY_CIV5D_DATA'!B:AS,4,FALSE) -> Noir cristal nacré (NH-731P) | D32: =B32 -> 25CIV-5AR-NH731
B33: 25CIV-5AR-R513 | C33: =VLOOKUP(B33,'26MY_CIV5D_DATA'!B:AS,4,FALSE) -> Rouge rallye (R-513) | D33: =B33 -> 25CIV-5AR-R513
B34: 25CIV-5AR-B637 | C34: =VLOOKUP(B34,'26MY_CIV5D_DATA'!B:AS,4,FALSE) -> Bleu turbo nacré (B-637P) | D34: =B34 -> 25CIV-5AR-B637
B36: 22CIV-COLD-PK20 | C36: =VLOOKUP(B36,'26MY_CIV5D_DATA'!B:AS,4,FALSE) -> Ensemble de temps froid - 2,0 L | D36: =B36 -> 22CIV-COLD-PK20 | E36: =VLOOKUP(B36,'26MY_CIV5D_DATA'!B:AS,9,FALSE) -> 230.85 | F36: =VLOOKUP(B36,'26MY_CIV5D_DATA'!B:AS,10,FALSE) -> 384.75 | G36: =VLOOKUP(B36,'26MY_CIV5D_DATA'!B:AS,7,FALSE) -> 1.4 | H36: =VLOOKUP(B36,'26MY_CIV5D_DATA'!B:AS,11,FALSE) -> 638.15 | I36: =VLOOKUP(B36,'26MY_CIV5D_DATA'!B:AS,12,FALSE) -> 0 | J36: =VLOOKUP(B36,'26MY_CIV5D_DATA'!B:AS,13,FALSE) -> 0 | K36: =VLOOKUP($B36,'26MY_CIV5D_DATA'!$B:$AS,14,FALSE) -> 0 | L36: =VLOOKUP(B36,'26MY_CIV5D_DATA'!B:AS,15,FALSE) -> • | M36: =VLOOKUP(B36,'26MY_CIV5D_DATA'!B:AS,16,FALSE) -> • | N36: =VLOOKUP($B36,'26MY_CIV5D_DATA'!$B:$AS,17,FALSE) -> 0 | O36: =VLOOKUP(B36,'26MY_CIV5D_DATA'!B:AS,18,FALSE) -> • | P36: =VLOOKUP(B36,'26MY_CIV5D_DATA'!B:AS,19,FALSE) -> N/A | Q36: =IF(VLOOKUP(B36,'26MY_CIV5D_DATA'!B:AS,21,FALSE)="","",VLOOKUP(B36,'26MY_CIV5D_DATA'!B:AS,21,FALSE)) -> Rabais de 5 % appliqué.
B37: 08T44-SNA-302 | C37: =VLOOKUP(B37,'26MY_CIV5D_DATA'!B:AS,4,FALSE) -> Chauffe-moteur - 2,0 L | D37: =B37 -> 08T44-SNA-302
B38: 31670-BMS-004H | C38: =VLOOKUP(B38,'26MY_CIV5D_DATA'!B:AS,4,FALSE) -> Chargeur/mainteneur de batterie automobile 12 V Optimate | D38: =B38 -> 31670-BMS-004H
B40: 22CIV-COLD-PK20 | C40: =VLOOKUP(B40,'26MY_CIV5D_DATA'!B:AS,4,FALSE) -> Ensemble de temps froid - 2,0 L | D40: =B40 -> 22CIV-COLD-PK20 | E40: =VLOOKUP(B40,'26MY_CIV5D_DATA'!B:AS,9,FALSE) -> 230.85 | F40: =VLOOKUP(B40,'26MY_CIV5D_DATA'!B:AS,10,FALSE) -> 384.75 | G40: =VLOOKUP(B40,'26MY_CIV5D_DATA'!B:AS,7,FALSE) -> 1.4 | H40: =VLOOKUP(B40,'26MY_CIV5D_DATA'!B:AS,11,FALSE) -> 638.15 | I40: =VLOOKUP(B40,'26MY_CIV5D_DATA'!B:AS,12,FALSE) -> 0 | J40: =VLOOKUP(B40,'26MY_CIV5D_DATA'!B:AS,13,FALSE) -> 0 | K40: =VLOOKUP($B40,'26MY_CIV5D_DATA'!$B:$AS,14,FALSE) -> 0 | L40: =VLOOKUP(B40,'26MY_CIV5D_DATA'!B:AS,15,FALSE) -> • | M40: =VLOOKUP(B40,'26MY_CIV5D_DATA'!B:AS,16,FALSE) -> • | N40: =VLOOKUP($B40,'26MY_CIV5D_DATA'!$B:$AS,17,FALSE) -> 0 | O40: =VLOOKUP(B40,'26MY_CIV5D_DATA'!B:AS,18,FALSE) -> • | P40: =VLOOKUP(B40,'26MY_CIV5D_DATA'!B:AS,19,FALSE) -> N/A | Q40: =IF(VLOOKUP(B40,'26MY_CIV5D_DATA'!B:AS,21,FALSE)="","",VLOOKUP(B40,'26MY_CIV5D_DATA'!B:AS,21,FALSE)) -> Rabais de 5 % appliqué.
B41: 08T44-SNA-302 | C41: =VLOOKUP(B41,'26MY_CIV5D_DATA'!B:AS,4,FALSE) -> Chauffe-moteur - 2,0 L | D41: =B41 -> 08T44-SNA-302
B42: 31670-BMS-004H | C42: =VLOOKUP(B42,'26MY_CIV5D_DATA'!B:AS,4,FALSE) -> Chargeur/mainteneur de batterie automobile 12 V Optimate | D42: =B42 -> 31670-BMS-004H
B44: 23CIV-COLD-TR | C44: =VLOOKUP(B44,'26MY_CIV5D_DATA'!B:AS,4,FALSE) -> Ensemble de temps froid - Type R | D44: =B44 -> 23CIV-COLD-TR | E44: =VLOOKUP(B44,'26MY_CIV5D_DATA'!B:AS,9,FALSE) -> 278.35 | F44: =VLOOKUP(B44,'26MY_CIV5D_DATA'!B:AS,10,FALSE) -> 464.55 | G44: =VLOOKUP(B44,'26MY_CIV5D_DATA'!B:AS,7,FALSE) -> 1.4 | H44: =VLOOKUP(B44,'26MY_CIV5D_DATA'!B:AS,11,FALSE) -> 717.95 | I44: =VLOOKUP(B44,'26MY_CIV5D_DATA'!B:AS,12,FALSE) -> 0 | J44: =VLOOKUP(B44,'26MY_CIV5D_DATA'!B:AS,13,FALSE) -> 0 | K44: =VLOOKUP($B44,'26MY_CIV5D_DATA'!$B:$AS,14,FALSE) -> 0 | L44: =VLOOKUP(B44,'26MY_CIV5D_DATA'!B:AS,15,FALSE) -> N/A | M44: =VLOOKUP(B44,'26MY_CIV5D_DATA'!B:AS,16,FALSE) -> N/A | N44: =VLOOKUP($B44,'26MY_CIV5D_DATA'!$B:$AS,17,FALSE) -> 0 | O44: =VLOOKUP(B44,'26MY_CIV5D_DATA'!B:AS,18,FALSE) -> N/A | P44: =VLOOKUP(B44,'26MY_CIV5D_DATA'!B:AS,19,FALSE) -> • | Q44: =IF(VLOOKUP(B44,'26MY_CIV5D_DATA'!B:AS,21,FALSE)="","",VLOOKUP(B44,'26MY_CIV5D_DATA'!B:AS,21,FALSE)) -> Rabais de 5 % appliqué.
B45: 08T44-TGH-300 | C45: =VLOOKUP(B45,'26MY_CIV5D_DATA'!B:AS,4,FALSE) -> Chauffe-moteur - Type R | D45: =B45 -> 08T44-TGH-300
B46: 31670-BMS-004H | C46: =VLOOKUP(B46,'26MY_CIV5D_DATA'!B:AS,4,FALSE) -> Chargeur/mainteneur de batterie automobile 12 V Optimate | D46: =B46 -> 31670-BMS-004H
B48: 25CIV5D-PRO-PET | C48: =VLOOKUP(B48,'26MY_CIV5D_DATA'!B:AS,4,FALSE) -> Ensemble de protection - Petrol | D48: =B48 -> 25CIV5D-PRO-PET | E48: =VLOOKUP(B48,'26MY_CIV5D_DATA'!B:AS,9,FALSE) -> 297 | F48: =VLOOKUP(B48,'26MY_CIV5D_DATA'!B:AS,10,FALSE) -> 550 | G48: =VLOOKUP(B48,'26MY_CIV5D_DATA'!B:AS,7,FALSE) -> 0.6 | H48: =VLOOKUP(B48,'26MY_CIV5D_DATA'!B:AS,11,FALSE) -> 658.6 | I48: =VLOOKUP(B48,'26MY_CIV5D_DATA'!B:AS,12,FALSE) -> 0 | J48: =VLOOKUP(B48,'26MY_CIV5D_DATA'!B:AS,13,FALSE) -> 0 | K48: =VLOOKUP($B48,'26MY_CIV5D_DATA'!$B:$AS,14,FALSE) -> 0 | L48: =VLOOKUP(B48,'26MY_CIV5D_DATA'!B:AS,15,FALSE) -> • | M48: =VLOOKUP(B48,'26MY_CIV5D_DATA'!B:AS,16,FALSE) -> N/A | N48: =VLOOKUP($B48,'26MY_CIV5D_DATA'!$B:$AS,17,FALSE) -> 0 | O48: =VLOOKUP(B48,'26MY_CIV5D_DATA'!B:AS,18,FALSE) -> N/A | P48: =VLOOKUP(B48,'26MY_CIV5D_DATA'!B:AS,19,FALSE) -> N/A | Q48: =IF(VLOOKUP(B48,'26MY_CIV5D_DATA'!B:AS,21,FALSE)="","",VLOOKUP(B48,'26MY_CIV5D_DATA'!B:AS,21,FALSE))
B49: 08P17-T20-110 | C49: =VLOOKUP(B49,'26MY_CIV5D_DATA'!B:AS,4,FALSE) -> Tapis toutes saisons | D49: =B49 -> 08P17-T20-110
B50: 08U45-T47-100B | C50: =VLOOKUP(B50,'26MY_CIV5D_DATA'!B:AS,4,FALSE) -> Plateau de coffre | D50: =B50 -> 08U45-T47-100B
B51: 08P09-T47-300 | C51: =VLOOKUP(B51,'26MY_CIV5D_DATA'!B:AS,4,FALSE) -> Garde-boue arrière | D51: =B51 -> 08P09-T47-300
B53: 25CIV5-PRO-HYB | C53: =VLOOKUP(B53,'26MY_CIV5D_DATA'!B:AS,4,FALSE) -> Ensemble de protection - Hybrid | D53: =B53 -> 25CIV5-PRO-HYB | E53: =VLOOKUP(B53,'26MY_CIV5D_DATA'!B:AS,9,FALSE) -> 297 | F53: =VLOOKUP(B53,'26MY_CIV5D_DATA'!B:AS,10,FALSE) -> 550 | G53: =VLOOKUP(B53,'26MY_CIV5D_DATA'!B:AS,7,FALSE) -> 0.6 | H53: =VLOOKUP(B53,'26MY_CIV5D_DATA'!B:AS,11,FALSE) -> 658.6 | I53: =VLOOKUP(B53,'26MY_CIV5D_DATA'!B:AS,12,FALSE) -> 0 | J53: =VLOOKUP(B53,'26MY_CIV5D_DATA'!B:AS,13,FALSE) -> 0 | K53: =VLOOKUP($B53,'26MY_CIV5D_DATA'!$B:$AS,14,FALSE) -> 0 | L53: =VLOOKUP(B53,'26MY_CIV5D_DATA'!B:AS,15,FALSE) -> N/A | M53: =VLOOKUP(B53,'26MY_CIV5D_DATA'!B:AS,16,FALSE) -> • | N53: =VLOOKUP($B53,'26MY_CIV5D_DATA'!$B:$AS,17,FALSE) -> 0 | O53: =VLOOKUP(B53,'26MY_CIV5D_DATA'!B:AS,18,FALSE) -> • | P53: =VLOOKUP(B53,'26MY_CIV5D_DATA'!B:AS,19,FALSE) -> N/A | Q53: =IF(VLOOKUP(B53,'26MY_CIV5D_DATA'!B:AS,21,FALSE)="","",VLOOKUP(B53,'26MY_CIV5D_DATA'!B:AS,21,FALSE))
B54: 08P17-T20-110A | C54: =VLOOKUP(B54,'26MY_CIV5D_DATA'!B:AS,4,FALSE) -> Tapis toutes saisons - Hybrid | D54: =B54 -> 08P17-T20-110A
B55: 08U45-T47-100B | C55: =VLOOKUP(B55,'26MY_CIV5D_DATA'!B:AS,4,FALSE) -> Plateau de coffre | D55: =B55 -> 08U45-T47-100B
B56: 08P09-T47-300 | C56: =VLOOKUP(B56,'26MY_CIV5D_DATA'!B:AS,4,FALSE) -> Garde-boue arrière | D56: =B56 -> 08P09-T47-300
B58: 23TYPER-PROPK | C58: =VLOOKUP(B58,'26MY_CIV5D_DATA'!B:AS,4,FALSE) -> Ensemble de protection - Type R | D58: =B58 -> 23TYPER-PROPK | E58: =VLOOKUP(B58,'26MY_CIV5D_DATA'!B:AS,9,FALSE) -> 245.7 | F58: =VLOOKUP(B58,'26MY_CIV5D_DATA'!B:AS,10,FALSE) -> 455 | G58: =VLOOKUP(B58,'26MY_CIV5D_DATA'!B:AS,7,FALSE) -> 0.2 | H58: =VLOOKUP(B58,'26MY_CIV5D_DATA'!B:AS,11,FALSE) -> 491.2 | I58: =VLOOKUP(B58,'26MY_CIV5D_DATA'!B:AS,12,FALSE) -> 0 | J58: =VLOOKUP(B58,'26MY_CIV5D_DATA'!B:AS,13,FALSE) -> 0 | K58: =VLOOKUP($B58,'26MY_CIV5D_DATA'!$B:$AS,14,FALSE) -> 0 | L58: =VLOOKUP(B58,'26MY_CIV5D_DATA'!B:AS,15,FALSE) -> N/A | M58: =VLOOKUP(B58,'26MY_CIV5D_DATA'!B:AS,16,FALSE) -> N/A | N58: =VLOOKUP($B58,'26MY_CIV5D_DATA'!$B:$AS,17,FALSE) -> 0 | O58: =VLOOKUP(B58,'26MY_CIV5D_DATA'!B:AS,18,FALSE) -> N/A | P58: =VLOOKUP(B58,'26MY_CIV5D_DATA'!B:AS,19,FALSE) -> • | Q58: =IF(VLOOKUP(B58,'26MY_CIV5D_DATA'!B:AS,21,FALSE)="","",VLOOKUP(B58,'26MY_CIV5D_DATA'!B:AS,21,FALSE))
B59: 08P17-T20-110 | C59: =VLOOKUP(B59,'26MY_CIV5D_DATA'!B:AS,4,FALSE) -> Tapis toutes saisons | D59: =B59 -> 08P17-T20-110
B60: 08U45-T60-100 | C60: =VLOOKUP(B60,'26MY_CIV5D_DATA'!B:AS,4,FALSE) -> Plateau pour compartiment utilitaire - Type R | D60: =B60 -> 08U45-T60-100
C62: 2.0 Jantes et accessoires de jantes
C63: La description | D63: Numéro de pièce | E63: Prix net | F63: Prix de liste | G63: T.F.F. | H63: Prix installé | I63: Application | Q63: Commentaires
I64: ='26MY_CIV5D_DATA'!M$6 -> 0 | J64: ='26MY_CIV5D_DATA'!N$6 -> 0 | K64: ='26MY_CIV5D_DATA'!O$6 -> 0 | L64: ='26MY_CIV5D_DATA'!P$6 -> SPORT | M64: ='26MY_CIV5D_DATA'!Q$6 -> SPORT Hybride | N64: ='26MY_CIV5D_DATA'!R$6 -> 0 | O64: ='26MY_CIV5D_DATA'!S$6 -> Sport Touring Hybride | P64: ='26MY_CIV5D_DATA'!T$6 -> Type R
B65: 42700-TBA-A12 | C65: =VLOOKUP(B65,'26MY_CIV5D_DATA'!B:AS,4,FALSE) -> Roues d’hiver de 16 po en acier | D65: =B65 -> 42700-TBA-A12 | E65: =VLOOKUP(B65,'26MY_CIV5D_DATA'!B:AS,9,FALSE) -> 317.84 | F65: =VLOOKUP(B65,'26MY_CIV5D_DATA'!B:AS,10,FALSE) -> 522.72 | G65: =VLOOKUP(B65,'26MY_CIV5D_DATA'!B:AS,7,FALSE) -> 1.6 | H65: =VLOOKUP(B65,'26MY_CIV5D_DATA'!B:AS,11,FALSE) -> 812.32 | I65: =VLOOKUP(B65,'26MY_CIV5D_DATA'!B:AS,12,FALSE) -> 0 | J65: =VLOOKUP(B65,'26MY_CIV5D_DATA'!B:AS,13,FALSE) -> 0 | K65: =VLOOKUP($B65,'26MY_CIV5D_DATA'!$B:$AS,14,FALSE) -> 0 | L65: =VLOOKUP(B65,'26MY_CIV5D_DATA'!B:AS,15,FALSE) -> • | M65: =VLOOKUP(B65,'26MY_CIV5D_DATA'!B:AS,16,FALSE) -> N/A | N65: =VLOOKUP($B65,'26MY_CIV5D_DATA'!$B:$AS,17,FALSE) -> 0 | O65: =VLOOKUP(B65,'26MY_CIV5D_DATA'!B:AS,18,FALSE) -> N/A | P65: =VLOOKUP(B65,'26MY_CIV5D_DATA'!B:AS,19,FALSE) -> N/A | Q65: =IF(VLOOKUP(B65,'26MY_CIV5D_DATA'!B:AS,21,FALSE)="","",VLOOKUP(B65,'26MY_CIV5D_DATA'!B:AS,21,FALSE)) -> Prix pour un ensemble de 4 roues. Pneus vendus séparément.
B66: 480-670-6545GB | C66: =VLOOKUP(B66,'26MY_CIV5D_DATA'!B:AS,4,FALSE) -> Jantes Enkei M52 de 16 po noir lustré | D66: =B66 -> 480-670-6545GB | E66: =VLOOKUP(B66,'26MY_CIV5D_DATA'!B:AS,9,FALSE) -> 764 | F66: =VLOOKUP(B66,'26MY_CIV5D_DATA'!B:AS,10,FALSE) -> 1028 | G66: =VLOOKUP(B66,'26MY_CIV5D_DATA'!B:AS,7,FALSE) -> 1.6 | H66: =VLOOKUP(B66,'26MY_CIV5D_DATA'!B:AS,11,FALSE) -> 1317.6 | I66: =VLOOKUP(B66,'26MY_CIV5D_DATA'!B:AS,12,FALSE) -> 0 | J66: =VLOOKUP(B66,'26MY_CIV5D_DATA'!B:AS,13,FALSE) -> 0 | K66: =VLOOKUP($B66,'26MY_CIV5D_DATA'!$B:$AS,14,FALSE) -> 0 | L66: =VLOOKUP(B66,'26MY_CIV5D_DATA'!B:AS,15,FALSE) -> T | M66: =VLOOKUP(B66,'26MY_CIV5D_DATA'!B:AS,16,FALSE) -> N/A | N66: =VLOOKUP($B66,'26MY_CIV5D_DATA'!$B:$AS,17,FALSE) -> 0 | O66: =VLOOKUP(B66,'26MY_CIV5D_DATA'!B:AS,18,FALSE) -> N/A | P66: =VLOOKUP(B66,'26MY_CIV5D_DATA'!B:AS,19,FALSE) -> N/A | Q66: =IF(VLOOKUP(B66,'26MY_CIV5D_DATA'!B:AS,21,FALSE)="","",VLOOKUP(B66,'26MY_CIV5D_DATA'!B:AS,21,FALSE)) -> Prix pour un ensemble de 4 roues. Pneus vendus séparément.
B67: 480-670-6545SP | C67: =VLOOKUP(B67,'26MY_CIV5D_DATA'!B:AS,4,FALSE) -> Jantes Enkei M52 de 16 po argent | D67: =B67 -> 480-670-6545SP | E67: =VLOOKUP(B67,'26MY_CIV5D_DATA'!B:AS,9,FALSE) -> 764 | F67: =VLOOKUP(B67,'26MY_CIV5D_DATA'!B:AS,10,FALSE) -> 1028 | G67: =VLOOKUP(B67,'26MY_CIV5D_DATA'!B:AS,7,FALSE) -> 1.6 | H67: =VLOOKUP(B67,'26MY_CIV5D_DATA'!B:AS,11,FALSE) -> 1317.6 | I67: =VLOOKUP(B67,'26MY_CIV5D_DATA'!B:AS,12,FALSE) -> 0 | J67: =VLOOKUP(B67,'26MY_CIV5D_DATA'!B:AS,13,FALSE) -> 0 | K67: =VLOOKUP($B67,'26MY_CIV5D_DATA'!$B:$AS,14,FALSE) -> 0 | L67: =VLOOKUP(B67,'26MY_CIV5D_DATA'!B:AS,15,FALSE) -> T | M67: =VLOOKUP(B67,'26MY_CIV5D_DATA'!B:AS,16,FALSE) -> N/A | N67: =VLOOKUP($B67,'26MY_CIV5D_DATA'!$B:$AS,17,FALSE) -> 0 | O67: =VLOOKUP(B67,'26MY_CIV5D_DATA'!B:AS,18,FALSE) -> N/A | P67: =VLOOKUP(B67,'26MY_CIV5D_DATA'!B:AS,19,FALSE) -> N/A | Q67: =IF(VLOOKUP(B67,'26MY_CIV5D_DATA'!B:AS,21,FALSE)="","",VLOOKUP(B67,'26MY_CIV5D_DATA'!B:AS,21,FALSE)) -> Prix pour un ensemble de 4 roues. Pneus vendus séparément.
B68: 509-775-6545BH | C68: =VLOOKUP(B68,'26MY_CIV5D_DATA'!B:AS,4,FALSE) -> Jantes Enkei de 17 po noir lustré | D68: =B68 -> 509-775-6545BH | E68: =VLOOKUP(B68,'26MY_CIV5D_DATA'!B:AS,9,FALSE) -> 856 | F68: =VLOOKUP(B68,'26MY_CIV5D_DATA'!B:AS,10,FALSE) -> 1148 | G68: =VLOOKUP(B68,'26MY_CIV5D_DATA'!B:AS,7,FALSE) -> 1.6 | H68: =VLOOKUP(B68,'26MY_CIV5D_DATA'!B:AS,11,FALSE) -> 1437.6 | I68: =VLOOKUP(B68,'26MY_CIV5D_DATA'!B:AS,12,FALSE) -> 0 | J68: =VLOOKUP(B68,'26MY_CIV5D_DATA'!B:AS,13,FALSE) -> 0 | K68: =VLOOKUP($B68,'26MY_CIV5D_DATA'!$B:$AS,14,FALSE) -> 0 | L68: =VLOOKUP(B68,'26MY_CIV5D_DATA'!B:AS,15,FALSE) -> T | M68: =VLOOKUP(B68,'26MY_CIV5D_DATA'!B:AS,16,FALSE) -> N/A | N68: =VLOOKUP($B68,'26MY_CIV5D_DATA'!$B:$AS,17,FALSE) -> 0 | O68: =VLOOKUP(B68,'26MY_CIV5D_DATA'!B:AS,18,FALSE) -> N/A | P68: =VLOOKUP(B68,'26MY_CIV5D_DATA'!B:AS,19,FALSE) -> N/A | Q68: =IF(VLOOKUP(B68,'26MY_CIV5D_DATA'!B:AS,21,FALSE)="","",VLOOKUP(B68,'26MY_CIV5D_DATA'!B:AS,21,FALSE)) -> Prix pour un ensemble de 4 roues. Pneus vendus séparément.
B69: 509-775-6545SH | C69: =VLOOKUP(B69,'26MY_CIV5D_DATA'!B:AS,4,FALSE) -> Jantes Enkei de 17 po argent | D69: =B69 -> 509-775-6545SH | E69: =VLOOKUP(B69,'26MY_CIV5D_DATA'!B:AS,9,FALSE) -> 856 | F69: =VLOOKUP(B69,'26MY_CIV5D_DATA'!B:AS,10,FALSE) -> 1148 | G69: =VLOOKUP(B69,'26MY_CIV5D_DATA'!B:AS,7,FALSE) -> 1.6 | H69: =VLOOKUP(B69,'26MY_CIV5D_DATA'!B:AS,11,FALSE) -> 1437.6 | I69: =VLOOKUP(B69,'26MY_CIV5D_DATA'!B:AS,12,FALSE) -> 0 | J69: =VLOOKUP(B69,'26MY_CIV5D_DATA'!B:AS,13,FALSE) -> 0 | K69: =VLOOKUP($B69,'26MY_CIV5D_DATA'!$B:$AS,14,FALSE) -> 0 | L69: =VLOOKUP(B69,'26MY_CIV5D_DATA'!B:AS,15,FALSE) -> T | M69: =VLOOKUP(B69,'26MY_CIV5D_DATA'!B:AS,16,FALSE) -> N/A | N69: =VLOOKUP($B69,'26MY_CIV5D_DATA'!$B:$AS,17,FALSE) -> 0 | O69: =VLOOKUP(B69,'26MY_CIV5D_DATA'!B:AS,18,FALSE) -> N/A | P69: =VLOOKUP(B69,'26MY_CIV5D_DATA'!B:AS,19,FALSE) -> N/A | Q69: =IF(VLOOKUP(B69,'26MY_CIV5D_DATA'!B:AS,21,FALSE)="","",VLOOKUP(B69,'26MY_CIV5D_DATA'!B:AS,21,FALSE)) -> Prix pour un ensemble de 4 roues. Pneus vendus séparément.
B70: 08W18-T20-100 | C70: =VLOOKUP(B70,'26MY_CIV5D_DATA'!B:AS,4,FALSE) -> Jantes de 18 pouces noir | D70: =B70 -> 08W18-T20-100 | E70: =VLOOKUP(B70,'26MY_CIV5D_DATA'!B:AS,9,FALSE) -> 2316 | F70: =VLOOKUP(B70,'26MY_CIV5D_DATA'!B:AS,10,FALSE) -> 3564 | G70: =VLOOKUP(B70,'26MY_CIV5D_DATA'!B:AS,7,FALSE) -> 1.6 | H70: =VLOOKUP(B70,'26MY_CIV5D_DATA'!B:AS,11,FALSE) -> 3853.6 | I70: =VLOOKUP(B70,'26MY_CIV5D_DATA'!B:AS,12,FALSE) -> 0 | J70: =VLOOKUP(B70,'26MY_CIV5D_DATA'!B:AS,13,FALSE) -> 0 | K70: =VLOOKUP($B70,'26MY_CIV5D_DATA'!$B:$AS,14,FALSE) -> 0 | L70: =VLOOKUP(B70,'26MY_CIV5D_DATA'!B:AS,15,FALSE) -> E | M70: =VLOOKUP(B70,'26MY_CIV5D_DATA'!B:AS,16,FALSE) -> E | N70: =VLOOKUP($B70,'26MY_CIV5D_DATA'!$B:$AS,17,FALSE) -> 0 | O70: =VLOOKUP(B70,'26MY_CIV5D_DATA'!B:AS,18,FALSE) -> E | P70: =VLOOKUP(B70,'26MY_CIV5D_DATA'!B:AS,19,FALSE) -> N/A | Q70: =IF(VLOOKUP(B70,'26MY_CIV5D_DATA'!B:AS,21,FALSE)="","",VLOOKUP(B70,'26MY_CIV5D_DATA'!B:AS,21,FALSE)) -> Prix pour un ensemble de 4 roues. Pneus vendus séparément.
B71: 08W19-T60-100 | C71: =VLOOKUP(B71,'26MY_CIV5D_DATA'!B:AS,4,FALSE) -> Jantes de 19 pouces | D71: =B71 -> 08W19-T60-100 | E71: =VLOOKUP(B71,'26MY_CIV5D_DATA'!B:AS,9,FALSE) -> 4664 | F71: =VLOOKUP(B71,'26MY_CIV5D_DATA'!B:AS,10,FALSE) -> 6664 | G71: =VLOOKUP(B71,'26MY_CIV5D_DATA'!B:AS,7,FALSE) -> 1.6 | H71: =VLOOKUP(B71,'26MY_CIV5D_DATA'!B:AS,11,FALSE) -> 6953.6 | I71: =VLOOKUP(B71,'26MY_CIV5D_DATA'!B:AS,12,FALSE) -> 0 | J71: =VLOOKUP(B71,'26MY_CIV5D_DATA'!B:AS,13,FALSE) -> 0 | K71: =VLOOKUP($B71,'26MY_CIV5D_DATA'!$B:$AS,14,FALSE) -> 0 | L71: =VLOOKUP(B71,'26MY_CIV5D_DATA'!B:AS,15,FALSE) -> N/A | M71: =VLOOKUP(B71,'26MY_CIV5D_DATA'!B:AS,16,FALSE) -> N/A | N71: =VLOOKUP($B71,'26MY_CIV5D_DATA'!$B:$AS,17,FALSE) -> 0 | O71: =VLOOKUP(B71,'26MY_CIV5D_DATA'!B:AS,18,FALSE) -> N/A | P71: =VLOOKUP(B71,'26MY_CIV5D_DATA'!B:AS,19,FALSE) -> E | Q71: =IF(VLOOKUP(B71,'26MY_CIV5D_DATA'!B:AS,21,FALSE)="","",VLOOKUP(B71,'26MY_CIV5D_DATA'!B:AS,21,FALSE)) -> Prix pour un ensemble de 4 roues. Pneus vendus séparément.
B72: 08W42-S2A-101 | C72: =VLOOKUP(B72,'26MY_CIV5D_DATA'!B:AS,4,FALSE) -> Écrous de roue antivols - Noirs | D72: =B72 -> 08W42-S2A-101 | E72: =VLOOKUP(B72,'26MY_CIV5D_DATA'!B:AS,9,FALSE) -> 61 | F72: =VLOOKUP(B72,'26MY_CIV5D_DATA'!B:AS,10,FALSE) -> 102 | G72: =VLOOKUP(B72,'26MY_CIV5D_DATA'!B:AS,7,FALSE) -> 0.2 | H72: =VLOOKUP(B72,'26MY_CIV5D_DATA'!B:AS,11,FALSE) -> 138.2 | I72: =VLOOKUP(B72,'26MY_CIV5D_DATA'!B:AS,12,FALSE) -> 0 | J72: =VLOOKUP(B72,'26MY_CIV5D_DATA'!B:AS,13,FALSE) -> 0 | K72: =VLOOKUP($B72,'26MY_CIV5D_DATA'!$B:$AS,14,FALSE) -> 0 | L72: =VLOOKUP(B72,'26MY_CIV5D_DATA'!B:AS,15,FALSE) -> • | M72: =VLOOKUP(B72,'26MY_CIV5D_DATA'!B:AS,16,FALSE) -> • | N72: =VLOOKUP($B72,'26MY_CIV5D_DATA'!$B:$AS,17,FALSE) -> 0 | O72: =VLOOKUP(B72,'26MY_CIV5D_DATA'!B:AS,18,FALSE) -> • | P72: =VLOOKUP(B72,'26MY_CIV5D_DATA'!B:AS,19,FALSE) -> N/A | Q72: =IF(VLOOKUP(B72,'26MY_CIV5D_DATA'!B:AS,21,FALSE)="","",VLOOKUP(B72,'26MY_CIV5D_DATA'!B:AS,21,FALSE))
B73: 08W42-SCV-302 | C73: =VLOOKUP(B73,'26MY_CIV5D_DATA'!B:AS,4,FALSE) -> Écrous de roue antivols - Chromés | D73: =B73 -> 08W42-SCV-302 | E73: =VLOOKUP(B73,'26MY_CIV5D_DATA'!B:AS,9,FALSE) -> 54 | F73: =VLOOKUP(B73,'26MY_CIV5D_DATA'!B:AS,10,FALSE) -> 90 | G73: =VLOOKUP(B73,'26MY_CIV5D_DATA'!B:AS,7,FALSE) -> 0.2 | H73: =VLOOKUP(B73,'26MY_CIV5D_DATA'!B:AS,11,FALSE) -> 126.2 | I73: =VLOOKUP(B73,'26MY_CIV5D_DATA'!B:AS,12,FALSE) -> 0 | J73: =VLOOKUP(B73,'26MY_CIV5D_DATA'!B:AS,13,FALSE) -> 0 | K73: =VLOOKUP($B73,'26MY_CIV5D_DATA'!$B:$AS,14,FALSE) -> 0 | L73: =VLOOKUP(B73,'26MY_CIV5D_DATA'!B:AS,15,FALSE) -> • | M73: =VLOOKUP(B73,'26MY_CIV5D_DATA'!B:AS,16,FALSE) -> • | N73: =VLOOKUP($B73,'26MY_CIV5D_DATA'!$B:$AS,17,FALSE) -> 0 | O73: =VLOOKUP(B73,'26MY_CIV5D_DATA'!B:AS,18,FALSE) -> • | P73: =VLOOKUP(B73,'26MY_CIV5D_DATA'!B:AS,19,FALSE) -> N/A | Q73: =IF(VLOOKUP(B73,'26MY_CIV5D_DATA'!B:AS,21,FALSE)="","",VLOOKUP(B73,'26MY_CIV5D_DATA'!B:AS,21,FALSE))
B74: 08W42-TG7-301A | C74: =VLOOKUP(B74,'26MY_CIV5D_DATA'!B:AS,4,FALSE) -> Écrous de roue antivols - Noirs (Type R) | D74: =B74 -> 08W42-TG7-301A | E74: =VLOOKUP(B74,'26MY_CIV5D_DATA'!B:AS,9,FALSE) -> 88 | F74: =VLOOKUP(B74,'26MY_CIV5D_DATA'!B:AS,10,FALSE) -> 147 | G74: =VLOOKUP(B74,'26MY_CIV5D_DATA'!B:AS,7,FALSE) -> 0.2 | H74: =VLOOKUP(B74,'26MY_CIV5D_DATA'!B:AS,11,FALSE) -> 183.2 | I74: =VLOOKUP(B74,'26MY_CIV5D_DATA'!B:AS,12,FALSE) -> 0 | J74: =VLOOKUP(B74,'26MY_CIV5D_DATA'!B:AS,13,FALSE) -> 0 | K74: =VLOOKUP($B74,'26MY_CIV5D_DATA'!$B:$AS,14,FALSE) -> 0 | L74: =VLOOKUP(B74,'26MY_CIV5D_DATA'!B:AS,15,FALSE) -> N/A | M74: =VLOOKUP(B74,'26MY_CIV5D_DATA'!B:AS,16,FALSE) -> N/A | N74: =VLOOKUP($B74,'26MY_CIV5D_DATA'!$B:$AS,17,FALSE) -> 0 | O74: =VLOOKUP(B74,'26MY_CIV5D_DATA'!B:AS,18,FALSE) -> N/A | P74: =VLOOKUP(B74,'26MY_CIV5D_DATA'!B:AS,19,FALSE) -> • | Q74: =IF(VLOOKUP(B74,'26MY_CIV5D_DATA'!B:AS,21,FALSE)="","",VLOOKUP(B74,'26MY_CIV5D_DATA'!B:AS,21,FALSE))
B75: 08W42-TK4-301 | C75: =VLOOKUP(B75,'26MY_CIV5D_DATA'!B:AS,4,FALSE) -> Écrous de roue antivols - Chromés (Type R) | D75: =B75 -> 08W42-TK4-301 | E75: =VLOOKUP(B75,'26MY_CIV5D_DATA'!B:AS,9,FALSE) -> 94 | F75: =VLOOKUP(B75,'26MY_CIV5D_DATA'!B:AS,10,FALSE) -> 157 | G75: =VLOOKUP(B75,'26MY_CIV5D_DATA'!B:AS,7,FALSE) -> 0.2 | H75: =VLOOKUP(B75,'26MY_CIV5D_DATA'!B:AS,11,FALSE) -> 193.2 | I75: =VLOOKUP(B75,'26MY_CIV5D_DATA'!B:AS,12,FALSE) -> 0 | J75: =VLOOKUP(B75,'26MY_CIV5D_DATA'!B:AS,13,FALSE) -> 0 | K75: =VLOOKUP($B75,'26MY_CIV5D_DATA'!$B:$AS,14,FALSE) -> 0 | L75: =VLOOKUP(B75,'26MY_CIV5D_DATA'!B:AS,15,FALSE) -> N/A | M75: =VLOOKUP(B75,'26MY_CIV5D_DATA'!B:AS,16,FALSE) -> N/A | N75: =VLOOKUP($B75,'26MY_CIV5D_DATA'!$B:$AS,17,FALSE) -> 0 | O75: =VLOOKUP(B75,'26MY_CIV5D_DATA'!B:AS,18,FALSE) -> N/A | P75: =VLOOKUP(B75,'26MY_CIV5D_DATA'!B:AS,19,FALSE) -> • | Q75: =IF(VLOOKUP(B75,'26MY_CIV5D_DATA'!B:AS,21,FALSE)="","",VLOOKUP(B75,'26MY_CIV5D_DATA'!B:AS,21,FALSE))
B76: 08W42-TGG-100 | C76: =VLOOKUP(B76,'26MY_CIV5D_DATA'!B:AS,4,FALSE) -> Écrous de roue - Noir | D76: =B76 -> 08W42-TGG-100 | E76: =VLOOKUP(B76,'26MY_CIV5D_DATA'!B:AS,9,FALSE) -> 57 | F76: =VLOOKUP(B76,'26MY_CIV5D_DATA'!B:AS,10,FALSE) -> 91 | G76: =VLOOKUP(B76,'26MY_CIV5D_DATA'!B:AS,7,FALSE) -> 0.2 | H76: =VLOOKUP(B76,'26MY_CIV5D_DATA'!B:AS,11,FALSE) -> 127.2 | I76: =VLOOKUP(B76,'26MY_CIV5D_DATA'!B:AS,12,FALSE) -> 0 | J76: =VLOOKUP(B76,'26MY_CIV5D_DATA'!B:AS,13,FALSE) -> 0 | K76: =VLOOKUP($B76,'26MY_CIV5D_DATA'!$B:$AS,14,FALSE) -> 0 | L76: =VLOOKUP(B76,'26MY_CIV5D_DATA'!B:AS,15,FALSE) -> • | M76: =VLOOKUP(B76,'26MY_CIV5D_DATA'!B:AS,16,FALSE) -> • | N76: =VLOOKUP($B76,'26MY_CIV5D_DATA'!$B:$AS,17,FALSE) -> 0 | O76: =VLOOKUP(B76,'26MY_CIV5D_DATA'!B:AS,18,FALSE) -> • | P76: =VLOOKUP(B76,'26MY_CIV5D_DATA'!B:AS,19,FALSE) -> N/A | Q76: =IF(VLOOKUP(B76,'26MY_CIV5D_DATA'!B:AS,21,FALSE)="","",VLOOKUP(B76,'26MY_CIV5D_DATA'!B:AS,21,FALSE)) -> Inclut 4 écrous de roue en 1 jeu. L'installation complète nécessite 5 jeux pour 4 roues (20 écrous de roue).
C78: 3.0 Extérieur
C79: La description | D79: Numéro de pièce | E79: Prix net | F79: Prix de liste | G79: T.F.F. | H79: Prix installé | I79: Application | Q79: Commentaires
I80: ='26MY_CIV5D_DATA'!M$6 -> 0 | J80: ='26MY_CIV5D_DATA'!N$6 -> 0 | K80: ='26MY_CIV5D_DATA'!O$6 -> 0 | L80: ='26MY_CIV5D_DATA'!P$6 -> SPORT | M80: ='26MY_CIV5D_DATA'!Q$6 -> SPORT Hybride | N80: ='26MY_CIV5D_DATA'!R$6 -> 0 | O80: ='26MY_CIV5D_DATA'!S$6 -> Sport Touring Hybride | P80: ='26MY_CIV5D_DATA'!T$6 -> Type R
B81: 08F20-T47-100E | C81: =VLOOKUP(B81,'26MY_CIV5D_DATA'!B:AS,4,FALSE) -> Emblèmes « H » noirs | D81: =B81 -> 08F20-T47-100E | E81: =VLOOKUP(B81,'26MY_CIV5D_DATA'!B:AS,9,FALSE) -> 86 | F81: =VLOOKUP(B81,'26MY_CIV5D_DATA'!B:AS,10,FALSE) -> 123 | G81: =VLOOKUP(B81,'26MY_CIV5D_DATA'!B:AS,7,FALSE) -> 0.7 | H81: =VLOOKUP(B81,'26MY_CIV5D_DATA'!B:AS,11,FALSE) -> 249.7 | I81: =VLOOKUP(B81,'26MY_CIV5D_DATA'!B:AS,12,FALSE) -> 0 | J81: =VLOOKUP(B81,'26MY_CIV5D_DATA'!B:AS,13,FALSE) -> 0 | K81: =VLOOKUP($B81,'26MY_CIV5D_DATA'!$B:$AS,14,FALSE) -> 0 | L81: =VLOOKUP(B81,'26MY_CIV5D_DATA'!B:AS,15,FALSE) -> • | M81: =VLOOKUP(B81,'26MY_CIV5D_DATA'!B:AS,16,FALSE) -> • | N81: =VLOOKUP($B81,'26MY_CIV5D_DATA'!$B:$AS,17,FALSE) -> 0 | O81: =VLOOKUP(B81,'26MY_CIV5D_DATA'!B:AS,18,FALSE) -> • | P81: =VLOOKUP(B81,'26MY_CIV5D_DATA'!B:AS,19,FALSE) -> N/A | Q81: =IF(VLOOKUP(B81,'26MY_CIV5D_DATA'!B:AS,21,FALSE)="","",VLOOKUP(B81,'26MY_CIV5D_DATA'!B:AS,21,FALSE)) -> Logo H-Mark à l'avant et à l'arrière.
B82: 08P47-T20-300 | C82: =VLOOKUP(B82,'26MY_CIV5D_DATA'!B:AS,4,FALSE) -> Protecteur de capot | D82: =B82 -> 08P47-T20-300 | E82: =VLOOKUP(B82,'26MY_CIV5D_DATA'!B:AS,9,FALSE) -> 221 | F82: =VLOOKUP(B82,'26MY_CIV5D_DATA'!B:AS,10,FALSE) -> 368 | G82: =VLOOKUP(B82,'26MY_CIV5D_DATA'!B:AS,7,FALSE) -> 0.6 | H82: =VLOOKUP(B82,'26MY_CIV5D_DATA'!B:AS,11,FALSE) -> 476.6 | I82: =VLOOKUP(B82,'26MY_CIV5D_DATA'!B:AS,12,FALSE) -> 0 | J82: =VLOOKUP(B82,'26MY_CIV5D_DATA'!B:AS,13,FALSE) -> 0 | K82: =VLOOKUP($B82,'26MY_CIV5D_DATA'!$B:$AS,14,FALSE) -> 0 | L82: =VLOOKUP(B82,'26MY_CIV5D_DATA'!B:AS,15,FALSE) -> • | M82: =VLOOKUP(B82,'26MY_CIV5D_DATA'!B:AS,16,FALSE) -> • | N82: =VLOOKUP($B82,'26MY_CIV5D_DATA'!$B:$AS,17,FALSE) -> 0 | O82: =VLOOKUP(B82,'26MY_CIV5D_DATA'!B:AS,18,FALSE) -> • | P82: =VLOOKUP(B82,'26MY_CIV5D_DATA'!B:AS,19,FALSE) -> N/A | Q82: =IF(VLOOKUP(B82,'26MY_CIV5D_DATA'!B:AS,21,FALSE)="","",VLOOKUP(B82,'26MY_CIV5D_DATA'!B:AS,21,FALSE))
B83: 08R04-T47-100A | C83: =VLOOKUP(B83,'26MY_CIV5D_DATA'!B:AS,4,FALSE) -> Déflecteurs de portières - noir | D83: =B83 -> 08R04-T47-100A | E83: =VLOOKUP(B83,'26MY_CIV5D_DATA'!B:AS,9,FALSE) -> 207 | F83: =VLOOKUP(B83,'26MY_CIV5D_DATA'!B:AS,10,FALSE) -> 345 | G83: =VLOOKUP(B83,'26MY_CIV5D_DATA'!B:AS,7,FALSE) -> 0.5 | H83: =VLOOKUP(B83,'26MY_CIV5D_DATA'!B:AS,11,FALSE) -> 435.5 | I83: =VLOOKUP(B83,'26MY_CIV5D_DATA'!B:AS,12,FALSE) -> 0 | J83: =VLOOKUP(B83,'26MY_CIV5D_DATA'!B:AS,13,FALSE) -> 0 | K83: =VLOOKUP($B83,'26MY_CIV5D_DATA'!$B:$AS,14,FALSE) -> 0 | L83: =VLOOKUP(B83,'26MY_CIV5D_DATA'!B:AS,15,FALSE) -> • | M83: =VLOOKUP(B83,'26MY_CIV5D_DATA'!B:AS,16,FALSE) -> • | N83: =VLOOKUP($B83,'26MY_CIV5D_DATA'!$B:$AS,17,FALSE) -> 0 | O83: =VLOOKUP(B83,'26MY_CIV5D_DATA'!B:AS,18,FALSE) -> • | P83: =VLOOKUP(B83,'26MY_CIV5D_DATA'!B:AS,19,FALSE) -> • | Q83: =IF(VLOOKUP(B83,'26MY_CIV5D_DATA'!B:AS,21,FALSE)="","",VLOOKUP(B83,'26MY_CIV5D_DATA'!B:AS,21,FALSE))
B84: 08P09-T47-300 | C84: =VLOOKUP(B84,'26MY_CIV5D_DATA'!B:AS,4,FALSE) -> Garde-boue arrière | D84: =B84 -> 08P09-T47-300 | E84: =VLOOKUP(B84,'26MY_CIV5D_DATA'!B:AS,9,FALSE) -> 63 | F84: =VLOOKUP(B84,'26MY_CIV5D_DATA'!B:AS,10,FALSE) -> 105 | G84: =VLOOKUP(B84,'26MY_CIV5D_DATA'!B:AS,7,FALSE) -> 0.4 | H84: =VLOOKUP(B84,'26MY_CIV5D_DATA'!B:AS,11,FALSE) -> 177.4 | I84: =VLOOKUP(B84,'26MY_CIV5D_DATA'!B:AS,12,FALSE) -> 0 | J84: =VLOOKUP(B84,'26MY_CIV5D_DATA'!B:AS,13,FALSE) -> 0 | K84: =VLOOKUP($B84,'26MY_CIV5D_DATA'!$B:$AS,14,FALSE) -> 0 | L84: =VLOOKUP(B84,'26MY_CIV5D_DATA'!B:AS,15,FALSE) -> • | M84: =VLOOKUP(B84,'26MY_CIV5D_DATA'!B:AS,16,FALSE) -> • | N84: =VLOOKUP($B84,'26MY_CIV5D_DATA'!$B:$AS,17,FALSE) -> 0 | O84: =VLOOKUP(B84,'26MY_CIV5D_DATA'!B:AS,18,FALSE) -> • | P84: =VLOOKUP(B84,'26MY_CIV5D_DATA'!B:AS,19,FALSE) -> N/A | Q84: =IF(VLOOKUP(B84,'26MY_CIV5D_DATA'!B:AS,21,FALSE)="","",VLOOKUP(B84,'26MY_CIV5D_DATA'!B:AS,21,FALSE))
B85: 08R01-T20-300 | C85: =VLOOKUP(B85,'26MY_CIV5D_DATA'!B:AS,4,FALSE) -> Déflecteur de toit ouvrant | D85: =B85 -> 08R01-T20-300 | E85: =VLOOKUP(B85,'26MY_CIV5D_DATA'!B:AS,9,FALSE) -> 174 | F85: =VLOOKUP(B85,'26MY_CIV5D_DATA'!B:AS,10,FALSE) -> 290 | G85: =VLOOKUP(B85,'26MY_CIV5D_DATA'!B:AS,7,FALSE) -> 0.3 | H85: =VLOOKUP(B85,'26MY_CIV5D_DATA'!B:AS,11,FALSE) -> 344.3 | I85: =VLOOKUP(B85,'26MY_CIV5D_DATA'!B:AS,12,FALSE) -> 0 | J85: =VLOOKUP(B85,'26MY_CIV5D_DATA'!B:AS,13,FALSE) -> 0 | K85: =VLOOKUP($B85,'26MY_CIV5D_DATA'!$B:$AS,14,FALSE) -> 0 | L85: =VLOOKUP(B85,'26MY_CIV5D_DATA'!B:AS,15,FALSE) -> • | M85: =VLOOKUP(B85,'26MY_CIV5D_DATA'!B:AS,16,FALSE) -> • | N85: =VLOOKUP($B85,'26MY_CIV5D_DATA'!$B:$AS,17,FALSE) -> 0 | O85: =VLOOKUP(B85,'26MY_CIV5D_DATA'!B:AS,18,FALSE) -> • | P85: =VLOOKUP(B85,'26MY_CIV5D_DATA'!B:AS,19,FALSE) -> N/A | Q85: =IF(VLOOKUP(B85,'26MY_CIV5D_DATA'!B:AS,21,FALSE)="","",VLOOKUP(B85,'26MY_CIV5D_DATA'!B:AS,21,FALSE))
B86: 08P01-T47-100 | C86: =VLOOKUP(B86,'26MY_CIV5D_DATA'!B:AS,4,FALSE) -> Protection de pare-chocs arrière | D86: =B86 -> 08P01-T47-100 | E86: =VLOOKUP(B86,'26MY_CIV5D_DATA'!B:AS,9,FALSE) -> 58 | F86: =VLOOKUP(B86,'26MY_CIV5D_DATA'!B:AS,10,FALSE) -> 83 | G86: =VLOOKUP(B86,'26MY_CIV5D_DATA'!B:AS,7,FALSE) -> 0.1 | H86: =VLOOKUP(B86,'26MY_CIV5D_DATA'!B:AS,11,FALSE) -> 101.1 | I86: =VLOOKUP(B86,'26MY_CIV5D_DATA'!B:AS,12,FALSE) -> 0 | J86: =VLOOKUP(B86,'26MY_CIV5D_DATA'!B:AS,13,FALSE) -> 0 | K86: =VLOOKUP($B86,'26MY_CIV5D_DATA'!$B:$AS,14,FALSE) -> 0 | L86: =VLOOKUP(B86,'26MY_CIV5D_DATA'!B:AS,15,FALSE) -> • | M86: =VLOOKUP(B86,'26MY_CIV5D_DATA'!B:AS,16,FALSE) -> • | N86: =VLOOKUP($B86,'26MY_CIV5D_DATA'!$B:$AS,17,FALSE) -> 0 | O86: =VLOOKUP(B86,'26MY_CIV5D_DATA'!B:AS,18,FALSE) -> • | P86: =VLOOKUP(B86,'26MY_CIV5D_DATA'!B:AS,19,FALSE) -> N/A | Q86: =IF(VLOOKUP(B86,'26MY_CIV5D_DATA'!B:AS,21,FALSE)="","",VLOOKUP(B86,'26MY_CIV5D_DATA'!B:AS,21,FALSE))
B87: 08P20-T20-100A | C87: =VLOOKUP(B87,'26MY_CIV5D_DATA'!B:AS,4,FALSE) -> Pellicule pour rebord de portière | D87: =B87 -> 08P20-T20-100A | E87: =VLOOKUP(B87,'26MY_CIV5D_DATA'!B:AS,9,FALSE) -> 67 | F87: =VLOOKUP(B87,'26MY_CIV5D_DATA'!B:AS,10,FALSE) -> 112 | G87: =VLOOKUP(B87,'26MY_CIV5D_DATA'!B:AS,7,FALSE) -> 0.5 | H87: =VLOOKUP(B87,'26MY_CIV5D_DATA'!B:AS,11,FALSE) -> 202.5 | I87: =VLOOKUP(B87,'26MY_CIV5D_DATA'!B:AS,12,FALSE) -> 0 | J87: =VLOOKUP(B87,'26MY_CIV5D_DATA'!B:AS,13,FALSE) -> 0 | K87: =VLOOKUP($B87,'26MY_CIV5D_DATA'!$B:$AS,14,FALSE) -> 0 | L87: =VLOOKUP(B87,'26MY_CIV5D_DATA'!B:AS,15,FALSE) -> • | M87: =VLOOKUP(B87,'26MY_CIV5D_DATA'!B:AS,16,FALSE) -> • | N87: =VLOOKUP($B87,'26MY_CIV5D_DATA'!$B:$AS,17,FALSE) -> 0 | O87: =VLOOKUP(B87,'26MY_CIV5D_DATA'!B:AS,18,FALSE) -> • | P87: =VLOOKUP(B87,'26MY_CIV5D_DATA'!B:AS,19,FALSE) -> N/A | Q87: =IF(VLOOKUP(B87,'26MY_CIV5D_DATA'!B:AS,21,FALSE)="","",VLOOKUP(B87,'26MY_CIV5D_DATA'!B:AS,21,FALSE)) -> Ne peut être installé simultanément avec protecteurs de bordure de porte.
B88: 08P48-T60-100 | C88: =VLOOKUP(B88,'26MY_CIV5D_DATA'!B:AS,4,FALSE) -> Film de Protection - Type R | D88: =B88 -> 08P48-T60-100 | E88: =VLOOKUP(B88,'26MY_CIV5D_DATA'!B:AS,9,FALSE) -> 169 | F88: =VLOOKUP(B88,'26MY_CIV5D_DATA'!B:AS,10,FALSE) -> 282 | G88: =VLOOKUP(B88,'26MY_CIV5D_DATA'!B:AS,7,FALSE) -> 1 | H88: =VLOOKUP(B88,'26MY_CIV5D_DATA'!B:AS,11,FALSE) -> 463 | I88: =VLOOKUP(B88,'26MY_CIV5D_DATA'!B:AS,12,FALSE) -> 0 | J88: =VLOOKUP(B88,'26MY_CIV5D_DATA'!B:AS,13,FALSE) -> 0 | K88: =VLOOKUP($B88,'26MY_CIV5D_DATA'!$B:$AS,14,FALSE) -> 0 | L88: =VLOOKUP(B88,'26MY_CIV5D_DATA'!B:AS,15,FALSE) -> N/A | M88: =VLOOKUP(B88,'26MY_CIV5D_DATA'!B:AS,16,FALSE) -> N/A | N88: =VLOOKUP($B88,'26MY_CIV5D_DATA'!$B:$AS,17,FALSE) -> 0 | O88: =VLOOKUP(B88,'26MY_CIV5D_DATA'!B:AS,18,FALSE) -> N/A | P88: =VLOOKUP(B88,'26MY_CIV5D_DATA'!B:AS,19,FALSE) -> • | Q88: =IF(VLOOKUP(B88,'26MY_CIV5D_DATA'!B:AS,21,FALSE)="","",VLOOKUP(B88,'26MY_CIV5D_DATA'!B:AS,21,FALSE)) -> Comprend la pellicule de rebord de portière, la pellicule pour poignée de portière et le revêtement de pare-chocs arrière.
B89: 08L02-T47-300 | C89: =VLOOKUP(B89,'26MY_CIV5D_DATA'!B:AS,4,FALSE) -> Porte-bagages de toit | D89: =B89 -> 08L02-T47-300 | E89: =VLOOKUP(B89,'26MY_CIV5D_DATA'!B:AS,9,FALSE) -> 498 | F89: =VLOOKUP(B89,'26MY_CIV5D_DATA'!B:AS,10,FALSE) -> 830 | G89: =VLOOKUP(B89,'26MY_CIV5D_DATA'!B:AS,7,FALSE) -> 0.4 | H89: =VLOOKUP(B89,'26MY_CIV5D_DATA'!B:AS,11,FALSE) -> 902.4 | I89: =VLOOKUP(B89,'26MY_CIV5D_DATA'!B:AS,12,FALSE) -> 0 | J89: =VLOOKUP(B89,'26MY_CIV5D_DATA'!B:AS,13,FALSE) -> 0 | K89: =VLOOKUP($B89,'26MY_CIV5D_DATA'!$B:$AS,14,FALSE) -> 0 | L89: =VLOOKUP(B89,'26MY_CIV5D_DATA'!B:AS,15,FALSE) -> • | M89: =VLOOKUP(B89,'26MY_CIV5D_DATA'!B:AS,16,FALSE) -> • | N89: =VLOOKUP($B89,'26MY_CIV5D_DATA'!$B:$AS,17,FALSE) -> 0 | O89: =VLOOKUP(B89,'26MY_CIV5D_DATA'!B:AS,18,FALSE) -> • | P89: =VLOOKUP(B89,'26MY_CIV5D_DATA'!B:AS,19,FALSE) -> • | Q89: =IF(VLOOKUP(B89,'26MY_CIV5D_DATA'!B:AS,21,FALSE)="","",VLOOKUP(B89,'26MY_CIV5D_DATA'!B:AS,21,FALSE))
B90: 08LXX-E09-XXXX | C90: =VLOOKUP(B90,'26MY_CIV5D_DATA'!B:AS,4,FALSE) -> Accessoires de toit
B91: 08L20-E09-300A | C91: =VLOOKUP(B91,'26MY_CIV5D_DATA'!B:AS,4,FALSE) -> Boîte de toit - moyenne | D91: =B91 -> 08L20-E09-300A | E91: =VLOOKUP(B91,'26MY_CIV5D_DATA'!B:AS,9,FALSE) -> 898 | F91: =VLOOKUP(B91,'26MY_CIV5D_DATA'!B:AS,10,FALSE) -> 1497 | G91: =VLOOKUP(B91,'26MY_CIV5D_DATA'!B:AS,7,FALSE) -> 0.2 | H91: =VLOOKUP(B91,'26MY_CIV5D_DATA'!B:AS,11,FALSE) -> 1533.2 | I91: =VLOOKUP(B91,'26MY_CIV5D_DATA'!B:AS,12,FALSE) -> 0 | J91: =VLOOKUP(B91,'26MY_CIV5D_DATA'!B:AS,13,FALSE) -> 0 | K91: =VLOOKUP($B91,'26MY_CIV5D_DATA'!$B:$AS,14,FALSE) -> 0 | L91: =VLOOKUP(B91,'26MY_CIV5D_DATA'!B:AS,15,FALSE) -> • | M91: =VLOOKUP(B91,'26MY_CIV5D_DATA'!B:AS,16,FALSE) -> • | N91: =VLOOKUP($B91,'26MY_CIV5D_DATA'!$B:$AS,17,FALSE) -> 0 | O91: =VLOOKUP(B91,'26MY_CIV5D_DATA'!B:AS,18,FALSE) -> • | P91: =VLOOKUP(B91,'26MY_CIV5D_DATA'!B:AS,19,FALSE) -> • | Q91: =IF(VLOOKUP(B91,'26MY_CIV5D_DATA'!B:AS,21,FALSE)="","",VLOOKUP(B91,'26MY_CIV5D_DATA'!B:AS,21,FALSE))
B92: 08L20-E09-300B | C92: =VLOOKUP(B92,'26MY_CIV5D_DATA'!B:AS,4,FALSE) -> Boîte de toit - courte | D92: =B92 -> 08L20-E09-300B | E92: =VLOOKUP(B92,'26MY_CIV5D_DATA'!B:AS,9,FALSE) -> 820 | F92: =VLOOKUP(B92,'26MY_CIV5D_DATA'!B:AS,10,FALSE) -> 1367 | G92: =VLOOKUP(B92,'26MY_CIV5D_DATA'!B:AS,7,FALSE) -> 0.2 | H92: =VLOOKUP(B92,'26MY_CIV5D_DATA'!B:AS,11,FALSE) -> 1403.2 | I92: =VLOOKUP(B92,'26MY_CIV5D_DATA'!B:AS,12,FALSE) -> 0 | J92: =VLOOKUP(B92,'26MY_CIV5D_DATA'!B:AS,13,FALSE) -> 0 | K92: =VLOOKUP($B92,'26MY_CIV5D_DATA'!$B:$AS,14,FALSE) -> 0 | L92: =VLOOKUP(B92,'26MY_CIV5D_DATA'!B:AS,15,FALSE) -> • | M92: =VLOOKUP(B92,'26MY_CIV5D_DATA'!B:AS,16,FALSE) -> • | N92: =VLOOKUP($B92,'26MY_CIV5D_DATA'!$B:$AS,17,FALSE) -> 0 | O92: =VLOOKUP(B92,'26MY_CIV5D_DATA'!B:AS,18,FALSE) -> • | P92: =VLOOKUP(B92,'26MY_CIV5D_DATA'!B:AS,19,FALSE) -> • | Q92: =IF(VLOOKUP(B92,'26MY_CIV5D_DATA'!B:AS,21,FALSE)="","",VLOOKUP(B92,'26MY_CIV5D_DATA'!B:AS,21,FALSE))
B93: 08L09-E09-101 | C93: =VLOOKUP(B93,'26MY_CIV5D_DATA'!B:AS,4,FALSE) -> Galerie de toit, fixation pour kayak | D93: =B93 -> 08L09-E09-101 | E93: =VLOOKUP(B93,'26MY_CIV5D_DATA'!B:AS,9,FALSE) -> 442 | F93: =VLOOKUP(B93,'26MY_CIV5D_DATA'!B:AS,10,FALSE) -> 737 | G93: =VLOOKUP(B93,'26MY_CIV5D_DATA'!B:AS,7,FALSE) -> 0.2 | H93: =VLOOKUP(B93,'26MY_CIV5D_DATA'!B:AS,11,FALSE) -> 773.2 | I93: =VLOOKUP(B93,'26MY_CIV5D_DATA'!B:AS,12,FALSE) -> 0 | J93: =VLOOKUP(B93,'26MY_CIV5D_DATA'!B:AS,13,FALSE) -> 0 | K93: =VLOOKUP($B93,'26MY_CIV5D_DATA'!$B:$AS,14,FALSE) -> 0 | L93: =VLOOKUP(B93,'26MY_CIV5D_DATA'!B:AS,15,FALSE) -> • | M93: =VLOOKUP(B93,'26MY_CIV5D_DATA'!B:AS,16,FALSE) -> • | N93: =VLOOKUP($B93,'26MY_CIV5D_DATA'!$B:$AS,17,FALSE) -> 0 | O93: =VLOOKUP(B93,'26MY_CIV5D_DATA'!B:AS,18,FALSE) -> • | P93: =VLOOKUP(B93,'26MY_CIV5D_DATA'!B:AS,19,FALSE) -> • | Q93: =IF(VLOOKUP(B93,'26MY_CIV5D_DATA'!B:AS,21,FALSE)="","",VLOOKUP(B93,'26MY_CIV5D_DATA'!B:AS,21,FALSE))
B94: 08L03-E09-300C | C94: =VLOOKUP(B94,'26MY_CIV5D_DATA'!B:AS,4,FALSE) -> Galerie de toit, Fixation pour skis/planche à neige | D94: =B94 -> 08L03-E09-300C | E94: =VLOOKUP(B94,'26MY_CIV5D_DATA'!B:AS,9,FALSE) -> 426 | F94: =VLOOKUP(B94,'26MY_CIV5D_DATA'!B:AS,10,FALSE) -> 710 | G94: =VLOOKUP(B94,'26MY_CIV5D_DATA'!B:AS,7,FALSE) -> 0.2 | H94: =VLOOKUP(B94,'26MY_CIV5D_DATA'!B:AS,11,FALSE) -> 746.2 | I94: =VLOOKUP(B94,'26MY_CIV5D_DATA'!B:AS,12,FALSE) -> 0 | J94: =VLOOKUP(B94,'26MY_CIV5D_DATA'!B:AS,13,FALSE) -> 0 | K94: =VLOOKUP($B94,'26MY_CIV5D_DATA'!$B:$AS,14,FALSE) -> 0 | L94: =VLOOKUP(B94,'26MY_CIV5D_DATA'!B:AS,15,FALSE) -> • | M94: =VLOOKUP(B94,'26MY_CIV5D_DATA'!B:AS,16,FALSE) -> • | N94: =VLOOKUP($B94,'26MY_CIV5D_DATA'!$B:$AS,17,FALSE) -> 0 | O94: =VLOOKUP(B94,'26MY_CIV5D_DATA'!B:AS,18,FALSE) -> • | P94: =VLOOKUP(B94,'26MY_CIV5D_DATA'!B:AS,19,FALSE) -> • | Q94: =IF(VLOOKUP(B94,'26MY_CIV5D_DATA'!B:AS,21,FALSE)="","",VLOOKUP(B94,'26MY_CIV5D_DATA'!B:AS,21,FALSE))
B95: 08L05-E09-100 | C95: =VLOOKUP(B95,'26MY_CIV5D_DATA'!B:AS,4,FALSE) -> Galerie de toit, Fixation pour planche de surf | D95: =B95 -> 08L05-E09-100 | E95: =VLOOKUP(B95,'26MY_CIV5D_DATA'!B:AS,9,FALSE) -> 213 | F95: =VLOOKUP(B95,'26MY_CIV5D_DATA'!B:AS,10,FALSE) -> 355 | G95: =VLOOKUP(B95,'26MY_CIV5D_DATA'!B:AS,7,FALSE) -> 0.2 | H95: =VLOOKUP(B95,'26MY_CIV5D_DATA'!B:AS,11,FALSE) -> 391.2 | I95: =VLOOKUP(B95,'26MY_CIV5D_DATA'!B:AS,12,FALSE) -> 0 | J95: =VLOOKUP(B95,'26MY_CIV5D_DATA'!B:AS,13,FALSE) -> 0 | K95: =VLOOKUP($B95,'26MY_CIV5D_DATA'!$B:$AS,14,FALSE) -> 0 | L95: =VLOOKUP(B95,'26MY_CIV5D_DATA'!B:AS,15,FALSE) -> • | M95: =VLOOKUP(B95,'26MY_CIV5D_DATA'!B:AS,16,FALSE) -> • | N95: =VLOOKUP($B95,'26MY_CIV5D_DATA'!$B:$AS,17,FALSE) -> 0 | O95: =VLOOKUP(B95,'26MY_CIV5D_DATA'!B:AS,18,FALSE) -> • | P95: =VLOOKUP(B95,'26MY_CIV5D_DATA'!B:AS,19,FALSE) -> • | Q95: =IF(VLOOKUP(B95,'26MY_CIV5D_DATA'!B:AS,21,FALSE)="","",VLOOKUP(B95,'26MY_CIV5D_DATA'!B:AS,21,FALSE))
B96: 08L07-E09-101 | C96: =VLOOKUP(B96,'26MY_CIV5D_DATA'!B:AS,4,FALSE) -> Support à vélo vertical pour porte-bagages de toit | D96: =B96 -> 08L07-E09-101 | E96: =VLOOKUP(B96,'26MY_CIV5D_DATA'!B:AS,9,FALSE) -> 393 | F96: =VLOOKUP(B96,'26MY_CIV5D_DATA'!B:AS,10,FALSE) -> 561 | G96: =VLOOKUP(B96,'26MY_CIV5D_DATA'!B:AS,7,FALSE) -> 0.6 | H96: =VLOOKUP(B96,'26MY_CIV5D_DATA'!B:AS,11,FALSE) -> 669.6 | I96: =VLOOKUP(B96,'26MY_CIV5D_DATA'!B:AS,12,FALSE) -> 0 | J96: =VLOOKUP(B96,'26MY_CIV5D_DATA'!B:AS,13,FALSE) -> 0 | K96: =VLOOKUP($B96,'26MY_CIV5D_DATA'!$B:$AS,14,FALSE) -> 0 | L96: =VLOOKUP(B96,'26MY_CIV5D_DATA'!B:AS,15,FALSE) -> • | M96: =VLOOKUP(B96,'26MY_CIV5D_DATA'!B:AS,16,FALSE) -> • | N96: =VLOOKUP($B96,'26MY_CIV5D_DATA'!$B:$AS,17,FALSE) -> 0 | O96: =VLOOKUP(B96,'26MY_CIV5D_DATA'!B:AS,18,FALSE) -> • | P96: =VLOOKUP(B96,'26MY_CIV5D_DATA'!B:AS,19,FALSE) -> • | Q96: =IF(VLOOKUP(B96,'26MY_CIV5D_DATA'!B:AS,21,FALSE)="","",VLOOKUP(B96,'26MY_CIV5D_DATA'!B:AS,21,FALSE)) -> Un (1) seul porte-vélo permis sur le porte-bagages de toit. Porte-bagages de toit requis.
B97: 08L20-E09-101C | C97: =VLOOKUP(B97,'26MY_CIV5D_DATA'!B:AS,4,FALSE) -> Panier de toit | D97: =B97 -> 08L20-E09-101C | E97: =VLOOKUP(B97,'26MY_CIV5D_DATA'!B:AS,9,FALSE) -> 586 | F97: =VLOOKUP(B97,'26MY_CIV5D_DATA'!B:AS,10,FALSE) -> 977 | G97: =VLOOKUP(B97,'26MY_CIV5D_DATA'!B:AS,7,FALSE) -> 0.4 | H97: =VLOOKUP(B97,'26MY_CIV5D_DATA'!B:AS,11,FALSE) -> 1049.4 | I97: =VLOOKUP(B97,'26MY_CIV5D_DATA'!B:AS,12,FALSE) -> 0 | J97: =VLOOKUP(B97,'26MY_CIV5D_DATA'!B:AS,13,FALSE) -> 0 | K97: =VLOOKUP($B97,'26MY_CIV5D_DATA'!$B:$AS,14,FALSE) -> 0 | L97: =VLOOKUP(B97,'26MY_CIV5D_DATA'!B:AS,15,FALSE) -> • | M97: =VLOOKUP(B97,'26MY_CIV5D_DATA'!B:AS,16,FALSE) -> • | N97: =VLOOKUP($B97,'26MY_CIV5D_DATA'!$B:$AS,17,FALSE) -> 0 | O97: =VLOOKUP(B97,'26MY_CIV5D_DATA'!B:AS,18,FALSE) -> • | P97: =VLOOKUP(B97,'26MY_CIV5D_DATA'!B:AS,19,FALSE) -> • | Q97: =IF(VLOOKUP(B97,'26MY_CIV5D_DATA'!B:AS,21,FALSE)="","",VLOOKUP(B97,'26MY_CIV5D_DATA'!B:AS,21,FALSE)) -> Ensemble de fixation de panier de toit (nécessaire de montage) et porte-bagages de toit requis.
B98: 08L20-E09-100D | C98: =VLOOKUP(B98,'26MY_CIV5D_DATA'!B:AS,4,FALSE) -> Ensemble de fixation de panier de toit | D98: =B98 -> 08L20-E09-100D | E98: =VLOOKUP(B98,'26MY_CIV5D_DATA'!B:AS,9,FALSE) -> 17 | F98: =VLOOKUP(B98,'26MY_CIV5D_DATA'!B:AS,10,FALSE) -> 28 | G98: =VLOOKUP(B98,'26MY_CIV5D_DATA'!B:AS,7,FALSE) -> 0 | H98: =VLOOKUP(B98,'26MY_CIV5D_DATA'!B:AS,11,FALSE) -> 28 | I98: =VLOOKUP(B98,'26MY_CIV5D_DATA'!B:AS,12,FALSE) -> 0 | J98: =VLOOKUP(B98,'26MY_CIV5D_DATA'!B:AS,13,FALSE) -> 0 | K98: =VLOOKUP($B98,'26MY_CIV5D_DATA'!$B:$AS,14,FALSE) -> 0 | L98: =VLOOKUP(B98,'26MY_CIV5D_DATA'!B:AS,15,FALSE) -> • | M98: =VLOOKUP(B98,'26MY_CIV5D_DATA'!B:AS,16,FALSE) -> • | N98: =VLOOKUP($B98,'26MY_CIV5D_DATA'!$B:$AS,17,FALSE) -> 0 | O98: =VLOOKUP(B98,'26MY_CIV5D_DATA'!B:AS,18,FALSE) -> • | P98: =VLOOKUP(B98,'26MY_CIV5D_DATA'!B:AS,19,FALSE) -> •
B99: 08F01-T20-XXXX | C99: =VLOOKUP(B99,'26MY_CIV5D_DATA'!B:AS,4,FALSE) -> Déflecteur de bas de caisse avant
B100: 08F01-T20-130A | C100: =VLOOKUP(B100,'26MY_CIV5D_DATA'!B:AS,4,FALSE) -> Blanc platine nacré (NH-883P) | D100: =B100 -> 08F01-T20-130A | E100: =VLOOKUP(B100,'26MY_CIV5D_DATA'!B:AS,9,FALSE) -> 262 | F100: =VLOOKUP(B100,'26MY_CIV5D_DATA'!B:AS,10,FALSE) -> 437 | G100: =VLOOKUP(B100,'26MY_CIV5D_DATA'!B:AS,7,FALSE) -> 1 | H100: =VLOOKUP(B100,'26MY_CIV5D_DATA'!B:AS,11,FALSE) -> 618 | I100: =VLOOKUP(B100,'26MY_CIV5D_DATA'!B:AS,12,FALSE) -> 0 | J100: =VLOOKUP(B100,'26MY_CIV5D_DATA'!B:AS,13,FALSE) -> 0 | K100: =VLOOKUP($B100,'26MY_CIV5D_DATA'!$B:$AS,14,FALSE) -> 0 | L100: =VLOOKUP(B100,'26MY_CIV5D_DATA'!B:AS,15,FALSE) -> • | M100: =VLOOKUP(B100,'26MY_CIV5D_DATA'!B:AS,16,FALSE) -> • | N100: =VLOOKUP($B100,'26MY_CIV5D_DATA'!$B:$AS,17,FALSE) -> 0 | O100: =VLOOKUP(B100,'26MY_CIV5D_DATA'!B:AS,18,FALSE) -> • | P100: =VLOOKUP(B100,'26MY_CIV5D_DATA'!B:AS,19,FALSE) -> N/A | Q100: =IF(VLOOKUP(B100,'26MY_CIV5D_DATA'!B:AS,21,FALSE)="","",VLOOKUP(B100,'26MY_CIV5D_DATA'!B:AS,21,FALSE))
B101: 08F01-T20-1Z0A | C101: =VLOOKUP(B101,'26MY_CIV5D_DATA'!B:AS,4,FALSE) -> Refl et solaire argent métallisé (NH-932M) | D101: =B101 -> 08F01-T20-1Z0A | E101: =VLOOKUP(B101,'26MY_CIV5D_DATA'!B:AS,9,FALSE) -> 262 | F101: =VLOOKUP(B101,'26MY_CIV5D_DATA'!B:AS,10,FALSE) -> 437 | G101: =VLOOKUP(B101,'26MY_CIV5D_DATA'!B:AS,7,FALSE) -> 1 | H101: =VLOOKUP(B101,'26MY_CIV5D_DATA'!B:AS,11,FALSE) -> 618 | I101: =VLOOKUP(B101,'26MY_CIV5D_DATA'!B:AS,12,FALSE) -> 0 | J101: =VLOOKUP(B101,'26MY_CIV5D_DATA'!B:AS,13,FALSE) -> 0 | K101: =VLOOKUP($B101,'26MY_CIV5D_DATA'!$B:$AS,14,FALSE) -> 0 | L101: =VLOOKUP(B101,'26MY_CIV5D_DATA'!B:AS,15,FALSE) -> • | M101: =VLOOKUP(B101,'26MY_CIV5D_DATA'!B:AS,16,FALSE) -> • | N101: =VLOOKUP($B101,'26MY_CIV5D_DATA'!$B:$AS,17,FALSE) -> 0 | O101: =VLOOKUP(B101,'26MY_CIV5D_DATA'!B:AS,18,FALSE) -> • | P101: =VLOOKUP(B101,'26MY_CIV5D_DATA'!B:AS,19,FALSE) -> N/A
B102: 08F01-T20-170A | C102: =VLOOKUP(B102,'26MY_CIV5D_DATA'!B:AS,4,FALSE) -> Gris météore nacré (NH-904M) | D102: =B102 -> 08F01-T20-170A | E102: =VLOOKUP(B102,'26MY_CIV5D_DATA'!B:AS,9,FALSE) -> 262 | F102: =VLOOKUP(B102,'26MY_CIV5D_DATA'!B:AS,10,FALSE) -> 437 | G102: =VLOOKUP(B102,'26MY_CIV5D_DATA'!B:AS,7,FALSE) -> 1 | H102: =VLOOKUP(B102,'26MY_CIV5D_DATA'!B:AS,11,FALSE) -> 618 | I102: =VLOOKUP(B102,'26MY_CIV5D_DATA'!B:AS,12,FALSE) -> 0 | J102: =VLOOKUP(B102,'26MY_CIV5D_DATA'!B:AS,13,FALSE) -> 0 | K102: =VLOOKUP($B102,'26MY_CIV5D_DATA'!$B:$AS,14,FALSE) -> 0 | L102: =VLOOKUP(B102,'26MY_CIV5D_DATA'!B:AS,15,FALSE) -> N/A | M102: =VLOOKUP(B102,'26MY_CIV5D_DATA'!B:AS,16,FALSE) -> • | N102: =VLOOKUP($B102,'26MY_CIV5D_DATA'!$B:$AS,17,FALSE) -> 0 | O102: =VLOOKUP(B102,'26MY_CIV5D_DATA'!B:AS,18,FALSE) -> N/A | P102: =VLOOKUP(B102,'26MY_CIV5D_DATA'!B:AS,19,FALSE) -> N/A
B103: 08F01-T20-180A | C103: =VLOOKUP(B103,'26MY_CIV5D_DATA'!B:AS,4,FALSE) -> Noir cristal nacré (NH-731P) | D103: =B103 -> 08F01-T20-180A | E103: =VLOOKUP(B103,'26MY_CIV5D_DATA'!B:AS,9,FALSE) -> 262 | F103: =VLOOKUP(B103,'26MY_CIV5D_DATA'!B:AS,10,FALSE) -> 437 | G103: =VLOOKUP(B103,'26MY_CIV5D_DATA'!B:AS,7,FALSE) -> 1 | H103: =VLOOKUP(B103,'26MY_CIV5D_DATA'!B:AS,11,FALSE) -> 618 | I103: =VLOOKUP(B103,'26MY_CIV5D_DATA'!B:AS,12,FALSE) -> 0 | J103: =VLOOKUP(B103,'26MY_CIV5D_DATA'!B:AS,13,FALSE) -> 0 | K103: =VLOOKUP($B103,'26MY_CIV5D_DATA'!$B:$AS,14,FALSE) -> 0 | L103: =VLOOKUP(B103,'26MY_CIV5D_DATA'!B:AS,15,FALSE) -> • | M103: =VLOOKUP(B103,'26MY_CIV5D_DATA'!B:AS,16,FALSE) -> • | N103: =VLOOKUP($B103,'26MY_CIV5D_DATA'!$B:$AS,17,FALSE) -> 0 | O103: =VLOOKUP(B103,'26MY_CIV5D_DATA'!B:AS,18,FALSE) -> • | P103: =VLOOKUP(B103,'26MY_CIV5D_DATA'!B:AS,19,FALSE) -> N/A
B104: 08F01-T20-190A | C104: =VLOOKUP(B104,'26MY_CIV5D_DATA'!B:AS,4,FALSE) -> Rouge rallye (R-513) | D104: =B104 -> 08F01-T20-190A | E104: =VLOOKUP(B104,'26MY_CIV5D_DATA'!B:AS,9,FALSE) -> 262 | F104: =VLOOKUP(B104,'26MY_CIV5D_DATA'!B:AS,10,FALSE) -> 437 | G104: =VLOOKUP(B104,'26MY_CIV5D_DATA'!B:AS,7,FALSE) -> 1 | H104: =VLOOKUP(B104,'26MY_CIV5D_DATA'!B:AS,11,FALSE) -> 618 | I104: =VLOOKUP(B104,'26MY_CIV5D_DATA'!B:AS,12,FALSE) -> 0 | J104: =VLOOKUP(B104,'26MY_CIV5D_DATA'!B:AS,13,FALSE) -> 0 | K104: =VLOOKUP($B104,'26MY_CIV5D_DATA'!$B:$AS,14,FALSE) -> 0 | L104: =VLOOKUP(B104,'26MY_CIV5D_DATA'!B:AS,15,FALSE) -> N/A | M104: =VLOOKUP(B104,'26MY_CIV5D_DATA'!B:AS,16,FALSE) -> • | N104: =VLOOKUP($B104,'26MY_CIV5D_DATA'!$B:$AS,17,FALSE) -> 0 | O104: =VLOOKUP(B104,'26MY_CIV5D_DATA'!B:AS,18,FALSE) -> • | P104: =VLOOKUP(B104,'26MY_CIV5D_DATA'!B:AS,19,FALSE) -> N/A
B105: 08F01-T20-1U0A | C105: =VLOOKUP(B105,'26MY_CIV5D_DATA'!B:AS,4,FALSE) -> Bleu turbo nacré (B-637P) | D105: =B105 -> 08F01-T20-1U0A | E105: =VLOOKUP(B105,'26MY_CIV5D_DATA'!B:AS,9,FALSE) -> 262 | F105: =VLOOKUP(B105,'26MY_CIV5D_DATA'!B:AS,10,FALSE) -> 437 | G105: =VLOOKUP(B105,'26MY_CIV5D_DATA'!B:AS,7,FALSE) -> 1 | H105: =VLOOKUP(B105,'26MY_CIV5D_DATA'!B:AS,11,FALSE) -> 618 | I105: =VLOOKUP(B105,'26MY_CIV5D_DATA'!B:AS,12,FALSE) -> 0 | J105: =VLOOKUP(B105,'26MY_CIV5D_DATA'!B:AS,13,FALSE) -> 0 | K105: =VLOOKUP($B105,'26MY_CIV5D_DATA'!$B:$AS,14,FALSE) -> 0 | L105: =VLOOKUP(B105,'26MY_CIV5D_DATA'!B:AS,15,FALSE) -> N/A | M105: =VLOOKUP(B105,'26MY_CIV5D_DATA'!B:AS,16,FALSE) -> N/A | N105: =VLOOKUP($B105,'26MY_CIV5D_DATA'!$B:$AS,17,FALSE) -> 0 | O105: =VLOOKUP(B105,'26MY_CIV5D_DATA'!B:AS,18,FALSE) -> • | P105: =VLOOKUP(B105,'26MY_CIV5D_DATA'!B:AS,19,FALSE) -> N/A
B106: 08F02-T47-XXX | C106: =VLOOKUP(B106,'26MY_CIV5D_DATA'!B:AS,4,FALSE) -> Déflecteur de hayon - HPD
B107: 08F02-T47-130 | C107: =VLOOKUP(B107,'26MY_CIV5D_DATA'!B:AS,4,FALSE) -> Blanc platine nacré (NH-883P) | D107: =B107 -> 08F02-T47-130 | E107: =VLOOKUP(B107,'26MY_CIV5D_DATA'!B:AS,9,FALSE) -> 472 | F107: =VLOOKUP(B107,'26MY_CIV5D_DATA'!B:AS,10,FALSE) -> 787 | G107: =VLOOKUP(B107,'26MY_CIV5D_DATA'!B:AS,7,FALSE) -> 1.2 | H107: =VLOOKUP(B107,'26MY_CIV5D_DATA'!B:AS,11,FALSE) -> 1004.2 | I107: =VLOOKUP(B107,'26MY_CIV5D_DATA'!B:AS,12,FALSE) -> 0 | J107: =VLOOKUP(B107,'26MY_CIV5D_DATA'!B:AS,13,FALSE) -> 0 | K107: =VLOOKUP($B107,'26MY_CIV5D_DATA'!$B:$AS,14,FALSE) -> 0 | L107: =VLOOKUP(B107,'26MY_CIV5D_DATA'!B:AS,15,FALSE) -> • | M107: =VLOOKUP(B107,'26MY_CIV5D_DATA'!B:AS,16,FALSE) -> • | N107: =VLOOKUP($B107,'26MY_CIV5D_DATA'!$B:$AS,17,FALSE) -> 0 | O107: =VLOOKUP(B107,'26MY_CIV5D_DATA'!B:AS,18,FALSE) -> • | P107: =VLOOKUP(B107,'26MY_CIV5D_DATA'!B:AS,19,FALSE) -> N/A | Q107: =IF(VLOOKUP(B107,'26MY_CIV5D_DATA'!B:AS,21,FALSE)="","",VLOOKUP(B107,'26MY_CIV5D_DATA'!B:AS,21,FALSE))
B108: 08F02-T47-1Z0 | C108: =VLOOKUP(B108,'26MY_CIV5D_DATA'!B:AS,4,FALSE) -> Refl et solaire argent métallisé (NH-932M) | D108: =B108 -> 08F02-T47-1Z0 | E108: =VLOOKUP(B108,'26MY_CIV5D_DATA'!B:AS,9,FALSE) -> 472 | F108: =VLOOKUP(B108,'26MY_CIV5D_DATA'!B:AS,10,FALSE) -> 787 | G108: =VLOOKUP(B108,'26MY_CIV5D_DATA'!B:AS,7,FALSE) -> 1.2 | H108: =VLOOKUP(B108,'26MY_CIV5D_DATA'!B:AS,11,FALSE) -> 1004.2 | I108: =VLOOKUP(B108,'26MY_CIV5D_DATA'!B:AS,12,FALSE) -> 0 | J108: =VLOOKUP(B108,'26MY_CIV5D_DATA'!B:AS,13,FALSE) -> 0 | K108: =VLOOKUP($B108,'26MY_CIV5D_DATA'!$B:$AS,14,FALSE) -> 0 | L108: =VLOOKUP(B108,'26MY_CIV5D_DATA'!B:AS,15,FALSE) -> • | M108: =VLOOKUP(B108,'26MY_CIV5D_DATA'!B:AS,16,FALSE) -> N/A | N108: =VLOOKUP($B108,'26MY_CIV5D_DATA'!$B:$AS,17,FALSE) -> 0 | O108: =VLOOKUP(B108,'26MY_CIV5D_DATA'!B:AS,18,FALSE) -> N/A | P108: =VLOOKUP(B108,'26MY_CIV5D_DATA'!B:AS,19,FALSE) -> N/A
B109: 08F02-T47-170 | C109: =VLOOKUP(B109,'26MY_CIV5D_DATA'!B:AS,4,FALSE) -> Gris météore nacré (NH-904M) | D109: =B109 -> 08F02-T47-170 | E109: =VLOOKUP(B109,'26MY_CIV5D_DATA'!B:AS,9,FALSE) -> 472 | F109: =VLOOKUP(B109,'26MY_CIV5D_DATA'!B:AS,10,FALSE) -> 787 | G109: =VLOOKUP(B109,'26MY_CIV5D_DATA'!B:AS,7,FALSE) -> 1.2 | H109: =VLOOKUP(B109,'26MY_CIV5D_DATA'!B:AS,11,FALSE) -> 1004.2 | I109: =VLOOKUP(B109,'26MY_CIV5D_DATA'!B:AS,12,FALSE) -> 0 | J109: =VLOOKUP(B109,'26MY_CIV5D_DATA'!B:AS,13,FALSE) -> 0 | K109: =VLOOKUP($B109,'26MY_CIV5D_DATA'!$B:$AS,14,FALSE) -> 0 | L109: =VLOOKUP(B109,'26MY_CIV5D_DATA'!B:AS,15,FALSE) -> N/A | M109: =VLOOKUP(B109,'26MY_CIV5D_DATA'!B:AS,16,FALSE) -> • | N109: =VLOOKUP($B109,'26MY_CIV5D_DATA'!$B:$AS,17,FALSE) -> 0 | O109: =VLOOKUP(B109,'26MY_CIV5D_DATA'!B:AS,18,FALSE) -> N/A | P109: =VLOOKUP(B109,'26MY_CIV5D_DATA'!B:AS,19,FALSE) -> N/A
B110: 08F02-T47-180 | C110: =VLOOKUP(B110,'26MY_CIV5D_DATA'!B:AS,4,FALSE) -> Noir cristal nacré (NH-731P) | D110: =B110 -> 08F02-T47-180 | E110: =VLOOKUP(B110,'26MY_CIV5D_DATA'!B:AS,9,FALSE) -> 472 | F110: =VLOOKUP(B110,'26MY_CIV5D_DATA'!B:AS,10,FALSE) -> 787 | G110: =VLOOKUP(B110,'26MY_CIV5D_DATA'!B:AS,7,FALSE) -> 1.2 | H110: =VLOOKUP(B110,'26MY_CIV5D_DATA'!B:AS,11,FALSE) -> 1004.2 | I110: =VLOOKUP(B110,'26MY_CIV5D_DATA'!B:AS,12,FALSE) -> 0 | J110: =VLOOKUP(B110,'26MY_CIV5D_DATA'!B:AS,13,FALSE) -> 0 | K110: =VLOOKUP($B110,'26MY_CIV5D_DATA'!$B:$AS,14,FALSE) -> 0 | L110: =VLOOKUP(B110,'26MY_CIV5D_DATA'!B:AS,15,FALSE) -> • | M110: =VLOOKUP(B110,'26MY_CIV5D_DATA'!B:AS,16,FALSE) -> • | N110: =VLOOKUP($B110,'26MY_CIV5D_DATA'!$B:$AS,17,FALSE) -> 0 | O110: =VLOOKUP(B110,'26MY_CIV5D_DATA'!B:AS,18,FALSE) -> • | P110: =VLOOKUP(B110,'26MY_CIV5D_DATA'!B:AS,19,FALSE) -> N/A
B111: 08F02-T47-190 | C111: =VLOOKUP(B111,'26MY_CIV5D_DATA'!B:AS,4,FALSE) -> Rouge rallye (R-513) | D111: =B111 -> 08F02-T47-190 | E111: =VLOOKUP(B111,'26MY_CIV5D_DATA'!B:AS,9,FALSE) -> 472 | F111: =VLOOKUP(B111,'26MY_CIV5D_DATA'!B:AS,10,FALSE) -> 787 | G111: =VLOOKUP(B111,'26MY_CIV5D_DATA'!B:AS,7,FALSE) -> 1.2 | H111: =VLOOKUP(B111,'26MY_CIV5D_DATA'!B:AS,11,FALSE) -> 1004.2 | I111: =VLOOKUP(B111,'26MY_CIV5D_DATA'!B:AS,12,FALSE) -> 0 | J111: =VLOOKUP(B111,'26MY_CIV5D_DATA'!B:AS,13,FALSE) -> 0 | K111: =VLOOKUP($B111,'26MY_CIV5D_DATA'!$B:$AS,14,FALSE) -> 0 | L111: =VLOOKUP(B111,'26MY_CIV5D_DATA'!B:AS,15,FALSE) -> N/A | M111: =VLOOKUP(B111,'26MY_CIV5D_DATA'!B:AS,16,FALSE) -> • | N111: =VLOOKUP($B111,'26MY_CIV5D_DATA'!$B:$AS,17,FALSE) -> 0 | O111: =VLOOKUP(B111,'26MY_CIV5D_DATA'!B:AS,18,FALSE) -> • | P111: =VLOOKUP(B111,'26MY_CIV5D_DATA'!B:AS,19,FALSE) -> N/A
B112: 08F02-T47-1U0 | C112: =VLOOKUP(B112,'26MY_CIV5D_DATA'!B:AS,4,FALSE) -> Bleu turbo nacré (B-637P) | D112: =B112 -> 08F02-T47-1U0 | E112: =VLOOKUP(B112,'26MY_CIV5D_DATA'!B:AS,9,FALSE) -> 472 | F112: =VLOOKUP(B112,'26MY_CIV5D_DATA'!B:AS,10,FALSE) -> 787 | G112: =VLOOKUP(B112,'26MY_CIV5D_DATA'!B:AS,7,FALSE) -> 1.2 | H112: =VLOOKUP(B112,'26MY_CIV5D_DATA'!B:AS,11,FALSE) -> 1004.2 | I112: =VLOOKUP(B112,'26MY_CIV5D_DATA'!B:AS,12,FALSE) -> 0 | J112: =VLOOKUP(B112,'26MY_CIV5D_DATA'!B:AS,13,FALSE) -> 0 | K112: =VLOOKUP($B112,'26MY_CIV5D_DATA'!$B:$AS,14,FALSE) -> 0 | L112: =VLOOKUP(B112,'26MY_CIV5D_DATA'!B:AS,15,FALSE) -> N/A | M112: =VLOOKUP(B112,'26MY_CIV5D_DATA'!B:AS,16,FALSE) -> N/A | N112: =VLOOKUP($B112,'26MY_CIV5D_DATA'!$B:$AS,17,FALSE) -> 0 | O112: =VLOOKUP(B112,'26MY_CIV5D_DATA'!B:AS,18,FALSE) -> • | P112: =VLOOKUP(B112,'26MY_CIV5D_DATA'!B:AS,19,FALSE) -> N/A
B113: 08P05-T20-XXXX | C113: =VLOOKUP(B113,'26MY_CIV5D_DATA'!B:AS,4,FALSE) -> Moulure latérale
...

Sheet 26MY_CIV5D_SELL-EN
B3: 26MY Honda Civic Hatch
B4: 200
B6: POPULAR ACCESSORIES
B7: 20
B8: 150 | M8: #VALUE!
B10: 20 | C10: ='26MY_CIV5D_APP_EN'!$C$128 -> Floor Mats - All-Season | H10: ='26MY_CIV5D_APP_EN'!$C$131 -> Cargo Tray | M10: ='26MY_CIV5D_APP_EN'!$C$77 -> Black Emblem H-Mark
B11: 20 | C11: ='26MY_CIV5D_APP_EN'!$H$128 -> 266.1 | D11: =-PMT($D$29/52,5*52,C11) -> 1.2133891 | E11: /wk * | F11: =$C$29 -> (6.99%) | H11: ='26MY_CIV5D_APP_EN'!$H$131 -> 215.1 | I11: =-PMT($D$29/52,5*52,H11) -> 0.98083424 | J11: /wk * | K11: =$C$29 -> (6.99%) | M11: ='26MY_CIV5D_APP_EN'!$H$77 -> 249.7 | N11: =-PMT($D$29/52,5*52,M11) -> 1.1386067 | O11: /wk * | P11: =$C$29 -> (6.99%)
B13: 150
B15: 20 | C15: ='26MY_CIV5D_APP_EN'!$C$79 -> Door Visors - Black | H15: ='26MY_CIV5D_DATA'!$D$55 -> Body Side Moulding | M15: ='26MY_CIV5D_APP_EN'!$C$148 -> Illuminated Door Sill Trim | N15: Ambient Lighting, Blue | O15: Ambient Lighting, Blue | P15: Ambient Lighting, Blue
B16: 50 | C16: ='26MY_CIV5D_APP_FR'!$H$83 -> 435.5 | D16: =-PMT($D$29/52,5*52,C16) -> 1.9858359 | E16: /wk * | F16: =$C$29 -> (6.99%) | H16: ='26MY_CIV5D_DATA'!$L$55 -> 430.4 | I16: =-PMT($D$29/52,5*52,H16) -> 1.9625805 | J16: /wk * | K16: =$C$29 -> (6.99%) | M16: ='26MY_CIV5D_APP_EN'!$H$148 -> 626.1 | N16: =-PMT($D$29/52,5*52,M16) -> 2.8549527 | O16: /wk * | P16: =$C$29 -> (6.99%)
B18: 150
B20: 20 | C20: ='26MY_CIV5D_APP_EN'!$C$104 -> Tailgate Spoiler, HPD | H20: ='26MY_CIV5D_APP_EN'!$C$87 -> Roof Rack | M20: ='26MY_CIV5D_APP_EN'!$C$19 -> 16” Enkei M52 Wheels & Michelin X-ICE Snow Tire Package
B21: 50 | C21: ='26MY_CIV5D_APP_EN'!$H$105 -> 1004.2 | D21: =-PMT($D$29/52,5*52,C21) -> 4.5790504 | E21: /wk * | F21: =$C$29 -> (6.99%) | H21: ='26MY_CIV5D_APP_EN'!$H$87 -> 902.4 | I21: =-PMT($D$29/52,5*52,H21) -> 4.1148527 | J21: /wk * | K21: =$C$29 -> (6.99%) | M21: =SUM('26MY_CIV5D_APP_EN'!$H$19:$H$21) -> 2245.2 | N21: =-PMT($D$29/52,5*52,M21) -> 10.237885 | O21: /wk * | P21: =$C$29 -> (6.99%)
C23: Genuine Honda Accessories purchased with a new Honda vehicle include a 3 year / 60,000 km manufacturer's warranty.
C24: Vehicle accessories purchased after vehicle sale include a 1 year / 20,000km manufacturer's warranty.
B25: 20 | C25: *Prices shown include the cost of installation.
B26: 60 | C26: *For informational purposes only. Weekly amounts shown are estimated payments based on a 60 month finance contract at 6.99% APR (including the cost of installation). Applicable taxes and fees are extra. Accessories cannot be financed on their own and must be financed through Honda Canada Finance Inc., on approved credit, in conjunction with a Honda vehicle. Representative finance example: $350.00 financed at 6.99% APR equals $1.60 weekly for 60 months. 260 weekly payments required. Cost of borrowing is $64.80 for a total obligation of $414.80. Actual payment amounts will vary based on APR, finance contract term and cost of the applicable accessories. Conditions apply. See your Honda dealer for full details.
C27: *More customized weekly payment options & accessories can be seen on Honda.ca - Build & Price
B28: 20
B29: 18 | C29: (6.99%) | D29: 0.0699
B30: 7.5 | C30: 12 | D30: 8 | E30: 8 | F30: 10 | G30: 8.5 | H30: 12 | I30: 8 | J30: 8 | K30: 10 | L30: 8.5 | M30: 12 | N30: 8 | O30: 8 | P30: 10 | Q30: 7.5
B31: Publication Date: | C31: ='26MY_CIV5D_DATA'!$C$4 -> 46142 | D31: ='SELECT PROVINCE'!$A$23 -> All published prices, trim specifications, and availability are subject to change without prior notice. | P31: Province | Q31: ='SELECT PROVINCE'!$F$12 -> YT

Sheet 26MY_CIV5D_SELL-FR
B3: 26MY Honda Civic à Hayon
B4: 200
B6: ACCESSOIRES POPULAIRES
B7: 20
B8: 150 | M8: #VALUE!
B10: 20 | C10: ='26MY_CIV5D_APP_FR'!$C$131 -> Tapis toutes saisons | H10: ='26MY_CIV5D_APP_FR'!$C$134 -> Plateau de coffre | M10: ='26MY_CIV5D_APP_FR'!$C$81 -> Emblèmes « H » noirs
B11: 20 | C11: ='26MY_CIV5D_APP_FR'!$H$131 -> 266.1 | D11: =-PMT($D$29/52,5*52,C11) -> 1.2133891 | E11: /wk * | F11: =$C$29 -> (6.99%) | H11: ='26MY_CIV5D_APP_FR'!$H$134 -> 215.1 | I11: =-PMT($D$29/52,5*52,H11) -> 0.98083424 | J11: /wk * | K11: =$C$29 -> (6.99%) | M11: ='26MY_CIV5D_APP_FR'!$H$81 -> 249.7 | N11: =-PMT($D$29/52,5*52,M11) -> 1.1386067 | O11: /wk * | P11: =$C$29 -> (6.99%)
B13: 150
B15: 20 | C15: ='26MY_CIV5D_APP_FR'!$C$83 -> Déflecteurs de portières - noir | H15: ='26MY_CIV5D_DATA'!$E$55 -> Moulure latérale | M15: ='26MY_CIV5D_APP_FR'!$C$151 -> Garniture de seuil de portière illuminée | N15: Ambient Lighting, Blue | O15: Ambient Lighting, Blue | P15: Ambient Lighting, Blue
B16: 50 | C16: ='26MY_CIV5D_APP_FR'!$H$83 -> 435.5 | D16: =-PMT($D$29/52,5*52,C16) -> 1.9858359 | E16: /wk * | F16: =$C$29 -> (6.99%) | H16: ='26MY_CIV5D_DATA'!$L$55 -> 430.4 | I16: =-PMT($D$29/52,5*52,H16) -> 1.9625805 | J16: /wk * | K16: =$C$29 -> (6.99%) | M16: ='26MY_CIV5D_APP_FR'!$H$151 -> 626.1 | N16: =-PMT($D$29/52,5*52,M16) -> 2.8549527 | O16: /wk * | P16: =$C$29 -> (6.99%)
B18: 150
B20: 20 | C20: ='26MY_CIV5D_APP_FR'!$C$106 -> Déflecteur de hayon - HPD | H20: ='26MY_CIV5D_APP_FR'!$C$89 -> Porte-bagages de toit | M20: ='26MY_CIV5D_DATA'!$E$8 -> Ensemble de roues Enkei M52 de 16 po et de pneus Michelin X-ICE Snow
B21: 50 | C21: ='26MY_CIV5D_APP_FR'!$H$107 -> 1004.2 | D21: =-PMT($D$29/52,5*52,C21) -> 4.5790504 | E21: /wk * | F21: =$C$29 -> (6.99%) | H21: ='26MY_CIV5D_APP_FR'!$H$89 -> 902.4 | I21: =-PMT($D$29/52,5*52,H21) -> 4.1148527 | J21: /wk * | K21: =$C$29 -> (6.99%) | M21: =SUM('26MY_CIV5D_APP_EN'!$H$19:$H$21) -> 2245.2 | N21: =-PMT($D$29/52,5*52,M21) -> 10.237885 | O21: /wk * | P21: =$C$29 -> (6.99%)
C23: Les accessoires Honda d’origine achetés avec un véhicule Honda neuf incluent une garantie du fabricant de 3 ans ou 60 000 km.
C24: Les accessoires de véhicule achetés après la vente du véhicule incluent une garantie du fabricant de 1 an ou 20 000 km.
B25: 20 | C25: *Les prix indiqués incluent le coût d'installation.
B26: 60 | C26: *À titre d’information seulement. Les montants hebdomadaires indiqués sont des paiements estimés basés sur un contrat de financement de 60 mois à un taux annuel en pourcentage (TAP) de 6,99 % (coût d’installation compris). Taxes et frais applicables en sus. Les accessoires ne peuvent être financés seuls et doivent être financés par l’entremise de Honda Canada Finance Inc., sur approbation de crédit, conjointement avec un véhicule Honda. Exemple de financement représentatif : Un montant de 350,00 $ financé à un TAP de 6,99 % équivaut à un paiement hebdomadaire de 1,60 $ pendant 60 mois. 260 paiements hebdomadaires sont requis. Le coût d’emprunt est de 64,80 $, pour une obligation totale de 414,80 $. Le montant réel des paiements variera en fonction du TAP, de la période du contrat de financement et du coût des accessoires applicables. Certaines conditions s’appliquent. Veuillez visiter votre concessionnaire Honda pour obtenir tous les détails.
C27: *Vous pouvez voir d’autres options de paiements hebdomadaires personnalisés ainsi que des accessoires sur le site Honda.ca – Configuration et prix.
B28: 20
B29: 18 | C29: (6.99%) | D29: 0.0699
B30: 7.5 | C30: 12 | D30: 8 | E30: 8 | F30: 10 | G30: 8.5 | H30: 12 | I30: 8 | J30: 8 | K30: 10 | L30: 8.5 | M30: 12 | N30: 8 | O30: 8 | P30: 10 | Q30: 7.5
B31: Date de publication: | C31: ='26MY_CIV5D_DATA'!$C$4 -> 46142 | D31: Tout prix, spécifications de versions et disponibilté d'accessoires publiés sont sujets à changer sans pré-avis. | P31: Province | Q31: ='26MY_CIV5D_APP_FR'!$H$11 -> YT
