Workbook
Name prov_cd: 'SELECT PROVINCE'!$B$1
Name province_codes: 'SELECT PROVINCE'!$B$6:$B$16
Name rate_table: 'SELECT PROVINCE'!$B$6:$C$16

Sheet 26MY_ACCORD_DATA
B1: 1 | C1: 2 | D1: 3 | E1: 4 | F1: 5 | G1: 6 | H1: 23 | I1: 24 | J1: 25 | K1: 26 | L1: 27 | M1: 28 | O1: 29 | P1: 30 | Q1: 31 | R1: 32 | T1: 33 | U1: 34 | V1: 35 | W1: 9 | X1: 7 | Y1: 8 | Z1: 8 | AA1: 8 | AB1: 8 | AC1: 8 | AD1: 8 | AE1: 8 | AF1: 8 | AG1: 10 | AH1: 11 | AI1: 12 | AJ1: 13 | AK1: 14 | AL1: 15 | AM1: 16 | AN1: 17 | AO1: 18 | AP1: 19 | AQ1: 20 | AR1: 21 | AS1: 22
B2: Model Name | C2: Accord | M2: = | P2: N/A | Q2: S | R2: E | T2: T | X2: Yes
B3: Model Year | C3: 2026
B4: Publication Date | C4: 46113 | D4: yyyy/mm/dd | M4: * if it's "N/A" or "S" do not show on trim
M5: Trim Application*
B6: PARTS | C6: HAC | L6: =prov_cd -> QC | O6: SE | Q6: Sport -L Hybride | R6: Touring Hybride | X6: Images | AG6: Wheels | AH6: Charging | AI6: Featured | AJ6: Included | AK6: Accessories
B7: Part Number / Kit Part Number | C7: Part Number | D7: Item Name English | E7: Item Name French | F7: Description English | G7: Description French | H7: FRT | I7: Residual-ized $ | J7: Dealer Net | K7: List Price | L7: Install Price | O7: SE | Q7: Sport -L Hybrid | R7: Touring Hybrid | U7: Comments English | V7: Comments French | W7: Display Order | X7: SiteCore | Y7: Overlay 1 | Z7: Overlay 2 | AA7: Overlay 3 | AB7: Overlay 4 | AC7: Overlay 5 | AD7: Overlay 6 | AE7: Overlay 7 | AF7: Overlay 8 | AK7: Safety & Exterior Protection | AL7: Winter Season | AM7: Exterior & Interior Utility | AN7: Interior Styling | AO7: Exterior Styling | AP7: Misc-ellaneous | AR7: Dependancies | AS7: Exclusions
B8: 23ACC-PRO-PK | C8: =B8 -> 23ACC-PRO-PK | D8: Protection Package | E8: Ensemble de protection | F8: Package includes: All-Season Floor Mats and Trunk Tray. | G8: L’ensemble inclut : Tapis toutes saisons et plateau de coffre. | H8: =H69+H70 -> 0.2 | J8: =(J69+J70)*0.9 -> 273.6 | K8: =K69+K70 -> 507 | L8: =K8+(H8*VLOOKUP(prov_cd,rate_table,2,FALSE)) -> 537.4 | O8: • | Q8: • | R8: • | W8: 1 | X8: Yes | AI8: • | AM8: • | AS8: 23ACC-PRO-PKA Protection Package Advance 08P17-30A-110 All Season Floor Mats 08U45-30A-100 Trunk Tray
B9: 23ACC-PRO-PKA | C9: =B9 -> 23ACC-PRO-PKA | D9: Protection Package Advance | E9: Ensemble de protection avancée | F9: Keep your car protected from the elements, inside and out. Includes All Season Floor Mats, Trunk Tray, Rear Splash Guards and Cargo Net. Packaged together with a 10% discount. | G9: Protégez votre voiture contre les intempéries, à l’intérieur comme à l’extérieur. Comprend les tapis toutes saisons, le plateau de coffre, les garde-boue arrière et le filet de cargaison. Offerts en ensemble avec une réduction de 10 %. | H9: =H69+H70+H40+H72 -> 1 | J9: =(J69+J70+J40+J72)*0.9 -> 342.891 | K9: =(K69+K70+K40+K72)*0.9 -> 583.2 | L9: =K9+(H9*VLOOKUP(prov_cd,rate_table,2,FALSE)) -> 735.2 | O9: • | Q9: • | R9: N/A | U9: 10% Discount Applied. | V9: Rabais de 10 % appliqué. | W9: 2 | X9: Yes | AI9: • | AM9: • | AS9: 23ACC-PRO-PK Protection Package 08P17-30A-110 All Season Floor Mats 08U45-30A-100 Trunk Tray 08L96-TVA-300 Cargo Net 08P09-30A-300 Rear Splash Gaurds
A10: NEW | B10: 26ACC-BLK-EMB | C10: =B10 -> 26ACC-BLK-EMB | D10: Black Emblem Set - Touring | E10: Ensemble d’emblèmes noirs – Touring | F10: Includes Rear "H" mark, "Accord," "Hybrid" and "Touring" black emblems. Packaged together with a 5% discount. | G10: Comprend les emblèmes noirs « H » arrière, « Accord » , « Hybride » et « Touring ». Offerts en ensemble avec une réduction de 5%. | H10: =SUM(H24:H27) -> 0.9 | J10: =(J24+J25+J26+J27)*0.95 -> 155.8 | K10: =(K24+K25+K26+K27)*0.95 -> 260.3 | L10: =K10+(H10*VLOOKUP(prov_cd,rate_table,2,FALSE)) -> 397.1 | O10: N/A | Q10: N/A | R10: • | U10: 5% Discount Applied. | V10: Rabais de 5 % appliqué. | W10: 3 | X10: Yes | AI10: • | AO10: • | AS10: 08F20-30A-100CBlack Emblem Rear "H" mark 08F20-30A-100DBlack Emblem, Accord 08F20-3A0-100CBlack Emblem, Touring 08F20-T20-100B Black Emblem, Hybrid
B11: 23ACC-ARO-EX | C11: =B11 -> 23ACC-ARO-EX | D11: Aero Kit - SE Trim | E11: Ensemble Aero – Version SE | F11: The Areo Kit adds a sporty and custom look to your Accord. Includes: Side Underbody Spoiler, Front & Rear Aero Bumpers, Door Mirror Cover, Lower Intake Accents and Black Decklid Spoiler. Packaged togther with a 10% discount. Requires the Front Splash Guards to be removed. | G11: L’ensemble Aero confère une allure sport et personnalisée à votre Accord. Inclus : Déflecteur latéral de bas de caisse, déflecteurs Aero de pare-chocs avant et arrière, couvercle de rétroviseur de portière, éléments visuels d’admission d’air et déflecteur de coffre noir. Offerts en ensemble avec une réduction de 10 %. Nécessite le retrait des garde-boue avant. | H11: =H31+H32+H33+H63+H34 -> 3.5 | J11: =(J31+J32+J33+J63+J34)*0.9 -> 1555.2 | K11: =(K31+K32+K33+K63+K34)*0.9 -> 2591.1 | L11: =K11+(H11*VLOOKUP(prov_cd,rate_table,2,FALSE)) -> 3123.1 | O11: • | Q11: N/A | R11: N/A | U11: 10% Discount Applied Decklid Spoiler - Crystal Black Pearl (NH-731P) colour | V11: Rabais de 10 % est appliqué Déflecteur arrière de coffre - Noir cristal nacré couleur (NH-731P) | W11: 4 | X11: Yes | AI11: • | AO11: • | AS11: 08F04-30A-1F0 Side Underbody Spoiler 08P98-30A-1F0 Front Aero Bumper 08P99-30A-1F0 Rear Aero Bumper 08R06-30A-110 Door Mirror Covers & Lower Intake Accents 08F10-30A-110 Decklid Spoiler
B12: 23ACC-ARO-SPHY | C12: =B12 -> 23ACC-ARO-SPHY | D12: Aero Kit - Sport Trim | E12: Ensemble Aero – Version Sport | F12: The Areo Kit adds a sporty and custom look to your Accord. Includes: Side Underbody Spoiler, Front & Rear Aero Bumpers, Door Mirror Cover and Lower Intake Accents. Packaged togther with a 10% discount. Requires the Front Splash Guards to be removed. | G12: L’ensemble Aero confère une allure sport et personnalisée à votre Accord. Inclus : Déflecteur latéral de bas de caisse, déflecteurs Aero de pare-chocs avant et arrière, couvercle de rétroviseur de portière et éléments visuels d’admission d’air. Offerts en ensemble avec une réduction de 10 %. Nécessite le retrait des garde-boue avant. | H12: =H31+H32+H33 -> 1.8 | J12: =(J31+J32+J33)*0.9 -> 1018.8 | K12: =(K31+K32+K33)*0.9 -> 1697.4 | L12: =K12+(H12*VLOOKUP(prov_cd,rate_table,2,FALSE)) -> 1971 | O12: N/A | Q12: • | R12: N/A | U12: 10% Discount Applied Sport Trim already comes standard with Decklid Spoiler | V12: Rabais de 10 % est appliqué Version Sport Hybride est livrée de série avec le becquet de bas de caisse, arrière | W12: 5 | X12: Yes | AI12: • | AO12: • | AS12: 08F04-30A-1F0 Side Underbody Spoiler 08P98-30A-1F0 Front Aero Bumper 08P99-30A-1F0 Rear Aero Bumper 08R06-30A-110 Door Mirror Covers & Lower Intake Accents
B13: 23ACC-ARO-TRHY | C13: =B13 -> 23ACC-ARO-TRHY | D13: Aero Kit - Touring Trim | E13: Ensemble Aero – Version Touring | F13: The Areo Kit adds a sporty and custom look to your Accord. Includes: Side Underbody Spoiler, Front & Rear Aero Bumpers, Door Mirror Cover, Lower Intake Accents and Black Decklid Spoiler. Packaged togther with a 10% discount. Requires the Front Splash Guards to be removed. | G13: L’ensemble Aero confère une allure sport et personnalisée à votre Accord. Inclus : Déflecteur latéral de bas de caisse, déflecteurs Aero de pare-chocs avant et arrière, couvercle de rétroviseur de portière, éléments visuels d’admission d’air et déflecteur de coffre noir. Offerts en ensemble avec une réduction de 10 %. Nécessite le retrait des garde-boue avant. | H13: =H31+H32+H33+H63+H35 -> 3.5 | J13: =(J31+J32+J33+J63+J35)*0.9 -> 1555.2 | K13: =(K31+K32+K33+K63+K35)*0.9 -> 2591.1 | L13: =K13+(H13*VLOOKUP(prov_cd,rate_table,2,FALSE)) -> 3123.1 | O13: N/A | Q13: N/A | R13: • | U13: 10% Discount Applied Decklid Spoiler - Crystal Black Pearl (NH-731P) colour | V13: Rabais de 10 % est appliqué Déflecteur arrière de coffre - Noir cristal nacré couleur (NH-731P) | W13: 6 | X13: Yes | AI13: • | AO13: • | AS13: 08F04-30A-1F0 Side Underbody Spoiler 08P98-30A-1F0 Front Aero Bumper 08P99-30A-1F0 Rear Aero Bumper 08R06-30A-110A Door Mirror Covers & Lower Intake Accents 08F10-30A-110 Decklid Spoiler
B14: 23ACC-COLD-PKP | C14: =B14 -> 23ACC-COLD-PKP | D14: Cold Weather Package | E14: Ensemble de temps froid | F14: Package includes: Engine Block Heater and Auto Battery Charger/Maintainer. Packaged together with a 5% discount. | G14: L’ensemble inclut : Chauffe-moteur et chargeur/mainteneur automatique de batterie de 12 V Optimate. Offerts en ensemble avec une remise de 5 %. | H14: =H82+H83 -> 1.2 | J14: =(J81+J83)*0.95 -> 226.1 | K14: =(K81+K83)*0.95 -> 377.15 | L14: =K14+(H14*VLOOKUP(prov_cd,rate_table,2,FALSE)) -> 559.55 | O14: • | Q14: N/A | R14: N/A | U14: 5% Discount Applied. | V14: Rabais de 5 % appliqué. | W14: 7 | X14: Yes | AI14: • | AL14: • | AS14: 08T44-30B-300A Engine Block Heater 31670-BMS-004H Optimate 12V Auto Battery Charger/Maintainer
B15: 23ACC-COLD-PKH | C15: =B15 -> 23ACC-COLD-PKH | D15: Cold Weather Package | E15: Ensemble de temps froid | F15: Package includes: Engine Block Heater and Auto Battery Charger/Maintainer. Packaged together with a 5% discount. | G15: L’ensemble inclut : Chauffe-moteur et chargeur/mainteneur automatique de batterie de 12 V Optimate. Offerts en ensemble avec une remise de 5 %. | H15: =H81+H83 -> 1.2 | J15: =(J82+J83)*0.95 -> 251.75 | K15: =(K82+K83)*0.95 -> 419.9 | L15: =K15+(H15*VLOOKUP(prov_cd,rate_table,2,FALSE)) -> 602.3 | O15: N/A | Q15: • | R15: • | U15: 5% Discount Applied. | V15: Rabais de 5 % appliqué. | W15: 8 | X15: Yes | AI15: • | AL15: • | AS15: 08T44-30A-300A Engine Block Heater 31670-BMS-004H Optimate 12V Auto Battery Charger/Maintainer
B18: 08W17-PC4-300 | C18: =B18 -> 08W17-PC4-300 | D18: 17" Steel Wheels | E18: 17 po en acier de roues | F18: Steel wheels offer great value and allow you to save your factory wheels from our harsh Canadian winters. Price listed excludes winter tires and installation. Set of 4. | G18: Des roues en acier offrent un excellent rapport qualité-prix et vous permettent de préserver les roues d’origine de votre véhicule de nos rigoureux hivers canadiens. Le prix indiqué exclut les pneus d'hiver et l'installation. Ensemble de quatre. | H18: 1.6 | J18: =VLOOKUP(B18,'[1]MASTER PART LIST'!$B:$C,2,FALSE)*4 -> 376.4 | K18: =VLOOKUP(B18,'[1]MASTER PART LIST'!$B:$D,3,FALSE)*4 -> 627.28 | L18: =K18+(H18*VLOOKUP(prov_cd,rate_table,2,FALSE)) -> 870.48 | O18: T | Q18: T | R18: T | U18: Priced as a set of 4 wheels. Tires sold separately. | V18: Prix pour un ensemble de 4 roues. Pneus vendus séparément. | W18: 10 | AG18: •
B19: 08W19-30A-300 | C19: =B19 -> 08W19-30A-300 | D19: 19" HPD Alloy Wheels, Black | E19: Jantes de 19 pouces HPD en alliage noir | F19: Attract even more attention with these stunning 19" HPD Black Alloy Wheels structurally matched to the original vehicle design so that handling remains undisturbed. Priced as a set of 4. Recommended tires sold separately. | G19: Attirez encore plus l’attention avec ces superbes jantes HPD de 19 pouces en alliage noir dont la structure est adaptée à la conception originale du véhicule afin que la maniabilité reste inchangée. Prix pour ensemble de 4. Pneus recommandés vendus séparément. | H19: 1.6 | J19: =VLOOKUP(B19,'[1]MASTER PART LIST'!$B:$C,2,FALSE)*4 -> 2628 | K19: =VLOOKUP(B19,'[1]MASTER PART LIST'!$B:$D,3,FALSE)*4 -> 3756 | L19: =K19+(H19*VLOOKUP(prov_cd,rate_table,2,FALSE)) -> 3999.2 | O19: E | Q19: E | R19: E | U19: Priced as a set of 4 wheels. Tires sold separately. | V19: Prix pour un ensemble de 4 roues. Pneus vendus séparément. | W19: 9 | AG19: •
B20: 08W42-S2A-101 | C20: =B20 -> 08W42-S2A-101 | D20: Wheel Locks - Black | E20: Écrous de roue antivols - Noirs | F20: A great way to help ensure that your wheels stay on your vehicle where they belong. | G20: Un excellent moyen de vous assurer que les roues demeurent sur votre véhicule là où elles devraient se trouver. | H20: 0.2 | J20: =VLOOKUP(B20,'[1]MASTER PART LIST'!$B:$C,2,FALSE) -> 61 | K20: =VLOOKUP(B20,'[1]MASTER PART LIST'!$B:$D,3,FALSE) -> 102 | L20: =K20+(H20*VLOOKUP(prov_cd,rate_table,2,FALSE)) -> 132.4 | O20: • | Q20: • | R20: • | W20: 11 | AK20: • | AS20: 08W42-SCV-302 Wheel Locks - Chrome
B21: 08W42-SCV-302 | C21: =B21 -> 08W42-SCV-302 | D21: Wheel Locks - Chrome | E21: Écrous de roue antivols - Chromés | F21: A great way to help ensure that your wheels stay on your vehicle where they belong. Chrome-plated triple-nickel finish for a brilliant shine and corrosion prevention | G21: Un excellent moyen de vous assurer que les roues demeurent sur votre véhicule, où elles devraient se trouver. La finition chromée triple nickel procure un éclat brillant et une prévention contre la corrosion. | H21: 0.2 | J21: =VLOOKUP(B21,'[1]MASTER PART LIST'!$B:$C,2,FALSE) -> 54 | K21: =VLOOKUP(B21,'[1]MASTER PART LIST'!$B:$D,3,FALSE) -> 90 | L21: =K21+(H21*VLOOKUP(prov_cd,rate_table,2,FALSE)) -> 120.4 | O21: • | Q21: • | R21: • | W21: 12 | AK21: • | AS21: 08W42-S2A-101 Wheel Locks - Black
B22: 08W42-PL4-100 | C22: =B22 -> 08W42-PL4-100 | D22: Wheel Lug Nuts - Black | E22: Écrous de roue - Noir | F22: Create a different look with a set of black lug nuts. Each package has a quantity of 20 lugs. | G22: Créez un aspect différent grâce à cet ensemble d’écrous de roue noirs qui complète les roues en alliage du véhicule. Chaque paquet contient 20 écrous de roue. | H22: 0.2 | J22: =VLOOKUP(B22,'[1]MASTER PART LIST'!$B:$C,2,FALSE) -> 170 | K22: =VLOOKUP(B22,'[1]MASTER PART LIST'!$B:$D,3,FALSE) -> 283 | L22: =K22+(H22*VLOOKUP(prov_cd,rate_table,2,FALSE)) -> 313.4 | O22: • | Q22: • | R22: • | U22: set of 20 lug nuts | V22: lot de 20 écrous de roue | W22: 14 | AO22: •
B23: 08W42-SNA-301 | C23: =B23 -> 08W42-SNA-301 | D23: Wheel Locks, Chrome - Exposed | E23: Écrous de roue antivol, chromée - exposés | F23: A great way to help ensure that your wheels stay on your vehicle where they belong. Chrome-plated triple-nickel finish for a brilliant shine and corrosion prevention | G23: Un excellent moyen de vous assurer que les roues demeurent sur votre véhicule, où elles devraient se trouver. La finition chromée triple nickel procure un éclat brillant et une prévention contre la corrosion. | H23: 0.2 | J23: =VLOOKUP(B23,'[1]MASTER PART LIST'!$B:$C,2,FALSE) -> 44 | K23: =VLOOKUP(B23,'[1]MASTER PART LIST'!$B:$D,3,FALSE) -> 73 | L23: =K23+(H23*VLOOKUP(prov_cd,rate_table,2,FALSE)) -> 103.4 | O23: • | Q23: • | R23: • | W23: 13 | AG23: •
A24: New | B24: 08F20-30A-100C | C24: =B24 -> 08F20-30A-100C | D24: Black Emblem Rear "H" mark | E24: Emblème, noirs lustré arrière « H » mark | F24: Add a unique and bold style with these gloss black emblems. Pair up with H-Mark, Accord, and Touring emblems to complete the look - sold separately. | G24: Donnez un style unique et audacieux avec ces emblèmes noir lustré. Jumelez-les aux emblèmes « H », Accord et Touring pour compléter l’apparence (vendus séparément). | H24: 0.2 | J24: =VLOOKUP(B24,'[1]MASTER PART LIST'!$B:$C,2,FALSE) -> 37 | K24: =VLOOKUP(B24,'[1]MASTER PART LIST'!$B:$D,3,FALSE) -> 62 | L24: =K24+(H24*VLOOKUP(prov_cd,rate_table,2,FALSE)) -> 92.4 | O24: • | Q24: • | R24: • | U24: Rear H-Mark Logo. | V24: Logo H-Mark l'arrière. | W24: 25 | AO24: • | AS24: 26ACC-BLK-EMB Black Emblem Set - Touring
A25: New | B25: 08F20-30A-100D | C25: =B25 -> 08F20-30A-100D | D25: Black Emblem, Accord | E25: Emblème, noirs lustré arrière « Accord » | F25: Add a unique and bold style with these gloss black emblems. Pair up with H-Mark, Accord, and Touring emblems to complete the look - sold separately. | G25: Donnez un style unique et audacieux avec ces emblèmes noir lustré. Jumelez-les aux emblèmes « H », Accord et Touring pour compléter l’apparence (vendus séparément). | H25: 0.3 | J25: =VLOOKUP(B25,'[1]MASTER PART LIST'!$B:$C,2,FALSE) -> 37 | K25: =VLOOKUP(B25,'[1]MASTER PART LIST'!$B:$D,3,FALSE) -> 62 | L25: =K25+(H25*VLOOKUP(prov_cd,rate_table,2,FALSE)) -> 107.6 | O25: • | Q25: N/A | R25: • | W25: 26 | AO25: • | AS25: 26ACC-BLK-EMB Black Emblem Set - Touring
A26: New | B26: 08F20-3A0-100C | C26: =B26 -> 08F20-3A0-100C | D26: Black Emblem, Touring | E26: Emblème, noirs lustré « Touring » | F26: Add a unique and bold style with these gloss black emblems. Pair up with H-Mark, Accord, and Touring emblems to complete the look - sold separately. | G26: Donnez un style unique et audacieux avec ces emblèmes noir lustré. Jumelez-les aux emblèmes « H », Accord et Touring pour compléter l’apparence (vendus séparément). | H26: 0.2 | J26: =VLOOKUP(B26,'[1]MASTER PART LIST'!$B:$C,2,FALSE) -> 44 | K26: =VLOOKUP(B26,'[1]MASTER PART LIST'!$B:$D,3,FALSE) -> 73 | L26: =K26+(H26*VLOOKUP(prov_cd,rate_table,2,FALSE)) -> 103.4 | O26: N/A | Q26: N/A | R26: • | W26: 27 | AO26: • | AS26: 26ACC-BLK-EMB Black Emblem Set - Touring
A27: New | B27: 08F20-T20-100B | C27: =B27 -> 08F20-T20-100B | D27: Black Emblem, Hybrid | E27: Emblème, noirs lustré « Hybride » | F27: Add a unique and bold style with these gloss black emblems. Pair up with H-Mark, Accord, and Touring emblems to complete the look - sold separately. | G27: Donnez un style unique et audacieux avec ces emblèmes noir lustré. Jumelez-les aux emblèmes « H », Accord et Touring pour compléter l’apparence (vendus séparément). | H27: 0.2 | J27: =VLOOKUP(B27,'[1]MASTER PART LIST'!$B:$C,2,FALSE) -> 46 | K27: =VLOOKUP(B27,'[1]MASTER PART LIST'!$B:$D,3,FALSE) -> 77 | L27: =K27+(H27*VLOOKUP(prov_cd,rate_table,2,FALSE)) -> 107.4 | O27: N/A | Q27: N/A | R27: • | W27: 28 | AO27: • | AS27: 26ACC-BLK-EMB Black Emblem Set - Touring
B29: 08F20-30A-100B | C29: =B29 -> 08F20-30A-100B | D29: HPD Badge | E29: Emblème HPD | F29: HPD - Honda Performance Development emblem with gloss black finish. A sporty, black HPD emblem finishes off the look of the other available HPD accessories. | G29: HPD – Emblème Honda Performance Development avec fini noir brillant. L'emblème HPD noir, d’allure sport, vient parfaire l'apparence des autres accessoires HPD disponibles. | H29: 0.1 | J29: =VLOOKUP(B29,'[1]MASTER PART LIST'!$B:$C,2,FALSE) -> 71 | K29: =VLOOKUP(B29,'[1]MASTER PART LIST'!$B:$D,3,FALSE) -> 118 | L29: =K29+(H29*VLOOKUP(prov_cd,rate_table,2,FALSE)) -> 133.2 | O29: • | Q29: • | R29: • | W29: 29 | AO29: •
B30: 08F59-30A-100 | C30: =B30 -> 08F59-30A-100 | D30: Fender Emblem | E30: Emblème d’aile | F30: If attention to detail is important to you, then you’re sure to love the look of the Fender Emblems. Their bold feature not only completes your Accord’s original unique exterior style, but also accentuates it. | G30: Si l’attention aux détails est importante pour vous, alors vous aimerez certainement l’allure des emblèmes d’ailes. Leurs lignes audacieuses complètent non seulement le style extérieur original et unique de votre Accord, mais le mettent également en valeur. | H30: 0.2 | J30: =VLOOKUP(B30,'[1]MASTER PART LIST'!$B:$C,2,FALSE) -> 94 | K30: =VLOOKUP(B30,'[1]MASTER PART LIST'!$B:$D,3,FALSE) -> 157 | L30: =K30+(H30*VLOOKUP(prov_cd,rate_table,2,FALSE)) -> 187.4 | O30: • | Q30: • | R30: • | W30: 30 | AO30: •
B31: 08F04-30A-1F0 | C31: =B31 -> 08F04-30A-1F0 | D31: Side Underbody Spoiler | E31: Becquet de bas de caisse, latéral | F31: The Side Underbody Spoiler adds a sporty, low-profile custom look that creates an accentuated aerodynamic style. Requires the Front Splash Guards to be removed. | G31: Le becquet de bas de caisse latéral confère une allure sportive et un profil abaissé personnalisé qui accentue le style aérodynamique. Nécessite le retrait des garde-boue avant. | H31: 0.6 | J31: =VLOOKUP(B31,'[1]MASTER PART LIST'!$B:$C,2,FALSE) -> 432 | K31: =VLOOKUP(B31,'[1]MASTER PART LIST'!$B:$D,3,FALSE) -> 720 | L31: =K31+(H31*VLOOKUP(prov_cd,rate_table,2,FALSE)) -> 811.2 | O31: • | Q31: • | R31: • | W31: 17 | AO31: • | AS31: 23ACC-ARO-EX Aeto Kit - EX Trim 23ACC-ARO-SPHY Aero Kit - Sport Trim 23ACC-ARO-TRHY Aero Kit - Touring Trim
B32: 08P98-30A-1F0 | C32: =B32 -> 08P98-30A-1F0 | D32: Front Aero Bumper | E32: Becquet de bas de caisse, avant | F32: The Front Underbody Spoiler adds a sporty, low-profile custom look that creates an accentuated aerodynamic style. | G32: Le becquet de bas de caisse avant confère une allure sportive et un profil abaissé personnalisé qui accentue le style aérodynamique. | H32: 0.6 | J32: =VLOOKUP(B32,'[1]MASTER PART LIST'!$B:$C,2,FALSE) -> 350 | K32: =VLOOKUP(B32,'[1]MASTER PART LIST'!$B:$D,3,FALSE) -> 583 | L32: =K32+(H32*VLOOKUP(prov_cd,rate_table,2,FALSE)) -> 674.2 | O32: • | Q32: • | R32: • | W32: 15 | AO32: • | AS32: 23ACC-ARO-EX Aeto Kit - EX Trim 23ACC-ARO-SPHY Aero Kit - Sport Trim 23ACC-ARO-TRHY Aero Kit - Touring Trim
B33: 08P99-30A-1F0 | C33: =B33 -> 08P99-30A-1F0 | D33: Rear Aero Bumper | E33: Becquet de bas de caisse, arrière | F33: The Rear Underbody Spoiler adds a sporty, low-profile custom look that creates an accentuated aerodynamic style. Cannot be combined with Rear Splash Guards. | G33: Le becquet de bas de caisse arrière confère une allure sportive et un profil abaissé personnalisé qui accentue le style aérodynamique. Ne peut être combiné aux garde-boue arrière. | H33: 0.6 | J33: =VLOOKUP(B33,'[1]MASTER PART LIST'!$B:$C,2,FALSE) -> 350 | K33: =VLOOKUP(B33,'[1]MASTER PART LIST'!$B:$D,3,FALSE) -> 583 | L33: =K33+(H33*VLOOKUP(prov_cd,rate_table,2,FALSE)) -> 674.2 | O33: • | Q33: • | R33: • | W33: 16 | AO33: • | AS33: 23ACC-ARO-EX Aeto Kit - EX Trim 23ACC-ARO-SPHY Aero Kit - Sport Trim 23ACC-ARO-TRHY Aero Kit - Touring Trim
B34: 08R06-30A-110 | C34: =B34 -> 08R06-30A-110 | D34: Door Mirror Covers & Lower Intake Accents | E34: Couvercle de rétroviseur de portière et élément inférieur d’admission d’air | F34: Promotional Priced Item offered for a limited time only. Item availability and price are subject to change without prior notice. Contact your local Honda Dealer for more information. Enhance the look of your car with these black Door Mirror Covers and Lower Intake Accents. Designed and engineered by Honda for a precise fit | G34: Article à prix promotionnel offert pour une durée limitée seulement. La disponibilité et le prix de l’article peuvent être modifiés sans préavis. Communiquez avec votre concessionnaire Honda pour plus d’information. Rehaussez l’apparence de votre voiture avec ces couvercles de rétroviseurs de portières noirs et éléments visuels d’admission d’air. Conçus et fabriqués par Honda pour un ajustement précis. | H34: 1.1 | J34: =VLOOKUP(B34,'[1]MASTER PART LIST'!$B:$C,2,FALSE) -> 210 | K34: =VLOOKUP(B34,'[1]MASTER PART LIST'!$B:$D,3,FALSE) -> 350 | L34: =K34+(H34*VLOOKUP(prov_cd,rate_table,2,FALSE)) -> 517.2 | O34: • | Q34: N/A | R34: N/A | W34: 18 | AO34: • | AS34: 23ACC-ARO-EX Aeto Kit - EX Trim 23ACC-ARO-SPHY Aero Kit - Sport Trim
B35: 08R06-30A-110A | C35: =B35 -> 08R06-30A-110A | D35: Door Mirror Covers & Lower Intake Accents | E35: Couvercle de rétroviseur de portière et élément inférieur d’admission d’air | F35: Enhance the look of your car with these black Door Mirror Covers and Lower Intake Accents. Designed and engineered by Honda for a precise fit | G35: Rehaussez l’apparence de votre voiture avec ces couvercles de rétroviseurs de portières noirs et éléments visuels d’admission d’air. Conçus et fabriqués par Honda pour un ajustement précis. | H35: 1.1 | J35: =VLOOKUP(B35,'[1]MASTER PART LIST'!$B:$C,2,FALSE) -> 210 | K35: =VLOOKUP(B35,'[1]MASTER PART LIST'!$B:$D,3,FALSE) -> 350 | L35: =K35+(H35*VLOOKUP(prov_cd,rate_table,2,FALSE)) -> 517.2 | O35: N/A | Q35: N/A | R35: • | W35: 19 | AO35: • | AS35: 23ACC-ARO-TRHY Aero Kit - Touring Trim
B36: 08P48-30A-100 | C36: =B36 -> 08P48-30A-100 | D36: Film Set - Door Handle & Rear Bumper Film | E36: Ensemble de pellicule – Pellicule de poignée de portière et de pare-chocs arrière | F36: Transparent urethane film in the well of the door handle helps safeguard the paint finish from unsightly scratches from nails, jewelry, and keys combined with The Rear Bumper Applique provides extra protection when loading and unloading the trunk. | G36: La pellicule transparente en uréthane dans le puits de la poignée de portière aide à protéger la peinture des rayures disgracieuses causées par les ongles, les bijoux et les clés. S’ajoute à celle-ci la pellicule du pare-chocs arrière pour procurer une protection supplémentaire lors du chargement et du déchargement du coffre. | H36: 0.7 | J36: =VLOOKUP(B36,'[1]MASTER PART LIST'!$B:$C,2,FALSE) -> 131 | K36: =VLOOKUP(B36,'[1]MASTER PART LIST'!$B:$D,3,FALSE) -> 218 | L36: =K36+(H36*VLOOKUP(prov_cd,rate_table,2,FALSE)) -> 324.4 | O36: • | Q36: • | R36: • | W36: 38 | X36: Yes | AM36: •
B37: 08P20-30A-100A | C37: =B37 -> 08P20-30A-100A | D37: Door Edge Film | E37: Pellicule pour rebord de portière | F37: Help protect against unsightly nicks and scrapes around your door edges. | G37: La pellicule aide à protéger les surfaces des rebords de portières contre des égratignures et éraflures inesthétiques. | H37: 0.5 | J37: =VLOOKUP(B37,'[1]MASTER PART LIST'!$B:$C,2,FALSE) -> 71 | K37: =VLOOKUP(B37,'[1]MASTER PART LIST'!$B:$D,3,FALSE) -> 118 | L37: =K37+(H37*VLOOKUP(prov_cd,rate_table,2,FALSE)) -> 194 | O37: • | Q37: • | R37: • | U37: Cannot be installed with Door Edge Guards | V37: Ne peut être installé simultanément avec protecteurs de bordure de porte. | W37: 37 | X37: Yes | AM37: • | AS37: 08P20-30A-110 Door Edge Guards
B38: 08R04-TVA-101 | C38: =B38 -> 08R04-TVA-101 | D38: Door Visors | E38: Déflecteurs de portières | F38: This tinted Door Visor helps to protect you and your passengers from sun glare and minimizes outside noise when the windows are partially open. | G38: Cet ensemble de déflecteur de portière teinté aide à réduire les reflets du soleil ainsi que le bruit provenant de l'extérieur quand les glaces sont partiellement ouvertes. Image si dessous est un ancient model | H38: 0.5 | J38: =VLOOKUP(B38,'[1]MASTER PART LIST'!$B:$C,2,FALSE) -> 200 | K38: =VLOOKUP(B38,'[1]MASTER PART LIST'!$B:$D,3,FALSE) -> 333 | L38: =K38+(H38*VLOOKUP(prov_cd,rate_table,2,FALSE)) -> 409 | O38: • | Q38: • | R38: • | W38: 21 | X38: Yes | AM38: •
B39: 08R01-30A-300 | C39: =B39 -> 08R01-30A-300 | D39: Moonroof Visor | E39: Déflecteur de toit ouvrant | F39: The Moonroof Visor helps reduce wind noise and glare for a more comfortable and enjoyable driving experience. | G39: Le déflecteur de toit contribue à réduire le bruit du vent et l'éblouissement pour une expérience de conduite plus confortable et plus agréable. | H39: 0.3 | J39: =VLOOKUP(B39,'[1]MASTER PART LIST'!$B:$C,2,FALSE) -> 200 | K39: =VLOOKUP(B39,'[1]MASTER PART LIST'!$B:$D,3,FALSE) -> 333 | L39: =K39+(H39*VLOOKUP(prov_cd,rate_table,2,FALSE)) -> 378.6 | O39: • | Q39: • | R39: • | W39: 22 | X39: Yes | AM39: •
B40: 08P09-30A-300 | C40: =B40 -> 08P09-30A-300 | D40: Rear Splash Guards | E40: Garde-boue arrière | F40: Rear Splash Guards are a nice finishing touch. They give your Accord a great look and help protect your paint from chips and stains. | G40: Les garde-boue arrière ajoutent une touche finale soignée. Les garde-boue procurent une belle apparence à votre Accord et contribuent à protéger la peinture contre les éclats et les taches. | H40: 0.4 | J40: =VLOOKUP(B40,'[1]MASTER PART LIST'!$B:$C,2,FALSE) -> 50 | K40: =VLOOKUP(B40,'[1]MASTER PART LIST'!$B:$D,3,FALSE) -> 83 | L40: =K40+(H40*VLOOKUP(prov_cd,rate_table,2,FALSE)) -> 143.8 | O40: • | Q40: • | R40: • | W40: 44 | X40: Yes | AM40: • | AS40: 23ACC-PRO-PKA Protection Package Advance
A41: no image | B41: 08P20-30A-XXXX | C41: =B42 -> 08P20-30A-110 | D41: Door Edge Guards | E41: Déflecteur de bas de caisse avant | F41: Door Edge Guards help protect your doors from nicks and scrapes that can be expensive to repair. | G41: Les protecteurs de rebords de portières aident à protéger les portières de votre véhicule contre les égratignures et éraflures dont la réparation serait coûteuse. | H41: =H42 -> 0.4 | J41: =J42 -> 176 | K41: =K42 -> 293 | L41: =K41+(H41*VLOOKUP(prov_cd,rate_table,2,FALSE)) -> 353.8 | O41: • | Q41: • | R41: • | W41: 39 | AM41: • | AS41: 08P20-30A-100A Door Edge Film
B42: 08P20-30A-110 | C42: N/A | D42: Platinum White Pearl (NH-883P) | E42: Blanc platine nacré (NH-883P) | H42: 0.4 | J42: =VLOOKUP(B42,'[1]MASTER PART LIST'!$B:$C,2,FALSE) -> 176 | K42: =VLOOKUP(B42,'[1]MASTER PART LIST'!$B:$D,3,FALSE) -> 293 | L42: =K42+(H42*VLOOKUP(prov_cd,rate_table,2,FALSE)) -> 353.8 | O42: • | Q42: • | R42: •
B43: 08P20-30A-140 | C43: N/A | D43: Meteoroid Gray Pearl (NH-904M) | E43: Gris météore nacré (NH-904M) | H43: 0.4 | J43: =VLOOKUP(B43,'[1]MASTER PART LIST'!$B:$C,2,FALSE) -> 176 | K43: =VLOOKUP(B43,'[1]MASTER PART LIST'!$B:$D,3,FALSE) -> 293 | L43: =K43+(H43*VLOOKUP(prov_cd,rate_table,2,FALSE)) -> 353.8 | O43: N/A | Q43: • | R43: N/A
B44: 08P20-30A-150 | C44: N/A | D44: Urban Grey Pearl (NH-912P) | E44: Gris urbain nacré (NH-912P) | H44: 0.4 | J44: =VLOOKUP(B44,'[1]MASTER PART LIST'!$B:$C,2,FALSE) -> 176 | K44: =VLOOKUP(B44,'[1]MASTER PART LIST'!$B:$D,3,FALSE) -> 293 | L44: =K44+(H44*VLOOKUP(prov_cd,rate_table,2,FALSE)) -> 353.8 | O44: N/A | Q44: N/A | R44: •
B45: 08P20-30A-170 | C45: N/A | D45: Crystal Black Pearl (NH-731P) | E45: Noir cristal nacré (NH-731P) | H45: 0.4 | J45: =VLOOKUP(B45,'[1]MASTER PART LIST'!$B:$C,2,FALSE) -> 176 | K45: =VLOOKUP(B45,'[1]MASTER PART LIST'!$B:$D,3,FALSE) -> 293 | L45: =K45+(H45*VLOOKUP(prov_cd,rate_table,2,FALSE)) -> 353.8 | O45: • | Q45: • | R45: •
B46: 08P20-30A-1A0 | C46: N/A | D46: Radiant Red Metallic (R-569M) | E46: Radiant rouge métallisé (R-569M) | H46: 0.4 | J46: =VLOOKUP(B46,'[1]MASTER PART LIST'!$B:$C,2,FALSE) -> 176 | K46: =VLOOKUP(B46,'[1]MASTER PART LIST'!$B:$D,3,FALSE) -> 293 | L46: =K46+(H46*VLOOKUP(prov_cd,rate_table,2,FALSE)) -> 353.8 | O46: N/A | Q46: • | R46: •
B47: 08P20-30A-1D0 | C47: N/A | D47: Canyon River Blue Metallic (B-640M) | E47: Bleu rivière canyon métallisé (B-640M) | H47: 0.4 | J47: =VLOOKUP(B47,'[1]MASTER PART LIST'!$B:$C,2,FALSE) -> 176 | K47: =VLOOKUP(B47,'[1]MASTER PART LIST'!$B:$D,3,FALSE) -> 293 | L47: =K47+(H47*VLOOKUP(prov_cd,rate_table,2,FALSE)) -> 353.8 | O47: N/A | Q47: N/A | R47: •
B48: 08P20-30A-1C0 | C48: N/A | D48: Still Night Pearl (B-575P) | E48: Nuit paisible fini nacré (B-575P) | H48: 0.4 | J48: =VLOOKUP(B48,'[1]MASTER PART LIST'!$B:$C,2,FALSE) -> 176 | K48: =VLOOKUP(B48,'[1]MASTER PART LIST'!$B:$D,3,FALSE) -> 293 | L48: =K48+(H48*VLOOKUP(prov_cd,rate_table,2,FALSE)) -> 353.8 | O48: N/A | Q48: • | R48: N/A
B49: 08P20-30A-1H0 | C49: N/A | D49: Solar Reflection Silver (NH-932M) | E49: Refl et solaire argent métallisé (NH-932M) | H49: 0.4 | J49: =VLOOKUP(B49,'[1]MASTER PART LIST'!$B:$C,2,FALSE) -> 176 | K49: =VLOOKUP(B49,'[1]MASTER PART LIST'!$B:$D,3,FALSE) -> 293 | L49: =K49+(H49*VLOOKUP(prov_cd,rate_table,2,FALSE)) -> 353.8 | O49: • | Q49: • | R49: •
B50: 08P05-30A-XXXX | C50: =B51 -> 08P05-30A-110 | D50: Body Side Moulding | E50: Moulure latérale | F50: Body Side Moulding accentuates the styling of the Accord and is ideally positioned where the side panel extends out the most, in order to help protect against door dings and scratches. | G50: Non seulement la moulure latérale accentue le style du Accord, son positionnement est idéal à l’endroit où les panneaux latéraux sont le plus en saillie, contribuant à protéger les portières des bosselures et des égratignures. | H50: =H53 -> 0.4 | J50: =J53 -> 232 | K50: =K53 -> 387 | L50: =K50+(H50*VLOOKUP(prov_cd,rate_table,2,FALSE)) -> 447.8 | O50: • | Q50: • | R50: • | W50: 23 | AK50: •
B51: 08P05-30A-110 | C51: N/A | D51: Platinum White Pearl (NH-883P) | E51: Blanc platine nacré (NH-883P) | H51: 0.4 | J51: =VLOOKUP(B51,'[1]MASTER PART LIST'!$B:$C,2,FALSE) -> 232 | K51: =VLOOKUP(B51,'[1]MASTER PART LIST'!$B:$D,3,FALSE) -> 387 | L51: =K51+(H51*VLOOKUP(prov_cd,rate_table,2,FALSE)) -> 447.8 | O51: • | Q51: • | R51: •
B52: 08P05-30A-140 | C52: N/A | D52: Meteoroid Gray Pearl (NH-904M) | E52: Gris météore nacré (NH-904M) | H52: 0.4 | J52: =VLOOKUP(B52,'[1]MASTER PART LIST'!$B:$C,2,FALSE) -> 232 | K52: =VLOOKUP(B52,'[1]MASTER PART LIST'!$B:$D,3,FALSE) -> 387 | L52: =K52+(H52*VLOOKUP(prov_cd,rate_table,2,FALSE)) -> 447.8 | O52: N/A | Q52: • | R52: N/A
B53: 08P05-30A-150 | C53: N/A | D53: Urban Grey Pearl (NH-912P) | E53: Gris urbain nacré (NH-912P) | H53: 0.4 | J53: =VLOOKUP(B53,'[1]MASTER PART LIST'!$B:$C,2,FALSE) -> 232 | K53: =VLOOKUP(B53,'[1]MASTER PART LIST'!$B:$D,3,FALSE) -> 387 | L53: =K53+(H53*VLOOKUP(prov_cd,rate_table,2,FALSE)) -> 447.8 | O53: N/A | Q53: N/A | R53: •
B54: 08P05-30A-170 | C54: N/A | D54: Crystal Black Pearl (NH-731P) | E54: Noir cristal nacré (NH-731P) | H54: 0.4 | J54: =VLOOKUP(B54,'[1]MASTER PART LIST'!$B:$C,2,FALSE) -> 232 | K54: =VLOOKUP(B54,'[1]MASTER PART LIST'!$B:$D,3,FALSE) -> 387 | L54: =K54+(H54*VLOOKUP(prov_cd,rate_table,2,FALSE)) -> 447.8 | O54: • | Q54: • | R54: •
B55: 08P05-30A-1A0 | C55: N/A | D55: Radiant Red Metallic (R-569M) | E55: Radiant rouge métallisé (R-569M) | H55: 0.4 | J55: =VLOOKUP(B55,'[1]MASTER PART LIST'!$B:$C,2,FALSE) -> 232 | K55: =VLOOKUP(B55,'[1]MASTER PART LIST'!$B:$D,3,FALSE) -> 387 | L55: =K55+(H55*VLOOKUP(prov_cd,rate_table,2,FALSE)) -> 447.8 | O55: N/A | Q55: • | R55: •
B56: 08P05-30A-1D0 | C56: N/A | D56: Canyon River Blue Metallic (B-640M) | E56: Bleu rivière canyon métallisé (B-640M) | H56: 0.4 | J56: =VLOOKUP(B56,'[1]MASTER PART LIST'!$B:$C,2,FALSE) -> 232 | K56: =VLOOKUP(B56,'[1]MASTER PART LIST'!$B:$D,3,FALSE) -> 387 | L56: =K56+(H56*VLOOKUP(prov_cd,rate_table,2,FALSE)) -> 447.8 | O56: N/A | Q56: N/A | R56: •
B57: 08P05-30A-1C0 | C57: N/A | D57: Still Night Pearl (B-575P) | E57: Nuit paisible fini nacré (B-575P) | H57: 0.4 | J57: =VLOOKUP(B57,'[1]MASTER PART LIST'!$B:$C,2,FALSE) -> 232 | K57: =VLOOKUP(B57,'[1]MASTER PART LIST'!$B:$D,3,FALSE) -> 387 | L57: =K57+(H57*VLOOKUP(prov_cd,rate_table,2,FALSE)) -> 447.8 | O57: N/A | Q57: • | R57: N/A
B58: 08P05-30A-1H0 | C58: N/A | D58: Solar Reflection Silver (NH-932M) | E58: Refl et solaire argent métallisé (NH-932M) | H58: 0.4 | J58: =VLOOKUP(B58,'[1]MASTER PART LIST'!$B:$C,2,FALSE) -> 232 | K58: =VLOOKUP(B58,'[1]MASTER PART LIST'!$B:$D,3,FALSE) -> 387 | L58: =K58+(H58*VLOOKUP(prov_cd,rate_table,2,FALSE)) -> 447.8 | O58: • | Q58: • | R58: •
B59: 08F02-30A-XXX | C59: =B60 -> 08F10-30A-110 | D59: Decklid Spoiler | E59: Déflecteur arrière de coffre | F59: The Decklid Spoiler adds a subtle, tasteful enhancement that makes a big contribution to the sleek aerodynamics of your Accord. | G59: Le déflecteur arrière de coffre ajoute une touche subtile et raffinée qui contribue grandement à l’aérodynamisme de votre Accord. | H59: =H60 -> 0.6 | J59: =J60 -> 386 | K59: =K60 -> 643 | L59: =K59+(H59*VLOOKUP(prov_cd,rate_table,2,FALSE)) -> 734.2 | O59: • | Q59: S | R59: • | W59: 20 | AO59: • | AS59: 23ACC-ARO-EX Aeto Kit - EX Trim 23ACC-ARO-TRHY Aero Kit - Touring Trim
B60: 08F10-30A-110 | C60: N/A | D60: Platinum White Pearl (NH-883P) | E60: Blanc platine nacré (NH-883P) | H60: 0.6 | J60: =VLOOKUP(B60,'[1]MASTER PART LIST'!$B:$C,2,FALSE) -> 386 | K60: =VLOOKUP(B60,'[1]MASTER PART LIST'!$B:$D,3,FALSE) -> 643 | L60: =K60+(H60*VLOOKUP(prov_cd,rate_table,2,FALSE)) -> 734.2 | O60: • | Q60: S | R60: •
B61: 08F10-30A-140 | C61: N/A | D61: Meteoroid Gray Pearl (NH-904M) | E61: Gris météore nacré (NH-904M) | H61: 0.6 | J61: =VLOOKUP(B61,'[1]MASTER PART LIST'!$B:$C,2,FALSE) -> 386 | K61: =VLOOKUP(B61,'[1]MASTER PART LIST'!$B:$D,3,FALSE) -> 643 | L61: =K61+(H61*VLOOKUP(prov_cd,rate_table,2,FALSE)) -> 734.2 | O61: N/A | Q61: S | R61: N/A
B62: 08F10-30A-150 | C62: N/A | D62: Urban Grey Pearl (NH-912P) | E62: Gris urbain nacré (NH-912P) | H62: 0.6 | J62: =VLOOKUP(B62,'[1]MASTER PART LIST'!$B:$C,2,FALSE) -> 386 | K62: =VLOOKUP(B62,'[1]MASTER PART LIST'!$B:$D,3,FALSE) -> 643 | L62: =K62+(H62*VLOOKUP(prov_cd,rate_table,2,FALSE)) -> 734.2 | O62: N/A | Q62: S | R62: •
B63: 08F10-30A-170 | C63: N/A | D63: Crystal Black Pearl (NH-731P) | E63: Noir cristal nacré (NH-731P) | H63: 0.6 | J63: =VLOOKUP(B63,'[1]MASTER PART LIST'!$B:$C,2,FALSE) -> 386 | K63: =VLOOKUP(B63,'[1]MASTER PART LIST'!$B:$D,3,FALSE) -> 643 | L63: =K63+(H63*VLOOKUP(prov_cd,rate_table,2,FALSE)) -> 734.2 | O63: • | Q63: S | R63: •
B64: 08F10-30A-1A0 | C64: N/A | D64: Radiant Red Metallic (R-569M) | E64: Radiant rouge métallisé (R-569M) | H64: 0.6 | J64: =VLOOKUP(B64,'[1]MASTER PART LIST'!$B:$C,2,FALSE) -> 386 | K64: =VLOOKUP(B64,'[1]MASTER PART LIST'!$B:$D,3,FALSE) -> 643 | L64: =K64+(H64*VLOOKUP(prov_cd,rate_table,2,FALSE)) -> 734.2 | O64: N/A | Q64: S | R64: •
B65: 08F10-30A-1D0 | C65: N/A | D65: Canyon River Blue Metallic (B-640M) | E65: Bleu rivière canyon métallisé (B-640M) | H65: 0.6 | J65: =VLOOKUP(B65,'[1]MASTER PART LIST'!$B:$C,2,FALSE) -> 386 | K65: =VLOOKUP(B65,'[1]MASTER PART LIST'!$B:$D,3,FALSE) -> 643 | L65: =K65+(H65*VLOOKUP(prov_cd,rate_table,2,FALSE)) -> 734.2 | O65: N/A | Q65: S | R65: •
B66: 08F10-30A-1C0 | C66: N/A | D66: Still Night Pearl (B-575P) | E66: Nuit paisible fini nacré (B-575P) | H66: 0.6 | J66: =VLOOKUP(B66,'[1]MASTER PART LIST'!$B:$C,2,FALSE) -> 386 | K66: =VLOOKUP(B66,'[1]MASTER PART LIST'!$B:$D,3,FALSE) -> 643 | L66: =K66+(H66*VLOOKUP(prov_cd,rate_table,2,FALSE)) -> 734.2 | O66: N/A | Q66: S | R66: N/A
B67: 08F10-30A-1H0 | C67: N/A | D67: Solar Reflection Silver (NH-932M) | E67: Refl et solaire argent métallisé (NH-932M) | H67: 0.6 | J67: =VLOOKUP(B67,'[1]MASTER PART LIST'!$B:$C,2,FALSE) -> 386 | K67: =VLOOKUP(B67,'[1]MASTER PART LIST'!$B:$D,3,FALSE) -> 643 | L67: =K67+(H67*VLOOKUP(prov_cd,rate_table,2,FALSE)) -> 734.2 | O67: • | Q67: S | R67: •
B68: 08U25-STK-413 | C68: =B68 -> 08U25-STK-413 | D68: Ashtray | E68: Cendrier de type porte-gobelet | F68: Front seat passengers can enjoy the added convenience of an ashtray. | G68: Les passagers avant apprécieront la commodité d'un cendrier. | H68: 0 | J68: =VLOOKUP(B68,'[1]MASTER PART LIST'!$B:$C,2,FALSE) -> 41 | K68: =VLOOKUP(B68,'[1]MASTER PART LIST'!$B:$D,3,FALSE) -> 68 | L68: =K68+(H68*VLOOKUP(prov_cd,rate_table,2,FALSE)) -> 68 | O68: • | Q68: • | R68: • | W68: 250 | X68: Yes | AM68: •
B69: 08P17-30A-110 | C69: =B69 -> 08P17-30A-110 | D69: All Season Floor Mats | E69: Protège-tapis toutes saisons | F69: The extended sidewalls of the high wall All-Season Floor Mats add extra protection to shield your original carpets from the wear and tear of everyday driving. | G69: Les parois hautes des tapis toutes saisons offrent une protection accrue de la moquette d’origine contre l’usure et la détérioration dues à la conduite quotidienne | H69: 0.1 | J69: =VLOOKUP(B69,'[1]MASTER PART LIST'!$B:$C,2,FALSE) -> 175 | K69: =VLOOKUP(B69,'[1]MASTER PART LIST'!$B:$D,3,FALSE) -> 292 | L69: =K69+(H69*VLOOKUP(prov_cd,rate_table,2,FALSE)) -> 307.2 | O69: • | Q69: • | R69: • | W69: 32 | X69: Yes | AM69: • | AS69: 23ACC-PRO-PK Protection Package 23ACC-PRO-PKA Protection Package Advance
B70: 08U45-30A-100 | C70: =B70 -> 08U45-30A-100 | D70: Trunk Tray | E70: Plateau de coffre | F70: The things you haul in your trunk often spill, leave stains or otherwise mar the original carpeting, making a Trunk Tray a wise investment. | G70: Il arrive souvent que les objets que vous transportez dans votre coffre se renversent, laissent des taches ou abîment la moquette d’origine, faisant du plateau de coffre un investissement judicieux. | H70: 0.1 | J70: =VLOOKUP(B70,'[1]MASTER PART LIST'!$B:$C,2,FALSE) -> 129 | K70: =VLOOKUP(B70,'[1]MASTER PART LIST'!$B:$D,3,FALSE) -> 215 | L70: =K70+(H70*VLOOKUP(prov_cd,rate_table,2,FALSE)) -> 230.2 | O70: • | Q70: • | R70: • | W70: 33 | X70: Yes | AM70: • | AS70: 23ACC-PRO-PK Protection Package 23ACC-PRO-PKA Protection Package Advance
B71: 08L96-TA0-301A | C71: =B71 -> 08L96-TA0-301A | D71: Cargo Hook | E71: Crochets de cargaison | F71: Avoid having to pick up groceries and other items that have spilled out of their bags and scattered all around the trunk. | G71: Évitez d’avoir à ramasser les articles d’épicerie et autres objets sortis des sacs et éparpillés partout dans le coffre. | H71: 0.2 | J71: =VLOOKUP(B71,'[1]MASTER PART LIST'!$B:$C,2,FALSE) -> 17 | K71: =VLOOKUP(B71,'[1]MASTER PART LIST'!$B:$D,3,FALSE) -> 28 | L71: =K71+(H71*VLOOKUP(prov_cd,rate_table,2,FALSE)) -> 58.4 | O71: • | Q71: • | R71: • | W71: 34 | X71: Yes | AM71: •
B72: 08L96-TVA-300 | C72: =B72 -> 08L96-TVA-300 | D72: Cargo Net | E72: Filet de cargaison | F72: The Cargo Net helps keep your grocery bags upright and holds most loose items securely in place. | G72: Le filet de cargaison contribue à garder vos sacs d’épicerie à la verticale et garde en place la plupart des articles en toute sécurité. | H72: 0.4 | J72: =VLOOKUP(B72,'[1]MASTER PART LIST'!$B:$C,2,FALSE) -> 26.99 | K72: =VLOOKUP(B72,'[1]MASTER PART LIST'!$B:$D,3,FALSE) -> 58 | L72: =K72+(H72*VLOOKUP(prov_cd,rate_table,2,FALSE)) -> 118.8 | O72: • | Q72: • | R72: • | W72: 35 | AM72: • | AS72: 23ACC-PRO-PKA Protection Package Advance
B73: 08P04-30A-100 | C73: =B73 -> 08P04-30A-100 | D73: Door Sill Protection Film | E73: Protecteur de panneau de portière | F73: The Lower Door Sill Protection Film helps provide the lower door sill with protection from scuffing. | G73: Le protecteur de panneau de portière protège des égratignures lors de l’entrée et de la sortie du véhicule. | H73: 0.4 | J73: =VLOOKUP(B73,'[1]MASTER PART LIST'!$B:$C,2,FALSE) -> 106 | K73: =VLOOKUP(B73,'[1]MASTER PART LIST'!$B:$D,3,FALSE) -> 177 | L73: =K73+(H73*VLOOKUP(prov_cd,rate_table,2,FALSE)) -> 237.8 | O73: • | Q73: • | R73: • | W73: 40 | AM73: •
B74: 08R13-30A-100 | C74: =B74 -> 08R13-30A-100 | D74: Rear Window Shade | E74: Pare-soleil pour glaces latérales arrière | F74: The Rear Passenger Window Shades provide added comfort for your rear seated passengers by shielding them from the sun’s heat and glare. Includes both left and right rear window shades. Integrated pull tabs for ease of operation | G74: Les pare-soleil pour glaces latérales arrière offrent un confort accru pour vos passagers arrière, en fournissant une protection contre l’éblouissement et la chaleur du soleil. Inclut le côté gauche et droit. | H74: 0.5 | J74: =VLOOKUP(B74,'[1]MASTER PART LIST'!$B:$C,2,FALSE) -> 180 | K74: =VLOOKUP(B74,'[1]MASTER PART LIST'!$B:$D,3,FALSE) -> 300 | L74: =K74+(H74*VLOOKUP(prov_cd,rate_table,2,FALSE)) -> 376 | O74: • | Q74: • | R74: • | W74: 36 | AM74: •
B75: Web only | C75: =B76 -> 08E12-30A-110 | D75: =D76 -> Illuminated Door Sill Trim | E75: =E76 -> Garniture de seuil de portière illuminée | F75: =F76 -> The Illuminated Door Sill Trim dresses up the interior while helping protect the lower door sill from scuff marks. White LED lights illuminate the outer perimeters of the Accord logo when the door is open. | G75: =G76 -> La garniture de seuil de portière illuminée rend l’habitacle plus attrayant tout en protégeant le seuil de portière des éraflures. Les lumières blanches à DEL illuminent le périmètre extérieur du logo Accord lors de l’ouverture de la portière. Livrable en noir ou en gris. | H75: =H76+H77 -> 1.4 | J75: =J76+J77 -> 368 | K75: =K76+K77 -> 559 | L75: =K75+(H75*VLOOKUP(prov_cd,rate_table,2,FALSE)) -> 771.8 | O75: =O76 -> • | Q75: =Q76 -> • | R75: =R76 -> • | W75: 31 | AN75: •
B76: 08E12-30A-110 | C76: N/A App Chart only | D76: Illuminated Door Sill Trim | E76: Garniture de seuil de portière illuminée | F76: The Illuminated Door Sill Trim dresses up the interior while helping protect the lower door sill from scuff marks. White LED lights illuminate the outer perimeters of the Accord logo when the door is open. | G76: La garniture de seuil de portière illuminée rend l’habitacle plus attrayant tout en protégeant le seuil de portière des éraflures. Les lumières blanches à DEL illuminent le périmètre extérieur du logo Accord lors de l’ouverture de la portière. Livrable en noir ou en gris. | H76: 1.4 | J76: =VLOOKUP(B76,'[1]MASTER PART LIST'!$B:$C,2,FALSE) -> 302 | K76: =VLOOKUP(B76,'[1]MASTER PART LIST'!$B:$D,3,FALSE) -> 465 | L76: =K76+(H76*VLOOKUP(prov_cd,rate_table,2,FALSE)) -> 677.8 | O76: • | Q76: • | R76: • | U76: Requires Illuminated Door Sill Trim Attachment. 08E12-30A-100A | V76: Nécessite une fixation degarniture de seuil de portière illuminée. 08E12-30A-100A
B77: 08E12-30A-100A | C77: N/A App Chart only | D77: Illuminated Door Sill Trim Attachment | E77: Fixation de garniture de seuil de portière illuminée | H77: 0 | J77: =VLOOKUP(B77,'[1]MASTER PART LIST'!$B:$C,2,FALSE) -> 66 | K77: =VLOOKUP(B77,'[1]MASTER PART LIST'!$B:$D,3,FALSE) -> 94 | L77: =K77+(H77*VLOOKUP(prov_cd,rate_table,2,FALSE)) -> 94 | O77: • | Q77: • | R77: •
B78: Web only | C78: =B80 -> 08V03-30A-100 | D78: =D79 -> Auto Day/Night Mirror with Home Link | E78: =E79 -> Rétroviseur automatique jour/nuit avec HomeLink | F78: =F79 -> A car is fast approaching from the rear. Headlights begin to blind you. No worries. The Automatic-Dimming Mirror with HomeLink darkens to reduce the glare. No hand adjustment necessary. Includes HomeLink Wireless Control System that can be programmed to activate devices such as garage door openers, gates, and RF controlled lighting. | G78: =G79 -> Un véhicule approche rapidement à l’arrière. Les phares commencent à vous éblouir. Soyez sans crainte. Le rétroviseur à gradation automatique s’assombrit pour réduire l’éblouissement. Aucun réglage manuel n’est requis. Comprend le système de commande sans fil HomeLink qui peut être programmé pour activer des dispositifs tels que des ouvre-portes de garage, des portails et des éclairages contrôlés par radiofréquence. | H78: =H79+H80 -> 0.8 | J78: =J79+J80 -> 394 | K78: =K79+K80 -> 580 | L78: =K78+(H78*VLOOKUP(prov_cd,rate_table,2,FALSE)) -> 701.6 | O78: =O79 -> • | Q78: =Q79 -> • | R78: =R79 -> S | W78: 45 | X78: Yes | AM78: •
B79: 08V03-3A0-100 | C79: N/A App Chart only | D79: Auto Day/Night Mirror with Home Link | E79: Rétroviseur automatique jour/nuit avec HomeLink | F79: A car is fast approaching from the rear. Headlights begin to blind you. No worries. The Automatic-Dimming Mirror with HomeLink darkens to reduce the glare. No hand adjustment necessary. Includes HomeLink Wireless Control System that can be programmed to activate devices such as garage door openers, gates, and RF controlled lighting. | G79: Un véhicule approche rapidement à l’arrière. Les phares commencent à vous éblouir. Soyez sans crainte. Le rétroviseur à gradation automatique s’assombrit pour réduire l’éblouissement. Aucun réglage manuel n’est requis. Comprend le système de commande sans fil HomeLink qui peut être programmé pour activer des dispositifs tels que des ouvre-portes de garage, des portails et des éclairages contrôlés par radiofréquence. | H79: 0.2 | J79: =VLOOKUP(B79,'[1]MASTER PART LIST'!$B:$C,2,FALSE) -> 324 | K79: =VLOOKUP(B79,'[1]MASTER PART LIST'!$B:$D,3,FALSE) -> 463 | L79: =K79+(H79*VLOOKUP(prov_cd,rate_table,2,FALSE)) -> 493.4 | O79: • | Q79: • | R79: S | U79: Requires Auto Day/Night Mirror Attachment. 08V03-30A-100 | V79: Nécessite une fixation pour rétroviseur jour/nuit automatique. 08V03-30A-100 | X79: Yes
B80: 08V03-30A-100 | C80: N/A App Chart only | D80: Auto Day/Night Mirror Attachment | E80: Fixation pour rétroviseur jour/nuit automatique | H80: 0.6 | J80: =VLOOKUP(B80,'[1]MASTER PART LIST'!$B:$C,2,FALSE) -> 70 | K80: =VLOOKUP(B80,'[1]MASTER PART LIST'!$B:$D,3,FALSE) -> 117 | L80: =K80+(H80*VLOOKUP(prov_cd,rate_table,2,FALSE)) -> 208.2 | O80: • | Q80: • | R80: S | X80: Yes
B81: 08T44-30A-300A | C81: =B81 -> 08T44-30A-300A | D81: Engine Block Heater | E81: Chauffe-moteur | F81: Don't let the cold Canadian winters stop you from enjoying your new car. The addition of the Engine Block Heater will help ensure a smooth start even on the coldest days. | G81: Ne laissez pas nos hivers froids vous priver du plaisir de votre voiture. L'ajout du chauffe-bloc aidera à assurer le démarrage de votre voiture, même aux températures les plus basses. | H81: 1.2 | J81: =VLOOKUP(B81,'[1]MASTER PART LIST'!$B:$C,2,FALSE) -> 144 | K81: =VLOOKUP(B81,'[1]MASTER PART LIST'!$B:$D,3,FALSE) -> 240 | L81: =K81+(H81*VLOOKUP(prov_cd,rate_table,2,FALSE)) -> 422.4 | O81: • | Q81: N/A | R81: N/A | W81: 41 | AL81: • | AS81: 23ACC-COLD-PKH Cold Weather Package
B82: 08T44-30B-300A | C82: =B82 -> 08T44-30B-300A | D82: Engine Block Heater | E82: Chauffe-moteur | F82: Don't let the cold Canadian winters stop you from enjoying your new car. The addition of the Engine Block Heater will help ensure a smooth start even on the coldest days. | G82: Ne laissez pas nos hivers froids vous priver du plaisir de votre voiture. L'ajout du chauffe-bloc aidera à assurer le démarrage de votre voiture, même aux températures les plus basses. | H82: 1.2 | J82: =VLOOKUP(B82,'[1]MASTER PART LIST'!$B:$C,2,FALSE) -> 171 | K82: =VLOOKUP(B82,'[1]MASTER PART LIST'!$B:$D,3,FALSE) -> 285 | L82: =K82+(H82*VLOOKUP(prov_cd,rate_table,2,FALSE)) -> 467.4 | O82: N/A | Q82: • | R82: • | W82: 42 | AL82: • | AS82: 23ACC-COLD-PKP Cold Weather Package
B83: 31670-BMS-004H | C83: =B83 -> 31670-BMS-004H | D83: Optimate 12V Auto Battery Charger/Maintainer | E83: Chargeur/mainteneur de batterie automobile 12 V Optimate | F83: Extended battery life by charging/maintaining a Honda battery to ideal charge levels. | G83: Vie prolongée de la batterie Honda en maintenant la charge au niveau ideal. | H83: 0 | J83: =VLOOKUP(B83,'[1]MASTER PART LIST'!$B:$C,2,FALSE) -> 94 | K83: =VLOOKUP(B83,'[1]MASTER PART LIST'!$B:$D,3,FALSE) -> 157 | L83: =K83+(H83*VLOOKUP(prov_cd,rate_table,2,FALSE)) -> 157 | O83: • | Q83: • | R83: • | W83: 43 | X83: Yes | AL83: • | AS83: 23ACC-COLD-PKP Cold Weather Package 23ACC-COLD-PKH Cold Weather Package
B84: 31670-BMS-LEAD | C84: N/A App Chart only | D84: Optimate Battery Lead | E84: Câble de batterie | H84: 0 | J84: =VLOOKUP(B84,'[1]MASTER PART LIST'!$B:$C,2,FALSE) -> 20 | K84: =VLOOKUP(B84,'[1]MASTER PART LIST'!$B:$D,3,FALSE) -> 28 | L84: =K84+(H84*VLOOKUP(prov_cd,rate_table,2,FALSE)) -> 28 | O84: • | Q84: • | R84: •
B85: TUPP-HONDA | C85: TUCH-NH883P-A1 | D85: Paint Pens | E85: Crayon de retouche de peinture | F85: Matched to your original paint colour, keep the Touch-Up Paint Pen on hand to conveniently cover minor scratches should they occur. | G85: Puisque celui-ci est agencé à la couleur de votre peinture d'origine, gardez un crayon de peinture de retouche sous la main pour masquer de petites égratignures imprévues. | H85: =H86 -> 0 | J85: =J86 -> 13.25 | K85: =K86 -> 22 | L85: =K85+(H85*VLOOKUP(prov_cd,rate_table,2,FALSE)) -> 22 | O85: • | Q85: • | R85: • | W85: 249 | AP85: •
B86: TUCH-NH883P-A1 | C86: N/A | D86: Platinum White Pearl (NH-883P) | E86: Blanc platine nacré (NH-883P) | H86: 0 | J86: =VLOOKUP(B86,'[1]MASTER PART LIST'!$B:$C,2,FALSE) -> 13.25 | K86: =VLOOKUP(B86,'[1]MASTER PART LIST'!$B:$D,3,FALSE) -> 22 | L86: =K86+(H86*VLOOKUP(prov_cd,rate_table,2,FALSE)) -> 22 | O86: • | Q86: • | R86: •
B87: TUCHNH904MA1 | C87: N/A | D87: Meteoroid Gray Pearl (NH-904M) | E87: Gris météore nacré (NH-904M) | H87: 0 | J87: =VLOOKUP(B87,'[1]MASTER PART LIST'!$B:$C,2,FALSE) -> #N/A | K87: =VLOOKUP(B87,'[1]MASTER PART LIST'!$B:$D,3,FALSE) -> #N/A | L87: =K87+(H87*VLOOKUP(prov_cd,rate_table,2,FALSE)) -> #N/A | O87: N/A | Q87: • | R87: N/A
B88: TUCHNH912PA1 | C88: N/A | D88: Urban Grey Pearl (NH-912P) | E88: Gris urbain nacré (NH-912P) | H88: 0 | J88: =VLOOKUP(B88,'[1]MASTER PART LIST'!$B:$C,2,FALSE) -> #N/A | K88: =VLOOKUP(B88,'[1]MASTER PART LIST'!$B:$D,3,FALSE) -> #N/A | L88: =K88+(H88*VLOOKUP(prov_cd,rate_table,2,FALSE)) -> #N/A | O88: N/A | Q88: N/A | R88: •
B89: TUCH-NH731P-A1 | C89: N/A | D89: Crystal Black Pearl (NH-731P) | E89: Noir cristal nacré (NH-731P) | H89: 0 | J89: =VLOOKUP(B89,'[1]MASTER PART LIST'!$B:$C,2,FALSE) -> 13.25 | K89: =VLOOKUP(B89,'[1]MASTER PART LIST'!$B:$D,3,FALSE) -> 22 | L89: =K89+(H89*VLOOKUP(prov_cd,rate_table,2,FALSE)) -> 22 | O89: • | Q89: • | R89: •
B90: TUCH-R569M-A1 | C90: N/A | D90: Radiant Red Metallic (R-569M) | E90: Radiant rouge métallisé (R-569M) | H90: 0 | J90: =VLOOKUP(B90,'[1]MASTER PART LIST'!$B:$C,2,FALSE) -> 13.25 | K90: =VLOOKUP(B90,'[1]MASTER PART LIST'!$B:$D,3,FALSE) -> 22 | L90: =K90+(H90*VLOOKUP(prov_cd,rate_table,2,FALSE)) -> 22 | O90: N/A | Q90: • | R90: •
B91: TUCH-B640M-A1 | C91: N/A | D91: Canyon River Blue Metallic (B-640M) | E91: Bleu rivière canyon métallisé (B-640M) | H91: 0 | J91: =VLOOKUP(B91,'[1]MASTER PART LIST'!$B:$C,2,FALSE) -> 13.25 | K91: =VLOOKUP(B91,'[1]MASTER PART LIST'!$B:$D,3,FALSE) -> 22 | L91: =K91+(H91*VLOOKUP(prov_cd,rate_table,2,FALSE)) -> 22 | O91: N/A | Q91: N/A | R91: •
B92: TUCH-B575P-A1 | C92: N/A | D92: Still Night Pearl (B-575P) | E92: Nuit paisible fini nacré (B-575P) | H92: 0 | J92: =VLOOKUP(B92,'[1]MASTER PART LIST'!$B:$C,2,FALSE) -> 13.25 | K92: =VLOOKUP(B92,'[1]MASTER PART LIST'!$B:$D,3,FALSE) -> 22 | L92: =K92+(H92*VLOOKUP(prov_cd,rate_table,2,FALSE)) -> 22 | O92: N/A | Q92: • | R92: N/A
B93: TUCH-NH932M-A1 | C93: N/A | D93: Solar Reflection Silver (NH-932M) | E93: Refl et solaire argent métallisé (NH-932M) | H93: 0 | J93: =VLOOKUP(B93,'[1]MASTER PART LIST'!$B:$C,2,FALSE) -> 13.25 | K93: =VLOOKUP(B93,'[1]MASTER PART LIST'!$B:$D,3,FALSE) -> 22 | L93: =K93+(H93*VLOOKUP(prov_cd,rate_table,2,FALSE)) -> 22 | O93: • | Q93: • | R93: •
B94: TUCH-NEEDLES | C94: TUCH-NEEDLES | D94: Fine Sanding Needles | E94: Aiguilles abrasives fines | H94: 0 | J94: =VLOOKUP(B94,'[1]MASTER PART LIST'!$B:$C,2,FALSE) -> 9.5 | K94: =VLOOKUP(B94,'[1]MASTER PART LIST'!$B:$D,3,FALSE) -> 15.75 | L94: =K94+(H94*VLOOKUP(prov_cd,rate_table,2,FALSE)) -> 15.75 | U94: Quantity of 5. | V94: Quantité de 5 | AP94: •
B95: TUCH-STICKS | C95: TUCH-STICKS | D95: Fine Sanding Sticks | E95: Bâtons abrasifs fins | H95: 0 | J95: =VLOOKUP(B95,'[1]MASTER PART LIST'!$B:$C,2,FALSE) -> 2.45 | K95: =VLOOKUP(B95,'[1]MASTER PART LIST'!$B:$D,3,FALSE) -> 4 | L95: =K95+(H95*VLOOKUP(prov_cd,rate_table,2,FALSE)) -> 4 | U95: Quantity of 5. | V95: Quantité de 5 | AP95: •
B96: TUCH-TIPS | C96: TUCH-TIPS | D96: Paint Pen Replacement Tips | E96: Pointes de remplacement pour stylos de peinture | H96: 0 | J96: =VLOOKUP(B96,'[1]MASTER PART LIST'!$B:$C,2,FALSE) -> 6.25 | K96: =VLOOKUP(B96,'[1]MASTER PART LIST'!$B:$D,3,FALSE) -> 13.75 | L96: =K96+(H96*VLOOKUP(prov_cd,rate_table,2,FALSE)) -> 13.75 | U96: Quantity of 25. | V96: Quantité de 25 | AP96: •
A101: DROPPED for 26MY | B101: 23ACC-BLK-TRHY | C101: =B101 -> 23ACC-BLK-TRHY | D101: Black Emblem Set - Touring | E101: Ensemble d’emblèmes noirs – Touring | F101: Includes Rear "H" mark, "Accord" and "Touring" black emblems. Packaged together with a 5% discount. | G101: Comprend les emblèmes noirs « H » arrière, « Accord » et « Touring ». Offerts en ensemble avec une réduction de 5%. | H101: =H103+H27 -> 0.7 | J101: =(J103+J26)*0.95 -> 113.05 | K101: =(K103+K26)*0.95 -> 188.1 | L101: =K101+(H101*VLOOKUP(prov_cd,rate_table,2,FALSE)) -> 294.5 | O101: N/A | Q101: N/A | R101: • | U101: 5% Discount Applied. | V101: Rabais de 5 % appliqué. | X101: Yes | AI101: • | AO101: • | AS101: 08F20-30A-100 Black Emblem Rear "H" mark & Accord 08F20-3A0-100C Black Emblem, Touring
A102: DROPPED for 26MY | B102: 23ACC-BLK-SPHY | C102: =B102 -> 23ACC-BLK-SPHY | D102: Black Emblem Set - Sport | E102: Ensemble d’emblèmes noirs – Sport | F102: Includes Rear "H" mark, "Accord" and "Sport" black emblems. Packaged together with a 5% discount. | G102: Comprend les emblèmes noirs « H » arrière, « Accord » et « Sport ». Offerts en ensemble avec une réduction de 5%. | H102: =H103+H104 -> 0.8 | J102: =(J103+J104)*0.95 -> 113.05 | K102: =(K103+K104)*0.95 -> 188.1 | L102: =K102+(H102*VLOOKUP(prov_cd,rate_table,2,FALSE)) -> 309.7 | O102: N/A | Q102: • | R102: N/A | U102: 5% Discount Applied. | V102: Rabais de 5 % appliqué. | X102: Yes | AI102: • | AO102: • | AS102: 08F20-30A-100 Black Emblem Rear "H" mark & Accord 08F20-TVA-100C Black Emblem, Sport
A103: DROPPED for 26MY | B103: 08F20-30A-100 | C103: =B103 -> 08F20-30A-100 | D103: Black Emblem Rear "H" mark & Accord | E103: Emblème, noirs lustré arrière « H » mark et « Accord » | F103: If attention to detail is important to you then you’re sure to love the look of the Gloss Black H-Mark and Accord Emblems. | G103: Si l’attention aux détails est importante pour vous, vous aimerez certainement l’allure des emblèmes « H » et Accord noir lustré. | H103: 0.5 | J103: =VLOOKUP(B103,'[1]MASTER PART LIST'!$B:$C,2,FALSE) -> 75 | K103: =VLOOKUP(B103,'[1]MASTER PART LIST'!$B:$D,3,FALSE) -> 125 | L103: =K103+(H103*VLOOKUP(prov_cd,rate_table,2,FALSE)) -> 201 | O103: • | Q103: N/A | R103: • | U103: Front and Rear H-Mark Logo. | V103: Logo H-Mark à l'avant et à l'arrière. | AO103: • | AS103: 23ACC-BLK-SPHY Black Emblem Set - Sport 23ACC-BLK-TRHY Black Emblem Set - Touring
A104: DROPPED for 26MY | B104: 08F20-TVA-100C | C104: =B104 -> 08F20-TVA-100C | D104: Black Emblem, Sport | E104: Emblème, noirs lustré « Sport » | F104: Add a unique and bold style with these gloss black emblems. Pair up with with H-Mark & Civic emblems to complete the look - sold separately. | G104: Donnez un style unique et audacieux avec ces emblèmes noir lustré. Jumelez-les aux emblèmes « H » et Civic pour compléter le style (vendus séparément). | H104: 0.3 | J104: =VLOOKUP(B104,'[1]MASTER PART LIST'!$B:$C,2,FALSE) -> 44 | K104: =VLOOKUP(B104,'[1]MASTER PART LIST'!$B:$D,3,FALSE) -> 73 | L104: =K104+(H104*VLOOKUP(prov_cd,rate_table,2,FALSE)) -> 118.6 | O104: N/A | Q104: N/A | R104: N/A | AO104: • | AS104: 23ACC-BLK-SPHY Black Emblem Set - Sport
A105: DROPPED for 26MY | B105: 08U58-30A-110A | C105: =B105 -> 08U58-30A-110A | D105: Wireless Charger | E105: Chargeur sans fil | F105: The Wireless Phone Charger provides a hassle-free charging zone that's easy to access and use. No more need for adapters and cords, flat charging surface keeps interior sleek and clean. Requires Qi enabled wireless device. | G105: Le chargeur de téléphone sans fil offre un espace de charge convivial, facile d’accès et d’utilisation. Plus besoin d’adaptateurs et de cordons, la surface de chargement plate permet de conserver un intérieur propre et élégant. Nécessite un appareil sans fil Qi pour téléphones compatibles. | H105: 1.5 | J105: =VLOOKUP(B105,'[1]MASTER PART LIST'!$B:$C,2,FALSE) -> 383 | K105: =VLOOKUP(B105,'[1]MASTER PART LIST'!$B:$D,3,FALSE) -> 547 | L105: =K105+(H105*VLOOKUP(prov_cd,rate_table,2,FALSE)) -> 775 | O105: • | Q105: S | R105: S | X105: Yes | AM105: •
A106: DROPPED for 25MY | B106: 08U58-30A-110B | C106: =B106 -> 08U58-30A-110B | D106: Wireless Charger | E106: Chargeur sans fil | F106: The Wireless Phone Charger provides a hassle-free charging zone that's easy to access and use. No more need for adapters and cords, flat charging surface keeps interior sleek and clean. Requires Qi enabled wireless device. | G106: Le chargeur de téléphone sans fil offre un espace de charge convivial, facile d’accès et d’utilisation. Plus besoin d’adaptateurs et de cordons, la surface de chargement plate permet de conserver un intérieur propre et élégant. Nécessite un appareil sans fil Qi pour téléphones compatibles. | H106: 1.5 | J106: =VLOOKUP(B106,'[1]MASTER PART LIST'!$B:$C,2,FALSE) -> 383 | K106: =VLOOKUP(B106,'[1]MASTER PART LIST'!$B:$D,3,FALSE) -> 547 | L106: =K106+(H106*VLOOKUP(prov_cd,rate_table,2,FALSE)) -> 775 | O106: N/A | Q106: • | R106: S | X106: Yes | AM106: •

Sheet SELECT PROVINCE
A1: Select Province: Choissisez votre province: | B1: QC
B4: Current Labor Rates
B5: Taux de main d'oeuvre en cours
B6: AB | C6: 171
B7: BC | C7: 181
B8: MB | C8: 164
B9: NB | C9: 142
B10: NL | C10: 142
B11: NS | C11: 142
B12: ON | C12: 160 | F12: =prov_cd -> QC
B13: PEI | C13: 134
B14: QC | C14: 152
B15: SK | C15: 164
B16: YT | C16: 181
A23: All published prices, trim specifications, and availability are subject to change without prior notice.
A24: Tout prix, spécifications de versions et disponibilté d'accessoires publiés sont sujets à changer sans pré-avis.

Sheet 26MY_ACCORD_APP_EN
C2: Honda Accessories
C3: Model Name | D3: ='26MY_ACCORD_DATA'!$C$2 -> Accord
C4: Model Year | D4: ='26MY_ACCORD_DATA'!$C$3 -> 2026
C5: S = Standard (accessory comes standard on this trim)
C6: T = Tire Size Change (the size of the accessory wheel is smaller/larger than the OE Wheel. Customer will require new tires to fit these wheels.)
C7: E = Exchange Standard Equipment (the size of the accessory wheel is the same size as the OE wheel and therefore they can use the OE tire.)
C8: N/A = Not Applicable (accessory cannot be applied to this trim)
H10: Province
C11: 1.0 Packages and Kits | H11: =prov_cd -> QC
C12: Description | D12: Part Number | E12: Dealer Net | F12: List Price | G12: FRT | H12: Installed Price | J12: Application | Q12: Comments
I13: ='26MY_ACCORD_DATA'!$M$7 -> 0 | J13: ='26MY_ACCORD_DATA'!$M$7 -> 0 | K13: ='26MY_ACCORD_DATA'!$O$7 -> SE | L13: ='26MY_ACCORD_DATA'!$P$7 -> 0 | M13: ='26MY_ACCORD_DATA'!$Q$7 -> Sport -L Hybrid | N13: ='26MY_ACCORD_DATA'!$R$7 -> Touring Hybrid | O13: ='26MY_ACCORD_DATA'!$T$7 -> 0 | P13: ='26MY_ACCORD_DATA'!$T$7 -> 0
B14: 23ACC-PRO-PK | C14: =VLOOKUP(B14,'26MY_ACCORD_DATA'!B:AS,3,FALSE) -> Protection Package | D14: =B14 -> 23ACC-PRO-PK | E14: =VLOOKUP(B14,'26MY_ACCORD_DATA'!B:AS,9,FALSE) -> 273.6 | F14: =VLOOKUP(B14,'26MY_ACCORD_DATA'!B:AS,10,FALSE) -> 507 | G14: =VLOOKUP(B14,'26MY_ACCORD_DATA'!B:AS,7,FALSE) -> 0.2 | H14: =VLOOKUP(B14,'26MY_ACCORD_DATA'!B:AS,11,FALSE) -> 537.4 | I14: =VLOOKUP($B14,'26MY_ACCORD_DATA'!$B:$AS,12,FALSE) -> 0 | J14: =VLOOKUP($B14,'26MY_ACCORD_DATA'!$B:$AS,13,FALSE) -> 0 | K14: =VLOOKUP(B14,'26MY_ACCORD_DATA'!B:AS,14,FALSE) -> • | L14: =VLOOKUP(B14,'26MY_ACCORD_DATA'!B:AS,15,FALSE) -> 0 | M14: =VLOOKUP(B14,'26MY_ACCORD_DATA'!B:AS,16,FALSE) -> • | N14: =VLOOKUP(B14,'26MY_ACCORD_DATA'!B:AS,17,FALSE) -> • | O14: =VLOOKUP($B14,'26MY_ACCORD_DATA'!$B:$AS,18,FALSE) -> 0 | P14: =VLOOKUP(B14,'26MY_ACCORD_DATA'!B:AS,19,FALSE) -> 0 | Q14: =IF(VLOOKUP(B14,'26MY_ACCORD_DATA'!B:AS,20,FALSE)="","",VLOOKUP(B14,'26MY_ACCORD_DATA'!B:AS,20,FALSE))
B15: 08P17-30A-110 | C15: =VLOOKUP(B15,'26MY_ACCORD_DATA'!B:AS,3,FALSE) -> All Season Floor Mats | D15: =B15 -> 08P17-30A-110
B16: 08U45-30A-100 | C16: =VLOOKUP(B16,'26MY_ACCORD_DATA'!B:AS,3,FALSE) -> Trunk Tray | D16: =B16 -> 08U45-30A-100
B18: 23ACC-PRO-PKA | C18: =VLOOKUP(B18,'26MY_ACCORD_DATA'!B:AS,3,FALSE) -> Protection Package Advance | D18: =B18 -> 23ACC-PRO-PKA | E18: =VLOOKUP(B18,'26MY_ACCORD_DATA'!B:AS,9,FALSE) -> 342.891 | F18: =VLOOKUP(B18,'26MY_ACCORD_DATA'!B:AS,10,FALSE) -> 583.2 | G18: =VLOOKUP(B18,'26MY_ACCORD_DATA'!B:AS,7,FALSE) -> 1 | H18: =VLOOKUP(B18,'26MY_ACCORD_DATA'!B:AS,11,FALSE) -> 735.2 | I18: =VLOOKUP(B18,'26MY_ACCORD_DATA'!B:AS,12,FALSE) -> 0 | J18: =VLOOKUP(B18,'26MY_ACCORD_DATA'!B:AS,13,FALSE) -> 0 | K18: =VLOOKUP(B18,'26MY_ACCORD_DATA'!B:AS,14,FALSE) -> • | L18: =VLOOKUP(B18,'26MY_ACCORD_DATA'!B:AS,15,FALSE) -> 0 | M18: =VLOOKUP(B18,'26MY_ACCORD_DATA'!B:AS,16,FALSE) -> • | N18: =VLOOKUP(B18,'26MY_ACCORD_DATA'!B:AS,17,FALSE) -> N/A | O18: =VLOOKUP(B18,'26MY_ACCORD_DATA'!B:AS,18,FALSE) -> 0 | P18: =VLOOKUP(B18,'26MY_ACCORD_DATA'!B:AS,19,FALSE) -> 0 | Q18: =IF(VLOOKUP(B18,'26MY_ACCORD_DATA'!B:AS,20,FALSE)="","",VLOOKUP(B18,'26MY_ACCORD_DATA'!B:AS,20,FALSE)) -> 10% Discount Applied.
B19: 08P17-30A-110 | C19: =VLOOKUP(B19,'26MY_ACCORD_DATA'!B:AS,3,FALSE) -> All Season Floor Mats | D19: =B19 -> 08P17-30A-110
B20: 08U45-30A-100 | C20: =VLOOKUP(B20,'26MY_ACCORD_DATA'!B:AS,3,FALSE) -> Trunk Tray | D20: =B20 -> 08U45-30A-100
B21: 08P09-30A-300 | C21: =VLOOKUP(B21,'26MY_ACCORD_DATA'!B:AS,3,FALSE) -> Rear Splash Guards | D21: =B21 -> 08P09-30A-300
B22: 08L96-TVA-300 | C22: =VLOOKUP(B22,'26MY_ACCORD_DATA'!B:AS,3,FALSE) -> Cargo Net | D22: =B22 -> 08L96-TVA-300
B24: 26ACC-BLK-EMB | C24: =VLOOKUP(B24,'26MY_ACCORD_DATA'!B:AS,3,FALSE) -> Black Emblem Set - Touring | D24: =B24 -> 26ACC-BLK-EMB | E24: =VLOOKUP(B24,'26MY_ACCORD_DATA'!B:AS,9,FALSE) -> 155.8 | F24: =VLOOKUP(B24,'26MY_ACCORD_DATA'!B:AS,10,FALSE) -> 260.3 | G24: =VLOOKUP(B24,'26MY_ACCORD_DATA'!B:AS,7,FALSE) -> 0.9 | H24: =VLOOKUP(B24,'26MY_ACCORD_DATA'!B:AS,11,FALSE) -> 397.1 | I24: =VLOOKUP($B24,'26MY_ACCORD_DATA'!$B:$AS,12,FALSE) -> 0 | J24: =VLOOKUP($B24,'26MY_ACCORD_DATA'!$B:$AS,13,FALSE) -> 0 | K24: =VLOOKUP(B24,'26MY_ACCORD_DATA'!B:AS,14,FALSE) -> N/A | L24: =VLOOKUP(B24,'26MY_ACCORD_DATA'!B:AS,15,FALSE) -> 0 | M24: =VLOOKUP(B24,'26MY_ACCORD_DATA'!B:AS,16,FALSE) -> N/A | N24: =VLOOKUP(B24,'26MY_ACCORD_DATA'!B:AS,17,FALSE) -> • | O24: =VLOOKUP($B24,'26MY_ACCORD_DATA'!$B:$AS,18,FALSE) -> 0 | P24: =VLOOKUP(B24,'26MY_ACCORD_DATA'!B:AS,19,FALSE) -> 0 | Q24: =IF(VLOOKUP(B24,'26MY_ACCORD_DATA'!B:AS,20,FALSE)="","",VLOOKUP(B24,'26MY_ACCORD_DATA'!B:AS,20,FALSE)) -> 5% Discount Applied.
B25: 08F20-30A-100C | C25: =VLOOKUP(B25,'26MY_ACCORD_DATA'!B:AS,3,FALSE) -> Black Emblem Rear "H" mark | D25: =B25 -> 08F20-30A-100C
B26: 08F20-30A-100D | C26: =VLOOKUP(B26,'26MY_ACCORD_DATA'!B:AS,3,FALSE) -> Black Emblem, Accord | D26: =B26 -> 08F20-30A-100D
B27: 08F20-3A0-100C | C27: =VLOOKUP(B27,'26MY_ACCORD_DATA'!B:AS,3,FALSE) -> Black Emblem, Touring | D27: =B27 -> 08F20-3A0-100C
B28: 08F20-T20-100B | C28: =VLOOKUP(B28,'26MY_ACCORD_DATA'!B:AS,3,FALSE) -> Black Emblem, Hybrid | D28: =B28 -> 08F20-T20-100B
B30: 23ACC-ARO-EX | C30: =VLOOKUP(B30,'26MY_ACCORD_DATA'!B:AS,3,FALSE) -> Aero Kit - SE Trim | D30: =B30 -> 23ACC-ARO-EX | E30: =VLOOKUP(B30,'26MY_ACCORD_DATA'!B:AS,9,FALSE) -> 1555.2 | F30: =VLOOKUP(B30,'26MY_ACCORD_DATA'!B:AS,10,FALSE) -> 2591.1 | G30: =VLOOKUP(B30,'26MY_ACCORD_DATA'!B:AS,7,FALSE) -> 3.5 | H30: =VLOOKUP(B30,'26MY_ACCORD_DATA'!B:AS,11,FALSE) -> 3123.1 | I30: =VLOOKUP(B30,'26MY_ACCORD_DATA'!B:AS,12,FALSE) -> 0 | J30: =VLOOKUP(B30,'26MY_ACCORD_DATA'!B:AS,13,FALSE) -> 0 | K30: =VLOOKUP(B30,'26MY_ACCORD_DATA'!B:AS,14,FALSE) -> • | L30: =VLOOKUP(B30,'26MY_ACCORD_DATA'!B:AS,15,FALSE) -> 0 | M30: =VLOOKUP(B30,'26MY_ACCORD_DATA'!B:AS,16,FALSE) -> N/A | N30: =VLOOKUP(B30,'26MY_ACCORD_DATA'!B:AS,17,FALSE) -> N/A | O30: =VLOOKUP(B30,'26MY_ACCORD_DATA'!B:AS,18,FALSE) -> 0 | P30: =VLOOKUP(B30,'26MY_ACCORD_DATA'!B:AS,19,FALSE) -> 0 | Q30: =IF(VLOOKUP(B30,'26MY_ACCORD_DATA'!B:AS,20,FALSE)="","",VLOOKUP(B30,'26MY_ACCORD_DATA'!B:AS,20,FALSE)) -> 10% Discount Applied Decklid Spoiler - Crystal Black Pearl (NH-731P) colour
B31: 08F04-30A-1F0 | C31: =VLOOKUP(B31,'26MY_ACCORD_DATA'!B:AS,3,FALSE) -> Side Underbody Spoiler | D31: =B31 -> 08F04-30A-1F0
B32: 08P98-30A-1F0 | C32: =VLOOKUP(B32,'26MY_ACCORD_DATA'!B:AS,3,FALSE) -> Front Aero Bumper | D32: =B32 -> 08P98-30A-1F0
B33: 08P99-30A-1F0 | C33: =VLOOKUP(B33,'26MY_ACCORD_DATA'!B:AS,3,FALSE) -> Rear Aero Bumper | D33: =B33 -> 08P99-30A-1F0
B34: 08F10-30A-170 | C34: =VLOOKUP(B34,'26MY_ACCORD_DATA'!B:AS,3,FALSE) -> Crystal Black Pearl (NH-731P) | D34: =B34 -> 08F10-30A-170
B35: 08R06-30A-110 | C35: =VLOOKUP(B35,'26MY_ACCORD_DATA'!B:AS,3,FALSE) -> Door Mirror Covers & Lower Intake Accents | D35: =B35 -> 08R06-30A-110
B37: 23ACC-ARO-SPHY | C37: =VLOOKUP(B37,'26MY_ACCORD_DATA'!B:AS,3,FALSE) -> Aero Kit - Sport Trim | D37: =B37 -> 23ACC-ARO-SPHY | E37: =VLOOKUP(B37,'26MY_ACCORD_DATA'!B:AS,9,FALSE) -> 1018.8 | F37: =VLOOKUP(B37,'26MY_ACCORD_DATA'!B:AS,10,FALSE) -> 1697.4 | G37: =VLOOKUP(B37,'26MY_ACCORD_DATA'!B:AS,7,FALSE) -> 1.8 | H37: =VLOOKUP(B37,'26MY_ACCORD_DATA'!B:AS,11,FALSE) -> 1971 | I37: =VLOOKUP(B37,'26MY_ACCORD_DATA'!B:AS,12,FALSE) -> 0 | J37: =VLOOKUP(B37,'26MY_ACCORD_DATA'!B:AS,13,FALSE) -> 0 | K37: =VLOOKUP(B37,'26MY_ACCORD_DATA'!B:AS,14,FALSE) -> N/A | L37: =VLOOKUP(B37,'26MY_ACCORD_DATA'!B:AS,15,FALSE) -> 0 | M37: =VLOOKUP(B37,'26MY_ACCORD_DATA'!B:AS,16,FALSE) -> • | N37: =VLOOKUP(B37,'26MY_ACCORD_DATA'!B:AS,17,FALSE) -> N/A | O37: =VLOOKUP(B37,'26MY_ACCORD_DATA'!B:AS,18,FALSE) -> 0 | P37: =VLOOKUP(B37,'26MY_ACCORD_DATA'!B:AS,19,FALSE) -> 0 | Q37: =IF(VLOOKUP(B37,'26MY_ACCORD_DATA'!B:AS,20,FALSE)="","",VLOOKUP(B37,'26MY_ACCORD_DATA'!B:AS,20,FALSE)) -> 10% Discount Applied Sport Trim already comes standard with Decklid Spoiler
B38: 08F04-30A-1F0 | C38: =VLOOKUP(B38,'26MY_ACCORD_DATA'!B:AS,3,FALSE) -> Side Underbody Spoiler | D38: =B38 -> 08F04-30A-1F0
B39: 08P98-30A-1F0 | C39: =VLOOKUP(B39,'26MY_ACCORD_DATA'!B:AS,3,FALSE) -> Front Aero Bumper | D39: =B39 -> 08P98-30A-1F0
B40: 08P99-30A-1F0 | C40: =VLOOKUP(B40,'26MY_ACCORD_DATA'!B:AS,3,FALSE) -> Rear Aero Bumper | D40: =B40 -> 08P99-30A-1F0
B42: 23ACC-ARO-TRHY | C42: =VLOOKUP(B42,'26MY_ACCORD_DATA'!B:AS,3,FALSE) -> Aero Kit - Touring Trim | D42: =B42 -> 23ACC-ARO-TRHY | E42: =VLOOKUP(B42,'26MY_ACCORD_DATA'!B:AS,9,FALSE) -> 1555.2 | F42: =VLOOKUP(B42,'26MY_ACCORD_DATA'!B:AS,10,FALSE) -> 2591.1 | G42: =VLOOKUP(B42,'26MY_ACCORD_DATA'!B:AS,7,FALSE) -> 3.5 | H42: =VLOOKUP(B42,'26MY_ACCORD_DATA'!B:AS,11,FALSE) -> 3123.1 | I42: =VLOOKUP(B42,'26MY_ACCORD_DATA'!B:AS,12,FALSE) -> 0 | J42: =VLOOKUP(B42,'26MY_ACCORD_DATA'!B:AS,13,FALSE) -> 0 | K42: =VLOOKUP(B42,'26MY_ACCORD_DATA'!B:AS,14,FALSE) -> N/A | L42: =VLOOKUP(B42,'26MY_ACCORD_DATA'!B:AS,15,FALSE) -> 0 | M42: =VLOOKUP(B42,'26MY_ACCORD_DATA'!B:AS,16,FALSE) -> N/A | N42: =VLOOKUP(B42,'26MY_ACCORD_DATA'!B:AS,17,FALSE) -> • | O42: =VLOOKUP(B42,'26MY_ACCORD_DATA'!B:AS,18,FALSE) -> 0 | P42: =VLOOKUP(B42,'26MY_ACCORD_DATA'!B:AS,19,FALSE) -> 0 | Q42: =IF(VLOOKUP(B42,'26MY_ACCORD_DATA'!B:AS,20,FALSE)="","",VLOOKUP(B42,'26MY_ACCORD_DATA'!B:AS,20,FALSE)) -> 10% Discount Applied Decklid Spoiler - Crystal Black Pearl (NH-731P) colour
B43: 08F04-30A-1F0 | C43: =VLOOKUP(B43,'26MY_ACCORD_DATA'!B:AS,3,FALSE) -> Side Underbody Spoiler | D43: =B43 -> 08F04-30A-1F0
B44: 08P98-30A-1F0 | C44: =VLOOKUP(B44,'26MY_ACCORD_DATA'!B:AS,3,FALSE) -> Front Aero Bumper | D44: =B44 -> 08P98-30A-1F0
B45: 08P99-30A-1F0 | C45: =VLOOKUP(B45,'26MY_ACCORD_DATA'!B:AS,3,FALSE) -> Rear Aero Bumper | D45: =B45 -> 08P99-30A-1F0
B46: 08F10-30A-170 | C46: =VLOOKUP(B46,'26MY_ACCORD_DATA'!B:AS,3,FALSE) -> Crystal Black Pearl (NH-731P) | D46: =B46 -> 08F10-30A-170
B47: 08R06-30A-110A | C47: =VLOOKUP(B47,'26MY_ACCORD_DATA'!B:AS,3,FALSE) -> Door Mirror Covers & Lower Intake Accents | D47: =B47 -> 08R06-30A-110A
B49: 23ACC-COLD-PKP | C49: =VLOOKUP(B49,'26MY_ACCORD_DATA'!B:AS,3,FALSE) -> Cold Weather Package | D49: =B49 -> 23ACC-COLD-PKP | E49: =VLOOKUP(B49,'26MY_ACCORD_DATA'!B:AS,9,FALSE) -> 226.1 | F49: =VLOOKUP(B49,'26MY_ACCORD_DATA'!B:AS,10,FALSE) -> 377.15 | G49: =VLOOKUP(B49,'26MY_ACCORD_DATA'!B:AS,7,FALSE) -> 1.2 | H49: =VLOOKUP(B49,'26MY_ACCORD_DATA'!B:AS,11,FALSE) -> 559.55 | I49: =VLOOKUP($B49,'26MY_ACCORD_DATA'!$B:$AS,12,FALSE) -> 0 | J49: =VLOOKUP($B49,'26MY_ACCORD_DATA'!$B:$AS,13,FALSE) -> 0 | K49: =VLOOKUP(B49,'26MY_ACCORD_DATA'!B:AS,14,FALSE) -> • | L49: =VLOOKUP(B49,'26MY_ACCORD_DATA'!B:AS,15,FALSE) -> 0 | M49: =VLOOKUP(B49,'26MY_ACCORD_DATA'!B:AS,16,FALSE) -> N/A | N49: =VLOOKUP(B49,'26MY_ACCORD_DATA'!B:AS,17,FALSE) -> N/A | O49: =VLOOKUP($B49,'26MY_ACCORD_DATA'!$B:$AS,18,FALSE) -> 0 | P49: =VLOOKUP(B49,'26MY_ACCORD_DATA'!B:AS,19,FALSE) -> 0 | Q49: =IF(VLOOKUP(B49,'26MY_ACCORD_DATA'!B:AS,20,FALSE)="","",VLOOKUP(B49,'26MY_ACCORD_DATA'!B:AS,20,FALSE)) -> 5% Discount Applied.
B50: 08T44-30A-300A | C50: =VLOOKUP(B50,'26MY_ACCORD_DATA'!B:AS,3,FALSE) -> Engine Block Heater | D50: =B50 -> 08T44-30A-300A
B51: 31670-BMS-004H | C51: =VLOOKUP(B51,'26MY_ACCORD_DATA'!B:AS,3,FALSE) -> Optimate 12V Auto Battery Charger/Maintainer | D51: =B51 -> 31670-BMS-004H
B53: 23ACC-COLD-PKH | C53: =VLOOKUP(B53,'26MY_ACCORD_DATA'!B:AS,3,FALSE) -> Cold Weather Package | D53: =B53 -> 23ACC-COLD-PKH | E53: =VLOOKUP(B53,'26MY_ACCORD_DATA'!B:AS,9,FALSE) -> 251.75 | F53: =VLOOKUP(B53,'26MY_ACCORD_DATA'!B:AS,10,FALSE) -> 419.9 | G53: =VLOOKUP(B53,'26MY_ACCORD_DATA'!B:AS,7,FALSE) -> 1.2 | H53: =VLOOKUP(B53,'26MY_ACCORD_DATA'!B:AS,11,FALSE) -> 602.3 | I53: =VLOOKUP($B53,'26MY_ACCORD_DATA'!$B:$AS,12,FALSE) -> 0 | J53: =VLOOKUP($B53,'26MY_ACCORD_DATA'!$B:$AS,13,FALSE) -> 0 | K53: =VLOOKUP(B53,'26MY_ACCORD_DATA'!B:AS,14,FALSE) -> N/A | L53: =VLOOKUP(B53,'26MY_ACCORD_DATA'!B:AS,15,FALSE) -> 0 | M53: =VLOOKUP(B53,'26MY_ACCORD_DATA'!B:AS,16,FALSE) -> • | N53: =VLOOKUP(B53,'26MY_ACCORD_DATA'!B:AS,17,FALSE) -> • | O53: =VLOOKUP($B53,'26MY_ACCORD_DATA'!$B:$AS,18,FALSE) -> 0 | P53: =VLOOKUP(B53,'26MY_ACCORD_DATA'!B:AS,19,FALSE) -> 0 | Q53: =IF(VLOOKUP(B53,'26MY_ACCORD_DATA'!B:AS,20,FALSE)="","",VLOOKUP(B53,'26MY_ACCORD_DATA'!B:AS,20,FALSE)) -> 5% Discount Applied.
B54: 08T44-30B-300A | C54: =VLOOKUP(B54,'26MY_ACCORD_DATA'!B:AS,3,FALSE) -> Engine Block Heater | D54: =B54 -> 08T44-30B-300A
B55: 31670-BMS-004H | C55: =VLOOKUP(B55,'26MY_ACCORD_DATA'!B:AS,3,FALSE) -> Optimate 12V Auto Battery Charger/Maintainer | D55: =B55 -> 31670-BMS-004H
C57: 2.0 Wheels and Wheel Accessories
C58: Description | D58: Part Number | E58: Dealer Net | F58: List Price | G58: FRT | H58: Installed Price | J58: Application | Q58: Comments
I59: ='26MY_ACCORD_DATA'!$M$7 -> 0 | J59: ='26MY_ACCORD_DATA'!$M$7 -> 0 | K59: ='26MY_ACCORD_DATA'!$O$7 -> SE | L59: ='26MY_ACCORD_DATA'!$P$7 -> 0 | M59: ='26MY_ACCORD_DATA'!$Q$7 -> Sport -L Hybrid | N59: ='26MY_ACCORD_DATA'!$R$7 -> Touring Hybrid | O59: ='26MY_ACCORD_DATA'!$T$7 -> 0 | P59: ='26MY_ACCORD_DATA'!$T$7 -> 0
B60: 08W17-PC4-300 | C60: =VLOOKUP(B60,'26MY_ACCORD_DATA'!B:AS,3,FALSE) -> 17" Steel Wheels | D60: =B60 -> 08W17-PC4-300 | E60: =VLOOKUP(B60,'26MY_ACCORD_DATA'!B:AS,9,FALSE) -> 376.4 | F60: =VLOOKUP(B60,'26MY_ACCORD_DATA'!B:AS,10,FALSE) -> 627.28 | G60: =VLOOKUP(B60,'26MY_ACCORD_DATA'!B:AS,7,FALSE) -> 1.6 | H60: =VLOOKUP(B60,'26MY_ACCORD_DATA'!B:AS,11,FALSE) -> 870.48 | I60: =VLOOKUP(B60,'26MY_ACCORD_DATA'!B:AS,12,FALSE) -> 0 | J60: =VLOOKUP(B60,'26MY_ACCORD_DATA'!B:AS,13,FALSE) -> 0 | K60: =VLOOKUP(B60,'26MY_ACCORD_DATA'!B:AS,14,FALSE) -> T | L60: =VLOOKUP(B60,'26MY_ACCORD_DATA'!B:AS,15,FALSE) -> 0 | M60: =VLOOKUP(B60,'26MY_ACCORD_DATA'!B:AS,16,FALSE) -> T | N60: =VLOOKUP(B60,'26MY_ACCORD_DATA'!B:AS,17,FALSE) -> T | O60: =VLOOKUP(B60,'26MY_ACCORD_DATA'!B:AS,18,FALSE) -> 0 | P60: =VLOOKUP(B60,'26MY_ACCORD_DATA'!B:AS,19,FALSE) -> 0 | Q60: =IF(VLOOKUP(B60,'26MY_ACCORD_DATA'!B:AS,20,FALSE)="","",VLOOKUP(B60,'26MY_ACCORD_DATA'!B:AS,20,FALSE)) -> Priced as a set of 4 wheels. Tires sold separately.
B61: 08W19-30A-300 | C61: =VLOOKUP(B61,'26MY_ACCORD_DATA'!B:AS,3,FALSE) -> 19" HPD Alloy Wheels, Black | D61: =B61 -> 08W19-30A-300 | E61: =VLOOKUP(B61,'26MY_ACCORD_DATA'!B:AS,9,FALSE) -> 2628 | F61: =VLOOKUP(B61,'26MY_ACCORD_DATA'!B:AS,10,FALSE) -> 3756 | G61: =VLOOKUP(B61,'26MY_ACCORD_DATA'!B:AS,7,FALSE) -> 1.6 | H61: =VLOOKUP(B61,'26MY_ACCORD_DATA'!B:AS,11,FALSE) -> 3999.2 | I61: =VLOOKUP(B61,'26MY_ACCORD_DATA'!B:AS,12,FALSE) -> 0 | J61: =VLOOKUP(B61,'26MY_ACCORD_DATA'!B:AS,13,FALSE) -> 0 | K61: =VLOOKUP(B61,'26MY_ACCORD_DATA'!B:AS,14,FALSE) -> E | L61: =VLOOKUP(B61,'26MY_ACCORD_DATA'!B:AS,15,FALSE) -> 0 | M61: =VLOOKUP(B61,'26MY_ACCORD_DATA'!B:AS,16,FALSE) -> E | N61: =VLOOKUP(B61,'26MY_ACCORD_DATA'!B:AS,17,FALSE) -> E | O61: =VLOOKUP(B61,'26MY_ACCORD_DATA'!B:AS,18,FALSE) -> 0 | P61: =VLOOKUP(B61,'26MY_ACCORD_DATA'!B:AS,19,FALSE) -> 0 | Q61: =IF(VLOOKUP(B61,'26MY_ACCORD_DATA'!B:AS,20,FALSE)="","",VLOOKUP(B61,'26MY_ACCORD_DATA'!B:AS,20,FALSE)) -> Priced as a set of 4 wheels. Tires sold separately.
B62: 08W42-SCV-302 | C62: =VLOOKUP(B62,'26MY_ACCORD_DATA'!B:AS,3,FALSE) -> Wheel Locks - Chrome | D62: =B62 -> 08W42-SCV-302 | E62: =VLOOKUP(B62,'26MY_ACCORD_DATA'!B:AS,9,FALSE) -> 54 | F62: =VLOOKUP(B62,'26MY_ACCORD_DATA'!B:AS,10,FALSE) -> 90 | G62: =VLOOKUP(B62,'26MY_ACCORD_DATA'!B:AS,7,FALSE) -> 0.2 | H62: =VLOOKUP(B62,'26MY_ACCORD_DATA'!B:AS,11,FALSE) -> 120.4 | I62: =VLOOKUP(B62,'26MY_ACCORD_DATA'!B:AS,12,FALSE) -> 0 | J62: =VLOOKUP(B62,'26MY_ACCORD_DATA'!B:AS,13,FALSE) -> 0 | K62: =VLOOKUP(B62,'26MY_ACCORD_DATA'!B:AS,14,FALSE) -> • | L62: =VLOOKUP(B62,'26MY_ACCORD_DATA'!B:AS,15,FALSE) -> 0 | M62: =VLOOKUP(B62,'26MY_ACCORD_DATA'!B:AS,16,FALSE) -> • | N62: =VLOOKUP(B62,'26MY_ACCORD_DATA'!B:AS,17,FALSE) -> • | O62: =VLOOKUP(B62,'26MY_ACCORD_DATA'!B:AS,18,FALSE) -> 0 | P62: =VLOOKUP(B62,'26MY_ACCORD_DATA'!B:AS,19,FALSE) -> 0 | Q62: =IF(VLOOKUP(B62,'26MY_ACCORD_DATA'!B:AS,20,FALSE)="","",VLOOKUP(B62,'26MY_ACCORD_DATA'!B:AS,20,FALSE))
B63: 08W42-SNA-301 | C63: =VLOOKUP(B63,'26MY_ACCORD_DATA'!B:AS,3,FALSE) -> Wheel Locks, Chrome - Exposed | D63: =B63 -> 08W42-SNA-301 | E63: =VLOOKUP(B63,'26MY_ACCORD_DATA'!B:AS,9,FALSE) -> 44 | F63: =VLOOKUP(B63,'26MY_ACCORD_DATA'!B:AS,10,FALSE) -> 73 | G63: =VLOOKUP(B63,'26MY_ACCORD_DATA'!B:AS,7,FALSE) -> 0.2 | H63: =VLOOKUP(B63,'26MY_ACCORD_DATA'!B:AS,11,FALSE) -> 103.4 | I63: =VLOOKUP(B63,'26MY_ACCORD_DATA'!B:AS,12,FALSE) -> 0 | J63: =VLOOKUP(B63,'26MY_ACCORD_DATA'!B:AS,13,FALSE) -> 0 | K63: =VLOOKUP(B63,'26MY_ACCORD_DATA'!B:AS,14,FALSE) -> • | L63: =VLOOKUP(B63,'26MY_ACCORD_DATA'!B:AS,15,FALSE) -> 0 | M63: =VLOOKUP(B63,'26MY_ACCORD_DATA'!B:AS,16,FALSE) -> • | N63: =VLOOKUP(B63,'26MY_ACCORD_DATA'!B:AS,17,FALSE) -> • | O63: =VLOOKUP(B63,'26MY_ACCORD_DATA'!B:AS,18,FALSE) -> 0 | P63: =VLOOKUP(B63,'26MY_ACCORD_DATA'!B:AS,19,FALSE) -> 0 | Q63: =IF(VLOOKUP(B63,'26MY_ACCORD_DATA'!B:AS,20,FALSE)="","",VLOOKUP(B63,'26MY_ACCORD_DATA'!B:AS,20,FALSE))
B64: 08W42-S2A-101 | C64: =VLOOKUP(B64,'26MY_ACCORD_DATA'!B:AS,3,FALSE) -> Wheel Locks - Black | D64: =B64 -> 08W42-S2A-101 | E64: =VLOOKUP(B64,'26MY_ACCORD_DATA'!B:AS,9,FALSE) -> 61 | F64: =VLOOKUP(B64,'26MY_ACCORD_DATA'!B:AS,10,FALSE) -> 102 | G64: =VLOOKUP(B64,'26MY_ACCORD_DATA'!B:AS,7,FALSE) -> 0.2 | H64: =VLOOKUP(B64,'26MY_ACCORD_DATA'!B:AS,11,FALSE) -> 132.4 | I64: =VLOOKUP(B64,'26MY_ACCORD_DATA'!B:AS,12,FALSE) -> 0 | J64: =VLOOKUP(B64,'26MY_ACCORD_DATA'!B:AS,13,FALSE) -> 0 | K64: =VLOOKUP(B64,'26MY_ACCORD_DATA'!B:AS,14,FALSE) -> • | L64: =VLOOKUP(B64,'26MY_ACCORD_DATA'!B:AS,15,FALSE) -> 0 | M64: =VLOOKUP(B64,'26MY_ACCORD_DATA'!B:AS,16,FALSE) -> • | N64: =VLOOKUP(B64,'26MY_ACCORD_DATA'!B:AS,17,FALSE) -> • | O64: =VLOOKUP(B64,'26MY_ACCORD_DATA'!B:AS,18,FALSE) -> 0 | P64: =VLOOKUP(B64,'26MY_ACCORD_DATA'!B:AS,19,FALSE) -> 0 | Q64: =IF(VLOOKUP(B64,'26MY_ACCORD_DATA'!B:AS,20,FALSE)="","",VLOOKUP(B64,'26MY_ACCORD_DATA'!B:AS,20,FALSE))
B65: 08W42-PL4-100 | C65: =VLOOKUP(B65,'26MY_ACCORD_DATA'!B:AS,3,FALSE) -> Wheel Lug Nuts - Black | D65: =B65 -> 08W42-PL4-100 | E65: =VLOOKUP(B65,'26MY_ACCORD_DATA'!B:AS,9,FALSE) -> 170 | F65: =VLOOKUP(B65,'26MY_ACCORD_DATA'!B:AS,10,FALSE) -> 283 | G65: =VLOOKUP(B65,'26MY_ACCORD_DATA'!B:AS,7,FALSE) -> 0.2 | H65: =VLOOKUP(B65,'26MY_ACCORD_DATA'!B:AS,11,FALSE) -> 313.4 | I65: =VLOOKUP(B65,'26MY_ACCORD_DATA'!B:AS,12,FALSE) -> 0 | J65: =VLOOKUP(B65,'26MY_ACCORD_DATA'!B:AS,13,FALSE) -> 0 | K65: =VLOOKUP(B65,'26MY_ACCORD_DATA'!B:AS,14,FALSE) -> • | L65: =VLOOKUP(B65,'26MY_ACCORD_DATA'!B:AS,15,FALSE) -> 0 | M65: =VLOOKUP(B65,'26MY_ACCORD_DATA'!B:AS,16,FALSE) -> • | N65: =VLOOKUP(B65,'26MY_ACCORD_DATA'!B:AS,17,FALSE) -> • | O65: =VLOOKUP(B65,'26MY_ACCORD_DATA'!B:AS,18,FALSE) -> 0 | P65: =VLOOKUP(B65,'26MY_ACCORD_DATA'!B:AS,19,FALSE) -> 0 | Q65: =IF(VLOOKUP(B65,'26MY_ACCORD_DATA'!B:AS,20,FALSE)="","",VLOOKUP(B65,'26MY_ACCORD_DATA'!B:AS,20,FALSE)) -> set of 20 lug nuts
C67: 3.0 Exterior
C68: Description | D68: Part Number | E68: Dealer Net | F68: List Price | G68: FRT | H68: Installed Price | J68: Application | Q68: Comments
I69: ='26MY_ACCORD_DATA'!$M$7 -> 0 | J69: ='26MY_ACCORD_DATA'!$M$7 -> 0 | K69: ='26MY_ACCORD_DATA'!$O$7 -> SE | L69: ='26MY_ACCORD_DATA'!$P$7 -> 0 | M69: ='26MY_ACCORD_DATA'!$Q$7 -> Sport -L Hybrid | N69: ='26MY_ACCORD_DATA'!$R$7 -> Touring Hybrid | O69: ='26MY_ACCORD_DATA'!$T$7 -> 0 | P69: ='26MY_ACCORD_DATA'!$T$7 -> 0
B70: 08F04-30A-1F0 | C70: =VLOOKUP(B70,'26MY_ACCORD_DATA'!B:AS,3,FALSE) -> Side Underbody Spoiler | D70: =B70 -> 08F04-30A-1F0 | E70: =VLOOKUP(B70,'26MY_ACCORD_DATA'!B:AS,9,FALSE) -> 432 | F70: =VLOOKUP(B70,'26MY_ACCORD_DATA'!B:AS,10,FALSE) -> 720 | G70: =VLOOKUP(B70,'26MY_ACCORD_DATA'!B:AS,7,FALSE) -> 0.6 | H70: =VLOOKUP(B70,'26MY_ACCORD_DATA'!B:AS,11,FALSE) -> 811.2 | I70: =VLOOKUP(B70,'26MY_ACCORD_DATA'!B:AS,12,FALSE) -> 0 | J70: =VLOOKUP(B70,'26MY_ACCORD_DATA'!B:AS,13,FALSE) -> 0 | K70: =VLOOKUP(B70,'26MY_ACCORD_DATA'!B:AS,14,FALSE) -> • | L70: =VLOOKUP(B70,'26MY_ACCORD_DATA'!B:AS,15,FALSE) -> 0 | M70: =VLOOKUP(B70,'26MY_ACCORD_DATA'!B:AS,16,FALSE) -> • | N70: =VLOOKUP(B70,'26MY_ACCORD_DATA'!B:AS,17,FALSE) -> • | O70: =VLOOKUP(B70,'26MY_ACCORD_DATA'!B:AS,18,FALSE) -> 0 | P70: =VLOOKUP(B70,'26MY_ACCORD_DATA'!B:AS,19,FALSE) -> 0 | Q70: =IF(VLOOKUP(B70,'26MY_ACCORD_DATA'!B:AS,20,FALSE)="","",VLOOKUP(B70,'26MY_ACCORD_DATA'!B:AS,20,FALSE))
B71: 08P98-30A-1F0 | C71: =VLOOKUP(B71,'26MY_ACCORD_DATA'!B:AS,3,FALSE) -> Front Aero Bumper | D71: =B71 -> 08P98-30A-1F0 | E71: =VLOOKUP(B71,'26MY_ACCORD_DATA'!B:AS,9,FALSE) -> 350 | F71: =VLOOKUP(B71,'26MY_ACCORD_DATA'!B:AS,10,FALSE) -> 583 | G71: =VLOOKUP(B71,'26MY_ACCORD_DATA'!B:AS,7,FALSE) -> 0.6 | H71: =VLOOKUP(B71,'26MY_ACCORD_DATA'!B:AS,11,FALSE) -> 674.2 | I71: =VLOOKUP(B71,'26MY_ACCORD_DATA'!B:AS,12,FALSE) -> 0 | J71: =VLOOKUP(B71,'26MY_ACCORD_DATA'!B:AS,13,FALSE) -> 0 | K71: =VLOOKUP(B71,'26MY_ACCORD_DATA'!B:AS,14,FALSE) -> • | L71: =VLOOKUP(B71,'26MY_ACCORD_DATA'!B:AS,15,FALSE) -> 0 | M71: =VLOOKUP(B71,'26MY_ACCORD_DATA'!B:AS,16,FALSE) -> • | N71: =VLOOKUP(B71,'26MY_ACCORD_DATA'!B:AS,17,FALSE) -> • | O71: =VLOOKUP(B71,'26MY_ACCORD_DATA'!B:AS,18,FALSE) -> 0 | P71: =VLOOKUP(B71,'26MY_ACCORD_DATA'!B:AS,19,FALSE) -> 0 | Q71: =IF(VLOOKUP(B71,'26MY_ACCORD_DATA'!B:AS,20,FALSE)="","",VLOOKUP(B71,'26MY_ACCORD_DATA'!B:AS,20,FALSE))
B72: 08P99-30A-1F0 | C72: =VLOOKUP(B72,'26MY_ACCORD_DATA'!B:AS,3,FALSE) -> Rear Aero Bumper | D72: =B72 -> 08P99-30A-1F0 | E72: =VLOOKUP(B72,'26MY_ACCORD_DATA'!B:AS,9,FALSE) -> 350 | F72: =VLOOKUP(B72,'26MY_ACCORD_DATA'!B:AS,10,FALSE) -> 583 | G72: =VLOOKUP(B72,'26MY_ACCORD_DATA'!B:AS,7,FALSE) -> 0.6 | H72: =VLOOKUP(B72,'26MY_ACCORD_DATA'!B:AS,11,FALSE) -> 674.2 | I72: =VLOOKUP(B72,'26MY_ACCORD_DATA'!B:AS,12,FALSE) -> 0 | J72: =VLOOKUP(B72,'26MY_ACCORD_DATA'!B:AS,13,FALSE) -> 0 | K72: =VLOOKUP(B72,'26MY_ACCORD_DATA'!B:AS,14,FALSE) -> • | L72: =VLOOKUP(B72,'26MY_ACCORD_DATA'!B:AS,15,FALSE) -> 0 | M72: =VLOOKUP(B72,'26MY_ACCORD_DATA'!B:AS,16,FALSE) -> • | N72: =VLOOKUP(B72,'26MY_ACCORD_DATA'!B:AS,17,FALSE) -> • | O72: =VLOOKUP(B72,'26MY_ACCORD_DATA'!B:AS,18,FALSE) -> 0 | P72: =VLOOKUP(B72,'26MY_ACCORD_DATA'!B:AS,19,FALSE) -> 0 | Q72: =IF(VLOOKUP(B72,'26MY_ACCORD_DATA'!B:AS,20,FALSE)="","",VLOOKUP(B72,'26MY_ACCORD_DATA'!B:AS,20,FALSE))
B73: 08R06-30A-110 | C73: =VLOOKUP(B73,'26MY_ACCORD_DATA'!B:AS,3,FALSE) -> Door Mirror Covers & Lower Intake Accents | D73: =B73 -> 08R06-30A-110 | E73: =VLOOKUP(B73,'26MY_ACCORD_DATA'!B:AS,9,FALSE) -> 210 | F73: =VLOOKUP(B73,'26MY_ACCORD_DATA'!B:AS,10,FALSE) -> 350 | G73: =VLOOKUP(B73,'26MY_ACCORD_DATA'!B:AS,7,FALSE) -> 1.1 | H73: =VLOOKUP(B73,'26MY_ACCORD_DATA'!B:AS,11,FALSE) -> 517.2 | I73: =VLOOKUP(B73,'26MY_ACCORD_DATA'!B:AS,12,FALSE) -> 0 | J73: =VLOOKUP(B73,'26MY_ACCORD_DATA'!B:AS,13,FALSE) -> 0 | K73: =VLOOKUP(B73,'26MY_ACCORD_DATA'!B:AS,14,FALSE) -> • | L73: =VLOOKUP(B73,'26MY_ACCORD_DATA'!B:AS,15,FALSE) -> 0 | M73: =VLOOKUP(B73,'26MY_ACCORD_DATA'!B:AS,16,FALSE) -> N/A | N73: =VLOOKUP(B73,'26MY_ACCORD_DATA'!B:AS,17,FALSE) -> N/A | O73: =VLOOKUP(B73,'26MY_ACCORD_DATA'!B:AS,18,FALSE) -> 0 | P73: =VLOOKUP(B73,'26MY_ACCORD_DATA'!B:AS,19,FALSE) -> 0 | Q73: =IF(VLOOKUP(B73,'26MY_ACCORD_DATA'!B:AS,20,FALSE)="","",VLOOKUP(B73,'26MY_ACCORD_DATA'!B:AS,20,FALSE))
B74: 08R06-30A-110A | C74: =VLOOKUP(B74,'26MY_ACCORD_DATA'!B:AS,3,FALSE) -> Door Mirror Covers & Lower Intake Accents | D74: =B74 -> 08R06-30A-110A | E74: =VLOOKUP(B74,'26MY_ACCORD_DATA'!B:AS,9,FALSE) -> 210 | F74: =VLOOKUP(B74,'26MY_ACCORD_DATA'!B:AS,10,FALSE) -> 350 | G74: =VLOOKUP(B74,'26MY_ACCORD_DATA'!B:AS,7,FALSE) -> 1.1 | H74: =VLOOKUP(B74,'26MY_ACCORD_DATA'!B:AS,11,FALSE) -> 517.2 | I74: =VLOOKUP(B74,'26MY_ACCORD_DATA'!B:AS,12,FALSE) -> 0 | J74: =VLOOKUP(B74,'26MY_ACCORD_DATA'!B:AS,13,FALSE) -> 0 | K74: =VLOOKUP(B74,'26MY_ACCORD_DATA'!B:AS,14,FALSE) -> N/A | L74: =VLOOKUP(B74,'26MY_ACCORD_DATA'!B:AS,15,FALSE) -> 0 | M74: =VLOOKUP(B74,'26MY_ACCORD_DATA'!B:AS,16,FALSE) -> N/A | N74: =VLOOKUP(B74,'26MY_ACCORD_DATA'!B:AS,17,FALSE) -> • | O74: =VLOOKUP(B74,'26MY_ACCORD_DATA'!B:AS,18,FALSE) -> 0 | P74: =VLOOKUP(B74,'26MY_ACCORD_DATA'!B:AS,19,FALSE) -> 0 | Q74: =IF(VLOOKUP(B74,'26MY_ACCORD_DATA'!B:AS,20,FALSE)="","",VLOOKUP(B74,'26MY_ACCORD_DATA'!B:AS,20,FALSE))
B75: 08F20-30A-100C | C75: =VLOOKUP(B75,'26MY_ACCORD_DATA'!B:AS,3,FALSE) -> Black Emblem Rear "H" mark | D75: =B75 -> 08F20-30A-100C | E75: =VLOOKUP(B75,'26MY_ACCORD_DATA'!B:AS,9,FALSE) -> 37 | F75: =VLOOKUP(B75,'26MY_ACCORD_DATA'!B:AS,10,FALSE) -> 62 | G75: =VLOOKUP(B75,'26MY_ACCORD_DATA'!B:AS,7,FALSE) -> 0.2 | H75: =VLOOKUP(B75,'26MY_ACCORD_DATA'!B:AS,11,FALSE) -> 92.4 | I75: =VLOOKUP(B75,'26MY_ACCORD_DATA'!B:AS,12,FALSE) -> 0 | J75: =VLOOKUP(B75,'26MY_ACCORD_DATA'!B:AS,13,FALSE) -> 0 | K75: =VLOOKUP(B75,'26MY_ACCORD_DATA'!B:AS,14,FALSE) -> • | L75: =VLOOKUP(B75,'26MY_ACCORD_DATA'!B:AS,15,FALSE) -> 0 | M75: =VLOOKUP(B75,'26MY_ACCORD_DATA'!B:AS,16,FALSE) -> • | N75: =VLOOKUP(B75,'26MY_ACCORD_DATA'!B:AS,17,FALSE) -> • | O75: =VLOOKUP(B75,'26MY_ACCORD_DATA'!B:AS,18,FALSE) -> 0 | P75: =VLOOKUP(B75,'26MY_ACCORD_DATA'!B:AS,19,FALSE) -> 0 | Q75: =IF(VLOOKUP(B75,'26MY_ACCORD_DATA'!B:AS,20,FALSE)="","",VLOOKUP(B75,'26MY_ACCORD_DATA'!B:AS,20,FALSE)) -> Rear H-Mark Logo.
B76: 08F20-30A-100D | C76: =VLOOKUP(B76,'26MY_ACCORD_DATA'!B:AS,3,FALSE) -> Black Emblem, Accord | D76: =B76 -> 08F20-30A-100D | E76: =VLOOKUP(B76,'26MY_ACCORD_DATA'!B:AS,9,FALSE) -> 37 | F76: =VLOOKUP(B76,'26MY_ACCORD_DATA'!B:AS,10,FALSE) -> 62 | G76: =VLOOKUP(B76,'26MY_ACCORD_DATA'!B:AS,7,FALSE) -> 0.3 | H76: =VLOOKUP(B76,'26MY_ACCORD_DATA'!B:AS,11,FALSE) -> 107.6 | I76: =VLOOKUP(B76,'26MY_ACCORD_DATA'!B:AS,12,FALSE) -> 0 | J76: =VLOOKUP(B76,'26MY_ACCORD_DATA'!B:AS,13,FALSE) -> 0 | K76: =VLOOKUP(B76,'26MY_ACCORD_DATA'!B:AS,14,FALSE) -> • | L76: =VLOOKUP(B76,'26MY_ACCORD_DATA'!B:AS,15,FALSE) -> 0 | M76: =VLOOKUP(B76,'26MY_ACCORD_DATA'!B:AS,16,FALSE) -> N/A | N76: =VLOOKUP(B76,'26MY_ACCORD_DATA'!B:AS,17,FALSE) -> • | O76: =VLOOKUP(B76,'26MY_ACCORD_DATA'!B:AS,18,FALSE) -> 0 | P76: =VLOOKUP(B76,'26MY_ACCORD_DATA'!B:AS,19,FALSE) -> 0 | Q76: =IF(VLOOKUP(B76,'26MY_ACCORD_DATA'!B:AS,20,FALSE)="","",VLOOKUP(B76,'26MY_ACCORD_DATA'!B:AS,20,FALSE))
B77: 08F20-3A0-100C | C77: =VLOOKUP(B77,'26MY_ACCORD_DATA'!B:AS,3,FALSE) -> Black Emblem, Touring | D77: =B77 -> 08F20-3A0-100C | E77: =VLOOKUP(B77,'26MY_ACCORD_DATA'!B:AS,9,FALSE) -> 44 | F77: =VLOOKUP(B77,'26MY_ACCORD_DATA'!B:AS,10,FALSE) -> 73 | G77: =VLOOKUP(B77,'26MY_ACCORD_DATA'!B:AS,7,FALSE) -> 0.2 | H77: =VLOOKUP(B77,'26MY_ACCORD_DATA'!B:AS,11,FALSE) -> 103.4 | I77: =VLOOKUP(B77,'26MY_ACCORD_DATA'!B:AS,12,FALSE) -> 0 | J77: =VLOOKUP(B77,'26MY_ACCORD_DATA'!B:AS,13,FALSE) -> 0 | K77: =VLOOKUP(B77,'26MY_ACCORD_DATA'!B:AS,14,FALSE) -> N/A | L77: =VLOOKUP(B77,'26MY_ACCORD_DATA'!B:AS,15,FALSE) -> 0 | M77: =VLOOKUP(B77,'26MY_ACCORD_DATA'!B:AS,16,FALSE) -> N/A | N77: =VLOOKUP(B77,'26MY_ACCORD_DATA'!B:AS,17,FALSE) -> • | O77: =VLOOKUP(B77,'26MY_ACCORD_DATA'!B:AS,18,FALSE) -> 0 | P77: =VLOOKUP(B77,'26MY_ACCORD_DATA'!B:AS,19,FALSE) -> 0 | Q77: =IF(VLOOKUP(B77,'26MY_ACCORD_DATA'!B:AS,20,FALSE)="","",VLOOKUP(B77,'26MY_ACCORD_DATA'!B:AS,20,FALSE))
B78: 08F20-T20-100B | C78: =VLOOKUP(B78,'26MY_ACCORD_DATA'!B:AS,3,FALSE) -> Black Emblem, Hybrid | D78: =B78 -> 08F20-T20-100B | E78: =VLOOKUP(B78,'26MY_ACCORD_DATA'!B:AS,9,FALSE) -> 46 | F78: =VLOOKUP(B78,'26MY_ACCORD_DATA'!B:AS,10,FALSE) -> 77 | G78: =VLOOKUP(B78,'26MY_ACCORD_DATA'!B:AS,7,FALSE) -> 0.2 | H78: =VLOOKUP(B78,'26MY_ACCORD_DATA'!B:AS,11,FALSE) -> 107.4 | I78: =VLOOKUP(B78,'26MY_ACCORD_DATA'!B:AS,12,FALSE) -> 0 | J78: =VLOOKUP(B78,'26MY_ACCORD_DATA'!B:AS,13,FALSE) -> 0 | K78: =VLOOKUP(B78,'26MY_ACCORD_DATA'!B:AS,14,FALSE) -> N/A | L78: =VLOOKUP(B78,'26MY_ACCORD_DATA'!B:AS,15,FALSE) -> 0 | M78: =VLOOKUP(B78,'26MY_ACCORD_DATA'!B:AS,16,FALSE) -> N/A | N78: =VLOOKUP(B78,'26MY_ACCORD_DATA'!B:AS,17,FALSE) -> • | O78: =VLOOKUP(B78,'26MY_ACCORD_DATA'!B:AS,18,FALSE) -> 0 | P78: =VLOOKUP(B78,'26MY_ACCORD_DATA'!B:AS,19,FALSE) -> 0 | Q78: =IF(VLOOKUP(B78,'26MY_ACCORD_DATA'!B:AS,20,FALSE)="","",VLOOKUP(B78,'26MY_ACCORD_DATA'!B:AS,20,FALSE))
B79: 08F59-30A-100 | C79: =VLOOKUP(B79,'26MY_ACCORD_DATA'!B:AS,3,FALSE) -> Fender Emblem | D79: =B79 -> 08F59-30A-100 | E79: =VLOOKUP(B79,'26MY_ACCORD_DATA'!B:AS,9,FALSE) -> 94 | F79: =VLOOKUP(B79,'26MY_ACCORD_DATA'!B:AS,10,FALSE) -> 157 | G79: =VLOOKUP(B79,'26MY_ACCORD_DATA'!B:AS,7,FALSE) -> 0.2 | H79: =VLOOKUP(B79,'26MY_ACCORD_DATA'!B:AS,11,FALSE) -> 187.4 | I79: =VLOOKUP(B79,'26MY_ACCORD_DATA'!B:AS,12,FALSE) -> 0 | J79: =VLOOKUP(B79,'26MY_ACCORD_DATA'!B:AS,13,FALSE) -> 0 | K79: =VLOOKUP(B79,'26MY_ACCORD_DATA'!B:AS,14,FALSE) -> • | L79: =VLOOKUP(B79,'26MY_ACCORD_DATA'!B:AS,15,FALSE) -> 0 | M79: =VLOOKUP(B79,'26MY_ACCORD_DATA'!B:AS,16,FALSE) -> • | N79: =VLOOKUP(B79,'26MY_ACCORD_DATA'!B:AS,17,FALSE) -> • | O79: =VLOOKUP(B79,'26MY_ACCORD_DATA'!B:AS,18,FALSE) -> 0 | P79: =VLOOKUP(B79,'26MY_ACCORD_DATA'!B:AS,19,FALSE) -> 0 | Q79: =IF(VLOOKUP(B79,'26MY_ACCORD_DATA'!B:AS,20,FALSE)="","",VLOOKUP(B79,'26MY_ACCORD_DATA'!B:AS,20,FALSE))
B80: 08F20-30A-100B | C80: =VLOOKUP(B80,'26MY_ACCORD_DATA'!B:AS,3,FALSE) -> HPD Badge | D80: =B80 -> 08F20-30A-100B | E80: =VLOOKUP(B80,'26MY_ACCORD_DATA'!B:AS,9,FALSE) -> 71 | F80: =VLOOKUP(B80,'26MY_ACCORD_DATA'!B:AS,10,FALSE) -> 118 | G80: =VLOOKUP(B80,'26MY_ACCORD_DATA'!B:AS,7,FALSE) -> 0.1 | H80: =VLOOKUP(B80,'26MY_ACCORD_DATA'!B:AS,11,FALSE) -> 133.2 | I80: =VLOOKUP(B80,'26MY_ACCORD_DATA'!B:AS,12,FALSE) -> 0 | J80: =VLOOKUP(B80,'26MY_ACCORD_DATA'!B:AS,13,FALSE) -> 0 | K80: =VLOOKUP(B80,'26MY_ACCORD_DATA'!B:AS,14,FALSE) -> • | L80: =VLOOKUP(B80,'26MY_ACCORD_DATA'!B:AS,15,FALSE) -> 0 | M80: =VLOOKUP(B80,'26MY_ACCORD_DATA'!B:AS,16,FALSE) -> • | N80: =VLOOKUP(B80,'26MY_ACCORD_DATA'!B:AS,17,FALSE) -> • | O80: =VLOOKUP(B80,'26MY_ACCORD_DATA'!B:AS,18,FALSE) -> 0 | P80: =VLOOKUP(B80,'26MY_ACCORD_DATA'!B:AS,19,FALSE) -> 0 | Q80: =IF(VLOOKUP(B80,'26MY_ACCORD_DATA'!B:AS,20,FALSE)="","",VLOOKUP(B80,'26MY_ACCORD_DATA'!B:AS,20,FALSE))
B81: 08P09-30A-300 | C81: =VLOOKUP(B81,'26MY_ACCORD_DATA'!B:AS,3,FALSE) -> Rear Splash Guards | D81: =B81 -> 08P09-30A-300 | E81: =VLOOKUP(B81,'26MY_ACCORD_DATA'!B:AS,9,FALSE) -> 50 | F81: =VLOOKUP(B81,'26MY_ACCORD_DATA'!B:AS,10,FALSE) -> 83 | G81: =VLOOKUP(B81,'26MY_ACCORD_DATA'!B:AS,7,FALSE) -> 0.4 | H81: =VLOOKUP(B81,'26MY_ACCORD_DATA'!B:AS,11,FALSE) -> 143.8 | I81: =VLOOKUP(B81,'26MY_ACCORD_DATA'!B:AS,12,FALSE) -> 0 | J81: =VLOOKUP(B81,'26MY_ACCORD_DATA'!B:AS,13,FALSE) -> 0 | K81: =VLOOKUP(B81,'26MY_ACCORD_DATA'!B:AS,14,FALSE) -> • | L81: =VLOOKUP(B81,'26MY_ACCORD_DATA'!B:AS,15,FALSE) -> 0 | M81: =VLOOKUP(B81,'26MY_ACCORD_DATA'!B:AS,16,FALSE) -> • | N81: =VLOOKUP(B81,'26MY_ACCORD_DATA'!B:AS,17,FALSE) -> • | O81: =VLOOKUP(B81,'26MY_ACCORD_DATA'!B:AS,18,FALSE) -> 0 | P81: =VLOOKUP(B81,'26MY_ACCORD_DATA'!B:AS,19,FALSE) -> 0 | Q81: =IF(VLOOKUP(B81,'26MY_ACCORD_DATA'!B:AS,20,FALSE)="","",VLOOKUP(B81,'26MY_ACCORD_DATA'!B:AS,20,FALSE))
... B85: 08P20-30A-100A | C85: =VLOOKUP(B85,'26MY_ACCORD_DATA'!B:AS,3,FALSE) -> Door Edge Film | D85: =B85 -> 08P20-30A-100A | E85: =VLOOKUP(B85,'26MY_ACCORD_DATA'!B:AS,9,FALSE) -> 71 | F85: =VLOOKUP(B85,'26MY_ACCORD_DATA'!B:AS,10,FALSE) -> 118 | G85: =VLOOKUP(B85,'26MY_ACCORD_DATA'!B:AS,7,FALSE) -> 0.5 | H85: =VLOOKUP(B85,'26MY_ACCORD_DATA'!B:AS,11,FALSE) -> 194 | I85: =VLOOKUP(B85,'26MY_ACCORD_DATA'!B:AS,12,FALSE) -> 0 | J85: =VLOOKUP(B85,'26MY_ACCORD_DATA'!B:AS,13,FALSE) -> 0 | K85: =VLOOKUP(B85,'26MY_ACCORD_DATA'!B:AS,14,FALSE) -> • | L85: =VLOOKUP(B85,'26MY_ACCORD_DATA'!B:AS,15,FALSE) -> 0 | M85: =VLOOKUP(B85,'26MY_ACCORD_DATA'!B:AS,16,FALSE) -> • | N85: =VLOOKUP(B85,'26MY_ACCORD_DATA'!B:AS,17,FALSE) -> • | O85: =VLOOKUP(B85,'26MY_ACCORD_DATA'!B:AS,18,FALSE) -> 0 | P85: =VLOOKUP(B85,'26MY_ACCORD_DATA'!B:AS,19,FALSE) -> 0 | Q85: =IF(VLOOKUP(B85,'26MY_ACCORD_DATA'!B:AS,20,FALSE)="","",VLOOKUP(B85,'26MY_ACCORD_DATA'!B:AS,20,FALSE)) -> Cannot be installed with Door Edge Guards
B86: 08F02-30A-XXX | C86: =VLOOKUP(B86,'26MY_ACCORD_DATA'!B:AS,3,FALSE) -> Decklid Spoiler
B87: 08F10-30A-110 | C87: =VLOOKUP(B87,'26MY_ACCORD_DATA'!B:AS,3,FALSE) -> Platinum White Pearl (NH-883P) | D87: =B87 -> 08F10-30A-110 | E87: =VLOOKUP(B87,'26MY_ACCORD_DATA'!B:AS,9,FALSE) -> 386 | F87: =VLOOKUP(B87,'26MY_ACCORD_DATA'!B:AS,10,FALSE) -> 643 | G87: =VLOOKUP(B87,'26MY_ACCORD_DATA'!B:AS,7,FALSE) -> 0.6 | H87: =VLOOKUP(B87,'26MY_ACCORD_DATA'!B:AS,11,FALSE) -> 734.2 | I87: =VLOOKUP(B87,'26MY_ACCORD_DATA'!B:AS,12,FALSE) -> 0 | J87: =VLOOKUP(B87,'26MY_ACCORD_DATA'!B:AS,13,FALSE) -> 0 | K87: =VLOOKUP(B87,'26MY_ACCORD_DATA'!B:AS,14,FALSE) -> • | L87: =VLOOKUP(B87,'26MY_ACCORD_DATA'!B:AS,15,FALSE) -> 0 | M87: =VLOOKUP(B87,'26MY_ACCORD_DATA'!B:AS,16,FALSE) -> S | N87: =VLOOKUP(B87,'26MY_ACCORD_DATA'!B:AS,17,FALSE) -> • | O87: =VLOOKUP(B87,'26MY_ACCORD_DATA'!B:AS,18,FALSE) -> 0 | P87: =VLOOKUP(B87,'26MY_ACCORD_DATA'!B:AS,19,FALSE) -> 0 | Q87: =IF(VLOOKUP(B87,'26MY_ACCORD_DATA'!B:AS,20,FALSE)="","",VLOOKUP(B87,'26MY_ACCORD_DATA'!B:AS,20,FALSE))
B88: 08F10-30A-140 | C88: =VLOOKUP(B88,'26MY_ACCORD_DATA'!B:AS,3,FALSE) -> Meteoroid Gray Pearl (NH-904M) | D88: =B88 -> 08F10-30A-140 | E88: =VLOOKUP(B88,'26MY_ACCORD_DATA'!B:AS,9,FALSE) -> 386 | F88: =VLOOKUP(B88,'26MY_ACCORD_DATA'!B:AS,10,FALSE) -> 643 | G88: =VLOOKUP(B88,'26MY_ACCORD_DATA'!B:AS,7,FALSE) -> 0.6 | H88: =VLOOKUP(B88,'26MY_ACCORD_DATA'!B:AS,11,FALSE) -> 734.2 | I88: =VLOOKUP(B88,'26MY_ACCORD_DATA'!B:AS,12,FALSE) -> 0 | J88: =VLOOKUP(B88,'26MY_ACCORD_DATA'!B:AS,13,FALSE) -> 0 | K88: =VLOOKUP(B88,'26MY_ACCORD_DATA'!B:AS,14,FALSE) -> N/A | L88: =VLOOKUP(B88,'26MY_ACCORD_DATA'!B:AS,15,FALSE) -> 0 | M88: =VLOOKUP(B88,'26MY_ACCORD_DATA'!B:AS,16,FALSE) -> S | N88: =VLOOKUP(B88,'26MY_ACCORD_DATA'!B:AS,17,FALSE) -> N/A | O88: =VLOOKUP(B88,'26MY_ACCORD_DATA'!B:AS,18,FALSE) -> 0 | P88: =VLOOKUP(B88,'26MY_ACCORD_DATA'!B:AS,19,FALSE) -> 0
B89: 08F10-30A-150 | C89: =VLOOKUP(B89,'26MY_ACCORD_DATA'!B:AS,3,FALSE) -> Urban Grey Pearl (NH-912P) | D89: =B89 -> 08F10-30A-150 | E89: =VLOOKUP(B89,'26MY_ACCORD_DATA'!B:AS,9,FALSE) -> 386 | F89: =VLOOKUP(B89,'26MY_ACCORD_DATA'!B:AS,10,FALSE) -> 643 | G89: =VLOOKUP(B89,'26MY_ACCORD_DATA'!B:AS,7,FALSE) -> 0.6 | H89: =VLOOKUP(B89,'26MY_ACCORD_DATA'!B:AS,11,FALSE) -> 734.2 | I89: =VLOOKUP(B89,'26MY_ACCORD_DATA'!B:AS,12,FALSE) -> 0 | J89: =VLOOKUP(B89,'26MY_ACCORD_DATA'!B:AS,13,FALSE) -> 0 | K89: =VLOOKUP(B89,'26MY_ACCORD_DATA'!B:AS,14,FALSE) -> N/A | L89: =VLOOKUP(B89,'26MY_ACCORD_DATA'!B:AS,15,FALSE) -> 0 | M89: =VLOOKUP(B89,'26MY_ACCORD_DATA'!B:AS,16,FALSE) -> S | N89: =VLOOKUP(B89,'26MY_ACCORD_DATA'!B:AS,17,FALSE) -> • | O89: =VLOOKUP(B89,'26MY_ACCORD_DATA'!B:AS,18,FALSE) -> 0 | P89: =VLOOKUP(B89,'26MY_ACCORD_DATA'!B:AS,19,FALSE) -> 0
B90: 08F10-30A-170 | C90: =VLOOKUP(B90,'26MY_ACCORD_DATA'!B:AS,3,FALSE) -> Crystal Black Pearl (NH-731P) | D90: =B90 -> 08F10-30A-170 | E90: =VLOOKUP(B90,'26MY_ACCORD_DATA'!B:AS,9,FALSE) -> 386 | F90: =VLOOKUP(B90,'26MY_ACCORD_DATA'!B:AS,10,FALSE) -> 643 | G90: =VLOOKUP(B90,'26MY_ACCORD_DATA'!B:AS,7,FALSE) -> 0.6 | H90: =VLOOKUP(B90,'26MY_ACCORD_DATA'!B:AS,11,FALSE) -> 734.2 | I90: =VLOOKUP(B90,'26MY_ACCORD_DATA'!B:AS,12,FALSE) -> 0 | J90: =VLOOKUP(B90,'26MY_ACCORD_DATA'!B:AS,13,FALSE) -> 0 | K90: =VLOOKUP(B90,'26MY_ACCORD_DATA'!B:AS,14,FALSE) -> • | L90: =VLOOKUP(B90,'26MY_ACCORD_DATA'!B:AS,15,FALSE) -> 0 | M90: =VLOOKUP(B90,'26MY_ACCORD_DATA'!B:AS,16,FALSE) -> S | N90: =VLOOKUP(B90,'26MY_ACCORD_DATA'!B:AS,17,FALSE) -> • | O90: =VLOOKUP(B90,'26MY_ACCORD_DATA'!B:AS,18,FALSE) -> 0 | P90: =VLOOKUP(B90,'26MY_ACCORD_DATA'!B:AS,19,FALSE) -> 0
B91: 08F10-30A-1A0 | C91: =VLOOKUP(B91,'26MY_ACCORD_DATA'!B:AS,3,FALSE) -> Radiant Red Metallic (R-569M) | D91: =B91 -> 08F10-30A-1A0 | E91: =VLOOKUP(B91,'26MY_ACCORD_DATA'!B:AS,9,FALSE) -> 386 | F91: =VLOOKUP(B91,'26MY_ACCORD_DATA'!B:AS,10,FALSE) -> 643 | G91: =VLOOKUP(B91,'26MY_ACCORD_DATA'!B:AS,7,FALSE) -> 0.6 | H91: =VLOOKUP(B91,'26MY_ACCORD_DATA'!B:AS,11,FALSE) -> 734.2 | I91: =VLOOKUP(B91,'26MY_ACCORD_DATA'!B:AS,12,FALSE) -> 0 | J91: =VLOOKUP(B91,'26MY_ACCORD_DATA'!B:AS,13,FALSE) -> 0 | K91: =VLOOKUP(B91,'26MY_ACCORD_DATA'!B:AS,14,FALSE) -> N/A | L91: =VLOOKUP(B91,'26MY_ACCORD_DATA'!B:AS,15,FALSE) -> 0 | M91: =VLOOKUP(B91,'26MY_ACCORD_DATA'!B:AS,16,FALSE) -> S | N91: =VLOOKUP(B91,'26MY_ACCORD_DATA'!B:AS,17,FALSE) -> • | O91: =VLOOKUP(B91,'26MY_ACCORD_DATA'!B:AS,18,FALSE) -> 0 | P91: =VLOOKUP(B91,'26MY_ACCORD_DATA'!B:AS,19,FALSE) -> 0
B92: 08F10-30A-1D0 | C92: =VLOOKUP(B92,'26MY_ACCORD_DATA'!B:AS,3,FALSE) -> Canyon River Blue Metallic (B-640M) | D92: =B92 -> 08F10-30A-1D0 | E92: =VLOOKUP(B92,'26MY_ACCORD_DATA'!B:AS,9,FALSE) -> 386 | F92: =VLOOKUP(B92,'26MY_ACCORD_DATA'!B:AS,10,FALSE) -> 643 | G92: =VLOOKUP(B92,'26MY_ACCORD_DATA'!B:AS,7,FALSE) -> 0.6 | H92: =VLOOKUP(B92,'26MY_ACCORD_DATA'!B:AS,11,FALSE) -> 734.2 | I92: =VLOOKUP(B92,'26MY_ACCORD_DATA'!B:AS,12,FALSE) -> 0 | J92: =VLOOKUP(B92,'26MY_ACCORD_DATA'!B:AS,13,FALSE) -> 0 | K92: =VLOOKUP(B92,'26MY_ACCORD_DATA'!B:AS,14,FALSE) -> N/A | L92: =VLOOKUP(B92,'26MY_ACCORD_DATA'!B:AS,15,FALSE) -> 0 | M92: =VLOOKUP(B92,'26MY_ACCORD_DATA'!B:AS,16,FALSE) -> S | N92: =VLOOKUP(B92,'26MY_ACCORD_DATA'!B:AS,17,FALSE) -> • | O92: =VLOOKUP(B92,'26MY_ACCORD_DATA'!B:AS,18,FALSE) -> 0 | P92: =VLOOKUP(B92,'26MY_ACCORD_DATA'!B:AS,19,FALSE) -> 0
B93: 08F10-30A-1C0 | C93: =VLOOKUP(B93,'26MY_ACCORD_DATA'!B:AS,3,FALSE) -> Still Night Pearl (B-575P) | D93: =B93 -> 08F10-30A-1C0 | E93: =VLOOKUP(B93,'26MY_ACCORD_DATA'!B:AS,9,FALSE) -> 386 | F93: =VLOOKUP(B93,'26MY_ACCORD_DATA'!B:AS,10,FALSE) -> 643 | G93: =VLOOKUP(B93,'26MY_ACCORD_DATA'!B:AS,7,FALSE) -> 0.6 | H93: =VLOOKUP(B93,'26MY_ACCORD_DATA'!B:AS,11,FALSE) -> 734.2 | I93: =VLOOKUP(B93,'26MY_ACCORD_DATA'!B:AS,12,FALSE) -> 0 | J93: =VLOOKUP(B93,'26MY_ACCORD_DATA'!B:AS,13,FALSE) -> 0 | K93: =VLOOKUP(B93,'26MY_ACCORD_DATA'!B:AS,14,FALSE) -> N/A | L93: =VLOOKUP(B93,'26MY_ACCORD_DATA'!B:AS,15,FALSE) -> 0 | M93: =VLOOKUP(B93,'26MY_ACCORD_DATA'!B:AS,16,FALSE) -> S | N93: =VLOOKUP(B93,'26MY_ACCORD_DATA'!B:AS,17,FALSE) -> N/A | O93: =VLOOKUP(B93,'26MY_ACCORD_DATA'!B:AS,18,FALSE) -> 0 | P93: =VLOOKUP(B93,'26MY_ACCORD_DATA'!B:AS,19,FALSE) -> 0
B94: 08F10-30A-1H0 | C94: =VLOOKUP(B94,'26MY_ACCORD_DATA'!B:AS,3,FALSE) -> Solar Reflection Silver (NH-932M) | D94: =B94 -> 08F10-30A-1H0 | E94: =VLOOKUP(B94,'26MY_ACCORD_DATA'!B:AS,9,FALSE) -> 386 | F94: =VLOOKUP(B94,'26MY_ACCORD_DATA'!B:AS,10,FALSE) -> 643 | G94: =VLOOKUP(B94,'26MY_ACCORD_DATA'!B:AS,7,FALSE) -> 0.6 | H94: =VLOOKUP(B94,'26MY_ACCORD_DATA'!B:AS,11,FALSE) -> 734.2 | I94: =VLOOKUP(B94,'26MY_ACCORD_DATA'!B:AS,12,FALSE) -> 0 | J94: =VLOOKUP(B94,'26MY_ACCORD_DATA'!B:AS,13,FALSE) -> 0 | K94: =VLOOKUP(B94,'26MY_ACCORD_DATA'!B:AS,14,FALSE) -> • | L94: =VLOOKUP(B94,'26MY_ACCORD_DATA'!B:AS,15,FALSE) -> 0 | M94: =VLOOKUP(B94,'26MY_ACCORD_DATA'!B:AS,16,FALSE) -> S | N94: =VLOOKUP(B94,'26MY_ACCORD_DATA'!B:AS,17,FALSE) -> • | O94: =VLOOKUP(B94,'26MY_ACCORD_DATA'!B:AS,18,FALSE) -> 0 | P94: =VLOOKUP(B94,'26MY_ACCORD_DATA'!B:AS,19,FALSE) -> 0
B95: 08P05-30A-XXXX | C95: =VLOOKUP(B95,'26MY_ACCORD_DATA'!B:AS,3,FALSE) -> Body Side Moulding
B96: 08P05-30A-110 | C96: =VLOOKUP(B96,'26MY_ACCORD_DATA'!B:AS,3,FALSE) -> Platinum White Pearl (NH-883P) | D96: =B96 -> 08P05-30A-110 | E96: =VLOOKUP(B96,'26MY_ACCORD_DATA'!B:AS,9,FALSE) -> 232 | F96: =VLOOKUP(B96,'26MY_ACCORD_DATA'!B:AS,10,FALSE) -> 387 | G96: =VLOOKUP(B96,'26MY_ACCORD_DATA'!B:AS,7,FALSE) -> 0.4 | H96: =VLOOKUP(B96,'26MY_ACCORD_DATA'!B:AS,11,FALSE) -> 447.8 | I96: =VLOOKUP(B96,'26MY_ACCORD_DATA'!B:AS,12,FALSE) -> 0 | J96: =VLOOKUP(B96,'26MY_ACCORD_DATA'!B:AS,13,FALSE) -> 0 | K96: =VLOOKUP(B96,'26MY_ACCORD_DATA'!B:AS,14,FALSE) -> • | L96: =VLOOKUP(B96,'26MY_ACCORD_DATA'!B:AS,15,FALSE) -> 0 | M96: =VLOOKUP(B96,'26MY_ACCORD_DATA'!B:AS,16,FALSE) -> • | N96: =VLOOKUP(B96,'26MY_ACCORD_DATA'!B:AS,17,FALSE) -> • | O96: =VLOOKUP(B96,'26MY_ACCORD_DATA'!B:AS,18,FALSE) -> 0 | P96: =VLOOKUP(B96,'26MY_ACCORD_DATA'!B:AS,19,FALSE) -> 0 | Q96: =IF(VLOOKUP(B96,'26MY_ACCORD_DATA'!B:AS,20,FALSE)="","",VLOOKUP(B96,'26MY_ACCORD_DATA'!B:AS,20,FALSE))
B97: 08P05-30A-140 | C97: =VLOOKUP(B97,'26MY_ACCORD_DATA'!B:AS,3,FALSE) -> Meteoroid Gray Pearl (NH-904M) | D97: =B97 -> 08P05-30A-140 | E97: =VLOOKUP(B97,'26MY_ACCORD_DATA'!B:AS,9,FALSE) -> 232 | F97: =VLOOKUP(B97,'26MY_ACCORD_DATA'!B:AS,10,FALSE) -> 387 | G97: =VLOOKUP(B97,'26MY_ACCORD_DATA'!B:AS,7,FALSE) -> 0.4 | H97: =VLOOKUP(B97,'26MY_ACCORD_DATA'!B:AS,11,FALSE) -> 447.8 | I97: =VLOOKUP(B97,'26MY_ACCORD_DATA'!B:AS,12,FALSE) -> 0 | J97: =VLOOKUP(B97,'26MY_ACCORD_DATA'!B:AS,13,FALSE) -> 0 | K97: =VLOOKUP(B97,'26MY_ACCORD_DATA'!B:AS,14,FALSE) -> N/A | L97: =VLOOKUP(B97,'26MY_ACCORD_DATA'!B:AS,15,FALSE) -> 0 | M97: =VLOOKUP(B97,'26MY_ACCORD_DATA'!B:AS,16,FALSE) -> • | N97: =VLOOKUP(B97,'26MY_ACCORD_DATA'!B:AS,17,FALSE) -> N/A | O97: =VLOOKUP(B97,'26MY_ACCORD_DATA'!B:AS,18,FALSE) -> 0 | P97: =VLOOKUP(B97,'26MY_ACCORD_DATA'!B:AS,19,FALSE) -> 0
B98: 08P05-30A-150 | C98: =VLOOKUP(B98,'26MY_ACCORD_DATA'!B:AS,3,FALSE) -> Urban Grey Pearl (NH-912P) | D98: =B98 -> 08P05-30A-150 | E98: =VLOOKUP(B98,'26MY_ACCORD_DATA'!B:AS,9,FALSE) -> 232 | F98: =VLOOKUP(B98,'26MY_ACCORD_DATA'!B:AS,10,FALSE) -> 387 | G98: =VLOOKUP(B98,'26MY_ACCORD_DATA'!B:AS,7,FALSE) -> 0.4 | H98: =VLOOKUP(B98,'26MY_ACCORD_DATA'!B:AS,11,FALSE) -> 447.8 | I98: =VLOOKUP(B98,'26MY_ACCORD_DATA'!B:AS,12,FALSE) -> 0 | J98: =VLOOKUP(B98,'26MY_ACCORD_DATA'!B:AS,13,FALSE) -> 0 | K98: =VLOOKUP(B98,'26MY_ACCORD_DATA'!B:AS,14,FALSE) -> N/A | L98: =VLOOKUP(B98,'26MY_ACCORD_DATA'!B:AS,15,FALSE) -> 0 | M98: =VLOOKUP(B98,'26MY_ACCORD_DATA'!B:AS,16,FALSE) -> N/A | N98: =VLOOKUP(B98,'26MY_ACCORD_DATA'!B:AS,17,FALSE) -> • | O98: =VLOOKUP(B98,'26MY_ACCORD_DATA'!B:AS,18,FALSE) -> 0 | P98: =VLOOKUP(B98,'26MY_ACCORD_DATA'!B:AS,19,FALSE) -> 0
B99: 08P05-30A-170 | C99: =VLOOKUP(B99,'26MY_ACCORD_DATA'!B:AS,3,FALSE) -> Crystal Black Pearl (NH-731P) | D99: =B99 -> 08P05-30A-170 | E99: =VLOOKUP(B99,'26MY_ACCORD_DATA'!B:AS,9,FALSE) -> 232 | F99: =VLOOKUP(B99,'26MY_ACCORD_DATA'!B:AS,10,FALSE) -> 387 | G99: =VLOOKUP(B99,'26MY_ACCORD_DATA'!B:AS,7,FALSE) -> 0.4 | H99: =VLOOKUP(B99,'26MY_ACCORD_DATA'!B:AS,11,FALSE) -> 447.8 | I99: =VLOOKUP(B99,'26MY_ACCORD_DATA'!B:AS,12,FALSE) -> 0 | J99: =VLOOKUP(B99,'26MY_ACCORD_DATA'!B:AS,13,FALSE) -> 0 | K99: =VLOOKUP(B99,'26MY_ACCORD_DATA'!B:AS,14,FALSE) -> • | L99: =VLOOKUP(B99,'26MY_ACCORD_DATA'!B:AS,15,FALSE) -> 0 | M99: =VLOOKUP(B99,'26MY_ACCORD_DATA'!B:AS,16,FALSE) -> • | N99: =VLOOKUP(B99,'26MY_ACCORD_DATA'!B:AS,17,FALSE) -> • | O99: =VLOOKUP(B99,'26MY_ACCORD_DATA'!B:AS,18,FALSE) -> 0 | P99: =VLOOKUP(B99,'26MY_ACCORD_DATA'!B:AS,19,FALSE) -> 0
B100: 08P05-30A-1A0 | C100: =VLOOKUP(B100,'26MY_ACCORD_DATA'!B:AS,3,FALSE) -> Radiant Red Metallic (R-569M) | D100: =B100 -> 08P05-30A-1A0 | E100: =VLOOKUP(B100,'26MY_ACCORD_DATA'!B:AS,9,FALSE) -> 232 | F100: =VLOOKUP(B100,'26MY_ACCORD_DATA'!B:AS,10,FALSE) -> 387 | G100: =VLOOKUP(B100,'26MY_ACCORD_DATA'!B:AS,7,FALSE) -> 0.4 | H100: =VLOOKUP(B100,'26MY_ACCORD_DATA'!B:AS,11,FALSE) -> 447.8 | I100: =VLOOKUP(B100,'26MY_ACCORD_DATA'!B:AS,12,FALSE) -> 0 | J100: =VLOOKUP(B100,'26MY_ACCORD_DATA'!B:AS,13,FALSE) -> 0 | K100: =VLOOKUP(B100,'26MY_ACCORD_DATA'!B:AS,14,FALSE) -> N/A | L100: =VLOOKUP(B100,'26MY_ACCORD_DATA'!B:AS,15,FALSE) -> 0 | M100: =VLOOKUP(B100,'26MY_ACCORD_DATA'!B:AS,16,FALSE) -> • | N100: =VLOOKUP(B100,'26MY_ACCORD_DATA'!B:AS,17,FALSE) -> • | O100: =VLOOKUP(B100,'26MY_ACCORD_DATA'!B:AS,18,FALSE) -> 0 | P100: =VLOOKUP(B100,'26MY_ACCORD_DATA'!B:AS,19,FALSE) -> 0
B101: 08P05-30A-1D0 | C101: =VLOOKUP(B101,'26MY_ACCORD_DATA'!B:AS,3,FALSE) -> Canyon River Blue Metallic (B-640M) | D101: =B101 -> 08P05-30A-1D0 | E101: =VLOOKUP(B101,'26MY_ACCORD_DATA'!B:AS,9,FALSE) -> 232 | F101: =VLOOKUP(B101,'26MY_ACCORD_DATA'!B:AS,10,FALSE) -> 387 | G101: =VLOOKUP(B101,'26MY_ACCORD_DATA'!B:AS,7,FALSE) -> 0.4 | H101: =VLOOKUP(B101,'26MY_ACCORD_DATA'!B:AS,11,FALSE) -> 447.8 | I101: =VLOOKUP(B101,'26MY_ACCORD_DATA'!B:AS,12,FALSE) -> 0 | J101: =VLOOKUP(B101,'26MY_ACCORD_DATA'!B:AS,13,FALSE) -> 0 | K101: =VLOOKUP(B101,'26MY_ACCORD_DATA'!B:AS,14,FALSE) -> N/A | L101: =VLOOKUP(B101,'26MY_ACCORD_DATA'!B:AS,15,FALSE) -> 0 | M101: =VLOOKUP(B101,'26MY_ACCORD_DATA'!B:AS,16,FALSE) -> N/A | N101: =VLOOKUP(B101,'26MY_ACCORD_DATA'!B:AS,17,FALSE) -> • | O101: =VLOOKUP(B101,'26MY_ACCORD_DATA'!B:AS,18,FALSE) -> 0 | P101: =VLOOKUP(B101,'26MY_ACCORD_DATA'!B:AS,19,FALSE) -> 0
B102: 08P05-30A-1C0 | C102: =VLOOKUP(B102,'26MY_ACCORD_DATA'!B:AS,3,FALSE) -> Still Night Pearl (B-575P) | D102: =B102 -> 08P05-30A-1C0 | E102: =VLOOKUP(B102,'26MY_ACCORD_DATA'!B:AS,9,FALSE) -> 232 | F102: =VLOOKUP(B102,'26MY_ACCORD_DATA'!B:AS,10,FALSE) -> 387 | G102: =VLOOKUP(B102,'26MY_ACCORD_DATA'!B:AS,7,FALSE) -> 0.4 | H102: =VLOOKUP(B102,'26MY_ACCORD_DATA'!B:AS,11,FALSE) -> 447.8 | I102: =VLOOKUP(B102,'26MY_ACCORD_DATA'!B:AS,12,FALSE) -> 0 | J102: =VLOOKUP(B102,'26MY_ACCORD_DATA'!B:AS,13,FALSE) -> 0 | K102: =VLOOKUP(B102,'26MY_ACCORD_DATA'!B:AS,14,FALSE) -> N/A | L102: =VLOOKUP(B102,'26MY_ACCORD_DATA'!B:AS,15,FALSE) -> 0 | M102: =VLOOKUP(B102,'26MY_ACCORD_DATA'!B:AS,16,FALSE) -> • | N102: =VLOOKUP(B102,'26MY_ACCORD_DATA'!B:AS,17,FALSE) -> N/A | O102: =VLOOKUP(B102,'26MY_ACCORD_DATA'!B:AS,18,FALSE) -> 0 | P102: =VLOOKUP(B102,'26MY_ACCORD_DATA'!B:AS,19,FALSE) -> 0
B103: 08P05-30A-1H0 | C103: =VLOOKUP(B103,'26MY_ACCORD_DATA'!B:AS,3,FALSE) -> Solar Reflection Silver (NH-932M) | D103: =B103 -> 08P05-30A-1H0 | E103: =VLOOKUP(B103,'26MY_ACCORD_DATA'!B:AS,9,FALSE) -> 232 | F103: =VLOOKUP(B103,'26MY_ACCORD_DATA'!B:AS,10,FALSE) -> 387 | G103: =VLOOKUP(B103,'26MY_ACCORD_DATA'!B:AS,7,FALSE) -> 0.4 | H103: =VLOOKUP(B103,'26MY_ACCORD_DATA'!B:AS,11,FALSE) -> 447.8 | I103: =VLOOKUP(B103,'26MY_ACCORD_DATA'!B:AS,12,FALSE) -> 0 | J103: =VLOOKUP(B103,'26MY_ACCORD_DATA'!B:AS,13,FALSE) -> 0 | K103: =VLOOKUP(B103,'26MY_ACCORD_DATA'!B:AS,14,FALSE) -> • | L103: =VLOOKUP(B103,'26MY_ACCORD_DATA'!B:AS,15,FALSE) -> 0 | M103: =VLOOKUP(B103,'26MY_ACCORD_DATA'!B:AS,16,FALSE) -> • | N103: =VLOOKUP(B103,'26MY_ACCORD_DATA'!B:AS,17,FALSE) -> • | O103: =VLOOKUP(B103,'26MY_ACCORD_DATA'!B:AS,18,FALSE) -> 0 | P103: =VLOOKUP(B103,'26MY_ACCORD_DATA'!B:AS,19,FALSE) -> 0
B104: 08P20-30A-XXXX | C104: =VLOOKUP(B104,'26MY_ACCORD_DATA'!B:AS,3,FALSE) -> Door Edge Guards
B105: 08P20-30A-110 | C105: =VLOOKUP(B105,'26MY_ACCORD_DATA'!B:AS,3,FALSE) -> Platinum White Pearl (NH-883P) | D105: =B105 -> 08P20-30A-110 | E105: =VLOOKUP(B105,'26MY_ACCORD_DATA'!B:AS,9,FALSE) -> 176 | F105: =VLOOKUP(B105,'26MY_ACCORD_DATA'!B:AS,10,FALSE) -> 293 | G105: =VLOOKUP(B105,'26MY_ACCORD_DATA'!B:AS,7,FALSE) -> 0.4 | H105: =VLOOKUP(B105,'26MY_ACCORD_DATA'!B:AS,11,FALSE) -> 353.8 | I105: =VLOOKUP(B105,'26MY_ACCORD_DATA'!B:AS,12,FALSE) -> 0 | J105: =VLOOKUP(B105,'26MY_ACCORD_DATA'!B:AS,13,FALSE) -> 0 | K105: =VLOOKUP(B105,'26MY_ACCORD_DATA'!B:AS,14,FALSE) -> • | L105: =VLOOKUP(B105,'26MY_ACCORD_DATA'!B:AS,15,FALSE) -> 0 | M105: =VLOOKUP(B105,'26MY_ACCORD_DATA'!B:AS,16,FALSE) -> • | N105: =VLOOKUP(B105,'26MY_ACCORD_DATA'!B:AS,17,FALSE) -> • | O105: =VLOOKUP(B105,'26MY_ACCORD_DATA'!B:AS,18,FALSE) -> 0 | P105: =VLOOKUP(B105,'26MY_ACCORD_DATA'!B:AS,19,FALSE) -> 0 | Q105: =IF(VLOOKUP(B105,'26MY_ACCORD_DATA'!B:AS,20,FALSE)="","",VLOOKUP(B105,'26MY_ACCORD_DATA'!B:AS,20,FALSE))
B106: 08P20-30A-140 | C106: =VLOOKUP(B106,'26MY_ACCORD_DATA'!B:AS,3,FALSE) -> Meteoroid Gray Pearl (NH-904M) | D106: =B106 -> 08P20-30A-140 | E106: =VLOOKUP(B106,'26MY_ACCORD_DATA'!B:AS,9,FALSE) -> 176 | F106: =VLOOKUP(B106,'26MY_ACCORD_DATA'!B:AS,10,FALSE) -> 293 | G106: =VLOOKUP(B106,'26MY_ACCORD_DATA'!B:AS,7,FALSE) -> 0.4 | H106: =VLOOKUP(B106,'26MY_ACCORD_DATA'!B:AS,11,FALSE) -> 353.8 | I106: =VLOOKUP(B106,'26MY_ACCORD_DATA'!B:AS,12,FALSE) -> 0 | J106: =VLOOKUP(B106,'26MY_ACCORD_DATA'!B:AS,13,FALSE) -> 0 | K106: =VLOOKUP(B106,'26MY_ACCORD_DATA'!B:AS,14,FALSE) -> N/A | L106: =VLOOKUP(B106,'26MY_ACCORD_DATA'!B:AS,15,FALSE) -> 0 | M106: =VLOOKUP(B106,'26MY_ACCORD_DATA'!B:AS,16,FALSE) -> • | N106: =VLOOKUP(B106,'26MY_ACCORD_DATA'!B:AS,17,FALSE) -> N/A | O106: =VLOOKUP(B106,'26MY_ACCORD_DATA'!B:AS,18,FALSE) -> 0 | P106: =VLOOKUP(B106,'26MY_ACCORD_DATA'!B:AS,19,FALSE) -> 0
B107: 08P20-30A-150 | C107: =VLOOKUP(B107,'26MY_ACCORD_DATA'!B:AS,3,FALSE) -> Urban Grey Pearl (NH-912P) | D107: =B107 -> 08P20-30A-150 | E107: =VLOOKUP(B107,'26MY_ACCORD_DATA'!B:AS,9,FALSE) -> 176 | F107: =VLOOKUP(B107,'26MY_ACCORD_DATA'!B:AS,10,FALSE) -> 293 | G107: =VLOOKUP(B107,'26MY_ACCORD_DATA'!B:AS,7,FALSE) -> 0.4 | H107: =VLOOKUP(B107,'26MY_ACCORD_DATA'!B:AS,11,FALSE) -> 353.8 | I107: =VLOOKUP(B107,'26MY_ACCORD_DATA'!B:AS,12,FALSE) -> 0 | J107: =VLOOKUP(B107,'26MY_ACCORD_DATA'!B:AS,13,FALSE) -> 0 | K107: =VLOOKUP(B107,'26MY_ACCORD_DATA'!B:AS,14,FALSE) -> N/A | L107: =VLOOKUP(B107,'26MY_ACCORD_DATA'!B:AS,15,FALSE) -> 0 | M107: =VLOOKUP(B107,'26MY_ACCORD_DATA'!B:AS,16,FALSE) -> N/A | N107: =VLOOKUP(B107,'26MY_ACCORD_DATA'!B:AS,17,FALSE) -> • | O107: =VLOOKUP(B107,'26MY_ACCORD_DATA'!B:AS,18,FALSE) -> 0 | P107: =VLOOKUP(B107,'26MY_ACCORD_DATA'!B:AS,19,FALSE) -> 0
B108: 08P20-30A-170 | C108: =VLOOKUP(B108,'26MY_ACCORD_DATA'!B:AS,3,FALSE) -> Crystal Black Pearl (NH-731P) | D108: =B108 -> 08P20-30A-170 | E108: =VLOOKUP(B108,'26MY_ACCORD_DATA'!B:AS,9,FALSE) -> 176 | F108: =VLOOKUP(B108,'26MY_ACCORD_DATA'!B:AS,10,FALSE) -> 293 | G108: =VLOOKUP(B108,'26MY_ACCORD_DATA'!B:AS,7,FALSE) -> 0.4 | H108: =VLOOKUP(B108,'26MY_ACCORD_DATA'!B:AS,11,FALSE) -> 353.8 | I108: =VLOOKUP(B108,'26MY_ACCORD_DATA'!B:AS,12,FALSE) -> 0 | J108: =VLOOKUP(B108,'26MY_ACCORD_DATA'!B:AS,13,FALSE) -> 0 | K108: =VLOOKUP(B108,'26MY_ACCORD_DATA'!B:AS,14,FALSE) -> • | L108: =VLOOKUP(B108,'26MY_ACCORD_DATA'!B:AS,15,FALSE) -> 0 | M108: =VLOOKUP(B108,'26MY_ACCORD_DATA'!B:AS,16,FALSE) -> • | N108: =VLOOKUP(B108,'26MY_ACCORD_DATA'!B:AS,17,FALSE) -> • | O108: =VLOOKUP(B108,'26MY_ACCORD_DATA'!B:AS,18,FALSE) -> 0 | P108: =VLOOKUP(B108,'26MY_ACCORD_DATA'!B:AS,19,FALSE) -> 0
B109: 08P20-30A-1A0 | C109: =VLOOKUP(B109,'26MY_ACCORD_DATA'!B:AS,3,FALSE) -> Radiant Red Metallic (R-569M) | D109: =B109 -> 08P20-30A-1A0 | E109: =VLOOKUP(B109,'26MY_ACCORD_DATA'!B:AS,9,FALSE) -> 176 | F109: =VLOOKUP(B109,'26MY_ACCORD_DATA'!B:AS,10,FALSE) -> 293 | G109: =VLOOKUP(B109,'26MY_ACCORD_DATA'!B:AS,7,FALSE) -> 0.4 | H109: =VLOOKUP(B109,'26MY_ACCORD_DATA'!B:AS,11,FALSE) -> 353.8 | I109: =VLOOKUP(B109,'26MY_ACCORD_DATA'!B:AS,12,FALSE) -> 0 | J109: =VLOOKUP(B109,'26MY_ACCORD_DATA'!B:AS,13,FALSE) -> 0 | K109: =VLOOKUP(B109,'26MY_ACCORD_DATA'!B:AS,14,FALSE) -> N/A | L109: =VLOOKUP(B109,'26MY_ACCORD_DATA'!B:AS,15,FALSE) -> 0 | M109: =VLOOKUP(B109,'26MY_ACCORD_DATA'!B:AS,16,FALSE) -> • | N109: =VLOOKUP(B109,'26MY_ACCORD_DATA'!B:AS,17,FALSE) -> • | O109: =VLOOKUP(B109,'26MY_ACCORD_DATA'!B:AS,18,FALSE) -> 0 | P109: =VLOOKUP(B109,'26MY_ACCORD_DATA'!B:AS,19,FALSE) -> 0
B110: 08P20-30A-1D0 | C110: =VLOOKUP(B110,'26MY_ACCORD_DATA'!B:AS,3,FALSE) -> Canyon River Blue Metallic (B-640M) | D110: =B110 -> 08P20-30A-1D0 | E110: =VLOOKUP(B110,'26MY_ACCORD_DATA'!B:AS,9,FALSE) -> 176 | F110: =VLOOKUP(B110,'26MY_ACCORD_DATA'!B:AS,10,FALSE) -> 293 | G110: =VLOOKUP(B110,'26MY_ACCORD_DATA'!B:AS,7,FALSE) -> 0.4 | H110: =VLOOKUP(B110,'26MY_ACCORD_DATA'!B:AS,11,FALSE) -> 353.8 | I110: =VLOOKUP(B110,'26MY_ACCORD_DATA'!B:AS,12,FALSE) -> 0 | J110: =VLOOKUP(B110,'26MY_ACCORD_DATA'!B:AS,13,FALSE) -> 0 | K110: =VLOOKUP(B110,'26MY_ACCORD_DATA'!B:AS,14,FALSE) -> N/A | L110: =VLOOKUP(B110,'26MY_ACCORD_DATA'!B:AS,15,FALSE) -> 0 | M110: =VLOOKUP(B110,'26MY_ACCORD_DATA'!B:AS,16,FALSE) -> N/A | N110: =VLOOKUP(B110,'26MY_ACCORD_DATA'!B:AS,17,FALSE) -> • | O110: =VLOOKUP(B110,'26MY_ACCORD_DATA'!B:AS,18,FALSE) -> 0 | P110: =VLOOKUP(B110,'26MY_ACCORD_DATA'!B:AS,19,FALSE) -> 0
B111: 08P20-30A-1C0 | C111: =VLOOKUP(B111,'26MY_ACCORD_DATA'!B:AS,3,FALSE) -> Still Night Pearl (B-575P) | D111: =B111 -> 08P20-30A-1C0 | E111: =VLOOKUP(B111,'26MY_ACCORD_DATA'!B:AS,9,FALSE) -> 176 | F111: =VLOOKUP(B111,'26MY_ACCORD_DATA'!B:AS,10,FALSE) -> 293 | G111: =VLOOKUP(B111,'26MY_ACCORD_DATA'!B:AS,7,FALSE) -> 0.4 | H111: =VLOOKUP(B111,'26MY_ACCORD_DATA'!B:AS,11,FALSE) -> 353.8 | I111: =VLOOKUP(B111,'26MY_ACCORD_DATA'!B:AS,12,FALSE) -> 0 | J111: =VLOOKUP(B111,'26MY_ACCORD_DATA'!B:AS,13,FALSE) -> 0 | K111: =VLOOKUP(B111,'26MY_ACCORD_DATA'!B:AS,14,FALSE) -> N/A | L111: =VLOOKUP(B111,'26MY_ACCORD_DATA'!B:AS,15,FALSE) -> 0 | M111: =VLOOKUP(B111,'26MY_ACCORD_DATA'!B:AS,16,FALSE) -> • | N111: =VLOOKUP(B111,'26MY_ACCORD_DATA'!B:AS,17,FALSE) -> N/A | O111: =VLOOKUP(B111,'26MY_ACCORD_DATA'!B:AS,18,FALSE) -> 0 | P111: =VLOOKUP(B111,'26MY_ACCORD_DATA'!B:AS,19,FALSE) -> 0
B112: 08P20-30A-1H0 | C112: =VLOOKUP(B112,'26MY_ACCORD_DATA'!B:AS,3,FALSE) -> Solar Reflection Silver (NH-932M) | D112: =B112 -> 08P20-30A-1H0 | E112: =VLOOKUP(B112,'26MY_ACCORD_DATA'!B:AS,9,FALSE) -> 176 | F112: =VLOOKUP(B112,'26MY_ACCORD_DATA'!B:AS,10,FALSE) -> 293 | G112: =VLOOKUP(B112,'26MY_ACCORD_DATA'!B:AS,7,FALSE) -> 0.4 | H112: =VLOOKUP(B112,'26MY_ACCORD_DATA'!B:AS,11,FALSE) -> 353.8 | I112: =VLOOKUP(B112,'26MY_ACCORD_DATA'!B:AS,12,FALSE) -> 0 | J112: =VLOOKUP(B112,'26MY_ACCORD_DATA'!B:AS,13,FALSE) -> 0 | K112: =VLOOKUP(B112,'26MY_ACCORD_DATA'!B:AS,14,FALSE) -> • | L112: =VLOOKUP(B112,'26MY_ACCORD_DATA'!B:AS,15,FALSE) -> 0 | M112: =VLOOKUP(B112,'26MY_ACCORD_DATA'!B:AS,16,FALSE) -> • | N112: =VLOOKUP(B112,'26MY_ACCORD_DATA'!B:AS,17,FALSE) -> • | O112: =VLOOKUP(B112,'26MY_ACCORD_DATA'!B:AS,18,FALSE) -> 0 | P112: =VLOOKUP(B112,'26MY_ACCORD_DATA'!B:AS,19,FALSE) -> 0
C114: 4.0 Interior
C115: Description | D115: Part Number | E115: Dealer Net | F115: List Price | G115: FRT | H115: Installed Price | J115: Application | Q115: Comments
...

Sheet 26MY_ACCORD_APP_FR
B2: Honda Internal | C2: Accessoires Honda
C3: Nom du modèle | D3: ='26MY_ACCORD_DATA'!$C$2 -> Accord
C4: Année modèle | D4: ='26MY_ACCORD_DATA'!$C$3 -> 2026
C5: S = De série (accessoire de série sur cette version).
C6: T = Taille des pneus (la taille de la jante accessoire diffère de la jante d’origine. Le client aura besoin de nouveaux pneus pour ces jantes).
C7: E = Échange d’équipement de série (la taille de la jante accessoire est la même que celle de la jante d’origine. Le client peut utiliser les pneus d’origine).
C8: N/A = Sans objet (l’accessoire ne peut être utilisé pour cette version).
H10: Province
C11: 1.0 Groupes et ensembles | H11: =prov_cd -> QC
C12: La description | D12: Numéro de pièce | E12: Prix net | F12: Prix de liste | G12: T.F.F. | H12: Prix installé | I12: Application | Q12: Commentaires
I13: ='26MY_ACCORD_DATA'!$M$6 -> 0 | J13: ='26MY_ACCORD_DATA'!$M$6 -> 0 | K13: ='26MY_ACCORD_DATA'!$O$6 -> SE | L13: ='26MY_ACCORD_DATA'!$P$6 -> 0 | M13: ='26MY_ACCORD_DATA'!$Q$6 -> Sport -L Hybride | N13: ='26MY_ACCORD_DATA'!$R$6 -> Touring Hybride | O13: ='26MY_ACCORD_DATA'!$T$6 -> 0 | P13: ='26MY_ACCORD_DATA'!$T$6 -> 0
B14: 23ACC-PRO-PK | C14: =VLOOKUP(B14,'26MY_ACCORD_DATA'!B:AS,4,FALSE) -> Ensemble de protection | D14: =B14 -> 23ACC-PRO-PK | E14: =VLOOKUP(B14,'26MY_ACCORD_DATA'!B:AS,9,FALSE) -> 273.6 | F14: =VLOOKUP(B14,'26MY_ACCORD_DATA'!B:AS,10,FALSE) -> 507 | G14: =VLOOKUP(B14,'26MY_ACCORD_DATA'!B:AS,7,FALSE) -> 0.2 | H14: =VLOOKUP(B14,'26MY_ACCORD_DATA'!B:AS,11,FALSE) -> 537.4 | I14: =VLOOKUP($B14,'26MY_ACCORD_DATA'!$B:$AS,12,FALSE) -> 0 | J14: =VLOOKUP($B14,'26MY_ACCORD_DATA'!$B:$AS,13,FALSE) -> 0 | K14: =VLOOKUP(B14,'26MY_ACCORD_DATA'!B:AS,14,FALSE) -> • | L14: =VLOOKUP(B14,'26MY_ACCORD_DATA'!B:AS,15,FALSE) -> 0 | M14: =VLOOKUP(B14,'26MY_ACCORD_DATA'!B:AS,16,FALSE) -> • | N14: =VLOOKUP(B14,'26MY_ACCORD_DATA'!B:AS,17,FALSE) -> • | O14: =VLOOKUP($B14,'26MY_ACCORD_DATA'!$B:$AS,18,FALSE) -> 0 | P14: =VLOOKUP(B14,'26MY_ACCORD_DATA'!B:AS,19,FALSE) -> 0 | Q14: =IF(VLOOKUP(B14,'26MY_ACCORD_DATA'!B:AS,21,FALSE)="","",VLOOKUP(B14,'26MY_ACCORD_DATA'!B:AS,21,FALSE))
B15: 08P17-30A-110 | C15: =VLOOKUP(B15,'26MY_ACCORD_DATA'!B:AS,4,FALSE) -> Protège-tapis toutes saisons | D15: =B15 -> 08P17-30A-110
B16: 08U45-30A-100 | C16: =VLOOKUP(B16,'26MY_ACCORD_DATA'!B:AS,4,FALSE) -> Plateau de coffre | D16: =B16 -> 08U45-30A-100
B18: 23ACC-PRO-PKA | C18: =VLOOKUP(B18,'26MY_ACCORD_DATA'!B:AS,4,FALSE) -> Ensemble de protection avancée | D18: =B18 -> 23ACC-PRO-PKA | E18: =VLOOKUP(B18,'26MY_ACCORD_DATA'!B:AS,9,FALSE) -> 342.891 | F18: =VLOOKUP(B18,'26MY_ACCORD_DATA'!B:AS,10,FALSE) -> 583.2 | G18: =VLOOKUP(B18,'26MY_ACCORD_DATA'!B:AS,7,FALSE) -> 1 | H18: =VLOOKUP(B18,'26MY_ACCORD_DATA'!B:AS,11,FALSE) -> 735.2 | I18: =VLOOKUP(B18,'26MY_ACCORD_DATA'!B:AS,12,FALSE) -> 0 | J18: =VLOOKUP(B18,'26MY_ACCORD_DATA'!B:AS,13,FALSE) -> 0 | K18: =VLOOKUP(B18,'26MY_ACCORD_DATA'!B:AS,14,FALSE) -> • | L18: =VLOOKUP(B18,'26MY_ACCORD_DATA'!B:AS,15,FALSE) -> 0 | M18: =VLOOKUP(B18,'26MY_ACCORD_DATA'!B:AS,16,FALSE) -> • | N18: =VLOOKUP(B18,'26MY_ACCORD_DATA'!B:AS,17,FALSE) -> N/A | O18: =VLOOKUP(B18,'26MY_ACCORD_DATA'!B:AS,18,FALSE) -> 0 | P18: =VLOOKUP(B18,'26MY_ACCORD_DATA'!B:AS,19,FALSE) -> 0 | Q18: =IF(VLOOKUP(B18,'26MY_ACCORD_DATA'!B:AS,21,FALSE)="","",VLOOKUP(B18,'26MY_ACCORD_DATA'!B:AS,21,FALSE)) -> Rabais de 10 % appliqué.
B19: 08P17-30A-110 | C19: =VLOOKUP(B19,'26MY_ACCORD_DATA'!B:AS,4,FALSE) -> Protège-tapis toutes saisons | D19: =B19 -> 08P17-30A-110
B20: 08U45-30A-100 | C20: =VLOOKUP(B20,'26MY_ACCORD_DATA'!B:AS,4,FALSE) -> Plateau de coffre | D20: =B20 -> 08U45-30A-100
B21: 08P09-30A-300 | C21: =VLOOKUP(B21,'26MY_ACCORD_DATA'!B:AS,4,FALSE) -> Garde-boue arrière | D21: =B21 -> 08P09-30A-300
B22: 08L96-TVA-300 | C22: =VLOOKUP(B22,'26MY_ACCORD_DATA'!B:AS,4,FALSE) -> Filet de cargaison | D22: =B22 -> 08L96-TVA-300
B24: 26ACC-BLK-EMB | C24: =VLOOKUP(B24,'26MY_ACCORD_DATA'!B:AS,4,FALSE) -> Ensemble d’emblèmes noirs – Touring | D24: =B24 -> 26ACC-BLK-EMB | E24: =VLOOKUP(B24,'26MY_ACCORD_DATA'!B:AS,9,FALSE) -> 155.8 | F24: =VLOOKUP(B24,'26MY_ACCORD_DATA'!B:AS,10,FALSE) -> 260.3 | G24: =VLOOKUP(B24,'26MY_ACCORD_DATA'!B:AS,7,FALSE) -> 0.9 | H24: =VLOOKUP(B24,'26MY_ACCORD_DATA'!B:AS,11,FALSE) -> 397.1 | I24: =VLOOKUP($B24,'26MY_ACCORD_DATA'!$B:$AS,12,FALSE) -> 0 | J24: =VLOOKUP($B24,'26MY_ACCORD_DATA'!$B:$AS,13,FALSE) -> 0 | K24: =VLOOKUP(B24,'26MY_ACCORD_DATA'!B:AS,14,FALSE) -> N/A | L24: =VLOOKUP(B24,'26MY_ACCORD_DATA'!B:AS,15,FALSE) -> 0 | M24: =VLOOKUP(B24,'26MY_ACCORD_DATA'!B:AS,16,FALSE) -> N/A | N24: =VLOOKUP(B24,'26MY_ACCORD_DATA'!B:AS,17,FALSE) -> • | O24: =VLOOKUP($B24,'26MY_ACCORD_DATA'!$B:$AS,18,FALSE) -> 0 | P24: =VLOOKUP(B24,'26MY_ACCORD_DATA'!B:AS,19,FALSE) -> 0 | Q24: =IF(VLOOKUP(B24,'26MY_ACCORD_DATA'!B:AS,21,FALSE)="","",VLOOKUP(B24,'26MY_ACCORD_DATA'!B:AS,21,FALSE)) -> Rabais de 5 % appliqué.
B25: 08F20-30A-100C | C25: =VLOOKUP(B25,'26MY_ACCORD_DATA'!B:AS,4,FALSE) -> Emblème, noirs lustré arrière « H » mark | D25: =B25 -> 08F20-30A-100C
B26: 08F20-30A-100D | C26: =VLOOKUP(B26,'26MY_ACCORD_DATA'!B:AS,4,FALSE) -> Emblème, noirs lustré arrière « Accord » | D26: =B26 -> 08F20-30A-100D
B27: 08F20-3A0-100C | C27: =VLOOKUP(B27,'26MY_ACCORD_DATA'!B:AS,4,FALSE) -> Emblème, noirs lustré « Touring » | D27: =B27 -> 08F20-3A0-100C
B28: 08F20-T20-100B | C28: =VLOOKUP(B28,'26MY_ACCORD_DATA'!B:AS,4,FALSE) -> Emblème, noirs lustré « Hybride » | D28: =B28 -> 08F20-T20-100B
B30: 23ACC-ARO-EX | C30: =VLOOKUP(B30,'26MY_ACCORD_DATA'!B:AS,4,FALSE) -> Ensemble Aero – Version SE | D30: =B30 -> 23ACC-ARO-EX | E30: =VLOOKUP(B30,'26MY_ACCORD_DATA'!B:AS,9,FALSE) -> 1555.2 | F30: =VLOOKUP(B30,'26MY_ACCORD_DATA'!B:AS,10,FALSE) -> 2591.1 | G30: =VLOOKUP(B30,'26MY_ACCORD_DATA'!B:AS,7,FALSE) -> 3.5 | H30: =VLOOKUP(B30,'26MY_ACCORD_DATA'!B:AS,11,FALSE) -> 3123.1 | I30: =VLOOKUP(B30,'26MY_ACCORD_DATA'!B:AS,12,FALSE) -> 0 | J30: =VLOOKUP(B30,'26MY_ACCORD_DATA'!B:AS,13,FALSE) -> 0 | K30: =VLOOKUP(B30,'26MY_ACCORD_DATA'!B:AS,14,FALSE) -> • | L30: =VLOOKUP(B30,'26MY_ACCORD_DATA'!B:AS,15,FALSE) -> 0 | M30: =VLOOKUP(B30,'26MY_ACCORD_DATA'!B:AS,16,FALSE) -> N/A | N30: =VLOOKUP(B30,'26MY_ACCORD_DATA'!B:AS,17,FALSE) -> N/A | O30: =VLOOKUP(B30,'26MY_ACCORD_DATA'!B:AS,18,FALSE) -> 0 | P30: =VLOOKUP(B30,'26MY_ACCORD_DATA'!B:AS,19,FALSE) -> 0 | Q30: =IF(VLOOKUP(B30,'26MY_ACCORD_DATA'!B:AS,21,FALSE)="","",VLOOKUP(B30,'26MY_ACCORD_DATA'!B:AS,21,FALSE)) -> Rabais de 10 % est appliqué Déflecteur arrière de coffre - Noir cristal nacré couleur (NH-731P)
B31: 08F04-30A-1F0 | C31: =VLOOKUP(B31,'26MY_ACCORD_DATA'!B:AS,4,FALSE) -> Becquet de bas de caisse, latéral | D31: =B31 -> 08F04-30A-1F0
B32: 08P98-30A-1F0 | C32: =VLOOKUP(B32,'26MY_ACCORD_DATA'!B:AS,4,FALSE) -> Becquet de bas de caisse, avant | D32: =B32 -> 08P98-30A-1F0
B33: 08P99-30A-1F0 | C33: =VLOOKUP(B33,'26MY_ACCORD_DATA'!B:AS,4,FALSE) -> Becquet de bas de caisse, arrière | D33: =B33 -> 08P99-30A-1F0
B34: 08F10-30A-170 | C34: =VLOOKUP(B34,'26MY_ACCORD_DATA'!B:AS,4,FALSE) -> Noir cristal nacré (NH-731P) | D34: =B34 -> 08F10-30A-170
B35: 08R06-30A-110 | C35: =VLOOKUP(B35,'26MY_ACCORD_DATA'!B:AS,4,FALSE) -> Couvercle de rétroviseur de portière et élément inférieur d’admission d’air | D35: =B35 -> 08R06-30A-110
B37: 23ACC-ARO-SPHY | C37: =VLOOKUP(B37,'26MY_ACCORD_DATA'!B:AS,4,FALSE) -> Ensemble Aero – Version Sport | D37: =B37 -> 23ACC-ARO-SPHY | E37: =VLOOKUP(B37,'26MY_ACCORD_DATA'!B:AS,9,FALSE) -> 1018.8 | F37: =VLOOKUP(B37,'26MY_ACCORD_DATA'!B:AS,10,FALSE) -> 1697.4 | G37: =VLOOKUP(B37,'26MY_ACCORD_DATA'!B:AS,7,FALSE) -> 1.8 | H37: =VLOOKUP(B37,'26MY_ACCORD_DATA'!B:AS,11,FALSE) -> 1971 | I37: =VLOOKUP(B37,'26MY_ACCORD_DATA'!B:AS,12,FALSE) -> 0 | J37: =VLOOKUP(B37,'26MY_ACCORD_DATA'!B:AS,13,FALSE) -> 0 | K37: =VLOOKUP(B37,'26MY_ACCORD_DATA'!B:AS,14,FALSE) -> N/A | L37: =VLOOKUP(B37,'26MY_ACCORD_DATA'!B:AS,15,FALSE) -> 0 | M37: =VLOOKUP(B37,'26MY_ACCORD_DATA'!B:AS,16,FALSE) -> • | N37: =VLOOKUP(B37,'26MY_ACCORD_DATA'!B:AS,17,FALSE) -> N/A | O37: =VLOOKUP(B37,'26MY_ACCORD_DATA'!B:AS,18,FALSE) -> 0 | P37: =VLOOKUP(B37,'26MY_ACCORD_DATA'!B:AS,19,FALSE) -> 0 | Q37: =IF(VLOOKUP(B37,'26MY_ACCORD_DATA'!B:AS,21,FALSE)="","",VLOOKUP(B37,'26MY_ACCORD_DATA'!B:AS,21,FALSE)) -> Rabais de 10 % est appliqué Version Sport Hybride est livrée de série avec le becquet de bas de caisse, arrière
B38: 08F04-30A-1F0 | C38: =VLOOKUP(B38,'26MY_ACCORD_DATA'!B:AS,4,FALSE) -> Becquet de bas de caisse, latéral | D38: =B38 -> 08F04-30A-1F0
B39: 08P98-30A-1F0 | C39: =VLOOKUP(B39,'26MY_ACCORD_DATA'!B:AS,4,FALSE) -> Becquet de bas de caisse, avant | D39: =B39 -> 08P98-30A-1F0
B40: 08P99-30A-1F0 | C40: =VLOOKUP(B40,'26MY_ACCORD_DATA'!B:AS,4,FALSE) -> Becquet de bas de caisse, arrière | D40: =B40 -> 08P99-30A-1F0
B42: 23ACC-ARO-TRHY | C42: =VLOOKUP(B42,'26MY_ACCORD_DATA'!B:AS,4,FALSE) -> Ensemble Aero – Version Touring | D42: =B42 -> 23ACC-ARO-TRHY | E42: =VLOOKUP(B42,'26MY_ACCORD_DATA'!B:AS,9,FALSE) -> 1555.2 | F42: =VLOOKUP(B42,'26MY_ACCORD_DATA'!B:AS,10,FALSE) -> 2591.1 | G42: =VLOOKUP(B42,'26MY_ACCORD_DATA'!B:AS,7,FALSE) -> 3.5 | H42: =VLOOKUP(B42,'26MY_ACCORD_DATA'!B:AS,11,FALSE) -> 3123.1 | I42: =VLOOKUP(B42,'26MY_ACCORD_DATA'!B:AS,12,FALSE) -> 0 | J42: =VLOOKUP(B42,'26MY_ACCORD_DATA'!B:AS,13,FALSE) -> 0 | K42: =VLOOKUP(B42,'26MY_ACCORD_DATA'!B:AS,14,FALSE) -> N/A | L42: =VLOOKUP(B42,'26MY_ACCORD_DATA'!B:AS,15,FALSE) -> 0 | M42: =VLOOKUP(B42,'26MY_ACCORD_DATA'!B:AS,16,FALSE) -> N/A | N42: =VLOOKUP(B42,'26MY_ACCORD_DATA'!B:AS,17,FALSE) -> • | O42: =VLOOKUP(B42,'26MY_ACCORD_DATA'!B:AS,18,FALSE) -> 0 | P42: =VLOOKUP(B42,'26MY_ACCORD_DATA'!B:AS,19,FALSE) -> 0 | Q42: =IF(VLOOKUP(B42,'26MY_ACCORD_DATA'!B:AS,21,FALSE)="","",VLOOKUP(B42,'26MY_ACCORD_DATA'!B:AS,21,FALSE)) -> Rabais de 10 % est appliqué Déflecteur arrière de coffre - Noir cristal nacré couleur (NH-731P)
B43: 08F04-30A-1F0 | C43: =VLOOKUP(B43,'26MY_ACCORD_DATA'!B:AS,4,FALSE) -> Becquet de bas de caisse, latéral | D43: =B43 -> 08F04-30A-1F0
B44: 08P98-30A-1F0 | C44: =VLOOKUP(B44,'26MY_ACCORD_DATA'!B:AS,4,FALSE) -> Becquet de bas de caisse, avant | D44: =B44 -> 08P98-30A-1F0
B45: 08P99-30A-1F0 | C45: =VLOOKUP(B45,'26MY_ACCORD_DATA'!B:AS,4,FALSE) -> Becquet de bas de caisse, arrière | D45: =B45 -> 08P99-30A-1F0
B46: 08F10-30A-170 | C46: =VLOOKUP(B46,'26MY_ACCORD_DATA'!B:AS,4,FALSE) -> Noir cristal nacré (NH-731P) | D46: =B46 -> 08F10-30A-170
B47: 08R06-30A-110A | C47: =VLOOKUP(B47,'26MY_ACCORD_DATA'!B:AS,4,FALSE) -> Couvercle de rétroviseur de portière et élément inférieur d’admission d’air | D47: =B47 -> 08R06-30A-110A
B49: 23ACC-COLD-PKP | C49: =VLOOKUP(B49,'26MY_ACCORD_DATA'!B:AS,4,FALSE) -> Ensemble de temps froid | D49: =B49 -> 23ACC-COLD-PKP | E49: =VLOOKUP(B49,'26MY_ACCORD_DATA'!B:AS,9,FALSE) -> 226.1 | F49: =VLOOKUP(B49,'26MY_ACCORD_DATA'!B:AS,10,FALSE) -> 377.15 | G49: =VLOOKUP(B49,'26MY_ACCORD_DATA'!B:AS,7,FALSE) -> 1.2 | H49: =VLOOKUP(B49,'26MY_ACCORD_DATA'!B:AS,11,FALSE) -> 559.55 | I49: =VLOOKUP($B49,'26MY_ACCORD_DATA'!$B:$AS,12,FALSE) -> 0 | J49: =VLOOKUP($B49,'26MY_ACCORD_DATA'!$B:$AS,13,FALSE) -> 0 | K49: =VLOOKUP(B49,'26MY_ACCORD_DATA'!B:AS,14,FALSE) -> • | L49: =VLOOKUP(B49,'26MY_ACCORD_DATA'!B:AS,15,FALSE) -> 0 | M49: =VLOOKUP(B49,'26MY_ACCORD_DATA'!B:AS,16,FALSE) -> N/A | N49: =VLOOKUP(B49,'26MY_ACCORD_DATA'!B:AS,17,FALSE) -> N/A | O49: =VLOOKUP($B49,'26MY_ACCORD_DATA'!$B:$AS,18,FALSE) -> 0 | P49: =VLOOKUP(B49,'26MY_ACCORD_DATA'!B:AS,19,FALSE) -> 0 | Q49: =IF(VLOOKUP(B49,'26MY_ACCORD_DATA'!B:AS,21,FALSE)="","",VLOOKUP(B49,'26MY_ACCORD_DATA'!B:AS,21,FALSE)) -> Rabais de 5 % appliqué.
B50: 08T44-30A-300A | C50: =VLOOKUP(B50,'26MY_ACCORD_DATA'!B:AS,4,FALSE) -> Chauffe-moteur | D50: =B50 -> 08T44-30A-300A
B51: 31670-BMS-004H | C51: =VLOOKUP(B51,'26MY_ACCORD_DATA'!B:AS,4,FALSE) -> Chargeur/mainteneur de batterie automobile 12 V Optimate | D51: =B51 -> 31670-BMS-004H
B53: 23ACC-COLD-PKH | C53: =VLOOKUP(B53,'26MY_ACCORD_DATA'!B:AS,4,FALSE) -> Ensemble de temps froid | D53: =B53 -> 23ACC-COLD-PKH | E53: =VLOOKUP(B53,'26MY_ACCORD_DATA'!B:AS,9,FALSE) -> 251.75 | F53: =VLOOKUP(B53,'26MY_ACCORD_DATA'!B:AS,10,FALSE) -> 419.9 | G53: =VLOOKUP(B53,'26MY_ACCORD_DATA'!B:AS,7,FALSE) -> 1.2 | H53: =VLOOKUP(B53,'26MY_ACCORD_DATA'!B:AS,11,FALSE) -> 602.3 | I53: =VLOOKUP($B53,'26MY_ACCORD_DATA'!$B:$AS,12,FALSE) -> 0 | J53: =VLOOKUP($B53,'26MY_ACCORD_DATA'!$B:$AS,13,FALSE) -> 0 | K53: =VLOOKUP(B53,'26MY_ACCORD_DATA'!B:AS,14,FALSE) -> N/A | L53: =VLOOKUP(B53,'26MY_ACCORD_DATA'!B:AS,15,FALSE) -> 0 | M53: =VLOOKUP(B53,'26MY_ACCORD_DATA'!B:AS,16,FALSE) -> • | N53: =VLOOKUP(B53,'26MY_ACCORD_DATA'!B:AS,17,FALSE) -> • | O53: =VLOOKUP($B53,'26MY_ACCORD_DATA'!$B:$AS,18,FALSE) -> 0 | P53: =VLOOKUP(B53,'26MY_ACCORD_DATA'!B:AS,19,FALSE) -> 0 | Q53: =IF(VLOOKUP(B53,'26MY_ACCORD_DATA'!B:AS,21,FALSE)="","",VLOOKUP(B53,'26MY_ACCORD_DATA'!B:AS,21,FALSE)) -> Rabais de 5 % appliqué.
A54: 08T44-30B-300A | B54: 08T44-30B-300A | C54: =VLOOKUP(B54,'26MY_ACCORD_DATA'!B:AS,4,FALSE) -> Chauffe-moteur | D54: =B54 -> 08T44-30B-300A
B55: 31670-BMS-004H | C55: =VLOOKUP(B55,'26MY_ACCORD_DATA'!B:AS,4,FALSE) -> Chargeur/mainteneur de batterie automobile 12 V Optimate | D55: =B55 -> 31670-BMS-004H
C57: 2.0 Jantes et accessoires de jantes
C58: La description | D58: Numéro de pièce | E58: Prix net | F58: Prix de liste | G58: T.F.F. | H58: Prix installé | I58: Application | Q58: Commentaires
I59: ='26MY_ACCORD_DATA'!$M$6 -> 0 | J59: ='26MY_ACCORD_DATA'!$M$6 -> 0 | K59: ='26MY_ACCORD_DATA'!$O$6 -> SE | L59: ='26MY_ACCORD_DATA'!$P$6 -> 0 | M59: ='26MY_ACCORD_DATA'!$Q$6 -> Sport -L Hybride | N59: ='26MY_ACCORD_DATA'!$R$6 -> Touring Hybride | O59: ='26MY_ACCORD_DATA'!$T$6 -> 0 | P59: ='26MY_ACCORD_DATA'!$T$6 -> 0
B60: 08W17-PC4-300 | C60: =VLOOKUP(B60,'26MY_ACCORD_DATA'!B:AS,4,FALSE) -> 17 po en acier de roues | D60: =B60 -> 08W17-PC4-300 | E60: =VLOOKUP(B60,'26MY_ACCORD_DATA'!B:AS,9,FALSE) -> 376.4 | F60: =VLOOKUP(B60,'26MY_ACCORD_DATA'!B:AS,10,FALSE) -> 627.28 | G60: =VLOOKUP(B60,'26MY_ACCORD_DATA'!B:AS,7,FALSE) -> 1.6 | H60: =VLOOKUP(B60,'26MY_ACCORD_DATA'!B:AS,11,FALSE) -> 870.48 | I60: =VLOOKUP(B60,'26MY_ACCORD_DATA'!B:AS,12,FALSE) -> 0 | J60: =VLOOKUP(B60,'26MY_ACCORD_DATA'!B:AS,13,FALSE) -> 0 | K60: =VLOOKUP(B60,'26MY_ACCORD_DATA'!B:AS,14,FALSE) -> T | L60: =VLOOKUP(B60,'26MY_ACCORD_DATA'!B:AS,15,FALSE) -> 0 | M60: =VLOOKUP(B60,'26MY_ACCORD_DATA'!B:AS,16,FALSE) -> T | N60: =VLOOKUP(B60,'26MY_ACCORD_DATA'!B:AS,17,FALSE) -> T | O60: =VLOOKUP(B60,'26MY_ACCORD_DATA'!B:AS,18,FALSE) -> 0 | P60: =VLOOKUP(B60,'26MY_ACCORD_DATA'!B:AS,19,FALSE) -> 0 | Q60: =IF(VLOOKUP(B60,'26MY_ACCORD_DATA'!B:AS,21,FALSE)="","",VLOOKUP(B60,'26MY_ACCORD_DATA'!B:AS,21,FALSE)) -> Prix pour un ensemble de 4 roues. Pneus vendus séparément.
B61: 08W19-30A-300 | C61: =VLOOKUP(B61,'26MY_ACCORD_DATA'!B:AS,4,FALSE) -> Jantes de 19 pouces HPD en alliage noir | D61: =B61 -> 08W19-30A-300 | E61: =VLOOKUP(B61,'26MY_ACCORD_DATA'!B:AS,9,FALSE) -> 2628 | F61: =VLOOKUP(B61,'26MY_ACCORD_DATA'!B:AS,10,FALSE) -> 3756 | G61: =VLOOKUP(B61,'26MY_ACCORD_DATA'!B:AS,7,FALSE) -> 1.6 | H61: =VLOOKUP(B61,'26MY_ACCORD_DATA'!B:AS,11,FALSE) -> 3999.2 | I61: =VLOOKUP(B61,'26MY_ACCORD_DATA'!B:AS,12,FALSE) -> 0 | J61: =VLOOKUP(B61,'26MY_ACCORD_DATA'!B:AS,13,FALSE) -> 0 | K61: =VLOOKUP(B61,'26MY_ACCORD_DATA'!B:AS,14,FALSE) -> E | L61: =VLOOKUP(B61,'26MY_ACCORD_DATA'!B:AS,15,FALSE) -> 0 | M61: =VLOOKUP(B61,'26MY_ACCORD_DATA'!B:AS,16,FALSE) -> E | N61: =VLOOKUP(B61,'26MY_ACCORD_DATA'!B:AS,17,FALSE) -> E | O61: =VLOOKUP(B61,'26MY_ACCORD_DATA'!B:AS,18,FALSE) -> 0 | P61: =VLOOKUP(B61,'26MY_ACCORD_DATA'!B:AS,19,FALSE) -> 0 | Q61: =IF(VLOOKUP(B61,'26MY_ACCORD_DATA'!B:AS,21,FALSE)="","",VLOOKUP(B61,'26MY_ACCORD_DATA'!B:AS,21,FALSE)) -> Prix pour un ensemble de 4 roues. Pneus vendus séparément.
B62: 08W42-SCV-302 | C62: =VLOOKUP(B62,'26MY_ACCORD_DATA'!B:AS,4,FALSE) -> Écrous de roue antivols - Chromés | D62: =B62 -> 08W42-SCV-302 | E62: =VLOOKUP(B62,'26MY_ACCORD_DATA'!B:AS,9,FALSE) -> 54 | F62: =VLOOKUP(B62,'26MY_ACCORD_DATA'!B:AS,10,FALSE) -> 90 | G62: =VLOOKUP(B62,'26MY_ACCORD_DATA'!B:AS,7,FALSE) -> 0.2 | H62: =VLOOKUP(B62,'26MY_ACCORD_DATA'!B:AS,11,FALSE) -> 120.4 | I62: =VLOOKUP(B62,'26MY_ACCORD_DATA'!B:AS,12,FALSE) -> 0 | J62: =VLOOKUP(B62,'26MY_ACCORD_DATA'!B:AS,13,FALSE) -> 0 | K62: =VLOOKUP(B62,'26MY_ACCORD_DATA'!B:AS,14,FALSE) -> • | L62: =VLOOKUP(B62,'26MY_ACCORD_DATA'!B:AS,15,FALSE) -> 0 | M62: =VLOOKUP(B62,'26MY_ACCORD_DATA'!B:AS,16,FALSE) -> • | N62: =VLOOKUP(B62,'26MY_ACCORD_DATA'!B:AS,17,FALSE) -> • | O62: =VLOOKUP(B62,'26MY_ACCORD_DATA'!B:AS,18,FALSE) -> 0 | P62: =VLOOKUP(B62,'26MY_ACCORD_DATA'!B:AS,19,FALSE) -> 0 | Q62: =IF(VLOOKUP(B62,'26MY_ACCORD_DATA'!B:AS,21,FALSE)="","",VLOOKUP(B62,'26MY_ACCORD_DATA'!B:AS,21,FALSE))
B63: 08W42-SNA-301 | C63: =VLOOKUP(B63,'26MY_ACCORD_DATA'!B:AS,4,FALSE) -> Écrous de roue antivol, chromée - exposés | D63: =B63 -> 08W42-SNA-301 | E63: =VLOOKUP(B63,'26MY_ACCORD_DATA'!B:AS,9,FALSE) -> 44 | F63: =VLOOKUP(B63,'26MY_ACCORD_DATA'!B:AS,10,FALSE) -> 73 | G63: =VLOOKUP(B63,'26MY_ACCORD_DATA'!B:AS,7,FALSE) -> 0.2 | H63: =VLOOKUP(B63,'26MY_ACCORD_DATA'!B:AS,11,FALSE) -> 103.4 | I63: =VLOOKUP(B63,'26MY_ACCORD_DATA'!B:AS,12,FALSE) -> 0 | J63: =VLOOKUP(B63,'26MY_ACCORD_DATA'!B:AS,13,FALSE) -> 0 | K63: =VLOOKUP(B63,'26MY_ACCORD_DATA'!B:AS,14,FALSE) -> • | L63: =VLOOKUP(B63,'26MY_ACCORD_DATA'!B:AS,15,FALSE) -> 0 | M63: =VLOOKUP(B63,'26MY_ACCORD_DATA'!B:AS,16,FALSE) -> • | N63: =VLOOKUP(B63,'26MY_ACCORD_DATA'!B:AS,17,FALSE) -> • | O63: =VLOOKUP(B63,'26MY_ACCORD_DATA'!B:AS,18,FALSE) -> 0 | P63: =VLOOKUP(B63,'26MY_ACCORD_DATA'!B:AS,19,FALSE) -> 0 | Q63: =IF(VLOOKUP(B63,'26MY_ACCORD_DATA'!B:AS,21,FALSE)="","",VLOOKUP(B63,'26MY_ACCORD_DATA'!B:AS,21,FALSE))
B64: 08W42-S2A-101 | C64: =VLOOKUP(B64,'26MY_ACCORD_DATA'!B:AS,4,FALSE) -> Écrous de roue antivols - Noirs | D64: =B64 -> 08W42-S2A-101 | E64: =VLOOKUP(B64,'26MY_ACCORD_DATA'!B:AS,9,FALSE) -> 61 | F64: =VLOOKUP(B64,'26MY_ACCORD_DATA'!B:AS,10,FALSE) -> 102 | G64: =VLOOKUP(B64,'26MY_ACCORD_DATA'!B:AS,7,FALSE) -> 0.2 | H64: =VLOOKUP(B64,'26MY_ACCORD_DATA'!B:AS,11,FALSE) -> 132.4 | I64: =VLOOKUP(B64,'26MY_ACCORD_DATA'!B:AS,12,FALSE) -> 0 | J64: =VLOOKUP(B64,'26MY_ACCORD_DATA'!B:AS,13,FALSE) -> 0 | K64: =VLOOKUP(B64,'26MY_ACCORD_DATA'!B:AS,14,FALSE) -> • | L64: =VLOOKUP(B64,'26MY_ACCORD_DATA'!B:AS,15,FALSE) -> 0 | M64: =VLOOKUP(B64,'26MY_ACCORD_DATA'!B:AS,16,FALSE) -> • | N64: =VLOOKUP(B64,'26MY_ACCORD_DATA'!B:AS,17,FALSE) -> • | O64: =VLOOKUP(B64,'26MY_ACCORD_DATA'!B:AS,18,FALSE) -> 0 | P64: =VLOOKUP(B64,'26MY_ACCORD_DATA'!B:AS,19,FALSE) -> 0 | Q64: =IF(VLOOKUP(B64,'26MY_ACCORD_DATA'!B:AS,21,FALSE)="","",VLOOKUP(B64,'26MY_ACCORD_DATA'!B:AS,21,FALSE))
B65: 08W42-PL4-100 | C65: =VLOOKUP(B65,'26MY_ACCORD_DATA'!B:AS,4,FALSE) -> Écrous de roue - Noir | D65: =B65 -> 08W42-PL4-100 | E65: =VLOOKUP(B65,'26MY_ACCORD_DATA'!B:AS,9,FALSE) -> 170 | F65: =VLOOKUP(B65,'26MY_ACCORD_DATA'!B:AS,10,FALSE) -> 283 | G65: =VLOOKUP(B65,'26MY_ACCORD_DATA'!B:AS,7,FALSE) -> 0.2 | H65: =VLOOKUP(B65,'26MY_ACCORD_DATA'!B:AS,11,FALSE) -> 313.4 | I65: =VLOOKUP(B65,'26MY_ACCORD_DATA'!B:AS,12,FALSE) -> 0 | J65: =VLOOKUP(B65,'26MY_ACCORD_DATA'!B:AS,13,FALSE) -> 0 | K65: =VLOOKUP(B65,'26MY_ACCORD_DATA'!B:AS,14,FALSE) -> • | L65: =VLOOKUP(B65,'26MY_ACCORD_DATA'!B:AS,15,FALSE) -> 0 | M65: =VLOOKUP(B65,'26MY_ACCORD_DATA'!B:AS,16,FALSE) -> • | N65: =VLOOKUP(B65,'26MY_ACCORD_DATA'!B:AS,17,FALSE) -> • | O65: =VLOOKUP(B65,'26MY_ACCORD_DATA'!B:AS,18,FALSE) -> 0 | P65: =VLOOKUP(B65,'26MY_ACCORD_DATA'!B:AS,19,FALSE) -> 0 | Q65: =IF(VLOOKUP(B65,'26MY_ACCORD_DATA'!B:AS,21,FALSE)="","",VLOOKUP(B65,'26MY_ACCORD_DATA'!B:AS,21,FALSE)) -> lot de 20 écrous de roue
C67: 3.0 Extérieur
C68: La description | D68: Numéro de pièce | E68: Prix net | F68: Prix de liste | G68: T.F.F. | H68: Prix installé | I68: Application | Q68: Commentaires
I69: ='26MY_ACCORD_DATA'!$M$6 -> 0 | J69: ='26MY_ACCORD_DATA'!$M$6 -> 0 | K69: ='26MY_ACCORD_DATA'!$O$6 -> SE | L69: ='26MY_ACCORD_DATA'!$P$6 -> 0 | M69: ='26MY_ACCORD_DATA'!$Q$6 -> Sport -L Hybride | N69: ='26MY_ACCORD_DATA'!$R$6 -> Touring Hybride | O69: ='26MY_ACCORD_DATA'!$T$6 -> 0 | P69: ='26MY_ACCORD_DATA'!$T$6 -> 0
B70: 08F04-30A-1F0 | C70: =VLOOKUP(B70,'26MY_ACCORD_DATA'!B:AS,4,FALSE) -> Becquet de bas de caisse, latéral | D70: =B70 -> 08F04-30A-1F0 | E70: =VLOOKUP(B70,'26MY_ACCORD_DATA'!B:AS,9,FALSE) -> 432 | F70: =VLOOKUP(B70,'26MY_ACCORD_DATA'!B:AS,10,FALSE) -> 720 | G70: =VLOOKUP(B70,'26MY_ACCORD_DATA'!B:AS,7,FALSE) -> 0.6 | H70: =VLOOKUP(B70,'26MY_ACCORD_DATA'!B:AS,11,FALSE) -> 811.2 | I70: =VLOOKUP(B70,'26MY_ACCORD_DATA'!B:AS,12,FALSE) -> 0 | J70: =VLOOKUP(B70,'26MY_ACCORD_DATA'!B:AS,13,FALSE) -> 0 | K70: =VLOOKUP(B70,'26MY_ACCORD_DATA'!B:AS,14,FALSE) -> • | L70: =VLOOKUP(B70,'26MY_ACCORD_DATA'!B:AS,15,FALSE) -> 0 | M70: =VLOOKUP(B70,'26MY_ACCORD_DATA'!B:AS,16,FALSE) -> • | N70: =VLOOKUP(B70,'26MY_ACCORD_DATA'!B:AS,17,FALSE) -> • | O70: =VLOOKUP(B70,'26MY_ACCORD_DATA'!B:AS,18,FALSE) -> 0 | P70: =VLOOKUP(B70,'26MY_ACCORD_DATA'!B:AS,19,FALSE) -> 0 | Q70: =IF(VLOOKUP(B70,'26MY_ACCORD_DATA'!B:AS,21,FALSE)="","",VLOOKUP(B70,'26MY_ACCORD_DATA'!B:AS,21,FALSE))
B71: 08P98-30A-1F0 | C71: =VLOOKUP(B71,'26MY_ACCORD_DATA'!B:AS,4,FALSE) -> Becquet de bas de caisse, avant | D71: =B71 -> 08P98-30A-1F0 | E71: =VLOOKUP(B71,'26MY_ACCORD_DATA'!B:AS,9,FALSE) -> 350 | F71: =VLOOKUP(B71,'26MY_ACCORD_DATA'!B:AS,10,FALSE) -> 583 | G71: =VLOOKUP(B71,'26MY_ACCORD_DATA'!B:AS,7,FALSE) -> 0.6 | H71: =VLOOKUP(B71,'26MY_ACCORD_DATA'!B:AS,11,FALSE) -> 674.2 | I71: =VLOOKUP(B71,'26MY_ACCORD_DATA'!B:AS,12,FALSE) -> 0 | J71: =VLOOKUP(B71,'26MY_ACCORD_DATA'!B:AS,13,FALSE) -> 0 | K71: =VLOOKUP(B71,'26MY_ACCORD_DATA'!B:AS,14,FALSE) -> • | L71: =VLOOKUP(B71,'26MY_ACCORD_DATA'!B:AS,15,FALSE) -> 0 | M71: =VLOOKUP(B71,'26MY_ACCORD_DATA'!B:AS,16,FALSE) -> • | N71: =VLOOKUP(B71,'26MY_ACCORD_DATA'!B:AS,17,FALSE) -> • | O71: =VLOOKUP(B71,'26MY_ACCORD_DATA'!B:AS,18,FALSE) -> 0 | P71: =VLOOKUP(B71,'26MY_ACCORD_DATA'!B:AS,19,FALSE) -> 0 | Q71: =IF(VLOOKUP(B71,'26MY_ACCORD_DATA'!B:AS,21,FALSE)="","",VLOOKUP(B71,'26MY_ACCORD_DATA'!B:AS,21,FALSE))
B72: 08P99-30A-1F0 | C72: =VLOOKUP(B72,'26MY_ACCORD_DATA'!B:AS,4,FALSE) -> Becquet de bas de caisse, arrière | D72: =B72 -> 08P99-30A-1F0 | E72: =VLOOKUP(B72,'26MY_ACCORD_DATA'!B:AS,9,FALSE) -> 350 | F72: =VLOOKUP(B72,'26MY_ACCORD_DATA'!B:AS,10,FALSE) -> 583 | G72: =VLOOKUP(B72,'26MY_ACCORD_DATA'!B:AS,7,FALSE) -> 0.6 | H72: =VLOOKUP(B72,'26MY_ACCORD_DATA'!B:AS,11,FALSE) -> 674.2 | I72: =VLOOKUP(B72,'26MY_ACCORD_DATA'!B:AS,12,FALSE) -> 0 | J72: =VLOOKUP(B72,'26MY_ACCORD_DATA'!B:AS,13,FALSE) -> 0 | K72: =VLOOKUP(B72,'26MY_ACCORD_DATA'!B:AS,14,FALSE) -> • | L72: =VLOOKUP(B72,'26MY_ACCORD_DATA'!B:AS,15,FALSE) -> 0 | M72: =VLOOKUP(B72,'26MY_ACCORD_DATA'!B:AS,16,FALSE) -> • | N72: =VLOOKUP(B72,'26MY_ACCORD_DATA'!B:AS,17,FALSE) -> • | O72: =VLOOKUP(B72,'26MY_ACCORD_DATA'!B:AS,18,FALSE) -> 0 | P72: =VLOOKUP(B72,'26MY_ACCORD_DATA'!B:AS,19,FALSE) -> 0 | Q72: =IF(VLOOKUP(B72,'26MY_ACCORD_DATA'!B:AS,21,FALSE)="","",VLOOKUP(B72,'26MY_ACCORD_DATA'!B:AS,21,FALSE))
B73: 08R06-30A-110 | C73: =VLOOKUP(B73,'26MY_ACCORD_DATA'!B:AS,4,FALSE) -> Couvercle de rétroviseur de portière et élément inférieur d’admission d’air | D73: =B73 -> 08R06-30A-110 | E73: =VLOOKUP(B73,'26MY_ACCORD_DATA'!B:AS,9,FALSE) -> 210 | F73: =VLOOKUP(B73,'26MY_ACCORD_DATA'!B:AS,10,FALSE) -> 350 | G73: =VLOOKUP(B73,'26MY_ACCORD_DATA'!B:AS,7,FALSE) -> 1.1 | H73: =VLOOKUP(B73,'26MY_ACCORD_DATA'!B:AS,11,FALSE) -> 517.2 | I73: =VLOOKUP(B73,'26MY_ACCORD_DATA'!B:AS,12,FALSE) -> 0 | J73: =VLOOKUP(B73,'26MY_ACCORD_DATA'!B:AS,13,FALSE) -> 0 | K73: =VLOOKUP(B73,'26MY_ACCORD_DATA'!B:AS,14,FALSE) -> • | L73: =VLOOKUP(B73,'26MY_ACCORD_DATA'!B:AS,15,FALSE) -> 0 | M73: =VLOOKUP(B73,'26MY_ACCORD_DATA'!B:AS,16,FALSE) -> N/A | N73: =VLOOKUP(B73,'26MY_ACCORD_DATA'!B:AS,17,FALSE) -> N/A | O73: =VLOOKUP(B73,'26MY_ACCORD_DATA'!B:AS,18,FALSE) -> 0 | P73: =VLOOKUP(B73,'26MY_ACCORD_DATA'!B:AS,19,FALSE) -> 0 | Q73: =IF(VLOOKUP(B73,'26MY_ACCORD_DATA'!B:AS,21,FALSE)="","",VLOOKUP(B73,'26MY_ACCORD_DATA'!B:AS,21,FALSE))
B74: 08R06-30A-110A | C74: =VLOOKUP(B74,'26MY_ACCORD_DATA'!B:AS,4,FALSE) -> Couvercle de rétroviseur de portière et élément inférieur d’admission d’air | D74: =B74 -> 08R06-30A-110A | E74: =VLOOKUP(B74,'26MY_ACCORD_DATA'!B:AS,9,FALSE) -> 210 | F74: =VLOOKUP(B74,'26MY_ACCORD_DATA'!B:AS,10,FALSE) -> 350 | G74: =VLOOKUP(B74,'26MY_ACCORD_DATA'!B:AS,7,FALSE) -> 1.1 | H74: =VLOOKUP(B74,'26MY_ACCORD_DATA'!B:AS,11,FALSE) -> 517.2 | I74: =VLOOKUP(B74,'26MY_ACCORD_DATA'!B:AS,12,FALSE) -> 0 | J74: =VLOOKUP(B74,'26MY_ACCORD_DATA'!B:AS,13,FALSE) -> 0 | K74: =VLOOKUP(B74,'26MY_ACCORD_DATA'!B:AS,14,FALSE) -> N/A | L74: =VLOOKUP(B74,'26MY_ACCORD_DATA'!B:AS,15,FALSE) -> 0 | M74: =VLOOKUP(B74,'26MY_ACCORD_DATA'!B:AS,16,FALSE) -> N/A | N74: =VLOOKUP(B74,'26MY_ACCORD_DATA'!B:AS,17,FALSE) -> • | O74: =VLOOKUP(B74,'26MY_ACCORD_DATA'!B:AS,18,FALSE) -> 0 | P74: =VLOOKUP(B74,'26MY_ACCORD_DATA'!B:AS,19,FALSE) -> 0 | Q74: =IF(VLOOKUP(B74,'26MY_ACCORD_DATA'!B:AS,21,FALSE)="","",VLOOKUP(B74,'26MY_ACCORD_DATA'!B:AS,21,FALSE))
B75: 08F20-30A-100C | C75: =VLOOKUP(B75,'26MY_ACCORD_DATA'!B:AS,4,FALSE) -> Emblème, noirs lustré arrière « H » mark | D75: =B75 -> 08F20-30A-100C | E75: =VLOOKUP(B75,'26MY_ACCORD_DATA'!B:AS,9,FALSE) -> 37 | F75: =VLOOKUP(B75,'26MY_ACCORD_DATA'!B:AS,10,FALSE) -> 62 | G75: =VLOOKUP(B75,'26MY_ACCORD_DATA'!B:AS,7,FALSE) -> 0.2 | H75: =VLOOKUP(B75,'26MY_ACCORD_DATA'!B:AS,11,FALSE) -> 92.4 | I75: =VLOOKUP(B75,'26MY_ACCORD_DATA'!B:AS,12,FALSE) -> 0 | J75: =VLOOKUP(B75,'26MY_ACCORD_DATA'!B:AS,13,FALSE) -> 0 | K75: =VLOOKUP(B75,'26MY_ACCORD_DATA'!B:AS,14,FALSE) -> • | L75: =VLOOKUP(B75,'26MY_ACCORD_DATA'!B:AS,15,FALSE) -> 0 | M75: =VLOOKUP(B75,'26MY_ACCORD_DATA'!B:AS,16,FALSE) -> • | N75: =VLOOKUP(B75,'26MY_ACCORD_DATA'!B:AS,17,FALSE) -> • | O75: =VLOOKUP(B75,'26MY_ACCORD_DATA'!B:AS,18,FALSE) -> 0 | P75: =VLOOKUP(B75,'26MY_ACCORD_DATA'!B:AS,19,FALSE) -> 0 | Q75: =IF(VLOOKUP(B75,'26MY_ACCORD_DATA'!B:AS,21,FALSE)="","",VLOOKUP(B75,'26MY_ACCORD_DATA'!B:AS,21,FALSE)) -> Logo H-Mark l'arrière.
B76: 08F20-30A-100D | C76: =VLOOKUP(B76,'26MY_ACCORD_DATA'!B:AS,4,FALSE) -> Emblème, noirs lustré arrière « Accord » | D76: =B76 -> 08F20-30A-100D | E76: =VLOOKUP(B76,'26MY_ACCORD_DATA'!B:AS,9,FALSE) -> 37 | F76: =VLOOKUP(B76,'26MY_ACCORD_DATA'!B:AS,10,FALSE) -> 62 | G76: =VLOOKUP(B76,'26MY_ACCORD_DATA'!B:AS,7,FALSE) -> 0.3 | H76: =VLOOKUP(B76,'26MY_ACCORD_DATA'!B:AS,11,FALSE) -> 107.6 | I76: =VLOOKUP(B76,'26MY_ACCORD_DATA'!B:AS,12,FALSE) -> 0 | J76: =VLOOKUP(B76,'26MY_ACCORD_DATA'!B:AS,13,FALSE) -> 0 | K76: =VLOOKUP(B76,'26MY_ACCORD_DATA'!B:AS,14,FALSE) -> • | L76: =VLOOKUP(B76,'26MY_ACCORD_DATA'!B:AS,15,FALSE) -> 0 | M76: =VLOOKUP(B76,'26MY_ACCORD_DATA'!B:AS,16,FALSE) -> N/A | N76: =VLOOKUP(B76,'26MY_ACCORD_DATA'!B:AS,17,FALSE) -> • | O76: =VLOOKUP(B76,'26MY_ACCORD_DATA'!B:AS,18,FALSE) -> 0 | P76: =VLOOKUP(B76,'26MY_ACCORD_DATA'!B:AS,19,FALSE) -> 0 | Q76: =IF(VLOOKUP(B76,'26MY_ACCORD_DATA'!B:AS,21,FALSE)="","",VLOOKUP(B76,'26MY_ACCORD_DATA'!B:AS,21,FALSE))
B77: 08F20-3A0-100C | C77: =VLOOKUP(B77,'26MY_ACCORD_DATA'!B:AS,4,FALSE) -> Emblème, noirs lustré « Touring » | D77: =B77 -> 08F20-3A0-100C | E77: =VLOOKUP(B77,'26MY_ACCORD_DATA'!B:AS,9,FALSE) -> 44 | F77: =VLOOKUP(B77,'26MY_ACCORD_DATA'!B:AS,10,FALSE) -> 73 | G77: =VLOOKUP(B77,'26MY_ACCORD_DATA'!B:AS,7,FALSE) -> 0.2 | H77: =VLOOKUP(B77,'26MY_ACCORD_DATA'!B:AS,11,FALSE) -> 103.4 | I77: =VLOOKUP(B77,'26MY_ACCORD_DATA'!B:AS,12,FALSE) -> 0 | J77: =VLOOKUP(B77,'26MY_ACCORD_DATA'!B:AS,13,FALSE) -> 0 | K77: =VLOOKUP(B77,'26MY_ACCORD_DATA'!B:AS,14,FALSE) -> N/A | L77: =VLOOKUP(B77,'26MY_ACCORD_DATA'!B:AS,15,FALSE) -> 0 | M77: =VLOOKUP(B77,'26MY_ACCORD_DATA'!B:AS,16,FALSE) -> N/A | N77: =VLOOKUP(B77,'26MY_ACCORD_DATA'!B:AS,17,FALSE) -> • | O77: =VLOOKUP(B77,'26MY_ACCORD_DATA'!B:AS,18,FALSE) -> 0 | P77: =VLOOKUP(B77,'26MY_ACCORD_DATA'!B:AS,19,FALSE) -> 0 | Q77: =IF(VLOOKUP(B77,'26MY_ACCORD_DATA'!B:AS,21,FALSE)="","",VLOOKUP(B77,'26MY_ACCORD_DATA'!B:AS,21,FALSE))
B78: 08F20-T20-100B | C78: =VLOOKUP(B78,'26MY_ACCORD_DATA'!B:AS,4,FALSE) -> Emblème, noirs lustré « Hybride » | D78: =B78 -> 08F20-T20-100B | E78: =VLOOKUP(B78,'26MY_ACCORD_DATA'!B:AS,9,FALSE) -> 46 | F78: =VLOOKUP(B78,'26MY_ACCORD_DATA'!B:AS,10,FALSE) -> 77 | G78: =VLOOKUP(B78,'26MY_ACCORD_DATA'!B:AS,7,FALSE) -> 0.2 | H78: =VLOOKUP(B78,'26MY_ACCORD_DATA'!B:AS,11,FALSE) -> 107.4 | I78: =VLOOKUP(B78,'26MY_ACCORD_DATA'!B:AS,12,FALSE) -> 0 | J78: =VLOOKUP(B78,'26MY_ACCORD_DATA'!B:AS,13,FALSE) -> 0 | K78: =VLOOKUP(B78,'26MY_ACCORD_DATA'!B:AS,14,FALSE) -> N/A | L78: =VLOOKUP(B78,'26MY_ACCORD_DATA'!B:AS,15,FALSE) -> 0 | M78: =VLOOKUP(B78,'26MY_ACCORD_DATA'!B:AS,16,FALSE) -> N/A | N78: =VLOOKUP(B78,'26MY_ACCORD_DATA'!B:AS,17,FALSE) -> • | O78: =VLOOKUP(B78,'26MY_ACCORD_DATA'!B:AS,18,FALSE) -> 0 | P78: =VLOOKUP(B78,'26MY_ACCORD_DATA'!B:AS,19,FALSE) -> 0 | Q78: =IF(VLOOKUP(B78,'26MY_ACCORD_DATA'!B:AS,21,FALSE)="","",VLOOKUP(B78,'26MY_ACCORD_DATA'!B:AS,21,FALSE))
B79: 08F59-30A-100 | C79: =VLOOKUP(B79,'26MY_ACCORD_DATA'!B:AS,4,FALSE) -> Emblème d’aile | D79: =B79 -> 08F59-30A-100 | E79: =VLOOKUP(B79,'26MY_ACCORD_DATA'!B:AS,9,FALSE) -> 94 | F79: =VLOOKUP(B79,'26MY_ACCORD_DATA'!B:AS,10,FALSE) -> 157 | G79: =VLOOKUP(B79,'26MY_ACCORD_DATA'!B:AS,7,FALSE) -> 0.2 | H79: =VLOOKUP(B79,'26MY_ACCORD_DATA'!B:AS,11,FALSE) -> 187.4 | I79: =VLOOKUP(B79,'26MY_ACCORD_DATA'!B:AS,12,FALSE) -> 0 | J79: =VLOOKUP(B79,'26MY_ACCORD_DATA'!B:AS,13,FALSE) -> 0 | K79: =VLOOKUP(B79,'26MY_ACCORD_DATA'!B:AS,14,FALSE) -> • | L79: =VLOOKUP(B79,'26MY_ACCORD_DATA'!B:AS,15,FALSE) -> 0 | M79: =VLOOKUP(B79,'26MY_ACCORD_DATA'!B:AS,16,FALSE) -> • | N79: =VLOOKUP(B79,'26MY_ACCORD_DATA'!B:AS,17,FALSE) -> • | O79: =VLOOKUP(B79,'26MY_ACCORD_DATA'!B:AS,18,FALSE) -> 0 | P79: =VLOOKUP(B79,'26MY_ACCORD_DATA'!B:AS,19,FALSE) -> 0 | Q79: =IF(VLOOKUP(B79,'26MY_ACCORD_DATA'!B:AS,21,FALSE)="","",VLOOKUP(B79,'26MY_ACCORD_DATA'!B:AS,21,FALSE))
B80: 08F20-30A-100B | C80: =VLOOKUP(B80,'26MY_ACCORD_DATA'!B:AS,4,FALSE) -> Emblème HPD | D80: =B80 -> 08F20-30A-100B | E80: =VLOOKUP(B80,'26MY_ACCORD_DATA'!B:AS,9,FALSE) -> 71 | F80: =VLOOKUP(B80,'26MY_ACCORD_DATA'!B:AS,10,FALSE) -> 118 | G80: =VLOOKUP(B80,'26MY_ACCORD_DATA'!B:AS,7,FALSE) -> 0.1 | H80: =VLOOKUP(B80,'26MY_ACCORD_DATA'!B:AS,11,FALSE) -> 133.2 | I80: =VLOOKUP(B80,'26MY_ACCORD_DATA'!B:AS,12,FALSE) -> 0 | J80: =VLOOKUP(B80,'26MY_ACCORD_DATA'!B:AS,13,FALSE) -> 0 | K80: =VLOOKUP(B80,'26MY_ACCORD_DATA'!B:AS,14,FALSE) -> • | L80: =VLOOKUP(B80,'26MY_ACCORD_DATA'!B:AS,15,FALSE) -> 0 | M80: =VLOOKUP(B80,'26MY_ACCORD_DATA'!B:AS,16,FALSE) -> • | N80: =VLOOKUP(B80,'26MY_ACCORD_DATA'!B:AS,17,FALSE) -> • | O80: =VLOOKUP(B80,'26MY_ACCORD_DATA'!B:AS,18,FALSE) -> 0 | P80: =VLOOKUP(B80,'26MY_ACCORD_DATA'!B:AS,19,FALSE) -> 0 | Q80: =IF(VLOOKUP(B80,'26MY_ACCORD_DATA'!B:AS,21,FALSE)="","",VLOOKUP(B80,'26MY_ACCORD_DATA'!B:AS,21,FALSE))
B81: 08P09-30A-300 | C81: =VLOOKUP(B81,'26MY_ACCORD_DATA'!B:AS,4,FALSE) -> Garde-boue arrière | D81: =B81 -> 08P09-30A-300 | E81: =VLOOKUP(B81,'26MY_ACCORD_DATA'!B:AS,9,FALSE) -> 50 | F81: =VLOOKUP(B81,'26MY_ACCORD_DATA'!B:AS,10,FALSE) -> 83 | G81: =VLOOKUP(B81,'26MY_ACCORD_DATA'!B:AS,7,FALSE) -> 0.4 | H81: =VLOOKUP(B81,'26MY_ACCORD_DATA'!B:AS,11,FALSE) -> 143.8 | I81: =VLOOKUP(B81,'26MY_ACCORD_DATA'!B:AS,12,FALSE) -> 0 | J81: =VLOOKUP(B81,'26MY_ACCORD_DATA'!B:AS,13,FALSE) -> 0 | K81: =VLOOKUP(B81,'26MY_ACCORD_DATA'!B:AS,14,FALSE) -> • | L81: =VLOOKUP(B81,'26MY_ACCORD_DATA'!B:AS,15,FALSE) -> 0 | M81: =VLOOKUP(B81,'26MY_ACCORD_DATA'!B:AS,16,FALSE) -> • | N81: =VLOOKUP(B81,'26MY_ACCORD_DATA'!B:AS,17,FALSE) -> • | O81: =VLOOKUP(B81,'26MY_ACCORD_DATA'!B:AS,18,FALSE) -> 0 | P81: =VLOOKUP(B81,'26MY_ACCORD_DATA'!B:AS,19,FALSE) -> 0 | Q81: =IF(VLOOKUP(B81,'26MY_ACCORD_DATA'!B:AS,21,FALSE)="","",VLOOKUP(B81,'26MY_ACCORD_DATA'!B:AS,21,FALSE))
... B85: 08P20-30A-100A | C85: =VLOOKUP(B85,'26MY_ACCORD_DATA'!B:AS,4,FALSE) -> Pellicule pour rebord de portière | D85: =B85 -> 08P20-30A-100A | E85: =VLOOKUP(B85,'26MY_ACCORD_DATA'!B:AS,9,FALSE) -> 71 | F85: =VLOOKUP(B85,'26MY_ACCORD_DATA'!B:AS,10,FALSE) -> 118 | G85: =VLOOKUP(B85,'26MY_ACCORD_DATA'!B:AS,7,FALSE) -> 0.5 | H85: =VLOOKUP(B85,'26MY_ACCORD_DATA'!B:AS,11,FALSE) -> 194 | I85: =VLOOKUP(B85,'26MY_ACCORD_DATA'!B:AS,12,FALSE) -> 0 | J85: =VLOOKUP(B85,'26MY_ACCORD_DATA'!B:AS,13,FALSE) -> 0 | K85: =VLOOKUP(B85,'26MY_ACCORD_DATA'!B:AS,14,FALSE) -> • | L85: =VLOOKUP(B85,'26MY_ACCORD_DATA'!B:AS,15,FALSE) -> 0 | M85: =VLOOKUP(B85,'26MY_ACCORD_DATA'!B:AS,16,FALSE) -> • | N85: =VLOOKUP(B85,'26MY_ACCORD_DATA'!B:AS,17,FALSE) -> • | O85: =VLOOKUP(B85,'26MY_ACCORD_DATA'!B:AS,18,FALSE) -> 0 | P85: =VLOOKUP(B85,'26MY_ACCORD_DATA'!B:AS,19,FALSE) -> 0 | Q85: =IF(VLOOKUP(B85,'26MY_ACCORD_DATA'!B:AS,21,FALSE)="","",VLOOKUP(B85,'26MY_ACCORD_DATA'!B:AS,21,FALSE)) -> Ne peut être installé simultanément avec protecteurs de bordure de porte.
B86: 08F02-30A-XXX | C86: =VLOOKUP(B86,'26MY_ACCORD_DATA'!B:AS,4,FALSE) -> Déflecteur arrière de coffre
B87: 08F10-30A-110 | C87: =VLOOKUP(B87,'26MY_ACCORD_DATA'!B:AS,4,FALSE) -> Blanc platine nacré (NH-883P) | D87: =B87 -> 08F10-30A-110 | E87: =VLOOKUP(B87,'26MY_ACCORD_DATA'!B:AS,9,FALSE) -> 386 | F87: =VLOOKUP(B87,'26MY_ACCORD_DATA'!B:AS,10,FALSE) -> 643 | G87: =VLOOKUP(B87,'26MY_ACCORD_DATA'!B:AS,7,FALSE) -> 0.6 | H87: =VLOOKUP(B87,'26MY_ACCORD_DATA'!B:AS,11,FALSE) -> 734.2 | I87: =VLOOKUP(B87,'26MY_ACCORD_DATA'!B:AS,12,FALSE) -> 0 | J87: =VLOOKUP(B87,'26MY_ACCORD_DATA'!B:AS,13,FALSE) -> 0 | K87: =VLOOKUP(B87,'26MY_ACCORD_DATA'!B:AS,14,FALSE) -> • | L87: =VLOOKUP(B87,'26MY_ACCORD_DATA'!B:AS,15,FALSE) -> 0 | M87: =VLOOKUP(B87,'26MY_ACCORD_DATA'!B:AS,16,FALSE) -> S | N87: =VLOOKUP(B87,'26MY_ACCORD_DATA'!B:AS,17,FALSE) -> • | O87: =VLOOKUP(B87,'26MY_ACCORD_DATA'!B:AS,18,FALSE) -> 0 | P87: =VLOOKUP(B87,'26MY_ACCORD_DATA'!B:AS,19,FALSE) -> 0 | Q87: =IF(VLOOKUP(B87,'26MY_ACCORD_DATA'!B:AS,21,FALSE)="","",VLOOKUP(B87,'26MY_ACCORD_DATA'!B:AS,21,FALSE))
B88: 08F10-30A-140 | C88: =VLOOKUP(B88,'26MY_ACCORD_DATA'!B:AS,4,FALSE) -> Gris météore nacré (NH-904M) | D88: =B88 -> 08F10-30A-140 | E88: =VLOOKUP(B88,'26MY_ACCORD_DATA'!B:AS,9,FALSE) -> 386 | F88: =VLOOKUP(B88,'26MY_ACCORD_DATA'!B:AS,10,FALSE) -> 643 | G88: =VLOOKUP(B88,'26MY_ACCORD_DATA'!B:AS,7,FALSE) -> 0.6 | H88: =VLOOKUP(B88,'26MY_ACCORD_DATA'!B:AS,11,FALSE) -> 734.2 | I88: =VLOOKUP(B88,'26MY_ACCORD_DATA'!B:AS,12,FALSE) -> 0 | J88: =VLOOKUP(B88,'26MY_ACCORD_DATA'!B:AS,13,FALSE) -> 0 | K88: =VLOOKUP(B88,'26MY_ACCORD_DATA'!B:AS,14,FALSE) -> N/A | L88: =VLOOKUP(B88,'26MY_ACCORD_DATA'!B:AS,15,FALSE) -> 0 | M88: =VLOOKUP(B88,'26MY_ACCORD_DATA'!B:AS,16,FALSE) -> S | N88: =VLOOKUP(B88,'26MY_ACCORD_DATA'!B:AS,17,FALSE) -> N/A | O88: =VLOOKUP(B88,'26MY_ACCORD_DATA'!B:AS,18,FALSE) -> 0 | P88: =VLOOKUP(B88,'26MY_ACCORD_DATA'!B:AS,19,FALSE) -> 0
B89: 08F10-30A-150 | C89: =VLOOKUP(B89,'26MY_ACCORD_DATA'!B:AS,4,FALSE) -> Gris urbain nacré (NH-912P) | D89: =B89 -> 08F10-30A-150 | E89: =VLOOKUP(B89,'26MY_ACCORD_DATA'!B:AS,9,FALSE) -> 386 | F89: =VLOOKUP(B89,'26MY_ACCORD_DATA'!B:AS,10,FALSE) -> 643 | G89: =VLOOKUP(B89,'26MY_ACCORD_DATA'!B:AS,7,FALSE) -> 0.6 | H89: =VLOOKUP(B89,'26MY_ACCORD_DATA'!B:AS,11,FALSE) -> 734.2 | I89: =VLOOKUP(B89,'26MY_ACCORD_DATA'!B:AS,12,FALSE) -> 0 | J89: =VLOOKUP(B89,'26MY_ACCORD_DATA'!B:AS,13,FALSE) -> 0 | K89: =VLOOKUP(B89,'26MY_ACCORD_DATA'!B:AS,14,FALSE) -> N/A | L89: =VLOOKUP(B89,'26MY_ACCORD_DATA'!B:AS,15,FALSE) -> 0 | M89: =VLOOKUP(B89,'26MY_ACCORD_DATA'!B:AS,16,FALSE) -> S | N89: =VLOOKUP(B89,'26MY_ACCORD_DATA'!B:AS,17,FALSE) -> • | O89: =VLOOKUP(B89,'26MY_ACCORD_DATA'!B:AS,18,FALSE) -> 0 | P89: =VLOOKUP(B89,'26MY_ACCORD_DATA'!B:AS,19,FALSE) -> 0
B90: 08F10-30A-170 | C90: =VLOOKUP(B90,'26MY_ACCORD_DATA'!B:AS,4,FALSE) -> Noir cristal nacré (NH-731P) | D90: =B90 -> 08F10-30A-170 | E90: =VLOOKUP(B90,'26MY_ACCORD_DATA'!B:AS,9,FALSE) -> 386 | F90: =VLOOKUP(B90,'26MY_ACCORD_DATA'!B:AS,10,FALSE) -> 643 | G90: =VLOOKUP(B90,'26MY_ACCORD_DATA'!B:AS,7,FALSE) -> 0.6 | H90: =VLOOKUP(B90,'26MY_ACCORD_DATA'!B:AS,11,FALSE) -> 734.2 | I90: =VLOOKUP(B90,'26MY_ACCORD_DATA'!B:AS,12,FALSE) -> 0 | J90: =VLOOKUP(B90,'26MY_ACCORD_DATA'!B:AS,13,FALSE) -> 0 | K90: =VLOOKUP(B90,'26MY_ACCORD_DATA'!B:AS,14,FALSE) -> • | L90: =VLOOKUP(B90,'26MY_ACCORD_DATA'!B:AS,15,FALSE) -> 0 | M90: =VLOOKUP(B90,'26MY_ACCORD_DATA'!B:AS,16,FALSE) -> S | N90: =VLOOKUP(B90,'26MY_ACCORD_DATA'!B:AS,17,FALSE) -> • | O90: =VLOOKUP(B90,'26MY_ACCORD_DATA'!B:AS,18,FALSE) -> 0 | P90: =VLOOKUP(B90,'26MY_ACCORD_DATA'!B:AS,19,FALSE) -> 0
B91: 08F10-30A-1A0 | C91: =VLOOKUP(B91,'26MY_ACCORD_DATA'!B:AS,4,FALSE) -> Radiant rouge métallisé (R-569M) | D91: =B91 -> 08F10-30A-1A0 | E91: =VLOOKUP(B91,'26MY_ACCORD_DATA'!B:AS,9,FALSE) -> 386 | F91: =VLOOKUP(B91,'26MY_ACCORD_DATA'!B:AS,10,FALSE) -> 643 | G91: =VLOOKUP(B91,'26MY_ACCORD_DATA'!B:AS,7,FALSE) -> 0.6 | H91: =VLOOKUP(B91,'26MY_ACCORD_DATA'!B:AS,11,FALSE) -> 734.2 | I91: =VLOOKUP(B91,'26MY_ACCORD_DATA'!B:AS,12,FALSE) -> 0 | J91: =VLOOKUP(B91,'26MY_ACCORD_DATA'!B:AS,13,FALSE) -> 0 | K91: =VLOOKUP(B91,'26MY_ACCORD_DATA'!B:AS,14,FALSE) -> N/A | L91: =VLOOKUP(B91,'26MY_ACCORD_DATA'!B:AS,15,FALSE) -> 0 | M91: =VLOOKUP(B91,'26MY_ACCORD_DATA'!B:AS,16,FALSE) -> S | N91: =VLOOKUP(B91,'26MY_ACCORD_DATA'!B:AS,17,FALSE) -> • | O91: =VLOOKUP(B91,'26MY_ACCORD_DATA'!B:AS,18,FALSE) -> 0 | P91: =VLOOKUP(B91,'26MY_ACCORD_DATA'!B:AS,19,FALSE) -> 0
B92: 08F10-30A-1D0 | C92: =VLOOKUP(B92,'26MY_ACCORD_DATA'!B:AS,4,FALSE) -> Bleu rivière canyon métallisé (B-640M) | D92: =B92 -> 08F10-30A-1D0 | E92: =VLOOKUP(B92,'26MY_ACCORD_DATA'!B:AS,9,FALSE) -> 386 | F92: =VLOOKUP(B92,'26MY_ACCORD_DATA'!B:AS,10,FALSE) -> 643 | G92: =VLOOKUP(B92,'26MY_ACCORD_DATA'!B:AS,7,FALSE) -> 0.6 | H92: =VLOOKUP(B92,'26MY_ACCORD_DATA'!B:AS,11,FALSE) -> 734.2 | I92: =VLOOKUP(B92,'26MY_ACCORD_DATA'!B:AS,12,FALSE) -> 0 | J92: =VLOOKUP(B92,'26MY_ACCORD_DATA'!B:AS,13,FALSE) -> 0 | K92: =VLOOKUP(B92,'26MY_ACCORD_DATA'!B:AS,14,FALSE) -> N/A | L92: =VLOOKUP(B92,'26MY_ACCORD_DATA'!B:AS,15,FALSE) -> 0 | M92: =VLOOKUP(B92,'26MY_ACCORD_DATA'!B:AS,16,FALSE) -> S | N92: =VLOOKUP(B92,'26MY_ACCORD_DATA'!B:AS,17,FALSE) -> • | O92: =VLOOKUP(B92,'26MY_ACCORD_DATA'!B:AS,18,FALSE) -> 0 | P92: =VLOOKUP(B92,'26MY_ACCORD_DATA'!B:AS,19,FALSE) -> 0
B93: 08F10-30A-1C0 | C93: =VLOOKUP(B93,'26MY_ACCORD_DATA'!B:AS,4,FALSE) -> Nuit paisible fini nacré (B-575P) | D93: =B93 -> 08F10-30A-1C0 | E93: =VLOOKUP(B93,'26MY_ACCORD_DATA'!B:AS,9,FALSE) -> 386 | F93: =VLOOKUP(B93,'26MY_ACCORD_DATA'!B:AS,10,FALSE) -> 643 | G93: =VLOOKUP(B93,'26MY_ACCORD_DATA'!B:AS,7,FALSE) -> 0.6 | H93: =VLOOKUP(B93,'26MY_ACCORD_DATA'!B:AS,11,FALSE) -> 734.2 | I93: =VLOOKUP(B93,'26MY_ACCORD_DATA'!B:AS,12,FALSE) -> 0 | J93: =VLOOKUP(B93,'26MY_ACCORD_DATA'!B:AS,13,FALSE) -> 0 | K93: =VLOOKUP(B93,'26MY_ACCORD_DATA'!B:AS,14,FALSE) -> N/A | L93: =VLOOKUP(B93,'26MY_ACCORD_DATA'!B:AS,15,FALSE) -> 0 | M93: =VLOOKUP(B93,'26MY_ACCORD_DATA'!B:AS,16,FALSE) -> S | N93: =VLOOKUP(B93,'26MY_ACCORD_DATA'!B:AS,17,FALSE) -> N/A | O93: =VLOOKUP(B93,'26MY_ACCORD_DATA'!B:AS,18,FALSE) -> 0 | P93: =VLOOKUP(B93,'26MY_ACCORD_DATA'!B:AS,19,FALSE) -> 0
B94: 08F10-30A-1H0 | C94: =VLOOKUP(B94,'26MY_ACCORD_DATA'!B:AS,4,FALSE) -> Refl et solaire argent métallisé (NH-932M) | D94: =B94 -> 08F10-30A-1H0 | E94: =VLOOKUP(B94,'26MY_ACCORD_DATA'!B:AS,9,FALSE) -> 386 | F94: =VLOOKUP(B94,'26MY_ACCORD_DATA'!B:AS,10,FALSE) -> 643 | G94: =VLOOKUP(B94,'26MY_ACCORD_DATA'!B:AS,7,FALSE) -> 0.6 | H94: =VLOOKUP(B94,'26MY_ACCORD_DATA'!B:AS,11,FALSE) -> 734.2 | I94: =VLOOKUP(B94,'26MY_ACCORD_DATA'!B:AS,12,FALSE) -> 0 | J94: =VLOOKUP(B94,'26MY_ACCORD_DATA'!B:AS,13,FALSE) -> 0 | K94: =VLOOKUP(B94,'26MY_ACCORD_DATA'!B:AS,14,FALSE) -> • | L94: =VLOOKUP(B94,'26MY_ACCORD_DATA'!B:AS,15,FALSE) -> 0 | M94: =VLOOKUP(B94,'26MY_ACCORD_DATA'!B:AS,16,FALSE) -> S | N94: =VLOOKUP(B94,'26MY_ACCORD_DATA'!B:AS,17,FALSE) -> • | O94: =VLOOKUP(B94,'26MY_ACCORD_DATA'!B:AS,18,FALSE) -> 0 | P94: =VLOOKUP(B94,'26MY_ACCORD_DATA'!B:AS,19,FALSE) -> 0
B95: 08P05-30A-XXXX | C95: =VLOOKUP(B95,'26MY_ACCORD_DATA'!B:AS,4,FALSE) -> Moulure latérale
B96: 08P05-30A-110 | C96: =VLOOKUP(B96,'26MY_ACCORD_DATA'!B:AS,4,FALSE) -> Blanc platine nacré (NH-883P) | D96: =B96 -> 08P05-30A-110 | E96: =VLOOKUP(B96,'26MY_ACCORD_DATA'!B:AS,9,FALSE) -> 232 | F96: =VLOOKUP(B96,'26MY_ACCORD_DATA'!B:AS,10,FALSE) -> 387 | G96: =VLOOKUP(B96,'26MY_ACCORD_DATA'!B:AS,7,FALSE) -> 0.4 | H96: =VLOOKUP(B96,'26MY_ACCORD_DATA'!B:AS,11,FALSE) -> 447.8 | I96: =VLOOKUP(B96,'26MY_ACCORD_DATA'!B:AS,12,FALSE) -> 0 | J96: =VLOOKUP(B96,'26MY_ACCORD_DATA'!B:AS,13,FALSE) -> 0 | K96: =VLOOKUP(B96,'26MY_ACCORD_DATA'!B:AS,14,FALSE) -> • | L96: =VLOOKUP(B96,'26MY_ACCORD_DATA'!B:AS,15,FALSE) -> 0 | M96: =VLOOKUP(B96,'26MY_ACCORD_DATA'!B:AS,16,FALSE) -> • | N96: =VLOOKUP(B96,'26MY_ACCORD_DATA'!B:AS,17,FALSE) -> • | O96: =VLOOKUP(B96,'26MY_ACCORD_DATA'!B:AS,18,FALSE) -> 0 | P96: =VLOOKUP(B96,'26MY_ACCORD_DATA'!B:AS,19,FALSE) -> 0 | Q96: =IF(VLOOKUP(B96,'26MY_ACCORD_DATA'!B:AS,21,FALSE)="","",VLOOKUP(B96,'26MY_ACCORD_DATA'!B:AS,21,FALSE))
B97: 08P05-30A-140 | C97: =VLOOKUP(B97,'26MY_ACCORD_DATA'!B:AS,4,FALSE) -> Gris météore nacré (NH-904M) | D97: =B97 -> 08P05-30A-140 | E97: =VLOOKUP(B97,'26MY_ACCORD_DATA'!B:AS,9,FALSE) -> 232 | F97: =VLOOKUP(B97,'26MY_ACCORD_DATA'!B:AS,10,FALSE) -> 387 | G97: =VLOOKUP(B97,'26MY_ACCORD_DATA'!B:AS,7,FALSE) -> 0.4 | H97: =VLOOKUP(B97,'26MY_ACCORD_DATA'!B:AS,11,FALSE) -> 447.8 | I97: =VLOOKUP(B97,'26MY_ACCORD_DATA'!B:AS,12,FALSE) -> 0 | J97: =VLOOKUP(B97,'26MY_ACCORD_DATA'!B:AS,13,FALSE) -> 0 | K97: =VLOOKUP(B97,'26MY_ACCORD_DATA'!B:AS,14,FALSE) -> N/A | L97: =VLOOKUP(B97,'26MY_ACCORD_DATA'!B:AS,15,FALSE) -> 0 | M97: =VLOOKUP(B97,'26MY_ACCORD_DATA'!B:AS,16,FALSE) -> • | N97: =VLOOKUP(B97,'26MY_ACCORD_DATA'!B:AS,17,FALSE) -> N/A | O97: =VLOOKUP(B97,'26MY_ACCORD_DATA'!B:AS,18,FALSE) -> 0 | P97: =VLOOKUP(B97,'26MY_ACCORD_DATA'!B:AS,19,FALSE) -> 0
B98: 08P05-30A-150 | C98: =VLOOKUP(B98,'26MY_ACCORD_DATA'!B:AS,4,FALSE) -> Gris urbain nacré (NH-912P) | D98: =B98 -> 08P05-30A-150 | E98: =VLOOKUP(B98,'26MY_ACCORD_DATA'!B:AS,9,FALSE) -> 232 | F98: =VLOOKUP(B98,'26MY_ACCORD_DATA'!B:AS,10,FALSE) -> 387 | G98: =VLOOKUP(B98,'26MY_ACCORD_DATA'!B:AS,7,FALSE) -> 0.4 | H98: =VLOOKUP(B98,'26MY_ACCORD_DATA'!B:AS,11,FALSE) -> 447.8 | I98: =VLOOKUP(B98,'26MY_ACCORD_DATA'!B:AS,12,FALSE) -> 0 | J98: =VLOOKUP(B98,'26MY_ACCORD_DATA'!B:AS,13,FALSE) -> 0 | K98: =VLOOKUP(B98,'26MY_ACCORD_DATA'!B:AS,14,FALSE) -> N/A | L98: =VLOOKUP(B98,'26MY_ACCORD_DATA'!B:AS,15,FALSE) -> 0 | M98: =VLOOKUP(B98,'26MY_ACCORD_DATA'!B:AS,16,FALSE) -> N/A | N98: =VLOOKUP(B98,'26MY_ACCORD_DATA'!B:AS,17,FALSE) -> • | O98: =VLOOKUP(B98,'26MY_ACCORD_DATA'!B:AS,18,FALSE) -> 0 | P98: =VLOOKUP(B98,'26MY_ACCORD_DATA'!B:AS,19,FALSE) -> 0
B99: 08P05-30A-170 | C99: =VLOOKUP(B99,'26MY_ACCORD_DATA'!B:AS,4,FALSE) -> Noir cristal nacré (NH-731P) | D99: =B99 -> 08P05-30A-170 | E99: =VLOOKUP(B99,'26MY_ACCORD_DATA'!B:AS,9,FALSE) -> 232 | F99: =VLOOKUP(B99,'26MY_ACCORD_DATA'!B:AS,10,FALSE) -> 387 | G99: =VLOOKUP(B99,'26MY_ACCORD_DATA'!B:AS,7,FALSE) -> 0.4 | H99: =VLOOKUP(B99,'26MY_ACCORD_DATA'!B:AS,11,FALSE) -> 447.8 | I99: =VLOOKUP(B99,'26MY_ACCORD_DATA'!B:AS,12,FALSE) -> 0 | J99: =VLOOKUP(B99,'26MY_ACCORD_DATA'!B:AS,13,FALSE) -> 0 | K99: =VLOOKUP(B99,'26MY_ACCORD_DATA'!B:AS,14,FALSE) -> • | L99: =VLOOKUP(B99,'26MY_ACCORD_DATA'!B:AS,15,FALSE) -> 0 | M99: =VLOOKUP(B99,'26MY_ACCORD_DATA'!B:AS,16,FALSE) -> • | N99: =VLOOKUP(B99,'26MY_ACCORD_DATA'!B:AS,17,FALSE) -> • | O99: =VLOOKUP(B99,'26MY_ACCORD_DATA'!B:AS,18,FALSE) -> 0 | P99: =VLOOKUP(B99,'26MY_ACCORD_DATA'!B:AS,19,FALSE) -> 0
B100: 08P05-30A-1A0 | C100: =VLOOKUP(B100,'26MY_ACCORD_DATA'!B:AS,4,FALSE) -> Radiant rouge métallisé (R-569M) | D100: =B100 -> 08P05-30A-1A0 | E100: =VLOOKUP(B100,'26MY_ACCORD_DATA'!B:AS,9,FALSE) -> 232 | F100: =VLOOKUP(B100,'26MY_ACCORD_DATA'!B:AS,10,FALSE) -> 387 | G100: =VLOOKUP(B100,'26MY_ACCORD_DATA'!B:AS,7,FALSE) -> 0.4 | H100: =VLOOKUP(B100,'26MY_ACCORD_DATA'!B:AS,11,FALSE) -> 447.8 | I100: =VLOOKUP(B100,'26MY_ACCORD_DATA'!B:AS,12,FALSE) -> 0 | J100: =VLOOKUP(B100,'26MY_ACCORD_DATA'!B:AS,13,FALSE) -> 0 | K100: =VLOOKUP(B100,'26MY_ACCORD_DATA'!B:AS,14,FALSE) -> N/A | L100: =VLOOKUP(B100,'26MY_ACCORD_DATA'!B:AS,15,FALSE) -> 0 | M100: =VLOOKUP(B100,'26MY_ACCORD_DATA'!B:AS,16,FALSE) -> • | N100: =VLOOKUP(B100,'26MY_ACCORD_DATA'!B:AS,17,FALSE) -> • | O100: =VLOOKUP(B100,'26MY_ACCORD_DATA'!B:AS,18,FALSE) -> 0 | P100: =VLOOKUP(B100,'26MY_ACCORD_DATA'!B:AS,19,FALSE) -> 0
B101: 08P05-30A-1D0 | C101: =VLOOKUP(B101,'26MY_ACCORD_DATA'!B:AS,4,FALSE) -> Bleu rivière canyon métallisé (B-640M) | D101: =B101 -> 08P05-30A-1D0 | E101: =VLOOKUP(B101,'26MY_ACCORD_DATA'!B:AS,9,FALSE) -> 232 | F101: =VLOOKUP(B101,'26MY_ACCORD_DATA'!B:AS,10,FALSE) -> 387 | G101: =VLOOKUP(B101,'26MY_ACCORD_DATA'!B:AS,7,FALSE) -> 0.4 | H101: =VLOOKUP(B101,'26MY_ACCORD_DATA'!B:AS,11,FALSE) -> 447.8 | I101: =VLOOKUP(B101,'26MY_ACCORD_DATA'!B:AS,12,FALSE) -> 0 | J101: =VLOOKUP(B101,'26MY_ACCORD_DATA'!B:AS,13,FALSE) -> 0 | K101: =VLOOKUP(B101,'26MY_ACCORD_DATA'!B:AS,14,FALSE) -> N/A | L101: =VLOOKUP(B101,'26MY_ACCORD_DATA'!B:AS,15,FALSE) -> 0 | M101: =VLOOKUP(B101,'26MY_ACCORD_DATA'!B:AS,16,FALSE) -> N/A | N101: =VLOOKUP(B101,'26MY_ACCORD_DATA'!B:AS,17,FALSE) -> • | O101: =VLOOKUP(B101,'26MY_ACCORD_DATA'!B:AS,18,FALSE) -> 0 | P101: =VLOOKUP(B101,'26MY_ACCORD_DATA'!B:AS,19,FALSE) -> 0
B102: 08P05-30A-1C0 | C102: =VLOOKUP(B102,'26MY_ACCORD_DATA'!B:AS,4,FALSE) -> Nuit paisible fini nacré (B-575P) | D102: =B102 -> 08P05-30A-1C0 | E102: =VLOOKUP(B102,'26MY_ACCORD_DATA'!B:AS,9,FALSE) -> 232 | F102: =VLOOKUP(B102,'26MY_ACCORD_DATA'!B:AS,10,FALSE) -> 387 | G102: =VLOOKUP(B102,'26MY_ACCORD_DATA'!B:AS,7,FALSE) -> 0.4 | H102: =VLOOKUP(B102,'26MY_ACCORD_DATA'!B:AS,11,FALSE) -> 447.8 | I102: =VLOOKUP(B102,'26MY_ACCORD_DATA'!B:AS,12,FALSE) -> 0 | J102: =VLOOKUP(B102,'26MY_ACCORD_DATA'!B:AS,13,FALSE) -> 0 | K102: =VLOOKUP(B102,'26MY_ACCORD_DATA'!B:AS,14,FALSE) -> N/A | L102: =VLOOKUP(B102,'26MY_ACCORD_DATA'!B:AS,15,FALSE) -> 0 | M102: =VLOOKUP(B102,'26MY_ACCORD_DATA'!B:AS,16,FALSE) -> • | N102: =VLOOKUP(B102,'26MY_ACCORD_DATA'!B:AS,17,FALSE) -> N/A | O102: =VLOOKUP(B102,'26MY_ACCORD_DATA'!B:AS,18,FALSE) -> 0 | P102: =VLOOKUP(B102,'26MY_ACCORD_DATA'!B:AS,19,FALSE) -> 0
B103: 08P05-30A-1H0 | C103: =VLOOKUP(B103,'26MY_ACCORD_DATA'!B:AS,4,FALSE) -> Refl et solaire argent métallisé (NH-932M) | D103: =B103 -> 08P05-30A-1H0 | E103: =VLOOKUP(B103,'26MY_ACCORD_DATA'!B:AS,9,FALSE) -> 232 | F103: =VLOOKUP(B103,'26MY_ACCORD_DATA'!B:AS,10,FALSE) -> 387 | G103: =VLOOKUP(B103,'26MY_ACCORD_DATA'!B:AS,7,FALSE) -> 0.4 | H103: =VLOOKUP(B103,'26MY_ACCORD_DATA'!B:AS,11,FALSE) -> 447.8 | I103: =VLOOKUP(B103,'26MY_ACCORD_DATA'!B:AS,12,FALSE) -> 0 | J103: =VLOOKUP(B103,'26MY_ACCORD_DATA'!B:AS,13,FALSE) -> 0 | K103: =VLOOKUP(B103,'26MY_ACCORD_DATA'!B:AS,14,FALSE) -> • | L103: =VLOOKUP(B103,'26MY_ACCORD_DATA'!B:AS,15,FALSE) -> 0 | M103: =VLOOKUP(B103,'26MY_ACCORD_DATA'!B:AS,16,FALSE) -> • | N103: =VLOOKUP(B103,'26MY_ACCORD_DATA'!B:AS,17,FALSE) -> • | O103: =VLOOKUP(B103,'26MY_ACCORD_DATA'!B:AS,18,FALSE) -> 0 | P103: =VLOOKUP(B103,'26MY_ACCORD_DATA'!B:AS,19,FALSE) -> 0
B104: 08P20-30A-XXXX | C104: =VLOOKUP(B104,'26MY_ACCORD_DATA'!B:AS,4,FALSE) -> Déflecteur de bas de caisse avant
B105: 08P20-30A-110 | C105: =VLOOKUP(B105,'26MY_ACCORD_DATA'!B:AS,4,FALSE) -> Blanc platine nacré (NH-883P) | D105: =B105 -> 08P20-30A-110 | E105: =VLOOKUP(B105,'26MY_ACCORD_DATA'!B:AS,9,FALSE) -> 176 | F105: =VLOOKUP(B105,'26MY_ACCORD_DATA'!B:AS,10,FALSE) -> 293 | G105: =VLOOKUP(B105,'26MY_ACCORD_DATA'!B:AS,7,FALSE) -> 0.4 | H105: =VLOOKUP(B105,'26MY_ACCORD_DATA'!B:AS,11,FALSE) -> 353.8 | I105: =VLOOKUP(B105,'26MY_ACCORD_DATA'!B:AS,12,FALSE) -> 0 | J105: =VLOOKUP(B105,'26MY_ACCORD_DATA'!B:AS,13,FALSE) -> 0 | K105: =VLOOKUP(B105,'26MY_ACCORD_DATA'!B:AS,14,FALSE) -> • | L105: =VLOOKUP(B105,'26MY_ACCORD_DATA'!B:AS,15,FALSE) -> 0 | M105: =VLOOKUP(B105,'26MY_ACCORD_DATA'!B:AS,16,FALSE) -> • | N105: =VLOOKUP(B105,'26MY_ACCORD_DATA'!B:AS,17,FALSE) -> • | O105: =VLOOKUP(B105,'26MY_ACCORD_DATA'!B:AS,18,FALSE) -> 0 | P105: =VLOOKUP(B105,'26MY_ACCORD_DATA'!B:AS,19,FALSE) -> 0 | Q105: =IF(VLOOKUP(B105,'26MY_ACCORD_DATA'!B:AS,21,FALSE)="","",VLOOKUP(B105,'26MY_ACCORD_DATA'!B:AS,21,FALSE))
B106: 08P20-30A-140 | C106: =VLOOKUP(B106,'26MY_ACCORD_DATA'!B:AS,4,FALSE) -> Gris météore nacré (NH-904M) | D106: =B106 -> 08P20-30A-140 | E106: =VLOOKUP(B106,'26MY_ACCORD_DATA'!B:AS,9,FALSE) -> 176 | F106: =VLOOKUP(B106,'26MY_ACCORD_DATA'!B:AS,10,FALSE) -> 293 | G106: =VLOOKUP(B106,'26MY_ACCORD_DATA'!B:AS,7,FALSE) -> 0.4 | H106: =VLOOKUP(B106,'26MY_ACCORD_DATA'!B:AS,11,FALSE) -> 353.8 | I106: =VLOOKUP(B106,'26MY_ACCORD_DATA'!B:AS,12,FALSE) -> 0 | J106: =VLOOKUP(B106,'26MY_ACCORD_DATA'!B:AS,13,FALSE) -> 0 | K106: =VLOOKUP(B106,'26MY_ACCORD_DATA'!B:AS,14,FALSE) -> N/A | L106: =VLOOKUP(B106,'26MY_ACCORD_DATA'!B:AS,15,FALSE) -> 0 | M106: =VLOOKUP(B106,'26MY_ACCORD_DATA'!B:AS,16,FALSE) -> • | N106: =VLOOKUP(B106,'26MY_ACCORD_DATA'!B:AS,17,FALSE) -> N/A | O106: =VLOOKUP(B106,'26MY_ACCORD_DATA'!B:AS,18,FALSE) -> 0 | P106: =VLOOKUP(B106,'26MY_ACCORD_DATA'!B:AS,19,FALSE) -> 0
B107: 08P20-30A-150 | C107: =VLOOKUP(B107,'26MY_ACCORD_DATA'!B:AS,4,FALSE) -> Gris urbain nacré (NH-912P) | D107: =B107 -> 08P20-30A-150 | E107: =VLOOKUP(B107,'26MY_ACCORD_DATA'!B:AS,9,FALSE) -> 176 | F107: =VLOOKUP(B107,'26MY_ACCORD_DATA'!B:AS,10,FALSE) -> 293 | G107: =VLOOKUP(B107,'26MY_ACCORD_DATA'!B:AS,7,FALSE) -> 0.4 | H107: =VLOOKUP(B107,'26MY_ACCORD_DATA'!B:AS,11,FALSE) -> 353.8 | I107: =VLOOKUP(B107,'26MY_ACCORD_DATA'!B:AS,12,FALSE) -> 0 | J107: =VLOOKUP(B107,'26MY_ACCORD_DATA'!B:AS,13,FALSE) -> 0 | K107: =VLOOKUP(B107,'26MY_ACCORD_DATA'!B:AS,14,FALSE) -> N/A | L107: =VLOOKUP(B107,'26MY_ACCORD_DATA'!B:AS,15,FALSE) -> 0 | M107: =VLOOKUP(B107,'26MY_ACCORD_DATA'!B:AS,16,FALSE) -> N/A | N107: =VLOOKUP(B107,'26MY_ACCORD_DATA'!B:AS,17,FALSE) -> • | O107: =VLOOKUP(B107,'26MY_ACCORD_DATA'!B:AS,18,FALSE) -> 0 | P107: =VLOOKUP(B107,'26MY_ACCORD_DATA'!B:AS,19,FALSE) -> 0
B108: 08P20-30A-170 | C108: =VLOOKUP(B108,'26MY_ACCORD_DATA'!B:AS,4,FALSE) -> Noir cristal nacré (NH-731P) | D108: =B108 -> 08P20-30A-170 | E108: =VLOOKUP(B108,'26MY_ACCORD_DATA'!B:AS,9,FALSE) -> 176 | F108: =VLOOKUP(B108,'26MY_ACCORD_DATA'!B:AS,10,FALSE) -> 293 | G108: =VLOOKUP(B108,'26MY_ACCORD_DATA'!B:AS,7,FALSE) -> 0.4 | H108: =VLOOKUP(B108,'26MY_ACCORD_DATA'!B:AS,11,FALSE) -> 353.8 | I108: =VLOOKUP(B108,'26MY_ACCORD_DATA'!B:AS,12,FALSE) -> 0 | J108: =VLOOKUP(B108,'26MY_ACCORD_DATA'!B:AS,13,FALSE) -> 0 | K108: =VLOOKUP(B108,'26MY_ACCORD_DATA'!B:AS,14,FALSE) -> • | L108: =VLOOKUP(B108,'26MY_ACCORD_DATA'!B:AS,15,FALSE) -> 0 | M108: =VLOOKUP(B108,'26MY_ACCORD_DATA'!B:AS,16,FALSE) -> • | N108: =VLOOKUP(B108,'26MY_ACCORD_DATA'!B:AS,17,FALSE) -> • | O108: =VLOOKUP(B108,'26MY_ACCORD_DATA'!B:AS,18,FALSE) -> 0 | P108: =VLOOKUP(B108,'26MY_ACCORD_DATA'!B:AS,19,FALSE) -> 0
B109: 08P20-30A-1A0 | C109: =VLOOKUP(B109,'26MY_ACCORD_DATA'!B:AS,4,FALSE) -> Radiant rouge métallisé (R-569M) | D109: =B109 -> 08P20-30A-1A0 | E109: =VLOOKUP(B109,'26MY_ACCORD_DATA'!B:AS,9,FALSE) -> 176 | F109: =VLOOKUP(B109,'26MY_ACCORD_DATA'!B:AS,10,FALSE) -> 293 | G109: =VLOOKUP(B109,'26MY_ACCORD_DATA'!B:AS,7,FALSE) -> 0.4 | H109: =VLOOKUP(B109,'26MY_ACCORD_DATA'!B:AS,11,FALSE) -> 353.8 | I109: =VLOOKUP(B109,'26MY_ACCORD_DATA'!B:AS,12,FALSE) -> 0 | J109: =VLOOKUP(B109,'26MY_ACCORD_DATA'!B:AS,13,FALSE) -> 0 | K109: =VLOOKUP(B109,'26MY_ACCORD_DATA'!B:AS,14,FALSE) -> N/A | L109: =VLOOKUP(B109,'26MY_ACCORD_DATA'!B:AS,15,FALSE) -> 0 | M109: =VLOOKUP(B109,'26MY_ACCORD_DATA'!B:AS,16,FALSE) -> • | N109: =VLOOKUP(B109,'26MY_ACCORD_DATA'!B:AS,17,FALSE) -> • | O109: =VLOOKUP(B109,'26MY_ACCORD_DATA'!B:AS,18,FALSE) -> 0 | P109: =VLOOKUP(B109,'26MY_ACCORD_DATA'!B:AS,19,FALSE) -> 0
B110: 08P20-30A-1D0 | C110: =VLOOKUP(B110,'26MY_ACCORD_DATA'!B:AS,4,FALSE) -> Bleu rivière canyon métallisé (B-640M) | D110: =B110 -> 08P20-30A-1D0 | E110: =VLOOKUP(B110,'26MY_ACCORD_DATA'!B:AS,9,FALSE) -> 176 | F110: =VLOOKUP(B110,'26MY_ACCORD_DATA'!B:AS,10,FALSE) -> 293 | G110: =VLOOKUP(B110,'26MY_ACCORD_DATA'!B:AS,7,FALSE) -> 0.4 | H110: =VLOOKUP(B110,'26MY_ACCORD_DATA'!B:AS,11,FALSE) -> 353.8 | I110: =VLOOKUP(B110,'26MY_ACCORD_DATA'!B:AS,12,FALSE) -> 0 | J110: =VLOOKUP(B110,'26MY_ACCORD_DATA'!B:AS,13,FALSE) -> 0 | K110: =VLOOKUP(B110,'26MY_ACCORD_DATA'!B:AS,14,FALSE) -> N/A | L110: =VLOOKUP(B110,'26MY_ACCORD_DATA'!B:AS,15,FALSE) -> 0 | M110: =VLOOKUP(B110,'26MY_ACCORD_DATA'!B:AS,16,FALSE) -> N/A | N110: =VLOOKUP(B110,'26MY_ACCORD_DATA'!B:AS,17,FALSE) -> • | O110: =VLOOKUP(B110,'26MY_ACCORD_DATA'!B:AS,18,FALSE) -> 0 | P110: =VLOOKUP(B110,'26MY_ACCORD_DATA'!B:AS,19,FALSE) -> 0
B111: 08P20-30A-1C0 | C111: =VLOOKUP(B111,'26MY_ACCORD_DATA'!B:AS,4,FALSE) -> Nuit paisible fini nacré (B-575P) | D111: =B111 -> 08P20-30A-1C0 | E111: =VLOOKUP(B111,'26MY_ACCORD_DATA'!B:AS,9,FALSE) -> 176 | F111: =VLOOKUP(B111,'26MY_ACCORD_DATA'!B:AS,10,FALSE) -> 293 | G111: =VLOOKUP(B111,'26MY_ACCORD_DATA'!B:AS,7,FALSE) -> 0.4 | H111: =VLOOKUP(B111,'26MY_ACCORD_DATA'!B:AS,11,FALSE) -> 353.8 | I111: =VLOOKUP(B111,'26MY_ACCORD_DATA'!B:AS,12,FALSE) -> 0 | J111: =VLOOKUP(B111,'26MY_ACCORD_DATA'!B:AS,13,FALSE) -> 0 | K111: =VLOOKUP(B111,'26MY_ACCORD_DATA'!B:AS,14,FALSE) -> N/A | L111: =VLOOKUP(B111,'26MY_ACCORD_DATA'!B:AS,15,FALSE) -> 0 | M111: =VLOOKUP(B111,'26MY_ACCORD_DATA'!B:AS,16,FALSE) -> • | N111: =VLOOKUP(B111,'26MY_ACCORD_DATA'!B:AS,17,FALSE) -> N/A | O111: =VLOOKUP(B111,'26MY_ACCORD_DATA'!B:AS,18,FALSE) -> 0 | P111: =VLOOKUP(B111,'26MY_ACCORD_DATA'!B:AS,19,FALSE) -> 0
B112: 08P20-30A-1H0 | C112: =VLOOKUP(B112,'26MY_ACCORD_DATA'!B:AS,4,FALSE) -> Refl et solaire argent métallisé (NH-932M) | D112: =B112 -> 08P20-30A-1H0 | E112: =VLOOKUP(B112,'26MY_ACCORD_DATA'!B:AS,9,FALSE) -> 176 | F112: =VLOOKUP(B112,'26MY_ACCORD_DATA'!B:AS,10,FALSE) -> 293 | G112: =VLOOKUP(B112,'26MY_ACCORD_DATA'!B:AS,7,FALSE) -> 0.4 | H112: =VLOOKUP(B112,'26MY_ACCORD_DATA'!B:AS,11,FALSE) -> 353.8 | I112: =VLOOKUP(B112,'26MY_ACCORD_DATA'!B:AS,12,FALSE) -> 0 | J112: =VLOOKUP(B112,'26MY_ACCORD_DATA'!B:AS,13,FALSE) -> 0 | K112: =VLOOKUP(B112,'26MY_ACCORD_DATA'!B:AS,14,FALSE) -> • | L112: =VLOOKUP(B112,'26MY_ACCORD_DATA'!B:AS,15,FALSE) -> 0 | M112: =VLOOKUP(B112,'26MY_ACCORD_DATA'!B:AS,16,FALSE) -> • | N112: =VLOOKUP(B112,'26MY_ACCORD_DATA'!B:AS,17,FALSE) -> • | O112: =VLOOKUP(B112,'26MY_ACCORD_DATA'!B:AS,18,FALSE) -> 0 | P112: =VLOOKUP(B112,'26MY_ACCORD_DATA'!B:AS,19,FALSE) -> 0
C114: 4.0 Intérieur
C115: La description | D115: Numéro de pièce | E115: Prix net | F115: Prix de liste | G115: T.F.F. | H115: Prix installé | I115: Application | Q115: Commentaires
...

Sheet 26MY_ACCORD_SELL_EN
B3: 26MY Honda Accord
B4: 200
B6: POPULAR ACCESSORIES
B7: 20
B8: 150
B10: 20 | C10: ='26MY_ACCORD_APP_EN'!$C$117 -> All Season Floor Mats | H10: ='26MY_ACCORD_APP_EN'!$C$118 -> Trunk Tray | M10: ='26MY_ACCORD_APP_EN'!$C$130 -> Auto Day/Night Mirror with Home Link
B11: 20 | C11: ='26MY_ACCORD_APP_EN'!$H$117 -> 307.2 | D11: =-PMT($D$29/52,5*52,C11) -> 1.4008009 | E11: /wk * | F11: =$C$29 -> (6.99%) | H11: ='26MY_ACCORD_APP_EN'!$H$118 -> 230.2 | I11: =-PMT($D$29/52,5*52,H11) -> 1.0496887 | J11: /wk * | K11: =$C$29 -> (6.99%) | M11: ='26MY_ACCORD_APP_EN'!$H$130+'26MY_ACCORD_APP_EN'!$H$131 -> 701.6 | N11: =-PMT($D$29/52,5*52,M11) -> 3.199225 | O11: /wk * | P11: =$C$29 -> (6.99%)
B13: 150
B15: 20 | C15: ='26MY_ACCORD_APP_EN'!$C$82 -> Door Visors | H15: ='26MY_ACCORD_APP_EN'!$C$61 -> 19" HPD Alloy Wheels, Black | M15: ='26MY_ACCORD_APP_EN'!$C$75 -> Black Emblem Rear "H" mark | N15: Ambient Lighting, Blue | O15: Ambient Lighting, Blue | P15: Ambient Lighting, Blue
B16: 50 | C16: ='26MY_ACCORD_APP_EN'!$H$82 -> 409 | D16: =-PMT($D$29/52,5*52,C16) -> 1.8649986 | E16: /wk * | F16: =$C$29 -> (6.99%) | H16: ='26MY_ACCORD_APP_EN'!$H$61 -> 3999.2 | I16: =-PMT($D$29/52,5*52,H16) -> 18.235947 | J16: /wk * | K16: =$C$29 -> (6.99%) | M16: ='26MY_ACCORD_APP_EN'!$H$75 -> 92.4 | N16: =-PMT($D$29/52,5*52,M16) -> 0.42133465 | O16: /wk * | P16: =$C$29 -> (6.99%)
B18: 150
B20: 20 | C20: ='26MY_ACCORD_APP_EN'!$C$95 -> Body Side Moulding | H20: ='26MY_ACCORD_APP_EN'!$C$132 -> Engine Block Heater | M20: ='26MY_ACCORD_APP_EN'!$C$42 -> Aero Kit - Touring Trim
B21: 50 | C21: ='26MY_ACCORD_APP_EN'!$H$96 -> 447.8 | D21: =-PMT($D$29/52,5*52,C21) -> 2.0419227 | E21: /wk * | F21: =$C$29 -> (6.99%) | H21: ='26MY_ACCORD_APP_EN'!$H$132 -> 422.4 | I21: =-PMT($D$29/52,5*52,H21) -> 1.9261013 | J21: /wk * | K21: =$C$29 -> (6.99%) | M21: =SUM('26MY_ACCORD_APP_EN'!$H$42:$H$47) -> 3123.1 | N21: =-PMT($D$29/52,5*52,M21) -> 14.24102 | O21: /wk * | P21: =$C$29 -> (6.99%)
C23: Genuine Honda Accessories purchased with a new Honda vehicle include a 3 year / 60,000 km manufacturer's warranty.
C24: Vehicle accessories purchased after vehicle sale include a 1 year / 20,000km manufacturer's warranty.
B25: 20 | C25: *Prices shown include the cost of installation.
B26: 60 | C26: *For informational purposes only. Weekly amounts shown are estimated payments based on a 60 month finance contract at 6.99% APR (including the cost of installation). Applicable taxes and fees are extra. Accessories cannot be financed on their own and must be financed through Honda Canada Finance Inc., on approved credit, in conjunction with a Honda vehicle. Representative finance example: $350.00 financed at 6.99% APR equals $1.60 weekly for 60 months. 260 weekly payments required. Cost of borrowing is $64.80 for a total obligation of $414.80. Actual payment amounts will vary based on APR, finance contract term and cost of the applicable accessories. Conditions apply. See your Honda dealer for full details.
C27: *More customized weekly payment options & accessories can be seen on Honda.ca - Build & Price
B28: 20
B29: 18 | C29: (6.99%) | D29: 0.0699
B30: 7.5 | C30: 12 | D30: 8 | E30: 8 | F30: 10 | G30: 8.5 | H30: 12 | I30: 8 | J30: 8 | K30: 10 | L30: 8.5 | M30: 12 | N30: 8 | O30: 8 | P30: 10 | Q30: 7.5
B31: Publication Date: | C31: ='26MY_ACCORD_DATA'!$C$4 -> 46113 | D31: ='SELECT PROVINCE'!$A$23 -> All published prices, trim specifications, and availability are subject to change without prior notice. | P31: Province | Q31: ='26MY_ACCORD_DATA'!L6 -> QC

Sheet 26MY_ACCORD_SELL_FR
B3: 26MY Accord
B4: 200
B6: ACCESSOIRES POPULAIRES
B7: 20
B8: 150
B10: 20 | C10: ='26MY_ACCORD_APP_FR'!$C$117 -> Protège-tapis toutes saisons | H10: ='26MY_ACCORD_APP_FR'!$C$120 -> Filet de cargaison | M10: ='26MY_ACCORD_APP_FR'!$C$130 -> Rétroviseur automatique jour/nuit avec HomeLink
B11: 20 | C11: ='26MY_ACCORD_APP_FR'!$H$117 -> 307.2 | D11: =-PMT($D$29/52,5*52,C11) -> 1.4008009 | E11: /wk * | F11: =$C$29 -> (6.99%) | H11: ='26MY_ACCORD_APP_FR'!$H$120 -> 118.8 | I11: =-PMT($D$29/52,5*52,H11) -> 0.54171598 | J11: /wk * | K11: =$C$29 -> (6.99%) | M11: =('26MY_ACCORD_APP_FR'!H130+'26MY_ACCORD_APP_FR'!H131) -> 701.6 | N11: =-PMT($D$29/52,5*52,M11) -> 3.199225 | O11: /wk * | P11: =$C$29 -> (6.99%)
B13: 150
B15: 20 | C15: ='26MY_ACCORD_APP_FR'!$C$82 -> Déflecteurs de portières | H15: ='26MY_ACCORD_APP_FR'!$C$61 -> Jantes de 19 pouces HPD en alliage noir | M15: ='26MY_ACCORD_APP_FR'!$C$75 -> Emblème, noirs lustré arrière « H » mark | N15: Ambient Lighting, Blue | O15: Ambient Lighting, Blue | P15: Ambient Lighting, Blue
B16: 50 | C16: ='26MY_ACCORD_APP_FR'!$H$82 -> 409 | D16: =-PMT($D$29/52,5*52,C16) -> 1.8649986 | E16: /wk * | F16: =$C$29 -> (6.99%) | H16: ='26MY_ACCORD_APP_FR'!$H$61 -> 3999.2 | I16: =-PMT($D$29/52,5*52,H16) -> 18.235947 | J16: /wk * | K16: =$C$29 -> (6.99%) | M16: ='26MY_ACCORD_APP_FR'!$H$75 -> 92.4 | N16: =-PMT($D$29/52,5*52,M16) -> 0.42133465 | O16: /wk * | P16: =$C$29 -> (6.99%)
B18: 150
B20: 20 | C20: ='26MY_ACCORD_APP_FR'!$C$95 -> Moulure latérale | H20: ='26MY_ACCORD_APP_FR'!$C$132 -> Chauffe-moteur | M20: ='26MY_ACCORD_APP_FR'!$C$42 -> Ensemble Aero – Version Touring
B21: 50 | C21: ='26MY_ACCORD_APP_FR'!H96+'26MY_ACCORD_APP_FR'!$H$96 -> 895.6 | D21: =-PMT($D$29/52,5*52,C21) -> 4.0838454 | E21: /wk * | F21: =$C$29 -> (6.99%) | H21: ='26MY_ACCORD_APP_FR'!$H$132 -> 422.4 | I21: =-PMT($D$29/52,5*52,H21) -> 1.9261013 | J21: /wk * | K21: =$C$29 -> (6.99%) | M21: =SUM('26MY_ACCORD_APP_FR'!$H$42:$H$47) -> 3123.1 | N21: =-PMT($D$29/52,5*52,M21) -> 14.24102 | O21: /wk * | P21: =$C$29 -> (6.99%)
C23: Les accessoires Honda d’origine achetés avec un véhicule Honda neuf incluent une garantie du fabricant de 3 ans ou 60 000 km.
C24: Les accessoires de véhicule achetés après la vente du véhicule incluent une garantie du fabricant de 1 an ou 20 000 km.
B25: 20 | C25: *Les prix indiqués incluent le coût d'installation.
B26: 60 | C26: *À titre d’information seulement. Les montants hebdomadaires indiqués sont des paiements estimés basés sur un contrat de financement de 60 mois à un taux annuel en pourcentage (TAP) de 6,99 % (coût d’installation compris). Taxes et frais applicables en sus. Les accessoires ne peuvent être financés seuls et doivent être financés par l’entremise de Honda Canada Finance Inc., sur approbation de crédit, conjointement avec un véhicule Honda. Exemple de financement représentatif : Un montant de 350,00 $ financé à un TAP de 6,99 % équivaut à un paiement hebdomadaire de 1,60 $ pendant 60 mois. 260 paiements hebdomadaires sont requis. Le coût d’emprunt est de 64,80 $, pour une obligation totale de 414,80 $. Le montant réel des paiements variera en fonction du TAP, de la période du contrat de financement et du coût des accessoires applicables. Certaines conditions s’appliquent. Veuillez visiter votre concessionnaire Honda pour obtenir tous les détails.
C27: *Vous pouvez voir d’autres options de paiements hebdomadaires personnalisés ainsi que des accessoires sur le site Honda.ca – Configuration et prix.
B28: 20
B29: 18 | C29: (6.99%) | D29: 0.0699
B30: 7.5 | C30: 12 | D30: 8 | E30: 8 | F30: 10 | G30: 8.5 | H30: 12 | I30: 8 | J30: 8 | K30: 10 | L30: 8.5 | M30: 12 | N30: 8 | O30: 8 | P30: 10 | Q30: 7.5
B31: Date de publication: | C31: ='26MY_ACCORD_DATA'!$C$4 -> 46113 | D31: Tout prix, spécifications de versions et disponibilté d'accessoires publiés sont sujets à changer sans pré-avis. | P31: Province | Q31: ='26MY_ACCORD_DATA'!L6 -> QC
