Workbook
Name prov_cd: 'SELECT PROVINCE'!$B$1
Name province_codes: 'SELECT PROVINCE'!$B$6:$B$16
Name rate_table: 'SELECT PROVINCE'!$B$6:$C$16

Sheet SELECT PROVINCE
A1: Select Province: Choissisez votre province: | B1: YT
B4: Current Labor Rates
B5: Taux de main d'oeuvre en cours
B6: AB | C6: 162
B7: BC | C7: 168
B8: MB | C8: 155
B9: NB | C9: 130
B10: NL | C10: 130
B11: NS | C11: 130
B12: ON | C12: 150 | F12: =prov_cd -> YT
B13: PEI | C13: 125
B14: QC | C14: 140
B15: SK | C15: 155
B16: YT | C16: 168
A23: All published prices, trim specifications, and availability are subject to change without prior notice.
A24: Tout prix, spécifications de versions et disponibilté d'accessoires publiés sont sujets à changer sans pré-avis.

Sheet 26MY_CIV5D_APP_EN
B2: Honda Internal | C2: Honda Accessories
C3: Model Name | D3: ='[1]26MY_CIV5D_DATA'!C2 -> Civic Hatch
C4: Model Year | D4: ='[1]26MY_CIV5D_DATA'!$C$3 -> 2026
C5: S = Standard (accessory comes standard on this trim)
C6: T = Tire Size Change (the size of the accessory wheel is smaller/larger than the OE Wheel. Customer will require new tires to fit these wheels.)
C7: E = Exchange Standard Equipment (the size of the accessory wheel is the same size as the OE wheel and therefore they can use the OE tire.)
C8: N/A = Not Applicable (accessory cannot be applied to this trim)
H10: Province
C11: 1.0 Packages and Kits | H11: =prov_cd -> YT
C12: Description | D12: Part Number | E12: Dealer Net | F12: List Price | G12: FRT | H12: Installed Price | I12: Application | Q12: Comments
I13: ='[1]26MY_CIV5D_DATA'!M$7 -> 0 | J13: ='[1]26MY_CIV5D_DATA'!N$7 -> 0 | K13: ='[1]26MY_CIV5D_DATA'!O$7 -> 0 | L13: ='[1]26MY_CIV5D_DATA'!P$7 -> SPORT | M13: ='[1]26MY_CIV5D_DATA'!Q$7 -> SPORT Hybrid | N13: ='[1]26MY_CIV5D_DATA'!R$7 -> 0 | O13: ='[1]26MY_CIV5D_DATA'!S$7 -> Sport Touring Hybrid | P13: ='[1]26MY_CIV5D_DATA'!T$7 -> Type R
B14: 25CIV-ENK-WTPK | C14: =VLOOKUP(B14,'[1]26MY_CIV5D_DATA'!B:AS,3,FALSE) -> 16” Enkei M52 Wheels & Michelin X-ICE Snow Tire Package | E14: =VLOOKUP(B14,'[1]26MY_CIV5D_DATA'!B:AS,9,FALSE) -> 1556.88 | F14: =VLOOKUP(B14,'[1]26MY_CIV5D_DATA'!B:AS,10,FALSE) -> 1980 | G14: =VLOOKUP(B14,'[1]26MY_CIV5D_DATA'!B:AS,7,FALSE) -> 1.2 | H14: =VLOOKUP(B14,'[1]26MY_CIV5D_DATA'!B:AS,11,FALSE) -> 2181.6 | I14: =VLOOKUP(B14,'[1]26MY_CIV5D_DATA'!B:AS,12,FALSE) -> 0 | J14: =VLOOKUP(B14,'[1]26MY_CIV5D_DATA'!B:AS,13,FALSE) -> 0 | K14: =VLOOKUP($B14,'[1]26MY_CIV5D_DATA'!$B:$AS,14,FALSE) -> 0 | L14: =VLOOKUP(B14,'[1]26MY_CIV5D_DATA'!B:AS,15,FALSE) -> • | M14: =VLOOKUP(B14,'[1]26MY_CIV5D_DATA'!B:AS,16,FALSE) -> N/A | N14: =VLOOKUP($B14,'[1]26MY_CIV5D_DATA'!$B:$AS,17,FALSE) -> 0 | O14: =VLOOKUP(B14,'[1]26MY_CIV5D_DATA'!B:AS,18,FALSE) -> N/A | P14: =VLOOKUP(B14,'[1]26MY_CIV5D_DATA'!B:AS,19,FALSE) -> N/A | Q14: =IF(VLOOKUP(B14,'[1]26MY_CIV5D_DATA'!B:AS,20,FALSE)="","",VLOOKUP(B14,'[1]26MY_CIV5D_DATA'!B:AS,20,FALSE)) -> Priced as a set of 4 wheels.
B15: 480-670-6545-SP or 480-670-6545-GB | C15: =VLOOKUP(B15,'[1]26MY_CIV5D_DATA'!B:AS,3,FALSE) -> 16" Enkei M52 Wheels - Silver or Gloss Black | D15: =B15 -> 480-670-6545-SP or 480-670-6545-GB
B16: 34417 | C16: =VLOOKUP(B16,'[1]26MY_CIV5D_DATA'!B:AS,3,FALSE) -> Michelin X-ICE Snow Tires - 215/55/16 | D16: =B16 -> 34417
B18: 25CIV-STL-WTPK | C18: =VLOOKUP(B18,'[1]26MY_CIV5D_DATA'!B:AS,3,FALSE) -> 16” Winter Steel Wheels & Michelin X-ICE Snow Tire Package | E18: =VLOOKUP(B18,'[1]26MY_CIV5D_DATA'!B:AS,9,FALSE) -> 1124.48 | F18: =VLOOKUP(B18,'[1]26MY_CIV5D_DATA'!B:AS,10,FALSE) -> 1492.48 | G18: =VLOOKUP(B18,'[1]26MY_CIV5D_DATA'!B:AS,7,FALSE) -> 1.2 | H18: =VLOOKUP(B18,'[1]26MY_CIV5D_DATA'!B:AS,11,FALSE) -> 1694.08 | I18: =VLOOKUP(B18,'[1]26MY_CIV5D_DATA'!B:AS,12,FALSE) -> 0 | J18: =VLOOKUP(B18,'[1]26MY_CIV5D_DATA'!B:AS,13,FALSE) -> 0 | K18: =VLOOKUP($B18,'[1]26MY_CIV5D_DATA'!$B:$AS,14,FALSE) -> 0 | L18: =VLOOKUP(B18,'[1]26MY_CIV5D_DATA'!B:AS,15,FALSE) -> • | M18: =VLOOKUP(B18,'[1]26MY_CIV5D_DATA'!B:AS,16,FALSE) -> N/A | N18: =VLOOKUP($B18,'[1]26MY_CIV5D_DATA'!$B:$AS,17,FALSE) -> 0 | O18: =VLOOKUP(B18,'[1]26MY_CIV5D_DATA'!B:AS,18,FALSE) -> N/A | P18: =VLOOKUP(B18,'[1]26MY_CIV5D_DATA'!B:AS,19,FALSE) -> N/A | Q18: =IF(VLOOKUP(B18,'[1]26MY_CIV5D_DATA'!B:AS,20,FALSE)="","",VLOOKUP(B18,'[1]26MY_CIV5D_DATA'!B:AS,20,FALSE)) -> Priced as a set of 4 wheels.
B19: 42700-TBA-A12 | C19: =VLOOKUP(B19,'[1]26MY_CIV5D_DATA'!B:AS,3,FALSE) -> 16” Winter Steel Wheels | D19: =B19 -> 42700-TBA-A12
B20: 34417 | C20: =VLOOKUP(B20,'[1]26MY_CIV5D_DATA'!B:AS,3,FALSE) -> Michelin X-ICE Snow Tires - 215/55/16 | D20: =B20 -> 34417
B22: 25CIV5-ARO-PK | C22: =VLOOKUP(B22,'[1]26MY_CIV5D_DATA'!B:AS,3,FALSE) -> Aero Kit | E22: =VLOOKUP(B22,'[1]26MY_CIV5D_DATA'!B:AS,9,FALSE) -> 643.5 | F22: =VLOOKUP(B22,'[1]26MY_CIV5D_DATA'!B:AS,10,FALSE) -> 1072.8 | G22: =VLOOKUP(B22,'[1]26MY_CIV5D_DATA'!B:AS,7,FALSE) -> 2.2 | H22: =VLOOKUP(B22,'[1]26MY_CIV5D_DATA'!B:AS,11,FALSE) -> 1442.4 | I22: =VLOOKUP(B22,'[1]26MY_CIV5D_DATA'!B:AS,12,FALSE) -> 0 | J22: =VLOOKUP(B22,'[1]26MY_CIV5D_DATA'!B:AS,13,FALSE) -> 0 | K22: =VLOOKUP($B22,'[1]26MY_CIV5D_DATA'!$B:$AS,14,FALSE) -> 0 | L22: =VLOOKUP(B22,'[1]26MY_CIV5D_DATA'!B:AS,15,FALSE) -> • | M22: =VLOOKUP(B22,'[1]26MY_CIV5D_DATA'!B:AS,16,FALSE) -> • | N22: =VLOOKUP($B22,'[1]26MY_CIV5D_DATA'!$B:$AS,17,FALSE) -> 0 | O22: =VLOOKUP(B22,'[1]26MY_CIV5D_DATA'!B:AS,18,FALSE) -> • | P22: =VLOOKUP(B22,'[1]26MY_CIV5D_DATA'!B:AS,19,FALSE) -> N/A | Q22: =IF(VLOOKUP(B22,'[1]26MY_CIV5D_DATA'!B:AS,20,FALSE)="","",VLOOKUP(B22,'[1]26MY_CIV5D_DATA'!B:AS,20,FALSE)) -> 10% Discount Applied. Includes body coloured front underbody spoiler and tailgate spoiler.
B23: 25CIV-5AR-NH883 | C23: =VLOOKUP(B23,'[1]26MY_CIV5D_DATA'!B:AS,3,FALSE) -> Platinum White Pearl (NH-883P) | D23: =B23 -> 25CIV-5AR-NH883
B24: 25CIV-5AR-NH932 | C24: =VLOOKUP(B24,'[1]26MY_CIV5D_DATA'!B:AS,3,FALSE) -> Solar Reflection Silver (NH-932M) | D24: =B24 -> 25CIV-5AR-NH932
B25: 25CIV-5AR-NH904 | C25: =VLOOKUP(B25,'[1]26MY_CIV5D_DATA'!B:AS,3,FALSE) -> Meteoroid Gray Pearl (NH-904M) | D25: =B25 -> 25CIV-5AR-NH904
B26: 25CIV-5AR-NH912 | C26: =VLOOKUP(B26,'[1]26MY_CIV5D_DATA'!B:AS,3,FALSE) -> Urban Grey Pearl (NH-912P) | D26: =B26 -> 25CIV-5AR-NH912
B27: 25CIV-5AR-NH731 | C27: =VLOOKUP(B27,'[1]26MY_CIV5D_DATA'!B:AS,3,FALSE) -> Crystal Black Pearl (NH-731P) | D27: =B27 -> 25CIV-5AR-NH731
B28: 25CIV-5AR-R513 | C28: =VLOOKUP(B28,'[1]26MY_CIV5D_DATA'!B:AS,3,FALSE) -> Rallye Red (R-513) | D28: =B28 -> 25CIV-5AR-R513
B29: 25CIV-5AR-B637 | C29: =VLOOKUP(B29,'[1]26MY_CIV5D_DATA'!B:AS,3,FALSE) -> Boost Blue Pearl (B-637P) | D29: =B29 -> 25CIV-5AR-B637
B31: 22CIV-COLD-PK20 | C31: =VLOOKUP(B31,'[1]26MY_CIV5D_DATA'!B:AS,3,FALSE) -> Cold Weather Package - 2.0L | D31: =B31 -> 22CIV-COLD-PK20 | E31: =VLOOKUP(B31,'[1]26MY_CIV5D_DATA'!B:AS,9,FALSE) -> 224.2 | F31: =VLOOKUP(B31,'[1]26MY_CIV5D_DATA'!B:AS,10,FALSE) -> 374.3 | G31: =VLOOKUP(B31,'[1]26MY_CIV5D_DATA'!B:AS,7,FALSE) -> 1.4 | H31: =VLOOKUP(B31,'[1]26MY_CIV5D_DATA'!B:AS,11,FALSE) -> 609.5 | I31: =VLOOKUP(B31,'[1]26MY_CIV5D_DATA'!B:AS,12,FALSE) -> 0 | J31: =VLOOKUP(B31,'[1]26MY_CIV5D_DATA'!B:AS,13,FALSE) -> 0 | K31: =VLOOKUP($B31,'[1]26MY_CIV5D_DATA'!$B:$AS,14,FALSE) -> 0 | L31: =VLOOKUP(B31,'[1]26MY_CIV5D_DATA'!B:AS,15,FALSE) -> • | M31: =VLOOKUP(B31,'[1]26MY_CIV5D_DATA'!B:AS,16,FALSE) -> • | N31: =VLOOKUP($B31,'[1]26MY_CIV5D_DATA'!$B:$AS,17,FALSE) -> 0 | O31: =VLOOKUP(B31,'[1]26MY_CIV5D_DATA'!B:AS,18,FALSE) -> • | P31: =VLOOKUP(B31,'[1]26MY_CIV5D_DATA'!B:AS,19,FALSE) -> N/A | Q31: =IF(VLOOKUP(B31,'[1]26MY_CIV5D_DATA'!B:AS,20,FALSE)="","",VLOOKUP(B31,'[1]26MY_CIV5D_DATA'!B:AS,20,FALSE)) -> 5% Discount Applied.
B32: 08T44-SNA-302 | C32: =VLOOKUP(B32,'[1]26MY_CIV5D_DATA'!B:AS,3,FALSE) -> Engine Block Heater - 2.0L | D32: =B32 -> 08T44-SNA-302
B33: 31670-BMS-004H | C33: =VLOOKUP(B33,'[1]26MY_CIV5D_DATA'!B:AS,3,FALSE) -> Optimate 12V Auto Battery Charger/Maintainer | D33: =B33 -> 31670-BMS-004H
B35: 25CIV5D-PRO-PET | C35: =VLOOKUP(B35,'[1]26MY_CIV5D_DATA'!B:AS,3,FALSE) -> Protection Package - Petrol | D35: =B35 -> 25CIV5D-PRO-PET | E35: =VLOOKUP(B35,'[1]26MY_CIV5D_DATA'!B:AS,9,FALSE) -> 288.9 | F35: =VLOOKUP(B35,'[1]26MY_CIV5D_DATA'!B:AS,10,FALSE) -> 536 | G35: =VLOOKUP(B35,'[1]26MY_CIV5D_DATA'!B:AS,7,FALSE) -> 0.6 | H35: =VLOOKUP(B35,'[1]26MY_CIV5D_DATA'!B:AS,11,FALSE) -> 636.8 | I35: =VLOOKUP(B35,'[1]26MY_CIV5D_DATA'!B:AS,12,FALSE) -> 0 | J35: =VLOOKUP(B35,'[1]26MY_CIV5D_DATA'!B:AS,13,FALSE) -> 0 | K35: =VLOOKUP($B35,'[1]26MY_CIV5D_DATA'!$B:$AS,14,FALSE) -> 0 | L35: =VLOOKUP(B35,'[1]26MY_CIV5D_DATA'!B:AS,15,FALSE) -> • | M35: =VLOOKUP(B35,'[1]26MY_CIV5D_DATA'!B:AS,16,FALSE) -> N/A | N35: =VLOOKUP($B35,'[1]26MY_CIV5D_DATA'!$B:$AS,17,FALSE) -> 0 | O35: =VLOOKUP(B35,'[1]26MY_CIV5D_DATA'!B:AS,18,FALSE) -> N/A | P35: =VLOOKUP(B35,'[1]26MY_CIV5D_DATA'!B:AS,19,FALSE) -> N/A | Q35: =IF(VLOOKUP(B35,'[1]26MY_CIV5D_DATA'!B:AS,20,FALSE)="","",VLOOKUP(B35,'[1]26MY_CIV5D_DATA'!B:AS,20,FALSE))
B36: 08P17-T20-110 | C36: =VLOOKUP(B36,'[1]26MY_CIV5D_DATA'!B:AS,3,FALSE) -> Floor Mats - All-Season | D36: =B36 -> 08P17-T20-110
B37: 08U45-T47-100B | C37: =VLOOKUP(B37,'[1]26MY_CIV5D_DATA'!B:AS,3,FALSE) -> Cargo Tray | D37: =B37 -> 08U45-T47-100B
B38: 08P09-T47-300 | C38: =VLOOKUP(B38,'[1]26MY_CIV5D_DATA'!B:AS,3,FALSE) -> Splash Guards - Rear | D38: =B38 -> 08P09-T47-300
B40: 25CIV5-PRO-HYB | C40: =VLOOKUP(B40,'[1]26MY_CIV5D_DATA'!B:AS,3,FALSE) -> Protection Package - Hybrid | D40: =B40 -> 25CIV5-PRO-HYB | E40: =VLOOKUP(B40,'[1]26MY_CIV5D_DATA'!B:AS,9,FALSE) -> 288.9 | F40: =VLOOKUP(B40,'[1]26MY_CIV5D_DATA'!B:AS,10,FALSE) -> 536 | G40: =VLOOKUP(B40,'[1]26MY_CIV5D_DATA'!B:AS,7,FALSE) -> 0.6 | H40: 602 | I40: =VLOOKUP(B40,'[1]26MY_CIV5D_DATA'!B:AS,12,FALSE) -> 0 | J40: =VLOOKUP(B40,'[1]26MY_CIV5D_DATA'!B:AS,13,FALSE) -> 0 | K40: =VLOOKUP($B40,'[1]26MY_CIV5D_DATA'!$B:$AS,14,FALSE) -> 0 | L40: =VLOOKUP(B40,'[1]26MY_CIV5D_DATA'!B:AS,15,FALSE) -> N/A | M40: =VLOOKUP(B40,'[1]26MY_CIV5D_DATA'!B:AS,16,FALSE) -> • | N40: =VLOOKUP($B40,'[1]26MY_CIV5D_DATA'!$B:$AS,17,FALSE) -> 0 | O40: =VLOOKUP(B40,'[1]26MY_CIV5D_DATA'!B:AS,18,FALSE) -> • | P40: =VLOOKUP(B40,'[1]26MY_CIV5D_DATA'!B:AS,19,FALSE) -> N/A | Q40: =IF(VLOOKUP(B40,'[1]26MY_CIV5D_DATA'!B:AS,20,FALSE)="","",VLOOKUP(B40,'[1]26MY_CIV5D_DATA'!B:AS,20,FALSE))
B41: 08P17-T20-110A | C41: =VLOOKUP(B41,'[1]26MY_CIV5D_DATA'!B:AS,3,FALSE) -> Floor Mats Hybrid - All-Season | D41: =B41 -> 08P17-T20-110A
B42: 08U45-T47-100B | C42: =VLOOKUP(B42,'[1]26MY_CIV5D_DATA'!B:AS,3,FALSE) -> Cargo Tray | D42: =B42 -> 08U45-T47-100B
B43: 08P09-T47-300 | C43: =VLOOKUP(B43,'[1]26MY_CIV5D_DATA'!B:AS,3,FALSE) -> Splash Guards - Rear | D43: =B43 -> 08P09-T47-300
B45: 25CIV5-PRO-FLM | C45: =VLOOKUP(B45,'[1]26MY_CIV5D_DATA'!B:AS,3,FALSE) -> Protection Package - Film | D45: =B45 -> 25CIV5-PRO-FLM | E45: =VLOOKUP(B45,'[1]26MY_CIV5D_DATA'!B:AS,9,FALSE) -> 198.9 | F45: =VLOOKUP(B45,'[1]26MY_CIV5D_DATA'!B:AS,10,FALSE) -> 319.5 | G45: =VLOOKUP(B45,'[1]26MY_CIV5D_DATA'!B:AS,7,FALSE) -> 1 | H45: =VLOOKUP(B45,'[1]26MY_CIV5D_DATA'!B:AS,11,FALSE) -> 487.5 | I45: =VLOOKUP(B45,'[1]26MY_CIV5D_DATA'!B:AS,12,FALSE) -> 0 | J45: =VLOOKUP(B45,'[1]26MY_CIV5D_DATA'!B:AS,13,FALSE) -> 0 | K45: =VLOOKUP($B45,'[1]26MY_CIV5D_DATA'!$B:$AS,14,FALSE) -> 0 | L45: =VLOOKUP(B45,'[1]26MY_CIV5D_DATA'!B:AS,15,FALSE) -> • | M45: =VLOOKUP(B45,'[1]26MY_CIV5D_DATA'!B:AS,16,FALSE) -> • | N45: =VLOOKUP($B45,'[1]26MY_CIV5D_DATA'!$B:$AS,17,FALSE) -> 0 | O45: =VLOOKUP(B45,'[1]26MY_CIV5D_DATA'!B:AS,18,FALSE) -> • | P45: =VLOOKUP(B45,'[1]26MY_CIV5D_DATA'!B:AS,19,FALSE) -> N/A | Q45: =IF(VLOOKUP(B45,'[1]26MY_CIV5D_DATA'!B:AS,20,FALSE)="","",VLOOKUP(B45,'[1]26MY_CIV5D_DATA'!B:AS,20,FALSE)) -> 10% Discount Applied. Cannot be installed with Door Edge Guards
B46: 08P04-T20-100 | C46: =VLOOKUP(B46,'[1]26MY_CIV5D_DATA'!B:AS,3,FALSE) -> Door Sill Protection Film | D46: =B46 -> 08P04-T20-100
B47: 08P20-T20-100A | C47: =VLOOKUP(B47,'[1]26MY_CIV5D_DATA'!B:AS,3,FALSE) -> Door Edge Film | D47: =B47 -> 08P20-T20-100A
B48: 08P01-T47-100 | C48: =VLOOKUP(B48,'[1]26MY_CIV5D_DATA'!B:AS,3,FALSE) -> Rear Bumper Protector | D48: =B48 -> 08P01-T47-100
C50: 2.0 Wheels and Wheel Accessories
C51: Description | D51: Part Number | E51: Dealer Net | F51: List Price | G51: FRT | H51: Installed Price | I51: Application | Q51: Comments
I52: ='[1]26MY_CIV5D_DATA'!M$7 -> 0 | J52: ='[1]26MY_CIV5D_DATA'!N$7 -> 0 | K52: ='[1]26MY_CIV5D_DATA'!O$7 -> 0 | L52: ='[1]26MY_CIV5D_DATA'!P$7 -> SPORT | M52: ='[1]26MY_CIV5D_DATA'!Q$7 -> SPORT Hybrid | N52: ='[1]26MY_CIV5D_DATA'!R$7 -> 0 | O52: ='[1]26MY_CIV5D_DATA'!S$7 -> Sport Touring Hybrid | P52: ='[1]26MY_CIV5D_DATA'!T$7 -> Type R
B53: 42700-TBA-A12 | C53: =VLOOKUP(B53,'[1]26MY_CIV5D_DATA'!B:AS,3,FALSE) -> 16” Winter Steel Wheels | D53: =B53 -> 42700-TBA-A12 | E53: =VLOOKUP(B53,'[1]26MY_CIV5D_DATA'!B:AS,9,FALSE) -> 311.6 | F53: =VLOOKUP(B53,'[1]26MY_CIV5D_DATA'!B:AS,10,FALSE) -> 512.48 | G53: =VLOOKUP(B53,'[1]26MY_CIV5D_DATA'!B:AS,7,FALSE) -> 1.6 | H53: =VLOOKUP(B53,'[1]26MY_CIV5D_DATA'!B:AS,11,FALSE) -> 781.28 | I53: =VLOOKUP(B53,'[1]26MY_CIV5D_DATA'!B:AS,12,FALSE) -> 0 | J53: =VLOOKUP(B53,'[1]26MY_CIV5D_DATA'!B:AS,13,FALSE) -> 0 | K53: =VLOOKUP($B53,'[1]26MY_CIV5D_DATA'!$B:$AS,14,FALSE) -> 0 | L53: =VLOOKUP(B53,'[1]26MY_CIV5D_DATA'!B:AS,15,FALSE) -> • | M53: =VLOOKUP(B53,'[1]26MY_CIV5D_DATA'!B:AS,16,FALSE) -> N/A | N53: =VLOOKUP($B53,'[1]26MY_CIV5D_DATA'!$B:$AS,17,FALSE) -> 0 | O53: =VLOOKUP(B53,'[1]26MY_CIV5D_DATA'!B:AS,18,FALSE) -> N/A | P53: =VLOOKUP(B53,'[1]26MY_CIV5D_DATA'!B:AS,19,FALSE) -> N/A | Q53: =IF(VLOOKUP(B53,'[1]26MY_CIV5D_DATA'!B:AS,20,FALSE)="","",VLOOKUP(B53,'[1]26MY_CIV5D_DATA'!B:AS,20,FALSE)) -> Priced as a set of 4 wheels. Tires sold separately.
B54: 480-670-6545GB | C54: =VLOOKUP(B54,'[1]26MY_CIV5D_DATA'!B:AS,3,FALSE) -> 16" Enkei M52 Wheel - Gloss Black | D54: =B54 -> 480-670-6545GB | E54: =VLOOKUP(B54,'[1]26MY_CIV5D_DATA'!B:AS,9,FALSE) -> 744 | F54: =VLOOKUP(B54,'[1]26MY_CIV5D_DATA'!B:AS,10,FALSE) -> 1000 | G54: =VLOOKUP(B54,'[1]26MY_CIV5D_DATA'!B:AS,7,FALSE) -> 1.6 | H54: =VLOOKUP(B54,'[1]26MY_CIV5D_DATA'!B:AS,11,FALSE) -> 1268.8 | I54: =VLOOKUP(B54,'[1]26MY_CIV5D_DATA'!B:AS,12,FALSE) -> 0 | J54: =VLOOKUP(B54,'[1]26MY_CIV5D_DATA'!B:AS,13,FALSE) -> 0 | K54: =VLOOKUP($B54,'[1]26MY_CIV5D_DATA'!$B:$AS,14,FALSE) -> 0 | L54: =VLOOKUP(B54,'[1]26MY_CIV5D_DATA'!B:AS,15,FALSE) -> T | M54: =VLOOKUP(B54,'[1]26MY_CIV5D_DATA'!B:AS,16,FALSE) -> N/A | N54: =VLOOKUP($B54,'[1]26MY_CIV5D_DATA'!$B:$AS,17,FALSE) -> 0 | O54: =VLOOKUP(B54,'[1]26MY_CIV5D_DATA'!B:AS,18,FALSE) -> N/A | P54: =VLOOKUP(B54,'[1]26MY_CIV5D_DATA'!B:AS,19,FALSE) -> N/A | Q54: =IF(VLOOKUP(B54,'[1]26MY_CIV5D_DATA'!B:AS,20,FALSE)="","",VLOOKUP(B54,'[1]26MY_CIV5D_DATA'!B:AS,20,FALSE)) -> Priced as a set of 4 wheels. Tires sold separately.
B55: 480-670-6545SP | C55: =VLOOKUP(B55,'[1]26MY_CIV5D_DATA'!B:AS,3,FALSE) -> 16" Enkei M52 Wheel - Silver | D55: =B55 -> 480-670-6545SP | E55: =VLOOKUP(B55,'[1]26MY_CIV5D_DATA'!B:AS,9,FALSE) -> 744 | F55: =VLOOKUP(B55,'[1]26MY_CIV5D_DATA'!B:AS,10,FALSE) -> 1000 | G55: =VLOOKUP(B55,'[1]26MY_CIV5D_DATA'!B:AS,7,FALSE) -> 1.6 | H55: =VLOOKUP(B55,'[1]26MY_CIV5D_DATA'!B:AS,11,FALSE) -> 1268.8 | I55: =VLOOKUP(B55,'[1]26MY_CIV5D_DATA'!B:AS,12,FALSE) -> 0 | J55: =VLOOKUP(B55,'[1]26MY_CIV5D_DATA'!B:AS,13,FALSE) -> 0 | K55: =VLOOKUP($B55,'[1]26MY_CIV5D_DATA'!$B:$AS,14,FALSE) -> 0 | L55: =VLOOKUP(B55,'[1]26MY_CIV5D_DATA'!B:AS,15,FALSE) -> T | M55: =VLOOKUP(B55,'[1]26MY_CIV5D_DATA'!B:AS,16,FALSE) -> N/A | N55: =VLOOKUP($B55,'[1]26MY_CIV5D_DATA'!$B:$AS,17,FALSE) -> 0 | O55: =VLOOKUP(B55,'[1]26MY_CIV5D_DATA'!B:AS,18,FALSE) -> N/A | P55: =VLOOKUP(B55,'[1]26MY_CIV5D_DATA'!B:AS,19,FALSE) -> N/A | Q55: =IF(VLOOKUP(B55,'[1]26MY_CIV5D_DATA'!B:AS,20,FALSE)="","",VLOOKUP(B55,'[1]26MY_CIV5D_DATA'!B:AS,20,FALSE)) -> Priced as a set of 4 wheels. Tires sold separately.
B56: 509-775-6545BH | C56: =VLOOKUP(B56,'[1]26MY_CIV5D_DATA'!B:AS,3,FALSE) -> 17" Enkei Draco Wheel, Gloss Black | D56: =B56 -> 509-775-6545BH | E56: =VLOOKUP(B56,'[1]26MY_CIV5D_DATA'!B:AS,9,FALSE) -> 832 | F56: =VLOOKUP(B56,'[1]26MY_CIV5D_DATA'!B:AS,10,FALSE) -> 1116 | G56: =VLOOKUP(B56,'[1]26MY_CIV5D_DATA'!B:AS,7,FALSE) -> 1.6 | H56: =VLOOKUP(B56,'[1]26MY_CIV5D_DATA'!B:AS,11,FALSE) -> 1384.8 | I56: =VLOOKUP(B56,'[1]26MY_CIV5D_DATA'!B:AS,12,FALSE) -> 0 | J56: =VLOOKUP(B56,'[1]26MY_CIV5D_DATA'!B:AS,13,FALSE) -> 0 | K56: =VLOOKUP($B56,'[1]26MY_CIV5D_DATA'!$B:$AS,14,FALSE) -> 0 | L56: =VLOOKUP(B56,'[1]26MY_CIV5D_DATA'!B:AS,15,FALSE) -> T | M56: =VLOOKUP(B56,'[1]26MY_CIV5D_DATA'!B:AS,16,FALSE) -> N/A | N56: =VLOOKUP($B56,'[1]26MY_CIV5D_DATA'!$B:$AS,17,FALSE) -> 0 | O56: =VLOOKUP(B56,'[1]26MY_CIV5D_DATA'!B:AS,18,FALSE) -> N/A | P56: =VLOOKUP(B56,'[1]26MY_CIV5D_DATA'!B:AS,19,FALSE) -> N/A | Q56: =IF(VLOOKUP(B56,'[1]26MY_CIV5D_DATA'!B:AS,20,FALSE)="","",VLOOKUP(B56,'[1]26MY_CIV5D_DATA'!B:AS,20,FALSE)) -> Priced as a set of 4 wheels. Tires sold separately.
B57: 509-775-6545SH | C57: =VLOOKUP(B57,'[1]26MY_CIV5D_DATA'!B:AS,3,FALSE) -> 17" Enkei Draco Wheel, Silver | D57: =B57 -> 509-775-6545SH | E57: =VLOOKUP(B57,'[1]26MY_CIV5D_DATA'!B:AS,9,FALSE) -> 832 | F57: =VLOOKUP(B57,'[1]26MY_CIV5D_DATA'!B:AS,10,FALSE) -> 1116 | G57: =VLOOKUP(B57,'[1]26MY_CIV5D_DATA'!B:AS,7,FALSE) -> 1.6 | H57: =VLOOKUP(B57,'[1]26MY_CIV5D_DATA'!B:AS,11,FALSE) -> 1384.8 | I57: =VLOOKUP(B57,'[1]26MY_CIV5D_DATA'!B:AS,12,FALSE) -> 0 | J57: =VLOOKUP(B57,'[1]26MY_CIV5D_DATA'!B:AS,13,FALSE) -> 0 | K57: =VLOOKUP($B57,'[1]26MY_CIV5D_DATA'!$B:$AS,14,FALSE) -> 0 | L57: =VLOOKUP(B57,'[1]26MY_CIV5D_DATA'!B:AS,15,FALSE) -> T | M57: =VLOOKUP(B57,'[1]26MY_CIV5D_DATA'!B:AS,16,FALSE) -> N/A | N57: =VLOOKUP($B57,'[1]26MY_CIV5D_DATA'!$B:$AS,17,FALSE) -> 0 | O57: =VLOOKUP(B57,'[1]26MY_CIV5D_DATA'!B:AS,18,FALSE) -> N/A | P57: =VLOOKUP(B57,'[1]26MY_CIV5D_DATA'!B:AS,19,FALSE) -> N/A | Q57: =IF(VLOOKUP(B57,'[1]26MY_CIV5D_DATA'!B:AS,20,FALSE)="","",VLOOKUP(B57,'[1]26MY_CIV5D_DATA'!B:AS,20,FALSE)) -> Priced as a set of 4 wheels. Tires sold separately.
B58: 08W18-T20-100 | C58: =VLOOKUP(B58,'[1]26MY_CIV5D_DATA'!B:AS,3,FALSE) -> 18" Alloy Wheel - Black | D58: =B58 -> 08W18-T20-100 | E58: =VLOOKUP(B58,'[1]26MY_CIV5D_DATA'!B:AS,9,FALSE) -> 2256 | F58: =VLOOKUP(B58,'[1]26MY_CIV5D_DATA'!B:AS,10,FALSE) -> 3472 | G58: =VLOOKUP(B58,'[1]26MY_CIV5D_DATA'!B:AS,7,FALSE) -> 1.6 | H58: =VLOOKUP(B58,'[1]26MY_CIV5D_DATA'!B:AS,11,FALSE) -> 3740.8 | I58: =VLOOKUP(B58,'[1]26MY_CIV5D_DATA'!B:AS,12,FALSE) -> 0 | J58: =VLOOKUP(B58,'[1]26MY_CIV5D_DATA'!B:AS,13,FALSE) -> 0 | K58: =VLOOKUP($B58,'[1]26MY_CIV5D_DATA'!$B:$AS,14,FALSE) -> 0 | L58: =VLOOKUP(B58,'[1]26MY_CIV5D_DATA'!B:AS,15,FALSE) -> E | M58: =VLOOKUP(B58,'[1]26MY_CIV5D_DATA'!B:AS,16,FALSE) -> E | N58: =VLOOKUP($B58,'[1]26MY_CIV5D_DATA'!$B:$AS,17,FALSE) -> 0 | O58: =VLOOKUP(B58,'[1]26MY_CIV5D_DATA'!B:AS,18,FALSE) -> E | P58: =VLOOKUP(B58,'[1]26MY_CIV5D_DATA'!B:AS,19,FALSE) -> N/A | Q58: =IF(VLOOKUP(B58,'[1]26MY_CIV5D_DATA'!B:AS,20,FALSE)="","",VLOOKUP(B58,'[1]26MY_CIV5D_DATA'!B:AS,20,FALSE)) -> Priced as a set of 4 wheels. Tires sold separately.
B59: 08W42-S2A-101 | C59: =VLOOKUP(B59,'[1]26MY_CIV5D_DATA'!B:AS,3,FALSE) -> Wheel Locks - Black | D59: =B59 -> 08W42-S2A-101 | E59: =VLOOKUP(B59,'[1]26MY_CIV5D_DATA'!B:AS,9,FALSE) -> 59 | F59: =VLOOKUP(B59,'[1]26MY_CIV5D_DATA'!B:AS,10,FALSE) -> 98 | G59: =VLOOKUP(B59,'[1]26MY_CIV5D_DATA'!B:AS,7,FALSE) -> 0.2 | H59: =VLOOKUP(B59,'[1]26MY_CIV5D_DATA'!B:AS,11,FALSE) -> 131.6 | I59: =VLOOKUP(B59,'[1]26MY_CIV5D_DATA'!B:AS,12,FALSE) -> 0 | J59: =VLOOKUP(B59,'[1]26MY_CIV5D_DATA'!B:AS,13,FALSE) -> 0 | K59: =VLOOKUP($B59,'[1]26MY_CIV5D_DATA'!$B:$AS,14,FALSE) -> 0 | L59: =VLOOKUP(B59,'[1]26MY_CIV5D_DATA'!B:AS,15,FALSE) -> • | M59: =VLOOKUP(B59,'[1]26MY_CIV5D_DATA'!B:AS,16,FALSE) -> • | N59: =VLOOKUP($B59,'[1]26MY_CIV5D_DATA'!$B:$AS,17,FALSE) -> 0 | O59: =VLOOKUP(B59,'[1]26MY_CIV5D_DATA'!B:AS,18,FALSE) -> • | P59: =VLOOKUP(B59,'[1]26MY_CIV5D_DATA'!B:AS,19,FALSE) -> • | Q59: =IF(VLOOKUP(B59,'[1]26MY_CIV5D_DATA'!B:AS,20,FALSE)="","",VLOOKUP(B59,'[1]26MY_CIV5D_DATA'!B:AS,20,FALSE))
B60: 08W42-SCV-302 | C60: =VLOOKUP(B60,'[1]26MY_CIV5D_DATA'!B:AS,3,FALSE) -> Wheel Locks - Chrome | D60: =B60 -> 08W42-SCV-302 | E60: =VLOOKUP(B60,'[1]26MY_CIV5D_DATA'!B:AS,9,FALSE) -> 52 | F60: =VLOOKUP(B60,'[1]26MY_CIV5D_DATA'!B:AS,10,FALSE) -> 87 | G60: =VLOOKUP(B60,'[1]26MY_CIV5D_DATA'!B:AS,7,FALSE) -> 0.2 | H60: =VLOOKUP(B60,'[1]26MY_CIV5D_DATA'!B:AS,11,FALSE) -> 120.6 | I60: =VLOOKUP(B60,'[1]26MY_CIV5D_DATA'!B:AS,12,FALSE) -> 0 | J60: =VLOOKUP(B60,'[1]26MY_CIV5D_DATA'!B:AS,13,FALSE) -> 0 | K60: =VLOOKUP($B60,'[1]26MY_CIV5D_DATA'!$B:$AS,14,FALSE) -> 0 | L60: =VLOOKUP(B60,'[1]26MY_CIV5D_DATA'!B:AS,15,FALSE) -> • | M60: =VLOOKUP(B60,'[1]26MY_CIV5D_DATA'!B:AS,16,FALSE) -> • | N60: =VLOOKUP($B60,'[1]26MY_CIV5D_DATA'!$B:$AS,17,FALSE) -> 0 | O60: =VLOOKUP(B60,'[1]26MY_CIV5D_DATA'!B:AS,18,FALSE) -> • | P60: =VLOOKUP(B60,'[1]26MY_CIV5D_DATA'!B:AS,19,FALSE) -> N/A | Q60: =IF(VLOOKUP(B60,'[1]26MY_CIV5D_DATA'!B:AS,20,FALSE)="","",VLOOKUP(B60,'[1]26MY_CIV5D_DATA'!B:AS,20,FALSE))
B61: 08W42-TGG-100 | C61: =VLOOKUP(B61,'[1]26MY_CIV5D_DATA'!B:AS,3,FALSE) -> Wheel Lug Nuts - Black | D61: =B61 -> 08W42-TGG-100 | E61: =VLOOKUP(B61,'[1]26MY_CIV5D_DATA'!B:AS,9,FALSE) -> 55 | F61: =VLOOKUP(B61,'[1]26MY_CIV5D_DATA'!B:AS,10,FALSE) -> 88 | G61: =VLOOKUP(B61,'[1]26MY_CIV5D_DATA'!B:AS,7,FALSE) -> 0.2 | H61: =VLOOKUP(B61,'[1]26MY_CIV5D_DATA'!B:AS,11,FALSE) -> 121.6 | I61: =VLOOKUP(B61,'[1]26MY_CIV5D_DATA'!B:AS,12,FALSE) -> 0 | J61: =VLOOKUP(B61,'[1]26MY_CIV5D_DATA'!B:AS,13,FALSE) -> 0 | K61: =VLOOKUP($B61,'[1]26MY_CIV5D_DATA'!$B:$AS,14,FALSE) -> 0 | L61: =VLOOKUP(B61,'[1]26MY_CIV5D_DATA'!B:AS,15,FALSE) -> • | M61: =VLOOKUP(B61,'[1]26MY_CIV5D_DATA'!B:AS,16,FALSE) -> • | N61: =VLOOKUP($B61,'[1]26MY_CIV5D_DATA'!$B:$AS,17,FALSE) -> 0 | O61: =VLOOKUP(B61,'[1]26MY_CIV5D_DATA'!B:AS,18,FALSE) -> • | P61: =VLOOKUP(B61,'[1]26MY_CIV5D_DATA'!B:AS,19,FALSE) -> N/A | Q61: =IF(VLOOKUP(B61,'[1]26MY_CIV5D_DATA'!B:AS,20,FALSE)="","",VLOOKUP(B61,'[1]26MY_CIV5D_DATA'!B:AS,20,FALSE)) -> Includes: 1 set (i.e. 4 lug nuts). A complete install requires 5 sets (i.e. 20 lug nuts) for 4 wheels.
C63: 3.0 Exterior
C64: Description | D64: Part Number | E64: Dealer Net | F64: List Price | G64: FRT | H64: Installed Price | I64: Application | Q64: Comments
I65: ='[1]26MY_CIV5D_DATA'!M$7 -> 0 | J65: ='[1]26MY_CIV5D_DATA'!N$7 -> 0 | K65: ='[1]26MY_CIV5D_DATA'!O$7 -> 0 | L65: ='[1]26MY_CIV5D_DATA'!P$7 -> SPORT | M65: ='[1]26MY_CIV5D_DATA'!Q$7 -> SPORT Hybrid | N65: ='[1]26MY_CIV5D_DATA'!R$7 -> 0 | O65: ='[1]26MY_CIV5D_DATA'!S$7 -> Sport Touring Hybrid | P65: ='[1]26MY_CIV5D_DATA'!T$7 -> Type R
B66: 08F20-T47-100E | C66: =VLOOKUP(B66,'[1]26MY_CIV5D_DATA'!B:AS,3,FALSE) -> Black Emblem H-Mark | D66: =B66 -> 08F20-T47-100E | E66: =VLOOKUP(B66,'[1]26MY_CIV5D_DATA'!B:AS,9,FALSE) -> 0 | F66: =VLOOKUP(B66,'[1]26MY_CIV5D_DATA'!B:AS,10,FALSE) -> 0 | G66: =VLOOKUP(B66,'[1]26MY_CIV5D_DATA'!B:AS,7,FALSE) -> 0.7 | H66: =VLOOKUP(B66,'[1]26MY_CIV5D_DATA'!B:AS,11,FALSE) -> 117.6 | I66: =VLOOKUP(B66,'[1]26MY_CIV5D_DATA'!B:AS,12,FALSE) -> 0 | J66: =VLOOKUP(B66,'[1]26MY_CIV5D_DATA'!B:AS,13,FALSE) -> 0 | K66: =VLOOKUP($B66,'[1]26MY_CIV5D_DATA'!$B:$AS,14,FALSE) -> 0 | L66: =VLOOKUP(B66,'[1]26MY_CIV5D_DATA'!B:AS,15,FALSE) -> • | M66: =VLOOKUP(B66,'[1]26MY_CIV5D_DATA'!B:AS,16,FALSE) -> • | N66: =VLOOKUP($B66,'[1]26MY_CIV5D_DATA'!$B:$AS,17,FALSE) -> 0 | O66: =VLOOKUP(B66,'[1]26MY_CIV5D_DATA'!B:AS,18,FALSE) -> • | P66: =VLOOKUP(B66,'[1]26MY_CIV5D_DATA'!B:AS,19,FALSE) -> N/A | Q66: =IF(VLOOKUP(B66,'[1]26MY_CIV5D_DATA'!B:AS,20,FALSE)="","",VLOOKUP(B66,'[1]26MY_CIV5D_DATA'!B:AS,20,FALSE)) -> Front and Rear H-Mark Logo.
B67: 08P47-T20-300 | C67: =VLOOKUP(B67,'[1]26MY_CIV5D_DATA'!B:AS,3,FALSE) -> Hood Protector | D67: =B67 -> 08P47-T20-300 | E67: =VLOOKUP(B67,'[1]26MY_CIV5D_DATA'!B:AS,9,FALSE) -> 215 | F67: =VLOOKUP(B67,'[1]26MY_CIV5D_DATA'!B:AS,10,FALSE) -> 358 | G67: =VLOOKUP(B67,'[1]26MY_CIV5D_DATA'!B:AS,7,FALSE) -> 0.6 | H67: =VLOOKUP(B67,'[1]26MY_CIV5D_DATA'!B:AS,11,FALSE) -> 458.8 | I67: =VLOOKUP(B67,'[1]26MY_CIV5D_DATA'!B:AS,12,FALSE) -> 0 | J67: =VLOOKUP(B67,'[1]26MY_CIV5D_DATA'!B:AS,13,FALSE) -> 0 | K67: =VLOOKUP($B67,'[1]26MY_CIV5D_DATA'!$B:$AS,14,FALSE) -> 0 | L67: =VLOOKUP(B67,'[1]26MY_CIV5D_DATA'!B:AS,15,FALSE) -> • | M67: =VLOOKUP(B67,'[1]26MY_CIV5D_DATA'!B:AS,16,FALSE) -> • | N67: =VLOOKUP($B67,'[1]26MY_CIV5D_DATA'!$B:$AS,17,FALSE) -> 0 | O67: =VLOOKUP(B67,'[1]26MY_CIV5D_DATA'!B:AS,18,FALSE) -> • | P67: =VLOOKUP(B67,'[1]26MY_CIV5D_DATA'!B:AS,19,FALSE) -> N/A | Q67: =IF(VLOOKUP(B67,'[1]26MY_CIV5D_DATA'!B:AS,20,FALSE)="","",VLOOKUP(B67,'[1]26MY_CIV5D_DATA'!B:AS,20,FALSE))
B68: 08R04-T47-100A | C68: =VLOOKUP(B68,'[1]26MY_CIV5D_DATA'!B:AS,3,FALSE) -> Door Visors - Black | D68: =B68 -> 08R04-T47-100A | E68: =VLOOKUP(B68,'[1]26MY_CIV5D_DATA'!B:AS,9,FALSE) -> 201 | F68: =VLOOKUP(B68,'[1]26MY_CIV5D_DATA'!B:AS,10,FALSE) -> 335 | G68: =VLOOKUP(B68,'[1]26MY_CIV5D_DATA'!B:AS,7,FALSE) -> 0.5 | H68: =VLOOKUP(B68,'[1]26MY_CIV5D_DATA'!B:AS,11,FALSE) -> 419 | I68: =VLOOKUP(B68,'[1]26MY_CIV5D_DATA'!B:AS,12,FALSE) -> 0 | J68: =VLOOKUP(B68,'[1]26MY_CIV5D_DATA'!B:AS,13,FALSE) -> 0 | K68: =VLOOKUP($B68,'[1]26MY_CIV5D_DATA'!$B:$AS,14,FALSE) -> 0 | L68: =VLOOKUP(B68,'[1]26MY_CIV5D_DATA'!B:AS,15,FALSE) -> • | M68: =VLOOKUP(B68,'[1]26MY_CIV5D_DATA'!B:AS,16,FALSE) -> • | N68: =VLOOKUP($B68,'[1]26MY_CIV5D_DATA'!$B:$AS,17,FALSE) -> 0 | O68: =VLOOKUP(B68,'[1]26MY_CIV5D_DATA'!B:AS,18,FALSE) -> • | P68: =VLOOKUP(B68,'[1]26MY_CIV5D_DATA'!B:AS,19,FALSE) -> • | Q68: =IF(VLOOKUP(B68,'[1]26MY_CIV5D_DATA'!B:AS,20,FALSE)="","",VLOOKUP(B68,'[1]26MY_CIV5D_DATA'!B:AS,20,FALSE))
B69: 08P09-T47-300 | C69: =VLOOKUP(B69,'[1]26MY_CIV5D_DATA'!B:AS,3,FALSE) -> Splash Guards - Rear | D69: =B69 -> 08P09-T47-300 | E69: =VLOOKUP(B69,'[1]26MY_CIV5D_DATA'!B:AS,9,FALSE) -> 61 | F69: =VLOOKUP(B69,'[1]26MY_CIV5D_DATA'!B:AS,10,FALSE) -> 102 | G69: =VLOOKUP(B69,'[1]26MY_CIV5D_DATA'!B:AS,7,FALSE) -> 0.4 | H69: =VLOOKUP(B69,'[1]26MY_CIV5D_DATA'!B:AS,11,FALSE) -> 169.2 | I69: =VLOOKUP(B69,'[1]26MY_CIV5D_DATA'!B:AS,12,FALSE) -> 0 | J69: =VLOOKUP(B69,'[1]26MY_CIV5D_DATA'!B:AS,13,FALSE) -> 0 | K69: =VLOOKUP($B69,'[1]26MY_CIV5D_DATA'!$B:$AS,14,FALSE) -> 0 | L69: =VLOOKUP(B69,'[1]26MY_CIV5D_DATA'!B:AS,15,FALSE) -> • | M69: =VLOOKUP(B69,'[1]26MY_CIV5D_DATA'!B:AS,16,FALSE) -> • | N69: =VLOOKUP($B69,'[1]26MY_CIV5D_DATA'!$B:$AS,17,FALSE) -> 0 | O69: =VLOOKUP(B69,'[1]26MY_CIV5D_DATA'!B:AS,18,FALSE) -> • | P69: =VLOOKUP(B69,'[1]26MY_CIV5D_DATA'!B:AS,19,FALSE) -> N/A | Q69: =IF(VLOOKUP(B69,'[1]26MY_CIV5D_DATA'!B:AS,20,FALSE)="","",VLOOKUP(B69,'[1]26MY_CIV5D_DATA'!B:AS,20,FALSE))
B70: 08R01-T20-300 | C70: =VLOOKUP(B70,'[1]26MY_CIV5D_DATA'!B:AS,3,FALSE) -> Moonroof Visor | D70: =B70 -> 08R01-T20-300 | E70: =VLOOKUP(B70,'[1]26MY_CIV5D_DATA'!B:AS,9,FALSE) -> 169 | F70: =VLOOKUP(B70,'[1]26MY_CIV5D_DATA'!B:AS,10,FALSE) -> 282 | G70: =VLOOKUP(B70,'[1]26MY_CIV5D_DATA'!B:AS,7,FALSE) -> 0.3 | H70: =VLOOKUP(B70,'[1]26MY_CIV5D_DATA'!B:AS,11,FALSE) -> 332.4 | I70: =VLOOKUP(B70,'[1]26MY_CIV5D_DATA'!B:AS,12,FALSE) -> 0 | J70: =VLOOKUP(B70,'[1]26MY_CIV5D_DATA'!B:AS,13,FALSE) -> 0 | K70: =VLOOKUP($B70,'[1]26MY_CIV5D_DATA'!$B:$AS,14,FALSE) -> 0 | L70: =VLOOKUP(B70,'[1]26MY_CIV5D_DATA'!B:AS,15,FALSE) -> • | M70: =VLOOKUP(B70,'[1]26MY_CIV5D_DATA'!B:AS,16,FALSE) -> • | N70: =VLOOKUP($B70,'[1]26MY_CIV5D_DATA'!$B:$AS,17,FALSE) -> 0 | O70: =VLOOKUP(B70,'[1]26MY_CIV5D_DATA'!B:AS,18,FALSE) -> • | P70: =VLOOKUP(B70,'[1]26MY_CIV5D_DATA'!B:AS,19,FALSE) -> N/A | Q70: =IF(VLOOKUP(B70,'[1]26MY_CIV5D_DATA'!B:AS,20,FALSE)="","",VLOOKUP(B70,'[1]26MY_CIV5D_DATA'!B:AS,20,FALSE))
B71: 08P01-T47-100 | C71: =VLOOKUP(B71,'[1]26MY_CIV5D_DATA'!B:AS,3,FALSE) -> Rear Bumper Protector | D71: =B71 -> 08P01-T47-100 | E71: =VLOOKUP(B71,'[1]26MY_CIV5D_DATA'!B:AS,9,FALSE) -> 56 | F71: =VLOOKUP(B71,'[1]26MY_CIV5D_DATA'!B:AS,10,FALSE) -> 80 | G71: =VLOOKUP(B71,'[1]26MY_CIV5D_DATA'!B:AS,7,FALSE) -> 0.1 | H71: =VLOOKUP(B71,'[1]26MY_CIV5D_DATA'!B:AS,11,FALSE) -> 96.8 | I71: =VLOOKUP(B71,'[1]26MY_CIV5D_DATA'!B:AS,12,FALSE) -> 0 | J71: =VLOOKUP(B71,'[1]26MY_CIV5D_DATA'!B:AS,13,FALSE) -> 0 | K71: =VLOOKUP($B71,'[1]26MY_CIV5D_DATA'!$B:$AS,14,FALSE) -> 0 | L71: =VLOOKUP(B71,'[1]26MY_CIV5D_DATA'!B:AS,15,FALSE) -> • | M71: =VLOOKUP(B71,'[1]26MY_CIV5D_DATA'!B:AS,16,FALSE) -> • | N71: =VLOOKUP($B71,'[1]26MY_CIV5D_DATA'!$B:$AS,17,FALSE) -> 0 | O71: =VLOOKUP(B71,'[1]26MY_CIV5D_DATA'!B:AS,18,FALSE) -> • | P71: =VLOOKUP(B71,'[1]26MY_CIV5D_DATA'!B:AS,19,FALSE) -> N/A | Q71: =IF(VLOOKUP(B71,'[1]26MY_CIV5D_DATA'!B:AS,20,FALSE)="","",VLOOKUP(B71,'[1]26MY_CIV5D_DATA'!B:AS,20,FALSE))
B72: 08P20-T20-100A | C72: =VLOOKUP(B72,'[1]26MY_CIV5D_DATA'!B:AS,3,FALSE) -> Door Edge Film | D72: =B72 -> 08P20-T20-100A | E72: =VLOOKUP(B72,'[1]26MY_CIV5D_DATA'!B:AS,9,FALSE) -> 65 | F72: =VLOOKUP(B72,'[1]26MY_CIV5D_DATA'!B:AS,10,FALSE) -> 108 | G72: =VLOOKUP(B72,'[1]26MY_CIV5D_DATA'!B:AS,7,FALSE) -> 0.5 | H72: =VLOOKUP(B72,'[1]26MY_CIV5D_DATA'!B:AS,11,FALSE) -> 192 | I72: =VLOOKUP(B72,'[1]26MY_CIV5D_DATA'!B:AS,12,FALSE) -> 0 | J72: =VLOOKUP(B72,'[1]26MY_CIV5D_DATA'!B:AS,13,FALSE) -> 0 | K72: =VLOOKUP($B72,'[1]26MY_CIV5D_DATA'!$B:$AS,14,FALSE) -> 0 | L72: =VLOOKUP(B72,'[1]26MY_CIV5D_DATA'!B:AS,15,FALSE) -> • | M72: =VLOOKUP(B72,'[1]26MY_CIV5D_DATA'!B:AS,16,FALSE) -> • | N72: =VLOOKUP($B72,'[1]26MY_CIV5D_DATA'!$B:$AS,17,FALSE) -> 0 | O72: =VLOOKUP(B72,'[1]26MY_CIV5D_DATA'!B:AS,18,FALSE) -> • | P72: =VLOOKUP(B72,'[1]26MY_CIV5D_DATA'!B:AS,19,FALSE) -> N/A | Q72: =IF(VLOOKUP(B72,'[1]26MY_CIV5D_DATA'!B:AS,20,FALSE)="","",VLOOKUP(B72,'[1]26MY_CIV5D_DATA'!B:AS,20,FALSE)) -> Cannot be installed with Door Edge Guards
B73: 08L02-T47-300 | C73: =VLOOKUP(B73,'[1]26MY_CIV5D_DATA'!B:AS,3,FALSE) -> Roof Rack | D73: =B73 -> 08L02-T47-300 | E73: =VLOOKUP(B73,'[1]26MY_CIV5D_DATA'!B:AS,9,FALSE) -> 485 | F73: =VLOOKUP(B73,'[1]26MY_CIV5D_DATA'!B:AS,10,FALSE) -> 808 | G73: =VLOOKUP(B73,'[1]26MY_CIV5D_DATA'!B:AS,7,FALSE) -> 0.4 | H73: =VLOOKUP(B73,'[1]26MY_CIV5D_DATA'!B:AS,11,FALSE) -> 875.2 | I73: =VLOOKUP(B73,'[1]26MY_CIV5D_DATA'!B:AS,12,FALSE) -> 0 | J73: =VLOOKUP(B73,'[1]26MY_CIV5D_DATA'!B:AS,13,FALSE) -> 0 | K73: =VLOOKUP($B73,'[1]26MY_CIV5D_DATA'!$B:$AS,14,FALSE) -> 0 | L73: =VLOOKUP(B73,'[1]26MY_CIV5D_DATA'!B:AS,15,FALSE) -> • | M73: =VLOOKUP(B73,'[1]26MY_CIV5D_DATA'!B:AS,16,FALSE) -> • | N73: =VLOOKUP($B73,'[1]26MY_CIV5D_DATA'!$B:$AS,17,FALSE) -> 0 | O73: =VLOOKUP(B73,'[1]26MY_CIV5D_DATA'!B:AS,18,FALSE) -> • | P73: =VLOOKUP(B73,'[1]26MY_CIV5D_DATA'!B:AS,19,FALSE) -> • | Q73: =IF(VLOOKUP(B73,'[1]26MY_CIV5D_DATA'!B:AS,20,FALSE)="","",VLOOKUP(B73,'[1]26MY_CIV5D_DATA'!B:AS,20,FALSE))
B74: 08LXX-E09-XXXX | C74: =VLOOKUP(B74,'[1]26MY_CIV5D_DATA'!B:AS,3,FALSE) -> Roof Attachments
B75: 08L20-E09-300A | C75: =VLOOKUP(B75,'[1]26MY_CIV5D_DATA'!B:AS,3,FALSE) -> Roof Box - Midsize | D75: =B75 -> 08L20-E09-300A | E75: =VLOOKUP(B75,'[1]26MY_CIV5D_DATA'!B:AS,9,FALSE) -> 875 | F75: =VLOOKUP(B75,'[1]26MY_CIV5D_DATA'!B:AS,10,FALSE) -> 1458 | G75: =VLOOKUP(B75,'[1]26MY_CIV5D_DATA'!B:AS,7,FALSE) -> 0.2 | H75: =VLOOKUP(B75,'[1]26MY_CIV5D_DATA'!B:AS,11,FALSE) -> 1491.6 | I75: =VLOOKUP(B75,'[1]26MY_CIV5D_DATA'!B:AS,12,FALSE) -> 0 | J75: =VLOOKUP(B75,'[1]26MY_CIV5D_DATA'!B:AS,13,FALSE) -> 0 | K75: =VLOOKUP($B75,'[1]26MY_CIV5D_DATA'!$B:$AS,14,FALSE) -> 0 | L75: =VLOOKUP(B75,'[1]26MY_CIV5D_DATA'!B:AS,15,FALSE) -> • | M75: =VLOOKUP(B75,'[1]26MY_CIV5D_DATA'!B:AS,16,FALSE) -> • | N75: =VLOOKUP($B75,'[1]26MY_CIV5D_DATA'!$B:$AS,17,FALSE) -> 0 | O75: =VLOOKUP(B75,'[1]26MY_CIV5D_DATA'!B:AS,18,FALSE) -> • | P75: =VLOOKUP(B75,'[1]26MY_CIV5D_DATA'!B:AS,19,FALSE) -> • | Q75: =IF(VLOOKUP(B75,'[1]26MY_CIV5D_DATA'!B:AS,20,FALSE)="","",VLOOKUP(B75,'[1]26MY_CIV5D_DATA'!B:AS,20,FALSE))
B76: 08L20-E09-300B | C76: =VLOOKUP(B76,'[1]26MY_CIV5D_DATA'!B:AS,3,FALSE) -> Roof Box - Short | D76: =B76 -> 08L20-E09-300B | E76: =VLOOKUP(B76,'[1]26MY_CIV5D_DATA'!B:AS,9,FALSE) -> 799 | F76: =VLOOKUP(B76,'[1]26MY_CIV5D_DATA'!B:AS,10,FALSE) -> 1332 | G76: =VLOOKUP(B76,'[1]26MY_CIV5D_DATA'!B:AS,7,FALSE) -> 0.2 | H76: =VLOOKUP(B76,'[1]26MY_CIV5D_DATA'!B:AS,11,FALSE) -> 1365.6 | I76: =VLOOKUP(B76,'[1]26MY_CIV5D_DATA'!B:AS,12,FALSE) -> 0 | J76: =VLOOKUP(B76,'[1]26MY_CIV5D_DATA'!B:AS,13,FALSE) -> 0 | K76: =VLOOKUP($B76,'[1]26MY_CIV5D_DATA'!$B:$AS,14,FALSE) -> 0 | L76: =VLOOKUP(B76,'[1]26MY_CIV5D_DATA'!B:AS,15,FALSE) -> • | M76: =VLOOKUP(B76,'[1]26MY_CIV5D_DATA'!B:AS,16,FALSE) -> • | N76: =VLOOKUP($B76,'[1]26MY_CIV5D_DATA'!$B:$AS,17,FALSE) -> 0 | O76: =VLOOKUP(B76,'[1]26MY_CIV5D_DATA'!B:AS,18,FALSE) -> • | P76: =VLOOKUP(B76,'[1]26MY_CIV5D_DATA'!B:AS,19,FALSE) -> • | Q76: =IF(VLOOKUP(B76,'[1]26MY_CIV5D_DATA'!B:AS,20,FALSE)="","",VLOOKUP(B76,'[1]26MY_CIV5D_DATA'!B:AS,20,FALSE))
B77: 08L09-E09-101 | C77: =VLOOKUP(B77,'[1]26MY_CIV5D_DATA'!B:AS,3,FALSE) -> Roof Kayak Attachment | D77: =B77 -> 08L09-E09-101 | E77: =VLOOKUP(B77,'[1]26MY_CIV5D_DATA'!B:AS,9,FALSE) -> 430 | F77: =VLOOKUP(B77,'[1]26MY_CIV5D_DATA'!B:AS,10,FALSE) -> 717 | G77: =VLOOKUP(B77,'[1]26MY_CIV5D_DATA'!B:AS,7,FALSE) -> 0.2 | H77: =VLOOKUP(B77,'[1]26MY_CIV5D_DATA'!B:AS,11,FALSE) -> 750.6 | I77: =VLOOKUP(B77,'[1]26MY_CIV5D_DATA'!B:AS,12,FALSE) -> 0 | J77: =VLOOKUP(B77,'[1]26MY_CIV5D_DATA'!B:AS,13,FALSE) -> 0 | K77: =VLOOKUP($B77,'[1]26MY_CIV5D_DATA'!$B:$AS,14,FALSE) -> 0 | L77: =VLOOKUP(B77,'[1]26MY_CIV5D_DATA'!B:AS,15,FALSE) -> • | M77: =VLOOKUP(B77,'[1]26MY_CIV5D_DATA'!B:AS,16,FALSE) -> • | N77: =VLOOKUP($B77,'[1]26MY_CIV5D_DATA'!$B:$AS,17,FALSE) -> 0 | O77: =VLOOKUP(B77,'[1]26MY_CIV5D_DATA'!B:AS,18,FALSE) -> • | P77: =VLOOKUP(B77,'[1]26MY_CIV5D_DATA'!B:AS,19,FALSE) -> • | Q77: =IF(VLOOKUP(B77,'[1]26MY_CIV5D_DATA'!B:AS,20,FALSE)="","",VLOOKUP(B77,'[1]26MY_CIV5D_DATA'!B:AS,20,FALSE))
B78: 08L03-E09-300C | C78: =VLOOKUP(B78,'[1]26MY_CIV5D_DATA'!B:AS,3,FALSE) -> Roof Ski/Snowboard Attachment | D78: =B78 -> 08L03-E09-300C | E78: =VLOOKUP(B78,'[1]26MY_CIV5D_DATA'!B:AS,9,FALSE) -> 415 | F78: =VLOOKUP(B78,'[1]26MY_CIV5D_DATA'!B:AS,10,FALSE) -> 692 | G78: =VLOOKUP(B78,'[1]26MY_CIV5D_DATA'!B:AS,7,FALSE) -> 0.2 | H78: =VLOOKUP(B78,'[1]26MY_CIV5D_DATA'!B:AS,11,FALSE) -> 725.6 | I78: =VLOOKUP(B78,'[1]26MY_CIV5D_DATA'!B:AS,12,FALSE) -> 0 | J78: =VLOOKUP(B78,'[1]26MY_CIV5D_DATA'!B:AS,13,FALSE) -> 0 | K78: =VLOOKUP($B78,'[1]26MY_CIV5D_DATA'!$B:$AS,14,FALSE) -> 0 | L78: =VLOOKUP(B78,'[1]26MY_CIV5D_DATA'!B:AS,15,FALSE) -> • | M78: =VLOOKUP(B78,'[1]26MY_CIV5D_DATA'!B:AS,16,FALSE) -> • | N78: =VLOOKUP($B78,'[1]26MY_CIV5D_DATA'!$B:$AS,17,FALSE) -> 0 | O78: =VLOOKUP(B78,'[1]26MY_CIV5D_DATA'!B:AS,18,FALSE) -> • | P78: =VLOOKUP(B78,'[1]26MY_CIV5D_DATA'!B:AS,19,FALSE) -> • | Q78: =IF(VLOOKUP(B78,'[1]26MY_CIV5D_DATA'!B:AS,20,FALSE)="","",VLOOKUP(B78,'[1]26MY_CIV5D_DATA'!B:AS,20,FALSE))
B79: 08L05-E09-100 | C79: =VLOOKUP(B79,'[1]26MY_CIV5D_DATA'!B:AS,3,FALSE) -> Roof Surfboard Attachment | D79: =B79 -> 08L05-E09-100 | E79: =VLOOKUP(B79,'[1]26MY_CIV5D_DATA'!B:AS,9,FALSE) -> 207 | F79: =VLOOKUP(B79,'[1]26MY_CIV5D_DATA'!B:AS,10,FALSE) -> 345 | G79: =VLOOKUP(B79,'[1]26MY_CIV5D_DATA'!B:AS,7,FALSE) -> 0.2 | H79: =VLOOKUP(B79,'[1]26MY_CIV5D_DATA'!B:AS,11,FALSE) -> 378.6 | I79: =VLOOKUP(B79,'[1]26MY_CIV5D_DATA'!B:AS,12,FALSE) -> 0 | J79: =VLOOKUP(B79,'[1]26MY_CIV5D_DATA'!B:AS,13,FALSE) -> 0 | K79: =VLOOKUP($B79,'[1]26MY_CIV5D_DATA'!$B:$AS,14,FALSE) -> 0 | L79: =VLOOKUP(B79,'[1]26MY_CIV5D_DATA'!B:AS,15,FALSE) -> • | M79: =VLOOKUP(B79,'[1]26MY_CIV5D_DATA'!B:AS,16,FALSE) -> • | N79: =VLOOKUP($B79,'[1]26MY_CIV5D_DATA'!$B:$AS,17,FALSE) -> 0 | O79: =VLOOKUP(B79,'[1]26MY_CIV5D_DATA'!B:AS,18,FALSE) -> • | P79: =VLOOKUP(B79,'[1]26MY_CIV5D_DATA'!B:AS,19,FALSE) -> • | Q79: =IF(VLOOKUP(B79,'[1]26MY_CIV5D_DATA'!B:AS,20,FALSE)="","",VLOOKUP(B79,'[1]26MY_CIV5D_DATA'!B:AS,20,FALSE))
B80: 08L07-E09-101 | C80: =VLOOKUP(B80,'[1]26MY_CIV5D_DATA'!B:AS,3,FALSE) -> Roof Bike Attachment - Frame Mount | D80: =B80 -> 08L07-E09-101 | E80: =VLOOKUP(B80,'[1]26MY_CIV5D_DATA'!B:AS,9,FALSE) -> 383 | F80: =VLOOKUP(B80,'[1]26MY_CIV5D_DATA'!B:AS,10,FALSE) -> 547 | G80: =VLOOKUP(B80,'[1]26MY_CIV5D_DATA'!B:AS,7,FALSE) -> 0.6 | H80: =VLOOKUP(B80,'[1]26MY_CIV5D_DATA'!B:AS,11,FALSE) -> 647.8 | I80: =VLOOKUP(B80,'[1]26MY_CIV5D_DATA'!B:AS,12,FALSE) -> 0 | J80: =VLOOKUP(B80,'[1]26MY_CIV5D_DATA'!B:AS,13,FALSE) -> 0 | K80: =VLOOKUP($B80,'[1]26MY_CIV5D_DATA'!$B:$AS,14,FALSE) -> 0 | L80: =VLOOKUP(B80,'[1]26MY_CIV5D_DATA'!B:AS,15,FALSE) -> • | M80: =VLOOKUP(B80,'[1]26MY_CIV5D_DATA'!B:AS,16,FALSE) -> • | N80: =VLOOKUP($B80,'[1]26MY_CIV5D_DATA'!$B:$AS,17,FALSE) -> 0 | O80: =VLOOKUP(B80,'[1]26MY_CIV5D_DATA'!B:AS,18,FALSE) -> • | P80: =VLOOKUP(B80,'[1]26MY_CIV5D_DATA'!B:AS,19,FALSE) -> • | Q80: =IF(VLOOKUP(B80,'[1]26MY_CIV5D_DATA'!B:AS,20,FALSE)="","",VLOOKUP(B80,'[1]26MY_CIV5D_DATA'!B:AS,20,FALSE)) -> Only one (1) bike attachment allowed on the Roof Rack. Roof Rack required.
B81: 08L20-E09-101C | C81: =VLOOKUP(B81,'[1]26MY_CIV5D_DATA'!B:AS,3,FALSE) -> Roof Basket | D81: =B81 -> 08L20-E09-101C | E81: =VLOOKUP(B81,'[1]26MY_CIV5D_DATA'!B:AS,9,FALSE) -> 571 | F81: =VLOOKUP(B81,'[1]26MY_CIV5D_DATA'!B:AS,10,FALSE) -> 952 | G81: =VLOOKUP(B81,'[1]26MY_CIV5D_DATA'!B:AS,7,FALSE) -> 0.4 | H81: =VLOOKUP(B81,'[1]26MY_CIV5D_DATA'!B:AS,11,FALSE) -> 1019.2 | I81: =VLOOKUP(B81,'[1]26MY_CIV5D_DATA'!B:AS,12,FALSE) -> 0 | J81: =VLOOKUP(B81,'[1]26MY_CIV5D_DATA'!B:AS,13,FALSE) -> 0 | K81: =VLOOKUP($B81,'[1]26MY_CIV5D_DATA'!$B:$AS,14,FALSE) -> 0 | L81: =VLOOKUP(B81,'[1]26MY_CIV5D_DATA'!B:AS,15,FALSE) -> • | M81: =VLOOKUP(B81,'[1]26MY_CIV5D_DATA'!B:AS,16,FALSE) -> • | N81: =VLOOKUP($B81,'[1]26MY_CIV5D_DATA'!$B:$AS,17,FALSE) -> 0 | O81: =VLOOKUP(B81,'[1]26MY_CIV5D_DATA'!B:AS,18,FALSE) -> • | P81: =VLOOKUP(B81,'[1]26MY_CIV5D_DATA'!B:AS,19,FALSE) -> • | Q81: =IF(VLOOKUP(B81,'[1]26MY_CIV5D_DATA'!B:AS,20,FALSE)="","",VLOOKUP(B81,'[1]26MY_CIV5D_DATA'!B:AS,20,FALSE)) -> Roof Basket Attachment Kit (hardware) and Roof Rack required.
B82: 08L20-E09-100D | C82: =VLOOKUP(B82,'[1]26MY_CIV5D_DATA'!B:AS,3,FALSE) -> Roof Basket Attachment Kit | D82: =B82 -> 08L20-E09-100D | E82: =VLOOKUP(B82,'[1]26MY_CIV5D_DATA'!B:AS,9,FALSE) -> 16 | F82: =VLOOKUP(B82,'[1]26MY_CIV5D_DATA'!B:AS,10,FALSE) -> 26 | G82: =VLOOKUP(B82,'[1]26MY_CIV5D_DATA'!B:AS,7,FALSE) -> 0 | H82: =VLOOKUP(B82,'[1]26MY_CIV5D_DATA'!B:AS,11,FALSE) -> 26 | I82: =VLOOKUP(B82,'[1]26MY_CIV5D_DATA'!B:AS,12,FALSE) -> 0 | J82: =VLOOKUP(B82,'[1]26MY_CIV5D_DATA'!B:AS,13,FALSE) -> 0 | K82: =VLOOKUP($B82,'[1]26MY_CIV5D_DATA'!$B:$AS,14,FALSE) -> 0 | L82: =VLOOKUP(B82,'[1]26MY_CIV5D_DATA'!B:AS,15,FALSE) -> • | M82: =VLOOKUP(B82,'[1]26MY_CIV5D_DATA'!B:AS,16,FALSE) -> • | N82: =VLOOKUP($B82,'[1]26MY_CIV5D_DATA'!$B:$AS,17,FALSE) -> 0 | O82: =VLOOKUP(B82,'[1]26MY_CIV5D_DATA'!B:AS,18,FALSE) -> • | P82: =VLOOKUP(B82,'[1]26MY_CIV5D_DATA'!B:AS,19,FALSE) -> •
B83: 08F01-T20-XXXX | C83: =VLOOKUP(B83,'[1]26MY_CIV5D_DATA'!B:AS,3,FALSE) -> Front Underbody Spoiler
B84: 08F01-T20-130A | C84: =VLOOKUP(B84,'[1]26MY_CIV5D_DATA'!B:AS,3,FALSE) -> Platinum White Pearl (NH-883P) | D84: =B84 -> 08F01-T20-130A | E84: =VLOOKUP(B84,'[1]26MY_CIV5D_DATA'!B:AS,9,FALSE) -> 255 | F84: =VLOOKUP(B84,'[1]26MY_CIV5D_DATA'!B:AS,10,FALSE) -> 425 | G84: =VLOOKUP(B84,'[1]26MY_CIV5D_DATA'!B:AS,7,FALSE) -> 1 | H84: =VLOOKUP(B84,'[1]26MY_CIV5D_DATA'!B:AS,11,FALSE) -> 593 | I84: =VLOOKUP(B84,'[1]26MY_CIV5D_DATA'!B:AS,12,FALSE) -> 0 | J84: =VLOOKUP(B84,'[1]26MY_CIV5D_DATA'!B:AS,13,FALSE) -> 0 | K84: =VLOOKUP($B84,'[1]26MY_CIV5D_DATA'!$B:$AS,14,FALSE) -> 0 | L84: =VLOOKUP(B84,'[1]26MY_CIV5D_DATA'!B:AS,15,FALSE) -> • | M84: =VLOOKUP(B84,'[1]26MY_CIV5D_DATA'!B:AS,16,FALSE) -> • | N84: =VLOOKUP($B84,'[1]26MY_CIV5D_DATA'!$B:$AS,17,FALSE) -> 0 | O84: =VLOOKUP(B84,'[1]26MY_CIV5D_DATA'!B:AS,18,FALSE) -> • | P84: =VLOOKUP(B84,'[1]26MY_CIV5D_DATA'!B:AS,19,FALSE) -> N/A | Q84: =IF(VLOOKUP(B84,'[1]26MY_CIV5D_DATA'!B:AS,20,FALSE)="","",VLOOKUP(B84,'[1]26MY_CIV5D_DATA'!B:AS,20,FALSE))
B85: 08F01-T20-1Z0A | C85: =VLOOKUP(B85,'[1]26MY_CIV5D_DATA'!B:AS,3,FALSE) -> Solar Reflection Silver (NH-932M) | D85: =B85 -> 08F01-T20-1Z0A | E85: =VLOOKUP(B85,'[1]26MY_CIV5D_DATA'!B:AS,9,FALSE) -> 255 | F85: =VLOOKUP(B85,'[1]26MY_CIV5D_DATA'!B:AS,10,FALSE) -> 425 | G85: =VLOOKUP(B85,'[1]26MY_CIV5D_DATA'!B:AS,7,FALSE) -> 1 | H85: =VLOOKUP(B85,'[1]26MY_CIV5D_DATA'!B:AS,11,FALSE) -> 593 | I85: =VLOOKUP(B85,'[1]26MY_CIV5D_DATA'!B:AS,12,FALSE) -> 0 | J85: =VLOOKUP(B85,'[1]26MY_CIV5D_DATA'!B:AS,13,FALSE) -> 0 | K85: =VLOOKUP($B85,'[1]26MY_CIV5D_DATA'!$B:$AS,14,FALSE) -> 0 | L85: =VLOOKUP(B85,'[1]26MY_CIV5D_DATA'!B:AS,15,FALSE) -> • | M85: =VLOOKUP(B85,'[1]26MY_CIV5D_DATA'!B:AS,16,FALSE) -> • | N85: =VLOOKUP($B85,'[1]26MY_CIV5D_DATA'!$B:$AS,17,FALSE) -> 0 | O85: =VLOOKUP(B85,'[1]26MY_CIV5D_DATA'!B:AS,18,FALSE) -> • | P85: =VLOOKUP(B85,'[1]26MY_CIV5D_DATA'!B:AS,19,FALSE) -> N/A
B86: 08F01-T20-170A | C86: =VLOOKUP(B86,'[1]26MY_CIV5D_DATA'!B:AS,3,FALSE) -> Meteoroid Gray Pearl (NH-904M) | D86: =B86 -> 08F01-T20-170A | E86: =VLOOKUP(B86,'[1]26MY_CIV5D_DATA'!B:AS,9,FALSE) -> 255 | F86: =VLOOKUP(B86,'[1]26MY_CIV5D_DATA'!B:AS,10,FALSE) -> 425 | G86: =VLOOKUP(B86,'[1]26MY_CIV5D_DATA'!B:AS,7,FALSE) -> 1 | H86: =VLOOKUP(B86,'[1]26MY_CIV5D_DATA'!B:AS,11,FALSE) -> 593 | I86: =VLOOKUP(B86,'[1]26MY_CIV5D_DATA'!B:AS,12,FALSE) -> 0 | J86: =VLOOKUP(B86,'[1]26MY_CIV5D_DATA'!B:AS,13,FALSE) -> 0 | K86: =VLOOKUP($B86,'[1]26MY_CIV5D_DATA'!$B:$AS,14,FALSE) -> 0 | L86: =VLOOKUP(B86,'[1]26MY_CIV5D_DATA'!B:AS,15,FALSE) -> N/A | M86: =VLOOKUP(B86,'[1]26MY_CIV5D_DATA'!B:AS,16,FALSE) -> • | N86: =VLOOKUP($B86,'[1]26MY_CIV5D_DATA'!$B:$AS,17,FALSE) -> 0 | O86: =VLOOKUP(B86,'[1]26MY_CIV5D_DATA'!B:AS,18,FALSE) -> N/A | P86: =VLOOKUP(B86,'[1]26MY_CIV5D_DATA'!B:AS,19,FALSE) -> N/A
B87: 08F01-T20-180A | C87: =VLOOKUP(B87,'[1]26MY_CIV5D_DATA'!B:AS,3,FALSE) -> Crystal Black Pearl (NH-731P) | D87: =B87 -> 08F01-T20-180A | E87: =VLOOKUP(B87,'[1]26MY_CIV5D_DATA'!B:AS,9,FALSE) -> 255 | F87: =VLOOKUP(B87,'[1]26MY_CIV5D_DATA'!B:AS,10,FALSE) -> 425 | G87: =VLOOKUP(B87,'[1]26MY_CIV5D_DATA'!B:AS,7,FALSE) -> 1 | H87: =VLOOKUP(B87,'[1]26MY_CIV5D_DATA'!B:AS,11,FALSE) -> 593 | I87: =VLOOKUP(B87,'[1]26MY_CIV5D_DATA'!B:AS,12,FALSE) -> 0 | J87: =VLOOKUP(B87,'[1]26MY_CIV5D_DATA'!B:AS,13,FALSE) -> 0 | K87: =VLOOKUP($B87,'[1]26MY_CIV5D_DATA'!$B:$AS,14,FALSE) -> 0 | L87: =VLOOKUP(B87,'[1]26MY_CIV5D_DATA'!B:AS,15,FALSE) -> • | M87: =VLOOKUP(B87,'[1]26MY_CIV5D_DATA'!B:AS,16,FALSE) -> • | N87: =VLOOKUP($B87,'[1]26MY_CIV5D_DATA'!$B:$AS,17,FALSE) -> 0 | O87: =VLOOKUP(B87,'[1]26MY_CIV5D_DATA'!B:AS,18,FALSE) -> • | P87: =VLOOKUP(B87,'[1]26MY_CIV5D_DATA'!B:AS,19,FALSE) -> N/A
B88: 08F01-T20-190A | C88: =VLOOKUP(B88,'[1]26MY_CIV5D_DATA'!B:AS,3,FALSE) -> Rallye Red (R-513) | D88: =B88 -> 08F01-T20-190A | E88: =VLOOKUP(B88,'[1]26MY_CIV5D_DATA'!B:AS,9,FALSE) -> 255 | F88: =VLOOKUP(B88,'[1]26MY_CIV5D_DATA'!B:AS,10,FALSE) -> 425 | G88: =VLOOKUP(B88,'[1]26MY_CIV5D_DATA'!B:AS,7,FALSE) -> 1 | H88: =VLOOKUP(B88,'[1]26MY_CIV5D_DATA'!B:AS,11,FALSE) -> 593 | I88: =VLOOKUP(B88,'[1]26MY_CIV5D_DATA'!B:AS,12,FALSE) -> 0 | J88: =VLOOKUP(B88,'[1]26MY_CIV5D_DATA'!B:AS,13,FALSE) -> 0 | K88: =VLOOKUP($B88,'[1]26MY_CIV5D_DATA'!$B:$AS,14,FALSE) -> 0 | L88: =VLOOKUP(B88,'[1]26MY_CIV5D_DATA'!B:AS,15,FALSE) -> N/A | M88: =VLOOKUP(B88,'[1]26MY_CIV5D_DATA'!B:AS,16,FALSE) -> • | N88: =VLOOKUP($B88,'[1]26MY_CIV5D_DATA'!$B:$AS,17,FALSE) -> 0 | O88: =VLOOKUP(B88,'[1]26MY_CIV5D_DATA'!B:AS,18,FALSE) -> • | P88: =VLOOKUP(B88,'[1]26MY_CIV5D_DATA'!B:AS,19,FALSE) -> N/A
B89: 08F01-T20-1U0A | C89: =VLOOKUP(B89,'[1]26MY_CIV5D_DATA'!B:AS,3,FALSE) -> Boost Blue Pearl (B-637P) | D89: =B89 -> 08F01-T20-1U0A | E89: =VLOOKUP(B89,'[1]26MY_CIV5D_DATA'!B:AS,9,FALSE) -> 255 | F89: =VLOOKUP(B89,'[1]26MY_CIV5D_DATA'!B:AS,10,FALSE) -> 425 | G89: =VLOOKUP(B89,'[1]26MY_CIV5D_DATA'!B:AS,7,FALSE) -> 1 | H89: =VLOOKUP(B89,'[1]26MY_CIV5D_DATA'!B:AS,11,FALSE) -> 593 | I89: =VLOOKUP(B89,'[1]26MY_CIV5D_DATA'!B:AS,12,FALSE) -> 0 | J89: =VLOOKUP(B89,'[1]26MY_CIV5D_DATA'!B:AS,13,FALSE) -> 0 | K89: =VLOOKUP($B89,'[1]26MY_CIV5D_DATA'!$B:$AS,14,FALSE) -> 0 | L89: =VLOOKUP(B89,'[1]26MY_CIV5D_DATA'!B:AS,15,FALSE) -> N/A | M89: =VLOOKUP(B89,'[1]26MY_CIV5D_DATA'!B:AS,16,FALSE) -> N/A | N89: =VLOOKUP($B89,'[1]26MY_CIV5D_DATA'!$B:$AS,17,FALSE) -> 0 | O89: =VLOOKUP(B89,'[1]26MY_CIV5D_DATA'!B:AS,18,FALSE) -> • | P89: =VLOOKUP(B89,'[1]26MY_CIV5D_DATA'!B:AS,19,FALSE) -> N/A
B90: 08F02-T47-XXX | C90: =VLOOKUP(B90,'[1]26MY_CIV5D_DATA'!B:AS,3,FALSE) -> Tailgate Spoiler, HPD
B91: 08F02-T47-130 | C91: =VLOOKUP(B91,'[1]26MY_CIV5D_DATA'!B:AS,3,FALSE) -> Platinum White Pearl (NH-883P) | D91: =B91 -> 08F02-T47-130 | E91: =VLOOKUP(B91,'[1]26MY_CIV5D_DATA'!B:AS,9,FALSE) -> 460 | F91: =VLOOKUP(B91,'[1]26MY_CIV5D_DATA'!B:AS,10,FALSE) -> 767 | G91: =VLOOKUP(B91,'[1]26MY_CIV5D_DATA'!B:AS,7,FALSE) -> 1.2 | H91: =VLOOKUP(B91,'[1]26MY_CIV5D_DATA'!B:AS,11,FALSE) -> 968.6 | I91: =VLOOKUP(B91,'[1]26MY_CIV5D_DATA'!B:AS,12,FALSE) -> 0 | J91: =VLOOKUP(B91,'[1]26MY_CIV5D_DATA'!B:AS,13,FALSE) -> 0 | K91: =VLOOKUP($B91,'[1]26MY_CIV5D_DATA'!$B:$AS,14,FALSE) -> 0 | L91: =VLOOKUP(B91,'[1]26MY_CIV5D_DATA'!B:AS,15,FALSE) -> • | M91: =VLOOKUP(B91,'[1]26MY_CIV5D_DATA'!B:AS,16,FALSE) -> • | N91: =VLOOKUP($B91,'[1]26MY_CIV5D_DATA'!$B:$AS,17,FALSE) -> 0 | O91: =VLOOKUP(B91,'[1]26MY_CIV5D_DATA'!B:AS,18,FALSE) -> • | P91: =VLOOKUP(B91,'[1]26MY_CIV5D_DATA'!B:AS,19,FALSE) -> N/A | Q91: =IF(VLOOKUP(B91,'[1]26MY_CIV5D_DATA'!B:AS,20,FALSE)="","",VLOOKUP(B91,'[1]26MY_CIV5D_DATA'!B:AS,20,FALSE))
B92: 08F02-T47-1Z0 | C92: =VLOOKUP(B92,'[1]26MY_CIV5D_DATA'!B:AS,3,FALSE) -> Solar Reflection Silver (NH-932M) | D92: =B92 -> 08F02-T47-1Z0 | E92: =VLOOKUP(B92,'[1]26MY_CIV5D_DATA'!B:AS,9,FALSE) -> 460 | F92: =VLOOKUP(B92,'[1]26MY_CIV5D_DATA'!B:AS,10,FALSE) -> 767 | G92: =VLOOKUP(B92,'[1]26MY_CIV5D_DATA'!B:AS,7,FALSE) -> 1.2 | H92: =VLOOKUP(B92,'[1]26MY_CIV5D_DATA'!B:AS,11,FALSE) -> 968.6 | I92: =VLOOKUP(B92,'[1]26MY_CIV5D_DATA'!B:AS,12,FALSE) -> 0 | J92: =VLOOKUP(B92,'[1]26MY_CIV5D_DATA'!B:AS,13,FALSE) -> 0 | K92: =VLOOKUP($B92,'[1]26MY_CIV5D_DATA'!$B:$AS,14,FALSE) -> 0 | L92: =VLOOKUP(B92,'[1]26MY_CIV5D_DATA'!B:AS,15,FALSE) -> • | M92: =VLOOKUP(B92,'[1]26MY_CIV5D_DATA'!B:AS,16,FALSE) -> N/A | N92: =VLOOKUP($B92,'[1]26MY_CIV5D_DATA'!$B:$AS,17,FALSE) -> 0 | O92: =VLOOKUP(B92,'[1]26MY_CIV5D_DATA'!B:AS,18,FALSE) -> N/A | P92: =VLOOKUP(B92,'[1]26MY_CIV5D_DATA'!B:AS,19,FALSE) -> N/A
B93: 08F02-T47-170 | C93: =VLOOKUP(B93,'[1]26MY_CIV5D_DATA'!B:AS,3,FALSE) -> Meteriod Gray Pearl (NH-904M) | D93: =B93 -> 08F02-T47-170 | E93: =VLOOKUP(B93,'[1]26MY_CIV5D_DATA'!B:AS,9,FALSE) -> 460 | F93: =VLOOKUP(B93,'[1]26MY_CIV5D_DATA'!B:AS,10,FALSE) -> 767 | G93: =VLOOKUP(B93,'[1]26MY_CIV5D_DATA'!B:AS,7,FALSE) -> 1.2 | H93: =VLOOKUP(B93,'[1]26MY_CIV5D_DATA'!B:AS,11,FALSE) -> 968.6 | I93: =VLOOKUP(B93,'[1]26MY_CIV5D_DATA'!B:AS,12,FALSE) -> 0 | J93: =VLOOKUP(B93,'[1]26MY_CIV5D_DATA'!B:AS,13,FALSE) -> 0 | K93: =VLOOKUP($B93,'[1]26MY_CIV5D_DATA'!$B:$AS,14,FALSE) -> 0 | L93: =VLOOKUP(B93,'[1]26MY_CIV5D_DATA'!B:AS,15,FALSE) -> N/A | M93: =VLOOKUP(B93,'[1]26MY_CIV5D_DATA'!B:AS,16,FALSE) -> • | N93: =VLOOKUP($B93,'[1]26MY_CIV5D_DATA'!$B:$AS,17,FALSE) -> 0 | O93: =VLOOKUP(B93,'[1]26MY_CIV5D_DATA'!B:AS,18,FALSE) -> N/A | P93: =VLOOKUP(B93,'[1]26MY_CIV5D_DATA'!B:AS,19,FALSE) -> N/A
B94: 08F02-T47-180 | C94: =VLOOKUP(B94,'[1]26MY_CIV5D_DATA'!B:AS,3,FALSE) -> Crystal Black Pearl (NH-731P) | D94: =B94 -> 08F02-T47-180 | E94: =VLOOKUP(B94,'[1]26MY_CIV5D_DATA'!B:AS,9,FALSE) -> 460 | F94: =VLOOKUP(B94,'[1]26MY_CIV5D_DATA'!B:AS,10,FALSE) -> 767 | G94: =VLOOKUP(B94,'[1]26MY_CIV5D_DATA'!B:AS,7,FALSE) -> 1.2 | H94: =VLOOKUP(B94,'[1]26MY_CIV5D_DATA'!B:AS,11,FALSE) -> 968.6 | I94: =VLOOKUP(B94,'[1]26MY_CIV5D_DATA'!B:AS,12,FALSE) -> 0 | J94: =VLOOKUP(B94,'[1]26MY_CIV5D_DATA'!B:AS,13,FALSE) -> 0 | K94: =VLOOKUP($B94,'[1]26MY_CIV5D_DATA'!$B:$AS,14,FALSE) -> 0 | L94: =VLOOKUP(B94,'[1]26MY_CIV5D_DATA'!B:AS,15,FALSE) -> • | M94: =VLOOKUP(B94,'[1]26MY_CIV5D_DATA'!B:AS,16,FALSE) -> • | N94: =VLOOKUP($B94,'[1]26MY_CIV5D_DATA'!$B:$AS,17,FALSE) -> 0 | O94: =VLOOKUP(B94,'[1]26MY_CIV5D_DATA'!B:AS,18,FALSE) -> • | P94: =VLOOKUP(B94,'[1]26MY_CIV5D_DATA'!B:AS,19,FALSE) -> N/A
B95: 08F02-T47-190 | C95: =VLOOKUP(B95,'[1]26MY_CIV5D_DATA'!B:AS,3,FALSE) -> Rallye Red (R-513) | D95: =B95 -> 08F02-T47-190 | E95: =VLOOKUP(B95,'[1]26MY_CIV5D_DATA'!B:AS,9,FALSE) -> 460 | F95: =VLOOKUP(B95,'[1]26MY_CIV5D_DATA'!B:AS,10,FALSE) -> 767 | G95: =VLOOKUP(B95,'[1]26MY_CIV5D_DATA'!B:AS,7,FALSE) -> 1.2 | H95: =VLOOKUP(B95,'[1]26MY_CIV5D_DATA'!B:AS,11,FALSE) -> 968.6 | I95: =VLOOKUP(B95,'[1]26MY_CIV5D_DATA'!B:AS,12,FALSE) -> 0 | J95: =VLOOKUP(B95,'[1]26MY_CIV5D_DATA'!B:AS,13,FALSE) -> 0 | K95: =VLOOKUP($B95,'[1]26MY_CIV5D_DATA'!$B:$AS,14,FALSE) -> 0 | L95: =VLOOKUP(B95,'[1]26MY_CIV5D_DATA'!B:AS,15,FALSE) -> N/A | M95: =VLOOKUP(B95,'[1]26MY_CIV5D_DATA'!B:AS,16,FALSE) -> • | N95: =VLOOKUP($B95,'[1]26MY_CIV5D_DATA'!$B:$AS,17,FALSE) -> 0 | O95: =VLOOKUP(B95,'[1]26MY_CIV5D_DATA'!B:AS,18,FALSE) -> • | P95: =VLOOKUP(B95,'[1]26MY_CIV5D_DATA'!B:AS,19,FALSE) -> N/A
B96: 08F02-T47-1U0 | C96: =VLOOKUP(B96,'[1]26MY_CIV5D_DATA'!B:AS,3,FALSE) -> Boost Blue Pearl (B-637P) | D96: =B96 -> 08F02-T47-1U0 | E96: =VLOOKUP(B96,'[1]26MY_CIV5D_DATA'!B:AS,9,FALSE) -> 460 | F96: =VLOOKUP(B96,'[1]26MY_CIV5D_DATA'!B:AS,10,FALSE) -> 767 | G96: =VLOOKUP(B96,'[1]26MY_CIV5D_DATA'!B:AS,7,FALSE) -> 1.2 | H96: =VLOOKUP(B96,'[1]26MY_CIV5D_DATA'!B:AS,11,FALSE) -> 968.6 | I96: =VLOOKUP(B96,'[1]26MY_CIV5D_DATA'!B:AS,12,FALSE) -> 0 | J96: =VLOOKUP(B96,'[1]26MY_CIV5D_DATA'!B:AS,13,FALSE) -> 0 | K96: =VLOOKUP($B96,'[1]26MY_CIV5D_DATA'!$B:$AS,14,FALSE) -> 0 | L96: =VLOOKUP(B96,'[1]26MY_CIV5D_DATA'!B:AS,15,FALSE) -> N/A | M96: =VLOOKUP(B96,'[1]26MY_CIV5D_DATA'!B:AS,16,FALSE) -> N/A | N96: =VLOOKUP($B96,'[1]26MY_CIV5D_DATA'!$B:$AS,17,FALSE) -> 0 | O96: =VLOOKUP(B96,'[1]26MY_CIV5D_DATA'!B:AS,18,FALSE) -> • | P96: =VLOOKUP(B96,'[1]26MY_CIV5D_DATA'!B:AS,19,FALSE) -> N/A
B97: 08P05-T20-XXXX | C97: =VLOOKUP(B97,'[1]26MY_CIV5D_DATA'!B:AS,3,FALSE) -> Body Side Moulding
B98: 08P05-T20-130 | C98: =VLOOKUP(B98,'[1]26MY_CIV5D_DATA'!B:AS,3,FALSE) -> Platinum White Pearl (NH-883P) | D98: =B98 -> 08P05-T20-130 | E98: =VLOOKUP(B98,'[1]26MY_CIV5D_DATA'!B:AS,9,FALSE) -> 209 | F98: =VLOOKUP(B98,'[1]26MY_CIV5D_DATA'!B:AS,10,FALSE) -> 348 | G98: =VLOOKUP(B98,'[1]26MY_CIV5D_DATA'!B:AS,7,FALSE) -> 0.4 | H98: =VLOOKUP(B98,'[1]26MY_CIV5D_DATA'!B:AS,11,FALSE) -> 415.2 | I98: =VLOOKUP(B98,'[1]26MY_CIV5D_DATA'!B:AS,12,FALSE) -> 0 | J98: =VLOOKUP(B98,'[1]26MY_CIV5D_DATA'!B:AS,13,FALSE) -> 0 | K98: =VLOOKUP($B98,'[1]26MY_CIV5D_DATA'!$B:$AS,14,FALSE) -> 0 | L98: =VLOOKUP(B98,'[1]26MY_CIV5D_DATA'!B:AS,15,FALSE) -> • | M98: =VLOOKUP(B98,'[1]26MY_CIV5D_DATA'!B:AS,16,FALSE) -> • | N98: =VLOOKUP($B98,'[1]26MY_CIV5D_DATA'!$B:$AS,17,FALSE) -> 0 | O98: =VLOOKUP(B98,'[1]26MY_CIV5D_DATA'!B:AS,18,FALSE) -> • | P98: =VLOOKUP(B98,'[1]26MY_CIV5D_DATA'!B:AS,19,FALSE) -> N/A | Q98: =IF(VLOOKUP(B98,'[1]26MY_CIV5D_DATA'!B:AS,20,FALSE)="","",VLOOKUP(B98,'[1]26MY_CIV5D_DATA'!B:AS,20,FALSE))
B99: 08P05-T20-1Z0 | C99: =VLOOKUP(B99,'[1]26MY_CIV5D_DATA'!B:AS,3,FALSE) -> Solar Reflection Silver (NH-932M) | D99: =B99 -> 08P05-T20-1Z0 | E99: =VLOOKUP(B99,'[1]26MY_CIV5D_DATA'!B:AS,9,FALSE) -> 209 | F99: =VLOOKUP(B99,'[1]26MY_CIV5D_DATA'!B:AS,10,FALSE) -> 348 | G99: =VLOOKUP(B99,'[1]26MY_CIV5D_DATA'!B:AS,7,FALSE) -> 0.4 | H99: =VLOOKUP(B99,'[1]26MY_CIV5D_DATA'!B:AS,11,FALSE) -> 415.2 | I99: =VLOOKUP(B99,'[1]26MY_CIV5D_DATA'!B:AS,12,FALSE) -> 0 | J99: =VLOOKUP(B99,'[1]26MY_CIV5D_DATA'!B:AS,13,FALSE) -> 0 | K99: =VLOOKUP($B99,'[1]26MY_CIV5D_DATA'!$B:$AS,14,FALSE) -> 0 | L99: =VLOOKUP(B99,'[1]26MY_CIV5D_DATA'!B:AS,15,FALSE) -> • | M99: =VLOOKUP(B99,'[1]26MY_CIV5D_DATA'!B:AS,16,FALSE) -> N/A | N99: =VLOOKUP($B99,'[1]26MY_CIV5D_DATA'!$B:$AS,17,FALSE) -> 0 | O99: =VLOOKUP(B99,'[1]26MY_CIV5D_DATA'!B:AS,18,FALSE) -> N/A | P99: =VLOOKUP(B99,'[1]26MY_CIV5D_DATA'!B:AS,19,FALSE) -> N/A
B100: 08P05-T20-170 | C100: =VLOOKUP(B100,'[1]26MY_CIV5D_DATA'!B:AS,3,FALSE) -> Meteoroid Gray Pearl (NH-904M) | D100: =B100 -> 08P05-T20-170 | E100: =VLOOKUP(B100,'[1]26MY_CIV5D_DATA'!B:AS,9,FALSE) -> 209 | F100: =VLOOKUP(B100,'[1]26MY_CIV5D_DATA'!B:AS,10,FALSE) -> 348 | G100: =VLOOKUP(B100,'[1]26MY_CIV5D_DATA'!B:AS,7,FALSE) -> 0.4 | H100: =VLOOKUP(B100,'[1]26MY_CIV5D_DATA'!B:AS,11,FALSE) -> 415.2 | I100: =VLOOKUP(B100,'[1]26MY_CIV5D_DATA'!B:AS,12,FALSE) -> 0 | J100: =VLOOKUP(B100,'[1]26MY_CIV5D_DATA'!B:AS,13,FALSE) -> 0 | K100: =VLOOKUP($B100,'[1]26MY_CIV5D_DATA'!$B:$AS,14,FALSE) -> 0 | L100: =VLOOKUP(B100,'[1]26MY_CIV5D_DATA'!B:AS,15,FALSE) -> N/A | M100: =VLOOKUP(B100,'[1]26MY_CIV5D_DATA'!B:AS,16,FALSE) -> • | N100: =VLOOKUP($B100,'[1]26MY_CIV5D_DATA'!$B:$AS,17,FALSE) -> 0 | O100: =VLOOKUP(B100,'[1]26MY_CIV5D_DATA'!B:AS,18,FALSE) -> N/A | P100: =VLOOKUP(B100,'[1]26MY_CIV5D_DATA'!B:AS,19,FALSE) -> N/A
B101: 08P05-T20-180 | C101: =VLOOKUP(B101,'[1]26MY_CIV5D_DATA'!B:AS,3,FALSE) -> Crystal Black Pearl (NH-731P) | D101: =B101 -> 08P05-T20-180 | E101: =VLOOKUP(B101,'[1]26MY_CIV5D_DATA'!B:AS,9,FALSE) -> 209 | F101: =VLOOKUP(B101,'[1]26MY_CIV5D_DATA'!B:AS,10,FALSE) -> 348 | G101: =VLOOKUP(B101,'[1]26MY_CIV5D_DATA'!B:AS,7,FALSE) -> 0.4 | H101: =VLOOKUP(B101,'[1]26MY_CIV5D_DATA'!B:AS,11,FALSE) -> 415.2 | I101: =VLOOKUP(B101,'[1]26MY_CIV5D_DATA'!B:AS,12,FALSE) -> 0 | J101: =VLOOKUP(B101,'[1]26MY_CIV5D_DATA'!B:AS,13,FALSE) -> 0 | K101: =VLOOKUP($B101,'[1]26MY_CIV5D_DATA'!$B:$AS,14,FALSE) -> 0 | L101: =VLOOKUP(B101,'[1]26MY_CIV5D_DATA'!B:AS,15,FALSE) -> • | M101: =VLOOKUP(B101,'[1]26MY_CIV5D_DATA'!B:AS,16,FALSE) -> • | N101: =VLOOKUP($B101,'[1]26MY_CIV5D_DATA'!$B:$AS,17,FALSE) -> 0 | O101: =VLOOKUP(B101,'[1]26MY_CIV5D_DATA'!B:AS,18,FALSE) -> • | P101: =VLOOKUP(B101,'[1]26MY_CIV5D_DATA'!B:AS,19,FALSE) -> N/A
B102: 08P05-T20-190 | C102: =VLOOKUP(B102,'[1]26MY_CIV5D_DATA'!B:AS,3,FALSE) -> Rallye Red (R-513) | D102: =B102 -> 08P05-T20-190 | E102: =VLOOKUP(B102,'[1]26MY_CIV5D_DATA'!B:AS,9,FALSE) -> 209 | F102: =VLOOKUP(B102,'[1]26MY_CIV5D_DATA'!B:AS,10,FALSE) -> 348 | G102: =VLOOKUP(B102,'[1]26MY_CIV5D_DATA'!B:AS,7,FALSE) -> 0.4 | H102: =VLOOKUP(B102,'[1]26MY_CIV5D_DATA'!B:AS,11,FALSE) -> 415.2 | I102: =VLOOKUP(B102,'[1]26MY_CIV5D_DATA'!B:AS,12,FALSE) -> 0 | J102: =VLOOKUP(B102,'[1]26MY_CIV5D_DATA'!B:AS,13,FALSE) -> 0 | K102: =VLOOKUP($B102,'[1]26MY_CIV5D_DATA'!$B:$AS,14,FALSE) -> 0 | L102: =VLOOKUP(B102,'[1]26MY_CIV5D_DATA'!B:AS,15,FALSE) -> N/A | M102: =VLOOKUP(B102,'[1]26MY_CIV5D_DATA'!B:AS,16,FALSE) -> • | N102: =VLOOKUP($B102,'[1]26MY_CIV5D_DATA'!$B:$AS,17,FALSE) -> 0 | O102: =VLOOKUP(B102,'[1]26MY_CIV5D_DATA'!B:AS,18,FALSE) -> • | P102: =VLOOKUP(B102,'[1]26MY_CIV5D_DATA'!B:AS,19,FALSE) -> N/A
B103: 08P05-T20-1U0 | C103: =VLOOKUP(B103,'[1]26MY_CIV5D_DATA'!B:AS,3,FALSE) -> Boost Blue Pearl (B-637P) | D103: =B103 -> 08P05-T20-1U0 | E103: =VLOOKUP(B103,'[1]26MY_CIV5D_DATA'!B:AS,9,FALSE) -> 209 | F103: =VLOOKUP(B103,'[1]26MY_CIV5D_DATA'!B:AS,10,FALSE) -> 348 | G103: =VLOOKUP(B103,'[1]26MY_CIV5D_DATA'!B:AS,7,FALSE) -> 0.4 | H103: =VLOOKUP(B103,'[1]26MY_CIV5D_DATA'!B:AS,11,FALSE) -> 415.2 | I103: =VLOOKUP(B103,'[1]26MY_CIV5D_DATA'!B:AS,12,FALSE) -> 0 | J103: =VLOOKUP(B103,'[1]26MY_CIV5D_DATA'!B:AS,13,FALSE) -> 0 | K103: =VLOOKUP($B103,'[1]26MY_CIV5D_DATA'!$B:$AS,14,FALSE) -> 0 | L103: =VLOOKUP(B103,'[1]26MY_CIV5D_DATA'!B:AS,15,FALSE) -> N/A | M103: =VLOOKUP(B103,'[1]26MY_CIV5D_DATA'!B:AS,16,FALSE) -> N/A | N103: =VLOOKUP($B103,'[1]26MY_CIV5D_DATA'!$B:$AS,17,FALSE) -> 0 | O103: =VLOOKUP(B103,'[1]26MY_CIV5D_DATA'!B:AS,18,FALSE) -> • | P103: =VLOOKUP(B103,'[1]26MY_CIV5D_DATA'!B:AS,19,FALSE) -> N/A
B104: 08P20-T20-XXXX | C104: =VLOOKUP(B104,'[1]26MY_CIV5D_DATA'!B:AS,3,FALSE) -> Door Edge Guards
B105: 08P20-T20-130 | C105: =VLOOKUP(B105,'[1]26MY_CIV5D_DATA'!B:AS,3,FALSE) -> Platinum White Pearl (NH-883P) | D105: =B105 -> 08P20-T20-130 | E105: =VLOOKUP(B105,'[1]26MY_CIV5D_DATA'!B:AS,9,FALSE) -> 136 | F105: =VLOOKUP(B105,'[1]26MY_CIV5D_DATA'!B:AS,10,FALSE) -> 194 | G105: =VLOOKUP(B105,'[1]26MY_CIV5D_DATA'!B:AS,7,FALSE) -> 0.4 | H105: =VLOOKUP(B105,'[1]26MY_CIV5D_DATA'!B:AS,11,FALSE) -> 261.2 | I105: =VLOOKUP(B105,'[1]26MY_CIV5D_DATA'!B:AS,12,FALSE) -> 0 | J105: =VLOOKUP(B105,'[1]26MY_CIV5D_DATA'!B:AS,13,FALSE) -> 0 | K105: =VLOOKUP($B105,'[1]26MY_CIV5D_DATA'!$B:$AS,14,FALSE) -> 0 | L105: =VLOOKUP(B105,'[1]26MY_CIV5D_DATA'!B:AS,15,FALSE) -> • | M105: =VLOOKUP(B105,'[1]26MY_CIV5D_DATA'!B:AS,16,FALSE) -> • | N105: =VLOOKUP($B105,'[1]26MY_CIV5D_DATA'!$B:$AS,17,FALSE) -> 0 | O105: =VLOOKUP(B105,'[1]26MY_CIV5D_DATA'!B:AS,18,FALSE) -> • | P105: =VLOOKUP(B105,'[1]26MY_CIV5D_DATA'!B:AS,19,FALSE) -> N/A | Q105: =IF(VLOOKUP(B105,'[1]26MY_CIV5D_DATA'!B:AS,20,FALSE)="","",VLOOKUP(B105,'[1]26MY_CIV5D_DATA'!B:AS,20,FALSE))
B106: 08P20-T20-1Z0 | C106: =VLOOKUP(B106,'[1]26MY_CIV5D_DATA'!B:AS,3,FALSE) -> Solar Reflection Silver (NH-932M) | D106: =B106 -> 08P20-T20-1Z0 | E106: =VLOOKUP(B106,'[1]26MY_CIV5D_DATA'!B:AS,9,FALSE) -> 136 | F106: =VLOOKUP(B106,'[1]26MY_CIV5D_DATA'!B:AS,10,FALSE) -> 194 | G106: =VLOOKUP(B106,'[1]26MY_CIV5D_DATA'!B:AS,7,FALSE) -> 0.4 | H106: =VLOOKUP(B106,'[1]26MY_CIV5D_DATA'!B:AS,11,FALSE) -> 261.2 | I106: =VLOOKUP(B106,'[1]26MY_CIV5D_DATA'!B:AS,12,FALSE) -> 0 | J106: =VLOOKUP(B106,'[1]26MY_CIV5D_DATA'!B:AS,13,FALSE) -> 0 | K106: =VLOOKUP($B106,'[1]26MY_CIV5D_DATA'!$B:$AS,14,FALSE) -> 0 | L106: =VLOOKUP(B106,'[1]26MY_CIV5D_DATA'!B:AS,15,FALSE) -> • | M106: =VLOOKUP(B106,'[1]26MY_CIV5D_DATA'!B:AS,16,FALSE) -> N/A | N106: =VLOOKUP($B106,'[1]26MY_CIV5D_DATA'!$B:$AS,17,FALSE) -> 0 | O106: =VLOOKUP(B106,'[1]26MY_CIV5D_DATA'!B:AS,18,FALSE) -> N/A | P106: =VLOOKUP(B106,'[1]26MY_CIV5D_DATA'!B:AS,19,FALSE) -> N/A
B107: 08P20-T20-170 | C107: =VLOOKUP(B107,'[1]26MY_CIV5D_DATA'!B:AS,3,FALSE) -> Meteoroid Gray Pearl (NH-904M) | D107: =B107 -> 08P20-T20-170 | E107: =VLOOKUP(B107,'[1]26MY_CIV5D_DATA'!B:AS,9,FALSE) -> 48.99 | F107: =VLOOKUP(B107,'[1]26MY_CIV5D_DATA'!B:AS,10,FALSE) -> 73.99 | G107: =VLOOKUP(B107,'[1]26MY_CIV5D_DATA'!B:AS,7,FALSE) -> 0.4 | H107: =VLOOKUP(B107,'[1]26MY_CIV5D_DATA'!B:AS,11,FALSE) -> 141.19 | I107: =VLOOKUP(B107,'[1]26MY_CIV5D_DATA'!B:AS,12,FALSE) -> 0 | J107: =VLOOKUP(B107,'[1]26MY_CIV5D_DATA'!B:AS,13,FALSE) -> 0 | K107: =VLOOKUP($B107,'[1]26MY_CIV5D_DATA'!$B:$AS,14,FALSE) -> 0 | L107: =VLOOKUP(B107,'[1]26MY_CIV5D_DATA'!B:AS,15,FALSE) -> N/A | M107: =VLOOKUP(B107,'[1]26MY_CIV5D_DATA'!B:AS,16,FALSE) -> • | N107: =VLOOKUP($B107,'[1]26MY_CIV5D_DATA'!$B:$AS,17,FALSE) -> 0 | O107: =VLOOKUP(B107,'[1]26MY_CIV5D_DATA'!B:AS,18,FALSE) -> N/A | P107: =VLOOKUP(B107,'[1]26MY_CIV5D_DATA'!B:AS,19,FALSE) -> N/A
B108: 08P20-T20-180 | C108: =VLOOKUP(B108,'[1]26MY_CIV5D_DATA'!B:AS,3,FALSE) -> Crystal Black Pearl (NH-731P) | D108: =B108 -> 08P20-T20-180 | E108: =VLOOKUP(B108,'[1]26MY_CIV5D_DATA'!B:AS,9,FALSE) -> 136 | F108: =VLOOKUP(B108,'[1]26MY_CIV5D_DATA'!B:AS,10,FALSE) -> 194 | G108: =VLOOKUP(B108,'[1]26MY_CIV5D_DATA'!B:AS,7,FALSE) -> 0.4 | H108: =VLOOKUP(B108,'[1]26MY_CIV5D_DATA'!B:AS,11,FALSE) -> 261.2 | I108: =VLOOKUP(B108,'[1]26MY_CIV5D_DATA'!B:AS,12,FALSE) -> 0 | J108: =VLOOKUP(B108,'[1]26MY_CIV5D_DATA'!B:AS,13,FALSE) -> 0 | K108: =VLOOKUP($B108,'[1]26MY_CIV5D_DATA'!$B:$AS,14,FALSE) -> 0 | L108: =VLOOKUP(B108,'[1]26MY_CIV5D_DATA'!B:AS,15,FALSE) -> • | M108: =VLOOKUP(B108,'[1]26MY_CIV5D_DATA'!B:AS,16,FALSE) -> • | N108: =VLOOKUP($B108,'[1]26MY_CIV5D_DATA'!$B:$AS,17,FALSE) -> 0 | O108: =VLOOKUP(B108,'[1]26MY_CIV5D_DATA'!B:AS,18,FALSE) -> • | P108: =VLOOKUP(B108,'[1]26MY_CIV5D_DATA'!B:AS,19,FALSE) -> N/A
B109: 08P20-T20-190 | C109: =VLOOKUP(B109,'[1]26MY_CIV5D_DATA'!B:AS,3,FALSE) -> Rallye Red (R-513) | D109: =B109 -> 08P20-T20-190 | E109: =VLOOKUP(B109,'[1]26MY_CIV5D_DATA'!B:AS,9,FALSE) -> 136 | F109: =VLOOKUP(B109,'[1]26MY_CIV5D_DATA'!B:AS,10,FALSE) -> 194 | G109: =VLOOKUP(B109,'[1]26MY_CIV5D_DATA'!B:AS,7,FALSE) -> 0.4 | H109: =VLOOKUP(B109,'[1]26MY_CIV5D_DATA'!B:AS,11,FALSE) -> 261.2 | I109: =VLOOKUP(B109,'[1]26MY_CIV5D_DATA'!B:AS,12,FALSE) -> 0 | J109: =VLOOKUP(B109,'[1]26MY_CIV5D_DATA'!B:AS,13,FALSE) -> 0 | K109: =VLOOKUP($B109,'[1]26MY_CIV5D_DATA'!$B:$AS,14,FALSE) -> 0 | L109: =VLOOKUP(B109,'[1]26MY_CIV5D_DATA'!B:AS,15,FALSE) -> N/A | M109: =VLOOKUP(B109,'[1]26MY_CIV5D_DATA'!B:AS,16,FALSE) -> • | N109: =VLOOKUP($B109,'[1]26MY_CIV5D_DATA'!$B:$AS,17,FALSE) -> 0 | O109: =VLOOKUP(B109,'[1]26MY_CIV5D_DATA'!B:AS,18,FALSE) -> • | P109: =VLOOKUP(B109,'[1]26MY_CIV5D_DATA'!B:AS,19,FALSE) -> N/A
C111: 4.0 Interior
...

Sheet 26MY_CIV5D_APP_FR
B2: Honda Internal | C2: Accessoires Honda
C3: Nom du modèle | D3: ='[1]26MY_CIV5D_DATA'!$D$2 -> Civic à Hayon
C4: Année modèle | D4: ='[1]26MY_CIV5D_DATA'!$C$3 -> 2026
C5: S = De série (accessoire de série sur cette version).
C6: T = Taille des pneus (la taille de la jante accessoire diffère de la jante d’origine. Le client aura besoin de nouveaux pneus pour ces jantes).
C7: E = Échange d’équipement de série (la taille de la jante accessoire est la même que celle de la jante d’origine. Le client peut utiliser les pneus d’origine).
C8: N/A = Sans objet (l’accessoire ne peut être utilisé pour cette version).
H10: Province
C11: 1.0 Groupes et ensembles | H11: =prov_cd -> YT
C12: La description | D12: Numéro de pièce | E12: Prix net | F12: Prix de liste | G12: T.F.F. | H12: Prix installé | I12: Application | Q12: Commentaires
I13: ='[1]26MY_CIV5D_DATA'!M$6 -> 0 | J13: ='[1]26MY_CIV5D_DATA'!N$6 -> 0 | K13: ='[1]26MY_CIV5D_DATA'!O$6 -> 0 | L13: ='[1]26MY_CIV5D_DATA'!P$6 -> SPORT | M13: ='[1]26MY_CIV5D_DATA'!Q$6 -> SPORT Hybride | N13: ='[1]26MY_CIV5D_DATA'!R$6 -> 0 | O13: ='[1]26MY_CIV5D_DATA'!S$6 -> Sport Touring Hybride | P13: ='[1]26MY_CIV5D_DATA'!T$6 -> Type R
B14: 25CIV-ENK-WTPK | C14: =VLOOKUP(B14,'[1]26MY_CIV5D_DATA'!B:AS,4,FALSE) -> Ensemble de roues Enkei M52 de 16 po et de pneus Michelin X-ICE Snow | E14: =VLOOKUP(B14,'[1]26MY_CIV5D_DATA'!B:AS,9,FALSE) -> 1556.88 | F14: =VLOOKUP(B14,'[1]26MY_CIV5D_DATA'!B:AS,10,FALSE) -> 1980 | G14: =VLOOKUP(B14,'[1]26MY_CIV5D_DATA'!B:AS,7,FALSE) -> 1.2 | H14: =VLOOKUP(B14,'[1]26MY_CIV5D_DATA'!B:AS,11,FALSE) -> 2181.6 | I14: =VLOOKUP(B14,'[1]26MY_CIV5D_DATA'!B:AS,12,FALSE) -> 0 | J14: =VLOOKUP(B14,'[1]26MY_CIV5D_DATA'!B:AS,13,FALSE) -> 0 | K14: =VLOOKUP($B14,'[1]26MY_CIV5D_DATA'!$B:$AS,14,FALSE) -> 0 | L14: =VLOOKUP(B14,'[1]26MY_CIV5D_DATA'!B:AS,15,FALSE) -> • | M14: =VLOOKUP(B14,'[1]26MY_CIV5D_DATA'!B:AS,16,FALSE) -> N/A | N14: =VLOOKUP($B14,'[1]26MY_CIV5D_DATA'!$B:$AS,17,FALSE) -> 0 | O14: =VLOOKUP(B14,'[1]26MY_CIV5D_DATA'!B:AS,18,FALSE) -> N/A | P14: =VLOOKUP(B14,'[1]26MY_CIV5D_DATA'!B:AS,19,FALSE) -> N/A | Q14: =IF(VLOOKUP(B14,'[1]26MY_CIV5D_DATA'!B:AS,21,FALSE)="","",VLOOKUP(B14,'[1]26MY_CIV5D_DATA'!B:AS,21,FALSE)) -> Prix établi pour ensemble de 4 pneus.
B15: 480-670-6545-SP ou 480-670-6545-GB | C15: =VLOOKUP(B15,'[1]26MY_CIV5D_DATA'!B:AS,4,FALSE) -> Roues Enkei M52 de 16 po - argent ou noir brillant | D15: =B15 -> 480-670-6545-SP ou 480-670-6545-GB
B16: 34417 | C16: =VLOOKUP(B16,'[1]26MY_CIV5D_DATA'!B:AS,4,FALSE) -> Pneus Michelin X-ICE Snow - 215/55/16 | D16: =B16 -> 34417
B18: 25CIV-STL-WTPK | C18: =VLOOKUP(B18,'[1]26MY_CIV5D_DATA'!B:AS,4,FALSE) -> Ensemble de roues d’hiver de 16 po en acier et de pneus Michelin X-ICE Snow | E18: =VLOOKUP(B18,'[1]26MY_CIV5D_DATA'!B:AS,9,FALSE) -> 1124.48 | F18: =VLOOKUP(B18,'[1]26MY_CIV5D_DATA'!B:AS,10,FALSE) -> 1492.48 | G18: =VLOOKUP(B18,'[1]26MY_CIV5D_DATA'!B:AS,7,FALSE) -> 1.2 | H18: =VLOOKUP(B18,'[1]26MY_CIV5D_DATA'!B:AS,11,FALSE) -> 1694.08 | I18: =VLOOKUP(B18,'[1]26MY_CIV5D_DATA'!B:AS,12,FALSE) -> 0 | J18: =VLOOKUP(B18,'[1]26MY_CIV5D_DATA'!B:AS,13,FALSE) -> 0 | K18: =VLOOKUP($B18,'[1]26MY_CIV5D_DATA'!$B:$AS,14,FALSE) -> 0 | L18: =VLOOKUP(B18,'[1]26MY_CIV5D_DATA'!B:AS,15,FALSE) -> • | M18: =VLOOKUP(B18,'[1]26MY_CIV5D_DATA'!B:AS,16,FALSE) -> N/A | N18: =VLOOKUP($B18,'[1]26MY_CIV5D_DATA'!$B:$AS,17,FALSE) -> 0 | O18: =VLOOKUP(B18,'[1]26MY_CIV5D_DATA'!B:AS,18,FALSE) -> N/A | P18: =VLOOKUP(B18,'[1]26MY_CIV5D_DATA'!B:AS,19,FALSE) -> N/A | Q18: =IF(VLOOKUP(B18,'[1]26MY_CIV5D_DATA'!B:AS,21,FALSE)="","",VLOOKUP(B18,'[1]26MY_CIV5D_DATA'!B:AS,21,FALSE)) -> Prix établi pour ensemble de 4 pneus.
B19: 42700-TBA-A12 | C19: =VLOOKUP(B19,'[1]26MY_CIV5D_DATA'!B:AS,4,FALSE) -> Roues d’hiver de 16 po en acier | D19: =B19 -> 42700-TBA-A12
B20: 34417 | C20: =VLOOKUP(B20,'[1]26MY_CIV5D_DATA'!B:AS,4,FALSE) -> Pneus Michelin X-ICE Snow - 215/55/16 | D20: =B20 -> 34417
B22: 25CIV5-ARO-PK | C22: =VLOOKUP(B22,'[1]26MY_CIV5D_DATA'!B:AS,4,FALSE) -> Ensemble Aero | E22: =VLOOKUP(B22,'[1]26MY_CIV5D_DATA'!B:AS,9,FALSE) -> 643.5 | F22: =VLOOKUP(B22,'[1]26MY_CIV5D_DATA'!B:AS,10,FALSE) -> 1072.8 | G22: =VLOOKUP(B22,'[1]26MY_CIV5D_DATA'!B:AS,7,FALSE) -> 2.2 | H22: =VLOOKUP(B22,'[1]26MY_CIV5D_DATA'!B:AS,11,FALSE) -> 1442.4 | I22: =VLOOKUP(B22,'[1]26MY_CIV5D_DATA'!B:AS,12,FALSE) -> 0 | J22: =VLOOKUP(B22,'[1]26MY_CIV5D_DATA'!B:AS,13,FALSE) -> 0 | K22: =VLOOKUP($B22,'[1]26MY_CIV5D_DATA'!$B:$AS,14,FALSE) -> 0 | L22: =VLOOKUP(B22,'[1]26MY_CIV5D_DATA'!B:AS,15,FALSE) -> • | M22: =VLOOKUP(B22,'[1]26MY_CIV5D_DATA'!B:AS,16,FALSE) -> • | N22: =VLOOKUP($B22,'[1]26MY_CIV5D_DATA'!$B:$AS,17,FALSE) -> 0 | O22: =VLOOKUP(B22,'[1]26MY_CIV5D_DATA'!B:AS,18,FALSE) -> • | P22: =VLOOKUP(B22,'[1]26MY_CIV5D_DATA'!B:AS,19,FALSE) -> N/A | Q22: =IF(VLOOKUP(B22,'[1]26MY_CIV5D_DATA'!B:AS,21,FALSE)="","",VLOOKUP(B22,'[1]26MY_CIV5D_DATA'!B:AS,21,FALSE)) -> Rabais de 10 % appliqué. Comprend déflecteur de bas de caisse avant de la couleur de la carrosserie et un becquet de hayon.
B23: 25CIV-5AR-NH883 | C23: =VLOOKUP(B23,'[1]26MY_CIV5D_DATA'!B:AS,4,FALSE) -> Blanc platine nacré (NH-883P) | D23: =B23 -> 25CIV-5AR-NH883
B24: 25CIV-5AR-NH932 | C24: =VLOOKUP(B24,'[1]26MY_CIV5D_DATA'!B:AS,4,FALSE) -> Refl et solaire argent métallisé (NH-932M) | D24: =B24 -> 25CIV-5AR-NH932
B25: 25CIV-5AR-NH904 | C25: =VLOOKUP(B25,'[1]26MY_CIV5D_DATA'!B:AS,4,FALSE) -> Gris météore nacré (NH-904M) | D25: =B25 -> 25CIV-5AR-NH904
B26: 25CIV-5AR-NH912 | C26: =VLOOKUP(B26,'[1]26MY_CIV5D_DATA'!B:AS,4,FALSE) -> Gris urbain nacré (NH-912P) | D26: =B26 -> 25CIV-5AR-NH912
B27: 25CIV-5AR-NH731 | C27: =VLOOKUP(B27,'[1]26MY_CIV5D_DATA'!B:AS,4,FALSE) -> Noir cristal nacré (NH-731P) | D27: =B27 -> 25CIV-5AR-NH731
B28: 25CIV-5AR-R513 | C28: =VLOOKUP(B28,'[1]26MY_CIV5D_DATA'!B:AS,4,FALSE) -> Rouge rallye (R-513) | D28: =B28 -> 25CIV-5AR-R513
B29: 25CIV-5AR-B637 | C29: =VLOOKUP(B29,'[1]26MY_CIV5D_DATA'!B:AS,4,FALSE) -> Bleu turbo nacré (B-637P) | D29: =B29 -> 25CIV-5AR-B637
B31: 22CIV-COLD-PK20 | C31: =VLOOKUP(B31,'[1]26MY_CIV5D_DATA'!B:AS,4,FALSE) -> Ensemble de temps froid - 2,0 L | D31: =B31 -> 22CIV-COLD-PK20 | E31: =VLOOKUP(B31,'[1]26MY_CIV5D_DATA'!B:AS,9,FALSE) -> 224.2 | F31: =VLOOKUP(B31,'[1]26MY_CIV5D_DATA'!B:AS,10,FALSE) -> 374.3 | G31: =VLOOKUP(B31,'[1]26MY_CIV5D_DATA'!B:AS,7,FALSE) -> 1.4 | H31: =VLOOKUP(B31,'[1]26MY_CIV5D_DATA'!B:AS,11,FALSE) -> 609.5 | I31: =VLOOKUP(B31,'[1]26MY_CIV5D_DATA'!B:AS,12,FALSE) -> 0 | J31: =VLOOKUP(B31,'[1]26MY_CIV5D_DATA'!B:AS,13,FALSE) -> 0 | K31: =VLOOKUP($B31,'[1]26MY_CIV5D_DATA'!$B:$AS,14,FALSE) -> 0 | L31: =VLOOKUP(B31,'[1]26MY_CIV5D_DATA'!B:AS,15,FALSE) -> • | M31: =VLOOKUP(B31,'[1]26MY_CIV5D_DATA'!B:AS,16,FALSE) -> • | N31: =VLOOKUP($B31,'[1]26MY_CIV5D_DATA'!$B:$AS,17,FALSE) -> 0 | O31: =VLOOKUP(B31,'[1]26MY_CIV5D_DATA'!B:AS,18,FALSE) -> • | P31: =VLOOKUP(B31,'[1]26MY_CIV5D_DATA'!B:AS,19,FALSE) -> N/A | Q31: =IF(VLOOKUP(B31,'[1]26MY_CIV5D_DATA'!B:AS,21,FALSE)="","",VLOOKUP(B31,'[1]26MY_CIV5D_DATA'!B:AS,21,FALSE)) -> Rabais de 5 % appliqué.
B32: 08T44-SNA-302 | C32: =VLOOKUP(B32,'[1]26MY_CIV5D_DATA'!B:AS,4,FALSE) -> Chauffe-moteur - 2,0 L | D32: =B32 -> 08T44-SNA-302
B33: 31670-BMS-004H | C33: =VLOOKUP(B33,'[1]26MY_CIV5D_DATA'!B:AS,4,FALSE) -> Chargeur/mainteneur de batterie automobile 12 V Optimate | D33: =B33 -> 31670-BMS-004H
B35: 25CIV5D-PRO-PET | C35: =VLOOKUP(B35,'[1]26MY_CIV5D_DATA'!B:AS,4,FALSE) -> Ensemble de protection - Petrol | D35: =B35 -> 25CIV5D-PRO-PET | E35: =VLOOKUP(B35,'[1]26MY_CIV5D_DATA'!B:AS,9,FALSE) -> 288.9 | F35: =VLOOKUP(B35,'[1]26MY_CIV5D_DATA'!B:AS,10,FALSE) -> 536 | G35: =VLOOKUP(B35,'[1]26MY_CIV5D_DATA'!B:AS,7,FALSE) -> 0.6 | H35: =VLOOKUP(B35,'[1]26MY_CIV5D_DATA'!B:AS,11,FALSE) -> 636.8 | I35: =VLOOKUP(B35,'[1]26MY_CIV5D_DATA'!B:AS,12,FALSE) -> 0 | J35: =VLOOKUP(B35,'[1]26MY_CIV5D_DATA'!B:AS,13,FALSE) -> 0 | K35: =VLOOKUP($B35,'[1]26MY_CIV5D_DATA'!$B:$AS,14,FALSE) -> 0 | L35: =VLOOKUP(B35,'[1]26MY_CIV5D_DATA'!B:AS,15,FALSE) -> • | M35: =VLOOKUP(B35,'[1]26MY_CIV5D_DATA'!B:AS,16,FALSE) -> N/A | N35: =VLOOKUP($B35,'[1]26MY_CIV5D_DATA'!$B:$AS,17,FALSE) -> 0 | O35: =VLOOKUP(B35,'[1]26MY_CIV5D_DATA'!B:AS,18,FALSE) -> N/A | P35: =VLOOKUP(B35,'[1]26MY_CIV5D_DATA'!B:AS,19,FALSE) -> N/A | Q35: =IF(VLOOKUP(B35,'[1]26MY_CIV5D_DATA'!B:AS,21,FALSE)="","",VLOOKUP(B35,'[1]26MY_CIV5D_DATA'!B:AS,21,FALSE))
B36: 08P17-T20-110 | C36: =VLOOKUP(B36,'[1]26MY_CIV5D_DATA'!B:AS,4,FALSE) -> Tapis toutes saisons | D36: =B36 -> 08P17-T20-110
B37: 08U45-T47-100B | C37: =VLOOKUP(B37,'[1]26MY_CIV5D_DATA'!B:AS,4,FALSE) -> Plateau de coffre | D37: =B37 -> 08U45-T47-100B
B38: 08P09-T47-300 | C38: =VLOOKUP(B38,'[1]26MY_CIV5D_DATA'!B:AS,4,FALSE) -> Garde-boue arrière | D38: =B38 -> 08P09-T47-300
B40: 25CIV5-PRO-HYB | C40: =VLOOKUP(B40,'[1]26MY_CIV5D_DATA'!B:AS,4,FALSE) -> Ensemble de protection - Hybrid | D40: =B40 -> 25CIV5-PRO-HYB | E40: =VLOOKUP(B40,'[1]26MY_CIV5D_DATA'!B:AS,9,FALSE) -> 288.9 | F40: =VLOOKUP(B40,'[1]26MY_CIV5D_DATA'!B:AS,10,FALSE) -> 536 | G40: =VLOOKUP(B40,'[1]26MY_CIV5D_DATA'!B:AS,7,FALSE) -> 0.6 | H40: =VLOOKUP(B40,'[1]26MY_CIV5D_DATA'!B:AS,11,FALSE) -> 636.8 | I40: =VLOOKUP(B40,'[1]26MY_CIV5D_DATA'!B:AS,12,FALSE) -> 0 | J40: =VLOOKUP(B40,'[1]26MY_CIV5D_DATA'!B:AS,13,FALSE) -> 0 | K40: =VLOOKUP($B40,'[1]26MY_CIV5D_DATA'!$B:$AS,14,FALSE) -> 0 | L40: =VLOOKUP(B40,'[1]26MY_CIV5D_DATA'!B:AS,15,FALSE) -> N/A | M40: =VLOOKUP(B40,'[1]26MY_CIV5D_DATA'!B:AS,16,FALSE) -> • | N40: =VLOOKUP($B40,'[1]26MY_CIV5D_DATA'!$B:$AS,17,FALSE) -> 0 | O40: =VLOOKUP(B40,'[1]26MY_CIV5D_DATA'!B:AS,18,FALSE) -> • | P40: =VLOOKUP(B40,'[1]26MY_CIV5D_DATA'!B:AS,19,FALSE) -> N/A | Q40: =IF(VLOOKUP(B40,'[1]26MY_CIV5D_DATA'!B:AS,21,FALSE)="","",VLOOKUP(B40,'[1]26MY_CIV5D_DATA'!B:AS,21,FALSE))
B41: 08P17-T20-110A | C41: =VLOOKUP(B41,'[1]26MY_CIV5D_DATA'!B:AS,4,FALSE) -> Tapis toutes saisons - Hybrid | D41: =B41 -> 08P17-T20-110A
B42: 08U45-T47-100B | C42: =VLOOKUP(B42,'[1]26MY_CIV5D_DATA'!B:AS,4,FALSE) -> Plateau de coffre | D42: =B42 -> 08U45-T47-100B
B43: 08P09-T47-300 | C43: =VLOOKUP(B43,'[1]26MY_CIV5D_DATA'!B:AS,4,FALSE) -> Garde-boue arrière | D43: =B43 -> 08P09-T47-300
B45: 25CIV5-PRO-FLM | C45: =VLOOKUP(B45,'[1]26MY_CIV5D_DATA'!B:AS,4,FALSE) -> Ensemble de protection - Film | D45: =B45 -> 25CIV5-PRO-FLM | E45: =VLOOKUP(B45,'[1]26MY_CIV5D_DATA'!B:AS,9,FALSE) -> 198.9 | F45: =VLOOKUP(B45,'[1]26MY_CIV5D_DATA'!B:AS,10,FALSE) -> 319.5 | G45: =VLOOKUP(B45,'[1]26MY_CIV5D_DATA'!B:AS,7,FALSE) -> 1 | H45: =VLOOKUP(B45,'[1]26MY_CIV5D_DATA'!B:AS,11,FALSE) -> 487.5 | I45: =VLOOKUP(B45,'[1]26MY_CIV5D_DATA'!B:AS,12,FALSE) -> 0 | J45: =VLOOKUP(B45,'[1]26MY_CIV5D_DATA'!B:AS,13,FALSE) -> 0 | K45: =VLOOKUP($B45,'[1]26MY_CIV5D_DATA'!$B:$AS,14,FALSE) -> 0 | L45: =VLOOKUP(B45,'[1]26MY_CIV5D_DATA'!B:AS,15,FALSE) -> • | M45: =VLOOKUP(B45,'[1]26MY_CIV5D_DATA'!B:AS,16,FALSE) -> • | N45: =VLOOKUP($B45,'[1]26MY_CIV5D_DATA'!$B:$AS,17,FALSE) -> 0 | O45: =VLOOKUP(B45,'[1]26MY_CIV5D_DATA'!B:AS,18,FALSE) -> • | P45: =VLOOKUP(B45,'[1]26MY_CIV5D_DATA'!B:AS,19,FALSE) -> N/A | Q45: =IF(VLOOKUP(B45,'[1]26MY_CIV5D_DATA'!B:AS,21,FALSE)="","",VLOOKUP(B45,'[1]26MY_CIV5D_DATA'!B:AS,21,FALSE)) -> Rabais de 10 % appliqué. Ne peut être installé simultanément avec protecteurs de bordure de porte.
B46: 08P04-T20-100 | C46: =VLOOKUP(B46,'[1]26MY_CIV5D_DATA'!B:AS,4,FALSE) -> Pellicule de protection de seuil de portière | D46: =B46 -> 08P04-T20-100
B47: 08P20-T20-100A | C47: =VLOOKUP(B47,'[1]26MY_CIV5D_DATA'!B:AS,4,FALSE) -> Pellicule pour rebord de portière | D47: =B47 -> 08P20-T20-100A
B48: 08P01-T47-100 | C48: =VLOOKUP(B48,'[1]26MY_CIV5D_DATA'!B:AS,4,FALSE) -> Protection de pare-chocs arrière | D48: =B48 -> 08P01-T47-100
C50: 2.0 Jantes et accessoires de jantes
C51: La description | D51: Numéro de pièce | E51: Prix net | F51: Prix de liste | G51: T.F.F. | H51: Prix installé | I51: Application | Q51: Commentaires
I52: ='[1]26MY_CIV5D_DATA'!M$6 -> 0 | J52: ='[1]26MY_CIV5D_DATA'!N$6 -> 0 | K52: ='[1]26MY_CIV5D_DATA'!O$6 -> 0 | L52: ='[1]26MY_CIV5D_DATA'!P$6 -> SPORT | M52: ='[1]26MY_CIV5D_DATA'!Q$6 -> SPORT Hybride | N52: ='[1]26MY_CIV5D_DATA'!R$6 -> 0 | O52: ='[1]26MY_CIV5D_DATA'!S$6 -> Sport Touring Hybride | P52: ='[1]26MY_CIV5D_DATA'!T$6 -> Type R
B53: 42700-TBA-A12 | C53: =VLOOKUP(B53,'[1]26MY_CIV5D_DATA'!B:AS,4,FALSE) -> Roues d’hiver de 16 po en acier | D53: =B53 -> 42700-TBA-A12 | E53: =VLOOKUP(B53,'[1]26MY_CIV5D_DATA'!B:AS,9,FALSE) -> 311.6 | F53: =VLOOKUP(B53,'[1]26MY_CIV5D_DATA'!B:AS,10,FALSE) -> 512.48 | G53: =VLOOKUP(B53,'[1]26MY_CIV5D_DATA'!B:AS,7,FALSE) -> 1.6 | H53: =VLOOKUP(B53,'[1]26MY_CIV5D_DATA'!B:AS,11,FALSE) -> 781.28 | I53: =VLOOKUP(B53,'[1]26MY_CIV5D_DATA'!B:AS,12,FALSE) -> 0 | J53: =VLOOKUP(B53,'[1]26MY_CIV5D_DATA'!B:AS,13,FALSE) -> 0 | K53: =VLOOKUP($B53,'[1]26MY_CIV5D_DATA'!$B:$AS,14,FALSE) -> 0 | L53: =VLOOKUP(B53,'[1]26MY_CIV5D_DATA'!B:AS,15,FALSE) -> • | M53: =VLOOKUP(B53,'[1]26MY_CIV5D_DATA'!B:AS,16,FALSE) -> N/A | N53: =VLOOKUP($B53,'[1]26MY_CIV5D_DATA'!$B:$AS,17,FALSE) -> 0 | O53: =VLOOKUP(B53,'[1]26MY_CIV5D_DATA'!B:AS,18,FALSE) -> N/A | P53: =VLOOKUP(B53,'[1]26MY_CIV5D_DATA'!B:AS,19,FALSE) -> N/A | Q53: =IF(VLOOKUP(B53,'[1]26MY_CIV5D_DATA'!B:AS,21,FALSE)="","",VLOOKUP(B53,'[1]26MY_CIV5D_DATA'!B:AS,21,FALSE)) -> Prix pour un ensemble de 4 roues. Pneus vendus séparément.
B54: 480-670-6545GB | C54: =VLOOKUP(B54,'[1]26MY_CIV5D_DATA'!B:AS,4,FALSE) -> Jantes Enkei M52 de 16 po noir lustré | D54: =B54 -> 480-670-6545GB | E54: =VLOOKUP(B54,'[1]26MY_CIV5D_DATA'!B:AS,9,FALSE) -> 744 | F54: =VLOOKUP(B54,'[1]26MY_CIV5D_DATA'!B:AS,10,FALSE) -> 1000 | G54: =VLOOKUP(B54,'[1]26MY_CIV5D_DATA'!B:AS,7,FALSE) -> 1.6 | H54: =VLOOKUP(B54,'[1]26MY_CIV5D_DATA'!B:AS,11,FALSE) -> 1268.8 | I54: =VLOOKUP(B54,'[1]26MY_CIV5D_DATA'!B:AS,12,FALSE) -> 0 | J54: =VLOOKUP(B54,'[1]26MY_CIV5D_DATA'!B:AS,13,FALSE) -> 0 | K54: =VLOOKUP($B54,'[1]26MY_CIV5D_DATA'!$B:$AS,14,FALSE) -> 0 | L54: =VLOOKUP(B54,'[1]26MY_CIV5D_DATA'!B:AS,15,FALSE) -> T | M54: =VLOOKUP(B54,'[1]26MY_CIV5D_DATA'!B:AS,16,FALSE) -> N/A | N54: =VLOOKUP($B54,'[1]26MY_CIV5D_DATA'!$B:$AS,17,FALSE) -> 0 | O54: =VLOOKUP(B54,'[1]26MY_CIV5D_DATA'!B:AS,18,FALSE) -> N/A | P54: =VLOOKUP(B54,'[1]26MY_CIV5D_DATA'!B:AS,19,FALSE) -> N/A | Q54: =IF(VLOOKUP(B54,'[1]26MY_CIV5D_DATA'!B:AS,21,FALSE)="","",VLOOKUP(B54,'[1]26MY_CIV5D_DATA'!B:AS,21,FALSE)) -> Prix pour un ensemble de 4 roues. Pneus vendus séparément.
B55: 480-670-6545SP | C55: =VLOOKUP(B55,'[1]26MY_CIV5D_DATA'!B:AS,4,FALSE) -> Jantes Enkei M52 de 16 po argent | D55: =B55 -> 480-670-6545SP | E55: =VLOOKUP(B55,'[1]26MY_CIV5D_DATA'!B:AS,9,FALSE) -> 744 | F55: =VLOOKUP(B55,'[1]26MY_CIV5D_DATA'!B:AS,10,FALSE) -> 1000 | G55: =VLOOKUP(B55,'[1]26MY_CIV5D_DATA'!B:AS,7,FALSE) -> 1.6 | H55: =VLOOKUP(B55,'[1]26MY_CIV5D_DATA'!B:AS,11,FALSE) -> 1268.8 | I55: =VLOOKUP(B55,'[1]26MY_CIV5D_DATA'!B:AS,12,FALSE) -> 0 | J55: =VLOOKUP(B55,'[1]26MY_CIV5D_DATA'!B:AS,13,FALSE) -> 0 | K55: =VLOOKUP($B55,'[1]26MY_CIV5D_DATA'!$B:$AS,14,FALSE) -> 0 | L55: =VLOOKUP(B55,'[1]26MY_CIV5D_DATA'!B:AS,15,FALSE) -> T | M55: =VLOOKUP(B55,'[1]26MY_CIV5D_DATA'!B:AS,16,FALSE) -> N/A | N55: =VLOOKUP($B55,'[1]26MY_CIV5D_DATA'!$B:$AS,17,FALSE) -> 0 | O55: =VLOOKUP(B55,'[1]26MY_CIV5D_DATA'!B:AS,18,FALSE) -> N/A | P55: =VLOOKUP(B55,'[1]26MY_CIV5D_DATA'!B:AS,19,FALSE) -> N/A | Q55: =IF(VLOOKUP(B55,'[1]26MY_CIV5D_DATA'!B:AS,21,FALSE)="","",VLOOKUP(B55,'[1]26MY_CIV5D_DATA'!B:AS,21,FALSE)) -> Prix pour un ensemble de 4 roues. Pneus vendus séparément.
B56: 509-775-6545BH | C56: =VLOOKUP(B56,'[1]26MY_CIV5D_DATA'!B:AS,4,FALSE) -> Jantes Enkei de 17 po noir lustré | D56: =B56 -> 509-775-6545BH | E56: =VLOOKUP(B56,'[1]26MY_CIV5D_DATA'!B:AS,9,FALSE) -> 832 | F56: =VLOOKUP(B56,'[1]26MY_CIV5D_DATA'!B:AS,10,FALSE) -> 1116 | G56: =VLOOKUP(B56,'[1]26MY_CIV5D_DATA'!B:AS,7,FALSE) -> 1.6 | H56: =VLOOKUP(B56,'[1]26MY_CIV5D_DATA'!B:AS,11,FALSE) -> 1384.8 | I56: =VLOOKUP(B56,'[1]26MY_CIV5D_DATA'!B:AS,12,FALSE) -> 0 | J56: =VLOOKUP(B56,'[1]26MY_CIV5D_DATA'!B:AS,13,FALSE) -> 0 | K56: =VLOOKUP($B56,'[1]26MY_CIV5D_DATA'!$B:$AS,14,FALSE) -> 0 | L56: =VLOOKUP(B56,'[1]26MY_CIV5D_DATA'!B:AS,15,FALSE) -> T | M56: =VLOOKUP(B56,'[1]26MY_CIV5D_DATA'!B:AS,16,FALSE) -> N/A | N56: =VLOOKUP($B56,'[1]26MY_CIV5D_DATA'!$B:$AS,17,FALSE) -> 0 | O56: =VLOOKUP(B56,'[1]26MY_CIV5D_DATA'!B:AS,18,FALSE) -> N/A | P56: =VLOOKUP(B56,'[1]26MY_CIV5D_DATA'!B:AS,19,FALSE) -> N/A | Q56: =IF(VLOOKUP(B56,'[1]26MY_CIV5D_DATA'!B:AS,21,FALSE)="","",VLOOKUP(B56,'[1]26MY_CIV5D_DATA'!B:AS,21,FALSE)) -> Prix pour un ensemble de 4 roues. Pneus vendus séparément.
B57: 509-775-6545SH | C57: =VLOOKUP(B57,'[1]26MY_CIV5D_DATA'!B:AS,4,FALSE) -> Jantes Enkei de 17 po argent | D57: =B57 -> 509-775-6545SH | E57: =VLOOKUP(B57,'[1]26MY_CIV5D_DATA'!B:AS,9,FALSE) -> 832 | F57: =VLOOKUP(B57,'[1]26MY_CIV5D_DATA'!B:AS,10,FALSE) -> 1116 | G57: =VLOOKUP(B57,'[1]26MY_CIV5D_DATA'!B:AS,7,FALSE) -> 1.6 | H57: =VLOOKUP(B57,'[1]26MY_CIV5D_DATA'!B:AS,11,FALSE) -> 1384.8 | I57: =VLOOKUP(B57,'[1]26MY_CIV5D_DATA'!B:AS,12,FALSE) -> 0 | J57: =VLOOKUP(B57,'[1]26MY_CIV5D_DATA'!B:AS,13,FALSE) -> 0 | K57: =VLOOKUP($B57,'[1]26MY_CIV5D_DATA'!$B:$AS,14,FALSE) -> 0 | L57: =VLOOKUP(B57,'[1]26MY_CIV5D_DATA'!B:AS,15,FALSE) -> T | M57: =VLOOKUP(B57,'[1]26MY_CIV5D_DATA'!B:AS,16,FALSE) -> N/A | N57: =VLOOKUP($B57,'[1]26MY_CIV5D_DATA'!$B:$AS,17,FALSE) -> 0 | O57: =VLOOKUP(B57,'[1]26MY_CIV5D_DATA'!B:AS,18,FALSE) -> N/A | P57: =VLOOKUP(B57,'[1]26MY_CIV5D_DATA'!B:AS,19,FALSE) -> N/A | Q57: =IF(VLOOKUP(B57,'[1]26MY_CIV5D_DATA'!B:AS,21,FALSE)="","",VLOOKUP(B57,'[1]26MY_CIV5D_DATA'!B:AS,21,FALSE)) -> Prix pour un ensemble de 4 roues. Pneus vendus séparément.
B58: 08W18-T20-100 | C58: =VLOOKUP(B58,'[1]26MY_CIV5D_DATA'!B:AS,4,FALSE) -> Jantes de 18 pouces noir | D58: =B58 -> 08W18-T20-100 | E58: =VLOOKUP(B58,'[1]26MY_CIV5D_DATA'!B:AS,9,FALSE) -> 2256 | F58: =VLOOKUP(B58,'[1]26MY_CIV5D_DATA'!B:AS,10,FALSE) -> 3472 | G58: =VLOOKUP(B58,'[1]26MY_CIV5D_DATA'!B:AS,7,FALSE) -> 1.6 | H58: =VLOOKUP(B58,'[1]26MY_CIV5D_DATA'!B:AS,11,FALSE) -> 3740.8 | I58: =VLOOKUP(B58,'[1]26MY_CIV5D_DATA'!B:AS,12,FALSE) -> 0 | J58: =VLOOKUP(B58,'[1]26MY_CIV5D_DATA'!B:AS,13,FALSE) -> 0 | K58: =VLOOKUP($B58,'[1]26MY_CIV5D_DATA'!$B:$AS,14,FALSE) -> 0 | L58: =VLOOKUP(B58,'[1]26MY_CIV5D_DATA'!B:AS,15,FALSE) -> E | M58: =VLOOKUP(B58,'[1]26MY_CIV5D_DATA'!B:AS,16,FALSE) -> E | N58: =VLOOKUP($B58,'[1]26MY_CIV5D_DATA'!$B:$AS,17,FALSE) -> 0 | O58: =VLOOKUP(B58,'[1]26MY_CIV5D_DATA'!B:AS,18,FALSE) -> E | P58: =VLOOKUP(B58,'[1]26MY_CIV5D_DATA'!B:AS,19,FALSE) -> N/A | Q58: =IF(VLOOKUP(B58,'[1]26MY_CIV5D_DATA'!B:AS,21,FALSE)="","",VLOOKUP(B58,'[1]26MY_CIV5D_DATA'!B:AS,21,FALSE)) -> Prix pour un ensemble de 4 roues. Pneus vendus séparément.
B59: 08W42-S2A-101 | C59: =VLOOKUP(B59,'[1]26MY_CIV5D_DATA'!B:AS,4,FALSE) -> Écrous de roue antivols - Noirs | D59: =B59 -> 08W42-S2A-101 | E59: =VLOOKUP(B59,'[1]26MY_CIV5D_DATA'!B:AS,9,FALSE) -> 59 | F59: =VLOOKUP(B59,'[1]26MY_CIV5D_DATA'!B:AS,10,FALSE) -> 98 | G59: =VLOOKUP(B59,'[1]26MY_CIV5D_DATA'!B:AS,7,FALSE) -> 0.2 | H59: =VLOOKUP(B59,'[1]26MY_CIV5D_DATA'!B:AS,11,FALSE) -> 131.6 | I59: =VLOOKUP(B59,'[1]26MY_CIV5D_DATA'!B:AS,12,FALSE) -> 0 | J59: =VLOOKUP(B59,'[1]26MY_CIV5D_DATA'!B:AS,13,FALSE) -> 0 | K59: =VLOOKUP($B59,'[1]26MY_CIV5D_DATA'!$B:$AS,14,FALSE) -> 0 | L59: =VLOOKUP(B59,'[1]26MY_CIV5D_DATA'!B:AS,15,FALSE) -> • | M59: =VLOOKUP(B59,'[1]26MY_CIV5D_DATA'!B:AS,16,FALSE) -> • | N59: =VLOOKUP($B59,'[1]26MY_CIV5D_DATA'!$B:$AS,17,FALSE) -> 0 | O59: =VLOOKUP(B59,'[1]26MY_CIV5D_DATA'!B:AS,18,FALSE) -> • | P59: =VLOOKUP(B59,'[1]26MY_CIV5D_DATA'!B:AS,19,FALSE) -> • | Q59: =IF(VLOOKUP(B59,'[1]26MY_CIV5D_DATA'!B:AS,21,FALSE)="","",VLOOKUP(B59,'[1]26MY_CIV5D_DATA'!B:AS,21,FALSE))
B60: 08W42-SCV-302 | C60: =VLOOKUP(B60,'[1]26MY_CIV5D_DATA'!B:AS,4,FALSE) -> Écrous de roue antivols - Chromés | D60: =B60 -> 08W42-SCV-302 | E60: =VLOOKUP(B60,'[1]26MY_CIV5D_DATA'!B:AS,9,FALSE) -> 52 | F60: =VLOOKUP(B60,'[1]26MY_CIV5D_DATA'!B:AS,10,FALSE) -> 87 | G60: =VLOOKUP(B60,'[1]26MY_CIV5D_DATA'!B:AS,7,FALSE) -> 0.2 | H60: =VLOOKUP(B60,'[1]26MY_CIV5D_DATA'!B:AS,11,FALSE) -> 120.6 | I60: =VLOOKUP(B60,'[1]26MY_CIV5D_DATA'!B:AS,12,FALSE) -> 0 | J60: =VLOOKUP(B60,'[1]26MY_CIV5D_DATA'!B:AS,13,FALSE) -> 0 | K60: =VLOOKUP($B60,'[1]26MY_CIV5D_DATA'!$B:$AS,14,FALSE) -> 0 | L60: =VLOOKUP(B60,'[1]26MY_CIV5D_DATA'!B:AS,15,FALSE) -> • | M60: =VLOOKUP(B60,'[1]26MY_CIV5D_DATA'!B:AS,16,FALSE) -> • | N60: =VLOOKUP($B60,'[1]26MY_CIV5D_DATA'!$B:$AS,17,FALSE) -> 0 | O60: =VLOOKUP(B60,'[1]26MY_CIV5D_DATA'!B:AS,18,FALSE) -> • | P60: =VLOOKUP(B60,'[1]26MY_CIV5D_DATA'!B:AS,19,FALSE) -> N/A | Q60: =IF(VLOOKUP(B60,'[1]26MY_CIV5D_DATA'!B:AS,21,FALSE)="","",VLOOKUP(B60,'[1]26MY_CIV5D_DATA'!B:AS,21,FALSE))
B61: 08W42-TGG-100 | C61: =VLOOKUP(B61,'[1]26MY_CIV5D_DATA'!B:AS,4,FALSE) -> Écrous de roue - Noir | D61: =B61 -> 08W42-TGG-100 | E61: =VLOOKUP(B61,'[1]26MY_CIV5D_DATA'!B:AS,9,FALSE) -> 55 | F61: =VLOOKUP(B61,'[1]26MY_CIV5D_DATA'!B:AS,10,FALSE) -> 88 | G61: =VLOOKUP(B61,'[1]26MY_CIV5D_DATA'!B:AS,7,FALSE) -> 0.2 | H61: =VLOOKUP(B61,'[1]26MY_CIV5D_DATA'!B:AS,11,FALSE) -> 121.6 | I61: =VLOOKUP(B61,'[1]26MY_CIV5D_DATA'!B:AS,12,FALSE) -> 0 | J61: =VLOOKUP(B61,'[1]26MY_CIV5D_DATA'!B:AS,13,FALSE) -> 0 | K61: =VLOOKUP($B61,'[1]26MY_CIV5D_DATA'!$B:$AS,14,FALSE) -> 0 | L61: =VLOOKUP(B61,'[1]26MY_CIV5D_DATA'!B:AS,15,FALSE) -> • | M61: =VLOOKUP(B61,'[1]26MY_CIV5D_DATA'!B:AS,16,FALSE) -> • | N61: =VLOOKUP($B61,'[1]26MY_CIV5D_DATA'!$B:$AS,17,FALSE) -> 0 | O61: =VLOOKUP(B61,'[1]26MY_CIV5D_DATA'!B:AS,18,FALSE) -> • | P61: =VLOOKUP(B61,'[1]26MY_CIV5D_DATA'!B:AS,19,FALSE) -> N/A | Q61: =IF(VLOOKUP(B61,'[1]26MY_CIV5D_DATA'!B:AS,21,FALSE)="","",VLOOKUP(B61,'[1]26MY_CIV5D_DATA'!B:AS,21,FALSE)) -> Inclut 4 écrous de roue en 1 jeu. L'installation complète nécessite 5 jeux pour 4 roues (20 écrous de roue).
C63: 3.0 Extérieur
C64: La description | D64: Numéro de pièce | E64: Prix net | F64: Prix de liste | G64: T.F.F. | H64: Prix installé | I64: Application | Q64: Commentaires
I65: ='[1]26MY_CIV5D_DATA'!M$6 -> 0 | J65: ='[1]26MY_CIV5D_DATA'!N$6 -> 0 | K65: ='[1]26MY_CIV5D_DATA'!O$6 -> 0 | L65: ='[1]26MY_CIV5D_DATA'!P$6 -> SPORT | M65: ='[1]26MY_CIV5D_DATA'!Q$6 -> SPORT Hybride | N65: ='[1]26MY_CIV5D_DATA'!R$6 -> 0 | O65: ='[1]26MY_CIV5D_DATA'!S$6 -> Sport Touring Hybride | P65: ='[1]26MY_CIV5D_DATA'!T$6 -> Type R
B66: 08F20-T47-100E | C66: =VLOOKUP(B66,'[1]26MY_CIV5D_DATA'!B:AS,4,FALSE) -> Emblèmes « H » noirs | D66: =B66 -> 08F20-T47-100E | E66: =VLOOKUP(B66,'[1]26MY_CIV5D_DATA'!B:AS,9,FALSE) -> 0 | F66: =VLOOKUP(B66,'[1]26MY_CIV5D_DATA'!B:AS,10,FALSE) -> 0 | G66: =VLOOKUP(B66,'[1]26MY_CIV5D_DATA'!B:AS,7,FALSE) -> 0.7 | H66: =VLOOKUP(B66,'[1]26MY_CIV5D_DATA'!B:AS,11,FALSE) -> 117.6 | I66: =VLOOKUP(B66,'[1]26MY_CIV5D_DATA'!B:AS,12,FALSE) -> 0 | J66: =VLOOKUP(B66,'[1]26MY_CIV5D_DATA'!B:AS,13,FALSE) -> 0 | K66: =VLOOKUP($B66,'[1]26MY_CIV5D_DATA'!$B:$AS,14,FALSE) -> 0 | L66: =VLOOKUP(B66,'[1]26MY_CIV5D_DATA'!B:AS,15,FALSE) -> • | M66: =VLOOKUP(B66,'[1]26MY_CIV5D_DATA'!B:AS,16,FALSE) -> • | N66: =VLOOKUP($B66,'[1]26MY_CIV5D_DATA'!$B:$AS,17,FALSE) -> 0 | O66: =VLOOKUP(B66,'[1]26MY_CIV5D_DATA'!B:AS,18,FALSE) -> • | P66: =VLOOKUP(B66,'[1]26MY_CIV5D_DATA'!B:AS,19,FALSE) -> N/A | Q66: =IF(VLOOKUP(B66,'[1]26MY_CIV5D_DATA'!B:AS,21,FALSE)="","",VLOOKUP(B66,'[1]26MY_CIV5D_DATA'!B:AS,21,FALSE)) -> Logo H-Mark à l'avant et à l'arrière.
B67: 08P47-T20-300 | C67: =VLOOKUP(B67,'[1]26MY_CIV5D_DATA'!B:AS,4,FALSE) -> Protecteur de capot | D67: =B67 -> 08P47-T20-300 | E67: =VLOOKUP(B67,'[1]26MY_CIV5D_DATA'!B:AS,9,FALSE) -> 215 | F67: =VLOOKUP(B67,'[1]26MY_CIV5D_DATA'!B:AS,10,FALSE) -> 358 | G67: =VLOOKUP(B67,'[1]26MY_CIV5D_DATA'!B:AS,7,FALSE) -> 0.6 | H67: =VLOOKUP(B67,'[1]26MY_CIV5D_DATA'!B:AS,11,FALSE) -> 458.8 | I67: =VLOOKUP(B67,'[1]26MY_CIV5D_DATA'!B:AS,12,FALSE) -> 0 | J67: =VLOOKUP(B67,'[1]26MY_CIV5D_DATA'!B:AS,13,FALSE) -> 0 | K67: =VLOOKUP($B67,'[1]26MY_CIV5D_DATA'!$B:$AS,14,FALSE) -> 0 | L67: =VLOOKUP(B67,'[1]26MY_CIV5D_DATA'!B:AS,15,FALSE) -> • | M67: =VLOOKUP(B67,'[1]26MY_CIV5D_DATA'!B:AS,16,FALSE) -> • | N67: =VLOOKUP($B67,'[1]26MY_CIV5D_DATA'!$B:$AS,17,FALSE) -> 0 | O67: =VLOOKUP(B67,'[1]26MY_CIV5D_DATA'!B:AS,18,FALSE) -> • | P67: =VLOOKUP(B67,'[1]26MY_CIV5D_DATA'!B:AS,19,FALSE) -> N/A | Q67: =IF(VLOOKUP(B67,'[1]26MY_CIV5D_DATA'!B:AS,21,FALSE)="","",VLOOKUP(B67,'[1]26MY_CIV5D_DATA'!B:AS,21,FALSE))
B68: 08R04-T47-100A | C68: =VLOOKUP(B68,'[1]26MY_CIV5D_DATA'!B:AS,4,FALSE) -> Déflecteurs de portières - noir | D68: =B68 -> 08R04-T47-100A | E68: =VLOOKUP(B68,'[1]26MY_CIV5D_DATA'!B:AS,9,FALSE) -> 201 | F68: =VLOOKUP(B68,'[1]26MY_CIV5D_DATA'!B:AS,10,FALSE) -> 335 | G68: =VLOOKUP(B68,'[1]26MY_CIV5D_DATA'!B:AS,7,FALSE) -> 0.5 | H68: =VLOOKUP(B68,'[1]26MY_CIV5D_DATA'!B:AS,11,FALSE) -> 419 | I68: =VLOOKUP(B68,'[1]26MY_CIV5D_DATA'!B:AS,12,FALSE) -> 0 | J68: =VLOOKUP(B68,'[1]26MY_CIV5D_DATA'!B:AS,13,FALSE) -> 0 | K68: =VLOOKUP($B68,'[1]26MY_CIV5D_DATA'!$B:$AS,14,FALSE) -> 0 | L68: =VLOOKUP(B68,'[1]26MY_CIV5D_DATA'!B:AS,15,FALSE) -> • | M68: =VLOOKUP(B68,'[1]26MY_CIV5D_DATA'!B:AS,16,FALSE) -> • | N68: =VLOOKUP($B68,'[1]26MY_CIV5D_DATA'!$B:$AS,17,FALSE) -> 0 | O68: =VLOOKUP(B68,'[1]26MY_CIV5D_DATA'!B:AS,18,FALSE) -> • | P68: =VLOOKUP(B68,'[1]26MY_CIV5D_DATA'!B:AS,19,FALSE) -> • | Q68: =IF(VLOOKUP(B68,'[1]26MY_CIV5D_DATA'!B:AS,21,FALSE)="","",VLOOKUP(B68,'[1]26MY_CIV5D_DATA'!B:AS,21,FALSE))
B69: 08P09-T47-300 | C69: =VLOOKUP(B69,'[1]26MY_CIV5D_DATA'!B:AS,4,FALSE) -> Garde-boue arrière | D69: =B69 -> 08P09-T47-300 | E69: =VLOOKUP(B69,'[1]26MY_CIV5D_DATA'!B:AS,9,FALSE) -> 61 | F69: =VLOOKUP(B69,'[1]26MY_CIV5D_DATA'!B:AS,10,FALSE) -> 102 | G69: =VLOOKUP(B69,'[1]26MY_CIV5D_DATA'!B:AS,7,FALSE) -> 0.4 | H69: =VLOOKUP(B69,'[1]26MY_CIV5D_DATA'!B:AS,11,FALSE) -> 169.2 | I69: =VLOOKUP(B69,'[1]26MY_CIV5D_DATA'!B:AS,12,FALSE) -> 0 | J69: =VLOOKUP(B69,'[1]26MY_CIV5D_DATA'!B:AS,13,FALSE) -> 0 | K69: =VLOOKUP($B69,'[1]26MY_CIV5D_DATA'!$B:$AS,14,FALSE) -> 0 | L69: =VLOOKUP(B69,'[1]26MY_CIV5D_DATA'!B:AS,15,FALSE) -> • | M69: =VLOOKUP(B69,'[1]26MY_CIV5D_DATA'!B:AS,16,FALSE) -> • | N69: =VLOOKUP($B69,'[1]26MY_CIV5D_DATA'!$B:$AS,17,FALSE) -> 0 | O69: =VLOOKUP(B69,'[1]26MY_CIV5D_DATA'!B:AS,18,FALSE) -> • | P69: =VLOOKUP(B69,'[1]26MY_CIV5D_DATA'!B:AS,19,FALSE) -> N/A | Q69: =IF(VLOOKUP(B69,'[1]26MY_CIV5D_DATA'!B:AS,21,FALSE)="","",VLOOKUP(B69,'[1]26MY_CIV5D_DATA'!B:AS,21,FALSE))
B70: 08R01-T20-300 | C70: =VLOOKUP(B70,'[1]26MY_CIV5D_DATA'!B:AS,4,FALSE) -> Déflecteur de toit ouvrant | D70: =B70 -> 08R01-T20-300 | E70: =VLOOKUP(B70,'[1]26MY_CIV5D_DATA'!B:AS,9,FALSE) -> 169 | F70: =VLOOKUP(B70,'[1]26MY_CIV5D_DATA'!B:AS,10,FALSE) -> 282 | G70: =VLOOKUP(B70,'[1]26MY_CIV5D_DATA'!B:AS,7,FALSE) -> 0.3 | H70: =VLOOKUP(B70,'[1]26MY_CIV5D_DATA'!B:AS,11,FALSE) -> 332.4 | I70: =VLOOKUP(B70,'[1]26MY_CIV5D_DATA'!B:AS,12,FALSE) -> 0 | J70: =VLOOKUP(B70,'[1]26MY_CIV5D_DATA'!B:AS,13,FALSE) -> 0 | K70: =VLOOKUP($B70,'[1]26MY_CIV5D_DATA'!$B:$AS,14,FALSE) -> 0 | L70: =VLOOKUP(B70,'[1]26MY_CIV5D_DATA'!B:AS,15,FALSE) -> • | M70: =VLOOKUP(B70,'[1]26MY_CIV5D_DATA'!B:AS,16,FALSE) -> • | N70: =VLOOKUP($B70,'[1]26MY_CIV5D_DATA'!$B:$AS,17,FALSE) -> 0 | O70: =VLOOKUP(B70,'[1]26MY_CIV5D_DATA'!B:AS,18,FALSE) -> • | P70: =VLOOKUP(B70,'[1]26MY_CIV5D_DATA'!B:AS,19,FALSE) -> N/A | Q70: =IF(VLOOKUP(B70,'[1]26MY_CIV5D_DATA'!B:AS,21,FALSE)="","",VLOOKUP(B70,'[1]26MY_CIV5D_DATA'!B:AS,21,FALSE))
B71: 08P01-T47-100 | C71: =VLOOKUP(B71,'[1]26MY_CIV5D_DATA'!B:AS,4,FALSE) -> Protection de pare-chocs arrière | D71: =B71 -> 08P01-T47-100 | E71: =VLOOKUP(B71,'[1]26MY_CIV5D_DATA'!B:AS,9,FALSE) -> 56 | F71: =VLOOKUP(B71,'[1]26MY_CIV5D_DATA'!B:AS,10,FALSE) -> 80 | G71: =VLOOKUP(B71,'[1]26MY_CIV5D_DATA'!B:AS,7,FALSE) -> 0.1 | H71: =VLOOKUP(B71,'[1]26MY_CIV5D_DATA'!B:AS,11,FALSE) -> 96.8 | I71: =VLOOKUP(B71,'[1]26MY_CIV5D_DATA'!B:AS,12,FALSE) -> 0 | J71: =VLOOKUP(B71,'[1]26MY_CIV5D_DATA'!B:AS,13,FALSE) -> 0 | K71: =VLOOKUP($B71,'[1]26MY_CIV5D_DATA'!$B:$AS,14,FALSE) -> 0 | L71: =VLOOKUP(B71,'[1]26MY_CIV5D_DATA'!B:AS,15,FALSE) -> • | M71: =VLOOKUP(B71,'[1]26MY_CIV5D_DATA'!B:AS,16,FALSE) -> • | N71: =VLOOKUP($B71,'[1]26MY_CIV5D_DATA'!$B:$AS,17,FALSE) -> 0 | O71: =VLOOKUP(B71,'[1]26MY_CIV5D_DATA'!B:AS,18,FALSE) -> • | P71: =VLOOKUP(B71,'[1]26MY_CIV5D_DATA'!B:AS,19,FALSE) -> N/A | Q71: =IF(VLOOKUP(B71,'[1]26MY_CIV5D_DATA'!B:AS,21,FALSE)="","",VLOOKUP(B71,'[1]26MY_CIV5D_DATA'!B:AS,21,FALSE))
B72: 08P20-T20-100A | C72: =VLOOKUP(B72,'[1]26MY_CIV5D_DATA'!B:AS,4,FALSE) -> Pellicule pour rebord de portière | D72: =B72 -> 08P20-T20-100A | E72: =VLOOKUP(B72,'[1]26MY_CIV5D_DATA'!B:AS,9,FALSE) -> 65 | F72: =VLOOKUP(B72,'[1]26MY_CIV5D_DATA'!B:AS,10,FALSE) -> 108 | G72: =VLOOKUP(B72,'[1]26MY_CIV5D_DATA'!B:AS,7,FALSE) -> 0.5 | H72: =VLOOKUP(B72,'[1]26MY_CIV5D_DATA'!B:AS,11,FALSE) -> 192 | I72: =VLOOKUP(B72,'[1]26MY_CIV5D_DATA'!B:AS,12,FALSE) -> 0 | J72: =VLOOKUP(B72,'[1]26MY_CIV5D_DATA'!B:AS,13,FALSE) -> 0 | K72: =VLOOKUP($B72,'[1]26MY_CIV5D_DATA'!$B:$AS,14,FALSE) -> 0 | L72: =VLOOKUP(B72,'[1]26MY_CIV5D_DATA'!B:AS,15,FALSE) -> • | M72: =VLOOKUP(B72,'[1]26MY_CIV5D_DATA'!B:AS,16,FALSE) -> • | N72: =VLOOKUP($B72,'[1]26MY_CIV5D_DATA'!$B:$AS,17,FALSE) -> 0 | O72: =VLOOKUP(B72,'[1]26MY_CIV5D_DATA'!B:AS,18,FALSE) -> • | P72: =VLOOKUP(B72,'[1]26MY_CIV5D_DATA'!B:AS,19,FALSE) -> N/A | Q72: =IF(VLOOKUP(B72,'[1]26MY_CIV5D_DATA'!B:AS,21,FALSE)="","",VLOOKUP(B72,'[1]26MY_CIV5D_DATA'!B:AS,21,FALSE)) -> Ne peut être installé simultanément avec protecteurs de bordure de porte.
B73: 08L02-T47-300 | C73: =VLOOKUP(B73,'[1]26MY_CIV5D_DATA'!B:AS,4,FALSE) -> Porte-bagages de toit | D73: =B73 -> 08L02-T47-300 | E73: =VLOOKUP(B73,'[1]26MY_CIV5D_DATA'!B:AS,9,FALSE) -> 485 | F73: =VLOOKUP(B73,'[1]26MY_CIV5D_DATA'!B:AS,10,FALSE) -> 808 | G73: =VLOOKUP(B73,'[1]26MY_CIV5D_DATA'!B:AS,7,FALSE) -> 0.4 | H73: =VLOOKUP(B73,'[1]26MY_CIV5D_DATA'!B:AS,11,FALSE) -> 875.2 | I73: =VLOOKUP(B73,'[1]26MY_CIV5D_DATA'!B:AS,12,FALSE) -> 0 | J73: =VLOOKUP(B73,'[1]26MY_CIV5D_DATA'!B:AS,13,FALSE) -> 0 | K73: =VLOOKUP($B73,'[1]26MY_CIV5D_DATA'!$B:$AS,14,FALSE) -> 0 | L73: =VLOOKUP(B73,'[1]26MY_CIV5D_DATA'!B:AS,15,FALSE) -> • | M73: =VLOOKUP(B73,'[1]26MY_CIV5D_DATA'!B:AS,16,FALSE) -> • | N73: =VLOOKUP($B73,'[1]26MY_CIV5D_DATA'!$B:$AS,17,FALSE) -> 0 | O73: =VLOOKUP(B73,'[1]26MY_CIV5D_DATA'!B:AS,18,FALSE) -> • | P73: =VLOOKUP(B73,'[1]26MY_CIV5D_DATA'!B:AS,19,FALSE) -> • | Q73: =IF(VLOOKUP(B73,'[1]26MY_CIV5D_DATA'!B:AS,21,FALSE)="","",VLOOKUP(B73,'[1]26MY_CIV5D_DATA'!B:AS,21,FALSE))
B74: 08LXX-E09-XXXX | C74: =VLOOKUP(B74,'[1]26MY_CIV5D_DATA'!B:AS,4,FALSE) -> Accessoires de toit
B75: 08L20-E09-300A | C75: =VLOOKUP(B75,'[1]26MY_CIV5D_DATA'!B:AS,4,FALSE) -> Boîte de toit - moyenne | D75: =B75 -> 08L20-E09-300A | E75: =VLOOKUP(B75,'[1]26MY_CIV5D_DATA'!B:AS,9,FALSE) -> 875 | F75: =VLOOKUP(B75,'[1]26MY_CIV5D_DATA'!B:AS,10,FALSE) -> 1458 | G75: =VLOOKUP(B75,'[1]26MY_CIV5D_DATA'!B:AS,7,FALSE) -> 0.2 | H75: =VLOOKUP(B75,'[1]26MY_CIV5D_DATA'!B:AS,11,FALSE) -> 1491.6 | I75: =VLOOKUP(B75,'[1]26MY_CIV5D_DATA'!B:AS,12,FALSE) -> 0 | J75: =VLOOKUP(B75,'[1]26MY_CIV5D_DATA'!B:AS,13,FALSE) -> 0 | K75: =VLOOKUP($B75,'[1]26MY_CIV5D_DATA'!$B:$AS,14,FALSE) -> 0 | L75: =VLOOKUP(B75,'[1]26MY_CIV5D_DATA'!B:AS,15,FALSE) -> • | M75: =VLOOKUP(B75,'[1]26MY_CIV5D_DATA'!B:AS,16,FALSE) -> • | N75: =VLOOKUP($B75,'[1]26MY_CIV5D_DATA'!$B:$AS,17,FALSE) -> 0 | O75: =VLOOKUP(B75,'[1]26MY_CIV5D_DATA'!B:AS,18,FALSE) -> • | P75: =VLOOKUP(B75,'[1]26MY_CIV5D_DATA'!B:AS,19,FALSE) -> • | Q75: =IF(VLOOKUP(B75,'[1]26MY_CIV5D_DATA'!B:AS,21,FALSE)="","",VLOOKUP(B75,'[1]26MY_CIV5D_DATA'!B:AS,21,FALSE))
B76: 08L20-E09-300B | C76: =VLOOKUP(B76,'[1]26MY_CIV5D_DATA'!B:AS,4,FALSE) -> Boîte de toit - courte | D76: =B76 -> 08L20-E09-300B | E76: =VLOOKUP(B76,'[1]26MY_CIV5D_DATA'!B:AS,9,FALSE) -> 799 | F76: =VLOOKUP(B76,'[1]26MY_CIV5D_DATA'!B:AS,10,FALSE) -> 1332 | G76: =VLOOKUP(B76,'[1]26MY_CIV5D_DATA'!B:AS,7,FALSE) -> 0.2 | H76: =VLOOKUP(B76,'[1]26MY_CIV5D_DATA'!B:AS,11,FALSE) -> 1365.6 | I76: =VLOOKUP(B76,'[1]26MY_CIV5D_DATA'!B:AS,12,FALSE) -> 0 | J76: =VLOOKUP(B76,'[1]26MY_CIV5D_DATA'!B:AS,13,FALSE) -> 0 | K76: =VLOOKUP($B76,'[1]26MY_CIV5D_DATA'!$B:$AS,14,FALSE) -> 0 | L76: =VLOOKUP(B76,'[1]26MY_CIV5D_DATA'!B:AS,15,FALSE) -> • | M76: =VLOOKUP(B76,'[1]26MY_CIV5D_DATA'!B:AS,16,FALSE) -> • | N76: =VLOOKUP($B76,'[1]26MY_CIV5D_DATA'!$B:$AS,17,FALSE) -> 0 | O76: =VLOOKUP(B76,'[1]26MY_CIV5D_DATA'!B:AS,18,FALSE) -> • | P76: =VLOOKUP(B76,'[1]26MY_CIV5D_DATA'!B:AS,19,FALSE) -> • | Q76: =IF(VLOOKUP(B76,'[1]26MY_CIV5D_DATA'!B:AS,21,FALSE)="","",VLOOKUP(B76,'[1]26MY_CIV5D_DATA'!B:AS,21,FALSE))
B77: 08L09-E09-101 | C77: =VLOOKUP(B77,'[1]26MY_CIV5D_DATA'!B:AS,4,FALSE) -> Galerie de toit, fixation pour kayak | D77: =B77 -> 08L09-E09-101 | E77: =VLOOKUP(B77,'[1]26MY_CIV5D_DATA'!B:AS,9,FALSE) -> 430 | F77: =VLOOKUP(B77,'[1]26MY_CIV5D_DATA'!B:AS,10,FALSE) -> 717 | G77: =VLOOKUP(B77,'[1]26MY_CIV5D_DATA'!B:AS,7,FALSE) -> 0.2 | H77: =VLOOKUP(B77,'[1]26MY_CIV5D_DATA'!B:AS,11,FALSE) -> 750.6 | I77: =VLOOKUP(B77,'[1]26MY_CIV5D_DATA'!B:AS,12,FALSE) -> 0 | J77: =VLOOKUP(B77,'[1]26MY_CIV5D_DATA'!B:AS,13,FALSE) -> 0 | K77: =VLOOKUP($B77,'[1]26MY_CIV5D_DATA'!$B:$AS,14,FALSE) -> 0 | L77: =VLOOKUP(B77,'[1]26MY_CIV5D_DATA'!B:AS,15,FALSE) -> • | M77: =VLOOKUP(B77,'[1]26MY_CIV5D_DATA'!B:AS,16,FALSE) -> • | N77: =VLOOKUP($B77,'[1]26MY_CIV5D_DATA'!$B:$AS,17,FALSE) -> 0 | O77: =VLOOKUP(B77,'[1]26MY_CIV5D_DATA'!B:AS,18,FALSE) -> • | P77: =VLOOKUP(B77,'[1]26MY_CIV5D_DATA'!B:AS,19,FALSE) -> • | Q77: =IF(VLOOKUP(B77,'[1]26MY_CIV5D_DATA'!B:AS,21,FALSE)="","",VLOOKUP(B77,'[1]26MY_CIV5D_DATA'!B:AS,21,FALSE))
B78: 08L03-E09-300C | C78: =VLOOKUP(B78,'[1]26MY_CIV5D_DATA'!B:AS,4,FALSE) -> Galerie de toit, Fixation pour skis/planche à neige | D78: =B78 -> 08L03-E09-300C | E78: =VLOOKUP(B78,'[1]26MY_CIV5D_DATA'!B:AS,9,FALSE) -> 415 | F78: =VLOOKUP(B78,'[1]26MY_CIV5D_DATA'!B:AS,10,FALSE) -> 692 | G78: =VLOOKUP(B78,'[1]26MY_CIV5D_DATA'!B:AS,7,FALSE) -> 0.2 | H78: =VLOOKUP(B78,'[1]26MY_CIV5D_DATA'!B:AS,11,FALSE) -> 725.6 | I78: =VLOOKUP(B78,'[1]26MY_CIV5D_DATA'!B:AS,12,FALSE) -> 0 | J78: =VLOOKUP(B78,'[1]26MY_CIV5D_DATA'!B:AS,13,FALSE) -> 0 | K78: =VLOOKUP($B78,'[1]26MY_CIV5D_DATA'!$B:$AS,14,FALSE) -> 0 | L78: =VLOOKUP(B78,'[1]26MY_CIV5D_DATA'!B:AS,15,FALSE) -> • | M78: =VLOOKUP(B78,'[1]26MY_CIV5D_DATA'!B:AS,16,FALSE) -> • | N78: =VLOOKUP($B78,'[1]26MY_CIV5D_DATA'!$B:$AS,17,FALSE) -> 0 | O78: =VLOOKUP(B78,'[1]26MY_CIV5D_DATA'!B:AS,18,FALSE) -> • | P78: =VLOOKUP(B78,'[1]26MY_CIV5D_DATA'!B:AS,19,FALSE) -> • | Q78: =IF(VLOOKUP(B78,'[1]26MY_CIV5D_DATA'!B:AS,21,FALSE)="","",VLOOKUP(B78,'[1]26MY_CIV5D_DATA'!B:AS,21,FALSE))
B79: 08L05-E09-100 | C79: =VLOOKUP(B79,'[1]26MY_CIV5D_DATA'!B:AS,4,FALSE) -> Galerie de toit, Fixation pour planche de surf | D79: =B79 -> 08L05-E09-100 | E79: =VLOOKUP(B79,'[1]26MY_CIV5D_DATA'!B:AS,9,FALSE) -> 207 | F79: =VLOOKUP(B79,'[1]26MY_CIV5D_DATA'!B:AS,10,FALSE) -> 345 | G79: =VLOOKUP(B79,'[1]26MY_CIV5D_DATA'!B:AS,7,FALSE) -> 0.2 | H79: =VLOOKUP(B79,'[1]26MY_CIV5D_DATA'!B:AS,11,FALSE) -> 378.6 | I79: =VLOOKUP(B79,'[1]26MY_CIV5D_DATA'!B:AS,12,FALSE) -> 0 | J79: =VLOOKUP(B79,'[1]26MY_CIV5D_DATA'!B:AS,13,FALSE) -> 0 | K79: =VLOOKUP($B79,'[1]26MY_CIV5D_DATA'!$B:$AS,14,FALSE) -> 0 | L79: =VLOOKUP(B79,'[1]26MY_CIV5D_DATA'!B:AS,15,FALSE) -> • | M79: =VLOOKUP(B79,'[1]26MY_CIV5D_DATA'!B:AS,16,FALSE) -> • | N79: =VLOOKUP($B79,'[1]26MY_CIV5D_DATA'!$B:$AS,17,FALSE) -> 0 | O79: =VLOOKUP(B79,'[1]26MY_CIV5D_DATA'!B:AS,18,FALSE) -> • | P79: =VLOOKUP(B79,'[1]26MY_CIV5D_DATA'!B:AS,19,FALSE) -> • | Q79: =IF(VLOOKUP(B79,'[1]26MY_CIV5D_DATA'!B:AS,21,FALSE)="","",VLOOKUP(B79,'[1]26MY_CIV5D_DATA'!B:AS,21,FALSE))
B80: 08L07-E09-101 | C80: =VLOOKUP(B80,'[1]26MY_CIV5D_DATA'!B:AS,4,FALSE) -> Support à vélo vertical pour porte-bagages de toit | D80: =B80 -> 08L07-E09-101 | E80: =VLOOKUP(B80,'[1]26MY_CIV5D_DATA'!B:AS,9,FALSE) -> 383 | F80: =VLOOKUP(B80,'[1]26MY_CIV5D_DATA'!B:AS,10,FALSE) -> 547 | G80: =VLOOKUP(B80,'[1]26MY_CIV5D_DATA'!B:AS,7,FALSE) -> 0.6 | H80: =VLOOKUP(B80,'[1]26MY_CIV5D_DATA'!B:AS,11,FALSE) -> 647.8 | I80: =VLOOKUP(B80,'[1]26MY_CIV5D_DATA'!B:AS,12,FALSE) -> 0 | J80: =VLOOKUP(B80,'[1]26MY_CIV5D_DATA'!B:AS,13,FALSE) -> 0 | K80: =VLOOKUP($B80,'[1]26MY_CIV5D_DATA'!$B:$AS,14,FALSE) -> 0 | L80: =VLOOKUP(B80,'[1]26MY_CIV5D_DATA'!B:AS,15,FALSE) -> • | M80: =VLOOKUP(B80,'[1]26MY_CIV5D_DATA'!B:AS,16,FALSE) -> • | N80: =VLOOKUP($B80,'[1]26MY_CIV5D_DATA'!$B:$AS,17,FALSE) -> 0 | O80: =VLOOKUP(B80,'[1]26MY_CIV5D_DATA'!B:AS,18,FALSE) -> • | P80: =VLOOKUP(B80,'[1]26MY_CIV5D_DATA'!B:AS,19,FALSE) -> • | Q80: =IF(VLOOKUP(B80,'[1]26MY_CIV5D_DATA'!B:AS,21,FALSE)="","",VLOOKUP(B80,'[1]26MY_CIV5D_DATA'!B:AS,21,FALSE)) -> Un (1) seul porte-vélo permis sur le porte-bagages de toit. Porte-bagages de toit requis.
B81: 08L20-E09-101C | C81: =VLOOKUP(B81,'[1]26MY_CIV5D_DATA'!B:AS,4,FALSE) -> Panier de toit | D81: =B81 -> 08L20-E09-101C | E81: =VLOOKUP(B81,'[1]26MY_CIV5D_DATA'!B:AS,9,FALSE) -> 571 | F81: =VLOOKUP(B81,'[1]26MY_CIV5D_DATA'!B:AS,10,FALSE) -> 952 | G81: =VLOOKUP(B81,'[1]26MY_CIV5D_DATA'!B:AS,7,FALSE) -> 0.4 | H81: =VLOOKUP(B81,'[1]26MY_CIV5D_DATA'!B:AS,11,FALSE) -> 1019.2 | I81: =VLOOKUP(B81,'[1]26MY_CIV5D_DATA'!B:AS,12,FALSE) -> 0 | J81: =VLOOKUP(B81,'[1]26MY_CIV5D_DATA'!B:AS,13,FALSE) -> 0 | K81: =VLOOKUP($B81,'[1]26MY_CIV5D_DATA'!$B:$AS,14,FALSE) -> 0 | L81: =VLOOKUP(B81,'[1]26MY_CIV5D_DATA'!B:AS,15,FALSE) -> • | M81: =VLOOKUP(B81,'[1]26MY_CIV5D_DATA'!B:AS,16,FALSE) -> • | N81: =VLOOKUP($B81,'[1]26MY_CIV5D_DATA'!$B:$AS,17,FALSE) -> 0 | O81: =VLOOKUP(B81,'[1]26MY_CIV5D_DATA'!B:AS,18,FALSE) -> • | P81: =VLOOKUP(B81,'[1]26MY_CIV5D_DATA'!B:AS,19,FALSE) -> • | Q81: =IF(VLOOKUP(B81,'[1]26MY_CIV5D_DATA'!B:AS,21,FALSE)="","",VLOOKUP(B81,'[1]26MY_CIV5D_DATA'!B:AS,21,FALSE)) -> Ensemble de fixation de panier de toit (nécessaire de montage) et porte-bagages de toit requis.
B82: 08L20-E09-100D | C82: =VLOOKUP(B82,'[1]26MY_CIV5D_DATA'!B:AS,4,FALSE) -> Ensemble de fixation de panier de toit | D82: =B82 -> 08L20-E09-100D | E82: =VLOOKUP(B82,'[1]26MY_CIV5D_DATA'!B:AS,9,FALSE) -> 16 | F82: =VLOOKUP(B82,'[1]26MY_CIV5D_DATA'!B:AS,10,FALSE) -> 26 | G82: =VLOOKUP(B82,'[1]26MY_CIV5D_DATA'!B:AS,7,FALSE) -> 0 | H82: =VLOOKUP(B82,'[1]26MY_CIV5D_DATA'!B:AS,11,FALSE) -> 26 | I82: =VLOOKUP(B82,'[1]26MY_CIV5D_DATA'!B:AS,12,FALSE) -> 0 | J82: =VLOOKUP(B82,'[1]26MY_CIV5D_DATA'!B:AS,13,FALSE) -> 0 | K82: =VLOOKUP($B82,'[1]26MY_CIV5D_DATA'!$B:$AS,14,FALSE) -> 0 | L82: =VLOOKUP(B82,'[1]26MY_CIV5D_DATA'!B:AS,15,FALSE) -> • | M82: =VLOOKUP(B82,'[1]26MY_CIV5D_DATA'!B:AS,16,FALSE) -> • | N82: =VLOOKUP($B82,'[1]26MY_CIV5D_DATA'!$B:$AS,17,FALSE) -> 0 | O82: =VLOOKUP(B82,'[1]26MY_CIV5D_DATA'!B:AS,18,FALSE) -> • | P82: =VLOOKUP(B82,'[1]26MY_CIV5D_DATA'!B:AS,19,FALSE) -> •
B83: 08F01-T20-XXXX | C83: =VLOOKUP(B83,'[1]26MY_CIV5D_DATA'!B:AS,4,FALSE) -> Déflecteur de bas de caisse avant
B84: 08F01-T20-130A | C84: =VLOOKUP(B84,'[1]26MY_CIV5D_DATA'!B:AS,4,FALSE) -> Blanc platine nacré (NH-883P) | D84: =B84 -> 08F01-T20-130A | E84: =VLOOKUP(B84,'[1]26MY_CIV5D_DATA'!B:AS,9,FALSE) -> 255 | F84: =VLOOKUP(B84,'[1]26MY_CIV5D_DATA'!B:AS,10,FALSE) -> 425 | G84: =VLOOKUP(B84,'[1]26MY_CIV5D_DATA'!B:AS,7,FALSE) -> 1 | H84: =VLOOKUP(B84,'[1]26MY_CIV5D_DATA'!B:AS,11,FALSE) -> 593 | I84: =VLOOKUP(B84,'[1]26MY_CIV5D_DATA'!B:AS,12,FALSE) -> 0 | J84: =VLOOKUP(B84,'[1]26MY_CIV5D_DATA'!B:AS,13,FALSE) -> 0 | K84: =VLOOKUP($B84,'[1]26MY_CIV5D_DATA'!$B:$AS,14,FALSE) -> 0 | L84: =VLOOKUP(B84,'[1]26MY_CIV5D_DATA'!B:AS,15,FALSE) -> • | M84: =VLOOKUP(B84,'[1]26MY_CIV5D_DATA'!B:AS,16,FALSE) -> • | N84: =VLOOKUP($B84,'[1]26MY_CIV5D_DATA'!$B:$AS,17,FALSE) -> 0 | O84: =VLOOKUP(B84,'[1]26MY_CIV5D_DATA'!B:AS,18,FALSE) -> • | P84: =VLOOKUP(B84,'[1]26MY_CIV5D_DATA'!B:AS,19,FALSE) -> N/A | Q84: =IF(VLOOKUP(B84,'[1]26MY_CIV5D_DATA'!B:AS,21,FALSE)="","",VLOOKUP(B84,'[1]26MY_CIV5D_DATA'!B:AS,21,FALSE))
B85: 08F01-T20-1Z0A | C85: =VLOOKUP(B85,'[1]26MY_CIV5D_DATA'!B:AS,4,FALSE) -> Refl et solaire argent métallisé (NH-932M) | D85: =B85 -> 08F01-T20-1Z0A | E85: =VLOOKUP(B85,'[1]26MY_CIV5D_DATA'!B:AS,9,FALSE) -> 255 | F85: =VLOOKUP(B85,'[1]26MY_CIV5D_DATA'!B:AS,10,FALSE) -> 425 | G85: =VLOOKUP(B85,'[1]26MY_CIV5D_DATA'!B:AS,7,FALSE) -> 1 | H85: =VLOOKUP(B85,'[1]26MY_CIV5D_DATA'!B:AS,11,FALSE) -> 593 | I85: =VLOOKUP(B85,'[1]26MY_CIV5D_DATA'!B:AS,12,FALSE) -> 0 | J85: =VLOOKUP(B85,'[1]26MY_CIV5D_DATA'!B:AS,13,FALSE) -> 0 | K85: =VLOOKUP($B85,'[1]26MY_CIV5D_DATA'!$B:$AS,14,FALSE) -> 0 | L85: =VLOOKUP(B85,'[1]26MY_CIV5D_DATA'!B:AS,15,FALSE) -> • | M85: =VLOOKUP(B85,'[1]26MY_CIV5D_DATA'!B:AS,16,FALSE) -> • | N85: =VLOOKUP($B85,'[1]26MY_CIV5D_DATA'!$B:$AS,17,FALSE) -> 0 | O85: =VLOOKUP(B85,'[1]26MY_CIV5D_DATA'!B:AS,18,FALSE) -> • | P85: =VLOOKUP(B85,'[1]26MY_CIV5D_DATA'!B:AS,19,FALSE) -> N/A
B86: 08F01-T20-170A | C86: =VLOOKUP(B86,'[1]26MY_CIV5D_DATA'!B:AS,4,FALSE) -> Gris météore nacré (NH-904M) | D86: =B86 -> 08F01-T20-170A | E86: =VLOOKUP(B86,'[1]26MY_CIV5D_DATA'!B:AS,9,FALSE) -> 255 | F86: =VLOOKUP(B86,'[1]26MY_CIV5D_DATA'!B:AS,10,FALSE) -> 425 | G86: =VLOOKUP(B86,'[1]26MY_CIV5D_DATA'!B:AS,7,FALSE) -> 1 | H86: =VLOOKUP(B86,'[1]26MY_CIV5D_DATA'!B:AS,11,FALSE) -> 593 | I86: =VLOOKUP(B86,'[1]26MY_CIV5D_DATA'!B:AS,12,FALSE) -> 0 | J86: =VLOOKUP(B86,'[1]26MY_CIV5D_DATA'!B:AS,13,FALSE) -> 0 | K86: =VLOOKUP($B86,'[1]26MY_CIV5D_DATA'!$B:$AS,14,FALSE) -> 0 | L86: =VLOOKUP(B86,'[1]26MY_CIV5D_DATA'!B:AS,15,FALSE) -> N/A | M86: =VLOOKUP(B86,'[1]26MY_CIV5D_DATA'!B:AS,16,FALSE) -> • | N86: =VLOOKUP($B86,'[1]26MY_CIV5D_DATA'!$B:$AS,17,FALSE) -> 0 | O86: =VLOOKUP(B86,'[1]26MY_CIV5D_DATA'!B:AS,18,FALSE) -> N/A | P86: =VLOOKUP(B86,'[1]26MY_CIV5D_DATA'!B:AS,19,FALSE) -> N/A
B87: 08F01-T20-180A | C87: =VLOOKUP(B87,'[1]26MY_CIV5D_DATA'!B:AS,4,FALSE) -> Noir cristal nacré (NH-731P) | D87: =B87 -> 08F01-T20-180A | E87: =VLOOKUP(B87,'[1]26MY_CIV5D_DATA'!B:AS,9,FALSE) -> 255 | F87: =VLOOKUP(B87,'[1]26MY_CIV5D_DATA'!B:AS,10,FALSE) -> 425 | G87: =VLOOKUP(B87,'[1]26MY_CIV5D_DATA'!B:AS,7,FALSE) -> 1 | H87: =VLOOKUP(B87,'[1]26MY_CIV5D_DATA'!B:AS,11,FALSE) -> 593 | I87: =VLOOKUP(B87,'[1]26MY_CIV5D_DATA'!B:AS,12,FALSE) -> 0 | J87: =VLOOKUP(B87,'[1]26MY_CIV5D_DATA'!B:AS,13,FALSE) -> 0 | K87: =VLOOKUP($B87,'[1]26MY_CIV5D_DATA'!$B:$AS,14,FALSE) -> 0 | L87: =VLOOKUP(B87,'[1]26MY_CIV5D_DATA'!B:AS,15,FALSE) -> • | M87: =VLOOKUP(B87,'[1]26MY_CIV5D_DATA'!B:AS,16,FALSE) -> • | N87: =VLOOKUP($B87,'[1]26MY_CIV5D_DATA'!$B:$AS,17,FALSE) -> 0 | O87: =VLOOKUP(B87,'[1]26MY_CIV5D_DATA'!B:AS,18,FALSE) -> • | P87: =VLOOKUP(B87,'[1]26MY_CIV5D_DATA'!B:AS,19,FALSE) -> N/A
B88: 08F01-T20-190A | C88: =VLOOKUP(B88,'[1]26MY_CIV5D_DATA'!B:AS,4,FALSE) -> Rouge rallye (R-513) | D88: =B88 -> 08F01-T20-190A | E88: =VLOOKUP(B88,'[1]26MY_CIV5D_DATA'!B:AS,9,FALSE) -> 255 | F88: =VLOOKUP(B88,'[1]26MY_CIV5D_DATA'!B:AS,10,FALSE) -> 425 | G88: =VLOOKUP(B88,'[1]26MY_CIV5D_DATA'!B:AS,7,FALSE) -> 1 | H88: =VLOOKUP(B88,'[1]26MY_CIV5D_DATA'!B:AS,11,FALSE) -> 593 | I88: =VLOOKUP(B88,'[1]26MY_CIV5D_DATA'!B:AS,12,FALSE) -> 0 | J88: =VLOOKUP(B88,'[1]26MY_CIV5D_DATA'!B:AS,13,FALSE) -> 0 | K88: =VLOOKUP($B88,'[1]26MY_CIV5D_DATA'!$B:$AS,14,FALSE) -> 0 | L88: =VLOOKUP(B88,'[1]26MY_CIV5D_DATA'!B:AS,15,FALSE) -> N/A | M88: =VLOOKUP(B88,'[1]26MY_CIV5D_DATA'!B:AS,16,FALSE) -> • | N88: =VLOOKUP($B88,'[1]26MY_CIV5D_DATA'!$B:$AS,17,FALSE) -> 0 | O88: =VLOOKUP(B88,'[1]26MY_CIV5D_DATA'!B:AS,18,FALSE) -> • | P88: =VLOOKUP(B88,'[1]26MY_CIV5D_DATA'!B:AS,19,FALSE) -> N/A
B89: 08F01-T20-1U0A | C89: =VLOOKUP(B89,'[1]26MY_CIV5D_DATA'!B:AS,4,FALSE) -> Bleu turbo nacré (B-637P) | D89: =B89 -> 08F01-T20-1U0A | E89: =VLOOKUP(B89,'[1]26MY_CIV5D_DATA'!B:AS,9,FALSE) -> 255 | F89: =VLOOKUP(B89,'[1]26MY_CIV5D_DATA'!B:AS,10,FALSE) -> 425 | G89: =VLOOKUP(B89,'[1]26MY_CIV5D_DATA'!B:AS,7,FALSE) -> 1 | H89: =VLOOKUP(B89,'[1]26MY_CIV5D_DATA'!B:AS,11,FALSE) -> 593 | I89: =VLOOKUP(B89,'[1]26MY_CIV5D_DATA'!B:AS,12,FALSE) -> 0 | J89: =VLOOKUP(B89,'[1]26MY_CIV5D_DATA'!B:AS,13,FALSE) -> 0 | K89: =VLOOKUP($B89,'[1]26MY_CIV5D_DATA'!$B:$AS,14,FALSE) -> 0 | L89: =VLOOKUP(B89,'[1]26MY_CIV5D_DATA'!B:AS,15,FALSE) -> N/A | M89: =VLOOKUP(B89,'[1]26MY_CIV5D_DATA'!B:AS,16,FALSE) -> N/A | N89: =VLOOKUP($B89,'[1]26MY_CIV5D_DATA'!$B:$AS,17,FALSE) -> 0 | O89: =VLOOKUP(B89,'[1]26MY_CIV5D_DATA'!B:AS,18,FALSE) -> • | P89: =VLOOKUP(B89,'[1]26MY_CIV5D_DATA'!B:AS,19,FALSE) -> N/A
B90: 08F02-T47-XXX | C90: =VLOOKUP(B90,'[1]26MY_CIV5D_DATA'!B:AS,4,FALSE) -> Déflecteur de hayon - HPD
B91: 08F02-T47-130 | C91: =VLOOKUP(B91,'[1]26MY_CIV5D_DATA'!B:AS,4,FALSE) -> Blanc platine nacré (NH-883P) | D91: =B91 -> 08F02-T47-130 | E91: =VLOOKUP(B91,'[1]26MY_CIV5D_DATA'!B:AS,9,FALSE) -> 460 | F91: =VLOOKUP(B91,'[1]26MY_CIV5D_DATA'!B:AS,10,FALSE) -> 767 | G91: =VLOOKUP(B91,'[1]26MY_CIV5D_DATA'!B:AS,7,FALSE) -> 1.2 | H91: =VLOOKUP(B91,'[1]26MY_CIV5D_DATA'!B:AS,11,FALSE) -> 968.6 | I91: =VLOOKUP(B91,'[1]26MY_CIV5D_DATA'!B:AS,12,FALSE) -> 0 | J91: =VLOOKUP(B91,'[1]26MY_CIV5D_DATA'!B:AS,13,FALSE) -> 0 | K91: =VLOOKUP($B91,'[1]26MY_CIV5D_DATA'!$B:$AS,14,FALSE) -> 0 | L91: =VLOOKUP(B91,'[1]26MY_CIV5D_DATA'!B:AS,15,FALSE) -> • | M91: =VLOOKUP(B91,'[1]26MY_CIV5D_DATA'!B:AS,16,FALSE) -> • | N91: =VLOOKUP($B91,'[1]26MY_CIV5D_DATA'!$B:$AS,17,FALSE) -> 0 | O91: =VLOOKUP(B91,'[1]26MY_CIV5D_DATA'!B:AS,18,FALSE) -> • | P91: =VLOOKUP(B91,'[1]26MY_CIV5D_DATA'!B:AS,19,FALSE) -> N/A | Q91: =IF(VLOOKUP(B91,'[1]26MY_CIV5D_DATA'!B:AS,21,FALSE)="","",VLOOKUP(B91,'[1]26MY_CIV5D_DATA'!B:AS,21,FALSE))
B92: 08F02-T47-1Z0 | C92: =VLOOKUP(B92,'[1]26MY_CIV5D_DATA'!B:AS,4,FALSE) -> Refl et solaire argent métallisé (NH-932M) | D92: =B92 -> 08F02-T47-1Z0 | E92: =VLOOKUP(B92,'[1]26MY_CIV5D_DATA'!B:AS,9,FALSE) -> 460 | F92: =VLOOKUP(B92,'[1]26MY_CIV5D_DATA'!B:AS,10,FALSE) -> 767 | G92: =VLOOKUP(B92,'[1]26MY_CIV5D_DATA'!B:AS,7,FALSE) -> 1.2 | H92: =VLOOKUP(B92,'[1]26MY_CIV5D_DATA'!B:AS,11,FALSE) -> 968.6 | I92: =VLOOKUP(B92,'[1]26MY_CIV5D_DATA'!B:AS,12,FALSE) -> 0 | J92: =VLOOKUP(B92,'[1]26MY_CIV5D_DATA'!B:AS,13,FALSE) -> 0 | K92: =VLOOKUP($B92,'[1]26MY_CIV5D_DATA'!$B:$AS,14,FALSE) -> 0 | L92: =VLOOKUP(B92,'[1]26MY_CIV5D_DATA'!B:AS,15,FALSE) -> • | M92: =VLOOKUP(B92,'[1]26MY_CIV5D_DATA'!B:AS,16,FALSE) -> N/A | N92: =VLOOKUP($B92,'[1]26MY_CIV5D_DATA'!$B:$AS,17,FALSE) -> 0 | O92: =VLOOKUP(B92,'[1]26MY_CIV5D_DATA'!B:AS,18,FALSE) -> N/A | P92: =VLOOKUP(B92,'[1]26MY_CIV5D_DATA'!B:AS,19,FALSE) -> N/A
B93: 08F02-T47-170 | C93: =VLOOKUP(B93,'[1]26MY_CIV5D_DATA'!B:AS,4,FALSE) -> Gris météore nacré (NH-904M) | D93: =B93 -> 08F02-T47-170 | E93: =VLOOKUP(B93,'[1]26MY_CIV5D_DATA'!B:AS,9,FALSE) -> 460 | F93: =VLOOKUP(B93,'[1]26MY_CIV5D_DATA'!B:AS,10,FALSE) -> 767 | G93: =VLOOKUP(B93,'[1]26MY_CIV5D_DATA'!B:AS,7,FALSE) -> 1.2 | H93: =VLOOKUP(B93,'[1]26MY_CIV5D_DATA'!B:AS,11,FALSE) -> 968.6 | I93: =VLOOKUP(B93,'[1]26MY_CIV5D_DATA'!B:AS,12,FALSE) -> 0 | J93: =VLOOKUP(B93,'[1]26MY_CIV5D_DATA'!B:AS,13,FALSE) -> 0 | K93: =VLOOKUP($B93,'[1]26MY_CIV5D_DATA'!$B:$AS,14,FALSE) -> 0 | L93: =VLOOKUP(B93,'[1]26MY_CIV5D_DATA'!B:AS,15,FALSE) -> N/A | M93: =VLOOKUP(B93,'[1]26MY_CIV5D_DATA'!B:AS,16,FALSE) -> • | N93: =VLOOKUP($B93,'[1]26MY_CIV5D_DATA'!$B:$AS,17,FALSE) -> 0 | O93: =VLOOKUP(B93,'[1]26MY_CIV5D_DATA'!B:AS,18,FALSE) -> N/A | P93: =VLOOKUP(B93,'[1]26MY_CIV5D_DATA'!B:AS,19,FALSE) -> N/A
B94: 08F02-T47-180 | C94: =VLOOKUP(B94,'[1]26MY_CIV5D_DATA'!B:AS,4,FALSE) -> Noir cristal nacré (NH-731P) | D94: =B94 -> 08F02-T47-180 | E94: =VLOOKUP(B94,'[1]26MY_CIV5D_DATA'!B:AS,9,FALSE) -> 460 | F94: =VLOOKUP(B94,'[1]26MY_CIV5D_DATA'!B:AS,10,FALSE) -> 767 | G94: =VLOOKUP(B94,'[1]26MY_CIV5D_DATA'!B:AS,7,FALSE) -> 1.2 | H94: =VLOOKUP(B94,'[1]26MY_CIV5D_DATA'!B:AS,11,FALSE) -> 968.6 | I94: =VLOOKUP(B94,'[1]26MY_CIV5D_DATA'!B:AS,12,FALSE) -> 0 | J94: =VLOOKUP(B94,'[1]26MY_CIV5D_DATA'!B:AS,13,FALSE) -> 0 | K94: =VLOOKUP($B94,'[1]26MY_CIV5D_DATA'!$B:$AS,14,FALSE) -> 0 | L94: =VLOOKUP(B94,'[1]26MY_CIV5D_DATA'!B:AS,15,FALSE) -> • | M94: =VLOOKUP(B94,'[1]26MY_CIV5D_DATA'!B:AS,16,FALSE) -> • | N94: =VLOOKUP($B94,'[1]26MY_CIV5D_DATA'!$B:$AS,17,FALSE) -> 0 | O94: =VLOOKUP(B94,'[1]26MY_CIV5D_DATA'!B:AS,18,FALSE) -> • | P94: =VLOOKUP(B94,'[1]26MY_CIV5D_DATA'!B:AS,19,FALSE) -> N/A
B95: 08F02-T47-190 | C95: =VLOOKUP(B95,'[1]26MY_CIV5D_DATA'!B:AS,4,FALSE) -> Rouge rallye (R-513) | D95: =B95 -> 08F02-T47-190 | E95: =VLOOKUP(B95,'[1]26MY_CIV5D_DATA'!B:AS,9,FALSE) -> 460 | F95: =VLOOKUP(B95,'[1]26MY_CIV5D_DATA'!B:AS,10,FALSE) -> 767 | G95: =VLOOKUP(B95,'[1]26MY_CIV5D_DATA'!B:AS,7,FALSE) -> 1.2 | H95: =VLOOKUP(B95,'[1]26MY_CIV5D_DATA'!B:AS,11,FALSE) -> 968.6 | I95: =VLOOKUP(B95,'[1]26MY_CIV5D_DATA'!B:AS,12,FALSE) -> 0 | J95: =VLOOKUP(B95,'[1]26MY_CIV5D_DATA'!B:AS,13,FALSE) -> 0 | K95: =VLOOKUP($B95,'[1]26MY_CIV5D_DATA'!$B:$AS,14,FALSE) -> 0 | L95: =VLOOKUP(B95,'[1]26MY_CIV5D_DATA'!B:AS,15,FALSE) -> N/A | M95: =VLOOKUP(B95,'[1]26MY_CIV5D_DATA'!B:AS,16,FALSE) -> • | N95: =VLOOKUP($B95,'[1]26MY_CIV5D_DATA'!$B:$AS,17,FALSE) -> 0 | O95: =VLOOKUP(B95,'[1]26MY_CIV5D_DATA'!B:AS,18,FALSE) -> • | P95: =VLOOKUP(B95,'[1]26MY_CIV5D_DATA'!B:AS,19,FALSE) -> N/A
B96: 08F02-T47-1U0 | C96: =VLOOKUP(B96,'[1]26MY_CIV5D_DATA'!B:AS,4,FALSE) -> Bleu turbo nacré (B-637P) | D96: =B96 -> 08F02-T47-1U0 | E96: =VLOOKUP(B96,'[1]26MY_CIV5D_DATA'!B:AS,9,FALSE) -> 460 | F96: =VLOOKUP(B96,'[1]26MY_CIV5D_DATA'!B:AS,10,FALSE) -> 767 | G96: =VLOOKUP(B96,'[1]26MY_CIV5D_DATA'!B:AS,7,FALSE) -> 1.2 | H96: =VLOOKUP(B96,'[1]26MY_CIV5D_DATA'!B:AS,11,FALSE) -> 968.6 | I96: =VLOOKUP(B96,'[1]26MY_CIV5D_DATA'!B:AS,12,FALSE) -> 0 | J96: =VLOOKUP(B96,'[1]26MY_CIV5D_DATA'!B:AS,13,FALSE) -> 0 | K96: =VLOOKUP($B96,'[1]26MY_CIV5D_DATA'!$B:$AS,14,FALSE) -> 0 | L96: =VLOOKUP(B96,'[1]26MY_CIV5D_DATA'!B:AS,15,FALSE) -> N/A | M96: =VLOOKUP(B96,'[1]26MY_CIV5D_DATA'!B:AS,16,FALSE) -> N/A | N96: =VLOOKUP($B96,'[1]26MY_CIV5D_DATA'!$B:$AS,17,FALSE) -> 0 | O96: =VLOOKUP(B96,'[1]26MY_CIV5D_DATA'!B:AS,18,FALSE) -> • | P96: =VLOOKUP(B96,'[1]26MY_CIV5D_DATA'!B:AS,19,FALSE) -> N/A
B97: 08P05-T20-XXXX | C97: =VLOOKUP(B97,'[1]26MY_CIV5D_DATA'!B:AS,4,FALSE) -> Moulure latérale
B98: 08P05-T20-130 | C98: =VLOOKUP(B98,'[1]26MY_CIV5D_DATA'!B:AS,4,FALSE) -> Blanc platine nacré (NH-883P) | D98: =B98 -> 08P05-T20-130 | E98: =VLOOKUP(B98,'[1]26MY_CIV5D_DATA'!B:AS,9,FALSE) -> 209 | F98: =VLOOKUP(B98,'[1]26MY_CIV5D_DATA'!B:AS,10,FALSE) -> 348 | G98: =VLOOKUP(B98,'[1]26MY_CIV5D_DATA'!B:AS,7,FALSE) -> 0.4 | H98: =VLOOKUP(B98,'[1]26MY_CIV5D_DATA'!B:AS,11,FALSE) -> 415.2 | I98: =VLOOKUP(B98,'[1]26MY_CIV5D_DATA'!B:AS,12,FALSE) -> 0 | J98: =VLOOKUP(B98,'[1]26MY_CIV5D_DATA'!B:AS,13,FALSE) -> 0 | K98: =VLOOKUP($B98,'[1]26MY_CIV5D_DATA'!$B:$AS,14,FALSE) -> 0 | L98: =VLOOKUP(B98,'[1]26MY_CIV5D_DATA'!B:AS,15,FALSE) -> • | M98: =VLOOKUP(B98,'[1]26MY_CIV5D_DATA'!B:AS,16,FALSE) -> • | N98: =VLOOKUP($B98,'[1]26MY_CIV5D_DATA'!$B:$AS,17,FALSE) -> 0 | O98: =VLOOKUP(B98,'[1]26MY_CIV5D_DATA'!B:AS,18,FALSE) -> • | P98: =VLOOKUP(B98,'[1]26MY_CIV5D_DATA'!B:AS,19,FALSE) -> N/A | Q98: =IF(VLOOKUP(B98,'[1]26MY_CIV5D_DATA'!B:AS,21,FALSE)="","",VLOOKUP(B98,'[1]26MY_CIV5D_DATA'!B:AS,21,FALSE))
B99: 08P05-T20-1Z0 | C99: =VLOOKUP(B99,'[1]26MY_CIV5D_DATA'!B:AS,4,FALSE) -> Refl et solaire argent métallisé (NH-932M) | D99: =B99 -> 08P05-T20-1Z0 | E99: =VLOOKUP(B99,'[1]26MY_CIV5D_DATA'!B:AS,9,FALSE) -> 209 | F99: =VLOOKUP(B99,'[1]26MY_CIV5D_DATA'!B:AS,10,FALSE) -> 348 | G99: =VLOOKUP(B99,'[1]26MY_CIV5D_DATA'!B:AS,7,FALSE) -> 0.4 | H99: =VLOOKUP(B99,'[1]26MY_CIV5D_DATA'!B:AS,11,FALSE) -> 415.2 | I99: =VLOOKUP(B99,'[1]26MY_CIV5D_DATA'!B:AS,12,FALSE) -> 0 | J99: =VLOOKUP(B99,'[1]26MY_CIV5D_DATA'!B:AS,13,FALSE) -> 0 | K99: =VLOOKUP($B99,'[1]26MY_CIV5D_DATA'!$B:$AS,14,FALSE) -> 0 | L99: =VLOOKUP(B99,'[1]26MY_CIV5D_DATA'!B:AS,15,FALSE) -> • | M99: =VLOOKUP(B99,'[1]26MY_CIV5D_DATA'!B:AS,16,FALSE) -> N/A | N99: =VLOOKUP($B99,'[1]26MY_CIV5D_DATA'!$B:$AS,17,FALSE) -> 0 | O99: =VLOOKUP(B99,'[1]26MY_CIV5D_DATA'!B:AS,18,FALSE) -> N/A | P99: =VLOOKUP(B99,'[1]26MY_CIV5D_DATA'!B:AS,19,FALSE) -> N/A
B100: 08P05-T20-170 | C100: =VLOOKUP(B100,'[1]26MY_CIV5D_DATA'!B:AS,4,FALSE) -> Gris météore nacré (NH-904M) | D100: =B100 -> 08P05-T20-170 | E100: =VLOOKUP(B100,'[1]26MY_CIV5D_DATA'!B:AS,9,FALSE) -> 209 | F100: =VLOOKUP(B100,'[1]26MY_CIV5D_DATA'!B:AS,10,FALSE) -> 348 | G100: =VLOOKUP(B100,'[1]26MY_CIV5D_DATA'!B:AS,7,FALSE) -> 0.4 | H100: =VLOOKUP(B100,'[1]26MY_CIV5D_DATA'!B:AS,11,FALSE) -> 415.2 | I100: =VLOOKUP(B100,'[1]26MY_CIV5D_DATA'!B:AS,12,FALSE) -> 0 | J100: =VLOOKUP(B100,'[1]26MY_CIV5D_DATA'!B:AS,13,FALSE) -> 0 | K100: =VLOOKUP($B100,'[1]26MY_CIV5D_DATA'!$B:$AS,14,FALSE) -> 0 | L100: =VLOOKUP(B100,'[1]26MY_CIV5D_DATA'!B:AS,15,FALSE) -> N/A | M100: =VLOOKUP(B100,'[1]26MY_CIV5D_DATA'!B:AS,16,FALSE) -> • | N100: =VLOOKUP($B100,'[1]26MY_CIV5D_DATA'!$B:$AS,17,FALSE) -> 0 | O100: =VLOOKUP(B100,'[1]26MY_CIV5D_DATA'!B:AS,18,FALSE) -> N/A | P100: =VLOOKUP(B100,'[1]26MY_CIV5D_DATA'!B:AS,19,FALSE) -> N/A
B101: 08P05-T20-180 | C101: =VLOOKUP(B101,'[1]26MY_CIV5D_DATA'!B:AS,4,FALSE) -> Noir cristal nacré (NH-731P) | D101: =B101 -> 08P05-T20-180 | E101: =VLOOKUP(B101,'[1]26MY_CIV5D_DATA'!B:AS,9,FALSE) -> 209 | F101: =VLOOKUP(B101,'[1]26MY_CIV5D_DATA'!B:AS,10,FALSE) -> 348 | G101: =VLOOKUP(B101,'[1]26MY_CIV5D_DATA'!B:AS,7,FALSE) -> 0.4 | H101: =VLOOKUP(B101,'[1]26MY_CIV5D_DATA'!B:AS,11,FALSE) -> 415.2 | I101: =VLOOKUP(B101,'[1]26MY_CIV5D_DATA'!B:AS,12,FALSE) -> 0 | J101: =VLOOKUP(B101,'[1]26MY_CIV5D_DATA'!B:AS,13,FALSE) -> 0 | K101: =VLOOKUP($B101,'[1]26MY_CIV5D_DATA'!$B:$AS,14,FALSE) -> 0 | L101: =VLOOKUP(B101,'[1]26MY_CIV5D_DATA'!B:AS,15,FALSE) -> • | M101: =VLOOKUP(B101,'[1]26MY_CIV5D_DATA'!B:AS,16,FALSE) -> • | N101: =VLOOKUP($B101,'[1]26MY_CIV5D_DATA'!$B:$AS,17,FALSE) -> 0 | O101: =VLOOKUP(B101,'[1]26MY_CIV5D_DATA'!B:AS,18,FALSE) -> • | P101: =VLOOKUP(B101,'[1]26MY_CIV5D_DATA'!B:AS,19,FALSE) -> N/A
B102: 08P05-T20-190 | C102: =VLOOKUP(B102,'[1]26MY_CIV5D_DATA'!B:AS,4,FALSE) -> Rouge rallye (R-513) | D102: =B102 -> 08P05-T20-190 | E102: =VLOOKUP(B102,'[1]26MY_CIV5D_DATA'!B:AS,9,FALSE) -> 209 | F102: =VLOOKUP(B102,'[1]26MY_CIV5D_DATA'!B:AS,10,FALSE) -> 348 | G102: =VLOOKUP(B102,'[1]26MY_CIV5D_DATA'!B:AS,7,FALSE) -> 0.4 | H102: =VLOOKUP(B102,'[1]26MY_CIV5D_DATA'!B:AS,11,FALSE) -> 415.2 | I102: =VLOOKUP(B102,'[1]26MY_CIV5D_DATA'!B:AS,12,FALSE) -> 0 | J102: =VLOOKUP(B102,'[1]26MY_CIV5D_DATA'!B:AS,13,FALSE) -> 0 | K102: =VLOOKUP($B102,'[1]26MY_CIV5D_DATA'!$B:$AS,14,FALSE) -> 0 | L102: =VLOOKUP(B102,'[1]26MY_CIV5D_DATA'!B:AS,15,FALSE) -> N/A | M102: =VLOOKUP(B102,'[1]26MY_CIV5D_DATA'!B:AS,16,FALSE) -> • | N102: =VLOOKUP($B102,'[1]26MY_CIV5D_DATA'!$B:$AS,17,FALSE) -> 0 | O102: =VLOOKUP(B102,'[1]26MY_CIV5D_DATA'!B:AS,18,FALSE) -> • | P102: =VLOOKUP(B102,'[1]26MY_CIV5D_DATA'!B:AS,19,FALSE) -> N/A
B103: 08P05-T20-1U0 | C103: =VLOOKUP(B103,'[1]26MY_CIV5D_DATA'!B:AS,4,FALSE) -> Bleu turbo nacré (B-637P) | D103: =B103 -> 08P05-T20-1U0 | E103: =VLOOKUP(B103,'[1]26MY_CIV5D_DATA'!B:AS,9,FALSE) -> 209 | F103: =VLOOKUP(B103,'[1]26MY_CIV5D_DATA'!B:AS,10,FALSE) -> 348 | G103: =VLOOKUP(B103,'[1]26MY_CIV5D_DATA'!B:AS,7,FALSE) -> 0.4 | H103: =VLOOKUP(B103,'[1]26MY_CIV5D_DATA'!B:AS,11,FALSE) -> 415.2 | I103: =VLOOKUP(B103,'[1]26MY_CIV5D_DATA'!B:AS,12,FALSE) -> 0 | J103: =VLOOKUP(B103,'[1]26MY_CIV5D_DATA'!B:AS,13,FALSE) -> 0 | K103: =VLOOKUP($B103,'[1]26MY_CIV5D_DATA'!$B:$AS,14,FALSE) -> 0 | L103: =VLOOKUP(B103,'[1]26MY_CIV5D_DATA'!B:AS,15,FALSE) -> N/A | M103: =VLOOKUP(B103,'[1]26MY_CIV5D_DATA'!B:AS,16,FALSE) -> N/A | N103: =VLOOKUP($B103,'[1]26MY_CIV5D_DATA'!$B:$AS,17,FALSE) -> 0 | O103: =VLOOKUP(B103,'[1]26MY_CIV5D_DATA'!B:AS,18,FALSE) -> • | P103: =VLOOKUP(B103,'[1]26MY_CIV5D_DATA'!B:AS,19,FALSE) -> N/A
B104: 08P20-T20-XXXX | C104: =VLOOKUP(B104,'[1]26MY_CIV5D_DATA'!B:AS,4,FALSE) -> Protecteurs de bordure de porte | D104: =B104 -> 08P20-T20-XXXX | E104: =VLOOKUP(B104,'[1]26MY_CIV5D_DATA'!B:AS,9,FALSE) -> 136 | F104: =VLOOKUP(B104,'[1]26MY_CIV5D_DATA'!B:AS,10,FALSE) -> 194 | G104: =VLOOKUP(B104,'[1]26MY_CIV5D_DATA'!B:AS,7,FALSE) -> 0.4 | H104: =VLOOKUP(B104,'[1]26MY_CIV5D_DATA'!B:AS,11,FALSE) -> 261.2 | I104: =VLOOKUP(B104,'[1]26MY_CIV5D_DATA'!B:AS,12,FALSE) -> 0 | J104: =VLOOKUP(B104,'[1]26MY_CIV5D_DATA'!B:AS,13,FALSE) -> 0 | K104: =VLOOKUP($B104,'[1]26MY_CIV5D_DATA'!$B:$AS,14,FALSE) -> 0 | L104: =VLOOKUP(B104,'[1]26MY_CIV5D_DATA'!B:AS,15,FALSE) -> • | M104: =VLOOKUP(B104,'[1]26MY_CIV5D_DATA'!B:AS,16,FALSE) -> • | N104: =VLOOKUP($B104,'[1]26MY_CIV5D_DATA'!$B:$AS,17,FALSE) -> 0 | O104: =VLOOKUP(B104,'[1]26MY_CIV5D_DATA'!B:AS,18,FALSE) -> • | P104: =VLOOKUP(B104,'[1]26MY_CIV5D_DATA'!B:AS,19,FALSE) -> N/A
B105: 08P20-T20-XXXX | C105: =VLOOKUP(B105,'[1]26MY_CIV5D_DATA'!B:AS,4,FALSE) -> Protecteurs de bordure de porte
B106: 08P20-T20-130 | C106: =VLOOKUP(B106,'[1]26MY_CIV5D_DATA'!B:AS,4,FALSE) -> Blanc platine nacré (NH-883P) | D106: =B106 -> 08P20-T20-130 | E106: =VLOOKUP(B106,'[1]26MY_CIV5D_DATA'!B:AS,9,FALSE) -> 136 | F106: =VLOOKUP(B106,'[1]26MY_CIV5D_DATA'!B:AS,10,FALSE) -> 194 | G106: =VLOOKUP(B106,'[1]26MY_CIV5D_DATA'!B:AS,7,FALSE) -> 0.4 | H106: =VLOOKUP(B106,'[1]26MY_CIV5D_DATA'!B:AS,11,FALSE) -> 261.2 | I106: =VLOOKUP(B106,'[1]26MY_CIV5D_DATA'!B:AS,12,FALSE) -> 0 | J106: =VLOOKUP(B106,'[1]26MY_CIV5D_DATA'!B:AS,13,FALSE) -> 0 | K106: =VLOOKUP($B106,'[1]26MY_CIV5D_DATA'!$B:$AS,14,FALSE) -> 0 | L106: =VLOOKUP(B106,'[1]26MY_CIV5D_DATA'!B:AS,15,FALSE) -> • | M106: =VLOOKUP(B106,'[1]26MY_CIV5D_DATA'!B:AS,16,FALSE) -> • | N106: =VLOOKUP($B106,'[1]26MY_CIV5D_DATA'!$B:$AS,17,FALSE) -> 0 | O106: =VLOOKUP(B106,'[1]26MY_CIV5D_DATA'!B:AS,18,FALSE) -> • | P106: =VLOOKUP(B106,'[1]26MY_CIV5D_DATA'!B:AS,19,FALSE) -> N/A | Q106: =IF(VLOOKUP(B106,'[1]26MY_CIV5D_DATA'!B:AS,21,FALSE)="","",VLOOKUP(B106,'[1]26MY_CIV5D_DATA'!B:AS,21,FALSE))
B107: 08P20-T20-1Z0 | C107: =VLOOKUP(B107,'[1]26MY_CIV5D_DATA'!B:AS,4,FALSE) -> Refl et solaire argent métallisé (NH-932M) | D107: =B107 -> 08P20-T20-1Z0 | E107: =VLOOKUP(B107,'[1]26MY_CIV5D_DATA'!B:AS,9,FALSE) -> 136 | F107: =VLOOKUP(B107,'[1]26MY_CIV5D_DATA'!B:AS,10,FALSE) -> 194 | G107: =VLOOKUP(B107,'[1]26MY_CIV5D_DATA'!B:AS,7,FALSE) -> 0.4 | H107: =VLOOKUP(B107,'[1]26MY_CIV5D_DATA'!B:AS,11,FALSE) -> 261.2 | I107: =VLOOKUP(B107,'[1]26MY_CIV5D_DATA'!B:AS,12,FALSE) -> 0 | J107: =VLOOKUP(B107,'[1]26MY_CIV5D_DATA'!B:AS,13,FALSE) -> 0 | K107: =VLOOKUP($B107,'[1]26MY_CIV5D_DATA'!$B:$AS,14,FALSE) -> 0 | L107: =VLOOKUP(B107,'[1]26MY_CIV5D_DATA'!B:AS,15,FALSE) -> • | M107: =VLOOKUP(B107,'[1]26MY_CIV5D_DATA'!B:AS,16,FALSE) -> N/A | N107: =VLOOKUP($B107,'[1]26MY_CIV5D_DATA'!$B:$AS,17,FALSE) -> 0 | O107: =VLOOKUP(B107,'[1]26MY_CIV5D_DATA'!B:AS,18,FALSE) -> N/A | P107: =VLOOKUP(B107,'[1]26MY_CIV5D_DATA'!B:AS,19,FALSE) -> N/A
B108: 08P20-T20-170 | C108: =VLOOKUP(B108,'[1]26MY_CIV5D_DATA'!B:AS,4,FALSE) -> Gris météore nacré (NH-904M) | D108: =B108 -> 08P20-T20-170 | E108: =VLOOKUP(B108,'[1]26MY_CIV5D_DATA'!B:AS,9,FALSE) -> 48.99 | F108: =VLOOKUP(B108,'[1]26MY_CIV5D_DATA'!B:AS,10,FALSE) -> 73.99 | G108: =VLOOKUP(B108,'[1]26MY_CIV5D_DATA'!B:AS,7,FALSE) -> 0.4 | H108: =VLOOKUP(B108,'[1]26MY_CIV5D_DATA'!B:AS,11,FALSE) -> 141.19 | I108: =VLOOKUP(B108,'[1]26MY_CIV5D_DATA'!B:AS,12,FALSE) -> 0 | J108: =VLOOKUP(B108,'[1]26MY_CIV5D_DATA'!B:AS,13,FALSE) -> 0 | K108: =VLOOKUP($B108,'[1]26MY_CIV5D_DATA'!$B:$AS,14,FALSE) -> 0 | L108: =VLOOKUP(B108,'[1]26MY_CIV5D_DATA'!B:AS,15,FALSE) -> N/A | M108: =VLOOKUP(B108,'[1]26MY_CIV5D_DATA'!B:AS,16,FALSE) -> • | N108: =VLOOKUP($B108,'[1]26MY_CIV5D_DATA'!$B:$AS,17,FALSE) -> 0 | O108: =VLOOKUP(B108,'[1]26MY_CIV5D_DATA'!B:AS,18,FALSE) -> N/A | P108: =VLOOKUP(B108,'[1]26MY_CIV5D_DATA'!B:AS,19,FALSE) -> N/A
B109: 08P20-T20-180 | C109: =VLOOKUP(B109,'[1]26MY_CIV5D_DATA'!B:AS,4,FALSE) -> Noir cristal nacré (NH-731P) | D109: =B109 -> 08P20-T20-180 | E109: =VLOOKUP(B109,'[1]26MY_CIV5D_DATA'!B:AS,9,FALSE) -> 136 | F109: =VLOOKUP(B109,'[1]26MY_CIV5D_DATA'!B:AS,10,FALSE) -> 194 | G109: =VLOOKUP(B109,'[1]26MY_CIV5D_DATA'!B:AS,7,FALSE) -> 0.4 | H109: =VLOOKUP(B109,'[1]26MY_CIV5D_DATA'!B:AS,11,FALSE) -> 261.2 | I109: =VLOOKUP(B109,'[1]26MY_CIV5D_DATA'!B:AS,12,FALSE) -> 0 | J109: =VLOOKUP(B109,'[1]26MY_CIV5D_DATA'!B:AS,13,FALSE) -> 0 | K109: =VLOOKUP($B109,'[1]26MY_CIV5D_DATA'!$B:$AS,14,FALSE) -> 0 | L109: =VLOOKUP(B109,'[1]26MY_CIV5D_DATA'!B:AS,15,FALSE) -> • | M109: =VLOOKUP(B109,'[1]26MY_CIV5D_DATA'!B:AS,16,FALSE) -> • | N109: =VLOOKUP($B109,'[1]26MY_CIV5D_DATA'!$B:$AS,17,FALSE) -> 0 | O109: =VLOOKUP(B109,'[1]26MY_CIV5D_DATA'!B:AS,18,FALSE) -> • | P109: =VLOOKUP(B109,'[1]26MY_CIV5D_DATA'!B:AS,19,FALSE) -> N/A
B110: 08P20-T20-190 | C110: =VLOOKUP(B110,'[1]26MY_CIV5D_DATA'!B:AS,4,FALSE) -> Rouge rallye (R-513) | D110: =B110 -> 08P20-T20-190 | E110: =VLOOKUP(B110,'[1]26MY_CIV5D_DATA'!B:AS,9,FALSE) -> 136 | F110: =VLOOKUP(B110,'[1]26MY_CIV5D_DATA'!B:AS,10,FALSE) -> 194 | G110: =VLOOKUP(B110,'[1]26MY_CIV5D_DATA'!B:AS,7,FALSE) -> 0.4 | H110: =VLOOKUP(B110,'[1]26MY_CIV5D_DATA'!B:AS,11,FALSE) -> 261.2 | I110: =VLOOKUP(B110,'[1]26MY_CIV5D_DATA'!B:AS,12,FALSE) -> 0 | J110: =VLOOKUP(B110,'[1]26MY_CIV5D_DATA'!B:AS,13,FALSE) -> 0 | K110: =VLOOKUP($B110,'[1]26MY_CIV5D_DATA'!$B:$AS,14,FALSE) -> 0 | L110: =VLOOKUP(B110,'[1]26MY_CIV5D_DATA'!B:AS,15,FALSE) -> N/A | M110: =VLOOKUP(B110,'[1]26MY_CIV5D_DATA'!B:AS,16,FALSE) -> • | N110: =VLOOKUP($B110,'[1]26MY_CIV5D_DATA'!$B:$AS,17,FALSE) -> 0 | O110: =VLOOKUP(B110,'[1]26MY_CIV5D_DATA'!B:AS,18,FALSE) -> • | P110: =VLOOKUP(B110,'[1]26MY_CIV5D_DATA'!B:AS,19,FALSE) -> N/A
...

Sheet 26MY_CIV5D_SELL-EN
B3: 26MY Honda Civic Hatch
B4: 200
B6: POPULAR ACCESSORIES
B7: 20
B8: 150 | M8: #VALUE!
B10: 20 | C10: ='26MY_CIV5D_APP_EN'!$C$114 -> Floor Mats - All-Season | H10: ='26MY_CIV5D_APP_EN'!$C$117 -> Cargo Tray | M10: ='26MY_CIV5D_APP_EN'!$C$66 -> Black Emblem H-Mark
B11: 20 | C11: ='26MY_CIV5D_APP_EN'!$H$114 -> 258.8 | D11: =-PMT($D$29/52,5*52,C11) -> 1.1801018 | E11: /wk * | F11: =$C$29 -> (6.99%) | H11: ='26MY_CIV5D_APP_EN'!$H$117 -> 208.8 | I11: =-PMT($D$29/52,5*52,H11) -> 0.95210688 | J11: /wk * | K11: =$C$29 -> (6.99%) | M11: ='26MY_CIV5D_APP_EN'!$H$66 -> 117.6 | N11: =-PMT($D$29/52,5*52,M11) -> 0.5362441 | O11: /wk * | P11: =$C$29 -> (6.99%)
B13: 150
B15: 20 | C15: ='26MY_CIV5D_APP_EN'!$C$68 -> Door Visors - Black | H15: ='[1]26MY_CIV5D_DATA'!$D$52 -> Body Side Moulding | M15: ='26MY_CIV5D_APP_EN'!$C$128 -> Illuminated Door Sill Trim | N15: Ambient Lighting, Blue | O15: Ambient Lighting, Blue | P15: Ambient Lighting, Blue
B16: 50 | C16: ='26MY_CIV5D_APP_FR'!$H$68 -> 419 | D16: =-PMT($D$29/52,5*52,C16) -> 1.9105976 | E16: /wk * | F16: =$C$29 -> (6.99%) | H16: ='[1]26MY_CIV5D_DATA'!$L$52 -> 415.2 | I16: =-PMT($D$29/52,5*52,H16) -> 1.89327 | J16: /wk * | K16: =$C$29 -> (6.99%) | M16: ='26MY_CIV5D_APP_EN'!$H$128 -> 599.8 | N16: =-PMT($D$29/52,5*52,M16) -> 2.7350273 | O16: /wk * | P16: =$C$29 -> (6.99%)
B18: 150
B20: 20 | C20: ='26MY_CIV5D_APP_EN'!$C$90 -> Tailgate Spoiler, HPD | H20: ='26MY_CIV5D_APP_EN'!$C$73 -> Roof Rack | M20: ='26MY_CIV5D_APP_EN'!$C$14 -> 16” Enkei M52 Wheels & Michelin X-ICE Snow Tire Package
B21: 50 | C21: ='26MY_CIV5D_APP_EN'!$H$91 -> 968.6 | D21: =-PMT($D$29/52,5*52,C21) -> 4.416718 | E21: /wk * | F21: =$C$29 -> (6.99%) | H21: ='26MY_CIV5D_APP_EN'!$H$73 -> 875.2 | I21: =-PMT($D$29/52,5*52,H21) -> 3.9908235 | J21: /wk * | K21: =$C$29 -> (6.99%) | M21: =SUM('26MY_CIV5D_APP_EN'!$H$14:$H$16) -> 2181.6 | N21: =-PMT($D$29/52,5*52,M21) -> 9.9478753 | O21: /wk * | P21: =$C$29 -> (6.99%)
C23: Genuine Honda Accessories purchased with a new Honda vehicle include a 3 year / 60,000 km manufacturer's warranty.
C24: Vehicle accessories purchased after vehicle sale include a 1 year / 20,000km manufacturer's warranty.
B25: 20 | C25: *Prices shown include the cost of installation.
B26: 60 | C26: *For informational purposes only. Weekly amounts shown are estimated payments based on a 60 month finance contract at 6.99% APR (including the cost of installation). Applicable taxes and fees are extra. Accessories cannot be financed on their own and must be financed through Honda Canada Finance Inc., on approved credit, in conjunction with a Honda vehicle. Representative finance example: $350.00 financed at 6.99% APR equals $1.60 weekly for 60 months. 260 weekly payments required. Cost of borrowing is $64.80 for a total obligation of $414.80. Actual payment amounts will vary based on APR, finance contract term and cost of the applicable accessories. Conditions apply. See your Honda dealer for full details.
C27: *More customized weekly payment options & accessories can be seen on Honda.ca - Build & Price
B28: 20
B29: 18 | C29: (6.99%) | D29: 0.0699
B30: 7.5 | C30: 12 | D30: 8 | E30: 8 | F30: 10 | G30: 8.5 | H30: 12 | I30: 8 | J30: 8 | K30: 10 | L30: 8.5 | M30: 12 | N30: 8 | O30: 8 | P30: 10 | Q30: 7.5
B31: Publication Date: | C31: ='[1]26MY_CIV5D_DATA'!$C$4 -> 45859 | D31: ='SELECT PROVINCE'!$A$23 -> All published prices, trim specifications, and availability are subject to change without prior notice. | P31: Province | Q31: ='SELECT PROVINCE'!$F$12 -> YT

Sheet 26MY_CIV5D_SELL-FR
B3: 26MY Honda Civic à Hayon
B4: 200
B6: ACCESSOIRES POPULAIRES
B7: 20
B8: 150 | M8: #VALUE!
B10: 20 | C10: ='26MY_CIV5D_APP_FR'!$C$115 -> Tapis toutes saisons | H10: ='26MY_CIV5D_APP_FR'!$C$118 -> Plateau de coffre | M10: ='26MY_CIV5D_APP_FR'!$C$66 -> Emblèmes « H » noirs
B11: 20 | C11: ='26MY_CIV5D_APP_FR'!$H$115 -> 258.8 | D11: =-PMT($D$29/52,5*52,C11) -> 1.1801018 | E11: /wk * | F11: =$C$29 -> (6.99%) | H11: ='26MY_CIV5D_APP_FR'!$H$118 -> 208.8 | I11: =-PMT($D$29/52,5*52,H11) -> 0.95210688 | J11: /wk * | K11: =$C$29 -> (6.99%) | M11: ='26MY_CIV5D_APP_FR'!$H$66 -> 117.6 | N11: =-PMT($D$29/52,5*52,M11) -> 0.5362441 | O11: /wk * | P11: =$C$29 -> (6.99%)
B13: 150
B15: 20 | C15: ='26MY_CIV5D_APP_FR'!$C$68 -> Déflecteurs de portières - noir | H15: ='[1]26MY_CIV5D_DATA'!$E$52 -> Moulure latérale | M15: ='26MY_CIV5D_APP_FR'!$C$129 -> Garniture de seuil de portière illuminée | N15: Ambient Lighting, Blue | O15: Ambient Lighting, Blue | P15: Ambient Lighting, Blue
B16: 50 | C16: ='26MY_CIV5D_APP_FR'!$H$68 -> 419 | D16: =-PMT($D$29/52,5*52,C16) -> 1.9105976 | E16: /wk * | F16: =$C$29 -> (6.99%) | H16: ='[1]26MY_CIV5D_DATA'!$L$52 -> 415.2 | I16: =-PMT($D$29/52,5*52,H16) -> 1.89327 | J16: /wk * | K16: =$C$29 -> (6.99%) | M16: ='26MY_CIV5D_APP_FR'!$H$129 -> 599.8 | N16: =-PMT($D$29/52,5*52,M16) -> 2.7350273 | O16: /wk * | P16: =$C$29 -> (6.99%)
B18: 150
B20: 20 | C20: ='26MY_CIV5D_APP_FR'!$C$90 -> Déflecteur de hayon - HPD | H20: ='26MY_CIV5D_APP_FR'!$C$73 -> Porte-bagages de toit | M20: ='[1]26MY_CIV5D_DATA'!$E$8 -> Ensemble de roues Enkei M52 de 16 po et de pneus Michelin X-ICE Snow
B21: 50 | C21: ='26MY_CIV5D_APP_FR'!$H$91 -> 968.6 | D21: =-PMT($D$29/52,5*52,C21) -> 4.416718 | E21: /wk * | F21: =$C$29 -> (6.99%) | H21: ='26MY_CIV5D_APP_FR'!$H$73 -> 875.2 | I21: =-PMT($D$29/52,5*52,H21) -> 3.9908235 | J21: /wk * | K21: =$C$29 -> (6.99%) | M21: =SUM('26MY_CIV5D_APP_EN'!$H$14:$H$16) -> 2181.6 | N21: =-PMT($D$29/52,5*52,M21) -> 9.9478753 | O21: /wk * | P21: =$C$29 -> (6.99%)
C23: Les accessoires Honda d’origine achetés avec un véhicule Honda neuf incluent une garantie du fabricant de 3 ans ou 60 000 km.
C24: Les accessoires de véhicule achetés après la vente du véhicule incluent une garantie du fabricant de 1 an ou 20 000 km.
B25: 20 | C25: *Les prix indiqués incluent le coût d'installation.
B26: 60 | C26: *À titre d’information seulement. Les montants hebdomadaires indiqués sont des paiements estimés basés sur un contrat de financement de 60 mois à un taux annuel en pourcentage (TAP) de 6,99 % (coût d’installation compris). Taxes et frais applicables en sus. Les accessoires ne peuvent être financés seuls et doivent être financés par l’entremise de Honda Canada Finance Inc., sur approbation de crédit, conjointement avec un véhicule Honda. Exemple de financement représentatif : Un montant de 350,00 $ financé à un TAP de 6,99 % équivaut à un paiement hebdomadaire de 1,60 $ pendant 60 mois. 260 paiements hebdomadaires sont requis. Le coût d’emprunt est de 64,80 $, pour une obligation totale de 414,80 $. Le montant réel des paiements variera en fonction du TAP, de la période du contrat de financement et du coût des accessoires applicables. Certaines conditions s’appliquent. Veuillez visiter votre concessionnaire Honda pour obtenir tous les détails.
C27: *Vous pouvez voir d’autres options de paiements hebdomadaires personnalisés ainsi que des accessoires sur le site Honda.ca – Configuration et prix.
B28: 20
B29: 18 | C29: (6.99%) | D29: 0.0699
B30: 7.5 | C30: 12 | D30: 8 | E30: 8 | F30: 10 | G30: 8.5 | H30: 12 | I30: 8 | J30: 8 | K30: 10 | L30: 8.5 | M30: 12 | N30: 8 | O30: 8 | P30: 10 | Q30: 7.5
B31: Date de publication: | C31: ='[1]26MY_CIV5D_DATA'!$C$4 -> 45859 | D31: Tout prix, spécifications de versions et disponibilté d'accessoires publiés sont sujets à changer sans pré-avis. | P31: Province | Q31: ='26MY_CIV5D_APP_FR'!$H$11 -> YT
