Workbook
Name HighlightSel: [2]EVL!$F$5
Name prov_cd: 'SELECT PROVINCE'!$B$1
Name province_codes: 'SELECT PROVINCE'!$B$6:$B$16
Name rate_table: 'SELECT PROVINCE'!$B$6:$C$16
Name SelColLBound: [2]EVL!$E$6
Name SelColUBound: [2]EVL!$F$6
Name SelRowLBound: [2]EVL!$E$7
Name SelRowUBound: [2]EVL!$F$7

Sheet SELECT PROVINCE
A1: Select Province: Choissisez votre province: | B1: YT
B4: Current Labor Rates
B5: Taux de main d'oeuvre en cours
B6: AB | C6: 162
B7: BC | C7: 168
B8: MB | C8: 155
B9: NB | C9: 130
B10: NL | C10: 130
B11: NS | C11: 130
B12: ON | C12: 150 | F12: =prov_cd -> YT
B13: PEI | C13: 125
B14: QC | C14: 140
B15: SK | C15: 155
B16: YT | C16: 168
A23: All published prices, trim specifications, and availability are subject to change without prior notice.
A24: Tout prix, spécifications de versions et disponibilté d'accessoires publiés sont sujets à changer sans pré-avis.
AF37: N/A

Sheet 26MY_ODYSSEY_APP_EN
B2: Honda Internal | C2: Honda Accessories
C3: Model Name | D3: ='[1]26MY_ODYSSEY_DATA'!C1 -> Odyssey
C4: Model Year | D4: ='[1]26MY_ODYSSEY_DATA'!C2 -> 2026
C5: S = Standard (accessory comes standard on this trim)
C6: T = Tire Size Change (the size of the accessory wheel is smaller/larger than the OE Wheel. Customer will require new tires to fit these wheels.)
C7: E = Exchange Standard Equipment (the size of the accessory wheel is the same size as the OE wheel and therefore they can use the OE tire.)
C8: N/A = Not Applicable (accessory cannot be applied to this trim)
H10: Province
C11: 1.0 Packages and Kits | H11: =prov_cd -> YT
C12: Description | D12: Part Number | E12: Dealer Net | F12: List Price | G12: FRT | H12: Installed Price | I12: Application | Q12: Comments
I13: ='[1]26MY_ODYSSEY_DATA'!M$6 -> 0 | J13: ='[1]26MY_ODYSSEY_DATA'!N$6 -> Sport | K13: ='[1]26MY_ODYSSEY_DATA'!O$6 -> Sport-L | L13: ='[1]26MY_ODYSSEY_DATA'!P$6 -> Touring | M13: ='[1]26MY_ODYSSEY_DATA'!Q$6 -> Black Edition | N13: ='[1]26MY_ODYSSEY_DATA'!R$6 -> 0 | O13: ='[1]26MY_ODYSSEY_DATA'!S$6 -> 0 | P13: ='[1]26MY_ODYSSEY_DATA'!T$6 -> 0
B14: 25ODY-PRO-PKG1 | C14: =VLOOKUP(B14,'[1]26MY_ODYSSEY_DATA'!B:AR,3,FALSE) -> Protection Package 1 | D14: =B14 -> 25ODY-PRO-PKG1 | E14: =VLOOKUP(B14,'[1]26MY_ODYSSEY_DATA'!B:AR,9,FALSE) -> 375.3 | F14: =VLOOKUP(B14,'[1]26MY_ODYSSEY_DATA'!B:AR,10,FALSE) -> 695 | G14: =VLOOKUP(B14,'[1]26MY_ODYSSEY_DATA'!B:AR,7,FALSE) -> 0.6 | H14: =VLOOKUP(B14,'[1]26MY_ODYSSEY_DATA'!B:AR,11,FALSE) -> 795.8 | I14: =VLOOKUP(B14,'[1]26MY_ODYSSEY_DATA'!B:AR,12,FALSE) -> 0 | J14: =VLOOKUP(B14,'[1]26MY_ODYSSEY_DATA'!B:AR,13,FALSE) -> • | K14: =VLOOKUP(B14,'[1]26MY_ODYSSEY_DATA'!B:AR,14,FALSE) -> • | L14: =VLOOKUP(B14,'[1]26MY_ODYSSEY_DATA'!B:AR,15,FALSE) -> • | M14: =VLOOKUP(B14,'[1]26MY_ODYSSEY_DATA'!B:AR,16,FALSE) -> • | N14: =VLOOKUP($B14,'[1]26MY_ODYSSEY_DATA'!$B:$AR,17,FALSE) -> 0 | O14: =VLOOKUP($B14,'[1]26MY_ODYSSEY_DATA'!$B:$AR,18,FALSE) -> 0 | P14: =VLOOKUP($B14,'[1]26MY_ODYSSEY_DATA'!$B:$AR,19,FALSE) -> 0 | Q14: =IF(VLOOKUP(B14,'[1]26MY_ODYSSEY_DATA'!B:AR,20,FALSE)="","",VLOOKUP(B14,'[1]26MY_ODYSSEY_DATA'!B:AR,20,FALSE)) -> White 'ODYSSEY' lettering on Floor Mats. Cargo Tray - Deep.
B15: 08P17-THR-110A | C15: =VLOOKUP(B15,'[1]26MY_ODYSSEY_DATA'!B:AR,3,FALSE) -> All-Season Floor Mats - White Logo | D15: =B15 -> 08P17-THR-110A
B16: 08U45-THR-100A | C16: =VLOOKUP(B16,'[1]26MY_ODYSSEY_DATA'!B:AR,3,FALSE) -> Cargo Tray - Deep | D16: =B16 -> 08U45-THR-100A
B17: 08P09-THR-300A | C17: =VLOOKUP(B17,'[1]26MY_ODYSSEY_DATA'!B:AR,3,FALSE) -> Rear Splash Guards | D17: =B17 -> 08P09-THR-300A
B19: 25ODY-PRO-PKG2 | C19: =VLOOKUP(B19,'[1]26MY_ODYSSEY_DATA'!B:AR,3,FALSE) -> Protection Package 2 | D19: =B19 -> 25ODY-PRO-PKG2 | E19: =VLOOKUP(B19,'[1]26MY_ODYSSEY_DATA'!B:AR,9,FALSE) -> 393.3 | F19: =VLOOKUP(B19,'[1]26MY_ODYSSEY_DATA'!B:AR,10,FALSE) -> 729 | G19: =VLOOKUP(B19,'[1]26MY_ODYSSEY_DATA'!B:AR,7,FALSE) -> 0.6 | H19: =VLOOKUP(B19,'[1]26MY_ODYSSEY_DATA'!B:AR,11,FALSE) -> 829.8 | I19: =VLOOKUP(B19,'[1]26MY_ODYSSEY_DATA'!B:AR,12,FALSE) -> 0 | J19: =VLOOKUP(B19,'[1]26MY_ODYSSEY_DATA'!B:AR,13,FALSE) -> • | K19: =VLOOKUP(B19,'[1]26MY_ODYSSEY_DATA'!B:AR,14,FALSE) -> • | L19: =VLOOKUP(B19,'[1]26MY_ODYSSEY_DATA'!B:AR,15,FALSE) -> • | M19: =VLOOKUP(B19,'[1]26MY_ODYSSEY_DATA'!B:AR,16,FALSE) -> • | N19: =VLOOKUP($B19,'[1]26MY_ODYSSEY_DATA'!$B:$AR,17,FALSE) -> 0 | O19: =VLOOKUP($B19,'[1]26MY_ODYSSEY_DATA'!$B:$AR,18,FALSE) -> 0 | P19: =VLOOKUP($B19,'[1]26MY_ODYSSEY_DATA'!$B:$AR,19,FALSE) -> 0 | Q19: =IF(VLOOKUP(B19,'[1]26MY_ODYSSEY_DATA'!B:AR,20,FALSE)="","",VLOOKUP(B19,'[1]26MY_ODYSSEY_DATA'!B:AR,20,FALSE)) -> White 'ODYSSEY' lettering on Floor Mats. Cargo Tray - Folding.
B20: 08P17-THR-110A | C20: =VLOOKUP(B20,'[1]26MY_ODYSSEY_DATA'!B:AR,3,FALSE) -> All-Season Floor Mats - White Logo | D20: =B20 -> 08P17-THR-110A
B21: 08U45-THR-100B | C21: =VLOOKUP(B21,'[1]26MY_ODYSSEY_DATA'!B:AR,3,FALSE) -> Cargo Tray - Folding | D21: =B21 -> 08U45-THR-100B
B22: 08P09-THR-300A | C22: =VLOOKUP(B22,'[1]26MY_ODYSSEY_DATA'!B:AR,3,FALSE) -> Rear Splash Guards | D22: =B22 -> 08P09-THR-300A
B24: 21ODY-COLD-PKG | C24: =VLOOKUP(B24,'[1]26MY_ODYSSEY_DATA'!B:AR,3,FALSE) -> Cold Weather Package | D24: =B24 -> 21ODY-COLD-PKG | E24: =VLOOKUP(B24,'[1]26MY_ODYSSEY_DATA'!B:AR,9,FALSE) -> 224.2 | F24: =VLOOKUP(B24,'[1]26MY_ODYSSEY_DATA'!B:AR,10,FALSE) -> 374.3 | G24: =VLOOKUP(B24,'[1]26MY_ODYSSEY_DATA'!B:AR,7,FALSE) -> 1.4 | H24: =VLOOKUP(B24,'[1]26MY_ODYSSEY_DATA'!B:AR,11,FALSE) -> 609.5 | I24: =VLOOKUP(B24,'[1]26MY_ODYSSEY_DATA'!B:AR,12,FALSE) -> 0 | J24: =VLOOKUP(B24,'[1]26MY_ODYSSEY_DATA'!B:AR,13,FALSE) -> • | K24: =VLOOKUP(B24,'[1]26MY_ODYSSEY_DATA'!B:AR,14,FALSE) -> • | L24: =VLOOKUP(B24,'[1]26MY_ODYSSEY_DATA'!B:AR,15,FALSE) -> • | M24: =VLOOKUP(B24,'[1]26MY_ODYSSEY_DATA'!B:AR,16,FALSE) -> • | N24: =VLOOKUP($B24,'[1]26MY_ODYSSEY_DATA'!$B:$AR,17,FALSE) -> 0 | O24: =VLOOKUP($B24,'[1]26MY_ODYSSEY_DATA'!$B:$AR,18,FALSE) -> 0 | P24: =VLOOKUP($B24,'[1]26MY_ODYSSEY_DATA'!$B:$AR,19,FALSE) -> 0 | Q24: =IF(VLOOKUP(B24,'[1]26MY_ODYSSEY_DATA'!B:AR,20,FALSE)="","",VLOOKUP(B24,'[1]26MY_ODYSSEY_DATA'!B:AR,20,FALSE)) -> 5% discount applied.
B25: 08T44-SJA-401A | C25: =VLOOKUP(B25,'[1]26MY_ODYSSEY_DATA'!B:AR,3,FALSE) -> Engine Block Heater | D25: =B25 -> 08T44-SJA-401A
B26: 31670-BMS-004H | C26: =VLOOKUP(B26,'[1]26MY_ODYSSEY_DATA'!B:AR,3,FALSE) -> Optimate 12V Auto Battery Charger/Maintainer | D26: =B26 -> 31670-BMS-004H
B28: 25ODY-TOW-A1 or 25ODY-TOW-B1 | C28: =VLOOKUP(B28,'[1]26MY_ODYSSEY_DATA'!B:AR,3,FALSE) -> Towing Package | D28: =B28 -> 25ODY-TOW-A1 or 25ODY-TOW-B1 | E28: =VLOOKUP(B28,'[1]26MY_ODYSSEY_DATA'!B:AR,9,FALSE) -> 784.8 | F28: =VLOOKUP(B28,'[1]26MY_ODYSSEY_DATA'!B:AR,10,FALSE) -> 1296 | G28: =VLOOKUP(B28,'[1]26MY_ODYSSEY_DATA'!B:AR,7,FALSE) -> 2.3 | H28: =VLOOKUP(B28,'[1]26MY_ODYSSEY_DATA'!B:AR,11,FALSE) -> 1682.4 | I28: =VLOOKUP(B28,'[1]26MY_ODYSSEY_DATA'!B:AR,12,FALSE) -> 0 | J28: =VLOOKUP(B28,'[1]26MY_ODYSSEY_DATA'!B:AR,13,FALSE) -> • | K28: =VLOOKUP(B28,'[1]26MY_ODYSSEY_DATA'!B:AR,14,FALSE) -> • | L28: =VLOOKUP(B28,'[1]26MY_ODYSSEY_DATA'!B:AR,15,FALSE) -> N/A | M28: =VLOOKUP(B28,'[1]26MY_ODYSSEY_DATA'!B:AR,16,FALSE) -> N/A | N28: =VLOOKUP($B28,'[1]26MY_ODYSSEY_DATA'!$B:$AR,17,FALSE) -> 0 | O28: =VLOOKUP($B28,'[1]26MY_ODYSSEY_DATA'!$B:$AR,18,FALSE) -> 0 | P28: =VLOOKUP($B28,'[1]26MY_ODYSSEY_DATA'!$B:$AR,19,FALSE) -> 0 | Q28: =IF(VLOOKUP(B28,'[1]26MY_ODYSSEY_DATA'!B:AR,20,FALSE)="","",VLOOKUP(B28,'[1]26MY_ODYSSEY_DATA'!B:AR,20,FALSE)) -> 10% Discount Applied. Trailer Hitch Rating: Class II. Trailer Hitch Receiver Size: 2-in x 2-in. Towing Capacity: 1,587 kg / 3,500 lbs.
B29: 08L92-THR-300A | C29: =VLOOKUP(B29,'[1]26MY_ODYSSEY_DATA'!B:AR,3,FALSE) -> Trailer Hitch | D29: =B29 -> 08L92-THR-300A
B30: 08L92-SCV-300A or 08L92-SCV-100B | C30: =VLOOKUP(B30,'[1]26MY_ODYSSEY_DATA'!B:AR,3,FALSE) -> Trailer Hitch Ball - 1-7/8" or 2" | D30: =B30 -> 08L92-SCV-300A or 08L92-SCV-100B
B31: 08L91-THR-300 | C31: =VLOOKUP(B31,'[1]26MY_ODYSSEY_DATA'!B:AR,3,FALSE) -> Trailer Hitch Harness | D31: =B31 -> 08L91-THR-300
B32: 08L92-SJC-300A | C32: =VLOOKUP(B32,'[1]26MY_ODYSSEY_DATA'!B:AR,3,FALSE) -> Trailer Hitch Locking Pin | D32: =B32 -> 08L92-SJC-300A
B34: 25ODY-TOW-A2 or 25ODY-TOW-B2 | C34: =VLOOKUP(B34,'[1]26MY_ODYSSEY_DATA'!B:AR,3,FALSE) -> Towing Package | D34: =B34 -> 25ODY-TOW-A2 or 25ODY-TOW-B2 | E34: =VLOOKUP(B34,'[1]26MY_ODYSSEY_DATA'!B:AR,9,FALSE) -> 999 | F34: =VLOOKUP(B34,'[1]26MY_ODYSSEY_DATA'!B:AR,10,FALSE) -> 1653.3 | G34: =VLOOKUP(B34,'[1]26MY_ODYSSEY_DATA'!B:AR,7,FALSE) -> 2.5 | H34: =VLOOKUP(B34,'[1]26MY_ODYSSEY_DATA'!B:AR,11,FALSE) -> 2073.3 | I34: =VLOOKUP(B34,'[1]26MY_ODYSSEY_DATA'!B:AR,12,FALSE) -> 0 | J34: =VLOOKUP(B34,'[1]26MY_ODYSSEY_DATA'!B:AR,13,FALSE) -> N/A | K34: =VLOOKUP(B34,'[1]26MY_ODYSSEY_DATA'!B:AR,14,FALSE) -> N/A | L34: =VLOOKUP(B34,'[1]26MY_ODYSSEY_DATA'!B:AR,15,FALSE) -> • | M34: =VLOOKUP(B34,'[1]26MY_ODYSSEY_DATA'!B:AR,16,FALSE) -> • | N34: =VLOOKUP($B34,'[1]26MY_ODYSSEY_DATA'!$B:$AR,17,FALSE) -> 0 | O34: =VLOOKUP($B34,'[1]26MY_ODYSSEY_DATA'!$B:$AR,18,FALSE) -> 0 | P34: =VLOOKUP($B34,'[1]26MY_ODYSSEY_DATA'!$B:$AR,19,FALSE) -> 0 | Q34: =IF(VLOOKUP(B34,'[1]26MY_ODYSSEY_DATA'!B:AR,20,FALSE)="","",VLOOKUP(B34,'[1]26MY_ODYSSEY_DATA'!B:AR,20,FALSE)) -> 10% Discount Applied. Black Edition: Requires Hands-Free Power Tailgate Sensor Adapter since Hands-Free comes standard. Trailer Hitch Rating: Class II. Trailer Hitch Receiver Size: 2-in x 2-in. Towing Capacity: 1,587 kg / 3,500 lbs.
B35: 08L92-THR-300A | C35: =VLOOKUP(B35,'[1]26MY_ODYSSEY_DATA'!B:AR,3,FALSE) -> Trailer Hitch | D35: =B35 -> 08L92-THR-300A
B36: 08L91-THR-300A | C36: =VLOOKUP(B36,'[1]26MY_ODYSSEY_DATA'!B:AR,3,FALSE) -> Hands-Free Power Tailgate Sensor Adapter | D36: =B36 -> 08L91-THR-300A
B37: 08L92-SCV-300A or 08L92-SCV-100B | C37: =VLOOKUP(B37,'[1]26MY_ODYSSEY_DATA'!B:AR,3,FALSE) -> Trailer Hitch Ball - 1-7/8" or 2" | D37: =B37 -> 08L92-SCV-300A or 08L92-SCV-100B
B38: 08L91-THR-300 | C38: =VLOOKUP(B38,'[1]26MY_ODYSSEY_DATA'!B:AR,3,FALSE) -> Trailer Hitch Harness | D38: =B38 -> 08L91-THR-300
B39: 08L92-SJC-300A | C39: =VLOOKUP(B39,'[1]26MY_ODYSSEY_DATA'!B:AR,3,FALSE) -> Trailer Hitch Locking Pin | D39: =B39 -> 08L92-SJC-300A
C41: 2.0 Wheels and Wheel Accessories
C42: Description | D42: Part Number | E42: Dealer Net | F42: List Price | G42: FRT | H42: Installed Price | I42: Application | Q42: Comments
I43: ='[1]26MY_ODYSSEY_DATA'!M$6 -> 0 | J43: ='[1]26MY_ODYSSEY_DATA'!N$6 -> Sport | K43: ='[1]26MY_ODYSSEY_DATA'!O$6 -> Sport-L | L43: ='[1]26MY_ODYSSEY_DATA'!P$6 -> Touring | M43: ='[1]26MY_ODYSSEY_DATA'!Q$6 -> Black Edition | N43: ='[1]26MY_ODYSSEY_DATA'!R$6 -> 0 | O43: ='[1]26MY_ODYSSEY_DATA'!S$6 -> 0 | P43: ='[1]26MY_ODYSSEY_DATA'!T$6 -> 0
B44: 08W42-TG7-301A | C44: =VLOOKUP(B44,'[1]26MY_ODYSSEY_DATA'!B:AR,3,FALSE) -> Wheel Locks - Black | D44: =B44 -> 08W42-TG7-301A | E44: =VLOOKUP(B44,'[1]26MY_ODYSSEY_DATA'!B:AR,9,FALSE) -> 85 | F44: =VLOOKUP(B44,'[1]26MY_ODYSSEY_DATA'!B:AR,10,FALSE) -> 140 | G44: =VLOOKUP(B44,'[1]26MY_ODYSSEY_DATA'!B:AR,7,FALSE) -> 0.2 | H44: =VLOOKUP(B44,'[1]26MY_ODYSSEY_DATA'!B:AR,11,FALSE) -> 173.6 | I44: =VLOOKUP(B44,'[1]26MY_ODYSSEY_DATA'!B:AR,12,FALSE) -> 0 | J44: =VLOOKUP(B44,'[1]26MY_ODYSSEY_DATA'!B:AR,13,FALSE) -> • | K44: =VLOOKUP(B44,'[1]26MY_ODYSSEY_DATA'!B:AR,14,FALSE) -> • | L44: =VLOOKUP(B44,'[1]26MY_ODYSSEY_DATA'!B:AR,15,FALSE) -> • | M44: =VLOOKUP(B44,'[1]26MY_ODYSSEY_DATA'!B:AR,16,FALSE) -> • | N44: =VLOOKUP($B44,'[1]26MY_ODYSSEY_DATA'!$B:$AR,17,FALSE) -> 0 | O44: =VLOOKUP($B44,'[1]26MY_ODYSSEY_DATA'!$B:$AR,18,FALSE) -> 0 | P44: =VLOOKUP($B44,'[1]26MY_ODYSSEY_DATA'!$B:$AR,19,FALSE) -> 0 | Q44: =IF(VLOOKUP(B44,'[1]26MY_ODYSSEY_DATA'!B:AR,20,FALSE)="","",VLOOKUP(B44,'[1]26MY_ODYSSEY_DATA'!B:AR,20,FALSE))
B45: 08W42-TK4-301 | C45: =VLOOKUP(B45,'[1]26MY_ODYSSEY_DATA'!B:AR,3,FALSE) -> Wheel Locks - Chrome | D45: =B45 -> 08W42-TK4-301 | E45: =VLOOKUP(B45,'[1]26MY_ODYSSEY_DATA'!B:AR,9,FALSE) -> 91 | F45: =VLOOKUP(B45,'[1]26MY_ODYSSEY_DATA'!B:AR,10,FALSE) -> 152 | G45: =VLOOKUP(B45,'[1]26MY_ODYSSEY_DATA'!B:AR,7,FALSE) -> 0.2 | H45: =VLOOKUP(B45,'[1]26MY_ODYSSEY_DATA'!B:AR,11,FALSE) -> 185.6 | I45: =VLOOKUP(B45,'[1]26MY_ODYSSEY_DATA'!B:AR,12,FALSE) -> 0 | J45: =VLOOKUP(B45,'[1]26MY_ODYSSEY_DATA'!B:AR,13,FALSE) -> • | K45: =VLOOKUP(B45,'[1]26MY_ODYSSEY_DATA'!B:AR,14,FALSE) -> • | L45: =VLOOKUP(B45,'[1]26MY_ODYSSEY_DATA'!B:AR,15,FALSE) -> • | M45: =VLOOKUP(B45,'[1]26MY_ODYSSEY_DATA'!B:AR,16,FALSE) -> • | N45: =VLOOKUP($B45,'[1]26MY_ODYSSEY_DATA'!$B:$AR,17,FALSE) -> 0 | O45: =VLOOKUP($B45,'[1]26MY_ODYSSEY_DATA'!$B:$AR,18,FALSE) -> 0 | P45: =VLOOKUP($B45,'[1]26MY_ODYSSEY_DATA'!$B:$AR,19,FALSE) -> 0 | Q45: =IF(VLOOKUP(B45,'[1]26MY_ODYSSEY_DATA'!B:AR,20,FALSE)="","",VLOOKUP(B45,'[1]26MY_ODYSSEY_DATA'!B:AR,20,FALSE))
C47: 3.0 Exterior
C48: Description | D48: Part Number | E48: Dealer Net | F48: List Price | G48: FRT | H48: Installed Price | I48: Application | Q48: Comments
I49: ='[1]26MY_ODYSSEY_DATA'!M$6 -> 0 | J49: ='[1]26MY_ODYSSEY_DATA'!N$6 -> Sport | K49: ='[1]26MY_ODYSSEY_DATA'!O$6 -> Sport-L | L49: ='[1]26MY_ODYSSEY_DATA'!P$6 -> Touring | M49: ='[1]26MY_ODYSSEY_DATA'!Q$6 -> Black Edition | N49: ='[1]26MY_ODYSSEY_DATA'!R$6 -> 0 | O49: ='[1]26MY_ODYSSEY_DATA'!S$6 -> 0 | P49: ='[1]26MY_ODYSSEY_DATA'!T$6 -> 0
B50: 08F20-THR-100 | C50: =VLOOKUP(B50,'[1]26MY_ODYSSEY_DATA'!B:AR,3,FALSE) -> Black Emblems - H-Mark & Odyssey | D50: =B50 -> 08F20-THR-100 | E50: =VLOOKUP(B50,'[1]26MY_ODYSSEY_DATA'!B:AR,9,FALSE) -> 69 | F50: =VLOOKUP(B50,'[1]26MY_ODYSSEY_DATA'!B:AR,10,FALSE) -> 115 | G50: =VLOOKUP(B50,'[1]26MY_ODYSSEY_DATA'!B:AR,7,FALSE) -> 0.9 | H50: =VLOOKUP(B50,'[1]26MY_ODYSSEY_DATA'!B:AR,11,FALSE) -> 266.2 | I50: =VLOOKUP(B50,'[1]26MY_ODYSSEY_DATA'!B:AR,12,FALSE) -> 0 | J50: =VLOOKUP(B50,'[1]26MY_ODYSSEY_DATA'!B:AR,13,FALSE) -> • | K50: =VLOOKUP(B50,'[1]26MY_ODYSSEY_DATA'!B:AR,14,FALSE) -> • | L50: =VLOOKUP(B50,'[1]26MY_ODYSSEY_DATA'!B:AR,15,FALSE) -> • | M50: =VLOOKUP(B50,'[1]26MY_ODYSSEY_DATA'!B:AR,16,FALSE) -> • | N50: =VLOOKUP($B50,'[1]26MY_ODYSSEY_DATA'!$B:$AR,17,FALSE) -> 0 | O50: =VLOOKUP($B50,'[1]26MY_ODYSSEY_DATA'!$B:$AR,18,FALSE) -> 0 | P50: =VLOOKUP($B50,'[1]26MY_ODYSSEY_DATA'!$B:$AR,19,FALSE) -> 0 | Q50: =IF(VLOOKUP(B50,'[1]26MY_ODYSSEY_DATA'!B:AR,20,FALSE)="","",VLOOKUP(B50,'[1]26MY_ODYSSEY_DATA'!B:AR,20,FALSE))
B51: 08F20-T7S-100C | C51: =VLOOKUP(B51,'[1]26MY_ODYSSEY_DATA'!B:AR,3,FALSE) -> Black Emblem - Sport | D51: =B51 -> 08F20-T7S-100C | E51: =VLOOKUP(B51,'[1]26MY_ODYSSEY_DATA'!B:AR,9,FALSE) -> 41 | F51: =VLOOKUP(B51,'[1]26MY_ODYSSEY_DATA'!B:AR,10,FALSE) -> 68 | G51: =VLOOKUP(B51,'[1]26MY_ODYSSEY_DATA'!B:AR,7,FALSE) -> 0.3 | H51: =VLOOKUP(B51,'[1]26MY_ODYSSEY_DATA'!B:AR,11,FALSE) -> 118.4 | I51: =VLOOKUP(B51,'[1]26MY_ODYSSEY_DATA'!B:AR,12,FALSE) -> 0 | J51: =VLOOKUP(B51,'[1]26MY_ODYSSEY_DATA'!B:AR,13,FALSE) -> • | K51: =VLOOKUP(B51,'[1]26MY_ODYSSEY_DATA'!B:AR,14,FALSE) -> • | L51: =VLOOKUP(B51,'[1]26MY_ODYSSEY_DATA'!B:AR,15,FALSE) -> N/A | M51: =VLOOKUP(B51,'[1]26MY_ODYSSEY_DATA'!B:AR,16,FALSE) -> N/A | N51: =VLOOKUP($B51,'[1]26MY_ODYSSEY_DATA'!$B:$AR,17,FALSE) -> 0 | O51: =VLOOKUP($B51,'[1]26MY_ODYSSEY_DATA'!$B:$AR,18,FALSE) -> 0 | P51: =VLOOKUP($B51,'[1]26MY_ODYSSEY_DATA'!$B:$AR,19,FALSE) -> 0 | Q51: =IF(VLOOKUP(B51,'[1]26MY_ODYSSEY_DATA'!B:AR,20,FALSE)="","",VLOOKUP(B51,'[1]26MY_ODYSSEY_DATA'!B:AR,20,FALSE))
B52: 08F20-TG7-100G | C52: =VLOOKUP(B52,'[1]26MY_ODYSSEY_DATA'!B:AR,3,FALSE) -> Black Emblem - Black Edition | D52: =B52 -> 08F20-TG7-100G | E52: =VLOOKUP(B52,'[1]26MY_ODYSSEY_DATA'!B:AR,9,FALSE) -> 70 | F52: =VLOOKUP(B52,'[1]26MY_ODYSSEY_DATA'!B:AR,10,FALSE) -> 117 | G52: =VLOOKUP(B52,'[1]26MY_ODYSSEY_DATA'!B:AR,7,FALSE) -> 0.3 | H52: =VLOOKUP(B52,'[1]26MY_ODYSSEY_DATA'!B:AR,11,FALSE) -> 167.4 | I52: =VLOOKUP(B52,'[1]26MY_ODYSSEY_DATA'!B:AR,12,FALSE) -> 0 | J52: =VLOOKUP(B52,'[1]26MY_ODYSSEY_DATA'!B:AR,13,FALSE) -> N/A | K52: =VLOOKUP(B52,'[1]26MY_ODYSSEY_DATA'!B:AR,14,FALSE) -> N/A | L52: =VLOOKUP(B52,'[1]26MY_ODYSSEY_DATA'!B:AR,15,FALSE) -> N/A | M52: =VLOOKUP(B52,'[1]26MY_ODYSSEY_DATA'!B:AR,16,FALSE) -> • | N52: =VLOOKUP($B52,'[1]26MY_ODYSSEY_DATA'!$B:$AR,17,FALSE) -> 0 | O52: =VLOOKUP($B52,'[1]26MY_ODYSSEY_DATA'!$B:$AR,18,FALSE) -> 0 | P52: =VLOOKUP($B52,'[1]26MY_ODYSSEY_DATA'!$B:$AR,19,FALSE) -> 0 | Q52: =IF(VLOOKUP(B52,'[1]26MY_ODYSSEY_DATA'!B:AR,20,FALSE)="","",VLOOKUP(B52,'[1]26MY_ODYSSEY_DATA'!B:AR,20,FALSE))
B53: 08F59-THR-100A | C53: =VLOOKUP(B53,'[1]26MY_ODYSSEY_DATA'!B:AR,3,FALSE) -> Fender Emblems | D53: =B53 -> 08F59-THR-100A | E53: =VLOOKUP(B53,'[1]26MY_ODYSSEY_DATA'!B:AR,9,FALSE) -> 138 | F53: =VLOOKUP(B53,'[1]26MY_ODYSSEY_DATA'!B:AR,10,FALSE) -> 197 | G53: =VLOOKUP(B53,'[1]26MY_ODYSSEY_DATA'!B:AR,7,FALSE) -> 0.2 | H53: =VLOOKUP(B53,'[1]26MY_ODYSSEY_DATA'!B:AR,11,FALSE) -> 230.6 | I53: =VLOOKUP(B53,'[1]26MY_ODYSSEY_DATA'!B:AR,12,FALSE) -> 0 | J53: =VLOOKUP(B53,'[1]26MY_ODYSSEY_DATA'!B:AR,13,FALSE) -> • | K53: =VLOOKUP(B53,'[1]26MY_ODYSSEY_DATA'!B:AR,14,FALSE) -> • | L53: =VLOOKUP(B53,'[1]26MY_ODYSSEY_DATA'!B:AR,15,FALSE) -> • | M53: =VLOOKUP(B53,'[1]26MY_ODYSSEY_DATA'!B:AR,16,FALSE) -> • | N53: =VLOOKUP($B53,'[1]26MY_ODYSSEY_DATA'!$B:$AR,17,FALSE) -> 0 | O53: =VLOOKUP($B53,'[1]26MY_ODYSSEY_DATA'!$B:$AR,18,FALSE) -> 0 | P53: =VLOOKUP($B53,'[1]26MY_ODYSSEY_DATA'!$B:$AR,19,FALSE) -> 0 | Q53: =IF(VLOOKUP(B53,'[1]26MY_ODYSSEY_DATA'!B:AR,20,FALSE)="","",VLOOKUP(B53,'[1]26MY_ODYSSEY_DATA'!B:AR,20,FALSE))
B54: 08F57-THR-101 | C54: =VLOOKUP(B54,'[1]26MY_ODYSSEY_DATA'!B:AR,3,FALSE) -> Lower Door Trim - Chrome | D54: =B54 -> 08F57-THR-101 | E54: =VLOOKUP(B54,'[1]26MY_ODYSSEY_DATA'!B:AR,9,FALSE) -> 9.99 | F54: =VLOOKUP(B54,'[1]26MY_ODYSSEY_DATA'!B:AR,10,FALSE) -> 16.99 | G54: =VLOOKUP(B54,'[1]26MY_ODYSSEY_DATA'!B:AR,7,FALSE) -> 0.4 | H54: =VLOOKUP(B54,'[1]26MY_ODYSSEY_DATA'!B:AR,11,FALSE) -> 84.19 | I54: =VLOOKUP(B54,'[1]26MY_ODYSSEY_DATA'!B:AR,12,FALSE) -> 0 | J54: =VLOOKUP(B54,'[1]26MY_ODYSSEY_DATA'!B:AR,13,FALSE) -> • | K54: =VLOOKUP(B54,'[1]26MY_ODYSSEY_DATA'!B:AR,14,FALSE) -> • | L54: =VLOOKUP(B54,'[1]26MY_ODYSSEY_DATA'!B:AR,15,FALSE) -> • | M54: =VLOOKUP(B54,'[1]26MY_ODYSSEY_DATA'!B:AR,16,FALSE) -> • | N54: =VLOOKUP($B54,'[1]26MY_ODYSSEY_DATA'!$B:$AR,17,FALSE) -> 0 | O54: =VLOOKUP($B54,'[1]26MY_ODYSSEY_DATA'!$B:$AR,18,FALSE) -> 0 | P54: =VLOOKUP($B54,'[1]26MY_ODYSSEY_DATA'!$B:$AR,19,FALSE) -> 0 | Q54: =IF(VLOOKUP(B54,'[1]26MY_ODYSSEY_DATA'!B:AR,20,FALSE)="","",VLOOKUP(B54,'[1]26MY_ODYSSEY_DATA'!B:AR,20,FALSE))
B55: 08P01-THR-100 | C55: =VLOOKUP(B55,'[1]26MY_ODYSSEY_DATA'!B:AR,3,FALSE) -> Bumper Protector - Chrome | D55: =B55 -> 08P01-THR-100 | E55: =VLOOKUP(B55,'[1]26MY_ODYSSEY_DATA'!B:AR,9,FALSE) -> 22.99 | F55: =VLOOKUP(B55,'[1]26MY_ODYSSEY_DATA'!B:AR,10,FALSE) -> 37.99 | G55: =VLOOKUP(B55,'[1]26MY_ODYSSEY_DATA'!B:AR,7,FALSE) -> 0.8 | H55: =VLOOKUP(B55,'[1]26MY_ODYSSEY_DATA'!B:AR,11,FALSE) -> 172.39 | I55: =VLOOKUP(B55,'[1]26MY_ODYSSEY_DATA'!B:AR,12,FALSE) -> 0 | J55: =VLOOKUP(B55,'[1]26MY_ODYSSEY_DATA'!B:AR,13,FALSE) -> • | K55: =VLOOKUP(B55,'[1]26MY_ODYSSEY_DATA'!B:AR,14,FALSE) -> • | L55: =VLOOKUP(B55,'[1]26MY_ODYSSEY_DATA'!B:AR,15,FALSE) -> • | M55: =VLOOKUP(B55,'[1]26MY_ODYSSEY_DATA'!B:AR,16,FALSE) -> • | N55: =VLOOKUP($B55,'[1]26MY_ODYSSEY_DATA'!$B:$AR,17,FALSE) -> 0 | O55: =VLOOKUP($B55,'[1]26MY_ODYSSEY_DATA'!$B:$AR,18,FALSE) -> 0 | P55: =VLOOKUP($B55,'[1]26MY_ODYSSEY_DATA'!$B:$AR,19,FALSE) -> 0 | Q55: =IF(VLOOKUP(B55,'[1]26MY_ODYSSEY_DATA'!B:AR,20,FALSE)="","",VLOOKUP(B55,'[1]26MY_ODYSSEY_DATA'!B:AR,20,FALSE))
B56: 08P20-THR-100 | C56: =VLOOKUP(B56,'[1]26MY_ODYSSEY_DATA'!B:AR,3,FALSE) -> Door Edge Film | D56: =B56 -> 08P20-THR-100 | E56: =VLOOKUP(B56,'[1]26MY_ODYSSEY_DATA'!B:AR,9,FALSE) -> 5.99 | F56: =VLOOKUP(B56,'[1]26MY_ODYSSEY_DATA'!B:AR,10,FALSE) -> 9.99 | G56: =VLOOKUP(B56,'[1]26MY_ODYSSEY_DATA'!B:AR,7,FALSE) -> 0.2 | H56: =VLOOKUP(B56,'[1]26MY_ODYSSEY_DATA'!B:AR,11,FALSE) -> 43.59 | I56: =VLOOKUP(B56,'[1]26MY_ODYSSEY_DATA'!B:AR,12,FALSE) -> 0 | J56: =VLOOKUP(B56,'[1]26MY_ODYSSEY_DATA'!B:AR,13,FALSE) -> • | K56: =VLOOKUP(B56,'[1]26MY_ODYSSEY_DATA'!B:AR,14,FALSE) -> • | L56: =VLOOKUP(B56,'[1]26MY_ODYSSEY_DATA'!B:AR,15,FALSE) -> • | M56: =VLOOKUP(B56,'[1]26MY_ODYSSEY_DATA'!B:AR,16,FALSE) -> • | N56: =VLOOKUP($B56,'[1]26MY_ODYSSEY_DATA'!$B:$AR,17,FALSE) -> 0 | O56: =VLOOKUP($B56,'[1]26MY_ODYSSEY_DATA'!$B:$AR,18,FALSE) -> 0 | P56: =VLOOKUP($B56,'[1]26MY_ODYSSEY_DATA'!$B:$AR,19,FALSE) -> 0 | Q56: =IF(VLOOKUP(B56,'[1]26MY_ODYSSEY_DATA'!B:AR,20,FALSE)="","",VLOOKUP(B56,'[1]26MY_ODYSSEY_DATA'!B:AR,20,FALSE)) -> Cannot be installed with Door Edge Guards.
B57: 08R04-THR-102 | C57: =VLOOKUP(B57,'[1]26MY_ODYSSEY_DATA'!B:AR,3,FALSE) -> Door Visor | D57: =B57 -> 08R04-THR-102 | E57: =VLOOKUP(B57,'[1]26MY_ODYSSEY_DATA'!B:AR,9,FALSE) -> 234 | F57: =VLOOKUP(B57,'[1]26MY_ODYSSEY_DATA'!B:AR,10,FALSE) -> 390 | G57: =VLOOKUP(B57,'[1]26MY_ODYSSEY_DATA'!B:AR,7,FALSE) -> 0.5 | H57: =VLOOKUP(B57,'[1]26MY_ODYSSEY_DATA'!B:AR,11,FALSE) -> 474 | I57: =VLOOKUP(B57,'[1]26MY_ODYSSEY_DATA'!B:AR,12,FALSE) -> 0 | J57: =VLOOKUP(B57,'[1]26MY_ODYSSEY_DATA'!B:AR,13,FALSE) -> • | K57: =VLOOKUP(B57,'[1]26MY_ODYSSEY_DATA'!B:AR,14,FALSE) -> • | L57: =VLOOKUP(B57,'[1]26MY_ODYSSEY_DATA'!B:AR,15,FALSE) -> • | M57: =VLOOKUP(B57,'[1]26MY_ODYSSEY_DATA'!B:AR,16,FALSE) -> • | N57: =VLOOKUP($B57,'[1]26MY_ODYSSEY_DATA'!$B:$AR,17,FALSE) -> 0 | O57: =VLOOKUP($B57,'[1]26MY_ODYSSEY_DATA'!$B:$AR,18,FALSE) -> 0 | P57: =VLOOKUP($B57,'[1]26MY_ODYSSEY_DATA'!$B:$AR,19,FALSE) -> 0 | Q57: =IF(VLOOKUP(B57,'[1]26MY_ODYSSEY_DATA'!B:AR,20,FALSE)="","",VLOOKUP(B57,'[1]26MY_ODYSSEY_DATA'!B:AR,20,FALSE))
B58: 08P47-THR-301 | C58: =VLOOKUP(B58,'[1]26MY_ODYSSEY_DATA'!B:AR,3,FALSE) -> Hood Air Deflector | D58: =B58 -> 08P47-THR-301 | E58: =VLOOKUP(B58,'[1]26MY_ODYSSEY_DATA'!B:AR,9,FALSE) -> 204 | F58: =VLOOKUP(B58,'[1]26MY_ODYSSEY_DATA'!B:AR,10,FALSE) -> 340 | G58: =VLOOKUP(B58,'[1]26MY_ODYSSEY_DATA'!B:AR,7,FALSE) -> 0.5 | H58: =VLOOKUP(B58,'[1]26MY_ODYSSEY_DATA'!B:AR,11,FALSE) -> 424 | I58: =VLOOKUP(B58,'[1]26MY_ODYSSEY_DATA'!B:AR,12,FALSE) -> 0 | J58: =VLOOKUP(B58,'[1]26MY_ODYSSEY_DATA'!B:AR,13,FALSE) -> • | K58: =VLOOKUP(B58,'[1]26MY_ODYSSEY_DATA'!B:AR,14,FALSE) -> • | L58: =VLOOKUP(B58,'[1]26MY_ODYSSEY_DATA'!B:AR,15,FALSE) -> • | M58: =VLOOKUP(B58,'[1]26MY_ODYSSEY_DATA'!B:AR,16,FALSE) -> • | N58: =VLOOKUP($B58,'[1]26MY_ODYSSEY_DATA'!$B:$AR,17,FALSE) -> 0 | O58: =VLOOKUP($B58,'[1]26MY_ODYSSEY_DATA'!$B:$AR,18,FALSE) -> 0 | P58: =VLOOKUP($B58,'[1]26MY_ODYSSEY_DATA'!$B:$AR,19,FALSE) -> 0 | Q58: =IF(VLOOKUP(B58,'[1]26MY_ODYSSEY_DATA'!B:AR,20,FALSE)="","",VLOOKUP(B58,'[1]26MY_ODYSSEY_DATA'!B:AR,20,FALSE))
B59: 08R01-THR-301 | C59: =VLOOKUP(B59,'[1]26MY_ODYSSEY_DATA'!B:AR,3,FALSE) -> Moonroof Visor | D59: =B59 -> 08R01-THR-301 | E59: =VLOOKUP(B59,'[1]26MY_ODYSSEY_DATA'!B:AR,9,FALSE) -> 171 | F59: =VLOOKUP(B59,'[1]26MY_ODYSSEY_DATA'!B:AR,10,FALSE) -> 285 | G59: =VLOOKUP(B59,'[1]26MY_ODYSSEY_DATA'!B:AR,7,FALSE) -> 0.3 | H59: =VLOOKUP(B59,'[1]26MY_ODYSSEY_DATA'!B:AR,11,FALSE) -> 335.4 | I59: =VLOOKUP(B59,'[1]26MY_ODYSSEY_DATA'!B:AR,12,FALSE) -> 0 | J59: =VLOOKUP(B59,'[1]26MY_ODYSSEY_DATA'!B:AR,13,FALSE) -> • | K59: =VLOOKUP(B59,'[1]26MY_ODYSSEY_DATA'!B:AR,14,FALSE) -> • | L59: =VLOOKUP(B59,'[1]26MY_ODYSSEY_DATA'!B:AR,15,FALSE) -> • | M59: =VLOOKUP(B59,'[1]26MY_ODYSSEY_DATA'!B:AR,16,FALSE) -> • | N59: =VLOOKUP($B59,'[1]26MY_ODYSSEY_DATA'!$B:$AR,17,FALSE) -> 0 | O59: =VLOOKUP($B59,'[1]26MY_ODYSSEY_DATA'!$B:$AR,18,FALSE) -> 0 | P59: =VLOOKUP($B59,'[1]26MY_ODYSSEY_DATA'!$B:$AR,19,FALSE) -> 0 | Q59: =IF(VLOOKUP(B59,'[1]26MY_ODYSSEY_DATA'!B:AR,20,FALSE)="","",VLOOKUP(B59,'[1]26MY_ODYSSEY_DATA'!B:AR,20,FALSE))
B60: 08P09-THR-300A | C60: =VLOOKUP(B60,'[1]26MY_ODYSSEY_DATA'!B:AR,3,FALSE) -> Rear Splash Guards | D60: =B60 -> 08P09-THR-300A | E60: =VLOOKUP(B60,'[1]26MY_ODYSSEY_DATA'!B:AR,9,FALSE) -> 82 | F60: =VLOOKUP(B60,'[1]26MY_ODYSSEY_DATA'!B:AR,10,FALSE) -> 137 | G60: =VLOOKUP(B60,'[1]26MY_ODYSSEY_DATA'!B:AR,7,FALSE) -> 0.4 | H60: =VLOOKUP(B60,'[1]26MY_ODYSSEY_DATA'!B:AR,11,FALSE) -> 204.2 | I60: =VLOOKUP(B60,'[1]26MY_ODYSSEY_DATA'!B:AR,12,FALSE) -> 0 | J60: =VLOOKUP(B60,'[1]26MY_ODYSSEY_DATA'!B:AR,13,FALSE) -> • | K60: =VLOOKUP(B60,'[1]26MY_ODYSSEY_DATA'!B:AR,14,FALSE) -> • | L60: =VLOOKUP(B60,'[1]26MY_ODYSSEY_DATA'!B:AR,15,FALSE) -> • | M60: =VLOOKUP(B60,'[1]26MY_ODYSSEY_DATA'!B:AR,16,FALSE) -> • | N60: =VLOOKUP($B60,'[1]26MY_ODYSSEY_DATA'!$B:$AR,17,FALSE) -> 0 | O60: =VLOOKUP($B60,'[1]26MY_ODYSSEY_DATA'!$B:$AR,18,FALSE) -> 0 | P60: =VLOOKUP($B60,'[1]26MY_ODYSSEY_DATA'!$B:$AR,19,FALSE) -> 0 | Q60: =IF(VLOOKUP(B60,'[1]26MY_ODYSSEY_DATA'!B:AR,20,FALSE)="","",VLOOKUP(B60,'[1]26MY_ODYSSEY_DATA'!B:AR,20,FALSE))
B61: 08Z04-SCV-110B | C61: =VLOOKUP(B61,'[1]26MY_ODYSSEY_DATA'!B:AR,3,FALSE) -> Tent | D61: =B61 -> 08Z04-SCV-110B | E61: =VLOOKUP(B61,'[1]26MY_ODYSSEY_DATA'!B:AR,9,FALSE) -> 477 | F61: =VLOOKUP(B61,'[1]26MY_ODYSSEY_DATA'!B:AR,10,FALSE) -> 681 | G61: =VLOOKUP(B61,'[1]26MY_ODYSSEY_DATA'!B:AR,7,FALSE) -> 0 | H61: =VLOOKUP(B61,'[1]26MY_ODYSSEY_DATA'!B:AR,11,FALSE) -> 681 | I61: =VLOOKUP(B61,'[1]26MY_ODYSSEY_DATA'!B:AR,12,FALSE) -> 0 | J61: =VLOOKUP(B61,'[1]26MY_ODYSSEY_DATA'!B:AR,13,FALSE) -> • | K61: =VLOOKUP(B61,'[1]26MY_ODYSSEY_DATA'!B:AR,14,FALSE) -> • | L61: =VLOOKUP(B61,'[1]26MY_ODYSSEY_DATA'!B:AR,15,FALSE) -> • | M61: =VLOOKUP(B61,'[1]26MY_ODYSSEY_DATA'!B:AR,16,FALSE) -> • | N61: =VLOOKUP($B61,'[1]26MY_ODYSSEY_DATA'!$B:$AR,17,FALSE) -> 0 | O61: =VLOOKUP($B61,'[1]26MY_ODYSSEY_DATA'!$B:$AR,18,FALSE) -> 0 | P61: =VLOOKUP($B61,'[1]26MY_ODYSSEY_DATA'!$B:$AR,19,FALSE) -> 0 | Q61: =IF(VLOOKUP(B61,'[1]26MY_ODYSSEY_DATA'!B:AR,20,FALSE)="","",VLOOKUP(B61,'[1]26MY_ODYSSEY_DATA'!B:AR,20,FALSE))
... B64: 08L04-THR-100 | C64: =VLOOKUP(B64,'[1]26MY_ODYSSEY_DATA'!B:AR,3,FALSE) -> Crossbars | D64: =B64 -> 08L04-THR-100 | E64: =VLOOKUP(B64,'[1]26MY_ODYSSEY_DATA'!B:AR,9,FALSE) -> 216 | F64: =VLOOKUP(B64,'[1]26MY_ODYSSEY_DATA'!B:AR,10,FALSE) -> 360 | G64: =VLOOKUP(B64,'[1]26MY_ODYSSEY_DATA'!B:AR,7,FALSE) -> 0.2 | H64: =VLOOKUP(B64,'[1]26MY_ODYSSEY_DATA'!B:AR,11,FALSE) -> 393.6 | I64: =VLOOKUP(B64,'[1]26MY_ODYSSEY_DATA'!B:AR,12,FALSE) -> 0 | J64: =VLOOKUP(B64,'[1]26MY_ODYSSEY_DATA'!B:AR,13,FALSE) -> • | K64: =VLOOKUP(B64,'[1]26MY_ODYSSEY_DATA'!B:AR,14,FALSE) -> • | L64: =VLOOKUP(B64,'[1]26MY_ODYSSEY_DATA'!B:AR,15,FALSE) -> • | M64: =VLOOKUP(B64,'[1]26MY_ODYSSEY_DATA'!B:AR,16,FALSE) -> • | N64: =VLOOKUP($B64,'[1]26MY_ODYSSEY_DATA'!$B:$AR,17,FALSE) -> 0 | O64: =VLOOKUP($B64,'[1]26MY_ODYSSEY_DATA'!$B:$AR,18,FALSE) -> 0 | P64: =VLOOKUP($B64,'[1]26MY_ODYSSEY_DATA'!$B:$AR,19,FALSE) -> 0 | Q64: =IF(VLOOKUP(B64,'[1]26MY_ODYSSEY_DATA'!B:AR,20,FALSE)="","",VLOOKUP(B64,'[1]26MY_ODYSSEY_DATA'!B:AR,20,FALSE)) -> Requires Roof Rails.
B65: 08LXX-E09-XXXX | C65: =VLOOKUP(B65,'[1]26MY_ODYSSEY_DATA'!B:AR,3,FALSE) -> Roof Attachments
B66: 08L20-E09-101C | C66: =VLOOKUP(B66,'[1]26MY_ODYSSEY_DATA'!B:AR,3,FALSE) -> Roof Basket | D66: =B66 -> 08L20-E09-101C | E66: =VLOOKUP(B66,'[1]26MY_ODYSSEY_DATA'!B:AR,9,FALSE) -> 571 | F66: =VLOOKUP(B66,'[1]26MY_ODYSSEY_DATA'!B:AR,10,FALSE) -> 952 | G66: =VLOOKUP(B66,'[1]26MY_ODYSSEY_DATA'!B:AR,7,FALSE) -> 0.4 | H66: =VLOOKUP(B66,'[1]26MY_ODYSSEY_DATA'!B:AR,11,FALSE) -> 1019.2 | I66: =VLOOKUP(B66,'[1]26MY_ODYSSEY_DATA'!B:AR,12,FALSE) -> 0 | J66: =VLOOKUP(B66,'[1]26MY_ODYSSEY_DATA'!B:AR,13,FALSE) -> • | K66: =VLOOKUP(B66,'[1]26MY_ODYSSEY_DATA'!B:AR,14,FALSE) -> • | L66: =VLOOKUP(B66,'[1]26MY_ODYSSEY_DATA'!B:AR,15,FALSE) -> • | M66: =VLOOKUP(B66,'[1]26MY_ODYSSEY_DATA'!B:AR,16,FALSE) -> • | N66: =VLOOKUP($B66,'[1]26MY_ODYSSEY_DATA'!$B:$AR,17,FALSE) -> 0 | O66: =VLOOKUP($B66,'[1]26MY_ODYSSEY_DATA'!$B:$AR,18,FALSE) -> 0 | P66: =VLOOKUP($B66,'[1]26MY_ODYSSEY_DATA'!$B:$AR,19,FALSE) -> 0 | Q66: =IF(VLOOKUP(B66,'[1]26MY_ODYSSEY_DATA'!B:AR,20,FALSE)="","",VLOOKUP(B66,'[1]26MY_ODYSSEY_DATA'!B:AR,20,FALSE)) -> Requires Roof Rails and Crossbars.
B67: 08L07-E09-300A | C67: =VLOOKUP(B67,'[1]26MY_ODYSSEY_DATA'!B:AR,3,FALSE) -> Roof Bicycle Attachment - Forkmount | D67: =B67 -> 08L07-E09-300A | E67: =VLOOKUP(B67,'[1]26MY_ODYSSEY_DATA'!B:AR,9,FALSE) -> 292 | F67: =VLOOKUP(B67,'[1]26MY_ODYSSEY_DATA'!B:AR,10,FALSE) -> 487 | G67: =VLOOKUP(B67,'[1]26MY_ODYSSEY_DATA'!B:AR,7,FALSE) -> 0.4 | H67: =VLOOKUP(B67,'[1]26MY_ODYSSEY_DATA'!B:AR,11,FALSE) -> 554.2 | I67: =VLOOKUP(B67,'[1]26MY_ODYSSEY_DATA'!B:AR,12,FALSE) -> 0 | J67: =VLOOKUP(B67,'[1]26MY_ODYSSEY_DATA'!B:AR,13,FALSE) -> • | K67: =VLOOKUP(B67,'[1]26MY_ODYSSEY_DATA'!B:AR,14,FALSE) -> • | L67: =VLOOKUP(B67,'[1]26MY_ODYSSEY_DATA'!B:AR,15,FALSE) -> • | M67: =VLOOKUP(B67,'[1]26MY_ODYSSEY_DATA'!B:AR,16,FALSE) -> • | N67: =VLOOKUP($B67,'[1]26MY_ODYSSEY_DATA'!$B:$AR,17,FALSE) -> 0 | O67: =VLOOKUP($B67,'[1]26MY_ODYSSEY_DATA'!$B:$AR,18,FALSE) -> 0 | P67: =VLOOKUP($B67,'[1]26MY_ODYSSEY_DATA'!$B:$AR,19,FALSE) -> 0
B68: 08L07-E09-101 | C68: =VLOOKUP(B68,'[1]26MY_ODYSSEY_DATA'!B:AR,3,FALSE) -> Roof Bicycle Attachment - Frame mount | D68: =B68 -> 08L07-E09-101 | E68: =VLOOKUP(B68,'[1]26MY_ODYSSEY_DATA'!B:AR,9,FALSE) -> 383 | F68: =VLOOKUP(B68,'[1]26MY_ODYSSEY_DATA'!B:AR,10,FALSE) -> 547 | G68: =VLOOKUP(B68,'[1]26MY_ODYSSEY_DATA'!B:AR,7,FALSE) -> 0.6 | H68: =VLOOKUP(B68,'[1]26MY_ODYSSEY_DATA'!B:AR,11,FALSE) -> 647.8 | I68: =VLOOKUP(B68,'[1]26MY_ODYSSEY_DATA'!B:AR,12,FALSE) -> 0 | J68: =VLOOKUP(B68,'[1]26MY_ODYSSEY_DATA'!B:AR,13,FALSE) -> • | K68: =VLOOKUP(B68,'[1]26MY_ODYSSEY_DATA'!B:AR,14,FALSE) -> • | L68: =VLOOKUP(B68,'[1]26MY_ODYSSEY_DATA'!B:AR,15,FALSE) -> • | M68: =VLOOKUP(B68,'[1]26MY_ODYSSEY_DATA'!B:AR,16,FALSE) -> • | N68: =VLOOKUP($B68,'[1]26MY_ODYSSEY_DATA'!$B:$AR,17,FALSE) -> 0 | O68: =VLOOKUP($B68,'[1]26MY_ODYSSEY_DATA'!$B:$AR,18,FALSE) -> 0 | P68: =VLOOKUP($B68,'[1]26MY_ODYSSEY_DATA'!$B:$AR,19,FALSE) -> 0
B69: 08L20-E09-300A | C69: =VLOOKUP(B69,'[1]26MY_ODYSSEY_DATA'!B:AR,3,FALSE) -> Roof Box - Mid-Size | D69: =B69 -> 08L20-E09-300A | E69: =VLOOKUP(B69,'[1]26MY_ODYSSEY_DATA'!B:AR,9,FALSE) -> 875 | F69: =VLOOKUP(B69,'[1]26MY_ODYSSEY_DATA'!B:AR,10,FALSE) -> 1458 | G69: =VLOOKUP(B69,'[1]26MY_ODYSSEY_DATA'!B:AR,7,FALSE) -> 0.2 | H69: =VLOOKUP(B69,'[1]26MY_ODYSSEY_DATA'!B:AR,11,FALSE) -> 1491.6 | I69: =VLOOKUP(B69,'[1]26MY_ODYSSEY_DATA'!B:AR,12,FALSE) -> 0 | J69: =VLOOKUP(B69,'[1]26MY_ODYSSEY_DATA'!B:AR,13,FALSE) -> • | K69: =VLOOKUP(B69,'[1]26MY_ODYSSEY_DATA'!B:AR,14,FALSE) -> • | L69: =VLOOKUP(B69,'[1]26MY_ODYSSEY_DATA'!B:AR,15,FALSE) -> • | M69: =VLOOKUP(B69,'[1]26MY_ODYSSEY_DATA'!B:AR,16,FALSE) -> • | N69: =VLOOKUP($B69,'[1]26MY_ODYSSEY_DATA'!$B:$AR,17,FALSE) -> 0 | O69: =VLOOKUP($B69,'[1]26MY_ODYSSEY_DATA'!$B:$AR,18,FALSE) -> 0 | P69: =VLOOKUP($B69,'[1]26MY_ODYSSEY_DATA'!$B:$AR,19,FALSE) -> 0
B70: 08L20-E09-300B | C70: =VLOOKUP(B70,'[1]26MY_ODYSSEY_DATA'!B:AR,3,FALSE) -> Roof Box - Short | D70: =B70 -> 08L20-E09-300B | E70: =VLOOKUP(B70,'[1]26MY_ODYSSEY_DATA'!B:AR,9,FALSE) -> 799 | F70: =VLOOKUP(B70,'[1]26MY_ODYSSEY_DATA'!B:AR,10,FALSE) -> 1332 | G70: =VLOOKUP(B70,'[1]26MY_ODYSSEY_DATA'!B:AR,7,FALSE) -> 0.2 | H70: =VLOOKUP(B70,'[1]26MY_ODYSSEY_DATA'!B:AR,11,FALSE) -> 1365.6 | I70: =VLOOKUP(B70,'[1]26MY_ODYSSEY_DATA'!B:AR,12,FALSE) -> 0 | J70: =VLOOKUP(B70,'[1]26MY_ODYSSEY_DATA'!B:AR,13,FALSE) -> • | K70: =VLOOKUP(B70,'[1]26MY_ODYSSEY_DATA'!B:AR,14,FALSE) -> • | L70: =VLOOKUP(B70,'[1]26MY_ODYSSEY_DATA'!B:AR,15,FALSE) -> • | M70: =VLOOKUP(B70,'[1]26MY_ODYSSEY_DATA'!B:AR,16,FALSE) -> • | N70: =VLOOKUP($B70,'[1]26MY_ODYSSEY_DATA'!$B:$AR,17,FALSE) -> 0 | O70: =VLOOKUP($B70,'[1]26MY_ODYSSEY_DATA'!$B:$AR,18,FALSE) -> 0 | P70: =VLOOKUP($B70,'[1]26MY_ODYSSEY_DATA'!$B:$AR,19,FALSE) -> 0
B71: 08L09-E09-101 | C71: =VLOOKUP(B71,'[1]26MY_ODYSSEY_DATA'!B:AR,3,FALSE) -> Roof Kayak Attachment | D71: =B71 -> 08L09-E09-101 | E71: =VLOOKUP(B71,'[1]26MY_ODYSSEY_DATA'!B:AR,9,FALSE) -> 430 | F71: =VLOOKUP(B71,'[1]26MY_ODYSSEY_DATA'!B:AR,10,FALSE) -> 717 | G71: =VLOOKUP(B71,'[1]26MY_ODYSSEY_DATA'!B:AR,7,FALSE) -> 0.2 | H71: =VLOOKUP(B71,'[1]26MY_ODYSSEY_DATA'!B:AR,11,FALSE) -> 750.6 | I71: =VLOOKUP(B71,'[1]26MY_ODYSSEY_DATA'!B:AR,12,FALSE) -> 0 | J71: =VLOOKUP(B71,'[1]26MY_ODYSSEY_DATA'!B:AR,13,FALSE) -> • | K71: =VLOOKUP(B71,'[1]26MY_ODYSSEY_DATA'!B:AR,14,FALSE) -> • | L71: =VLOOKUP(B71,'[1]26MY_ODYSSEY_DATA'!B:AR,15,FALSE) -> • | M71: =VLOOKUP(B71,'[1]26MY_ODYSSEY_DATA'!B:AR,16,FALSE) -> • | N71: =VLOOKUP($B71,'[1]26MY_ODYSSEY_DATA'!$B:$AR,17,FALSE) -> 0 | O71: =VLOOKUP($B71,'[1]26MY_ODYSSEY_DATA'!$B:$AR,18,FALSE) -> 0 | P71: =VLOOKUP($B71,'[1]26MY_ODYSSEY_DATA'!$B:$AR,19,FALSE) -> 0
B72: 08L03-E09-300C | C72: =VLOOKUP(B72,'[1]26MY_ODYSSEY_DATA'!B:AR,3,FALSE) -> Roof Ski/Snowboard Attachment | D72: =B72 -> 08L03-E09-300C | E72: =VLOOKUP(B72,'[1]26MY_ODYSSEY_DATA'!B:AR,9,FALSE) -> 415 | F72: =VLOOKUP(B72,'[1]26MY_ODYSSEY_DATA'!B:AR,10,FALSE) -> 692 | G72: =VLOOKUP(B72,'[1]26MY_ODYSSEY_DATA'!B:AR,7,FALSE) -> 0.2 | H72: =VLOOKUP(B72,'[1]26MY_ODYSSEY_DATA'!B:AR,11,FALSE) -> 725.6 | I72: =VLOOKUP(B72,'[1]26MY_ODYSSEY_DATA'!B:AR,12,FALSE) -> 0 | J72: =VLOOKUP(B72,'[1]26MY_ODYSSEY_DATA'!B:AR,13,FALSE) -> • | K72: =VLOOKUP(B72,'[1]26MY_ODYSSEY_DATA'!B:AR,14,FALSE) -> • | L72: =VLOOKUP(B72,'[1]26MY_ODYSSEY_DATA'!B:AR,15,FALSE) -> • | M72: =VLOOKUP(B72,'[1]26MY_ODYSSEY_DATA'!B:AR,16,FALSE) -> • | N72: =VLOOKUP($B72,'[1]26MY_ODYSSEY_DATA'!$B:$AR,17,FALSE) -> 0 | O72: =VLOOKUP($B72,'[1]26MY_ODYSSEY_DATA'!$B:$AR,18,FALSE) -> 0 | P72: =VLOOKUP($B72,'[1]26MY_ODYSSEY_DATA'!$B:$AR,19,FALSE) -> 0
B73: 08L05-E09-100 | C73: =VLOOKUP(B73,'[1]26MY_ODYSSEY_DATA'!B:AR,3,FALSE) -> Roof Surfboard Attachment | D73: =B73 -> 08L05-E09-100 | E73: =VLOOKUP(B73,'[1]26MY_ODYSSEY_DATA'!B:AR,9,FALSE) -> 207 | F73: =VLOOKUP(B73,'[1]26MY_ODYSSEY_DATA'!B:AR,10,FALSE) -> 345 | G73: =VLOOKUP(B73,'[1]26MY_ODYSSEY_DATA'!B:AR,7,FALSE) -> 0.2 | H73: =VLOOKUP(B73,'[1]26MY_ODYSSEY_DATA'!B:AR,11,FALSE) -> 378.6 | I73: =VLOOKUP(B73,'[1]26MY_ODYSSEY_DATA'!B:AR,12,FALSE) -> 0 | J73: =VLOOKUP(B73,'[1]26MY_ODYSSEY_DATA'!B:AR,13,FALSE) -> • | K73: =VLOOKUP(B73,'[1]26MY_ODYSSEY_DATA'!B:AR,14,FALSE) -> • | L73: =VLOOKUP(B73,'[1]26MY_ODYSSEY_DATA'!B:AR,15,FALSE) -> • | M73: =VLOOKUP(B73,'[1]26MY_ODYSSEY_DATA'!B:AR,16,FALSE) -> • | N73: =VLOOKUP($B73,'[1]26MY_ODYSSEY_DATA'!$B:$AR,17,FALSE) -> 0 | O73: =VLOOKUP($B73,'[1]26MY_ODYSSEY_DATA'!$B:$AR,18,FALSE) -> 0 | P73: =VLOOKUP($B73,'[1]26MY_ODYSSEY_DATA'!$B:$AR,19,FALSE) -> 0
B74: 08L91-THR-XXXX | C74: =VLOOKUP(B74,'[1]26MY_ODYSSEY_DATA'!B:AR,3,FALSE) -> Trailer Hitch parts
B75: 08L92-THR-300A | C75: =VLOOKUP(B75,'[1]26MY_ODYSSEY_DATA'!B:AR,3,FALSE) -> Trailer Hitch | D75: =B75 -> 08L92-THR-300A | E75: =VLOOKUP(B75,'[1]26MY_ODYSSEY_DATA'!B:AR,9,FALSE) -> 576 | F75: =VLOOKUP(B75,'[1]26MY_ODYSSEY_DATA'!B:AR,10,FALSE) -> 960 | G75: =VLOOKUP(B75,'[1]26MY_ODYSSEY_DATA'!B:AR,7,FALSE) -> 1.5 | H75: =VLOOKUP(B75,'[1]26MY_ODYSSEY_DATA'!B:AR,11,FALSE) -> 1212 | I75: =VLOOKUP(B75,'[1]26MY_ODYSSEY_DATA'!B:AR,12,FALSE) -> 0 | J75: =VLOOKUP(B75,'[1]26MY_ODYSSEY_DATA'!B:AR,13,FALSE) -> • | K75: =VLOOKUP(B75,'[1]26MY_ODYSSEY_DATA'!B:AR,14,FALSE) -> • | L75: =VLOOKUP(B75,'[1]26MY_ODYSSEY_DATA'!B:AR,15,FALSE) -> • | M75: =VLOOKUP(B75,'[1]26MY_ODYSSEY_DATA'!B:AR,16,FALSE) -> • | N75: =VLOOKUP($B75,'[1]26MY_ODYSSEY_DATA'!$B:$AR,17,FALSE) -> 0 | O75: =VLOOKUP($B75,'[1]26MY_ODYSSEY_DATA'!$B:$AR,18,FALSE) -> 0 | P75: =VLOOKUP($B75,'[1]26MY_ODYSSEY_DATA'!$B:$AR,19,FALSE) -> 0 | Q75: =IF(VLOOKUP(B75,'[1]26MY_ODYSSEY_DATA'!B:AR,20,FALSE)="","",VLOOKUP(B75,'[1]26MY_ODYSSEY_DATA'!B:AR,20,FALSE)) -> Trailer Hitch Rating: Class II. Trailer Hitch Receiver Size: 2-in x 2-in. TOURING: Requires Hands-Free Power Tailgate Sensor Adaptor.
B76: 08L92-SCV-300A | C76: =VLOOKUP(B76,'[1]26MY_ODYSSEY_DATA'!B:AR,3,FALSE) -> Trailer Hitch Ball - 1-7/8" | D76: =B76 -> 08L92-SCV-300A | E76: =VLOOKUP(B76,'[1]26MY_ODYSSEY_DATA'!B:AR,9,FALSE) -> 28 | F76: =VLOOKUP(B76,'[1]26MY_ODYSSEY_DATA'!B:AR,10,FALSE) -> 47 | G76: =VLOOKUP(B76,'[1]26MY_ODYSSEY_DATA'!B:AR,7,FALSE) -> 0 | H76: =VLOOKUP(B76,'[1]26MY_ODYSSEY_DATA'!B:AR,11,FALSE) -> 47 | I76: =VLOOKUP(B76,'[1]26MY_ODYSSEY_DATA'!B:AR,12,FALSE) -> 0 | J76: =VLOOKUP(B76,'[1]26MY_ODYSSEY_DATA'!B:AR,13,FALSE) -> • | K76: =VLOOKUP(B76,'[1]26MY_ODYSSEY_DATA'!B:AR,14,FALSE) -> • | L76: =VLOOKUP(B76,'[1]26MY_ODYSSEY_DATA'!B:AR,15,FALSE) -> • | M76: =VLOOKUP(B76,'[1]26MY_ODYSSEY_DATA'!B:AR,16,FALSE) -> • | N76: =VLOOKUP($B76,'[1]26MY_ODYSSEY_DATA'!$B:$AR,17,FALSE) -> 0 | O76: =VLOOKUP($B76,'[1]26MY_ODYSSEY_DATA'!$B:$AR,18,FALSE) -> 0 | P76: =VLOOKUP($B76,'[1]26MY_ODYSSEY_DATA'!$B:$AR,19,FALSE) -> 0
B77: 08L92-SCV-100B | C77: =VLOOKUP(B77,'[1]26MY_ODYSSEY_DATA'!B:AR,3,FALSE) -> Trailer Hitch Ball - 2" | D77: =B77 -> 08L92-SCV-100B | E77: =VLOOKUP(B77,'[1]26MY_ODYSSEY_DATA'!B:AR,9,FALSE) -> 28 | F77: =VLOOKUP(B77,'[1]26MY_ODYSSEY_DATA'!B:AR,10,FALSE) -> 47 | G77: =VLOOKUP(B77,'[1]26MY_ODYSSEY_DATA'!B:AR,7,FALSE) -> 0 | H77: =VLOOKUP(B77,'[1]26MY_ODYSSEY_DATA'!B:AR,11,FALSE) -> 47 | I77: =VLOOKUP(B77,'[1]26MY_ODYSSEY_DATA'!B:AR,12,FALSE) -> 0 | J77: =VLOOKUP(B77,'[1]26MY_ODYSSEY_DATA'!B:AR,13,FALSE) -> • | K77: =VLOOKUP(B77,'[1]26MY_ODYSSEY_DATA'!B:AR,14,FALSE) -> • | L77: =VLOOKUP(B77,'[1]26MY_ODYSSEY_DATA'!B:AR,15,FALSE) -> • | M77: =VLOOKUP(B77,'[1]26MY_ODYSSEY_DATA'!B:AR,16,FALSE) -> • | N77: =VLOOKUP($B77,'[1]26MY_ODYSSEY_DATA'!$B:$AR,17,FALSE) -> 0 | O77: =VLOOKUP($B77,'[1]26MY_ODYSSEY_DATA'!$B:$AR,18,FALSE) -> 0 | P77: =VLOOKUP($B77,'[1]26MY_ODYSSEY_DATA'!$B:$AR,19,FALSE) -> 0
B78: 08L91-THR-300 | C78: =VLOOKUP(B78,'[1]26MY_ODYSSEY_DATA'!B:AR,3,FALSE) -> Trailer Hitch Harness | D78: =B78 -> 08L91-THR-300 | E78: =VLOOKUP(B78,'[1]26MY_ODYSSEY_DATA'!B:AR,9,FALSE) -> 162 | F78: =VLOOKUP(B78,'[1]26MY_ODYSSEY_DATA'!B:AR,10,FALSE) -> 270 | G78: =VLOOKUP(B78,'[1]26MY_ODYSSEY_DATA'!B:AR,7,FALSE) -> 0.8 | H78: =VLOOKUP(B78,'[1]26MY_ODYSSEY_DATA'!B:AR,11,FALSE) -> 404.4 | I78: =VLOOKUP(B78,'[1]26MY_ODYSSEY_DATA'!B:AR,12,FALSE) -> 0 | J78: =VLOOKUP(B78,'[1]26MY_ODYSSEY_DATA'!B:AR,13,FALSE) -> • | K78: =VLOOKUP(B78,'[1]26MY_ODYSSEY_DATA'!B:AR,14,FALSE) -> • | L78: =VLOOKUP(B78,'[1]26MY_ODYSSEY_DATA'!B:AR,15,FALSE) -> • | M78: =VLOOKUP(B78,'[1]26MY_ODYSSEY_DATA'!B:AR,16,FALSE) -> • | N78: =VLOOKUP($B78,'[1]26MY_ODYSSEY_DATA'!$B:$AR,17,FALSE) -> 0 | O78: =VLOOKUP($B78,'[1]26MY_ODYSSEY_DATA'!$B:$AR,18,FALSE) -> 0 | P78: =VLOOKUP($B78,'[1]26MY_ODYSSEY_DATA'!$B:$AR,19,FALSE) -> 0
B79: 08L92-SJC-300A | C79: =VLOOKUP(B79,'[1]26MY_ODYSSEY_DATA'!B:AR,3,FALSE) -> Trailer Hitch Locking Pin | D79: =B79 -> 08L92-SJC-300A | E79: =VLOOKUP(B79,'[1]26MY_ODYSSEY_DATA'!B:AR,9,FALSE) -> 106 | F79: =VLOOKUP(B79,'[1]26MY_ODYSSEY_DATA'!B:AR,10,FALSE) -> 163 | G79: =VLOOKUP(B79,'[1]26MY_ODYSSEY_DATA'!B:AR,7,FALSE) -> 0 | H79: =VLOOKUP(B79,'[1]26MY_ODYSSEY_DATA'!B:AR,11,FALSE) -> 163 | I79: =VLOOKUP(B79,'[1]26MY_ODYSSEY_DATA'!B:AR,12,FALSE) -> 0 | J79: =VLOOKUP(B79,'[1]26MY_ODYSSEY_DATA'!B:AR,13,FALSE) -> • | K79: =VLOOKUP(B79,'[1]26MY_ODYSSEY_DATA'!B:AR,14,FALSE) -> • | L79: =VLOOKUP(B79,'[1]26MY_ODYSSEY_DATA'!B:AR,15,FALSE) -> • | M79: =VLOOKUP(B79,'[1]26MY_ODYSSEY_DATA'!B:AR,16,FALSE) -> • | N79: =VLOOKUP($B79,'[1]26MY_ODYSSEY_DATA'!$B:$AR,17,FALSE) -> 0 | O79: =VLOOKUP($B79,'[1]26MY_ODYSSEY_DATA'!$B:$AR,18,FALSE) -> 0 | P79: =VLOOKUP($B79,'[1]26MY_ODYSSEY_DATA'!$B:$AR,19,FALSE) -> 0
B80: 08L91-THR-300A | C80: =VLOOKUP(B80,'[1]26MY_ODYSSEY_DATA'!B:AR,3,FALSE) -> Hands-Free Power Tailgate Sensor Adapter | D80: =B80 -> 08L91-THR-300A | E80: =VLOOKUP(B80,'[1]26MY_ODYSSEY_DATA'!B:AR,9,FALSE) -> 238 | F80: =VLOOKUP(B80,'[1]26MY_ODYSSEY_DATA'!B:AR,10,FALSE) -> 397 | G80: =VLOOKUP(B80,'[1]26MY_ODYSSEY_DATA'!B:AR,7,FALSE) -> 0.2 | H80: =VLOOKUP(B80,'[1]26MY_ODYSSEY_DATA'!B:AR,11,FALSE) -> 430.6 | I80: =VLOOKUP(B80,'[1]26MY_ODYSSEY_DATA'!B:AR,12,FALSE) -> 0 | J80: =VLOOKUP(B80,'[1]26MY_ODYSSEY_DATA'!B:AR,13,FALSE) -> • | K80: =VLOOKUP(B80,'[1]26MY_ODYSSEY_DATA'!B:AR,14,FALSE) -> • | L80: =VLOOKUP(B80,'[1]26MY_ODYSSEY_DATA'!B:AR,15,FALSE) -> • | M80: =VLOOKUP(B80,'[1]26MY_ODYSSEY_DATA'!B:AR,16,FALSE) -> • | N80: =VLOOKUP($B80,'[1]26MY_ODYSSEY_DATA'!$B:$AR,17,FALSE) -> 0 | O80: =VLOOKUP($B80,'[1]26MY_ODYSSEY_DATA'!$B:$AR,18,FALSE) -> 0 | P80: =VLOOKUP($B80,'[1]26MY_ODYSSEY_DATA'!$B:$AR,19,FALSE) -> 0
B81: 08P05-THR-XXXX | C81: =VLOOKUP(B81,'[1]26MY_ODYSSEY_DATA'!B:AR,3,FALSE) -> Body Side Moulding
B82: 08P05-THR-191 | C82: =VLOOKUP(B82,'[1]26MY_ODYSSEY_DATA'!B:AR,3,FALSE) -> Platinum White Pearl (NH-883P) | D82: =B82 -> 08P05-THR-191 | E82: =VLOOKUP(B82,'[1]26MY_ODYSSEY_DATA'!B:AR,9,FALSE) -> 231 | F82: =VLOOKUP(B82,'[1]26MY_ODYSSEY_DATA'!B:AR,10,FALSE) -> 385 | G82: =VLOOKUP(B82,'[1]26MY_ODYSSEY_DATA'!B:AR,7,FALSE) -> 0.4 | H82: =VLOOKUP(B82,'[1]26MY_ODYSSEY_DATA'!B:AR,11,FALSE) -> 452.2 | I82: =VLOOKUP(B82,'[1]26MY_ODYSSEY_DATA'!B:AR,12,FALSE) -> 0 | J82: =VLOOKUP(B82,'[1]26MY_ODYSSEY_DATA'!B:AR,13,FALSE) -> • | K82: =VLOOKUP(B82,'[1]26MY_ODYSSEY_DATA'!B:AR,14,FALSE) -> • | L82: =VLOOKUP(B82,'[1]26MY_ODYSSEY_DATA'!B:AR,15,FALSE) -> • | M82: =VLOOKUP(B82,'[1]26MY_ODYSSEY_DATA'!B:AR,16,FALSE) -> • | N82: =VLOOKUP($B82,'[1]26MY_ODYSSEY_DATA'!$B:$AR,17,FALSE) -> 0 | O82: =VLOOKUP($B82,'[1]26MY_ODYSSEY_DATA'!$B:$AR,18,FALSE) -> 0 | P82: =VLOOKUP($B82,'[1]26MY_ODYSSEY_DATA'!$B:$AR,19,FALSE) -> 0 | Q82: =IF(VLOOKUP(B82,'[1]26MY_ODYSSEY_DATA'!B:AR,20,FALSE)="","",VLOOKUP(B82,'[1]26MY_ODYSSEY_DATA'!B:AR,20,FALSE))
B83: 08P05-THR-121 | C83: =VLOOKUP(B83,'[1]26MY_ODYSSEY_DATA'!B:AR,3,FALSE) -> Crystal Black Pearl (NH-731P) | D83: =B83 -> 08P05-THR-121 | E83: =VLOOKUP(B83,'[1]26MY_ODYSSEY_DATA'!B:AR,9,FALSE) -> 231 | F83: =VLOOKUP(B83,'[1]26MY_ODYSSEY_DATA'!B:AR,10,FALSE) -> 385 | G83: =VLOOKUP(B83,'[1]26MY_ODYSSEY_DATA'!B:AR,7,FALSE) -> 0.4 | H83: =VLOOKUP(B83,'[1]26MY_ODYSSEY_DATA'!B:AR,11,FALSE) -> 452.2 | I83: =VLOOKUP(B83,'[1]26MY_ODYSSEY_DATA'!B:AR,12,FALSE) -> 0 | J83: =VLOOKUP(B83,'[1]26MY_ODYSSEY_DATA'!B:AR,13,FALSE) -> • | K83: =VLOOKUP(B83,'[1]26MY_ODYSSEY_DATA'!B:AR,14,FALSE) -> N/A | L83: =VLOOKUP(B83,'[1]26MY_ODYSSEY_DATA'!B:AR,15,FALSE) -> N/A | M83: =VLOOKUP(B83,'[1]26MY_ODYSSEY_DATA'!B:AR,16,FALSE) -> • | N83: =VLOOKUP($B83,'[1]26MY_ODYSSEY_DATA'!$B:$AR,17,FALSE) -> 0 | O83: =VLOOKUP($B83,'[1]26MY_ODYSSEY_DATA'!$B:$AR,18,FALSE) -> 0 | P83: =VLOOKUP($B83,'[1]26MY_ODYSSEY_DATA'!$B:$AR,19,FALSE) -> 0
B84: 08P05-THR-131 | C84: =VLOOKUP(B84,'[1]26MY_ODYSSEY_DATA'!B:AR,3,FALSE) -> Modern Steel Metallic (NH-797M) | D84: =B84 -> 08P05-THR-131 | E84: =VLOOKUP(B84,'[1]26MY_ODYSSEY_DATA'!B:AR,9,FALSE) -> 231 | F84: =VLOOKUP(B84,'[1]26MY_ODYSSEY_DATA'!B:AR,10,FALSE) -> 385 | G84: =VLOOKUP(B84,'[1]26MY_ODYSSEY_DATA'!B:AR,7,FALSE) -> 0.4 | H84: =VLOOKUP(B84,'[1]26MY_ODYSSEY_DATA'!B:AR,11,FALSE) -> 452.2 | I84: =VLOOKUP(B84,'[1]26MY_ODYSSEY_DATA'!B:AR,12,FALSE) -> 0 | J84: =VLOOKUP(B84,'[1]26MY_ODYSSEY_DATA'!B:AR,13,FALSE) -> N/A | K84: =VLOOKUP(B84,'[1]26MY_ODYSSEY_DATA'!B:AR,14,FALSE) -> • | L84: =VLOOKUP(B84,'[1]26MY_ODYSSEY_DATA'!B:AR,15,FALSE) -> • | M84: =VLOOKUP(B84,'[1]26MY_ODYSSEY_DATA'!B:AR,16,FALSE) -> N/A | N84: =VLOOKUP($B84,'[1]26MY_ODYSSEY_DATA'!$B:$AR,17,FALSE) -> 0 | O84: =VLOOKUP($B84,'[1]26MY_ODYSSEY_DATA'!$B:$AR,18,FALSE) -> 0 | P84: =VLOOKUP($B84,'[1]26MY_ODYSSEY_DATA'!$B:$AR,19,FALSE) -> 0
B85: 08P05-THR-1B1 | C85: =VLOOKUP(B85,'[1]26MY_ODYSSEY_DATA'!B:AR,3,FALSE) -> Sonic Gray Pearl (NH-877P) | D85: =B85 -> 08P05-THR-1B1 | E85: =VLOOKUP(B85,'[1]26MY_ODYSSEY_DATA'!B:AR,9,FALSE) -> 231 | F85: =VLOOKUP(B85,'[1]26MY_ODYSSEY_DATA'!B:AR,10,FALSE) -> 385 | G85: =VLOOKUP(B85,'[1]26MY_ODYSSEY_DATA'!B:AR,7,FALSE) -> 0.4 | H85: =VLOOKUP(B85,'[1]26MY_ODYSSEY_DATA'!B:AR,11,FALSE) -> 452.2 | I85: =VLOOKUP(B85,'[1]26MY_ODYSSEY_DATA'!B:AR,12,FALSE) -> 0 | J85: =VLOOKUP(B85,'[1]26MY_ODYSSEY_DATA'!B:AR,13,FALSE) -> N/A | K85: =VLOOKUP(B85,'[1]26MY_ODYSSEY_DATA'!B:AR,14,FALSE) -> N/A | L85: =VLOOKUP(B85,'[1]26MY_ODYSSEY_DATA'!B:AR,15,FALSE) -> • | M85: =VLOOKUP(B85,'[1]26MY_ODYSSEY_DATA'!B:AR,16,FALSE) -> • | N85: =VLOOKUP($B85,'[1]26MY_ODYSSEY_DATA'!$B:$AR,17,FALSE) -> 0 | O85: =VLOOKUP($B85,'[1]26MY_ODYSSEY_DATA'!$B:$AR,18,FALSE) -> 0 | P85: =VLOOKUP($B85,'[1]26MY_ODYSSEY_DATA'!$B:$AR,19,FALSE) -> 0
B86: 08P05-THR-1A1 | C86: =VLOOKUP(B86,'[1]26MY_ODYSSEY_DATA'!B:AR,3,FALSE) -> Radiant Red Metallic II (R-580M) | D86: =B86 -> 08P05-THR-1A1 | E86: =VLOOKUP(B86,'[1]26MY_ODYSSEY_DATA'!B:AR,9,FALSE) -> 231 | F86: =VLOOKUP(B86,'[1]26MY_ODYSSEY_DATA'!B:AR,10,FALSE) -> 385 | G86: =VLOOKUP(B86,'[1]26MY_ODYSSEY_DATA'!B:AR,7,FALSE) -> 0.4 | H86: =VLOOKUP(B86,'[1]26MY_ODYSSEY_DATA'!B:AR,11,FALSE) -> 452.2 | I86: =VLOOKUP(B86,'[1]26MY_ODYSSEY_DATA'!B:AR,12,FALSE) -> 0 | J86: =VLOOKUP(B86,'[1]26MY_ODYSSEY_DATA'!B:AR,13,FALSE) -> N/A | K86: =VLOOKUP(B86,'[1]26MY_ODYSSEY_DATA'!B:AR,14,FALSE) -> N/A | L86: =VLOOKUP(B86,'[1]26MY_ODYSSEY_DATA'!B:AR,15,FALSE) -> N/A | M86: =VLOOKUP(B86,'[1]26MY_ODYSSEY_DATA'!B:AR,16,FALSE) -> • | N86: =VLOOKUP($B86,'[1]26MY_ODYSSEY_DATA'!$B:$AR,17,FALSE) -> 0 | O86: =VLOOKUP($B86,'[1]26MY_ODYSSEY_DATA'!$B:$AR,18,FALSE) -> 0 | P86: =VLOOKUP($B86,'[1]26MY_ODYSSEY_DATA'!$B:$AR,19,FALSE) -> 0
B87: 08P05-THR-1C1 | C87: =VLOOKUP(B87,'[1]26MY_ODYSSEY_DATA'!B:AR,3,FALSE) -> Solar Reflection Silver (NH-932M) | D87: =B87 -> 08P05-THR-1C1 | E87: =VLOOKUP(B87,'[1]26MY_ODYSSEY_DATA'!B:AR,9,FALSE) -> 231 | F87: =VLOOKUP(B87,'[1]26MY_ODYSSEY_DATA'!B:AR,10,FALSE) -> 385 | G87: =VLOOKUP(B87,'[1]26MY_ODYSSEY_DATA'!B:AR,7,FALSE) -> 0.4 | H87: =VLOOKUP(B87,'[1]26MY_ODYSSEY_DATA'!B:AR,11,FALSE) -> 452.2 | I87: =VLOOKUP(B87,'[1]26MY_ODYSSEY_DATA'!B:AR,12,FALSE) -> 0 | J87: =VLOOKUP(B87,'[1]26MY_ODYSSEY_DATA'!B:AR,13,FALSE) -> • | K87: =VLOOKUP(B87,'[1]26MY_ODYSSEY_DATA'!B:AR,14,FALSE) -> • | L87: =VLOOKUP(B87,'[1]26MY_ODYSSEY_DATA'!B:AR,15,FALSE) -> • | M87: =VLOOKUP(B87,'[1]26MY_ODYSSEY_DATA'!B:AR,16,FALSE) -> N/A | N87: =VLOOKUP($B87,'[1]26MY_ODYSSEY_DATA'!$B:$AR,17,FALSE) -> 0 | O87: =VLOOKUP($B87,'[1]26MY_ODYSSEY_DATA'!$B:$AR,18,FALSE) -> 0 | P87: =VLOOKUP($B87,'[1]26MY_ODYSSEY_DATA'!$B:$AR,19,FALSE) -> 0
B88: 08P20-THR-XXXX | C88: =VLOOKUP(B88,'[1]26MY_ODYSSEY_DATA'!B:AR,3,FALSE) -> Door Edge Guards
B89: 08P20-THR-190A | C89: =VLOOKUP(B89,'[1]26MY_ODYSSEY_DATA'!B:AR,3,FALSE) -> Platinum White Pearl (NH-883P) | D89: =B89 -> 08P20-THR-190A | E89: =VLOOKUP(B89,'[1]26MY_ODYSSEY_DATA'!B:AR,9,FALSE) -> 87 | F89: =VLOOKUP(B89,'[1]26MY_ODYSSEY_DATA'!B:AR,10,FALSE) -> 145 | G89: =VLOOKUP(B89,'[1]26MY_ODYSSEY_DATA'!B:AR,7,FALSE) -> 0.3 | H89: =VLOOKUP(B89,'[1]26MY_ODYSSEY_DATA'!B:AR,11,FALSE) -> 195.4 | I89: =VLOOKUP(B89,'[1]26MY_ODYSSEY_DATA'!B:AR,12,FALSE) -> 0 | J89: =VLOOKUP(B89,'[1]26MY_ODYSSEY_DATA'!B:AR,13,FALSE) -> • | K89: =VLOOKUP(B89,'[1]26MY_ODYSSEY_DATA'!B:AR,14,FALSE) -> • | L89: =VLOOKUP(B89,'[1]26MY_ODYSSEY_DATA'!B:AR,15,FALSE) -> • | M89: =VLOOKUP(B89,'[1]26MY_ODYSSEY_DATA'!B:AR,16,FALSE) -> • | N89: =VLOOKUP($B89,'[1]26MY_ODYSSEY_DATA'!$B:$AR,17,FALSE) -> 0 | O89: =VLOOKUP($B89,'[1]26MY_ODYSSEY_DATA'!$B:$AR,18,FALSE) -> 0 | P89: =VLOOKUP($B89,'[1]26MY_ODYSSEY_DATA'!$B:$AR,19,FALSE) -> 0 | Q89: =IF(VLOOKUP(B89,'[1]26MY_ODYSSEY_DATA'!B:AR,20,FALSE)="","",VLOOKUP(B89,'[1]26MY_ODYSSEY_DATA'!B:AR,20,FALSE))
B90: 08P20-THR-120A | C90: =VLOOKUP(B90,'[1]26MY_ODYSSEY_DATA'!B:AR,3,FALSE) -> Crystal Black Pearl (NH-731P) | D90: =B90 -> 08P20-THR-120A | E90: =VLOOKUP(B90,'[1]26MY_ODYSSEY_DATA'!B:AR,9,FALSE) -> 87 | F90: =VLOOKUP(B90,'[1]26MY_ODYSSEY_DATA'!B:AR,10,FALSE) -> 145 | G90: =VLOOKUP(B90,'[1]26MY_ODYSSEY_DATA'!B:AR,7,FALSE) -> 0.3 | H90: =VLOOKUP(B90,'[1]26MY_ODYSSEY_DATA'!B:AR,11,FALSE) -> 195.4 | I90: =VLOOKUP(B90,'[1]26MY_ODYSSEY_DATA'!B:AR,12,FALSE) -> 0 | J90: =VLOOKUP(B90,'[1]26MY_ODYSSEY_DATA'!B:AR,13,FALSE) -> • | K90: =VLOOKUP(B90,'[1]26MY_ODYSSEY_DATA'!B:AR,14,FALSE) -> N/A | L90: =VLOOKUP(B90,'[1]26MY_ODYSSEY_DATA'!B:AR,15,FALSE) -> N/A | M90: =VLOOKUP(B90,'[1]26MY_ODYSSEY_DATA'!B:AR,16,FALSE) -> • | N90: =VLOOKUP($B90,'[1]26MY_ODYSSEY_DATA'!$B:$AR,17,FALSE) -> 0 | O90: =VLOOKUP($B90,'[1]26MY_ODYSSEY_DATA'!$B:$AR,18,FALSE) -> 0 | P90: =VLOOKUP($B90,'[1]26MY_ODYSSEY_DATA'!$B:$AR,19,FALSE) -> 0
B91: 08P20-THR-130A | C91: =VLOOKUP(B91,'[1]26MY_ODYSSEY_DATA'!B:AR,3,FALSE) -> Modern Steel Metallic (NH-797M) | D91: =B91 -> 08P20-THR-130A | E91: =VLOOKUP(B91,'[1]26MY_ODYSSEY_DATA'!B:AR,9,FALSE) -> 87 | F91: =VLOOKUP(B91,'[1]26MY_ODYSSEY_DATA'!B:AR,10,FALSE) -> 145 | G91: =VLOOKUP(B91,'[1]26MY_ODYSSEY_DATA'!B:AR,7,FALSE) -> 0.3 | H91: =VLOOKUP(B91,'[1]26MY_ODYSSEY_DATA'!B:AR,11,FALSE) -> 195.4 | I91: =VLOOKUP(B91,'[1]26MY_ODYSSEY_DATA'!B:AR,12,FALSE) -> 0 | J91: =VLOOKUP(B91,'[1]26MY_ODYSSEY_DATA'!B:AR,13,FALSE) -> N/A | K91: =VLOOKUP(B91,'[1]26MY_ODYSSEY_DATA'!B:AR,14,FALSE) -> • | L91: =VLOOKUP(B91,'[1]26MY_ODYSSEY_DATA'!B:AR,15,FALSE) -> • | M91: =VLOOKUP(B91,'[1]26MY_ODYSSEY_DATA'!B:AR,16,FALSE) -> N/A | N91: =VLOOKUP($B91,'[1]26MY_ODYSSEY_DATA'!$B:$AR,17,FALSE) -> 0 | O91: =VLOOKUP($B91,'[1]26MY_ODYSSEY_DATA'!$B:$AR,18,FALSE) -> 0 | P91: =VLOOKUP($B91,'[1]26MY_ODYSSEY_DATA'!$B:$AR,19,FALSE) -> 0
B92: 08P20-THR-1B0A | C92: =VLOOKUP(B92,'[1]26MY_ODYSSEY_DATA'!B:AR,3,FALSE) -> Sonic Gray Pearl (NH-877P) | D92: =B92 -> 08P20-THR-1B0A | E92: =VLOOKUP(B92,'[1]26MY_ODYSSEY_DATA'!B:AR,9,FALSE) -> 87 | F92: =VLOOKUP(B92,'[1]26MY_ODYSSEY_DATA'!B:AR,10,FALSE) -> 145 | G92: =VLOOKUP(B92,'[1]26MY_ODYSSEY_DATA'!B:AR,7,FALSE) -> 0.3 | H92: =VLOOKUP(B92,'[1]26MY_ODYSSEY_DATA'!B:AR,11,FALSE) -> 195.4 | I92: =VLOOKUP(B92,'[1]26MY_ODYSSEY_DATA'!B:AR,12,FALSE) -> 0 | J92: =VLOOKUP(B92,'[1]26MY_ODYSSEY_DATA'!B:AR,13,FALSE) -> N/A | K92: =VLOOKUP(B92,'[1]26MY_ODYSSEY_DATA'!B:AR,14,FALSE) -> N/A | L92: =VLOOKUP(B92,'[1]26MY_ODYSSEY_DATA'!B:AR,15,FALSE) -> • | M92: =VLOOKUP(B92,'[1]26MY_ODYSSEY_DATA'!B:AR,16,FALSE) -> • | N92: =VLOOKUP($B92,'[1]26MY_ODYSSEY_DATA'!$B:$AR,17,FALSE) -> 0 | O92: =VLOOKUP($B92,'[1]26MY_ODYSSEY_DATA'!$B:$AR,18,FALSE) -> 0 | P92: =VLOOKUP($B92,'[1]26MY_ODYSSEY_DATA'!$B:$AR,19,FALSE) -> 0
B93: 08P20-THR-1A0A | C93: =VLOOKUP(B93,'[1]26MY_ODYSSEY_DATA'!B:AR,3,FALSE) -> Radiant Red Metallic II (R-580M) | D93: =B93 -> 08P20-THR-1A0A | E93: =VLOOKUP(B93,'[1]26MY_ODYSSEY_DATA'!B:AR,9,FALSE) -> 23.99 | F93: =VLOOKUP(B93,'[1]26MY_ODYSSEY_DATA'!B:AR,10,FALSE) -> 39.99 | G93: =VLOOKUP(B93,'[1]26MY_ODYSSEY_DATA'!B:AR,7,FALSE) -> 0.3 | H93: =VLOOKUP(B93,'[1]26MY_ODYSSEY_DATA'!B:AR,11,FALSE) -> 90.39 | I93: =VLOOKUP(B93,'[1]26MY_ODYSSEY_DATA'!B:AR,12,FALSE) -> 0 | J93: =VLOOKUP(B93,'[1]26MY_ODYSSEY_DATA'!B:AR,13,FALSE) -> N/A | K93: =VLOOKUP(B93,'[1]26MY_ODYSSEY_DATA'!B:AR,14,FALSE) -> N/A | L93: =VLOOKUP(B93,'[1]26MY_ODYSSEY_DATA'!B:AR,15,FALSE) -> N/A | M93: =VLOOKUP(B93,'[1]26MY_ODYSSEY_DATA'!B:AR,16,FALSE) -> • | N93: =VLOOKUP($B93,'[1]26MY_ODYSSEY_DATA'!$B:$AR,17,FALSE) -> 0 | O93: =VLOOKUP($B93,'[1]26MY_ODYSSEY_DATA'!$B:$AR,18,FALSE) -> 0 | P93: =VLOOKUP($B93,'[1]26MY_ODYSSEY_DATA'!$B:$AR,19,FALSE) -> 0
B94: 08P20-THR-1C0A | C94: =VLOOKUP(B94,'[1]26MY_ODYSSEY_DATA'!B:AR,3,FALSE) -> Solar Reflection Silver (NH-932M) | D94: =B94 -> 08P20-THR-1C0A | E94: =VLOOKUP(B94,'[1]26MY_ODYSSEY_DATA'!B:AR,9,FALSE) -> 87 | F94: =VLOOKUP(B94,'[1]26MY_ODYSSEY_DATA'!B:AR,10,FALSE) -> 145 | G94: =VLOOKUP(B94,'[1]26MY_ODYSSEY_DATA'!B:AR,7,FALSE) -> 0.3 | H94: =VLOOKUP(B94,'[1]26MY_ODYSSEY_DATA'!B:AR,11,FALSE) -> 195.4 | I94: =VLOOKUP(B94,'[1]26MY_ODYSSEY_DATA'!B:AR,12,FALSE) -> 0 | J94: =VLOOKUP(B94,'[1]26MY_ODYSSEY_DATA'!B:AR,13,FALSE) -> • | K94: =VLOOKUP(B94,'[1]26MY_ODYSSEY_DATA'!B:AR,14,FALSE) -> • | L94: =VLOOKUP(B94,'[1]26MY_ODYSSEY_DATA'!B:AR,15,FALSE) -> • | M94: =VLOOKUP(B94,'[1]26MY_ODYSSEY_DATA'!B:AR,16,FALSE) -> N/A | N94: =VLOOKUP($B94,'[1]26MY_ODYSSEY_DATA'!$B:$AR,17,FALSE) -> 0 | O94: =VLOOKUP($B94,'[1]26MY_ODYSSEY_DATA'!$B:$AR,18,FALSE) -> 0 | P94: =VLOOKUP($B94,'[1]26MY_ODYSSEY_DATA'!$B:$AR,19,FALSE) -> 0
C96: 4.0 Interior
C97: Description | D97: Part Number | E97: Dealer Net | F97: List Price | G97: FRT | H97: Installed Price | I97: Application | Q97: Comments
I98: ='[1]26MY_ODYSSEY_DATA'!M$6 -> 0 | J98: ='[1]26MY_ODYSSEY_DATA'!N$6 -> Sport | K98: ='[1]26MY_ODYSSEY_DATA'!O$6 -> Sport-L | L98: ='[1]26MY_ODYSSEY_DATA'!P$6 -> Touring | M98: ='[1]26MY_ODYSSEY_DATA'!Q$6 -> Black Edition | N98: ='[1]26MY_ODYSSEY_DATA'!R$6 -> 0 | O98: ='[1]26MY_ODYSSEY_DATA'!S$6 -> 0 | P98: ='[1]26MY_ODYSSEY_DATA'!T$6 -> 0
B99: 08P17-THR-110A | C99: =VLOOKUP(B99,'[1]26MY_ODYSSEY_DATA'!B:AR,3,FALSE) -> All-Season Floor Mats - White Logo | D99: =B99 -> 08P17-THR-110A | E99: =VLOOKUP(B99,'[1]26MY_ODYSSEY_DATA'!B:AR,9,FALSE) -> 195 | F99: =VLOOKUP(B99,'[1]26MY_ODYSSEY_DATA'!B:AR,10,FALSE) -> 325 | G99: =VLOOKUP(B99,'[1]26MY_ODYSSEY_DATA'!B:AR,7,FALSE) -> 0.1 | H99: =VLOOKUP(B99,'[1]26MY_ODYSSEY_DATA'!B:AR,11,FALSE) -> 341.8 | I99: =VLOOKUP(B99,'[1]26MY_ODYSSEY_DATA'!B:AR,12,FALSE) -> 0 | J99: =VLOOKUP(B99,'[1]26MY_ODYSSEY_DATA'!B:AR,13,FALSE) -> • | K99: =VLOOKUP(B99,'[1]26MY_ODYSSEY_DATA'!B:AR,14,FALSE) -> • | L99: =VLOOKUP(B99,'[1]26MY_ODYSSEY_DATA'!B:AR,15,FALSE) -> • | M99: =VLOOKUP(B99,'[1]26MY_ODYSSEY_DATA'!B:AR,16,FALSE) -> • | N99: =VLOOKUP($B99,'[1]26MY_ODYSSEY_DATA'!$B:$AR,17,FALSE) -> 0 | O99: =VLOOKUP($B99,'[1]26MY_ODYSSEY_DATA'!$B:$AR,18,FALSE) -> 0 | P99: =VLOOKUP($B99,'[1]26MY_ODYSSEY_DATA'!$B:$AR,19,FALSE) -> 0 | Q99: =IF(VLOOKUP(B99,'[1]26MY_ODYSSEY_DATA'!B:AR,20,FALSE)="","",VLOOKUP(B99,'[1]26MY_ODYSSEY_DATA'!B:AR,20,FALSE)) -> White Logo.
B100: 08U45-THR-100A | C100: =VLOOKUP(B100,'[1]26MY_ODYSSEY_DATA'!B:AR,3,FALSE) -> Cargo Tray - Deep | D100: =B100 -> 08U45-THR-100A | E100: =VLOOKUP(B100,'[1]26MY_ODYSSEY_DATA'!B:AR,9,FALSE) -> 140 | F100: =VLOOKUP(B100,'[1]26MY_ODYSSEY_DATA'!B:AR,10,FALSE) -> 233 | G100: =VLOOKUP(B100,'[1]26MY_ODYSSEY_DATA'!B:AR,7,FALSE) -> 0.1 | H100: =VLOOKUP(B100,'[1]26MY_ODYSSEY_DATA'!B:AR,11,FALSE) -> 249.8 | I100: =VLOOKUP(B100,'[1]26MY_ODYSSEY_DATA'!B:AR,12,FALSE) -> 0 | J100: =VLOOKUP(B100,'[1]26MY_ODYSSEY_DATA'!B:AR,13,FALSE) -> • | K100: =VLOOKUP(B100,'[1]26MY_ODYSSEY_DATA'!B:AR,14,FALSE) -> • | L100: =VLOOKUP(B100,'[1]26MY_ODYSSEY_DATA'!B:AR,15,FALSE) -> • | M100: =VLOOKUP(B100,'[1]26MY_ODYSSEY_DATA'!B:AR,16,FALSE) -> • | N100: =VLOOKUP($B100,'[1]26MY_ODYSSEY_DATA'!$B:$AR,17,FALSE) -> 0 | O100: =VLOOKUP($B100,'[1]26MY_ODYSSEY_DATA'!$B:$AR,18,FALSE) -> 0 | P100: =VLOOKUP($B100,'[1]26MY_ODYSSEY_DATA'!$B:$AR,19,FALSE) -> 0 | Q100: =IF(VLOOKUP(B100,'[1]26MY_ODYSSEY_DATA'!B:AR,20,FALSE)="","",VLOOKUP(B100,'[1]26MY_ODYSSEY_DATA'!B:AR,20,FALSE))
B101: 08U45-THR-100B | C101: =VLOOKUP(B101,'[1]26MY_ODYSSEY_DATA'!B:AR,3,FALSE) -> Cargo Tray - Folding | D101: =B101 -> 08U45-THR-100B | E101: =VLOOKUP(B101,'[1]26MY_ODYSSEY_DATA'!B:AR,9,FALSE) -> 160 | F101: =VLOOKUP(B101,'[1]26MY_ODYSSEY_DATA'!B:AR,10,FALSE) -> 267 | G101: =VLOOKUP(B101,'[1]26MY_ODYSSEY_DATA'!B:AR,7,FALSE) -> 0.1 | H101: =VLOOKUP(B101,'[1]26MY_ODYSSEY_DATA'!B:AR,11,FALSE) -> 283.8 | I101: =VLOOKUP(B101,'[1]26MY_ODYSSEY_DATA'!B:AR,12,FALSE) -> 0 | J101: =VLOOKUP(B101,'[1]26MY_ODYSSEY_DATA'!B:AR,13,FALSE) -> • | K101: =VLOOKUP(B101,'[1]26MY_ODYSSEY_DATA'!B:AR,14,FALSE) -> • | L101: =VLOOKUP(B101,'[1]26MY_ODYSSEY_DATA'!B:AR,15,FALSE) -> • | M101: =VLOOKUP(B101,'[1]26MY_ODYSSEY_DATA'!B:AR,16,FALSE) -> • | N101: =VLOOKUP($B101,'[1]26MY_ODYSSEY_DATA'!$B:$AR,17,FALSE) -> 0 | O101: =VLOOKUP($B101,'[1]26MY_ODYSSEY_DATA'!$B:$AR,18,FALSE) -> 0 | P101: =VLOOKUP($B101,'[1]26MY_ODYSSEY_DATA'!$B:$AR,19,FALSE) -> 0 | Q101: =IF(VLOOKUP(B101,'[1]26MY_ODYSSEY_DATA'!B:AR,20,FALSE)="","",VLOOKUP(B101,'[1]26MY_ODYSSEY_DATA'!B:AR,20,FALSE))
B102: 08U45-THR-300 | C102: =VLOOKUP(B102,'[1]26MY_ODYSSEY_DATA'!B:AR,3,FALSE) -> Cargo Bins | D102: =B102 -> 08U45-THR-300 | E102: =VLOOKUP(B102,'[1]26MY_ODYSSEY_DATA'!B:AR,9,FALSE) -> 413 | F102: =VLOOKUP(B102,'[1]26MY_ODYSSEY_DATA'!B:AR,10,FALSE) -> 688 | G102: =VLOOKUP(B102,'[1]26MY_ODYSSEY_DATA'!B:AR,7,FALSE) -> 0.1 | H102: =VLOOKUP(B102,'[1]26MY_ODYSSEY_DATA'!B:AR,11,FALSE) -> 704.8 | I102: =VLOOKUP(B102,'[1]26MY_ODYSSEY_DATA'!B:AR,12,FALSE) -> 0 | J102: =VLOOKUP(B102,'[1]26MY_ODYSSEY_DATA'!B:AR,13,FALSE) -> • | K102: =VLOOKUP(B102,'[1]26MY_ODYSSEY_DATA'!B:AR,14,FALSE) -> • | L102: =VLOOKUP(B102,'[1]26MY_ODYSSEY_DATA'!B:AR,15,FALSE) -> • | M102: =VLOOKUP(B102,'[1]26MY_ODYSSEY_DATA'!B:AR,16,FALSE) -> • | N102: =VLOOKUP($B102,'[1]26MY_ODYSSEY_DATA'!$B:$AR,17,FALSE) -> 0 | O102: =VLOOKUP($B102,'[1]26MY_ODYSSEY_DATA'!$B:$AR,18,FALSE) -> 0 | P102: =VLOOKUP($B102,'[1]26MY_ODYSSEY_DATA'!$B:$AR,19,FALSE) -> 0 | Q102: =IF(VLOOKUP(B102,'[1]26MY_ODYSSEY_DATA'!B:AR,20,FALSE)="","",VLOOKUP(B102,'[1]26MY_ODYSSEY_DATA'!B:AR,20,FALSE))
B103: 08P42-THR-100 | C103: =VLOOKUP(B103,'[1]26MY_ODYSSEY_DATA'!B:AR,3,FALSE) -> Cargo Liner | D103: =B103 -> 08P42-THR-100 | E103: =VLOOKUP(B103,'[1]26MY_ODYSSEY_DATA'!B:AR,9,FALSE) -> 295 | F103: =VLOOKUP(B103,'[1]26MY_ODYSSEY_DATA'!B:AR,10,FALSE) -> 421 | G103: =VLOOKUP(B103,'[1]26MY_ODYSSEY_DATA'!B:AR,7,FALSE) -> 1.2 | H103: =VLOOKUP(B103,'[1]26MY_ODYSSEY_DATA'!B:AR,11,FALSE) -> 622.6 | I103: =VLOOKUP(B103,'[1]26MY_ODYSSEY_DATA'!B:AR,12,FALSE) -> 0 | J103: =VLOOKUP(B103,'[1]26MY_ODYSSEY_DATA'!B:AR,13,FALSE) -> • | K103: =VLOOKUP(B103,'[1]26MY_ODYSSEY_DATA'!B:AR,14,FALSE) -> • | L103: =VLOOKUP(B103,'[1]26MY_ODYSSEY_DATA'!B:AR,15,FALSE) -> • | M103: =VLOOKUP(B103,'[1]26MY_ODYSSEY_DATA'!B:AR,16,FALSE) -> • | N103: =VLOOKUP($B103,'[1]26MY_ODYSSEY_DATA'!$B:$AR,17,FALSE) -> 0 | O103: =VLOOKUP($B103,'[1]26MY_ODYSSEY_DATA'!$B:$AR,18,FALSE) -> 0 | P103: =VLOOKUP($B103,'[1]26MY_ODYSSEY_DATA'!$B:$AR,19,FALSE) -> 0 | Q103: =IF(VLOOKUP(B103,'[1]26MY_ODYSSEY_DATA'!B:AR,20,FALSE)="","",VLOOKUP(B103,'[1]26MY_ODYSSEY_DATA'!B:AR,20,FALSE))
B104: 08L96-THR-100 | C104: =VLOOKUP(B104,'[1]26MY_ODYSSEY_DATA'!B:AR,3,FALSE) -> Cargo Net | D104: =B104 -> 08L96-THR-100 | E104: =VLOOKUP(B104,'[1]26MY_ODYSSEY_DATA'!B:AR,9,FALSE) -> 42 | F104: =VLOOKUP(B104,'[1]26MY_ODYSSEY_DATA'!B:AR,10,FALSE) -> 70 | G104: =VLOOKUP(B104,'[1]26MY_ODYSSEY_DATA'!B:AR,7,FALSE) -> 0.1 | H104: =VLOOKUP(B104,'[1]26MY_ODYSSEY_DATA'!B:AR,11,FALSE) -> 86.8 | I104: =VLOOKUP(B104,'[1]26MY_ODYSSEY_DATA'!B:AR,12,FALSE) -> 0 | J104: =VLOOKUP(B104,'[1]26MY_ODYSSEY_DATA'!B:AR,13,FALSE) -> • | K104: =VLOOKUP(B104,'[1]26MY_ODYSSEY_DATA'!B:AR,14,FALSE) -> • | L104: =VLOOKUP(B104,'[1]26MY_ODYSSEY_DATA'!B:AR,15,FALSE) -> • | M104: =VLOOKUP(B104,'[1]26MY_ODYSSEY_DATA'!B:AR,16,FALSE) -> • | N104: =VLOOKUP($B104,'[1]26MY_ODYSSEY_DATA'!$B:$AR,17,FALSE) -> 0 | O104: =VLOOKUP($B104,'[1]26MY_ODYSSEY_DATA'!$B:$AR,18,FALSE) -> 0 | P104: =VLOOKUP($B104,'[1]26MY_ODYSSEY_DATA'!$B:$AR,19,FALSE) -> 0 | Q104: =IF(VLOOKUP(B104,'[1]26MY_ODYSSEY_DATA'!B:AR,20,FALSE)="","",VLOOKUP(B104,'[1]26MY_ODYSSEY_DATA'!B:AR,20,FALSE))
B105: 08P32-THR-310D | C105: =VLOOKUP(B105,'[1]26MY_ODYSSEY_DATA'!B:AR,3,FALSE) -> Seat Cover, 2nd Row (8P) | D105: =B105 -> 08P32-THR-310D | E105: =VLOOKUP(B105,'[1]26MY_ODYSSEY_DATA'!B:AR,9,FALSE) -> 394 | F105: =VLOOKUP(B105,'[1]26MY_ODYSSEY_DATA'!B:AR,10,FALSE) -> 563 | G105: =VLOOKUP(B105,'[1]26MY_ODYSSEY_DATA'!B:AR,7,FALSE) -> 0.3 | H105: =VLOOKUP(B105,'[1]26MY_ODYSSEY_DATA'!B:AR,11,FALSE) -> 613.4 | I105: =VLOOKUP(B105,'[1]26MY_ODYSSEY_DATA'!B:AR,12,FALSE) -> 0 | J105: =VLOOKUP(B105,'[1]26MY_ODYSSEY_DATA'!B:AR,13,FALSE) -> • | K105: =VLOOKUP(B105,'[1]26MY_ODYSSEY_DATA'!B:AR,14,FALSE) -> • | L105: =VLOOKUP(B105,'[1]26MY_ODYSSEY_DATA'!B:AR,15,FALSE) -> • | M105: =VLOOKUP(B105,'[1]26MY_ODYSSEY_DATA'!B:AR,16,FALSE) -> • | N105: =VLOOKUP($B105,'[1]26MY_ODYSSEY_DATA'!$B:$AR,17,FALSE) -> 0 | O105: =VLOOKUP($B105,'[1]26MY_ODYSSEY_DATA'!$B:$AR,18,FALSE) -> 0 | P105: =VLOOKUP($B105,'[1]26MY_ODYSSEY_DATA'!$B:$AR,19,FALSE) -> 0 | Q105: =IF(VLOOKUP(B105,'[1]26MY_ODYSSEY_DATA'!B:AR,20,FALSE)="","",VLOOKUP(B105,'[1]26MY_ODYSSEY_DATA'!B:AR,20,FALSE)) -> 8 Passenger Seating.
B106: 08P32-THR-310F | C106: =VLOOKUP(B106,'[1]26MY_ODYSSEY_DATA'!B:AR,3,FALSE) -> Seat Cover, 3rd Row | D106: =B106 -> 08P32-THR-310F | E106: =VLOOKUP(B106,'[1]26MY_ODYSSEY_DATA'!B:AR,9,FALSE) -> 304 | F106: =VLOOKUP(B106,'[1]26MY_ODYSSEY_DATA'!B:AR,10,FALSE) -> 434 | G106: =VLOOKUP(B106,'[1]26MY_ODYSSEY_DATA'!B:AR,7,FALSE) -> 0.2 | H106: =VLOOKUP(B106,'[1]26MY_ODYSSEY_DATA'!B:AR,11,FALSE) -> 467.6 | I106: =VLOOKUP(B106,'[1]26MY_ODYSSEY_DATA'!B:AR,12,FALSE) -> 0 | J106: =VLOOKUP(B106,'[1]26MY_ODYSSEY_DATA'!B:AR,13,FALSE) -> • | K106: =VLOOKUP(B106,'[1]26MY_ODYSSEY_DATA'!B:AR,14,FALSE) -> • | L106: =VLOOKUP(B106,'[1]26MY_ODYSSEY_DATA'!B:AR,15,FALSE) -> • | M106: =VLOOKUP(B106,'[1]26MY_ODYSSEY_DATA'!B:AR,16,FALSE) -> • | N106: =VLOOKUP($B106,'[1]26MY_ODYSSEY_DATA'!$B:$AR,17,FALSE) -> 0 | O106: =VLOOKUP($B106,'[1]26MY_ODYSSEY_DATA'!$B:$AR,18,FALSE) -> 0 | P106: =VLOOKUP($B106,'[1]26MY_ODYSSEY_DATA'!$B:$AR,19,FALSE) -> 0 | Q106: =IF(VLOOKUP(B106,'[1]26MY_ODYSSEY_DATA'!B:AR,20,FALSE)="","",VLOOKUP(B106,'[1]26MY_ODYSSEY_DATA'!B:AR,20,FALSE))
C108: 5.0 Electrical
C109: Description | D109: Part Number | E109: Dealer Net | F109: List Price | G109: FRT | H109: Installed Price | I109: Application | Q109: Comments
I110: ='[1]26MY_ODYSSEY_DATA'!M$6 -> 0 | J110: ='[1]26MY_ODYSSEY_DATA'!N$6 -> Sport | K110: ='[1]26MY_ODYSSEY_DATA'!O$6 -> Sport-L | L110: ='[1]26MY_ODYSSEY_DATA'!P$6 -> Touring | M110: ='[1]26MY_ODYSSEY_DATA'!Q$6 -> Black Edition | N110: ='[1]26MY_ODYSSEY_DATA'!R$6 -> 0 | O110: ='[1]26MY_ODYSSEY_DATA'!S$6 -> 0 | P110: ='[1]26MY_ODYSSEY_DATA'!T$6 -> 0
B111: 08E12-THR-100 | C111: =VLOOKUP(B111,'[1]26MY_ODYSSEY_DATA'!B:AR,3,FALSE) -> Illuminated Door Sill Trim - Front & Rear | D111: =B111 -> 08E12-THR-100 | E111: =VLOOKUP(B111,'[1]26MY_ODYSSEY_DATA'!B:AR,9,FALSE) -> 564 | F111: =VLOOKUP(B111,'[1]26MY_ODYSSEY_DATA'!B:AR,10,FALSE) -> 868 | G111: =VLOOKUP(B111,'[1]26MY_ODYSSEY_DATA'!B:AR,7,FALSE) -> 1.2 | H111: =VLOOKUP(B111,'[1]26MY_ODYSSEY_DATA'!B:AR,11,FALSE) -> 1069.6 | I111: =VLOOKUP(B111,'[1]26MY_ODYSSEY_DATA'!B:AR,12,FALSE) -> 0 | J111: =VLOOKUP(B111,'[1]26MY_ODYSSEY_DATA'!B:AR,13,FALSE) -> • | K111: =VLOOKUP(B111,'[1]26MY_ODYSSEY_DATA'!B:AR,14,FALSE) -> • | L111: =VLOOKUP(B111,'[1]26MY_ODYSSEY_DATA'!B:AR,15,FALSE) -> • | M111: =VLOOKUP(B111,'[1]26MY_ODYSSEY_DATA'!B:AR,16,FALSE) -> • | N111: =VLOOKUP($B111,'[1]26MY_ODYSSEY_DATA'!$B:$AR,17,FALSE) -> 0 | O111: =VLOOKUP($B111,'[1]26MY_ODYSSEY_DATA'!$B:$AR,18,FALSE) -> 0 | P111: =VLOOKUP($B111,'[1]26MY_ODYSSEY_DATA'!$B:$AR,19,FALSE) -> 0 | Q111: =IF(VLOOKUP(B111,'[1]26MY_ODYSSEY_DATA'!B:AR,20,FALSE)="","",VLOOKUP(B111,'[1]26MY_ODYSSEY_DATA'!B:AR,20,FALSE)) -> Front and Rear Doors Sills.
B112: 08E12-THR-100A | C112: =VLOOKUP(B112,'[1]26MY_ODYSSEY_DATA'!B:AR,3,FALSE) -> Illuminated Door Sill Trim - Front Only | D112: =B112 -> 08E12-THR-100A | E112: =VLOOKUP(B112,'[1]26MY_ODYSSEY_DATA'!B:AR,9,FALSE) -> 19.99 | F112: =VLOOKUP(B112,'[1]26MY_ODYSSEY_DATA'!B:AR,10,FALSE) -> 32.99 | G112: =VLOOKUP(B112,'[1]26MY_ODYSSEY_DATA'!B:AR,7,FALSE) -> 0.8 | H112: =VLOOKUP(B112,'[1]26MY_ODYSSEY_DATA'!B:AR,11,FALSE) -> 167.39 | I112: =VLOOKUP(B112,'[1]26MY_ODYSSEY_DATA'!B:AR,12,FALSE) -> 0 | J112: =VLOOKUP(B112,'[1]26MY_ODYSSEY_DATA'!B:AR,13,FALSE) -> • | K112: =VLOOKUP(B112,'[1]26MY_ODYSSEY_DATA'!B:AR,14,FALSE) -> • | L112: =VLOOKUP(B112,'[1]26MY_ODYSSEY_DATA'!B:AR,15,FALSE) -> • | M112: =VLOOKUP(B112,'[1]26MY_ODYSSEY_DATA'!B:AR,16,FALSE) -> • | N112: =VLOOKUP($B112,'[1]26MY_ODYSSEY_DATA'!$B:$AR,17,FALSE) -> 0 | O112: =VLOOKUP($B112,'[1]26MY_ODYSSEY_DATA'!$B:$AR,18,FALSE) -> 0 | P112: =VLOOKUP($B112,'[1]26MY_ODYSSEY_DATA'!$B:$AR,19,FALSE) -> 0 | Q112: =IF(VLOOKUP(B112,'[1]26MY_ODYSSEY_DATA'!B:AR,20,FALSE)="","",VLOOKUP(B112,'[1]26MY_ODYSSEY_DATA'!B:AR,20,FALSE)) -> Front Doors Sills only.
...

Sheet 25MY_ODYSSEY_SELL-EN
B3: 26MY Honda Odyssey
B4: 200
B6: POPULAR ACCESSORIES
B7: 20
B8: 150
B10: 20 | C10: ='26MY_ODYSSEY_APP_EN'!$C$99 -> All-Season Floor Mats - White Logo | H10: ='26MY_ODYSSEY_APP_EN'!$C$100 -> Cargo Tray - Deep | M10: ='26MY_ODYSSEY_APP_EN'!$C$101 -> Cargo Tray - Folding
B11: 20 | C11: ='26MY_ODYSSEY_APP_EN'!$H$99 -> 341.8 | D11: =-PMT($D$29/52,5*52,C11) -> 1.5585734 | E11: /wk * | F11: =$C$29 -> (6.99%) | H11: ='26MY_ODYSSEY_APP_EN'!$H$101 -> 283.8 | I11: =-PMT($D$29/52,5*52,H11) -> 1.2940993 | J11: /wk * | K11: =$C$29 -> (6.99%) | M11: ='26MY_ODYSSEY_APP_EN'!$H$111 -> 1069.6 | N11: =-PMT($D$29/52,5*52,M11) -> 4.8772678 | O11: /wk * | P11: =$C$29 -> (6.99%)
B13: &
B15: 20 | C15: =TEXT('26MY_ODYSSEY_APP_EN'!$C$62,0)&(TEXT($B$13,0)&TEXT('26MY_ODYSSEY_APP_EN'!$C$64,0)) -> Roof Rails - Black & Crossbars | H15: =TEXT('26MY_ODYSSEY_APP_EN'!$C$75,0)&(TEXT($B$13,0)&TEXT('26MY_ODYSSEY_APP_EN'!$C$78,0)) -> Trailer Hitch & Trailer Hitch Harness | M15: ='26MY_ODYSSEY_APP_EN'!$C$111 -> Illuminated Door Sill Trim - Front & Rear
B16: 50 | C16: ='26MY_ODYSSEY_APP_EN'!$H$62+'26MY_ODYSSEY_APP_EN'!$H$64 -> 1328.6 | D16: =-PMT($D$29/52,5*52,C16) -> 6.0582816 | E16: /wk * | F16: =$C$29 -> (6.99%) | H16: ='26MY_ODYSSEY_APP_EN'!$H$75+'26MY_ODYSSEY_APP_EN'!$H$78 -> 1616.4 | I16: =-PMT($D$29/52,5*52,H16) -> 7.3706205 | J16: /wk * | K16: =$C$29 -> (6.99%) | M16: ='26MY_ODYSSEY_APP_EN'!$H$111 -> 1069.6 | N16: =-PMT($D$29/52,5*52,M16) -> 4.8772678 | O16: /wk * | P16: =$C$29 -> (6.99%)
B18: 150
B20: 20 | C20: ='26MY_ODYSSEY_APP_EN'!$C$58 -> Hood Air Deflector | H20: ='26MY_ODYSSEY_APP_EN'!$C$57 -> Door Visor | M20: ='26MY_ODYSSEY_APP_EN'!$C$61 -> Tent
B21: 50 | C21: ='26MY_ODYSSEY_APP_EN'!$H$58 -> 424 | D21: =-PMT($D$29/52,5*52,C21) -> 1.9333971 | E21: /wk * | F21: =$C$29 -> (6.99%) | H21: ='26MY_ODYSSEY_APP_EN'!$H$57 -> 474 | I21: =-PMT($D$29/52,5*52,H21) -> 2.161392 | J21: /wk * | K21: =$C$29 -> (6.99%) | M21: ='26MY_ODYSSEY_APP_EN'!$H$61 -> 681 | N21: =-PMT($D$29/52,5*52,M21) -> 3.1052911 | O21: /wk * | P21: =$C$29 -> (6.99%)
C23: Genuine Honda Accessories purchased with a new Honda vehicle include a 3 year / 60,000 km manufacturer's warranty.
C24: Vehicle accessories purchased after vehicle sale include a 1 year / 20,000km manufacturer's warranty.
B25: 20 | C25: *Prices shown include the cost of installation.
B26: 60 | C26: *For informational purposes only. Weekly amounts shown are estimated payments based on a 60 month finance contract at 6.99% APR (including the cost of installation). Applicable taxes and fees are extra. Accessories cannot be financed on their own and must be financed through Honda Canada Finance Inc., on approved credit, in conjunction with a Honda vehicle. Representative finance example: $350.00 financed at 6.99% APR equals $1.60 weekly for 60 months. 260 weekly payments required. Cost of borrowing is $64.80 for a total obligation of $414.80. Actual payment amounts will vary based on APR, finance contract term and cost of the applicable accessories. Conditions apply. See your Honda dealer for full details.
C27: *More customized weekly payment options & accessories can be seen on Honda.ca - Build & Price
B28: 20
B29: 18 | C29: (6.99%) | D29: 0.0699
B30: 7.5 | C30: 12 | D30: 8 | E30: 8 | F30: 10 | G30: 8.5 | H30: 12 | I30: 8 | J30: 8 | K30: 10 | L30: 8.5 | M30: 12 | N30: 8 | O30: 8 | P30: 10 | Q30: 7.5
B31: Publication Date: | C31: ='[1]26MY_ODYSSEY_DATA'!$C$3 -> 45902 | D31: ='SELECT PROVINCE'!$A$23 -> All published prices, trim specifications, and availability are subject to change without prior notice. | P31: Province | Q31: ='[1]26MY_ODYSSEY_DATA'!L5 -> YT

Sheet 26MY_ODYSSEY_APP_FR
B2: Honda Internal | C2: Accessoires Honda
C3: Nom du modèle | D3: ='[1]26MY_ODYSSEY_DATA'!C1 -> Odyssey
C4: Année modèle | D4: ='[1]26MY_ODYSSEY_DATA'!C2 -> 2026
C5: S = De série (accessoire de série sur cette version).
C6: T = Taille des pneus (la taille de la jante accessoire diffère de la jante d’origine. Le client aura besoin de nouveaux pneus pour ces jantes).
C7: E = Échange d’équipement de série (la taille de la jante accessoire est la même que celle de la jante d’origine. Le client peut utiliser les pneus d’origine).
C8: N/A = Sans objet (l’accessoire ne peut être utilisé pour cette version).
H10: Province
C11: 1.0 Groupes et ensembles | H11: =prov_cd -> YT
C12: La description | D12: Numéro de pièce | E12: Prix net | F12: Prix de liste | G12: T.F.F. | H12: Prix installé | I12: Application | Q12: Commentaires
I13: ='[1]26MY_ODYSSEY_DATA'!M$6 -> 0 | J13: ='[1]26MY_ODYSSEY_DATA'!N$6 -> Sport | K13: ='[1]26MY_ODYSSEY_DATA'!O$6 -> Sport-L | L13: ='[1]26MY_ODYSSEY_DATA'!P$6 -> Touring | M13: ='[1]26MY_ODYSSEY_DATA'!Q$6 -> Black Edition | N13: ='[1]26MY_ODYSSEY_DATA'!R$6 -> 0 | O13: ='[1]26MY_ODYSSEY_DATA'!S$6 -> 0 | P13: ='[1]26MY_ODYSSEY_DATA'!T$6 -> 0
B14: 25ODY-PRO-PKG1 | C14: =VLOOKUP(B14,'[1]26MY_ODYSSEY_DATA'!B:AR,4,FALSE) -> Ensemble de protection 1 | D14: =B14 -> 25ODY-PRO-PKG1 | E14: =VLOOKUP(B14,'[1]26MY_ODYSSEY_DATA'!B:AR,9,FALSE) -> 375.3 | F14: =VLOOKUP(B14,'[1]26MY_ODYSSEY_DATA'!B:AR,10,FALSE) -> 695 | G14: =VLOOKUP(B14,'[1]26MY_ODYSSEY_DATA'!B:AR,7,FALSE) -> 0.6 | H14: =VLOOKUP(B14,'[1]26MY_ODYSSEY_DATA'!B:AR,11,FALSE) -> 795.8 | I14: =VLOOKUP(B14,'[1]26MY_ODYSSEY_DATA'!B:AR,12,FALSE) -> 0 | J14: =VLOOKUP(B14,'[1]26MY_ODYSSEY_DATA'!B:AR,13,FALSE) -> • | K14: =VLOOKUP(B14,'[1]26MY_ODYSSEY_DATA'!B:AR,14,FALSE) -> • | L14: =VLOOKUP(B14,'[1]26MY_ODYSSEY_DATA'!B:AR,15,FALSE) -> • | M14: =VLOOKUP(B14,'[1]26MY_ODYSSEY_DATA'!B:AR,16,FALSE) -> • | N14: =VLOOKUP($B14,'[1]26MY_ODYSSEY_DATA'!$B:$AR,17,FALSE) -> 0 | O14: =VLOOKUP($B14,'[1]26MY_ODYSSEY_DATA'!$B:$AR,18,FALSE) -> 0 | P14: =VLOOKUP($B14,'[1]26MY_ODYSSEY_DATA'!$B:$AR,19,FALSE) -> 0 | Q14: =IF(VLOOKUP(B14,'[1]26MY_ODYSSEY_DATA'!B:AR,21,FALSE)="","",VLOOKUP(B14,'[1]26MY_ODYSSEY_DATA'!B:AR,21,FALSE)) -> Inscription 'ODYSSEY' blanche sur les tapis de sol.Plateau de chargement - Profond.
B15: 08P17-THR-110A | C15: =VLOOKUP(B15,'[1]26MY_ODYSSEY_DATA'!B:AR,4,FALSE) -> Protège-tapis toutes saisons - logo blanc | D15: =B15 -> 08P17-THR-110A
B16: 08U45-THR-100A | C16: =VLOOKUP(B16,'[1]26MY_ODYSSEY_DATA'!B:AR,4,FALSE) -> Plateau de compartiment à bagages - profond | D16: =B16 -> 08U45-THR-100A
B17: 08P09-THR-300A | C17: =VLOOKUP(B17,'[1]26MY_ODYSSEY_DATA'!B:AR,4,FALSE) -> Garde-boue arrière | D17: =B17 -> 08P09-THR-300A
B19: 25ODY-PRO-PKG2 | C19: =VLOOKUP(B19,'[1]26MY_ODYSSEY_DATA'!B:AR,4,FALSE) -> Ensemble de protection 2 | D19: =B19 -> 25ODY-PRO-PKG2 | E19: =VLOOKUP(B19,'[1]26MY_ODYSSEY_DATA'!B:AR,9,FALSE) -> 393.3 | F19: =VLOOKUP(B19,'[1]26MY_ODYSSEY_DATA'!B:AR,10,FALSE) -> 729 | G19: =VLOOKUP(B19,'[1]26MY_ODYSSEY_DATA'!B:AR,7,FALSE) -> 0.6 | H19: =VLOOKUP(B19,'[1]26MY_ODYSSEY_DATA'!B:AR,11,FALSE) -> 829.8 | I19: =VLOOKUP(B19,'[1]26MY_ODYSSEY_DATA'!B:AR,12,FALSE) -> 0 | J19: =VLOOKUP(B19,'[1]26MY_ODYSSEY_DATA'!B:AR,13,FALSE) -> • | K19: =VLOOKUP(B19,'[1]26MY_ODYSSEY_DATA'!B:AR,14,FALSE) -> • | L19: =VLOOKUP(B19,'[1]26MY_ODYSSEY_DATA'!B:AR,15,FALSE) -> • | M19: =VLOOKUP(B19,'[1]26MY_ODYSSEY_DATA'!B:AR,16,FALSE) -> • | N19: =VLOOKUP($B19,'[1]26MY_ODYSSEY_DATA'!$B:$AR,17,FALSE) -> 0 | O19: =VLOOKUP($B19,'[1]26MY_ODYSSEY_DATA'!$B:$AR,18,FALSE) -> 0 | P19: =VLOOKUP($B19,'[1]26MY_ODYSSEY_DATA'!$B:$AR,19,FALSE) -> 0 | Q19: =IF(VLOOKUP(B19,'[1]26MY_ODYSSEY_DATA'!B:AR,21,FALSE)="","",VLOOKUP(B19,'[1]26MY_ODYSSEY_DATA'!B:AR,21,FALSE)) -> Inscription 'ODYSSEY' blanche sur les tapis de sol. Plateau de chargement - Pliable.
B20: 08P17-THR-110A | C20: =VLOOKUP(B20,'[1]26MY_ODYSSEY_DATA'!B:AR,4,FALSE) -> Protège-tapis toutes saisons - logo blanc | D20: =B20 -> 08P17-THR-110A
B21: 08U45-THR-100B | C21: =VLOOKUP(B21,'[1]26MY_ODYSSEY_DATA'!B:AR,4,FALSE) -> Plateaux de coffre pliants | D21: =B21 -> 08U45-THR-100B
B22: 08P09-THR-300A | C22: =VLOOKUP(B22,'[1]26MY_ODYSSEY_DATA'!B:AR,4,FALSE) -> Garde-boue arrière | D22: =B22 -> 08P09-THR-300A
B24: 21ODY-COLD-PKG | C24: =VLOOKUP(B24,'[1]26MY_ODYSSEY_DATA'!B:AR,4,FALSE) -> Ensemble de temps froid | D24: =B24 -> 21ODY-COLD-PKG | E24: =VLOOKUP(B24,'[1]26MY_ODYSSEY_DATA'!B:AR,9,FALSE) -> 224.2 | F24: =VLOOKUP(B24,'[1]26MY_ODYSSEY_DATA'!B:AR,10,FALSE) -> 374.3 | G24: =VLOOKUP(B24,'[1]26MY_ODYSSEY_DATA'!B:AR,7,FALSE) -> 1.4 | H24: =VLOOKUP(B24,'[1]26MY_ODYSSEY_DATA'!B:AR,11,FALSE) -> 609.5 | I24: =VLOOKUP(B24,'[1]26MY_ODYSSEY_DATA'!B:AR,12,FALSE) -> 0 | J24: =VLOOKUP(B24,'[1]26MY_ODYSSEY_DATA'!B:AR,13,FALSE) -> • | K24: =VLOOKUP(B24,'[1]26MY_ODYSSEY_DATA'!B:AR,14,FALSE) -> • | L24: =VLOOKUP(B24,'[1]26MY_ODYSSEY_DATA'!B:AR,15,FALSE) -> • | M24: =VLOOKUP(B24,'[1]26MY_ODYSSEY_DATA'!B:AR,16,FALSE) -> • | N24: =VLOOKUP($B24,'[1]26MY_ODYSSEY_DATA'!$B:$AR,17,FALSE) -> 0 | O24: =VLOOKUP($B24,'[1]26MY_ODYSSEY_DATA'!$B:$AR,18,FALSE) -> 0 | P24: =VLOOKUP($B24,'[1]26MY_ODYSSEY_DATA'!$B:$AR,19,FALSE) -> 0 | Q24: =IF(VLOOKUP(B24,'[1]26MY_ODYSSEY_DATA'!B:AR,21,FALSE)="","",VLOOKUP(B24,'[1]26MY_ODYSSEY_DATA'!B:AR,21,FALSE)) -> Rabais de 5% est appliqué.
B25: 08T44-SJA-401A | C25: =VLOOKUP(B25,'[1]26MY_ODYSSEY_DATA'!B:AR,4,FALSE) -> Chauffe-moteur | D25: =B25 -> 08T44-SJA-401A
B26: 31670-BMS-004H | C26: =VLOOKUP(B26,'[1]26MY_ODYSSEY_DATA'!B:AR,4,FALSE) -> Chargeur/mainteneur de charge de batterie automobile 12 V | D26: =B26 -> 31670-BMS-004H
B28: 25ODY-TOWA1 ou 25ODY-TOWB1 | C28: =VLOOKUP(B28,'[1]26MY_ODYSSEY_DATA'!B:AR,4,FALSE) -> Ensemble de remorquage | D28: =B28 -> 25ODY-TOWA1 ou 25ODY-TOWB1 | E28: =VLOOKUP(B28,'[1]26MY_ODYSSEY_DATA'!B:AR,9,FALSE) -> 784.8 | F28: =VLOOKUP(B28,'[1]26MY_ODYSSEY_DATA'!B:AR,10,FALSE) -> 1296 | G28: =VLOOKUP(B28,'[1]26MY_ODYSSEY_DATA'!B:AR,7,FALSE) -> 2.3 | H28: =VLOOKUP(B28,'[1]26MY_ODYSSEY_DATA'!B:AR,11,FALSE) -> 1682.4 | I28: =VLOOKUP(B28,'[1]26MY_ODYSSEY_DATA'!B:AR,12,FALSE) -> 0 | J28: =VLOOKUP(B28,'[1]26MY_ODYSSEY_DATA'!B:AR,13,FALSE) -> • | K28: =VLOOKUP(B28,'[1]26MY_ODYSSEY_DATA'!B:AR,14,FALSE) -> • | L28: =VLOOKUP(B28,'[1]26MY_ODYSSEY_DATA'!B:AR,15,FALSE) -> N/A | M28: =VLOOKUP(B28,'[1]26MY_ODYSSEY_DATA'!B:AR,16,FALSE) -> N/A | N28: =VLOOKUP($B28,'[1]26MY_ODYSSEY_DATA'!$B:$AR,17,FALSE) -> 0 | O28: =VLOOKUP($B28,'[1]26MY_ODYSSEY_DATA'!$B:$AR,18,FALSE) -> 0 | P28: =VLOOKUP($B28,'[1]26MY_ODYSSEY_DATA'!$B:$AR,19,FALSE) -> 0 | Q28: =IF(VLOOKUP(B28,'[1]26MY_ODYSSEY_DATA'!B:AR,21,FALSE)="","",VLOOKUP(B28,'[1]26MY_ODYSSEY_DATA'!B:AR,21,FALSE)) -> Rabais de 10 % est appliqué. Attelage de remorque: Classe II. Attelage de remorque dimensions du réceptacle: 2 po x 2 po. Capacité de remorquage: 1,360 kg / 3,000 lbs.
B29: 08L92-THR-300A | C29: =VLOOKUP(B29,'[1]26MY_ODYSSEY_DATA'!B:AR,4,FALSE) -> Attelage de remorque | D29: =B29 -> 08L92-THR-300A
B30: 08L92-SCV-300A ou 08L92-SCV-100B | C30: =VLOOKUP(B30,'[1]26MY_ODYSSEY_DATA'!B:AR,4,FALSE) -> Rotule d'attelage de 1 7/8 po ou 2 po | D30: =B30 -> 08L92-SCV-300A ou 08L92-SCV-100B
B31: 08L91-THR-300 | C31: =VLOOKUP(B31,'[1]26MY_ODYSSEY_DATA'!B:AR,4,FALSE) -> Harnais pour remorque | D31: =B31 -> 08L91-THR-300
B32: 08L92-SJC-300A | C32: =VLOOKUP(B32,'[1]26MY_ODYSSEY_DATA'!B:AR,4,FALSE) -> Goupille de verrouillage pour l'attelage de remorque | D32: =B32 -> 08L92-SJC-300A
B34: 25ODY-TOW-A2 ou 25ODY-TOW-B2 | C34: =VLOOKUP(B34,'[1]26MY_ODYSSEY_DATA'!B:AR,4,FALSE) -> Ensemble de remorquage | D34: =B34 -> 25ODY-TOW-A2 ou 25ODY-TOW-B2 | E34: =VLOOKUP(B34,'[1]26MY_ODYSSEY_DATA'!B:AR,9,FALSE) -> 999 | F34: =VLOOKUP(B34,'[1]26MY_ODYSSEY_DATA'!B:AR,10,FALSE) -> 1653.3 | G34: =VLOOKUP(B34,'[1]26MY_ODYSSEY_DATA'!B:AR,7,FALSE) -> 2.5 | H34: =VLOOKUP(B34,'[1]26MY_ODYSSEY_DATA'!B:AR,11,FALSE) -> 2073.3 | I34: =VLOOKUP(B34,'[1]26MY_ODYSSEY_DATA'!B:AR,12,FALSE) -> 0 | J34: =VLOOKUP(B34,'[1]26MY_ODYSSEY_DATA'!B:AR,13,FALSE) -> N/A | K34: =VLOOKUP(B34,'[1]26MY_ODYSSEY_DATA'!B:AR,14,FALSE) -> N/A | L34: =VLOOKUP(B34,'[1]26MY_ODYSSEY_DATA'!B:AR,15,FALSE) -> • | M34: =VLOOKUP(B34,'[1]26MY_ODYSSEY_DATA'!B:AR,16,FALSE) -> • | N34: =VLOOKUP($B34,'[1]26MY_ODYSSEY_DATA'!$B:$AR,17,FALSE) -> 0 | O34: =VLOOKUP($B34,'[1]26MY_ODYSSEY_DATA'!$B:$AR,18,FALSE) -> 0 | P34: =VLOOKUP($B34,'[1]26MY_ODYSSEY_DATA'!$B:$AR,19,FALSE) -> 0 | Q34: =IF(VLOOKUP(B34,'[1]26MY_ODYSSEY_DATA'!B:AR,21,FALSE)="","",VLOOKUP(B34,'[1]26MY_ODYSSEY_DATA'!B:AR,21,FALSE)) -> Rabais de 10 % est appliqué. Black Edition :Nécessite adaptateur de capteur de hayon électrique mains libres puisque le système mains libres est de série. Attelage de remorque: Classe II. Attelage de remorque dimensions du réceptacle: 2 po x 2 po. Capacité de remorquage: 1,360 kg / 3,000 lbs.
B35: 08L92-THR-300A | C35: =VLOOKUP(B35,'[1]26MY_ODYSSEY_DATA'!B:AR,4,FALSE) -> Attelage de remorque | D35: =B35 -> 08L92-THR-300A
B36: 08L91-THR-300A | C36: =VLOOKUP(B36,'[1]26MY_ODYSSEY_DATA'!B:AR,4,FALSE) -> Adaptateur de capteur de hayon électrique mains libres | D36: =B36 -> 08L91-THR-300A
B37: 08L92-SCV-300A ou 08L92-SCV-100B | C37: =VLOOKUP(B37,'[1]26MY_ODYSSEY_DATA'!B:AR,4,FALSE) -> Rotule d'attelage de 1 7/8 po ou 2 po | D37: =B37 -> 08L92-SCV-300A ou 08L92-SCV-100B
B38: 08L91-THR-300 | C38: =VLOOKUP(B38,'[1]26MY_ODYSSEY_DATA'!B:AR,4,FALSE) -> Harnais pour remorque | D38: =B38 -> 08L91-THR-300
B39: 08L92-SJC-300A | C39: =VLOOKUP(B39,'[1]26MY_ODYSSEY_DATA'!B:AR,4,FALSE) -> Goupille de verrouillage pour l'attelage de remorque | D39: =B39 -> 08L92-SJC-300A
C41: 2.0 Jantes et accessoires de jantes
C42: La description | D42: Numéro de pièce | E42: Prix net | F42: Prix de liste | G42: T.F.F. | H42: Prix installé | I42: Application | Q42: Commentaires
I43: ='[1]26MY_ODYSSEY_DATA'!M$6 -> 0 | J43: ='[1]26MY_ODYSSEY_DATA'!N$6 -> Sport | K43: ='[1]26MY_ODYSSEY_DATA'!O$6 -> Sport-L | L43: ='[1]26MY_ODYSSEY_DATA'!P$6 -> Touring | M43: ='[1]26MY_ODYSSEY_DATA'!Q$6 -> Black Edition | N43: ='[1]26MY_ODYSSEY_DATA'!R$6 -> 0 | O43: ='[1]26MY_ODYSSEY_DATA'!S$6 -> 0 | P43: ='[1]26MY_ODYSSEY_DATA'!T$6 -> 0
B44: 08W42-TG7-301A | C44: =VLOOKUP(B44,'[1]26MY_ODYSSEY_DATA'!B:AR,4,FALSE) -> Écrous de roue antivol - Noirs | D44: =B44 -> 08W42-TG7-301A | E44: =VLOOKUP(B44,'[1]26MY_ODYSSEY_DATA'!B:AR,9,FALSE) -> 85 | F44: =VLOOKUP(B44,'[1]26MY_ODYSSEY_DATA'!B:AR,10,FALSE) -> 140 | G44: =VLOOKUP(B44,'[1]26MY_ODYSSEY_DATA'!B:AR,7,FALSE) -> 0.2 | H44: =VLOOKUP(B44,'[1]26MY_ODYSSEY_DATA'!B:AR,11,FALSE) -> 173.6 | I44: =VLOOKUP(B44,'[1]26MY_ODYSSEY_DATA'!B:AR,12,FALSE) -> 0 | J44: =VLOOKUP(B44,'[1]26MY_ODYSSEY_DATA'!B:AR,13,FALSE) -> • | K44: =VLOOKUP(B44,'[1]26MY_ODYSSEY_DATA'!B:AR,14,FALSE) -> • | L44: =VLOOKUP(B44,'[1]26MY_ODYSSEY_DATA'!B:AR,15,FALSE) -> • | M44: =VLOOKUP(B44,'[1]26MY_ODYSSEY_DATA'!B:AR,16,FALSE) -> • | N44: =VLOOKUP($B44,'[1]26MY_ODYSSEY_DATA'!$B:$AR,17,FALSE) -> 0 | O44: =VLOOKUP($B44,'[1]26MY_ODYSSEY_DATA'!$B:$AR,18,FALSE) -> 0 | P44: =VLOOKUP($B44,'[1]26MY_ODYSSEY_DATA'!$B:$AR,19,FALSE) -> 0 | Q44: =IF(VLOOKUP(B44,'[1]26MY_ODYSSEY_DATA'!B:AR,21,FALSE)="","",VLOOKUP(B44,'[1]26MY_ODYSSEY_DATA'!B:AR,21,FALSE))
B45: 08W42-TK4-301 | C45: =VLOOKUP(B45,'[1]26MY_ODYSSEY_DATA'!B:AR,4,FALSE) -> Écrous de roue antivol - Chromés | D45: =B45 -> 08W42-TK4-301 | E45: =VLOOKUP(B45,'[1]26MY_ODYSSEY_DATA'!B:AR,9,FALSE) -> 91 | F45: =VLOOKUP(B45,'[1]26MY_ODYSSEY_DATA'!B:AR,10,FALSE) -> 152 | G45: =VLOOKUP(B45,'[1]26MY_ODYSSEY_DATA'!B:AR,7,FALSE) -> 0.2 | H45: =VLOOKUP(B45,'[1]26MY_ODYSSEY_DATA'!B:AR,11,FALSE) -> 185.6 | I45: =VLOOKUP(B45,'[1]26MY_ODYSSEY_DATA'!B:AR,12,FALSE) -> 0 | J45: =VLOOKUP(B45,'[1]26MY_ODYSSEY_DATA'!B:AR,13,FALSE) -> • | K45: =VLOOKUP(B45,'[1]26MY_ODYSSEY_DATA'!B:AR,14,FALSE) -> • | L45: =VLOOKUP(B45,'[1]26MY_ODYSSEY_DATA'!B:AR,15,FALSE) -> • | M45: =VLOOKUP(B45,'[1]26MY_ODYSSEY_DATA'!B:AR,16,FALSE) -> • | N45: =VLOOKUP($B45,'[1]26MY_ODYSSEY_DATA'!$B:$AR,17,FALSE) -> 0 | O45: =VLOOKUP($B45,'[1]26MY_ODYSSEY_DATA'!$B:$AR,18,FALSE) -> 0 | P45: =VLOOKUP($B45,'[1]26MY_ODYSSEY_DATA'!$B:$AR,19,FALSE) -> 0 | Q45: =IF(VLOOKUP(B45,'[1]26MY_ODYSSEY_DATA'!B:AR,21,FALSE)="","",VLOOKUP(B45,'[1]26MY_ODYSSEY_DATA'!B:AR,21,FALSE))
C47: 3.0 Extérieur
C48: La description | D48: Numéro de pièce | E48: Prix net | F48: Prix de liste | G48: T.F.F. | H48: Prix installé | I48: Application | Q48: Commentaires
I49: ='[1]26MY_ODYSSEY_DATA'!M$6 -> 0 | J49: ='[1]26MY_ODYSSEY_DATA'!N$6 -> Sport | K49: ='[1]26MY_ODYSSEY_DATA'!O$6 -> Sport-L | L49: ='[1]26MY_ODYSSEY_DATA'!P$6 -> Touring | M49: ='[1]26MY_ODYSSEY_DATA'!Q$6 -> Black Edition | N49: ='[1]26MY_ODYSSEY_DATA'!R$6 -> 0 | O49: ='[1]26MY_ODYSSEY_DATA'!S$6 -> 0 | P49: ='[1]26MY_ODYSSEY_DATA'!T$6 -> 0
B50: 08F20-THR-100 | C50: =VLOOKUP(B50,'[1]26MY_ODYSSEY_DATA'!B:AR,4,FALSE) -> Emblèmes noir - Logo « H » et Oydssey | D50: =B50 -> 08F20-THR-100 | E50: =VLOOKUP(B50,'[1]26MY_ODYSSEY_DATA'!B:AR,9,FALSE) -> 69 | F50: =VLOOKUP(B50,'[1]26MY_ODYSSEY_DATA'!B:AR,10,FALSE) -> 115 | G50: =VLOOKUP(B50,'[1]26MY_ODYSSEY_DATA'!B:AR,7,FALSE) -> 0.9 | H50: =VLOOKUP(B50,'[1]26MY_ODYSSEY_DATA'!B:AR,11,FALSE) -> 266.2 | I50: =VLOOKUP(B50,'[1]26MY_ODYSSEY_DATA'!B:AR,12,FALSE) -> 0 | J50: =VLOOKUP(B50,'[1]26MY_ODYSSEY_DATA'!B:AR,13,FALSE) -> • | K50: =VLOOKUP(B50,'[1]26MY_ODYSSEY_DATA'!B:AR,14,FALSE) -> • | L50: =VLOOKUP(B50,'[1]26MY_ODYSSEY_DATA'!B:AR,15,FALSE) -> • | M50: =VLOOKUP(B50,'[1]26MY_ODYSSEY_DATA'!B:AR,16,FALSE) -> • | N50: =VLOOKUP($B50,'[1]26MY_ODYSSEY_DATA'!$B:$AR,17,FALSE) -> 0 | O50: =VLOOKUP($B50,'[1]26MY_ODYSSEY_DATA'!$B:$AR,18,FALSE) -> 0 | P50: =VLOOKUP($B50,'[1]26MY_ODYSSEY_DATA'!$B:$AR,19,FALSE) -> 0 | Q50: =IF(VLOOKUP(B50,'[1]26MY_ODYSSEY_DATA'!B:AR,21,FALSE)="","",VLOOKUP(B50,'[1]26MY_ODYSSEY_DATA'!B:AR,21,FALSE))
B51: 08F20-T7S-100C | C51: =VLOOKUP(B51,'[1]26MY_ODYSSEY_DATA'!B:AR,4,FALSE) -> Emblème noir - SPORT | D51: =B51 -> 08F20-T7S-100C | E51: =VLOOKUP(B51,'[1]26MY_ODYSSEY_DATA'!B:AR,9,FALSE) -> 41 | F51: =VLOOKUP(B51,'[1]26MY_ODYSSEY_DATA'!B:AR,10,FALSE) -> 68 | G51: =VLOOKUP(B51,'[1]26MY_ODYSSEY_DATA'!B:AR,7,FALSE) -> 0.3 | H51: =VLOOKUP(B51,'[1]26MY_ODYSSEY_DATA'!B:AR,11,FALSE) -> 118.4 | I51: =VLOOKUP(B51,'[1]26MY_ODYSSEY_DATA'!B:AR,12,FALSE) -> 0 | J51: =VLOOKUP(B51,'[1]26MY_ODYSSEY_DATA'!B:AR,13,FALSE) -> • | K51: =VLOOKUP(B51,'[1]26MY_ODYSSEY_DATA'!B:AR,14,FALSE) -> • | L51: =VLOOKUP(B51,'[1]26MY_ODYSSEY_DATA'!B:AR,15,FALSE) -> N/A | M51: =VLOOKUP(B51,'[1]26MY_ODYSSEY_DATA'!B:AR,16,FALSE) -> N/A | N51: =VLOOKUP($B51,'[1]26MY_ODYSSEY_DATA'!$B:$AR,17,FALSE) -> 0 | O51: =VLOOKUP($B51,'[1]26MY_ODYSSEY_DATA'!$B:$AR,18,FALSE) -> 0 | P51: =VLOOKUP($B51,'[1]26MY_ODYSSEY_DATA'!$B:$AR,19,FALSE) -> 0 | Q51: =IF(VLOOKUP(B51,'[1]26MY_ODYSSEY_DATA'!B:AR,21,FALSE)="","",VLOOKUP(B51,'[1]26MY_ODYSSEY_DATA'!B:AR,21,FALSE))
B52: 08F20-TG7-100G | C52: =VLOOKUP(B52,'[1]26MY_ODYSSEY_DATA'!B:AR,4,FALSE) -> Emblème noir - Black Edition | D52: =B52 -> 08F20-TG7-100G | E52: =VLOOKUP(B52,'[1]26MY_ODYSSEY_DATA'!B:AR,9,FALSE) -> 70 | F52: =VLOOKUP(B52,'[1]26MY_ODYSSEY_DATA'!B:AR,10,FALSE) -> 117 | G52: =VLOOKUP(B52,'[1]26MY_ODYSSEY_DATA'!B:AR,7,FALSE) -> 0.3 | H52: =VLOOKUP(B52,'[1]26MY_ODYSSEY_DATA'!B:AR,11,FALSE) -> 167.4 | I52: =VLOOKUP(B52,'[1]26MY_ODYSSEY_DATA'!B:AR,12,FALSE) -> 0 | J52: =VLOOKUP(B52,'[1]26MY_ODYSSEY_DATA'!B:AR,13,FALSE) -> N/A | K52: =VLOOKUP(B52,'[1]26MY_ODYSSEY_DATA'!B:AR,14,FALSE) -> N/A | L52: =VLOOKUP(B52,'[1]26MY_ODYSSEY_DATA'!B:AR,15,FALSE) -> N/A | M52: =VLOOKUP(B52,'[1]26MY_ODYSSEY_DATA'!B:AR,16,FALSE) -> • | N52: =VLOOKUP($B52,'[1]26MY_ODYSSEY_DATA'!$B:$AR,17,FALSE) -> 0 | O52: =VLOOKUP($B52,'[1]26MY_ODYSSEY_DATA'!$B:$AR,18,FALSE) -> 0 | P52: =VLOOKUP($B52,'[1]26MY_ODYSSEY_DATA'!$B:$AR,19,FALSE) -> 0 | Q52: =IF(VLOOKUP(B52,'[1]26MY_ODYSSEY_DATA'!B:AR,21,FALSE)="","",VLOOKUP(B52,'[1]26MY_ODYSSEY_DATA'!B:AR,21,FALSE))
B53: 08F59-THR-100A | C53: =VLOOKUP(B53,'[1]26MY_ODYSSEY_DATA'!B:AR,4,FALSE) -> Écussons d’ailes | D53: =B53 -> 08F59-THR-100A | E53: =VLOOKUP(B53,'[1]26MY_ODYSSEY_DATA'!B:AR,9,FALSE) -> 138 | F53: =VLOOKUP(B53,'[1]26MY_ODYSSEY_DATA'!B:AR,10,FALSE) -> 197 | G53: =VLOOKUP(B53,'[1]26MY_ODYSSEY_DATA'!B:AR,7,FALSE) -> 0.2 | H53: =VLOOKUP(B53,'[1]26MY_ODYSSEY_DATA'!B:AR,11,FALSE) -> 230.6 | I53: =VLOOKUP(B53,'[1]26MY_ODYSSEY_DATA'!B:AR,12,FALSE) -> 0 | J53: =VLOOKUP(B53,'[1]26MY_ODYSSEY_DATA'!B:AR,13,FALSE) -> • | K53: =VLOOKUP(B53,'[1]26MY_ODYSSEY_DATA'!B:AR,14,FALSE) -> • | L53: =VLOOKUP(B53,'[1]26MY_ODYSSEY_DATA'!B:AR,15,FALSE) -> • | M53: =VLOOKUP(B53,'[1]26MY_ODYSSEY_DATA'!B:AR,16,FALSE) -> • | N53: =VLOOKUP($B53,'[1]26MY_ODYSSEY_DATA'!$B:$AR,17,FALSE) -> 0 | O53: =VLOOKUP($B53,'[1]26MY_ODYSSEY_DATA'!$B:$AR,18,FALSE) -> 0 | P53: =VLOOKUP($B53,'[1]26MY_ODYSSEY_DATA'!$B:$AR,19,FALSE) -> 0 | Q53: =IF(VLOOKUP(B53,'[1]26MY_ODYSSEY_DATA'!B:AR,21,FALSE)="","",VLOOKUP(B53,'[1]26MY_ODYSSEY_DATA'!B:AR,21,FALSE))
B54: 08F57-THR-101 | C54: =VLOOKUP(B54,'[1]26MY_ODYSSEY_DATA'!B:AR,4,FALSE) -> Garnitures de portière - chromées | D54: =B54 -> 08F57-THR-101 | E54: =VLOOKUP(B54,'[1]26MY_ODYSSEY_DATA'!B:AR,9,FALSE) -> 9.99 | F54: =VLOOKUP(B54,'[1]26MY_ODYSSEY_DATA'!B:AR,10,FALSE) -> 16.99 | G54: =VLOOKUP(B54,'[1]26MY_ODYSSEY_DATA'!B:AR,7,FALSE) -> 0.4 | H54: =VLOOKUP(B54,'[1]26MY_ODYSSEY_DATA'!B:AR,11,FALSE) -> 84.19 | I54: =VLOOKUP(B54,'[1]26MY_ODYSSEY_DATA'!B:AR,12,FALSE) -> 0 | J54: =VLOOKUP(B54,'[1]26MY_ODYSSEY_DATA'!B:AR,13,FALSE) -> • | K54: =VLOOKUP(B54,'[1]26MY_ODYSSEY_DATA'!B:AR,14,FALSE) -> • | L54: =VLOOKUP(B54,'[1]26MY_ODYSSEY_DATA'!B:AR,15,FALSE) -> • | M54: =VLOOKUP(B54,'[1]26MY_ODYSSEY_DATA'!B:AR,16,FALSE) -> • | N54: =VLOOKUP($B54,'[1]26MY_ODYSSEY_DATA'!$B:$AR,17,FALSE) -> 0 | O54: =VLOOKUP($B54,'[1]26MY_ODYSSEY_DATA'!$B:$AR,18,FALSE) -> 0 | P54: =VLOOKUP($B54,'[1]26MY_ODYSSEY_DATA'!$B:$AR,19,FALSE) -> 0 | Q54: =IF(VLOOKUP(B54,'[1]26MY_ODYSSEY_DATA'!B:AR,21,FALSE)="","",VLOOKUP(B54,'[1]26MY_ODYSSEY_DATA'!B:AR,21,FALSE))
B55: 08P01-THR-100 | C55: =VLOOKUP(B55,'[1]26MY_ODYSSEY_DATA'!B:AR,4,FALSE) -> Protecteur de pare-chocs arrière | D55: =B55 -> 08P01-THR-100 | E55: =VLOOKUP(B55,'[1]26MY_ODYSSEY_DATA'!B:AR,9,FALSE) -> 22.99 | F55: =VLOOKUP(B55,'[1]26MY_ODYSSEY_DATA'!B:AR,10,FALSE) -> 37.99 | G55: =VLOOKUP(B55,'[1]26MY_ODYSSEY_DATA'!B:AR,7,FALSE) -> 0.8 | H55: =VLOOKUP(B55,'[1]26MY_ODYSSEY_DATA'!B:AR,11,FALSE) -> 172.39 | I55: =VLOOKUP(B55,'[1]26MY_ODYSSEY_DATA'!B:AR,12,FALSE) -> 0 | J55: =VLOOKUP(B55,'[1]26MY_ODYSSEY_DATA'!B:AR,13,FALSE) -> • | K55: =VLOOKUP(B55,'[1]26MY_ODYSSEY_DATA'!B:AR,14,FALSE) -> • | L55: =VLOOKUP(B55,'[1]26MY_ODYSSEY_DATA'!B:AR,15,FALSE) -> • | M55: =VLOOKUP(B55,'[1]26MY_ODYSSEY_DATA'!B:AR,16,FALSE) -> • | N55: =VLOOKUP($B55,'[1]26MY_ODYSSEY_DATA'!$B:$AR,17,FALSE) -> 0 | O55: =VLOOKUP($B55,'[1]26MY_ODYSSEY_DATA'!$B:$AR,18,FALSE) -> 0 | P55: =VLOOKUP($B55,'[1]26MY_ODYSSEY_DATA'!$B:$AR,19,FALSE) -> 0 | Q55: =IF(VLOOKUP(B55,'[1]26MY_ODYSSEY_DATA'!B:AR,21,FALSE)="","",VLOOKUP(B55,'[1]26MY_ODYSSEY_DATA'!B:AR,21,FALSE))
B56: 08P20-THR-100 | C56: =VLOOKUP(B56,'[1]26MY_ODYSSEY_DATA'!B:AR,4,FALSE) -> Pellicule pour rebord de portière | D56: =B56 -> 08P20-THR-100 | E56: =VLOOKUP(B56,'[1]26MY_ODYSSEY_DATA'!B:AR,9,FALSE) -> 5.99 | F56: =VLOOKUP(B56,'[1]26MY_ODYSSEY_DATA'!B:AR,10,FALSE) -> 9.99 | G56: =VLOOKUP(B56,'[1]26MY_ODYSSEY_DATA'!B:AR,7,FALSE) -> 0.2 | H56: =VLOOKUP(B56,'[1]26MY_ODYSSEY_DATA'!B:AR,11,FALSE) -> 43.59 | I56: =VLOOKUP(B56,'[1]26MY_ODYSSEY_DATA'!B:AR,12,FALSE) -> 0 | J56: =VLOOKUP(B56,'[1]26MY_ODYSSEY_DATA'!B:AR,13,FALSE) -> • | K56: =VLOOKUP(B56,'[1]26MY_ODYSSEY_DATA'!B:AR,14,FALSE) -> • | L56: =VLOOKUP(B56,'[1]26MY_ODYSSEY_DATA'!B:AR,15,FALSE) -> • | M56: =VLOOKUP(B56,'[1]26MY_ODYSSEY_DATA'!B:AR,16,FALSE) -> • | N56: =VLOOKUP($B56,'[1]26MY_ODYSSEY_DATA'!$B:$AR,17,FALSE) -> 0 | O56: =VLOOKUP($B56,'[1]26MY_ODYSSEY_DATA'!$B:$AR,18,FALSE) -> 0 | P56: =VLOOKUP($B56,'[1]26MY_ODYSSEY_DATA'!$B:$AR,19,FALSE) -> 0 | Q56: =IF(VLOOKUP(B56,'[1]26MY_ODYSSEY_DATA'!B:AR,21,FALSE)="","",VLOOKUP(B56,'[1]26MY_ODYSSEY_DATA'!B:AR,21,FALSE)) -> Ne peut être installé simultanément avec pellicule pour rebord de portière
B57: 08R04-THR-102 | C57: =VLOOKUP(B57,'[1]26MY_ODYSSEY_DATA'!B:AR,4,FALSE) -> Pare-soleil de portière | D57: =B57 -> 08R04-THR-102 | E57: =VLOOKUP(B57,'[1]26MY_ODYSSEY_DATA'!B:AR,9,FALSE) -> 234 | F57: =VLOOKUP(B57,'[1]26MY_ODYSSEY_DATA'!B:AR,10,FALSE) -> 390 | G57: =VLOOKUP(B57,'[1]26MY_ODYSSEY_DATA'!B:AR,7,FALSE) -> 0.5 | H57: =VLOOKUP(B57,'[1]26MY_ODYSSEY_DATA'!B:AR,11,FALSE) -> 474 | I57: =VLOOKUP(B57,'[1]26MY_ODYSSEY_DATA'!B:AR,12,FALSE) -> 0 | J57: =VLOOKUP(B57,'[1]26MY_ODYSSEY_DATA'!B:AR,13,FALSE) -> • | K57: =VLOOKUP(B57,'[1]26MY_ODYSSEY_DATA'!B:AR,14,FALSE) -> • | L57: =VLOOKUP(B57,'[1]26MY_ODYSSEY_DATA'!B:AR,15,FALSE) -> • | M57: =VLOOKUP(B57,'[1]26MY_ODYSSEY_DATA'!B:AR,16,FALSE) -> • | N57: =VLOOKUP($B57,'[1]26MY_ODYSSEY_DATA'!$B:$AR,17,FALSE) -> 0 | O57: =VLOOKUP($B57,'[1]26MY_ODYSSEY_DATA'!$B:$AR,18,FALSE) -> 0 | P57: =VLOOKUP($B57,'[1]26MY_ODYSSEY_DATA'!$B:$AR,19,FALSE) -> 0 | Q57: =IF(VLOOKUP(B57,'[1]26MY_ODYSSEY_DATA'!B:AR,21,FALSE)="","",VLOOKUP(B57,'[1]26MY_ODYSSEY_DATA'!B:AR,21,FALSE))
B58: 08P47-THR-301 | C58: =VLOOKUP(B58,'[1]26MY_ODYSSEY_DATA'!B:AR,4,FALSE) -> Déflecteur d’air du capot | D58: =B58 -> 08P47-THR-301 | E58: =VLOOKUP(B58,'[1]26MY_ODYSSEY_DATA'!B:AR,9,FALSE) -> 204 | F58: =VLOOKUP(B58,'[1]26MY_ODYSSEY_DATA'!B:AR,10,FALSE) -> 340 | G58: =VLOOKUP(B58,'[1]26MY_ODYSSEY_DATA'!B:AR,7,FALSE) -> 0.5 | H58: =VLOOKUP(B58,'[1]26MY_ODYSSEY_DATA'!B:AR,11,FALSE) -> 424 | I58: =VLOOKUP(B58,'[1]26MY_ODYSSEY_DATA'!B:AR,12,FALSE) -> 0 | J58: =VLOOKUP(B58,'[1]26MY_ODYSSEY_DATA'!B:AR,13,FALSE) -> • | K58: =VLOOKUP(B58,'[1]26MY_ODYSSEY_DATA'!B:AR,14,FALSE) -> • | L58: =VLOOKUP(B58,'[1]26MY_ODYSSEY_DATA'!B:AR,15,FALSE) -> • | M58: =VLOOKUP(B58,'[1]26MY_ODYSSEY_DATA'!B:AR,16,FALSE) -> • | N58: =VLOOKUP($B58,'[1]26MY_ODYSSEY_DATA'!$B:$AR,17,FALSE) -> 0 | O58: =VLOOKUP($B58,'[1]26MY_ODYSSEY_DATA'!$B:$AR,18,FALSE) -> 0 | P58: =VLOOKUP($B58,'[1]26MY_ODYSSEY_DATA'!$B:$AR,19,FALSE) -> 0 | Q58: =IF(VLOOKUP(B58,'[1]26MY_ODYSSEY_DATA'!B:AR,21,FALSE)="","",VLOOKUP(B58,'[1]26MY_ODYSSEY_DATA'!B:AR,21,FALSE))
B59: 08R01-THR-301 | C59: =VLOOKUP(B59,'[1]26MY_ODYSSEY_DATA'!B:AR,4,FALSE) -> Pare-soleil de toit ouvrant | D59: =B59 -> 08R01-THR-301 | E59: =VLOOKUP(B59,'[1]26MY_ODYSSEY_DATA'!B:AR,9,FALSE) -> 171 | F59: =VLOOKUP(B59,'[1]26MY_ODYSSEY_DATA'!B:AR,10,FALSE) -> 285 | G59: =VLOOKUP(B59,'[1]26MY_ODYSSEY_DATA'!B:AR,7,FALSE) -> 0.3 | H59: =VLOOKUP(B59,'[1]26MY_ODYSSEY_DATA'!B:AR,11,FALSE) -> 335.4 | I59: =VLOOKUP(B59,'[1]26MY_ODYSSEY_DATA'!B:AR,12,FALSE) -> 0 | J59: =VLOOKUP(B59,'[1]26MY_ODYSSEY_DATA'!B:AR,13,FALSE) -> • | K59: =VLOOKUP(B59,'[1]26MY_ODYSSEY_DATA'!B:AR,14,FALSE) -> • | L59: =VLOOKUP(B59,'[1]26MY_ODYSSEY_DATA'!B:AR,15,FALSE) -> • | M59: =VLOOKUP(B59,'[1]26MY_ODYSSEY_DATA'!B:AR,16,FALSE) -> • | N59: =VLOOKUP($B59,'[1]26MY_ODYSSEY_DATA'!$B:$AR,17,FALSE) -> 0 | O59: =VLOOKUP($B59,'[1]26MY_ODYSSEY_DATA'!$B:$AR,18,FALSE) -> 0 | P59: =VLOOKUP($B59,'[1]26MY_ODYSSEY_DATA'!$B:$AR,19,FALSE) -> 0 | Q59: =IF(VLOOKUP(B59,'[1]26MY_ODYSSEY_DATA'!B:AR,21,FALSE)="","",VLOOKUP(B59,'[1]26MY_ODYSSEY_DATA'!B:AR,21,FALSE))
B60: 08P09-THR-300A | C60: =VLOOKUP(B60,'[1]26MY_ODYSSEY_DATA'!B:AR,4,FALSE) -> Garde-boue arrière | D60: =B60 -> 08P09-THR-300A | E60: =VLOOKUP(B60,'[1]26MY_ODYSSEY_DATA'!B:AR,9,FALSE) -> 82 | F60: =VLOOKUP(B60,'[1]26MY_ODYSSEY_DATA'!B:AR,10,FALSE) -> 137 | G60: =VLOOKUP(B60,'[1]26MY_ODYSSEY_DATA'!B:AR,7,FALSE) -> 0.4 | H60: =VLOOKUP(B60,'[1]26MY_ODYSSEY_DATA'!B:AR,11,FALSE) -> 204.2 | I60: =VLOOKUP(B60,'[1]26MY_ODYSSEY_DATA'!B:AR,12,FALSE) -> 0 | J60: =VLOOKUP(B60,'[1]26MY_ODYSSEY_DATA'!B:AR,13,FALSE) -> • | K60: =VLOOKUP(B60,'[1]26MY_ODYSSEY_DATA'!B:AR,14,FALSE) -> • | L60: =VLOOKUP(B60,'[1]26MY_ODYSSEY_DATA'!B:AR,15,FALSE) -> • | M60: =VLOOKUP(B60,'[1]26MY_ODYSSEY_DATA'!B:AR,16,FALSE) -> • | N60: =VLOOKUP($B60,'[1]26MY_ODYSSEY_DATA'!$B:$AR,17,FALSE) -> 0 | O60: =VLOOKUP($B60,'[1]26MY_ODYSSEY_DATA'!$B:$AR,18,FALSE) -> 0 | P60: =VLOOKUP($B60,'[1]26MY_ODYSSEY_DATA'!$B:$AR,19,FALSE) -> 0 | Q60: =IF(VLOOKUP(B60,'[1]26MY_ODYSSEY_DATA'!B:AR,21,FALSE)="","",VLOOKUP(B60,'[1]26MY_ODYSSEY_DATA'!B:AR,21,FALSE))
B61: 08Z04-SCV-110B | C61: =VLOOKUP(B61,'[1]26MY_ODYSSEY_DATA'!B:AR,4,FALSE) -> Tente | D61: =B61 -> 08Z04-SCV-110B | E61: =VLOOKUP(B61,'[1]26MY_ODYSSEY_DATA'!B:AR,9,FALSE) -> 477 | F61: =VLOOKUP(B61,'[1]26MY_ODYSSEY_DATA'!B:AR,10,FALSE) -> 681 | G61: =VLOOKUP(B61,'[1]26MY_ODYSSEY_DATA'!B:AR,7,FALSE) -> 0 | H61: =VLOOKUP(B61,'[1]26MY_ODYSSEY_DATA'!B:AR,11,FALSE) -> 681 | I61: =VLOOKUP(B61,'[1]26MY_ODYSSEY_DATA'!B:AR,12,FALSE) -> 0 | J61: =VLOOKUP(B61,'[1]26MY_ODYSSEY_DATA'!B:AR,13,FALSE) -> • | K61: =VLOOKUP(B61,'[1]26MY_ODYSSEY_DATA'!B:AR,14,FALSE) -> • | L61: =VLOOKUP(B61,'[1]26MY_ODYSSEY_DATA'!B:AR,15,FALSE) -> • | M61: =VLOOKUP(B61,'[1]26MY_ODYSSEY_DATA'!B:AR,16,FALSE) -> • | N61: =VLOOKUP($B61,'[1]26MY_ODYSSEY_DATA'!$B:$AR,17,FALSE) -> 0 | O61: =VLOOKUP($B61,'[1]26MY_ODYSSEY_DATA'!$B:$AR,18,FALSE) -> 0 | P61: =VLOOKUP($B61,'[1]26MY_ODYSSEY_DATA'!$B:$AR,19,FALSE) -> 0 | Q61: =IF(VLOOKUP(B61,'[1]26MY_ODYSSEY_DATA'!B:AR,21,FALSE)="","",VLOOKUP(B61,'[1]26MY_ODYSSEY_DATA'!B:AR,21,FALSE))
... B64: 08L04-THR-100 | C64: =VLOOKUP(B64,'[1]26MY_ODYSSEY_DATA'!B:AR,4,FALSE) -> Barres transversales | D64: =B64 -> 08L04-THR-100 | E64: =VLOOKUP(B64,'[1]26MY_ODYSSEY_DATA'!B:AR,9,FALSE) -> 216 | F64: =VLOOKUP(B64,'[1]26MY_ODYSSEY_DATA'!B:AR,10,FALSE) -> 360 | G64: =VLOOKUP(B64,'[1]26MY_ODYSSEY_DATA'!B:AR,7,FALSE) -> 0.2 | H64: =VLOOKUP(B64,'[1]26MY_ODYSSEY_DATA'!B:AR,11,FALSE) -> 393.6 | I64: =VLOOKUP(B64,'[1]26MY_ODYSSEY_DATA'!B:AR,12,FALSE) -> 0 | J64: =VLOOKUP(B64,'[1]26MY_ODYSSEY_DATA'!B:AR,13,FALSE) -> • | K64: =VLOOKUP(B64,'[1]26MY_ODYSSEY_DATA'!B:AR,14,FALSE) -> • | L64: =VLOOKUP(B64,'[1]26MY_ODYSSEY_DATA'!B:AR,15,FALSE) -> • | M64: =VLOOKUP(B64,'[1]26MY_ODYSSEY_DATA'!B:AR,16,FALSE) -> • | N64: =VLOOKUP($B64,'[1]26MY_ODYSSEY_DATA'!$B:$AR,17,FALSE) -> 0 | O64: =VLOOKUP($B64,'[1]26MY_ODYSSEY_DATA'!$B:$AR,18,FALSE) -> 0 | P64: =VLOOKUP($B64,'[1]26MY_ODYSSEY_DATA'!$B:$AR,19,FALSE) -> 0 | Q64: =IF(VLOOKUP(B64,'[1]26MY_ODYSSEY_DATA'!B:AR,21,FALSE)="","",VLOOKUP(B64,'[1]26MY_ODYSSEY_DATA'!B:AR,21,FALSE)) -> Nécessite des rails de toit.
B65: 08LXX-E09-XXXX | C65: =VLOOKUP(B65,'[1]26MY_ODYSSEY_DATA'!B:AR,4,FALSE) -> Accessoires de toit
B66: 08L20-E09-101C | C66: =VLOOKUP(B66,'[1]26MY_ODYSSEY_DATA'!B:AR,4,FALSE) -> Panier de toit | D66: =B66 -> 08L20-E09-101C | E66: =VLOOKUP(B66,'[1]26MY_ODYSSEY_DATA'!B:AR,9,FALSE) -> 571 | F66: =VLOOKUP(B66,'[1]26MY_ODYSSEY_DATA'!B:AR,10,FALSE) -> 952 | G66: =VLOOKUP(B66,'[1]26MY_ODYSSEY_DATA'!B:AR,7,FALSE) -> 0.4 | H66: =VLOOKUP(B66,'[1]26MY_ODYSSEY_DATA'!B:AR,11,FALSE) -> 1019.2 | I66: =VLOOKUP(B66,'[1]26MY_ODYSSEY_DATA'!B:AR,12,FALSE) -> 0 | J66: =VLOOKUP(B66,'[1]26MY_ODYSSEY_DATA'!B:AR,13,FALSE) -> • | K66: =VLOOKUP(B66,'[1]26MY_ODYSSEY_DATA'!B:AR,14,FALSE) -> • | L66: =VLOOKUP(B66,'[1]26MY_ODYSSEY_DATA'!B:AR,15,FALSE) -> • | M66: =VLOOKUP(B66,'[1]26MY_ODYSSEY_DATA'!B:AR,16,FALSE) -> • | N66: =VLOOKUP($B66,'[1]26MY_ODYSSEY_DATA'!$B:$AR,17,FALSE) -> 0 | O66: =VLOOKUP($B66,'[1]26MY_ODYSSEY_DATA'!$B:$AR,18,FALSE) -> 0 | P66: =VLOOKUP($B66,'[1]26MY_ODYSSEY_DATA'!$B:$AR,19,FALSE) -> 0 | Q66: =IF(VLOOKUP(B66,'[1]26MY_ODYSSEY_DATA'!B:AR,21,FALSE)="","",VLOOKUP(B66,'[1]26MY_ODYSSEY_DATA'!B:AR,21,FALSE)) -> Nécessite des rails de toit et des barres transversales.
B67: 08L07-E09-300A | C67: =VLOOKUP(B67,'[1]26MY_ODYSSEY_DATA'!B:AR,4,FALSE) -> Galerie de toit, Porte-vélo - monture de fourche | D67: =B67 -> 08L07-E09-300A | E67: =VLOOKUP(B67,'[1]26MY_ODYSSEY_DATA'!B:AR,9,FALSE) -> 292 | F67: =VLOOKUP(B67,'[1]26MY_ODYSSEY_DATA'!B:AR,10,FALSE) -> 487 | G67: =VLOOKUP(B67,'[1]26MY_ODYSSEY_DATA'!B:AR,7,FALSE) -> 0.4 | H67: =VLOOKUP(B67,'[1]26MY_ODYSSEY_DATA'!B:AR,11,FALSE) -> 554.2 | I67: =VLOOKUP(B67,'[1]26MY_ODYSSEY_DATA'!B:AR,12,FALSE) -> 0 | J67: =VLOOKUP(B67,'[1]26MY_ODYSSEY_DATA'!B:AR,13,FALSE) -> • | K67: =VLOOKUP(B67,'[1]26MY_ODYSSEY_DATA'!B:AR,14,FALSE) -> • | L67: =VLOOKUP(B67,'[1]26MY_ODYSSEY_DATA'!B:AR,15,FALSE) -> • | M67: =VLOOKUP(B67,'[1]26MY_ODYSSEY_DATA'!B:AR,16,FALSE) -> • | N67: =VLOOKUP($B67,'[1]26MY_ODYSSEY_DATA'!$B:$AR,17,FALSE) -> 0 | O67: =VLOOKUP($B67,'[1]26MY_ODYSSEY_DATA'!$B:$AR,18,FALSE) -> 0 | P67: =VLOOKUP($B67,'[1]26MY_ODYSSEY_DATA'!$B:$AR,19,FALSE) -> 0
B68: 08L07-E09-101 | C68: =VLOOKUP(B68,'[1]26MY_ODYSSEY_DATA'!B:AR,4,FALSE) -> Support à vélo vertical pour porte-bagages de toit | D68: =B68 -> 08L07-E09-101 | E68: =VLOOKUP(B68,'[1]26MY_ODYSSEY_DATA'!B:AR,9,FALSE) -> 383 | F68: =VLOOKUP(B68,'[1]26MY_ODYSSEY_DATA'!B:AR,10,FALSE) -> 547 | G68: =VLOOKUP(B68,'[1]26MY_ODYSSEY_DATA'!B:AR,7,FALSE) -> 0.6 | H68: =VLOOKUP(B68,'[1]26MY_ODYSSEY_DATA'!B:AR,11,FALSE) -> 647.8 | I68: =VLOOKUP(B68,'[1]26MY_ODYSSEY_DATA'!B:AR,12,FALSE) -> 0 | J68: =VLOOKUP(B68,'[1]26MY_ODYSSEY_DATA'!B:AR,13,FALSE) -> • | K68: =VLOOKUP(B68,'[1]26MY_ODYSSEY_DATA'!B:AR,14,FALSE) -> • | L68: =VLOOKUP(B68,'[1]26MY_ODYSSEY_DATA'!B:AR,15,FALSE) -> • | M68: =VLOOKUP(B68,'[1]26MY_ODYSSEY_DATA'!B:AR,16,FALSE) -> • | N68: =VLOOKUP($B68,'[1]26MY_ODYSSEY_DATA'!$B:$AR,17,FALSE) -> 0 | O68: =VLOOKUP($B68,'[1]26MY_ODYSSEY_DATA'!$B:$AR,18,FALSE) -> 0 | P68: =VLOOKUP($B68,'[1]26MY_ODYSSEY_DATA'!$B:$AR,19,FALSE) -> 0
B69: 08L20-E09-300A | C69: =VLOOKUP(B69,'[1]26MY_ODYSSEY_DATA'!B:AR,4,FALSE) -> Boîte de toit - moyenne | D69: =B69 -> 08L20-E09-300A | E69: =VLOOKUP(B69,'[1]26MY_ODYSSEY_DATA'!B:AR,9,FALSE) -> 875 | F69: =VLOOKUP(B69,'[1]26MY_ODYSSEY_DATA'!B:AR,10,FALSE) -> 1458 | G69: =VLOOKUP(B69,'[1]26MY_ODYSSEY_DATA'!B:AR,7,FALSE) -> 0.2 | H69: =VLOOKUP(B69,'[1]26MY_ODYSSEY_DATA'!B:AR,11,FALSE) -> 1491.6 | I69: =VLOOKUP(B69,'[1]26MY_ODYSSEY_DATA'!B:AR,12,FALSE) -> 0 | J69: =VLOOKUP(B69,'[1]26MY_ODYSSEY_DATA'!B:AR,13,FALSE) -> • | K69: =VLOOKUP(B69,'[1]26MY_ODYSSEY_DATA'!B:AR,14,FALSE) -> • | L69: =VLOOKUP(B69,'[1]26MY_ODYSSEY_DATA'!B:AR,15,FALSE) -> • | M69: =VLOOKUP(B69,'[1]26MY_ODYSSEY_DATA'!B:AR,16,FALSE) -> • | N69: =VLOOKUP($B69,'[1]26MY_ODYSSEY_DATA'!$B:$AR,17,FALSE) -> 0 | O69: =VLOOKUP($B69,'[1]26MY_ODYSSEY_DATA'!$B:$AR,18,FALSE) -> 0 | P69: =VLOOKUP($B69,'[1]26MY_ODYSSEY_DATA'!$B:$AR,19,FALSE) -> 0
B70: 08L20-E09-300B | C70: =VLOOKUP(B70,'[1]26MY_ODYSSEY_DATA'!B:AR,4,FALSE) -> Boîte de toit - courte | D70: =B70 -> 08L20-E09-300B | E70: =VLOOKUP(B70,'[1]26MY_ODYSSEY_DATA'!B:AR,9,FALSE) -> 799 | F70: =VLOOKUP(B70,'[1]26MY_ODYSSEY_DATA'!B:AR,10,FALSE) -> 1332 | G70: =VLOOKUP(B70,'[1]26MY_ODYSSEY_DATA'!B:AR,7,FALSE) -> 0.2 | H70: =VLOOKUP(B70,'[1]26MY_ODYSSEY_DATA'!B:AR,11,FALSE) -> 1365.6 | I70: =VLOOKUP(B70,'[1]26MY_ODYSSEY_DATA'!B:AR,12,FALSE) -> 0 | J70: =VLOOKUP(B70,'[1]26MY_ODYSSEY_DATA'!B:AR,13,FALSE) -> • | K70: =VLOOKUP(B70,'[1]26MY_ODYSSEY_DATA'!B:AR,14,FALSE) -> • | L70: =VLOOKUP(B70,'[1]26MY_ODYSSEY_DATA'!B:AR,15,FALSE) -> • | M70: =VLOOKUP(B70,'[1]26MY_ODYSSEY_DATA'!B:AR,16,FALSE) -> • | N70: =VLOOKUP($B70,'[1]26MY_ODYSSEY_DATA'!$B:$AR,17,FALSE) -> 0 | O70: =VLOOKUP($B70,'[1]26MY_ODYSSEY_DATA'!$B:$AR,18,FALSE) -> 0 | P70: =VLOOKUP($B70,'[1]26MY_ODYSSEY_DATA'!$B:$AR,19,FALSE) -> 0
B71: 08L09-E09-101 | C71: =VLOOKUP(B71,'[1]26MY_ODYSSEY_DATA'!B:AR,4,FALSE) -> Galerie de toit, fixation pour kayak | D71: =B71 -> 08L09-E09-101 | E71: =VLOOKUP(B71,'[1]26MY_ODYSSEY_DATA'!B:AR,9,FALSE) -> 430 | F71: =VLOOKUP(B71,'[1]26MY_ODYSSEY_DATA'!B:AR,10,FALSE) -> 717 | G71: =VLOOKUP(B71,'[1]26MY_ODYSSEY_DATA'!B:AR,7,FALSE) -> 0.2 | H71: =VLOOKUP(B71,'[1]26MY_ODYSSEY_DATA'!B:AR,11,FALSE) -> 750.6 | I71: =VLOOKUP(B71,'[1]26MY_ODYSSEY_DATA'!B:AR,12,FALSE) -> 0 | J71: =VLOOKUP(B71,'[1]26MY_ODYSSEY_DATA'!B:AR,13,FALSE) -> • | K71: =VLOOKUP(B71,'[1]26MY_ODYSSEY_DATA'!B:AR,14,FALSE) -> • | L71: =VLOOKUP(B71,'[1]26MY_ODYSSEY_DATA'!B:AR,15,FALSE) -> • | M71: =VLOOKUP(B71,'[1]26MY_ODYSSEY_DATA'!B:AR,16,FALSE) -> • | N71: =VLOOKUP($B71,'[1]26MY_ODYSSEY_DATA'!$B:$AR,17,FALSE) -> 0 | O71: =VLOOKUP($B71,'[1]26MY_ODYSSEY_DATA'!$B:$AR,18,FALSE) -> 0 | P71: =VLOOKUP($B71,'[1]26MY_ODYSSEY_DATA'!$B:$AR,19,FALSE) -> 0
B72: 08L03-E09-300C | C72: =VLOOKUP(B72,'[1]26MY_ODYSSEY_DATA'!B:AR,4,FALSE) -> Galerie de toit, Fixation pour skis/planche à neige | D72: =B72 -> 08L03-E09-300C | E72: =VLOOKUP(B72,'[1]26MY_ODYSSEY_DATA'!B:AR,9,FALSE) -> 415 | F72: =VLOOKUP(B72,'[1]26MY_ODYSSEY_DATA'!B:AR,10,FALSE) -> 692 | G72: =VLOOKUP(B72,'[1]26MY_ODYSSEY_DATA'!B:AR,7,FALSE) -> 0.2 | H72: =VLOOKUP(B72,'[1]26MY_ODYSSEY_DATA'!B:AR,11,FALSE) -> 725.6 | I72: =VLOOKUP(B72,'[1]26MY_ODYSSEY_DATA'!B:AR,12,FALSE) -> 0 | J72: =VLOOKUP(B72,'[1]26MY_ODYSSEY_DATA'!B:AR,13,FALSE) -> • | K72: =VLOOKUP(B72,'[1]26MY_ODYSSEY_DATA'!B:AR,14,FALSE) -> • | L72: =VLOOKUP(B72,'[1]26MY_ODYSSEY_DATA'!B:AR,15,FALSE) -> • | M72: =VLOOKUP(B72,'[1]26MY_ODYSSEY_DATA'!B:AR,16,FALSE) -> • | N72: =VLOOKUP($B72,'[1]26MY_ODYSSEY_DATA'!$B:$AR,17,FALSE) -> 0 | O72: =VLOOKUP($B72,'[1]26MY_ODYSSEY_DATA'!$B:$AR,18,FALSE) -> 0 | P72: =VLOOKUP($B72,'[1]26MY_ODYSSEY_DATA'!$B:$AR,19,FALSE) -> 0
B73: 08L05-E09-100 | C73: =VLOOKUP(B73,'[1]26MY_ODYSSEY_DATA'!B:AR,4,FALSE) -> Galerie de toit, Fixation pour planche de surf | D73: =B73 -> 08L05-E09-100 | E73: =VLOOKUP(B73,'[1]26MY_ODYSSEY_DATA'!B:AR,9,FALSE) -> 207 | F73: =VLOOKUP(B73,'[1]26MY_ODYSSEY_DATA'!B:AR,10,FALSE) -> 345 | G73: =VLOOKUP(B73,'[1]26MY_ODYSSEY_DATA'!B:AR,7,FALSE) -> 0.2 | H73: =VLOOKUP(B73,'[1]26MY_ODYSSEY_DATA'!B:AR,11,FALSE) -> 378.6 | I73: =VLOOKUP(B73,'[1]26MY_ODYSSEY_DATA'!B:AR,12,FALSE) -> 0 | J73: =VLOOKUP(B73,'[1]26MY_ODYSSEY_DATA'!B:AR,13,FALSE) -> • | K73: =VLOOKUP(B73,'[1]26MY_ODYSSEY_DATA'!B:AR,14,FALSE) -> • | L73: =VLOOKUP(B73,'[1]26MY_ODYSSEY_DATA'!B:AR,15,FALSE) -> • | M73: =VLOOKUP(B73,'[1]26MY_ODYSSEY_DATA'!B:AR,16,FALSE) -> • | N73: =VLOOKUP($B73,'[1]26MY_ODYSSEY_DATA'!$B:$AR,17,FALSE) -> 0 | O73: =VLOOKUP($B73,'[1]26MY_ODYSSEY_DATA'!$B:$AR,18,FALSE) -> 0 | P73: =VLOOKUP($B73,'[1]26MY_ODYSSEY_DATA'!$B:$AR,19,FALSE) -> 0
B74: 08L91-THR-XXXX | C74: =VLOOKUP(B74,'[1]26MY_ODYSSEY_DATA'!B:AR,4,FALSE) -> Pièces d’attelage de remorque
B75: 08L92-THR-300A | C75: =VLOOKUP(B75,'[1]26MY_ODYSSEY_DATA'!B:AR,4,FALSE) -> Attelage de remorque | D75: =B75 -> 08L92-THR-300A | E75: =VLOOKUP(B75,'[1]26MY_ODYSSEY_DATA'!B:AR,9,FALSE) -> 576 | F75: =VLOOKUP(B75,'[1]26MY_ODYSSEY_DATA'!B:AR,10,FALSE) -> 960 | G75: =VLOOKUP(B75,'[1]26MY_ODYSSEY_DATA'!B:AR,7,FALSE) -> 1.5 | H75: =VLOOKUP(B75,'[1]26MY_ODYSSEY_DATA'!B:AR,11,FALSE) -> 1212 | I75: =VLOOKUP(B75,'[1]26MY_ODYSSEY_DATA'!B:AR,12,FALSE) -> 0 | J75: =VLOOKUP(B75,'[1]26MY_ODYSSEY_DATA'!B:AR,13,FALSE) -> • | K75: =VLOOKUP(B75,'[1]26MY_ODYSSEY_DATA'!B:AR,14,FALSE) -> • | L75: =VLOOKUP(B75,'[1]26MY_ODYSSEY_DATA'!B:AR,15,FALSE) -> • | M75: =VLOOKUP(B75,'[1]26MY_ODYSSEY_DATA'!B:AR,16,FALSE) -> • | N75: =VLOOKUP($B75,'[1]26MY_ODYSSEY_DATA'!$B:$AR,17,FALSE) -> 0 | O75: =VLOOKUP($B75,'[1]26MY_ODYSSEY_DATA'!$B:$AR,18,FALSE) -> 0 | P75: =VLOOKUP($B75,'[1]26MY_ODYSSEY_DATA'!$B:$AR,19,FALSE) -> 0 | Q75: =IF(VLOOKUP(B75,'[1]26MY_ODYSSEY_DATA'!B:AR,21,FALSE)="","",VLOOKUP(B75,'[1]26MY_ODYSSEY_DATA'!B:AR,21,FALSE)) -> Attelage de remorque: Classe II. Attelage de remorque dimensions du réceptacle: 2 po x 2 po. TOURING: Nécessite adaptateur de capteur de hayon électrique mains libres.
B76: 08L92-SCV-300A | C76: =VLOOKUP(B76,'[1]26MY_ODYSSEY_DATA'!B:AR,4,FALSE) -> Rotule d'attelage de 1 7/8 po | D76: =B76 -> 08L92-SCV-300A | E76: =VLOOKUP(B76,'[1]26MY_ODYSSEY_DATA'!B:AR,9,FALSE) -> 28 | F76: =VLOOKUP(B76,'[1]26MY_ODYSSEY_DATA'!B:AR,10,FALSE) -> 47 | G76: =VLOOKUP(B76,'[1]26MY_ODYSSEY_DATA'!B:AR,7,FALSE) -> 0 | H76: =VLOOKUP(B76,'[1]26MY_ODYSSEY_DATA'!B:AR,11,FALSE) -> 47 | I76: =VLOOKUP(B76,'[1]26MY_ODYSSEY_DATA'!B:AR,12,FALSE) -> 0 | J76: =VLOOKUP(B76,'[1]26MY_ODYSSEY_DATA'!B:AR,13,FALSE) -> • | K76: =VLOOKUP(B76,'[1]26MY_ODYSSEY_DATA'!B:AR,14,FALSE) -> • | L76: =VLOOKUP(B76,'[1]26MY_ODYSSEY_DATA'!B:AR,15,FALSE) -> • | M76: =VLOOKUP(B76,'[1]26MY_ODYSSEY_DATA'!B:AR,16,FALSE) -> • | N76: =VLOOKUP($B76,'[1]26MY_ODYSSEY_DATA'!$B:$AR,17,FALSE) -> 0 | O76: =VLOOKUP($B76,'[1]26MY_ODYSSEY_DATA'!$B:$AR,18,FALSE) -> 0 | P76: =VLOOKUP($B76,'[1]26MY_ODYSSEY_DATA'!$B:$AR,19,FALSE) -> 0
B77: 08L92-SCV-100B | C77: =VLOOKUP(B77,'[1]26MY_ODYSSEY_DATA'!B:AR,4,FALSE) -> Rotule d'attelage de 2 po | D77: =B77 -> 08L92-SCV-100B | E77: =VLOOKUP(B77,'[1]26MY_ODYSSEY_DATA'!B:AR,9,FALSE) -> 28 | F77: =VLOOKUP(B77,'[1]26MY_ODYSSEY_DATA'!B:AR,10,FALSE) -> 47 | G77: =VLOOKUP(B77,'[1]26MY_ODYSSEY_DATA'!B:AR,7,FALSE) -> 0 | H77: =VLOOKUP(B77,'[1]26MY_ODYSSEY_DATA'!B:AR,11,FALSE) -> 47 | I77: =VLOOKUP(B77,'[1]26MY_ODYSSEY_DATA'!B:AR,12,FALSE) -> 0 | J77: =VLOOKUP(B77,'[1]26MY_ODYSSEY_DATA'!B:AR,13,FALSE) -> • | K77: =VLOOKUP(B77,'[1]26MY_ODYSSEY_DATA'!B:AR,14,FALSE) -> • | L77: =VLOOKUP(B77,'[1]26MY_ODYSSEY_DATA'!B:AR,15,FALSE) -> • | M77: =VLOOKUP(B77,'[1]26MY_ODYSSEY_DATA'!B:AR,16,FALSE) -> • | N77: =VLOOKUP($B77,'[1]26MY_ODYSSEY_DATA'!$B:$AR,17,FALSE) -> 0 | O77: =VLOOKUP($B77,'[1]26MY_ODYSSEY_DATA'!$B:$AR,18,FALSE) -> 0 | P77: =VLOOKUP($B77,'[1]26MY_ODYSSEY_DATA'!$B:$AR,19,FALSE) -> 0
B78: 08L91-THR-300 | C78: =VLOOKUP(B78,'[1]26MY_ODYSSEY_DATA'!B:AR,4,FALSE) -> Harnais pour remorque | D78: =B78 -> 08L91-THR-300 | E78: =VLOOKUP(B78,'[1]26MY_ODYSSEY_DATA'!B:AR,9,FALSE) -> 162 | F78: =VLOOKUP(B78,'[1]26MY_ODYSSEY_DATA'!B:AR,10,FALSE) -> 270 | G78: =VLOOKUP(B78,'[1]26MY_ODYSSEY_DATA'!B:AR,7,FALSE) -> 0.8 | H78: =VLOOKUP(B78,'[1]26MY_ODYSSEY_DATA'!B:AR,11,FALSE) -> 404.4 | I78: =VLOOKUP(B78,'[1]26MY_ODYSSEY_DATA'!B:AR,12,FALSE) -> 0 | J78: =VLOOKUP(B78,'[1]26MY_ODYSSEY_DATA'!B:AR,13,FALSE) -> • | K78: =VLOOKUP(B78,'[1]26MY_ODYSSEY_DATA'!B:AR,14,FALSE) -> • | L78: =VLOOKUP(B78,'[1]26MY_ODYSSEY_DATA'!B:AR,15,FALSE) -> • | M78: =VLOOKUP(B78,'[1]26MY_ODYSSEY_DATA'!B:AR,16,FALSE) -> • | N78: =VLOOKUP($B78,'[1]26MY_ODYSSEY_DATA'!$B:$AR,17,FALSE) -> 0 | O78: =VLOOKUP($B78,'[1]26MY_ODYSSEY_DATA'!$B:$AR,18,FALSE) -> 0 | P78: =VLOOKUP($B78,'[1]26MY_ODYSSEY_DATA'!$B:$AR,19,FALSE) -> 0
B79: 08L92-SJC-300A | C79: =VLOOKUP(B79,'[1]26MY_ODYSSEY_DATA'!B:AR,4,FALSE) -> Goupille de verrouillage pour l'attelage de remorque | D79: =B79 -> 08L92-SJC-300A | E79: =VLOOKUP(B79,'[1]26MY_ODYSSEY_DATA'!B:AR,9,FALSE) -> 106 | F79: =VLOOKUP(B79,'[1]26MY_ODYSSEY_DATA'!B:AR,10,FALSE) -> 163 | G79: =VLOOKUP(B79,'[1]26MY_ODYSSEY_DATA'!B:AR,7,FALSE) -> 0 | H79: =VLOOKUP(B79,'[1]26MY_ODYSSEY_DATA'!B:AR,11,FALSE) -> 163 | I79: =VLOOKUP(B79,'[1]26MY_ODYSSEY_DATA'!B:AR,12,FALSE) -> 0 | J79: =VLOOKUP(B79,'[1]26MY_ODYSSEY_DATA'!B:AR,13,FALSE) -> • | K79: =VLOOKUP(B79,'[1]26MY_ODYSSEY_DATA'!B:AR,14,FALSE) -> • | L79: =VLOOKUP(B79,'[1]26MY_ODYSSEY_DATA'!B:AR,15,FALSE) -> • | M79: =VLOOKUP(B79,'[1]26MY_ODYSSEY_DATA'!B:AR,16,FALSE) -> • | N79: =VLOOKUP($B79,'[1]26MY_ODYSSEY_DATA'!$B:$AR,17,FALSE) -> 0 | O79: =VLOOKUP($B79,'[1]26MY_ODYSSEY_DATA'!$B:$AR,18,FALSE) -> 0 | P79: =VLOOKUP($B79,'[1]26MY_ODYSSEY_DATA'!$B:$AR,19,FALSE) -> 0
B80: 08L91-THR-300A | C80: =VLOOKUP(B80,'[1]26MY_ODYSSEY_DATA'!B:AR,4,FALSE) -> Adaptateur de capteur de hayon électrique mains libres | D80: =B80 -> 08L91-THR-300A | E80: =VLOOKUP(B80,'[1]26MY_ODYSSEY_DATA'!B:AR,9,FALSE) -> 238 | F80: =VLOOKUP(B80,'[1]26MY_ODYSSEY_DATA'!B:AR,10,FALSE) -> 397 | G80: =VLOOKUP(B80,'[1]26MY_ODYSSEY_DATA'!B:AR,7,FALSE) -> 0.2 | H80: =VLOOKUP(B80,'[1]26MY_ODYSSEY_DATA'!B:AR,11,FALSE) -> 430.6 | I80: =VLOOKUP(B80,'[1]26MY_ODYSSEY_DATA'!B:AR,12,FALSE) -> 0 | J80: =VLOOKUP(B80,'[1]26MY_ODYSSEY_DATA'!B:AR,13,FALSE) -> • | K80: =VLOOKUP(B80,'[1]26MY_ODYSSEY_DATA'!B:AR,14,FALSE) -> • | L80: =VLOOKUP(B80,'[1]26MY_ODYSSEY_DATA'!B:AR,15,FALSE) -> • | M80: =VLOOKUP(B80,'[1]26MY_ODYSSEY_DATA'!B:AR,16,FALSE) -> • | N80: =VLOOKUP($B80,'[1]26MY_ODYSSEY_DATA'!$B:$AR,17,FALSE) -> 0 | O80: =VLOOKUP($B80,'[1]26MY_ODYSSEY_DATA'!$B:$AR,18,FALSE) -> 0 | P80: =VLOOKUP($B80,'[1]26MY_ODYSSEY_DATA'!$B:$AR,19,FALSE) -> 0
B81: 08P05-THR-XXXX | C81: =VLOOKUP(B81,'[1]26MY_ODYSSEY_DATA'!B:AR,4,FALSE) -> Moulure latérale
B82: 08P05-THR-191 | C82: =VLOOKUP(B82,'[1]26MY_ODYSSEY_DATA'!B:AR,4,FALSE) -> Blanc platine nacré (NH-883P) | D82: =B82 -> 08P05-THR-191 | E82: =VLOOKUP(B82,'[1]26MY_ODYSSEY_DATA'!B:AR,9,FALSE) -> 231 | F82: =VLOOKUP(B82,'[1]26MY_ODYSSEY_DATA'!B:AR,10,FALSE) -> 385 | G82: =VLOOKUP(B82,'[1]26MY_ODYSSEY_DATA'!B:AR,7,FALSE) -> 0.4 | H82: =VLOOKUP(B82,'[1]26MY_ODYSSEY_DATA'!B:AR,11,FALSE) -> 452.2 | I82: =VLOOKUP(B82,'[1]26MY_ODYSSEY_DATA'!B:AR,12,FALSE) -> 0 | J82: =VLOOKUP(B82,'[1]26MY_ODYSSEY_DATA'!B:AR,13,FALSE) -> • | K82: =VLOOKUP(B82,'[1]26MY_ODYSSEY_DATA'!B:AR,14,FALSE) -> • | L82: =VLOOKUP(B82,'[1]26MY_ODYSSEY_DATA'!B:AR,15,FALSE) -> • | M82: =VLOOKUP(B82,'[1]26MY_ODYSSEY_DATA'!B:AR,16,FALSE) -> • | N82: =VLOOKUP($B82,'[1]26MY_ODYSSEY_DATA'!$B:$AR,17,FALSE) -> 0 | O82: =VLOOKUP($B82,'[1]26MY_ODYSSEY_DATA'!$B:$AR,18,FALSE) -> 0 | P82: =VLOOKUP($B82,'[1]26MY_ODYSSEY_DATA'!$B:$AR,19,FALSE) -> 0 | Q82: =IF(VLOOKUP(B82,'[1]26MY_ODYSSEY_DATA'!B:AR,21,FALSE)="","",VLOOKUP(B82,'[1]26MY_ODYSSEY_DATA'!B:AR,21,FALSE))
B83: 08P05-THR-121 | C83: =VLOOKUP(B83,'[1]26MY_ODYSSEY_DATA'!B:AR,4,FALSE) -> Noir cristal nacré (NH-731P) | D83: =B83 -> 08P05-THR-121 | E83: =VLOOKUP(B83,'[1]26MY_ODYSSEY_DATA'!B:AR,9,FALSE) -> 231 | F83: =VLOOKUP(B83,'[1]26MY_ODYSSEY_DATA'!B:AR,10,FALSE) -> 385 | G83: =VLOOKUP(B83,'[1]26MY_ODYSSEY_DATA'!B:AR,7,FALSE) -> 0.4 | H83: =VLOOKUP(B83,'[1]26MY_ODYSSEY_DATA'!B:AR,11,FALSE) -> 452.2 | I83: =VLOOKUP(B83,'[1]26MY_ODYSSEY_DATA'!B:AR,12,FALSE) -> 0 | J83: =VLOOKUP(B83,'[1]26MY_ODYSSEY_DATA'!B:AR,13,FALSE) -> • | K83: =VLOOKUP(B83,'[1]26MY_ODYSSEY_DATA'!B:AR,14,FALSE) -> N/A | L83: =VLOOKUP(B83,'[1]26MY_ODYSSEY_DATA'!B:AR,15,FALSE) -> N/A | M83: =VLOOKUP(B83,'[1]26MY_ODYSSEY_DATA'!B:AR,16,FALSE) -> • | N83: =VLOOKUP($B83,'[1]26MY_ODYSSEY_DATA'!$B:$AR,17,FALSE) -> 0 | O83: =VLOOKUP($B83,'[1]26MY_ODYSSEY_DATA'!$B:$AR,18,FALSE) -> 0 | P83: =VLOOKUP($B83,'[1]26MY_ODYSSEY_DATA'!$B:$AR,19,FALSE) -> 0
B84: 08P05-THR-131 | C84: =VLOOKUP(B84,'[1]26MY_ODYSSEY_DATA'!B:AR,4,FALSE) -> Acier moderne métallisé (NH-797M) | D84: =B84 -> 08P05-THR-131 | E84: =VLOOKUP(B84,'[1]26MY_ODYSSEY_DATA'!B:AR,9,FALSE) -> 231 | F84: =VLOOKUP(B84,'[1]26MY_ODYSSEY_DATA'!B:AR,10,FALSE) -> 385 | G84: =VLOOKUP(B84,'[1]26MY_ODYSSEY_DATA'!B:AR,7,FALSE) -> 0.4 | H84: =VLOOKUP(B84,'[1]26MY_ODYSSEY_DATA'!B:AR,11,FALSE) -> 452.2 | I84: =VLOOKUP(B84,'[1]26MY_ODYSSEY_DATA'!B:AR,12,FALSE) -> 0 | J84: =VLOOKUP(B84,'[1]26MY_ODYSSEY_DATA'!B:AR,13,FALSE) -> N/A | K84: =VLOOKUP(B84,'[1]26MY_ODYSSEY_DATA'!B:AR,14,FALSE) -> • | L84: =VLOOKUP(B84,'[1]26MY_ODYSSEY_DATA'!B:AR,15,FALSE) -> • | M84: =VLOOKUP(B84,'[1]26MY_ODYSSEY_DATA'!B:AR,16,FALSE) -> N/A | N84: =VLOOKUP($B84,'[1]26MY_ODYSSEY_DATA'!$B:$AR,17,FALSE) -> 0 | O84: =VLOOKUP($B84,'[1]26MY_ODYSSEY_DATA'!$B:$AR,18,FALSE) -> 0 | P84: =VLOOKUP($B84,'[1]26MY_ODYSSEY_DATA'!$B:$AR,19,FALSE) -> 0
B85: 08P05-THR-1B1 | C85: =VLOOKUP(B85,'[1]26MY_ODYSSEY_DATA'!B:AR,4,FALSE) -> Gris sonique nacré (NH-877P) | D85: =B85 -> 08P05-THR-1B1 | E85: =VLOOKUP(B85,'[1]26MY_ODYSSEY_DATA'!B:AR,9,FALSE) -> 231 | F85: =VLOOKUP(B85,'[1]26MY_ODYSSEY_DATA'!B:AR,10,FALSE) -> 385 | G85: =VLOOKUP(B85,'[1]26MY_ODYSSEY_DATA'!B:AR,7,FALSE) -> 0.4 | H85: =VLOOKUP(B85,'[1]26MY_ODYSSEY_DATA'!B:AR,11,FALSE) -> 452.2 | I85: =VLOOKUP(B85,'[1]26MY_ODYSSEY_DATA'!B:AR,12,FALSE) -> 0 | J85: =VLOOKUP(B85,'[1]26MY_ODYSSEY_DATA'!B:AR,13,FALSE) -> N/A | K85: =VLOOKUP(B85,'[1]26MY_ODYSSEY_DATA'!B:AR,14,FALSE) -> N/A | L85: =VLOOKUP(B85,'[1]26MY_ODYSSEY_DATA'!B:AR,15,FALSE) -> • | M85: =VLOOKUP(B85,'[1]26MY_ODYSSEY_DATA'!B:AR,16,FALSE) -> • | N85: =VLOOKUP($B85,'[1]26MY_ODYSSEY_DATA'!$B:$AR,17,FALSE) -> 0 | O85: =VLOOKUP($B85,'[1]26MY_ODYSSEY_DATA'!$B:$AR,18,FALSE) -> 0 | P85: =VLOOKUP($B85,'[1]26MY_ODYSSEY_DATA'!$B:$AR,19,FALSE) -> 0
B86: 08P05-THR-1A1 | C86: =VLOOKUP(B86,'[1]26MY_ODYSSEY_DATA'!B:AR,4,FALSE) -> Radiant rouge métallisé II (R-580M) | D86: =B86 -> 08P05-THR-1A1 | E86: =VLOOKUP(B86,'[1]26MY_ODYSSEY_DATA'!B:AR,9,FALSE) -> 231 | F86: =VLOOKUP(B86,'[1]26MY_ODYSSEY_DATA'!B:AR,10,FALSE) -> 385 | G86: =VLOOKUP(B86,'[1]26MY_ODYSSEY_DATA'!B:AR,7,FALSE) -> 0.4 | H86: =VLOOKUP(B86,'[1]26MY_ODYSSEY_DATA'!B:AR,11,FALSE) -> 452.2 | I86: =VLOOKUP(B86,'[1]26MY_ODYSSEY_DATA'!B:AR,12,FALSE) -> 0 | J86: =VLOOKUP(B86,'[1]26MY_ODYSSEY_DATA'!B:AR,13,FALSE) -> N/A | K86: =VLOOKUP(B86,'[1]26MY_ODYSSEY_DATA'!B:AR,14,FALSE) -> N/A | L86: =VLOOKUP(B86,'[1]26MY_ODYSSEY_DATA'!B:AR,15,FALSE) -> N/A | M86: =VLOOKUP(B86,'[1]26MY_ODYSSEY_DATA'!B:AR,16,FALSE) -> • | N86: =VLOOKUP($B86,'[1]26MY_ODYSSEY_DATA'!$B:$AR,17,FALSE) -> 0 | O86: =VLOOKUP($B86,'[1]26MY_ODYSSEY_DATA'!$B:$AR,18,FALSE) -> 0 | P86: =VLOOKUP($B86,'[1]26MY_ODYSSEY_DATA'!$B:$AR,19,FALSE) -> 0
B87: 08P05-THR-1C1 | C87: =VLOOKUP(B87,'[1]26MY_ODYSSEY_DATA'!B:AR,4,FALSE) -> Refl et solaire argent métallisé (NH-932M) | D87: =B87 -> 08P05-THR-1C1 | E87: =VLOOKUP(B87,'[1]26MY_ODYSSEY_DATA'!B:AR,9,FALSE) -> 231 | F87: =VLOOKUP(B87,'[1]26MY_ODYSSEY_DATA'!B:AR,10,FALSE) -> 385 | G87: =VLOOKUP(B87,'[1]26MY_ODYSSEY_DATA'!B:AR,7,FALSE) -> 0.4 | H87: =VLOOKUP(B87,'[1]26MY_ODYSSEY_DATA'!B:AR,11,FALSE) -> 452.2 | I87: =VLOOKUP(B87,'[1]26MY_ODYSSEY_DATA'!B:AR,12,FALSE) -> 0 | J87: =VLOOKUP(B87,'[1]26MY_ODYSSEY_DATA'!B:AR,13,FALSE) -> • | K87: =VLOOKUP(B87,'[1]26MY_ODYSSEY_DATA'!B:AR,14,FALSE) -> • | L87: =VLOOKUP(B87,'[1]26MY_ODYSSEY_DATA'!B:AR,15,FALSE) -> • | M87: =VLOOKUP(B87,'[1]26MY_ODYSSEY_DATA'!B:AR,16,FALSE) -> N/A | N87: =VLOOKUP($B87,'[1]26MY_ODYSSEY_DATA'!$B:$AR,17,FALSE) -> 0 | O87: =VLOOKUP($B87,'[1]26MY_ODYSSEY_DATA'!$B:$AR,18,FALSE) -> 0 | P87: =VLOOKUP($B87,'[1]26MY_ODYSSEY_DATA'!$B:$AR,19,FALSE) -> 0
B88: 08P20-THR-XXXX | C88: =VLOOKUP(B88,'[1]26MY_ODYSSEY_DATA'!B:AR,4,FALSE) -> Protecteurs de bordure de porte
B89: 08P20-THR-190A | C89: =VLOOKUP(B89,'[1]26MY_ODYSSEY_DATA'!B:AR,4,FALSE) -> Blanc platine nacré (NH-883P) | D89: =B89 -> 08P20-THR-190A | E89: =VLOOKUP(B89,'[1]26MY_ODYSSEY_DATA'!B:AR,9,FALSE) -> 87 | F89: =VLOOKUP(B89,'[1]26MY_ODYSSEY_DATA'!B:AR,10,FALSE) -> 145 | G89: =VLOOKUP(B89,'[1]26MY_ODYSSEY_DATA'!B:AR,7,FALSE) -> 0.3 | H89: =VLOOKUP(B89,'[1]26MY_ODYSSEY_DATA'!B:AR,11,FALSE) -> 195.4 | I89: =VLOOKUP(B89,'[1]26MY_ODYSSEY_DATA'!B:AR,12,FALSE) -> 0 | J89: =VLOOKUP(B89,'[1]26MY_ODYSSEY_DATA'!B:AR,13,FALSE) -> • | K89: =VLOOKUP(B89,'[1]26MY_ODYSSEY_DATA'!B:AR,14,FALSE) -> • | L89: =VLOOKUP(B89,'[1]26MY_ODYSSEY_DATA'!B:AR,15,FALSE) -> • | M89: =VLOOKUP(B89,'[1]26MY_ODYSSEY_DATA'!B:AR,16,FALSE) -> • | N89: =VLOOKUP($B89,'[1]26MY_ODYSSEY_DATA'!$B:$AR,17,FALSE) -> 0 | O89: =VLOOKUP($B89,'[1]26MY_ODYSSEY_DATA'!$B:$AR,18,FALSE) -> 0 | P89: =VLOOKUP($B89,'[1]26MY_ODYSSEY_DATA'!$B:$AR,19,FALSE) -> 0 | Q89: =IF(VLOOKUP(B89,'[1]26MY_ODYSSEY_DATA'!B:AR,21,FALSE)="","",VLOOKUP(B89,'[1]26MY_ODYSSEY_DATA'!B:AR,21,FALSE))
B90: 08P20-THR-120A | C90: =VLOOKUP(B90,'[1]26MY_ODYSSEY_DATA'!B:AR,4,FALSE) -> Noir cristal nacré (NH-731P) | D90: =B90 -> 08P20-THR-120A | E90: =VLOOKUP(B90,'[1]26MY_ODYSSEY_DATA'!B:AR,9,FALSE) -> 87 | F90: =VLOOKUP(B90,'[1]26MY_ODYSSEY_DATA'!B:AR,10,FALSE) -> 145 | G90: =VLOOKUP(B90,'[1]26MY_ODYSSEY_DATA'!B:AR,7,FALSE) -> 0.3 | H90: =VLOOKUP(B90,'[1]26MY_ODYSSEY_DATA'!B:AR,11,FALSE) -> 195.4 | I90: =VLOOKUP(B90,'[1]26MY_ODYSSEY_DATA'!B:AR,12,FALSE) -> 0 | J90: =VLOOKUP(B90,'[1]26MY_ODYSSEY_DATA'!B:AR,13,FALSE) -> • | K90: =VLOOKUP(B90,'[1]26MY_ODYSSEY_DATA'!B:AR,14,FALSE) -> N/A | L90: =VLOOKUP(B90,'[1]26MY_ODYSSEY_DATA'!B:AR,15,FALSE) -> N/A | M90: =VLOOKUP(B90,'[1]26MY_ODYSSEY_DATA'!B:AR,16,FALSE) -> • | N90: =VLOOKUP($B90,'[1]26MY_ODYSSEY_DATA'!$B:$AR,17,FALSE) -> 0 | O90: =VLOOKUP($B90,'[1]26MY_ODYSSEY_DATA'!$B:$AR,18,FALSE) -> 0 | P90: =VLOOKUP($B90,'[1]26MY_ODYSSEY_DATA'!$B:$AR,19,FALSE) -> 0
B91: 08P20-THR-130A | C91: =VLOOKUP(B91,'[1]26MY_ODYSSEY_DATA'!B:AR,4,FALSE) -> Acier moderne métallisé (NH-797M) | D91: =B91 -> 08P20-THR-130A | E91: =VLOOKUP(B91,'[1]26MY_ODYSSEY_DATA'!B:AR,9,FALSE) -> 87 | F91: =VLOOKUP(B91,'[1]26MY_ODYSSEY_DATA'!B:AR,10,FALSE) -> 145 | G91: =VLOOKUP(B91,'[1]26MY_ODYSSEY_DATA'!B:AR,7,FALSE) -> 0.3 | H91: =VLOOKUP(B91,'[1]26MY_ODYSSEY_DATA'!B:AR,11,FALSE) -> 195.4 | I91: =VLOOKUP(B91,'[1]26MY_ODYSSEY_DATA'!B:AR,12,FALSE) -> 0 | J91: =VLOOKUP(B91,'[1]26MY_ODYSSEY_DATA'!B:AR,13,FALSE) -> N/A | K91: =VLOOKUP(B91,'[1]26MY_ODYSSEY_DATA'!B:AR,14,FALSE) -> • | L91: =VLOOKUP(B91,'[1]26MY_ODYSSEY_DATA'!B:AR,15,FALSE) -> • | M91: =VLOOKUP(B91,'[1]26MY_ODYSSEY_DATA'!B:AR,16,FALSE) -> N/A | N91: =VLOOKUP($B91,'[1]26MY_ODYSSEY_DATA'!$B:$AR,17,FALSE) -> 0 | O91: =VLOOKUP($B91,'[1]26MY_ODYSSEY_DATA'!$B:$AR,18,FALSE) -> 0 | P91: =VLOOKUP($B91,'[1]26MY_ODYSSEY_DATA'!$B:$AR,19,FALSE) -> 0
B92: 08P20-THR-1B0A | C92: =VLOOKUP(B92,'[1]26MY_ODYSSEY_DATA'!B:AR,4,FALSE) -> Gris sonique nacré (NH-877P) | D92: =B92 -> 08P20-THR-1B0A | E92: =VLOOKUP(B92,'[1]26MY_ODYSSEY_DATA'!B:AR,9,FALSE) -> 87 | F92: =VLOOKUP(B92,'[1]26MY_ODYSSEY_DATA'!B:AR,10,FALSE) -> 145 | G92: =VLOOKUP(B92,'[1]26MY_ODYSSEY_DATA'!B:AR,7,FALSE) -> 0.3 | H92: =VLOOKUP(B92,'[1]26MY_ODYSSEY_DATA'!B:AR,11,FALSE) -> 195.4 | I92: =VLOOKUP(B92,'[1]26MY_ODYSSEY_DATA'!B:AR,12,FALSE) -> 0 | J92: =VLOOKUP(B92,'[1]26MY_ODYSSEY_DATA'!B:AR,13,FALSE) -> N/A | K92: =VLOOKUP(B92,'[1]26MY_ODYSSEY_DATA'!B:AR,14,FALSE) -> N/A | L92: =VLOOKUP(B92,'[1]26MY_ODYSSEY_DATA'!B:AR,15,FALSE) -> • | M92: =VLOOKUP(B92,'[1]26MY_ODYSSEY_DATA'!B:AR,16,FALSE) -> • | N92: =VLOOKUP($B92,'[1]26MY_ODYSSEY_DATA'!$B:$AR,17,FALSE) -> 0 | O92: =VLOOKUP($B92,'[1]26MY_ODYSSEY_DATA'!$B:$AR,18,FALSE) -> 0 | P92: =VLOOKUP($B92,'[1]26MY_ODYSSEY_DATA'!$B:$AR,19,FALSE) -> 0
B93: 08P20-THR-1A0A | C93: =VLOOKUP(B93,'[1]26MY_ODYSSEY_DATA'!B:AR,4,FALSE) -> Radiant rouge métallisé II (R-580M) | D93: =B93 -> 08P20-THR-1A0A | E93: =VLOOKUP(B93,'[1]26MY_ODYSSEY_DATA'!B:AR,9,FALSE) -> 23.99 | F93: =VLOOKUP(B93,'[1]26MY_ODYSSEY_DATA'!B:AR,10,FALSE) -> 39.99 | G93: =VLOOKUP(B93,'[1]26MY_ODYSSEY_DATA'!B:AR,7,FALSE) -> 0.3 | H93: =VLOOKUP(B93,'[1]26MY_ODYSSEY_DATA'!B:AR,11,FALSE) -> 90.39 | I93: =VLOOKUP(B93,'[1]26MY_ODYSSEY_DATA'!B:AR,12,FALSE) -> 0 | J93: =VLOOKUP(B93,'[1]26MY_ODYSSEY_DATA'!B:AR,13,FALSE) -> N/A | K93: =VLOOKUP(B93,'[1]26MY_ODYSSEY_DATA'!B:AR,14,FALSE) -> N/A | L93: =VLOOKUP(B93,'[1]26MY_ODYSSEY_DATA'!B:AR,15,FALSE) -> N/A | M93: =VLOOKUP(B93,'[1]26MY_ODYSSEY_DATA'!B:AR,16,FALSE) -> • | N93: =VLOOKUP($B93,'[1]26MY_ODYSSEY_DATA'!$B:$AR,17,FALSE) -> 0 | O93: =VLOOKUP($B93,'[1]26MY_ODYSSEY_DATA'!$B:$AR,18,FALSE) -> 0 | P93: =VLOOKUP($B93,'[1]26MY_ODYSSEY_DATA'!$B:$AR,19,FALSE) -> 0
B94: 08P20-THR-1C0A | C94: =VLOOKUP(B94,'[1]26MY_ODYSSEY_DATA'!B:AR,4,FALSE) -> Refl et solaire argent métallisé (NH-932M) | D94: =B94 -> 08P20-THR-1C0A | E94: =VLOOKUP(B94,'[1]26MY_ODYSSEY_DATA'!B:AR,9,FALSE) -> 87 | F94: =VLOOKUP(B94,'[1]26MY_ODYSSEY_DATA'!B:AR,10,FALSE) -> 145 | G94: =VLOOKUP(B94,'[1]26MY_ODYSSEY_DATA'!B:AR,7,FALSE) -> 0.3 | H94: =VLOOKUP(B94,'[1]26MY_ODYSSEY_DATA'!B:AR,11,FALSE) -> 195.4 | I94: =VLOOKUP(B94,'[1]26MY_ODYSSEY_DATA'!B:AR,12,FALSE) -> 0 | J94: =VLOOKUP(B94,'[1]26MY_ODYSSEY_DATA'!B:AR,13,FALSE) -> • | K94: =VLOOKUP(B94,'[1]26MY_ODYSSEY_DATA'!B:AR,14,FALSE) -> • | L94: =VLOOKUP(B94,'[1]26MY_ODYSSEY_DATA'!B:AR,15,FALSE) -> • | M94: =VLOOKUP(B94,'[1]26MY_ODYSSEY_DATA'!B:AR,16,FALSE) -> N/A | N94: =VLOOKUP($B94,'[1]26MY_ODYSSEY_DATA'!$B:$AR,17,FALSE) -> 0 | O94: =VLOOKUP($B94,'[1]26MY_ODYSSEY_DATA'!$B:$AR,18,FALSE) -> 0 | P94: =VLOOKUP($B94,'[1]26MY_ODYSSEY_DATA'!$B:$AR,19,FALSE) -> 0
B95: 08V67-THR-1A0K | C95: =VLOOKUP(B95,'[1]26MY_ODYSSEY_DATA'!B:AR,4,FALSE) -> Radiant rouge métallisé II (R-580M) | D95: =B95 -> 08V67-THR-1A0K | E95: =VLOOKUP(B95,'[1]26MY_ODYSSEY_DATA'!B:AR,24,FALSE) -> 0 | F95: =VLOOKUP(B95,'[1]26MY_ODYSSEY_DATA'!B:AR,25,FALSE) -> 0 | G95: =VLOOKUP(B95,'[1]26MY_ODYSSEY_DATA'!B:AR,22,FALSE) -> 0 | H95: =VLOOKUP(B95,'[1]26MY_ODYSSEY_DATA'!B:AR,26,FALSE) -> 0 | J95: =VLOOKUP(B95,'[1]26MY_ODYSSEY_DATA'!B:AR,28,FALSE) -> 0 | K95: =VLOOKUP(B95,'[1]26MY_ODYSSEY_DATA'!B:AR,29,FALSE) -> 0 | L95: =VLOOKUP(B95,'[1]26MY_ODYSSEY_DATA'!B:AR,30,FALSE) -> 0 | M95: =VLOOKUP(B95,'[1]26MY_ODYSSEY_DATA'!B:AR,31,FALSE) -> 0 | N95: =VLOOKUP(C95,'[1]26MY_ODYSSEY_DATA'!C:AS,31,FALSE) -> #N/A | O95: =VLOOKUP(C95,'[1]26MY_ODYSSEY_DATA'!C:AS,31,FALSE) -> #N/A
C97: 4.0 Intérieur
C98: La description | D98: Numéro de pièce | E98: Prix net | F98: Prix de liste | G98: T.F.F. | H98: Prix installé | I98: Application | Q98: Commentaires
I99: ='[1]26MY_ODYSSEY_DATA'!M$6 -> 0 | J99: ='[1]26MY_ODYSSEY_DATA'!N$6 -> Sport | K99: ='[1]26MY_ODYSSEY_DATA'!O$6 -> Sport-L | L99: ='[1]26MY_ODYSSEY_DATA'!P$6 -> Touring | M99: ='[1]26MY_ODYSSEY_DATA'!Q$6 -> Black Edition | N99: ='[1]26MY_ODYSSEY_DATA'!R$6 -> 0 | O99: ='[1]26MY_ODYSSEY_DATA'!S$6 -> 0 | P99: ='[1]26MY_ODYSSEY_DATA'!T$6 -> 0
B100: 08P17-THR-110A | C100: =VLOOKUP(B100,'[1]26MY_ODYSSEY_DATA'!B:AR,4,FALSE) -> Protège-tapis toutes saisons - logo blanc | D100: =B100 -> 08P17-THR-110A | E100: =VLOOKUP(B100,'[1]26MY_ODYSSEY_DATA'!B:AR,9,FALSE) -> 195 | F100: =VLOOKUP(B100,'[1]26MY_ODYSSEY_DATA'!B:AR,10,FALSE) -> 325 | G100: =VLOOKUP(B100,'[1]26MY_ODYSSEY_DATA'!B:AR,7,FALSE) -> 0.1 | H100: =VLOOKUP(B100,'[1]26MY_ODYSSEY_DATA'!B:AR,11,FALSE) -> 341.8 | I100: =VLOOKUP(B100,'[1]26MY_ODYSSEY_DATA'!B:AR,12,FALSE) -> 0 | J100: =VLOOKUP(B100,'[1]26MY_ODYSSEY_DATA'!B:AR,13,FALSE) -> • | K100: =VLOOKUP(B100,'[1]26MY_ODYSSEY_DATA'!B:AR,14,FALSE) -> • | L100: =VLOOKUP(B100,'[1]26MY_ODYSSEY_DATA'!B:AR,15,FALSE) -> • | M100: =VLOOKUP(B100,'[1]26MY_ODYSSEY_DATA'!B:AR,16,FALSE) -> • | N100: =VLOOKUP($B100,'[1]26MY_ODYSSEY_DATA'!$B:$AR,17,FALSE) -> 0 | O100: =VLOOKUP($B100,'[1]26MY_ODYSSEY_DATA'!$B:$AR,18,FALSE) -> 0 | P100: =VLOOKUP($B100,'[1]26MY_ODYSSEY_DATA'!$B:$AR,19,FALSE) -> 0 | Q100: =IF(VLOOKUP(B100,'[1]26MY_ODYSSEY_DATA'!B:AR,21,FALSE)="","",VLOOKUP(B100,'[1]26MY_ODYSSEY_DATA'!B:AR,21,FALSE)) -> Logo blanc.
B101: 08U45-THR-100A | C101: =VLOOKUP(B101,'[1]26MY_ODYSSEY_DATA'!B:AR,4,FALSE) -> Plateau de compartiment à bagages - profond | D101: =B101 -> 08U45-THR-100A | E101: =VLOOKUP(B101,'[1]26MY_ODYSSEY_DATA'!B:AR,9,FALSE) -> 140 | F101: =VLOOKUP(B101,'[1]26MY_ODYSSEY_DATA'!B:AR,10,FALSE) -> 233 | G101: =VLOOKUP(B101,'[1]26MY_ODYSSEY_DATA'!B:AR,7,FALSE) -> 0.1 | H101: =VLOOKUP(B101,'[1]26MY_ODYSSEY_DATA'!B:AR,11,FALSE) -> 249.8 | I101: =VLOOKUP(B101,'[1]26MY_ODYSSEY_DATA'!B:AR,12,FALSE) -> 0 | J101: =VLOOKUP(B101,'[1]26MY_ODYSSEY_DATA'!B:AR,13,FALSE) -> • | K101: =VLOOKUP(B101,'[1]26MY_ODYSSEY_DATA'!B:AR,14,FALSE) -> • | L101: =VLOOKUP(B101,'[1]26MY_ODYSSEY_DATA'!B:AR,15,FALSE) -> • | M101: =VLOOKUP(B101,'[1]26MY_ODYSSEY_DATA'!B:AR,16,FALSE) -> • | N101: =VLOOKUP($B101,'[1]26MY_ODYSSEY_DATA'!$B:$AR,17,FALSE) -> 0 | O101: =VLOOKUP($B101,'[1]26MY_ODYSSEY_DATA'!$B:$AR,18,FALSE) -> 0 | P101: =VLOOKUP($B101,'[1]26MY_ODYSSEY_DATA'!$B:$AR,19,FALSE) -> 0 | Q101: =IF(VLOOKUP(B101,'[1]26MY_ODYSSEY_DATA'!B:AR,21,FALSE)="","",VLOOKUP(B101,'[1]26MY_ODYSSEY_DATA'!B:AR,21,FALSE))
B102: 08U45-THR-100B | C102: =VLOOKUP(B102,'[1]26MY_ODYSSEY_DATA'!B:AR,4,FALSE) -> Plateaux de coffre pliants | D102: =B102 -> 08U45-THR-100B | E102: =VLOOKUP(B102,'[1]26MY_ODYSSEY_DATA'!B:AR,9,FALSE) -> 160 | F102: =VLOOKUP(B102,'[1]26MY_ODYSSEY_DATA'!B:AR,10,FALSE) -> 267 | G102: =VLOOKUP(B102,'[1]26MY_ODYSSEY_DATA'!B:AR,7,FALSE) -> 0.1 | H102: =VLOOKUP(B102,'[1]26MY_ODYSSEY_DATA'!B:AR,11,FALSE) -> 283.8 | I102: =VLOOKUP(B102,'[1]26MY_ODYSSEY_DATA'!B:AR,12,FALSE) -> 0 | J102: =VLOOKUP(B102,'[1]26MY_ODYSSEY_DATA'!B:AR,13,FALSE) -> • | K102: =VLOOKUP(B102,'[1]26MY_ODYSSEY_DATA'!B:AR,14,FALSE) -> • | L102: =VLOOKUP(B102,'[1]26MY_ODYSSEY_DATA'!B:AR,15,FALSE) -> • | M102: =VLOOKUP(B102,'[1]26MY_ODYSSEY_DATA'!B:AR,16,FALSE) -> • | N102: =VLOOKUP($B102,'[1]26MY_ODYSSEY_DATA'!$B:$AR,17,FALSE) -> 0 | O102: =VLOOKUP($B102,'[1]26MY_ODYSSEY_DATA'!$B:$AR,18,FALSE) -> 0 | P102: =VLOOKUP($B102,'[1]26MY_ODYSSEY_DATA'!$B:$AR,19,FALSE) -> 0 | Q102: =IF(VLOOKUP(B102,'[1]26MY_ODYSSEY_DATA'!B:AR,21,FALSE)="","",VLOOKUP(B102,'[1]26MY_ODYSSEY_DATA'!B:AR,21,FALSE))
B103: 08U45-THR-300 | C103: =VLOOKUP(B103,'[1]26MY_ODYSSEY_DATA'!B:AR,4,FALSE) -> Des paniers de compartiment à bagages | D103: =B103 -> 08U45-THR-300 | E103: =VLOOKUP(B103,'[1]26MY_ODYSSEY_DATA'!B:AR,9,FALSE) -> 413 | F103: =VLOOKUP(B103,'[1]26MY_ODYSSEY_DATA'!B:AR,10,FALSE) -> 688 | G103: =VLOOKUP(B103,'[1]26MY_ODYSSEY_DATA'!B:AR,7,FALSE) -> 0.1 | H103: =VLOOKUP(B103,'[1]26MY_ODYSSEY_DATA'!B:AR,11,FALSE) -> 704.8 | I103: =VLOOKUP(B103,'[1]26MY_ODYSSEY_DATA'!B:AR,12,FALSE) -> 0 | J103: =VLOOKUP(B103,'[1]26MY_ODYSSEY_DATA'!B:AR,13,FALSE) -> • | K103: =VLOOKUP(B103,'[1]26MY_ODYSSEY_DATA'!B:AR,14,FALSE) -> • | L103: =VLOOKUP(B103,'[1]26MY_ODYSSEY_DATA'!B:AR,15,FALSE) -> • | M103: =VLOOKUP(B103,'[1]26MY_ODYSSEY_DATA'!B:AR,16,FALSE) -> • | N103: =VLOOKUP($B103,'[1]26MY_ODYSSEY_DATA'!$B:$AR,17,FALSE) -> 0 | O103: =VLOOKUP($B103,'[1]26MY_ODYSSEY_DATA'!$B:$AR,18,FALSE) -> 0 | P103: =VLOOKUP($B103,'[1]26MY_ODYSSEY_DATA'!$B:$AR,19,FALSE) -> 0 | Q103: =IF(VLOOKUP(B103,'[1]26MY_ODYSSEY_DATA'!B:AR,21,FALSE)="","",VLOOKUP(B103,'[1]26MY_ODYSSEY_DATA'!B:AR,21,FALSE))
B104: 08P42-THR-100 | C104: =VLOOKUP(B104,'[1]26MY_ODYSSEY_DATA'!B:AR,4,FALSE) -> Protection pour compartiment utilitaire | D104: =B104 -> 08P42-THR-100 | E104: =VLOOKUP(B104,'[1]26MY_ODYSSEY_DATA'!B:AR,9,FALSE) -> 295 | F104: =VLOOKUP(B104,'[1]26MY_ODYSSEY_DATA'!B:AR,10,FALSE) -> 421 | G104: =VLOOKUP(B104,'[1]26MY_ODYSSEY_DATA'!B:AR,7,FALSE) -> 1.2 | H104: =VLOOKUP(B104,'[1]26MY_ODYSSEY_DATA'!B:AR,11,FALSE) -> 622.6 | I104: =VLOOKUP(B104,'[1]26MY_ODYSSEY_DATA'!B:AR,12,FALSE) -> 0 | J104: =VLOOKUP(B104,'[1]26MY_ODYSSEY_DATA'!B:AR,13,FALSE) -> • | K104: =VLOOKUP(B104,'[1]26MY_ODYSSEY_DATA'!B:AR,14,FALSE) -> • | L104: =VLOOKUP(B104,'[1]26MY_ODYSSEY_DATA'!B:AR,15,FALSE) -> • | M104: =VLOOKUP(B104,'[1]26MY_ODYSSEY_DATA'!B:AR,16,FALSE) -> • | N104: =VLOOKUP($B104,'[1]26MY_ODYSSEY_DATA'!$B:$AR,17,FALSE) -> 0 | O104: =VLOOKUP($B104,'[1]26MY_ODYSSEY_DATA'!$B:$AR,18,FALSE) -> 0 | P104: =VLOOKUP($B104,'[1]26MY_ODYSSEY_DATA'!$B:$AR,19,FALSE) -> 0 | Q104: =IF(VLOOKUP(B104,'[1]26MY_ODYSSEY_DATA'!B:AR,21,FALSE)="","",VLOOKUP(B104,'[1]26MY_ODYSSEY_DATA'!B:AR,21,FALSE))
B105: 08L96-THR-100 | C105: =VLOOKUP(B105,'[1]26MY_ODYSSEY_DATA'!B:AR,4,FALSE) -> Filet d’arrimage | D105: =B105 -> 08L96-THR-100 | E105: =VLOOKUP(B105,'[1]26MY_ODYSSEY_DATA'!B:AR,9,FALSE) -> 42 | F105: =VLOOKUP(B105,'[1]26MY_ODYSSEY_DATA'!B:AR,10,FALSE) -> 70 | G105: =VLOOKUP(B105,'[1]26MY_ODYSSEY_DATA'!B:AR,7,FALSE) -> 0.1 | H105: =VLOOKUP(B105,'[1]26MY_ODYSSEY_DATA'!B:AR,11,FALSE) -> 86.8 | I105: =VLOOKUP(B105,'[1]26MY_ODYSSEY_DATA'!B:AR,12,FALSE) -> 0 | J105: =VLOOKUP(B105,'[1]26MY_ODYSSEY_DATA'!B:AR,13,FALSE) -> • | K105: =VLOOKUP(B105,'[1]26MY_ODYSSEY_DATA'!B:AR,14,FALSE) -> • | L105: =VLOOKUP(B105,'[1]26MY_ODYSSEY_DATA'!B:AR,15,FALSE) -> • | M105: =VLOOKUP(B105,'[1]26MY_ODYSSEY_DATA'!B:AR,16,FALSE) -> • | N105: =VLOOKUP($B105,'[1]26MY_ODYSSEY_DATA'!$B:$AR,17,FALSE) -> 0 | O105: =VLOOKUP($B105,'[1]26MY_ODYSSEY_DATA'!$B:$AR,18,FALSE) -> 0 | P105: =VLOOKUP($B105,'[1]26MY_ODYSSEY_DATA'!$B:$AR,19,FALSE) -> 0 | Q105: =IF(VLOOKUP(B105,'[1]26MY_ODYSSEY_DATA'!B:AR,21,FALSE)="","",VLOOKUP(B105,'[1]26MY_ODYSSEY_DATA'!B:AR,21,FALSE))
B106: 08P32-THR-310D | C106: =VLOOKUP(B106,'[1]26MY_ODYSSEY_DATA'!B:AR,4,FALSE) -> Housse pour sièges, 2e rangée | D106: =B106 -> 08P32-THR-310D | E106: =VLOOKUP(B106,'[1]26MY_ODYSSEY_DATA'!B:AR,9,FALSE) -> 394 | F106: =VLOOKUP(B106,'[1]26MY_ODYSSEY_DATA'!B:AR,10,FALSE) -> 563 | G106: =VLOOKUP(B106,'[1]26MY_ODYSSEY_DATA'!B:AR,7,FALSE) -> 0.3 | H106: =VLOOKUP(B106,'[1]26MY_ODYSSEY_DATA'!B:AR,11,FALSE) -> 613.4 | I106: =VLOOKUP(B106,'[1]26MY_ODYSSEY_DATA'!B:AR,12,FALSE) -> 0 | J106: =VLOOKUP(B106,'[1]26MY_ODYSSEY_DATA'!B:AR,13,FALSE) -> • | K106: =VLOOKUP(B106,'[1]26MY_ODYSSEY_DATA'!B:AR,14,FALSE) -> • | L106: =VLOOKUP(B106,'[1]26MY_ODYSSEY_DATA'!B:AR,15,FALSE) -> • | M106: =VLOOKUP(B106,'[1]26MY_ODYSSEY_DATA'!B:AR,16,FALSE) -> • | N106: =VLOOKUP($B106,'[1]26MY_ODYSSEY_DATA'!$B:$AR,17,FALSE) -> 0 | O106: =VLOOKUP($B106,'[1]26MY_ODYSSEY_DATA'!$B:$AR,18,FALSE) -> 0 | P106: =VLOOKUP($B106,'[1]26MY_ODYSSEY_DATA'!$B:$AR,19,FALSE) -> 0 | Q106: =IF(VLOOKUP(B106,'[1]26MY_ODYSSEY_DATA'!B:AR,21,FALSE)="","",VLOOKUP(B106,'[1]26MY_ODYSSEY_DATA'!B:AR,21,FALSE)) -> 8 sièges passagers.
B107: 08P32-THR-310F | C107: =VLOOKUP(B107,'[1]26MY_ODYSSEY_DATA'!B:AR,4,FALSE) -> Housse pour sièges, 3e rangée | D107: =B107 -> 08P32-THR-310F | E107: =VLOOKUP(B107,'[1]26MY_ODYSSEY_DATA'!B:AR,9,FALSE) -> 304 | F107: =VLOOKUP(B107,'[1]26MY_ODYSSEY_DATA'!B:AR,10,FALSE) -> 434 | G107: =VLOOKUP(B107,'[1]26MY_ODYSSEY_DATA'!B:AR,7,FALSE) -> 0.2 | H107: =VLOOKUP(B107,'[1]26MY_ODYSSEY_DATA'!B:AR,11,FALSE) -> 467.6 | I107: =VLOOKUP(B107,'[1]26MY_ODYSSEY_DATA'!B:AR,12,FALSE) -> 0 | J107: =VLOOKUP(B107,'[1]26MY_ODYSSEY_DATA'!B:AR,13,FALSE) -> • | K107: =VLOOKUP(B107,'[1]26MY_ODYSSEY_DATA'!B:AR,14,FALSE) -> • | L107: =VLOOKUP(B107,'[1]26MY_ODYSSEY_DATA'!B:AR,15,FALSE) -> • | M107: =VLOOKUP(B107,'[1]26MY_ODYSSEY_DATA'!B:AR,16,FALSE) -> • | N107: =VLOOKUP($B107,'[1]26MY_ODYSSEY_DATA'!$B:$AR,17,FALSE) -> 0 | O107: =VLOOKUP($B107,'[1]26MY_ODYSSEY_DATA'!$B:$AR,18,FALSE) -> 0 | P107: =VLOOKUP($B107,'[1]26MY_ODYSSEY_DATA'!$B:$AR,19,FALSE) -> 0 | Q107: =IF(VLOOKUP(B107,'[1]26MY_ODYSSEY_DATA'!B:AR,21,FALSE)="","",VLOOKUP(B107,'[1]26MY_ODYSSEY_DATA'!B:AR,21,FALSE))
C109: 5.0 Électrique
C110: La description | D110: Numéro de pièce | E110: Prix net | F110: Prix de liste | G110: T.F.F. | H110: Prix installé | I110: Application | Q110: Commentaires
I111: ='[1]26MY_ODYSSEY_DATA'!M$6 -> 0 | J111: ='[1]26MY_ODYSSEY_DATA'!N$6 -> Sport | K111: ='[1]26MY_ODYSSEY_DATA'!O$6 -> Sport-L | L111: ='[1]26MY_ODYSSEY_DATA'!P$6 -> Touring | M111: ='[1]26MY_ODYSSEY_DATA'!Q$6 -> Black Edition | N111: ='[1]26MY_ODYSSEY_DATA'!R$6 -> 0 | O111: ='[1]26MY_ODYSSEY_DATA'!S$6 -> 0 | P111: ='[1]26MY_ODYSSEY_DATA'!T$6 -> 0
B112: 08E12-THR-100 | C112: =VLOOKUP(B112,'[1]26MY_ODYSSEY_DATA'!B:AR,4,FALSE) -> Garniture lumineuses de bas de portière - Avant et arrière | D112: =B112 -> 08E12-THR-100 | E112: =VLOOKUP(B112,'[1]26MY_ODYSSEY_DATA'!B:AR,9,FALSE) -> 564 | F112: =VLOOKUP(B112,'[1]26MY_ODYSSEY_DATA'!B:AR,10,FALSE) -> 868 | G112: =VLOOKUP(B112,'[1]26MY_ODYSSEY_DATA'!B:AR,7,FALSE) -> 1.2 | H112: =VLOOKUP(B112,'[1]26MY_ODYSSEY_DATA'!B:AR,11,FALSE) -> 1069.6 | I112: =VLOOKUP(B112,'[1]26MY_ODYSSEY_DATA'!B:AR,12,FALSE) -> 0 | J112: =VLOOKUP(B112,'[1]26MY_ODYSSEY_DATA'!B:AR,13,FALSE) -> • | K112: =VLOOKUP(B112,'[1]26MY_ODYSSEY_DATA'!B:AR,14,FALSE) -> • | L112: =VLOOKUP(B112,'[1]26MY_ODYSSEY_DATA'!B:AR,15,FALSE) -> • | M112: =VLOOKUP(B112,'[1]26MY_ODYSSEY_DATA'!B:AR,16,FALSE) -> • | N112: =VLOOKUP($B112,'[1]26MY_ODYSSEY_DATA'!$B:$AR,17,FALSE) -> 0 | O112: =VLOOKUP($B112,'[1]26MY_ODYSSEY_DATA'!$B:$AR,18,FALSE) -> 0 | P112: =VLOOKUP($B112,'[1]26MY_ODYSSEY_DATA'!$B:$AR,19,FALSE) -> 0 | Q112: =IF(VLOOKUP(B112,'[1]26MY_ODYSSEY_DATA'!B:AR,21,FALSE)="","",VLOOKUP(B112,'[1]26MY_ODYSSEY_DATA'!B:AR,21,FALSE)) -> Garniture de portes avant et arrière.
...

Sheet 25MY_ODYSSEY_SELL-FR
B3: 26MY Honda Odyssey
B4: 200
B6: ACCESSOIRES POPULAIRES
B7: 20
B8: 150
B10: 20 | C10: ='26MY_ODYSSEY_APP_FR'!$C$100 -> Protège-tapis toutes saisons - logo blanc | H10: ='26MY_ODYSSEY_APP_FR'!$C$101 -> Plateau de compartiment à bagages - profond | M10: ='26MY_ODYSSEY_APP_FR'!$C$102 -> Plateaux de coffre pliants
B11: 20 | C11: ='26MY_ODYSSEY_APP_FR'!$H$100 -> 341.8 | D11: =-PMT($D$29/52,5*52,C11) -> 1.5585734 | E11: /wk * | F11: =$C$29 -> (6.99%) | H11: ='26MY_ODYSSEY_APP_FR'!$H$101 -> 249.8 | I11: =-PMT($D$29/52,5*52,H11) -> 1.1390627 | J11: /wk * | K11: =$C$29 -> (6.99%) | M11: ='26MY_ODYSSEY_APP_FR'!$H$102 -> 283.8 | N11: =-PMT($D$29/52,5*52,M11) -> 1.2940993 | O11: /wk * | P11: =$C$29 -> (6.99%)
B13: et
B15: 20 | C15: =TEXT('26MY_ODYSSEY_APP_FR'!$C$62,0)&(TEXT($B$13,0)&TEXT('26MY_ODYSSEY_APP_FR'!$C$64,0)) -> Rails de toit - Noir et Barres transversales | H15: =TEXT('26MY_ODYSSEY_APP_FR'!$C$75,0)&(TEXT($B$13,0)&TEXT('26MY_ODYSSEY_APP_FR'!$C$78,0)) -> Attelage de remorque et Harnais pour remorque | M15: ='26MY_ODYSSEY_APP_FR'!$C$112 -> Garniture lumineuses de bas de portière - Avant et arrière
B16: 50 | C16: ='26MY_ODYSSEY_APP_FR'!$H$62+'26MY_ODYSSEY_APP_FR'!$H$64 -> 1328.6 | D16: =-PMT($D$29/52,5*52,C16) -> 6.0582816 | E16: /wk * | F16: =$C$29 -> (6.99%) | H16: ='26MY_ODYSSEY_APP_FR'!$H$75+'26MY_ODYSSEY_APP_FR'!$H$78 -> 1616.4 | I16: =-PMT($D$29/52,5*52,H16) -> 7.3706205 | J16: /wk * | K16: =$C$29 -> (6.99%) | M16: ='26MY_ODYSSEY_APP_FR'!$H$112 -> 1069.6 | N16: =-PMT($D$29/52,5*52,M16) -> 4.8772678 | O16: /wk * | P16: =$C$29 -> (6.99%)
B18: 150
B20: 20 | C20: ='26MY_ODYSSEY_APP_FR'!$C$58 -> Déflecteur d’air du capot | H20: ='26MY_ODYSSEY_APP_FR'!$C$57 -> Pare-soleil de portière | M20: ='26MY_ODYSSEY_APP_FR'!$C$61 -> Tente
B21: 50 | C21: ='26MY_ODYSSEY_APP_FR'!$H$58 -> 424 | D21: =-PMT($D$29/52,5*52,C21) -> 1.9333971 | E21: /wk * | F21: =$C$29 -> (6.99%) | H21: ='26MY_ODYSSEY_APP_FR'!$H$57 -> 474 | I21: =-PMT($D$29/52,5*52,H21) -> 2.161392 | J21: /wk * | K21: =$C$29 -> (6.99%) | M21: ='26MY_ODYSSEY_APP_FR'!$H$61 -> 681 | N21: =-PMT($D$29/52,5*52,M21) -> 3.1052911 | O21: /wk * | P21: =$C$29 -> (6.99%)
C23: Les accessoires Honda d’origine achetés avec un véhicule Honda neuf incluent une garantie du fabricant de 3 ans ou 60 000 km.
C24: Les accessoires de véhicule achetés après la vente du véhicule incluent une garantie du fabricant de 1 an ou 20 000 km.
B25: 20 | C25: *Les prix indiqués incluent le coût d'installation.
B26: 60 | C26: *À titre d’information seulement. Les montants hebdomadaires indiqués sont des paiements estimés basés sur un contrat de financement de 60 mois à un taux annuel en pourcentage (TAP) de 6,99 % (coût d’installation compris). Taxes et frais applicables en sus. Les accessoires ne peuvent être financés seuls et doivent être financés par l’entremise de Honda Canada Finance Inc., sur approbation de crédit, conjointement avec un véhicule Honda. Exemple de financement représentatif : Un montant de 350,00 $ financé à un TAP de 6,99 % équivaut à un paiement hebdomadaire de 1,60 $ pendant 60 mois. 260 paiements hebdomadaires sont requis. Le coût d’emprunt est de 64,80 $, pour une obligation totale de 414,80 $. Le montant réel des paiements variera en fonction du TAP, de la période du contrat de financement et du coût des accessoires applicables. Certaines conditions s’appliquent. Veuillez visiter votre concessionnaire Honda pour obtenir tous les détails.
C27: *Vous pouvez voir d’autres options de paiements hebdomadaires personnalisés ainsi que des accessoires sur le site Honda.ca – Configuration et prix.
B28: 20
B29: 18 | C29: (6.99%) | D29: 0.0699
B30: 7.5 | C30: 12 | D30: 8 | E30: 8 | F30: 10 | G30: 8.5 | H30: 12 | I30: 8 | J30: 8 | K30: 10 | L30: 8.5 | M30: 12 | N30: 8 | O30: 8 | P30: 10 | Q30: 7.5
B31: Date de publication: | C31: ='[1]26MY_ODYSSEY_DATA'!$C$3 -> 45902 | D31: Tout prix, spécifications de versions et disponibilté d'accessoires publiés sont sujets à changer sans pré-avis. | P31: Province | Q31: ='[1]26MY_ODYSSEY_DATA'!L5 -> YT
