Workbook
Name prov_cd: 'SELECT PROVINCE'!$B$1
Name province_codes: 'SELECT PROVINCE'!$B$6:$B$16
Name rate_table: 'SELECT PROVINCE'!$B$6:$C$16

Sheet SELECT PROVINCE
A1: Select Province: Choissisez votre province: | B1: YT
B4: Current Labor Rates
B5: Taux de main d'oeuvre en cours
B6: AB | C6: 162
B7: BC | C7: 165
B8: MB | C8: 155
B9: NB | C9: 129
B10: NL | C10: 129
B11: NS | C11: 129
B12: ON | C12: 149 | F12: =prov_cd -> YT
B13: PEI | C13: 123
B14: QC | C14: 140
B15: SK | C15: 155
B16: YT | C16: 165
A23: All published prices, trim specifications, and availability are subject to change without prior notice.
A24: Tout prix, spécifications de versions et disponibilté d'accessoires publiés sont sujets à changer sans pré-avis.

Sheet 26MY_Pilot_APP_EN
B2: Honda Internal | C2: Honda Accessories
C3: Model Name | D3: ='[1]26MY_PILOT_DATA'!C2 -> Pilot
C4: Model Year | D4: ='[1]26MY_PILOT_DATA'!$C$3 -> 2026
C5: S = Standard (accessory comes standard on this trim)
C6: T = Tire Size Change (the size of the accessory wheel is smaller/larger than the OE Wheel. Customer will require new tires to fit these wheels.)
C7: E = Exchange Standard Equipment (the size of the accessory wheel is the same size as the OE wheel and therefore they can use the OE tire.)
C8: N/A = Not Applicable (accessory cannot be applied to this trim)
H10: Province
C11: 1.0 Packages and Kits | H11: =prov_cd -> YT
C12: Description | D12: Part Number | E12: Dealer Net | F12: List Price | G12: FRT | H12: Installed Price | I12: Application | Q12: Comments
I13: ='[1]26MY_PILOT_DATA'!$M$7 -> 0 | J13: ='[1]26MY_PILOT_DATA'!$M$7 -> 0 | K13: ='[1]26MY_PILOT_DATA'!$M$7 -> 0 | L13: ='[1]26MY_PILOT_DATA'!$P$7 -> Sport | M13: ='[1]26MY_PILOT_DATA'!$Q$7 -> EX-L | N13: ='[1]26MY_PILOT_DATA'!$R$7 -> TrailSport | O13: ='[1]26MY_PILOT_DATA'!$S$7 -> Touring | P13: ='[1]26MY_PILOT_DATA'!$T$7 -> Black Edition
B14: 23PIL-PRO-PK1 or 23PIL-PRO-PK2 | C14: =VLOOKUP(B14,'[1]26MY_PILOT_DATA'!B:V,3,FALSE) -> Protection Package | D14: =B14 -> 23PIL-PRO-PK1 or 23PIL-PRO-PK2 | E14: =VLOOKUP($B14,'[1]26MY_PILOT_DATA'!B:V,9,FALSE) -> 298.8 | F14: =VLOOKUP(B14,'[1]26MY_PILOT_DATA'!B:V,10,FALSE) -> 553 | G14: =VLOOKUP(B14,'[1]26MY_PILOT_DATA'!B:V,7,FALSE) -> 0.2 | H14: =VLOOKUP(B14,'[1]26MY_PILOT_DATA'!B:V,11,FALSE) -> 586 | I14: =VLOOKUP($B14,'[1]26MY_PILOT_DATA'!B:V,12,FALSE) -> 0 | J14: =VLOOKUP($B14,'[1]26MY_PILOT_DATA'!B:V,13,FALSE) -> 0 | K14: =VLOOKUP($B14,'[1]26MY_PILOT_DATA'!B:V,14,FALSE) -> 0 | L14: =VLOOKUP(B14,'[1]26MY_PILOT_DATA'!B:V,15,FALSE) -> • | M14: =VLOOKUP(B14,'[1]26MY_PILOT_DATA'!B:V,16,FALSE) -> • | N14: =VLOOKUP(B14,'[1]26MY_PILOT_DATA'!B:V,17,FALSE) -> • | O14: =VLOOKUP(B14,'[1]26MY_PILOT_DATA'!B:V,18,FALSE) -> • | P14: =VLOOKUP(B14,'[1]26MY_PILOT_DATA'!B:V,19,FALSE) -> • | Q14: =IF(VLOOKUP(B14,'[1]26MY_PILOT_DATA'!B:V,20,FALSE)="","",VLOOKUP(B14,'[1]26MY_PILOT_DATA'!B:V,20,FALSE)) -> 23PIL-PRO-PK1: applicable for Sport, EX-L, Touring, and Black Ed. trims 23PIL-PRO-PK2: applicable for TrailSport trim
B15: 08P17-T90-110 or 08P17-T90-300C | C15: =VLOOKUP(B15,'[1]26MY_PILOT_DATA'!B:V,3,FALSE) -> All Season Floor Mats | D15: =B15 -> 08P17-T90-110 or 08P17-T90-300C
B16: 08U45-T90-100 | C16: =VLOOKUP(B16,'[1]26MY_PILOT_DATA'!B:V,3,FALSE) -> Cargo Tray | D16: =B16 -> 08U45-T90-100
B18: 23PIL-PRO-PKA1 | C18: =VLOOKUP(B18,'[1]26MY_PILOT_DATA'!B:V,3,FALSE) -> Protection Package Advance | D18: =B18 -> 23PIL-PRO-PKA1 | E18: =VLOOKUP($B18,'[1]26MY_PILOT_DATA'!B:V,9,FALSE) -> 791.1 | F18: =VLOOKUP(B18,'[1]26MY_PILOT_DATA'!B:V,10,FALSE) -> 1318.5 | G18: =VLOOKUP(B18,'[1]26MY_PILOT_DATA'!B:V,7,FALSE) -> 1.2 | H18: =VLOOKUP(B18,'[1]26MY_PILOT_DATA'!B:V,11,FALSE) -> 1516.5 | I18: =VLOOKUP($B18,'[1]26MY_PILOT_DATA'!B:V,12,FALSE) -> 0 | J18: =VLOOKUP($B18,'[1]26MY_PILOT_DATA'!B:V,13,FALSE) -> 0 | K18: =VLOOKUP($B18,'[1]26MY_PILOT_DATA'!B:V,14,FALSE) -> 0 | L18: =VLOOKUP(B18,'[1]26MY_PILOT_DATA'!B:V,15,FALSE) -> • | M18: =VLOOKUP(B18,'[1]26MY_PILOT_DATA'!B:V,16,FALSE) -> • | N18: =VLOOKUP(B18,'[1]26MY_PILOT_DATA'!B:V,17,FALSE) -> N/A | O18: =VLOOKUP(B18,'[1]26MY_PILOT_DATA'!B:V,18,FALSE) -> • | P18: =VLOOKUP(B18,'[1]26MY_PILOT_DATA'!B:V,19,FALSE) -> • | Q18: =IF(VLOOKUP(B18,'[1]26MY_PILOT_DATA'!B:V,20,FALSE)="","",VLOOKUP(B18,'[1]26MY_PILOT_DATA'!B:V,20,FALSE)) -> 10% Discount applied 23PIL-PRO-PKA1: applicable for Sport, EX-L, Touring, and Black Ed. Trims 23PIL-PRO-PKA2: applicable for TrailSport trim.
B19: 08P17-T90-110 | C19: =VLOOKUP(B19,'[1]26MY_PILOT_DATA'!B:V,3,FALSE) -> All Season Floor Mats | D19: =B19 -> 08P17-T90-110
B20: 08U45-T90-100 | C20: =VLOOKUP(B20,'[1]26MY_PILOT_DATA'!B:V,3,FALSE) -> Cargo Tray | D20: =B20 -> 08U45-T90-100
B21: 08U35-T90-110 | C21: =VLOOKUP(B21,'[1]26MY_PILOT_DATA'!B:V,3,FALSE) -> Cargo Cover | D21: =B21 -> 08U35-T90-110
B22: 08P42-T90-100B | C22: =VLOOKUP(B22,'[1]26MY_PILOT_DATA'!B:V,3,FALSE) -> Seat Back Protector | D22: =B22 -> 08P42-T90-100B
B23: 08P42-T90-100A | C23: =VLOOKUP(B23,'[1]26MY_PILOT_DATA'!B:V,3,FALSE) -> Side Lining Protectors | D23: =B23 -> 08P42-T90-100A
B25: 23PIL-PRO-PKA2 | C25: =VLOOKUP(B25,'[1]26MY_PILOT_DATA'!B:V,3,FALSE) -> Protection Package Advance | D25: =B25 -> 23PIL-PRO-PKA2 | E25: =VLOOKUP($B25,'[1]26MY_PILOT_DATA'!B:V,9,FALSE) -> 776.7 | F25: =VLOOKUP(B25,'[1]26MY_PILOT_DATA'!B:V,10,FALSE) -> 1284.3 | G25: =VLOOKUP(B25,'[1]26MY_PILOT_DATA'!B:V,7,FALSE) -> 1.1 | H25: =VLOOKUP(B25,'[1]26MY_PILOT_DATA'!B:V,11,FALSE) -> 1465.8 | I25: =VLOOKUP($B25,'[1]26MY_PILOT_DATA'!B:V,12,FALSE) -> 0 | J25: =VLOOKUP($B25,'[1]26MY_PILOT_DATA'!B:V,13,FALSE) -> 0 | K25: =VLOOKUP($B25,'[1]26MY_PILOT_DATA'!B:V,14,FALSE) -> 0 | L25: =VLOOKUP(B25,'[1]26MY_PILOT_DATA'!B:V,15,FALSE) -> N/A | M25: =VLOOKUP(B25,'[1]26MY_PILOT_DATA'!B:V,16,FALSE) -> N/A | N25: =VLOOKUP(B25,'[1]26MY_PILOT_DATA'!B:V,17,FALSE) -> • | O25: =VLOOKUP(B25,'[1]26MY_PILOT_DATA'!B:V,18,FALSE) -> N/A | P25: =VLOOKUP(B25,'[1]26MY_PILOT_DATA'!B:V,19,FALSE) -> N/A
B26: 08P17-T90-310C | C26: =VLOOKUP(B26,'[1]26MY_PILOT_DATA'!B:V,3,FALSE) -> All Season Floor Mats TrailSport | D26: =B26 -> 08P17-T90-310C
B27: 08U45-T90-100 | C27: =VLOOKUP(B27,'[1]26MY_PILOT_DATA'!B:V,3,FALSE) -> Cargo Tray | D27: =B27 -> 08U45-T90-100
B28: 08U35-T90-110 | C28: =VLOOKUP(B28,'[1]26MY_PILOT_DATA'!B:V,3,FALSE) -> Cargo Cover | D28: =B28 -> 08U35-T90-110
B29: 08P42-T90-100C | C29: =VLOOKUP(B29,'[1]26MY_PILOT_DATA'!B:V,3,FALSE) -> Seat Back Protector | D29: =B29 -> 08P42-T90-100C
B30: 08P42-T90-100A | C30: =VLOOKUP(B30,'[1]26MY_PILOT_DATA'!B:V,3,FALSE) -> Side Lining Protectors | D30: =B30 -> 08P42-T90-100A
B32: 26PIL-TOW-B1 ou 26PIL-TOW-B2 | C32: =VLOOKUP(B32,'[1]26MY_PILOT_DATA'!B:V,3,FALSE) -> Towing Package | D32: See Comments | E32: =VLOOKUP($B32,'[1]26MY_PILOT_DATA'!B:V,9,FALSE) -> 998.1 | F32: =VLOOKUP(B32,'[1]26MY_PILOT_DATA'!B:V,10,FALSE) -> 1651.5 | G32: =VLOOKUP(B32,'[1]26MY_PILOT_DATA'!B:V,7,FALSE) -> 1.8 | H32: =VLOOKUP(B32,'[1]26MY_PILOT_DATA'!B:V,11,FALSE) -> 1948.5 | I32: =VLOOKUP($B32,'[1]26MY_PILOT_DATA'!B:V,12,FALSE) -> 0 | J32: =VLOOKUP($B32,'[1]26MY_PILOT_DATA'!B:V,13,FALSE) -> 0 | K32: =VLOOKUP($B32,'[1]26MY_PILOT_DATA'!B:V,14,FALSE) -> 0 | L32: =VLOOKUP(B32,'[1]26MY_PILOT_DATA'!B:V,15,FALSE) -> • | M32: =VLOOKUP(B32,'[1]26MY_PILOT_DATA'!B:V,16,FALSE) -> • | N32: =VLOOKUP(B32,'[1]26MY_PILOT_DATA'!B:V,17,FALSE) -> N/A | O32: =VLOOKUP(B32,'[1]26MY_PILOT_DATA'!B:V,18,FALSE) -> N/A | P32: =VLOOKUP(B32,'[1]26MY_PILOT_DATA'!B:V,19,FALSE) -> N/A | Q32: =IF(VLOOKUP(B32,'[1]26MY_PILOT_DATA'!B:V,20,FALSE)="","",VLOOKUP(B32,'[1]26MY_PILOT_DATA'!B:V,20,FALSE)) -> 10% Discount Applied ATF Cooler not needed for 23MY Pilot. Towing capacity is 5000lbs. Sport Trim(Trailer Hitch Panel Black) : 26PIL-TOW-B1: 1-7/8" Trailer Hitch Ball 26PIL-TOW-B2: 2" Trailer Hitch Ball EX-L Trim(Trailer Hitch Panel Silver): 26PIL-TOW-S1: 1-7/8" Trailer Hitch Ball 26PIL-TOW-S2: 2" Trailer Hitch Ball Touring Trim**(Trailer Hitch Panel Silver): 26PIL-TOW-SA1: 1-7/8" Trailer Hitch Ball 26PIL-TOW-SA2: 2" Trailer Hitch Ball Black Edition Trim**(Trailer Hitch Panel Black) : 26PIL-TOW-BA1: 1-7/8" Trailer Hitch Ball 26PIL-TOW-BA2: 2" Trailer Hitch Ball **Touring & Black Edition requires HFA Adapter - 08L91-T90-300A
B33: 08L92-T90-100 | C33: =VLOOKUP(B33,'[1]26MY_PILOT_DATA'!B:V,3,FALSE) -> Trailer Hitch | D33: =B33 -> 08L92-T90-100
B34: 08L91-T90-300B | C34: =VLOOKUP(B34,'[1]26MY_PILOT_DATA'!B:V,3,FALSE) -> Trailer Hitch Harness | D34: =B34 -> 08L91-T90-300B
B35: 08L92-T90-300D or 08L92-T90-300E | C35: =VLOOKUP(B35,'[1]26MY_PILOT_DATA'!B:V,3,FALSE) -> Trailer Hitch Panel Black or Silver | D35: =B35 -> 08L92-T90-300D or 08L92-T90-300E
B36: 08L92-T90-100A | C36: =VLOOKUP(B36,'[1]26MY_PILOT_DATA'!B:V,3,FALSE) -> Trailer Hitch Ball Mount | D36: =B36 -> 08L92-T90-100A
B37: 08L92-S9V-300G or 08L92-S9V-300H | C37: =VLOOKUP(B37,'[1]26MY_PILOT_DATA'!B:V,3,FALSE) -> Trailer Hitch Ball - 1-7/8" or 2" | D37: =B37 -> 08L92-S9V-300G or 08L92-S9V-300H
B38: 08L92-SJC-300A | C38: =VLOOKUP(B38,'[1]26MY_PILOT_DATA'!B:V,3,FALSE) -> Trailer Hitch Locking Pin | D38: =B38 -> 08L92-SJC-300A
B40: 26PIL-TOW-SA1 or 26PIL-TOW-SA2 | C40: =VLOOKUP(B40,'[1]26MY_PILOT_DATA'!B:V,3,FALSE) -> Towing Package | D40: See Comments | E40: =VLOOKUP($B40,'[1]26MY_PILOT_DATA'!B:V,9,FALSE) -> 1292.4 | F40: =VLOOKUP(B40,'[1]26MY_PILOT_DATA'!B:V,10,FALSE) -> 2071.8 | G40: =VLOOKUP(B40,'[1]26MY_PILOT_DATA'!B:V,7,FALSE) -> 1.9 | H40: =VLOOKUP(B40,'[1]26MY_PILOT_DATA'!B:V,11,FALSE) -> 2385.3 | I40: =VLOOKUP($B40,'[1]26MY_PILOT_DATA'!B:V,12,FALSE) -> 0 | J40: =VLOOKUP($B40,'[1]26MY_PILOT_DATA'!B:V,13,FALSE) -> 0 | K40: =VLOOKUP($B40,'[1]26MY_PILOT_DATA'!B:V,14,FALSE) -> 0 | L40: =VLOOKUP(B40,'[1]26MY_PILOT_DATA'!B:V,15,FALSE) -> N/A | M40: =VLOOKUP(B40,'[1]26MY_PILOT_DATA'!B:V,16,FALSE) -> N/A | N40: =VLOOKUP(B40,'[1]26MY_PILOT_DATA'!B:V,17,FALSE) -> N/A | O40: =VLOOKUP(B40,'[1]26MY_PILOT_DATA'!B:V,18,FALSE) -> • | P40: =VLOOKUP(B40,'[1]26MY_PILOT_DATA'!B:V,19,FALSE) -> •
B41: 08L92-T90-100 | C41: =VLOOKUP(B41,'[1]26MY_PILOT_DATA'!B:V,3,FALSE) -> Trailer Hitch | D41: =B41 -> 08L92-T90-100
B42: 08L91-T90-300B | C42: =VLOOKUP(B42,'[1]26MY_PILOT_DATA'!B:V,3,FALSE) -> Trailer Hitch Harness | D42: =B42 -> 08L91-T90-300B
B43: 08L92-T90-300D or 08L92-T90-300E | C43: =VLOOKUP(B43,'[1]26MY_PILOT_DATA'!B:V,3,FALSE) -> Trailer Hitch Panel Black or Silver | D43: =B43 -> 08L92-T90-300D or 08L92-T90-300E
B44: 08L92-T90-100A | C44: =VLOOKUP(B44,'[1]26MY_PILOT_DATA'!B:V,3,FALSE) -> Trailer Hitch Ball Mount | D44: =B44 -> 08L92-T90-100A
B45: 08L92-S9V-300G or 08L92-S9V-300H | C45: =VLOOKUP(B45,'[1]26MY_PILOT_DATA'!B:V,3,FALSE) -> Trailer Hitch Ball - 1-7/8" or 2" | D45: =B45 -> 08L92-S9V-300G or 08L92-S9V-300H
B46: 08L92-SJC-300A | C46: =VLOOKUP(B46,'[1]26MY_PILOT_DATA'!B:V,3,FALSE) -> Trailer Hitch Locking Pin | D46: =B46 -> 08L92-SJC-300A
B47: 08L91-T90-300A | C47: =VLOOKUP(B47,'[1]26MY_PILOT_DATA'!B:V,3,FALSE) -> Trailer Hitch HFA Adapter | D47: =B47 -> 08L91-T90-300A
B49: 26PIL-TOW-TS1 or 26PIL-TOW-TS2 | C49: =VLOOKUP(B49,'[1]26MY_PILOT_DATA'!B:V,3,FALSE) -> Towing Package - TrailSport | D49: =B49 -> 26PIL-TOW-TS1 or 26PIL-TOW-TS2 | E49: =VLOOKUP($B49,'[1]26MY_PILOT_DATA'!B:V,9,FALSE) -> 500.65 | F49: =VLOOKUP(B49,'[1]26MY_PILOT_DATA'!B:V,10,FALSE) -> 821.75 | G49: =VLOOKUP(B49,'[1]26MY_PILOT_DATA'!B:V,7,FALSE) -> 1.2 | H49: =VLOOKUP(B49,'[1]26MY_PILOT_DATA'!B:V,11,FALSE) -> 1019.75 | I49: =VLOOKUP($B49,'[1]26MY_PILOT_DATA'!B:V,12,FALSE) -> 0 | J49: =VLOOKUP($B49,'[1]26MY_PILOT_DATA'!B:V,13,FALSE) -> 0 | K49: =VLOOKUP($B49,'[1]26MY_PILOT_DATA'!B:V,14,FALSE) -> 0 | L49: =VLOOKUP(B49,'[1]26MY_PILOT_DATA'!B:V,15,FALSE) -> N/A | M49: =VLOOKUP(B49,'[1]26MY_PILOT_DATA'!B:V,16,FALSE) -> N/A | N49: =VLOOKUP(B49,'[1]26MY_PILOT_DATA'!B:V,17,FALSE) -> • | O49: =VLOOKUP(B49,'[1]26MY_PILOT_DATA'!B:V,18,FALSE) -> N/A | P49: =VLOOKUP(B49,'[1]26MY_PILOT_DATA'!B:V,19,FALSE) -> N/A | Q49: =IF(VLOOKUP(B49,'[1]26MY_PILOT_DATA'!B:V,20,FALSE)="","",VLOOKUP(B49,'[1]26MY_PILOT_DATA'!B:V,20,FALSE)) -> 5% Discount applied ATF Cooler not needed for 26MY Pilot. Towing capacity is 5000lbs. 26PIL-TOW-TS1: 1-7/8" Trailer Hitch Ball 26PIL-TOW-TS2: 2" Trailer Hitch Ball
B50: 08L91-T90-300-TS | C50: =VLOOKUP(B50,'[1]26MY_PILOT_DATA'!B:V,3,FALSE) -> Trailer Hitch Harness - TrailSport | D50: =D42 -> 08L91-T90-300B
B51: 08L92-T90-100A | C51: =VLOOKUP(B51,'[1]26MY_PILOT_DATA'!B:V,3,FALSE) -> Trailer Hitch Ball Mount | D51: =B51 -> 08L92-T90-100A
B52: 08L92-S9V-300G or 08L92-S9V-300H | C52: =VLOOKUP(B52,'[1]26MY_PILOT_DATA'!B:V,3,FALSE) -> Trailer Hitch Ball - 1-7/8" or 2" | D52: =B52 -> 08L92-S9V-300G or 08L92-S9V-300H
B53: 08L92-SJC-300A | C53: =VLOOKUP(B53,'[1]26MY_PILOT_DATA'!B:V,3,FALSE) -> Trailer Hitch Locking Pin | D53: =B53 -> 08L92-SJC-300A
B55: 23PIL-COLD-PK | C55: =VLOOKUP(B55,'[1]26MY_PILOT_DATA'!B:V,3,FALSE) -> Cold Weather Package | D55: =B55 -> 23PIL-COLD-PK | E55: =VLOOKUP($B55,'[1]26MY_PILOT_DATA'!B:V,9,FALSE) -> 224.2 | F55: =VLOOKUP(B55,'[1]26MY_PILOT_DATA'!B:V,10,FALSE) -> 374.3 | G55: =VLOOKUP(B55,'[1]26MY_PILOT_DATA'!B:V,7,FALSE) -> 1.4 | H55: =VLOOKUP(B55,'[1]26MY_PILOT_DATA'!B:V,11,FALSE) -> 605.3 | I55: =VLOOKUP($B55,'[1]26MY_PILOT_DATA'!B:V,12,FALSE) -> 0 | J55: =VLOOKUP($B55,'[1]26MY_PILOT_DATA'!B:V,13,FALSE) -> 0 | K55: =VLOOKUP($B55,'[1]26MY_PILOT_DATA'!B:V,14,FALSE) -> 0 | L55: =VLOOKUP(B55,'[1]26MY_PILOT_DATA'!B:V,15,FALSE) -> • | M55: =VLOOKUP(B55,'[1]26MY_PILOT_DATA'!B:V,16,FALSE) -> • | N55: =VLOOKUP(B55,'[1]26MY_PILOT_DATA'!B:V,17,FALSE) -> • | O55: =VLOOKUP(B55,'[1]26MY_PILOT_DATA'!B:V,18,FALSE) -> • | P55: =VLOOKUP(B55,'[1]26MY_PILOT_DATA'!B:V,19,FALSE) -> • | Q55: =IF(VLOOKUP(B55,'[1]26MY_PILOT_DATA'!B:V,20,FALSE)="","",VLOOKUP(B55,'[1]26MY_PILOT_DATA'!B:V,20,FALSE)) -> 5% Discount Applied
B56: 08T44-SNA-302 | C56: =VLOOKUP(B56,'[1]26MY_PILOT_DATA'!B:V,3,FALSE) -> Engine Block Heater | D56: =B56 -> 08T44-SNA-302
B57: 31670-BMS-004H | C57: =VLOOKUP(B57,'[1]26MY_PILOT_DATA'!B:V,3,FALSE) -> Optimate 12V Auto Battery Charger/Maintainer | D57: =B57 -> 31670-BMS-004H
B59: 26PIL-BLK-EM1 | C59: =VLOOKUP(B59,'[1]26MY_PILOT_DATA'!B:V,3,FALSE) -> Black Emblem Set | D59: =B59 -> 26PIL-BLK-EM1 | E59: =VLOOKUP($B59,'[1]26MY_PILOT_DATA'!B:V,9,FALSE) -> 134.1 | F59: =VLOOKUP(B59,'[1]26MY_PILOT_DATA'!B:V,10,FALSE) -> 223.2 | G59: =VLOOKUP(B59,'[1]26MY_PILOT_DATA'!B:V,7,FALSE) -> 0.7 | H59: =VLOOKUP(B59,'[1]26MY_PILOT_DATA'!B:V,11,FALSE) -> 338.7 | I59: =VLOOKUP($B59,'[1]26MY_PILOT_DATA'!B:V,12,FALSE) -> 0 | J59: =VLOOKUP($B59,'[1]26MY_PILOT_DATA'!B:V,13,FALSE) -> 0 | K59: =VLOOKUP($B59,'[1]26MY_PILOT_DATA'!B:V,14,FALSE) -> 0 | L59: =VLOOKUP(B59,'[1]26MY_PILOT_DATA'!B:V,15,FALSE) -> N/A | M59: =VLOOKUP(B59,'[1]26MY_PILOT_DATA'!B:V,16,FALSE) -> • | N59: =VLOOKUP(B59,'[1]26MY_PILOT_DATA'!B:V,17,FALSE) -> N/A | O59: =VLOOKUP(B59,'[1]26MY_PILOT_DATA'!B:V,18,FALSE) -> N/A | P59: =VLOOKUP(B59,'[1]26MY_PILOT_DATA'!B:V,19,FALSE) -> N/A | Q59: =IF(VLOOKUP(B59,'[1]26MY_PILOT_DATA'!B:V,20,FALSE)="","",VLOOKUP(B59,'[1]26MY_PILOT_DATA'!B:V,20,FALSE)) -> 10% Discount applied
B60: 08F20-T90-100 | C60: =VLOOKUP(B60,'[1]26MY_PILOT_DATA'!B:V,3,FALSE) -> Rear "H" mark | D60: =B60 -> 08F20-T90-100
B61: 08F20-T90-100D | C61: =VLOOKUP(B61,'[1]26MY_PILOT_DATA'!B:V,3,FALSE) -> Pilot | D61: =B61 -> 08F20-T90-100D
B62: 08F20-T90-100A | C62: =VLOOKUP(B62,'[1]26MY_PILOT_DATA'!B:V,3,FALSE) -> Rear "AWD" | D62: =B62 -> 08F20-T90-100A
B64: 26PIL-BLK-EM2 | C64: =VLOOKUP(B64,'[1]26MY_PILOT_DATA'!B:V,3,FALSE) -> Black Emblem Set | D64: =B64 -> 26PIL-BLK-EM2 | E64: =VLOOKUP($B64,'[1]26MY_PILOT_DATA'!B:V,9,FALSE) -> 176.4 | F64: =VLOOKUP(B64,'[1]26MY_PILOT_DATA'!B:V,10,FALSE) -> 293.4 | G64: =VLOOKUP(B64,'[1]26MY_PILOT_DATA'!B:V,7,FALSE) -> 0.8 | H64: =VLOOKUP(B64,'[1]26MY_PILOT_DATA'!B:V,11,FALSE) -> 425.4 | I64: =VLOOKUP($B64,'[1]26MY_PILOT_DATA'!B:V,12,FALSE) -> 0 | J64: =VLOOKUP($B64,'[1]26MY_PILOT_DATA'!B:V,13,FALSE) -> 0 | K64: =VLOOKUP($B64,'[1]26MY_PILOT_DATA'!B:V,14,FALSE) -> 0 | L64: =VLOOKUP(B64,'[1]26MY_PILOT_DATA'!B:V,15,FALSE) -> N/A | M64: =VLOOKUP(B64,'[1]26MY_PILOT_DATA'!B:V,16,FALSE) -> N/A | N64: =VLOOKUP(B64,'[1]26MY_PILOT_DATA'!B:V,17,FALSE) -> N/A | O64: =VLOOKUP(B64,'[1]26MY_PILOT_DATA'!B:V,18,FALSE) -> • | P64: =VLOOKUP(B64,'[1]26MY_PILOT_DATA'!B:V,19,FALSE) -> N/A | Q64: =IF(VLOOKUP(B64,'[1]26MY_PILOT_DATA'!B:V,20,FALSE)="","",VLOOKUP(B64,'[1]26MY_PILOT_DATA'!B:V,20,FALSE)) -> 10% Discount applied
B65: 08F20-T90-100 | C65: =VLOOKUP(B65,'[1]26MY_PILOT_DATA'!B:V,3,FALSE) -> Rear "H" mark | D65: =B65 -> 08F20-T90-100
B66: 08F20-T90-100A | C66: =VLOOKUP(B66,'[1]26MY_PILOT_DATA'!B:V,3,FALSE) -> Rear "AWD" | D66: =B66 -> 08F20-T90-100A
B67: 08F20-T90-100D | C67: =VLOOKUP(B67,'[1]26MY_PILOT_DATA'!B:V,3,FALSE) -> Pilot | D67: =B67 -> 08F20-T90-100D
B68: 08F20-PS2-100A | C68: =VLOOKUP(B68,'[1]26MY_PILOT_DATA'!B:V,3,FALSE) -> Touring | D68: =B68 -> 08F20-PS2-100A
C71: 2.0 Wheels and Wheel Accessories
C72: Description | D72: Part Number | E72: Dealer Net | F72: List Price | G72: FRT | H72: Installed Price | I72: Application | Q72: Comments
I73: ='[1]26MY_PILOT_DATA'!$M$7 -> 0 | J73: ='[1]26MY_PILOT_DATA'!$M$7 -> 0 | K73: ='[1]26MY_PILOT_DATA'!$M$7 -> 0 | L73: ='[1]26MY_PILOT_DATA'!$P$7 -> Sport | M73: ='[1]26MY_PILOT_DATA'!$Q$7 -> EX-L | N73: ='[1]26MY_PILOT_DATA'!$R$7 -> TrailSport | O73: ='[1]26MY_PILOT_DATA'!$S$7 -> Touring | P73: ='[1]26MY_PILOT_DATA'!$T$7 -> Black Edition
B74: 08W18-T90-100D | C74: =VLOOKUP(B74,'[1]26MY_PILOT_DATA'!B:V,3,FALSE) -> 18" Alloy Wheel | D74: =B74 -> 08W18-T90-100D | E74: =VLOOKUP($B74,'[1]26MY_PILOT_DATA'!B:V,9,FALSE) -> 1160 | F74: =VLOOKUP(B74,'[1]26MY_PILOT_DATA'!B:V,10,FALSE) -> 1920 | G74: =VLOOKUP(B74,'[1]26MY_PILOT_DATA'!B:V,7,FALSE) -> 1.6 | H74: =VLOOKUP(B74,'[1]26MY_PILOT_DATA'!B:V,11,FALSE) -> 2184 | I74: =VLOOKUP($B74,'[1]26MY_PILOT_DATA'!B:V,12,FALSE) -> 0 | J74: =VLOOKUP($B74,'[1]26MY_PILOT_DATA'!B:V,13,FALSE) -> 0 | K74: =VLOOKUP($B74,'[1]26MY_PILOT_DATA'!B:V,14,FALSE) -> 0 | L74: =VLOOKUP(B74,'[1]26MY_PILOT_DATA'!B:V,15,FALSE) -> T | M74: =VLOOKUP(B74,'[1]26MY_PILOT_DATA'!B:V,16,FALSE) -> E | N74: =VLOOKUP(B74,'[1]26MY_PILOT_DATA'!B:V,17,FALSE) -> E | O74: =VLOOKUP(B74,'[1]26MY_PILOT_DATA'!B:V,18,FALSE) -> T | P74: =VLOOKUP(B74,'[1]26MY_PILOT_DATA'!B:V,19,FALSE) -> T | Q74: =IF(VLOOKUP(B74,'[1]26MY_PILOT_DATA'!B:V,20,FALSE)="","",VLOOKUP(B74,'[1]26MY_PILOT_DATA'!B:V,20,FALSE))
B75: 08W20-T90-100C | C75: =VLOOKUP(B75,'[1]26MY_PILOT_DATA'!B:V,3,FALSE) -> 20" Alloy Wheel - Gloss Black | D75: =B75 -> 08W20-T90-100C | E75: =VLOOKUP($B75,'[1]26MY_PILOT_DATA'!B:V,9,FALSE) -> 1596 | F75: =VLOOKUP(B75,'[1]26MY_PILOT_DATA'!B:V,10,FALSE) -> 2660 | G75: =VLOOKUP(B75,'[1]26MY_PILOT_DATA'!B:V,7,FALSE) -> 1.6 | H75: =VLOOKUP(B75,'[1]26MY_PILOT_DATA'!B:V,11,FALSE) -> 2924 | I75: =VLOOKUP($B75,'[1]26MY_PILOT_DATA'!B:V,12,FALSE) -> 0 | J75: =VLOOKUP($B75,'[1]26MY_PILOT_DATA'!B:V,13,FALSE) -> 0 | K75: =VLOOKUP($B75,'[1]26MY_PILOT_DATA'!B:V,14,FALSE) -> 0 | L75: =VLOOKUP(B75,'[1]26MY_PILOT_DATA'!B:V,15,FALSE) -> E | M75: =VLOOKUP(B75,'[1]26MY_PILOT_DATA'!B:V,16,FALSE) -> T | N75: =VLOOKUP(B75,'[1]26MY_PILOT_DATA'!B:V,17,FALSE) -> T | O75: =VLOOKUP(B75,'[1]26MY_PILOT_DATA'!B:V,18,FALSE) -> E | P75: =VLOOKUP(B75,'[1]26MY_PILOT_DATA'!B:V,19,FALSE) -> E | Q75: =IF(VLOOKUP(B75,'[1]26MY_PILOT_DATA'!B:V,20,FALSE)="","",VLOOKUP(B75,'[1]26MY_PILOT_DATA'!B:V,20,FALSE))
B76: 08W20-T90-300E | C76: =VLOOKUP(B76,'[1]26MY_PILOT_DATA'!B:V,3,FALSE) -> 20" Alloy Wheel - Matte Black | D76: =B76 -> 08W20-T90-300E | E76: =VLOOKUP($B76,'[1]26MY_PILOT_DATA'!B:V,9,FALSE) -> 1596 | F76: =VLOOKUP(B76,'[1]26MY_PILOT_DATA'!B:V,10,FALSE) -> 2660 | G76: =VLOOKUP(B76,'[1]26MY_PILOT_DATA'!B:V,7,FALSE) -> 1.6 | H76: =VLOOKUP(B76,'[1]26MY_PILOT_DATA'!B:V,11,FALSE) -> 2924 | I76: =VLOOKUP($B76,'[1]26MY_PILOT_DATA'!B:V,12,FALSE) -> 0 | J76: =VLOOKUP($B76,'[1]26MY_PILOT_DATA'!B:V,13,FALSE) -> 0 | K76: =VLOOKUP($B76,'[1]26MY_PILOT_DATA'!B:V,14,FALSE) -> 0 | L76: =VLOOKUP(B76,'[1]26MY_PILOT_DATA'!B:V,15,FALSE) -> E | M76: =VLOOKUP(B76,'[1]26MY_PILOT_DATA'!B:V,16,FALSE) -> T | N76: =VLOOKUP(B76,'[1]26MY_PILOT_DATA'!B:V,17,FALSE) -> T | O76: =VLOOKUP(B76,'[1]26MY_PILOT_DATA'!B:V,18,FALSE) -> E | P76: =VLOOKUP(B76,'[1]26MY_PILOT_DATA'!B:V,19,FALSE) -> E | Q76: =IF(VLOOKUP(B76,'[1]26MY_PILOT_DATA'!B:V,20,FALSE)="","",VLOOKUP(B76,'[1]26MY_PILOT_DATA'!B:V,20,FALSE))
B77: 08W42-TK4-301 | C77: =VLOOKUP(B77,'[1]26MY_PILOT_DATA'!B:V,3,FALSE) -> Wheel Locks - Chrome | D77: =B77 -> 08W42-TK4-301 | E77: =VLOOKUP($B77,'[1]26MY_PILOT_DATA'!B:V,9,FALSE) -> 91 | F77: =VLOOKUP(B77,'[1]26MY_PILOT_DATA'!B:V,10,FALSE) -> 152 | G77: =VLOOKUP(B77,'[1]26MY_PILOT_DATA'!B:V,7,FALSE) -> 0.2 | H77: =VLOOKUP(B77,'[1]26MY_PILOT_DATA'!B:V,11,FALSE) -> 185 | I77: =VLOOKUP($B77,'[1]26MY_PILOT_DATA'!B:V,12,FALSE) -> 0 | J77: =VLOOKUP($B77,'[1]26MY_PILOT_DATA'!B:V,13,FALSE) -> 0 | K77: =VLOOKUP($B77,'[1]26MY_PILOT_DATA'!B:V,14,FALSE) -> 0 | L77: =VLOOKUP(B77,'[1]26MY_PILOT_DATA'!B:V,15,FALSE) -> N/A | M77: =VLOOKUP(B77,'[1]26MY_PILOT_DATA'!B:V,16,FALSE) -> • | N77: =VLOOKUP(B77,'[1]26MY_PILOT_DATA'!B:V,17,FALSE) -> N/A | O77: =VLOOKUP(B77,'[1]26MY_PILOT_DATA'!B:V,18,FALSE) -> N/A | P77: =VLOOKUP(B77,'[1]26MY_PILOT_DATA'!B:V,19,FALSE) -> N/A | Q77: =IF(VLOOKUP(B77,'[1]26MY_PILOT_DATA'!B:V,20,FALSE)="","",VLOOKUP(B77,'[1]26MY_PILOT_DATA'!B:V,20,FALSE))
B78: 08W42-TG7-301A | C78: =VLOOKUP(B78,'[1]26MY_PILOT_DATA'!B:V,3,FALSE) -> Wheel Locks - Black | D78: =B78 -> 08W42-TG7-301A | E78: =VLOOKUP($B78,'[1]26MY_PILOT_DATA'!B:V,9,FALSE) -> 85 | F78: =VLOOKUP(B78,'[1]26MY_PILOT_DATA'!B:V,10,FALSE) -> 140 | G78: =VLOOKUP(B78,'[1]26MY_PILOT_DATA'!B:V,7,FALSE) -> 0.2 | H78: =VLOOKUP(B78,'[1]26MY_PILOT_DATA'!B:V,11,FALSE) -> 173 | I78: =VLOOKUP($B78,'[1]26MY_PILOT_DATA'!B:V,12,FALSE) -> 0 | J78: =VLOOKUP($B78,'[1]26MY_PILOT_DATA'!B:V,13,FALSE) -> 0 | K78: =VLOOKUP($B78,'[1]26MY_PILOT_DATA'!B:V,14,FALSE) -> 0 | L78: =VLOOKUP(B78,'[1]26MY_PILOT_DATA'!B:V,15,FALSE) -> • | M78: =VLOOKUP(B78,'[1]26MY_PILOT_DATA'!B:V,16,FALSE) -> • | N78: =VLOOKUP(B78,'[1]26MY_PILOT_DATA'!B:V,17,FALSE) -> • | O78: =VLOOKUP(B78,'[1]26MY_PILOT_DATA'!B:V,18,FALSE) -> • | P78: =VLOOKUP(B78,'[1]26MY_PILOT_DATA'!B:V,19,FALSE) -> • | Q78: =IF(VLOOKUP(B78,'[1]26MY_PILOT_DATA'!B:V,20,FALSE)="","",VLOOKUP(B78,'[1]26MY_PILOT_DATA'!B:V,20,FALSE))
B79: 08W42-PL4-100A | C79: =VLOOKUP(B79,'[1]26MY_PILOT_DATA'!B:V,3,FALSE) -> Wheel Lug Nuts - Black | D79: =B79 -> 08W42-PL4-100A | E79: =VLOOKUP($B79,'[1]26MY_PILOT_DATA'!B:V,9,FALSE) -> 165 | F79: =VLOOKUP(B79,'[1]26MY_PILOT_DATA'!B:V,10,FALSE) -> 275 | G79: =VLOOKUP(B79,'[1]26MY_PILOT_DATA'!B:V,7,FALSE) -> 0.4 | H79: =VLOOKUP(B79,'[1]26MY_PILOT_DATA'!B:V,11,FALSE) -> 341 | I79: =VLOOKUP($B79,'[1]26MY_PILOT_DATA'!B:V,12,FALSE) -> 0 | J79: =VLOOKUP($B79,'[1]26MY_PILOT_DATA'!B:V,13,FALSE) -> 0 | K79: =VLOOKUP($B79,'[1]26MY_PILOT_DATA'!B:V,14,FALSE) -> 0 | L79: =VLOOKUP(B79,'[1]26MY_PILOT_DATA'!B:V,15,FALSE) -> S | M79: =VLOOKUP(B79,'[1]26MY_PILOT_DATA'!B:V,16,FALSE) -> • | N79: =VLOOKUP(B79,'[1]26MY_PILOT_DATA'!B:V,17,FALSE) -> S | O79: =VLOOKUP(B79,'[1]26MY_PILOT_DATA'!B:V,18,FALSE) -> S | P79: =VLOOKUP(B79,'[1]26MY_PILOT_DATA'!B:V,19,FALSE) -> S | Q79: =IF(VLOOKUP(B79,'[1]26MY_PILOT_DATA'!B:V,20,FALSE)="","",VLOOKUP(B79,'[1]26MY_PILOT_DATA'!B:V,20,FALSE)) -> Set of 20 lug nuts
C81: 3.0 Exterior
C82: Description | D82: Part Number | E82: Dealer Net | F82: List Price | G82: FRT | H82: Installed Price | I82: Application | Q82: Comments
I83: ='[1]26MY_PILOT_DATA'!$M$7 -> 0 | J83: ='[1]26MY_PILOT_DATA'!$M$7 -> 0 | K83: ='[1]26MY_PILOT_DATA'!$M$7 -> 0 | L83: ='[1]26MY_PILOT_DATA'!$P$7 -> Sport | M83: ='[1]26MY_PILOT_DATA'!$Q$7 -> EX-L | N83: ='[1]26MY_PILOT_DATA'!$R$7 -> TrailSport | O83: ='[1]26MY_PILOT_DATA'!$S$7 -> Touring | P83: ='[1]26MY_PILOT_DATA'!$T$7 -> Black Edition
B84: 08F04-T90-100 | C84: =VLOOKUP(B84,'[1]26MY_PILOT_DATA'!B:V,3,FALSE) -> Side Skid Garnish | D84: =B84 -> 08F04-T90-100 | E84: =VLOOKUP($B84,'[1]26MY_PILOT_DATA'!B:V,9,FALSE) -> 324 | F84: =VLOOKUP(B84,'[1]26MY_PILOT_DATA'!B:V,10,FALSE) -> 540 | G84: =VLOOKUP(B84,'[1]26MY_PILOT_DATA'!B:V,7,FALSE) -> 0.6 | H84: =VLOOKUP(B84,'[1]26MY_PILOT_DATA'!B:V,11,FALSE) -> 639 | I84: =VLOOKUP($B84,'[1]26MY_PILOT_DATA'!B:V,12,FALSE) -> 0 | J84: =VLOOKUP($B84,'[1]26MY_PILOT_DATA'!B:V,13,FALSE) -> 0 | K84: =VLOOKUP($B84,'[1]26MY_PILOT_DATA'!B:V,14,FALSE) -> 0 | L84: =VLOOKUP(B84,'[1]26MY_PILOT_DATA'!B:V,15,FALSE) -> • | M84: =VLOOKUP(B84,'[1]26MY_PILOT_DATA'!B:V,16,FALSE) -> • | N84: =VLOOKUP(B84,'[1]26MY_PILOT_DATA'!B:V,17,FALSE) -> • | O84: =VLOOKUP(B84,'[1]26MY_PILOT_DATA'!B:V,18,FALSE) -> • | P84: =VLOOKUP(B84,'[1]26MY_PILOT_DATA'!B:V,19,FALSE) -> • | Q84: =IF(VLOOKUP(B84,'[1]26MY_PILOT_DATA'!B:V,20,FALSE)="","",VLOOKUP(B84,'[1]26MY_PILOT_DATA'!B:V,20,FALSE))
B85: 08F21-T90-100A | C85: =VLOOKUP(B85,'[1]26MY_PILOT_DATA'!B:V,3,FALSE) -> Front Grille Garnish | D85: =B85 -> 08F21-T90-100A | E85: =VLOOKUP($B85,'[1]26MY_PILOT_DATA'!B:V,9,FALSE) -> 247 | F85: =VLOOKUP(B85,'[1]26MY_PILOT_DATA'!B:V,10,FALSE) -> 412 | G85: =VLOOKUP(B85,'[1]26MY_PILOT_DATA'!B:V,7,FALSE) -> 0.2 | H85: =VLOOKUP(B85,'[1]26MY_PILOT_DATA'!B:V,11,FALSE) -> 445 | I85: =VLOOKUP($B85,'[1]26MY_PILOT_DATA'!B:V,12,FALSE) -> 0 | J85: =VLOOKUP($B85,'[1]26MY_PILOT_DATA'!B:V,13,FALSE) -> 0 | K85: =VLOOKUP($B85,'[1]26MY_PILOT_DATA'!B:V,14,FALSE) -> 0 | L85: =VLOOKUP(B85,'[1]26MY_PILOT_DATA'!B:V,15,FALSE) -> S | M85: =VLOOKUP(B85,'[1]26MY_PILOT_DATA'!B:V,16,FALSE) -> • | N85: =VLOOKUP(B85,'[1]26MY_PILOT_DATA'!B:V,17,FALSE) -> S | O85: =VLOOKUP(B85,'[1]26MY_PILOT_DATA'!B:V,18,FALSE) -> • | P85: =VLOOKUP(B85,'[1]26MY_PILOT_DATA'!B:V,19,FALSE) -> S | Q85: =IF(VLOOKUP(B85,'[1]26MY_PILOT_DATA'!B:V,20,FALSE)="","",VLOOKUP(B85,'[1]26MY_PILOT_DATA'!B:V,20,FALSE))
B86: PILOTEMBLEM | C86: =VLOOKUP(B86,'[1]26MY_PILOT_DATA'!B:V,3,FALSE) -> Black Emblems
B87: 08F20-T90-100 | C87: =VLOOKUP(B87,'[1]26MY_PILOT_DATA'!B:V,3,FALSE) -> Rear "H" mark | D87: =B87 -> 08F20-T90-100 | E87: =VLOOKUP($B87,'[1]26MY_PILOT_DATA'!B:V,9,FALSE) -> 41 | F87: =VLOOKUP(B87,'[1]26MY_PILOT_DATA'!B:V,10,FALSE) -> 68 | G87: =VLOOKUP(B87,'[1]26MY_PILOT_DATA'!B:V,7,FALSE) -> 0.2 | H87: =VLOOKUP(B87,'[1]26MY_PILOT_DATA'!B:V,11,FALSE) -> 101 | I87: =VLOOKUP($B87,'[1]26MY_PILOT_DATA'!B:V,12,FALSE) -> 0 | J87: =VLOOKUP($B87,'[1]26MY_PILOT_DATA'!B:V,13,FALSE) -> 0 | K87: =VLOOKUP($B87,'[1]26MY_PILOT_DATA'!B:V,14,FALSE) -> 0 | L87: =VLOOKUP(B87,'[1]26MY_PILOT_DATA'!B:V,15,FALSE) -> • | M87: =VLOOKUP(B87,'[1]26MY_PILOT_DATA'!B:V,16,FALSE) -> • | N87: =VLOOKUP(B87,'[1]26MY_PILOT_DATA'!B:V,17,FALSE) -> • | O87: =VLOOKUP(B87,'[1]26MY_PILOT_DATA'!B:V,18,FALSE) -> • | P87: =VLOOKUP(B87,'[1]26MY_PILOT_DATA'!B:V,19,FALSE) -> • | Q87: =IF(VLOOKUP(B87,'[1]26MY_PILOT_DATA'!B:V,20,FALSE)="","",VLOOKUP(B87,'[1]26MY_PILOT_DATA'!B:V,20,FALSE))
B88: 08F20-T90-100A | C88: =VLOOKUP(B88,'[1]26MY_PILOT_DATA'!B:V,3,FALSE) -> Rear "AWD" | D88: =B88 -> 08F20-T90-100A | E88: =VLOOKUP($B88,'[1]26MY_PILOT_DATA'!B:V,9,FALSE) -> 35 | F88: =VLOOKUP(B88,'[1]26MY_PILOT_DATA'!B:V,10,FALSE) -> 58 | G88: =VLOOKUP(B88,'[1]26MY_PILOT_DATA'!B:V,7,FALSE) -> 0.2 | H88: =VLOOKUP(B88,'[1]26MY_PILOT_DATA'!B:V,11,FALSE) -> 91 | I88: =VLOOKUP($B88,'[1]26MY_PILOT_DATA'!B:V,12,FALSE) -> 0 | J88: =VLOOKUP($B88,'[1]26MY_PILOT_DATA'!B:V,13,FALSE) -> 0 | K88: =VLOOKUP($B88,'[1]26MY_PILOT_DATA'!B:V,14,FALSE) -> 0 | L88: =VLOOKUP(B88,'[1]26MY_PILOT_DATA'!B:V,15,FALSE) -> N/A | M88: =VLOOKUP(B88,'[1]26MY_PILOT_DATA'!B:V,16,FALSE) -> • | N88: =VLOOKUP(B88,'[1]26MY_PILOT_DATA'!B:V,17,FALSE) -> • | O88: =VLOOKUP(B88,'[1]26MY_PILOT_DATA'!B:V,18,FALSE) -> • | P88: =VLOOKUP(B88,'[1]26MY_PILOT_DATA'!B:V,19,FALSE) -> • | Q88: =IF(VLOOKUP(B88,'[1]26MY_PILOT_DATA'!B:V,20,FALSE)="","",VLOOKUP(B88,'[1]26MY_PILOT_DATA'!B:V,20,FALSE))
B89: 08F20-T90-100D | C89: =VLOOKUP(B89,'[1]26MY_PILOT_DATA'!B:V,3,FALSE) -> Pilot | D89: =B89 -> 08F20-T90-100D | E89: =VLOOKUP($B89,'[1]26MY_PILOT_DATA'!B:V,9,FALSE) -> 73 | F89: =VLOOKUP(B89,'[1]26MY_PILOT_DATA'!B:V,10,FALSE) -> 122 | G89: =VLOOKUP(B89,'[1]26MY_PILOT_DATA'!B:V,7,FALSE) -> 0.3 | H89: =VLOOKUP(B89,'[1]26MY_PILOT_DATA'!B:V,11,FALSE) -> 171.5 | I89: =VLOOKUP($B89,'[1]26MY_PILOT_DATA'!B:V,12,FALSE) -> 0 | J89: =VLOOKUP($B89,'[1]26MY_PILOT_DATA'!B:V,13,FALSE) -> 0 | K89: =VLOOKUP($B89,'[1]26MY_PILOT_DATA'!B:V,14,FALSE) -> 0 | L89: =VLOOKUP(B89,'[1]26MY_PILOT_DATA'!B:V,15,FALSE) -> • | M89: =VLOOKUP(B89,'[1]26MY_PILOT_DATA'!B:V,16,FALSE) -> • | N89: =VLOOKUP(B89,'[1]26MY_PILOT_DATA'!B:V,17,FALSE) -> • | O89: =VLOOKUP(B89,'[1]26MY_PILOT_DATA'!B:V,18,FALSE) -> • | P89: =VLOOKUP(B89,'[1]26MY_PILOT_DATA'!B:V,19,FALSE) -> • | Q89: =IF(VLOOKUP(B89,'[1]26MY_PILOT_DATA'!B:V,20,FALSE)="","",VLOOKUP(B89,'[1]26MY_PILOT_DATA'!B:V,20,FALSE))
B90: 08F20-PS2-100A | C90: =VLOOKUP(B90,'[1]26MY_PILOT_DATA'!B:V,3,FALSE) -> Touring | D90: =B90 -> 08F20-PS2-100A | E90: =VLOOKUP($B90,'[1]26MY_PILOT_DATA'!B:V,9,FALSE) -> 47 | F90: =VLOOKUP(B90,'[1]26MY_PILOT_DATA'!B:V,10,FALSE) -> 78 | G90: =VLOOKUP(B90,'[1]26MY_PILOT_DATA'!B:V,7,FALSE) -> 0.1 | H90: =VLOOKUP(B90,'[1]26MY_PILOT_DATA'!B:V,11,FALSE) -> 94.5 | I90: =VLOOKUP($B90,'[1]26MY_PILOT_DATA'!B:V,12,FALSE) -> 0 | J90: =VLOOKUP($B90,'[1]26MY_PILOT_DATA'!B:V,13,FALSE) -> 0 | K90: =VLOOKUP($B90,'[1]26MY_PILOT_DATA'!B:V,14,FALSE) -> 0 | L90: =VLOOKUP(B90,'[1]26MY_PILOT_DATA'!B:V,15,FALSE) -> N/A | M90: =VLOOKUP(B90,'[1]26MY_PILOT_DATA'!B:V,16,FALSE) -> N/A | N90: =VLOOKUP(B90,'[1]26MY_PILOT_DATA'!B:V,17,FALSE) -> N/A | O90: =VLOOKUP(B90,'[1]26MY_PILOT_DATA'!B:V,18,FALSE) -> • | P90: =VLOOKUP(B90,'[1]26MY_PILOT_DATA'!B:V,19,FALSE) -> N/A | Q90: =IF(VLOOKUP(B90,'[1]26MY_PILOT_DATA'!B:V,20,FALSE)="","",VLOOKUP(B90,'[1]26MY_PILOT_DATA'!B:V,20,FALSE))
B91: 08L33-T90-100 | C91: =VLOOKUP(B91,'[1]26MY_PILOT_DATA'!B:V,3,FALSE) -> Running Boards Traditional | D91: =B91 -> 08L33-T90-100 | E91: =VLOOKUP($B91,'[1]26MY_PILOT_DATA'!B:V,9,FALSE) -> 743 | F91: =VLOOKUP(B91,'[1]26MY_PILOT_DATA'!B:V,10,FALSE) -> 1061 | G91: =VLOOKUP(B91,'[1]26MY_PILOT_DATA'!B:V,7,FALSE) -> 0.7 | H91: =VLOOKUP(B91,'[1]26MY_PILOT_DATA'!B:V,11,FALSE) -> 1176.5 | I91: =VLOOKUP($B91,'[1]26MY_PILOT_DATA'!B:V,12,FALSE) -> 0 | J91: =VLOOKUP($B91,'[1]26MY_PILOT_DATA'!B:V,13,FALSE) -> 0 | K91: =VLOOKUP($B91,'[1]26MY_PILOT_DATA'!B:V,14,FALSE) -> 0 | L91: =VLOOKUP(B91,'[1]26MY_PILOT_DATA'!B:V,15,FALSE) -> • | M91: =VLOOKUP(B91,'[1]26MY_PILOT_DATA'!B:V,16,FALSE) -> • | N91: =VLOOKUP(B91,'[1]26MY_PILOT_DATA'!B:V,17,FALSE) -> • | O91: =VLOOKUP(B91,'[1]26MY_PILOT_DATA'!B:V,18,FALSE) -> • | P91: =VLOOKUP(B91,'[1]26MY_PILOT_DATA'!B:V,19,FALSE) -> • | Q91: =IF(VLOOKUP(B91,'[1]26MY_PILOT_DATA'!B:V,20,FALSE)="","",VLOOKUP(B91,'[1]26MY_PILOT_DATA'!B:V,20,FALSE))
B92: 08L33-T90-100B | C92: =VLOOKUP(B92,'[1]26MY_PILOT_DATA'!B:V,3,FALSE) -> Running Boards Rugged | D92: =B92 -> 08L33-T90-100B | E92: =VLOOKUP($B92,'[1]26MY_PILOT_DATA'!B:V,9,FALSE) -> 936 | F92: =VLOOKUP(B92,'[1]26MY_PILOT_DATA'!B:V,10,FALSE) -> 1337 | G92: =VLOOKUP(B92,'[1]26MY_PILOT_DATA'!B:V,7,FALSE) -> 0.7 | H92: =VLOOKUP(B92,'[1]26MY_PILOT_DATA'!B:V,11,FALSE) -> 1452.5 | I92: =VLOOKUP($B92,'[1]26MY_PILOT_DATA'!B:V,12,FALSE) -> 0 | J92: =VLOOKUP($B92,'[1]26MY_PILOT_DATA'!B:V,13,FALSE) -> 0 | K92: =VLOOKUP($B92,'[1]26MY_PILOT_DATA'!B:V,14,FALSE) -> 0 | L92: =VLOOKUP(B92,'[1]26MY_PILOT_DATA'!B:V,15,FALSE) -> • | M92: =VLOOKUP(B92,'[1]26MY_PILOT_DATA'!B:V,16,FALSE) -> • | N92: =VLOOKUP(B92,'[1]26MY_PILOT_DATA'!B:V,17,FALSE) -> • | O92: =VLOOKUP(B92,'[1]26MY_PILOT_DATA'!B:V,18,FALSE) -> • | P92: =VLOOKUP(B92,'[1]26MY_PILOT_DATA'!B:V,19,FALSE) -> • | Q92: =IF(VLOOKUP(B92,'[1]26MY_PILOT_DATA'!B:V,20,FALSE)="","",VLOOKUP(B92,'[1]26MY_PILOT_DATA'!B:V,20,FALSE))
B93: 08P21-T90-100 | C93: =VLOOKUP(B93,'[1]26MY_PILOT_DATA'!B:V,3,FALSE) -> Fender Flares | D93: =B93 -> 08P21-T90-100 | E93: =VLOOKUP($B93,'[1]26MY_PILOT_DATA'!B:V,9,FALSE) -> 550 | F93: =VLOOKUP(B93,'[1]26MY_PILOT_DATA'!B:V,10,FALSE) -> 917 | G93: =VLOOKUP(B93,'[1]26MY_PILOT_DATA'!B:V,7,FALSE) -> 1 | H93: =VLOOKUP(B93,'[1]26MY_PILOT_DATA'!B:V,11,FALSE) -> 1082 | I93: =VLOOKUP($B93,'[1]26MY_PILOT_DATA'!B:V,12,FALSE) -> 0 | J93: =VLOOKUP($B93,'[1]26MY_PILOT_DATA'!B:V,13,FALSE) -> 0 | K93: =VLOOKUP($B93,'[1]26MY_PILOT_DATA'!B:V,14,FALSE) -> 0 | L93: =VLOOKUP(B93,'[1]26MY_PILOT_DATA'!B:V,15,FALSE) -> • | M93: =VLOOKUP(B93,'[1]26MY_PILOT_DATA'!B:V,16,FALSE) -> • | N93: =VLOOKUP(B93,'[1]26MY_PILOT_DATA'!B:V,17,FALSE) -> • | O93: =VLOOKUP(B93,'[1]26MY_PILOT_DATA'!B:V,18,FALSE) -> • | P93: =VLOOKUP(B93,'[1]26MY_PILOT_DATA'!B:V,19,FALSE) -> • | Q93: =IF(VLOOKUP(B93,'[1]26MY_PILOT_DATA'!B:V,20,FALSE)="","",VLOOKUP(B93,'[1]26MY_PILOT_DATA'!B:V,20,FALSE)) -> Replaces Splash Guards and cannot be installed with Door Edge Film
B94: 08R04-T90-100 | C94: =VLOOKUP(B94,'[1]26MY_PILOT_DATA'!B:V,3,FALSE) -> Door Visor | D94: =B94 -> 08R04-T90-100 | E94: =VLOOKUP($B94,'[1]26MY_PILOT_DATA'!B:V,9,FALSE) -> 258 | F94: =VLOOKUP(B94,'[1]26MY_PILOT_DATA'!B:V,10,FALSE) -> 430 | G94: =VLOOKUP(B94,'[1]26MY_PILOT_DATA'!B:V,7,FALSE) -> 0.6 | H94: =VLOOKUP(B94,'[1]26MY_PILOT_DATA'!B:V,11,FALSE) -> 529 | I94: =VLOOKUP($B94,'[1]26MY_PILOT_DATA'!B:V,12,FALSE) -> 0 | J94: =VLOOKUP($B94,'[1]26MY_PILOT_DATA'!B:V,13,FALSE) -> 0 | K94: =VLOOKUP($B94,'[1]26MY_PILOT_DATA'!B:V,14,FALSE) -> 0 | L94: =VLOOKUP(B94,'[1]26MY_PILOT_DATA'!B:V,15,FALSE) -> • | M94: =VLOOKUP(B94,'[1]26MY_PILOT_DATA'!B:V,16,FALSE) -> • | N94: =VLOOKUP(B94,'[1]26MY_PILOT_DATA'!B:V,17,FALSE) -> • | O94: =VLOOKUP(B94,'[1]26MY_PILOT_DATA'!B:V,18,FALSE) -> • | P94: =VLOOKUP(B94,'[1]26MY_PILOT_DATA'!B:V,19,FALSE) -> • | Q94: =IF(VLOOKUP(B94,'[1]26MY_PILOT_DATA'!B:V,20,FALSE)="","",VLOOKUP(B94,'[1]26MY_PILOT_DATA'!B:V,20,FALSE))
B95: 08L91-T90-XXXX | C95: =VLOOKUP(B95,'[1]26MY_PILOT_DATA'!B:V,3,FALSE) -> Trailer Hitch parts
B96: 08L92-T90-100 | C96: =VLOOKUP(B96,'[1]26MY_PILOT_DATA'!B:V,3,FALSE) -> Trailer Hitch | D96: =B96 -> 08L92-T90-100 | E96: =VLOOKUP($B96,'[1]26MY_PILOT_DATA'!B:V,9,FALSE) -> 432 | F96: =VLOOKUP(B96,'[1]26MY_PILOT_DATA'!B:V,10,FALSE) -> 720 | G96: =VLOOKUP(B96,'[1]26MY_PILOT_DATA'!B:V,7,FALSE) -> 1.2 | H96: =VLOOKUP(B96,'[1]26MY_PILOT_DATA'!B:V,11,FALSE) -> 918 | I96: =VLOOKUP($B96,'[1]26MY_PILOT_DATA'!B:V,12,FALSE) -> 0 | J96: =VLOOKUP($B96,'[1]26MY_PILOT_DATA'!B:V,13,FALSE) -> 0 | K96: =VLOOKUP($B96,'[1]26MY_PILOT_DATA'!B:V,14,FALSE) -> 0 | L96: =VLOOKUP(B96,'[1]26MY_PILOT_DATA'!B:V,15,FALSE) -> • | M96: =VLOOKUP(B96,'[1]26MY_PILOT_DATA'!B:V,16,FALSE) -> • | N96: =VLOOKUP(B96,'[1]26MY_PILOT_DATA'!B:V,17,FALSE) -> S | O96: =VLOOKUP(B96,'[1]26MY_PILOT_DATA'!B:V,18,FALSE) -> • | P96: =VLOOKUP(B96,'[1]26MY_PILOT_DATA'!B:V,19,FALSE) -> • | Q96: =IF(VLOOKUP(B96,'[1]26MY_PILOT_DATA'!B:V,20,FALSE)="","",VLOOKUP(B96,'[1]26MY_PILOT_DATA'!B:V,20,FALSE)) -> ATF Cooler not needed for 23MY Pilot. Towing capacity is 5000lbs. Requires Trailer Hitch Panel - 08L92-T90-300B/C Touring & Black Edition also requires HFA Adapter - 08L91-T90-300A
B97: 08L91-T90-300B | C97: =VLOOKUP(B97,'[1]26MY_PILOT_DATA'!B:V,3,FALSE) -> Trailer Hitch Harness | D97: =B97 -> 08L91-T90-300B | E97: =VLOOKUP($B97,'[1]26MY_PILOT_DATA'!B:V,9,FALSE) -> 336 | F97: =VLOOKUP(B97,'[1]26MY_PILOT_DATA'!B:V,10,FALSE) -> 560 | G97: =VLOOKUP(B97,'[1]26MY_PILOT_DATA'!B:V,7,FALSE) -> 0.6 | H97: =VLOOKUP(B97,'[1]26MY_PILOT_DATA'!B:V,11,FALSE) -> 659 | I97: =VLOOKUP($B97,'[1]26MY_PILOT_DATA'!B:V,12,FALSE) -> 0 | J97: =VLOOKUP($B97,'[1]26MY_PILOT_DATA'!B:V,13,FALSE) -> 0 | K97: =VLOOKUP($B97,'[1]26MY_PILOT_DATA'!B:V,14,FALSE) -> 0 | L97: =VLOOKUP(B97,'[1]26MY_PILOT_DATA'!B:V,15,FALSE) -> • | M97: =VLOOKUP(B97,'[1]26MY_PILOT_DATA'!B:V,16,FALSE) -> • | N97: =VLOOKUP(B97,'[1]26MY_PILOT_DATA'!B:V,17,FALSE) -> • | O97: =VLOOKUP(B97,'[1]26MY_PILOT_DATA'!B:V,18,FALSE) -> • | P97: =VLOOKUP(B97,'[1]26MY_PILOT_DATA'!B:V,19,FALSE) -> • | Q97: =IF(VLOOKUP(B97,'[1]26MY_PILOT_DATA'!B:V,20,FALSE)="","",VLOOKUP(B97,'[1]26MY_PILOT_DATA'!B:V,20,FALSE))
B98: 08L91-T90-300-TS | C98: =VLOOKUP(B98,'[1]26MY_PILOT_DATA'!B:V,3,FALSE) -> Trailer Hitch Harness - TrailSport | D98: =D97 -> 08L91-T90-300B | E98: =VLOOKUP($B98,'[1]26MY_PILOT_DATA'!B:V,9,FALSE) -> 336 | F98: =VLOOKUP(B97,'[1]26MY_PILOT_DATA'!B:V,10,FALSE) -> 560 | G98: =VLOOKUP(B98,'[1]26MY_PILOT_DATA'!B:V,7,FALSE) -> 1.2 | H98: =VLOOKUP(B98,'[1]26MY_PILOT_DATA'!B:V,11,FALSE) -> 758 | I98: =VLOOKUP($B98,'[1]26MY_PILOT_DATA'!B:V,12,FALSE) -> 0 | J98: =VLOOKUP($B98,'[1]26MY_PILOT_DATA'!B:V,13,FALSE) -> 0 | K98: =VLOOKUP($B98,'[1]26MY_PILOT_DATA'!B:V,14,FALSE) -> 0 | L98: =VLOOKUP(B98,'[1]26MY_PILOT_DATA'!B:V,15,FALSE) -> N/A | M98: =VLOOKUP(B98,'[1]26MY_PILOT_DATA'!B:V,16,FALSE) -> N/A | N98: =VLOOKUP(B98,'[1]26MY_PILOT_DATA'!B:V,17,FALSE) -> • | O98: =VLOOKUP(B98,'[1]26MY_PILOT_DATA'!B:V,18,FALSE) -> N/A | P98: =VLOOKUP(B98,'[1]26MY_PILOT_DATA'!B:V,19,FALSE) -> N/A | Q98: =IF(VLOOKUP(B98,'[1]26MY_PILOT_DATA'!B:V,20,FALSE)="","",VLOOKUP(B98,'[1]26MY_PILOT_DATA'!B:V,20,FALSE)) -> Longer FRT for TrailSport trim due to standard Trailer Hitch.
B99: 08L92-T90-300D | C99: =VLOOKUP(B99,'[1]26MY_PILOT_DATA'!B:V,3,FALSE) -> Trailer Hitch Panel Black | D99: =B99 -> 08L92-T90-300D | E99: =VLOOKUP($B99,'[1]26MY_PILOT_DATA'!B:V,9,FALSE) -> 150 | F99: =VLOOKUP(B99,'[1]26MY_PILOT_DATA'!B:V,10,FALSE) -> 250 | G99: =VLOOKUP(B99,'[1]26MY_PILOT_DATA'!B:V,7,FALSE) -> 0 | H99: =VLOOKUP(B99,'[1]26MY_PILOT_DATA'!B:V,11,FALSE) -> 250 | I99: =VLOOKUP($B99,'[1]26MY_PILOT_DATA'!B:V,12,FALSE) -> 0 | J99: =VLOOKUP($B99,'[1]26MY_PILOT_DATA'!B:V,13,FALSE) -> 0 | K99: =VLOOKUP($B99,'[1]26MY_PILOT_DATA'!B:V,14,FALSE) -> 0 | L99: =VLOOKUP(B99,'[1]26MY_PILOT_DATA'!B:V,15,FALSE) -> • | M99: =VLOOKUP(B99,'[1]26MY_PILOT_DATA'!B:V,16,FALSE) -> N/A | N99: =VLOOKUP(B99,'[1]26MY_PILOT_DATA'!B:V,17,FALSE) -> S | O99: =VLOOKUP(B99,'[1]26MY_PILOT_DATA'!B:V,18,FALSE) -> N/A | P99: =VLOOKUP(B99,'[1]26MY_PILOT_DATA'!B:V,19,FALSE) -> • | Q99: =IF(VLOOKUP(B99,'[1]26MY_PILOT_DATA'!B:V,20,FALSE)="","",VLOOKUP(B99,'[1]26MY_PILOT_DATA'!B:V,20,FALSE)) -> Required for Trailer Hitch - 08L92-T90-100
B100: 08L92-T90-300E | C100: =VLOOKUP(B100,'[1]26MY_PILOT_DATA'!B:V,3,FALSE) -> Trailer Hitch Panel Silver | D100: =B100 -> 08L92-T90-300E | E100: =VLOOKUP($B100,'[1]26MY_PILOT_DATA'!B:V,9,FALSE) -> 150 | F100: =VLOOKUP(B100,'[1]26MY_PILOT_DATA'!B:V,10,FALSE) -> 250 | G100: =VLOOKUP(B100,'[1]26MY_PILOT_DATA'!B:V,7,FALSE) -> 0 | H100: =VLOOKUP(B100,'[1]26MY_PILOT_DATA'!B:V,11,FALSE) -> 250 | I100: =VLOOKUP($B100,'[1]26MY_PILOT_DATA'!B:V,12,FALSE) -> 0 | J100: =VLOOKUP($B100,'[1]26MY_PILOT_DATA'!B:V,13,FALSE) -> 0 | K100: =VLOOKUP($B100,'[1]26MY_PILOT_DATA'!B:V,14,FALSE) -> 0 | L100: =VLOOKUP(B100,'[1]26MY_PILOT_DATA'!B:V,15,FALSE) -> N/A | M100: =VLOOKUP(B100,'[1]26MY_PILOT_DATA'!B:V,16,FALSE) -> • | N100: =VLOOKUP(B100,'[1]26MY_PILOT_DATA'!B:V,17,FALSE) -> S | O100: =VLOOKUP(B100,'[1]26MY_PILOT_DATA'!B:V,18,FALSE) -> • | P100: =VLOOKUP(B100,'[1]26MY_PILOT_DATA'!B:V,19,FALSE) -> N/A | Q100: =IF(VLOOKUP(B100,'[1]26MY_PILOT_DATA'!B:V,20,FALSE)="","",VLOOKUP(B100,'[1]26MY_PILOT_DATA'!B:V,20,FALSE))
B101: 08L92-T90-100A | C101: =VLOOKUP(B101,'[1]26MY_PILOT_DATA'!B:V,3,FALSE) -> Trailer Hitch Ball Mount | D101: =B101 -> 08L92-T90-100A | E101: =VLOOKUP($B101,'[1]26MY_PILOT_DATA'!B:V,9,FALSE) -> 57 | F101: =VLOOKUP(B101,'[1]26MY_PILOT_DATA'!B:V,10,FALSE) -> 95 | G101: =VLOOKUP(B101,'[1]26MY_PILOT_DATA'!B:V,7,FALSE) -> 0 | H101: =VLOOKUP(B101,'[1]26MY_PILOT_DATA'!B:V,11,FALSE) -> 95 | I101: =VLOOKUP($B101,'[1]26MY_PILOT_DATA'!B:V,12,FALSE) -> 0 | J101: =VLOOKUP($B101,'[1]26MY_PILOT_DATA'!B:V,13,FALSE) -> 0 | K101: =VLOOKUP($B101,'[1]26MY_PILOT_DATA'!B:V,14,FALSE) -> 0 | L101: =VLOOKUP(B101,'[1]26MY_PILOT_DATA'!B:V,15,FALSE) -> • | M101: =VLOOKUP(B101,'[1]26MY_PILOT_DATA'!B:V,16,FALSE) -> • | N101: =VLOOKUP(B101,'[1]26MY_PILOT_DATA'!B:V,17,FALSE) -> • | O101: =VLOOKUP(B101,'[1]26MY_PILOT_DATA'!B:V,18,FALSE) -> • | P101: =VLOOKUP(B101,'[1]26MY_PILOT_DATA'!B:V,19,FALSE) -> • | Q101: =IF(VLOOKUP(B101,'[1]26MY_PILOT_DATA'!B:V,20,FALSE)="","",VLOOKUP(B101,'[1]26MY_PILOT_DATA'!B:V,20,FALSE))
B102: 08L92-S9V-300G | C102: =VLOOKUP(B102,'[1]26MY_PILOT_DATA'!B:V,3,FALSE) -> Trailer Hitch Ball - 1-7/8" | D102: =B102 -> 08L92-S9V-300G | E102: =VLOOKUP($B102,'[1]26MY_PILOT_DATA'!B:V,9,FALSE) -> 28 | F102: =VLOOKUP(B102,'[1]26MY_PILOT_DATA'!B:V,10,FALSE) -> 47 | G102: =VLOOKUP(B102,'[1]26MY_PILOT_DATA'!B:V,7,FALSE) -> 0 | H102: =VLOOKUP(B102,'[1]26MY_PILOT_DATA'!B:V,11,FALSE) -> 47 | I102: =VLOOKUP($B102,'[1]26MY_PILOT_DATA'!B:V,12,FALSE) -> 0 | J102: =VLOOKUP($B102,'[1]26MY_PILOT_DATA'!B:V,13,FALSE) -> 0 | K102: =VLOOKUP($B102,'[1]26MY_PILOT_DATA'!B:V,14,FALSE) -> 0 | L102: =VLOOKUP(B102,'[1]26MY_PILOT_DATA'!B:V,15,FALSE) -> • | M102: =VLOOKUP(B102,'[1]26MY_PILOT_DATA'!B:V,16,FALSE) -> • | N102: =VLOOKUP(B102,'[1]26MY_PILOT_DATA'!B:V,17,FALSE) -> • | O102: =VLOOKUP(B102,'[1]26MY_PILOT_DATA'!B:V,18,FALSE) -> • | P102: =VLOOKUP(B102,'[1]26MY_PILOT_DATA'!B:V,19,FALSE) -> • | Q102: =IF(VLOOKUP(B102,'[1]26MY_PILOT_DATA'!B:V,20,FALSE)="","",VLOOKUP(B102,'[1]26MY_PILOT_DATA'!B:V,20,FALSE))
B103: 08L92-S9V-300H | C103: =VLOOKUP(B103,'[1]26MY_PILOT_DATA'!B:V,3,FALSE) -> Trailer Hitch Ball - 2" | D103: =B103 -> 08L92-S9V-300H | E103: =VLOOKUP($B103,'[1]26MY_PILOT_DATA'!B:V,9,FALSE) -> 28 | F103: =VLOOKUP(B103,'[1]26MY_PILOT_DATA'!B:V,10,FALSE) -> 47 | G103: =VLOOKUP(B103,'[1]26MY_PILOT_DATA'!B:V,7,FALSE) -> 0 | H103: =VLOOKUP(B103,'[1]26MY_PILOT_DATA'!B:V,11,FALSE) -> 47 | I103: =VLOOKUP($B103,'[1]26MY_PILOT_DATA'!B:V,12,FALSE) -> 0 | J103: =VLOOKUP($B103,'[1]26MY_PILOT_DATA'!B:V,13,FALSE) -> 0 | K103: =VLOOKUP($B103,'[1]26MY_PILOT_DATA'!B:V,14,FALSE) -> 0 | L103: =VLOOKUP(B103,'[1]26MY_PILOT_DATA'!B:V,15,FALSE) -> • | M103: =VLOOKUP(B103,'[1]26MY_PILOT_DATA'!B:V,16,FALSE) -> • | N103: =VLOOKUP(B103,'[1]26MY_PILOT_DATA'!B:V,17,FALSE) -> • | O103: =VLOOKUP(B103,'[1]26MY_PILOT_DATA'!B:V,18,FALSE) -> • | P103: =VLOOKUP(B103,'[1]26MY_PILOT_DATA'!B:V,19,FALSE) -> • | Q103: =IF(VLOOKUP(B103,'[1]26MY_PILOT_DATA'!B:V,20,FALSE)="","",VLOOKUP(B103,'[1]26MY_PILOT_DATA'!B:V,20,FALSE))
B104: 08L92-SJC-300A | C104: =VLOOKUP(B104,'[1]26MY_PILOT_DATA'!B:V,3,FALSE) -> Trailer Hitch Locking Pin | D104: =B104 -> 08L92-SJC-300A | E104: =VLOOKUP($B104,'[1]26MY_PILOT_DATA'!B:V,9,FALSE) -> 106 | F104: =VLOOKUP(B104,'[1]26MY_PILOT_DATA'!B:V,10,FALSE) -> 163 | G104: =VLOOKUP(B104,'[1]26MY_PILOT_DATA'!B:V,7,FALSE) -> 0 | H104: =VLOOKUP(B104,'[1]26MY_PILOT_DATA'!B:V,11,FALSE) -> 163 | I104: =VLOOKUP($B104,'[1]26MY_PILOT_DATA'!B:V,12,FALSE) -> 0 | J104: =VLOOKUP($B104,'[1]26MY_PILOT_DATA'!B:V,13,FALSE) -> 0 | K104: =VLOOKUP($B104,'[1]26MY_PILOT_DATA'!B:V,14,FALSE) -> 0 | L104: =VLOOKUP(B104,'[1]26MY_PILOT_DATA'!B:V,15,FALSE) -> • | M104: =VLOOKUP(B104,'[1]26MY_PILOT_DATA'!B:V,16,FALSE) -> • | N104: =VLOOKUP(B104,'[1]26MY_PILOT_DATA'!B:V,17,FALSE) -> • | O104: =VLOOKUP(B104,'[1]26MY_PILOT_DATA'!B:V,18,FALSE) -> • | P104: =VLOOKUP(B104,'[1]26MY_PILOT_DATA'!B:V,19,FALSE) -> • | Q104: =IF(VLOOKUP(B104,'[1]26MY_PILOT_DATA'!B:V,20,FALSE)="","",VLOOKUP(B104,'[1]26MY_PILOT_DATA'!B:V,20,FALSE))
B105: 08L04-T90-300 | C105: =VLOOKUP(B105,'[1]26MY_PILOT_DATA'!B:V,3,FALSE) -> Crossbars | D105: =B105 -> 08L04-T90-300 | E105: =VLOOKUP($B105,'[1]26MY_PILOT_DATA'!B:V,9,FALSE) -> 246 | F105: =VLOOKUP(B105,'[1]26MY_PILOT_DATA'!B:V,10,FALSE) -> 410 | G105: =VLOOKUP(B105,'[1]26MY_PILOT_DATA'!B:V,7,FALSE) -> 0.2 | H105: =VLOOKUP(B105,'[1]26MY_PILOT_DATA'!B:V,11,FALSE) -> 443 | I105: =VLOOKUP($B105,'[1]26MY_PILOT_DATA'!B:V,12,FALSE) -> 0 | J105: =VLOOKUP($B105,'[1]26MY_PILOT_DATA'!B:V,13,FALSE) -> 0 | K105: =VLOOKUP($B105,'[1]26MY_PILOT_DATA'!B:V,14,FALSE) -> 0 | L105: =VLOOKUP(B105,'[1]26MY_PILOT_DATA'!B:V,15,FALSE) -> • | M105: =VLOOKUP(B105,'[1]26MY_PILOT_DATA'!B:V,16,FALSE) -> • | N105: =VLOOKUP(B105,'[1]26MY_PILOT_DATA'!B:V,17,FALSE) -> • | O105: =VLOOKUP(B105,'[1]26MY_PILOT_DATA'!B:V,18,FALSE) -> • | P105: =VLOOKUP(B105,'[1]26MY_PILOT_DATA'!B:V,19,FALSE) -> • | Q105: =IF(VLOOKUP(B105,'[1]26MY_PILOT_DATA'!B:V,20,FALSE)="","",VLOOKUP(B105,'[1]26MY_PILOT_DATA'!B:V,20,FALSE))
B106: 08LXX-E09-XXXX | C106: =VLOOKUP(B106,'[1]26MY_PILOT_DATA'!B:V,3,FALSE) -> Roof Attachments
B107: 08L03-E09-300C | C107: =VLOOKUP(B107,'[1]26MY_PILOT_DATA'!B:V,3,FALSE) -> Roof Ski/Snowboard Attachment | D107: =B107 -> 08L03-E09-300C | E107: =VLOOKUP($B107,'[1]26MY_PILOT_DATA'!B:V,9,FALSE) -> 415 | F107: =VLOOKUP(B107,'[1]26MY_PILOT_DATA'!B:V,10,FALSE) -> 692 | G107: =VLOOKUP(B107,'[1]26MY_PILOT_DATA'!B:V,7,FALSE) -> 0.2 | H107: =VLOOKUP(B107,'[1]26MY_PILOT_DATA'!B:V,11,FALSE) -> 725 | I107: =VLOOKUP($B107,'[1]26MY_PILOT_DATA'!B:V,12,FALSE) -> 0 | J107: =VLOOKUP($B107,'[1]26MY_PILOT_DATA'!B:V,13,FALSE) -> 0 | K107: =VLOOKUP($B107,'[1]26MY_PILOT_DATA'!B:V,14,FALSE) -> 0 | L107: =VLOOKUP(B107,'[1]26MY_PILOT_DATA'!B:V,15,FALSE) -> • | M107: =VLOOKUP(B107,'[1]26MY_PILOT_DATA'!B:V,16,FALSE) -> • | N107: =VLOOKUP(B107,'[1]26MY_PILOT_DATA'!B:V,17,FALSE) -> • | O107: =VLOOKUP(B107,'[1]26MY_PILOT_DATA'!B:V,18,FALSE) -> • | P107: =VLOOKUP(B107,'[1]26MY_PILOT_DATA'!B:V,19,FALSE) -> • | Q107: =IF(VLOOKUP(B107,'[1]26MY_PILOT_DATA'!B:V,20,FALSE)="","",VLOOKUP(B107,'[1]26MY_PILOT_DATA'!B:V,20,FALSE)) -> Requires Roof Rails & Crossbars.
B108: 08L07-E09-101 | C108: =VLOOKUP(B108,'[1]26MY_PILOT_DATA'!B:V,3,FALSE) -> Roof Bicycle Attachment - Frame mount | D108: =B108 -> 08L07-E09-101 | E108: =VLOOKUP($B108,'[1]26MY_PILOT_DATA'!B:V,9,FALSE) -> 383 | F108: =VLOOKUP(B108,'[1]26MY_PILOT_DATA'!B:V,10,FALSE) -> 547 | G108: =VLOOKUP(B108,'[1]26MY_PILOT_DATA'!B:V,7,FALSE) -> 0.4 | H108: =VLOOKUP(B108,'[1]26MY_PILOT_DATA'!B:V,11,FALSE) -> 613 | I108: =VLOOKUP($B108,'[1]26MY_PILOT_DATA'!B:V,12,FALSE) -> 0 | J108: =VLOOKUP($B108,'[1]26MY_PILOT_DATA'!B:V,13,FALSE) -> 0 | K108: =VLOOKUP($B108,'[1]26MY_PILOT_DATA'!B:V,14,FALSE) -> 0 | L108: =VLOOKUP(B108,'[1]26MY_PILOT_DATA'!B:V,15,FALSE) -> • | M108: =VLOOKUP(B108,'[1]26MY_PILOT_DATA'!B:V,16,FALSE) -> • | N108: =VLOOKUP(B108,'[1]26MY_PILOT_DATA'!B:V,17,FALSE) -> • | O108: =VLOOKUP(B108,'[1]26MY_PILOT_DATA'!B:V,18,FALSE) -> • | P108: =VLOOKUP(B108,'[1]26MY_PILOT_DATA'!B:V,19,FALSE) -> •
B109: 08L07-E09-300A | C109: =VLOOKUP(B109,'[1]26MY_PILOT_DATA'!B:V,3,FALSE) -> Bicycle Attachment - Fork Mount | D109: =B109 -> 08L07-E09-300A | E109: =VLOOKUP($B109,'[1]26MY_PILOT_DATA'!B:V,9,FALSE) -> 292 | F109: =VLOOKUP(B109,'[1]26MY_PILOT_DATA'!B:V,10,FALSE) -> 487 | G109: =VLOOKUP(B109,'[1]26MY_PILOT_DATA'!B:V,7,FALSE) -> 0.4 | H109: =VLOOKUP(B109,'[1]26MY_PILOT_DATA'!B:V,11,FALSE) -> 553 | I109: =VLOOKUP($B109,'[1]26MY_PILOT_DATA'!B:V,12,FALSE) -> 0 | J109: =VLOOKUP($B109,'[1]26MY_PILOT_DATA'!B:V,13,FALSE) -> 0 | K109: =VLOOKUP($B109,'[1]26MY_PILOT_DATA'!B:V,14,FALSE) -> 0 | L109: =VLOOKUP(B109,'[1]26MY_PILOT_DATA'!B:V,15,FALSE) -> • | M109: =VLOOKUP(B109,'[1]26MY_PILOT_DATA'!B:V,16,FALSE) -> • | N109: =VLOOKUP(B109,'[1]26MY_PILOT_DATA'!B:V,17,FALSE) -> • | O109: =VLOOKUP(B109,'[1]26MY_PILOT_DATA'!B:V,18,FALSE) -> • | P109: =VLOOKUP(B109,'[1]26MY_PILOT_DATA'!B:V,19,FALSE) -> •
B110: 08L20-E09-300B | C110: =VLOOKUP(B110,'[1]26MY_PILOT_DATA'!B:V,3,FALSE) -> Roof Box Short | D110: =B110 -> 08L20-E09-300B | E110: =VLOOKUP($B110,'[1]26MY_PILOT_DATA'!B:V,9,FALSE) -> 799 | F110: =VLOOKUP(B110,'[1]26MY_PILOT_DATA'!B:V,10,FALSE) -> 1332 | G110: =VLOOKUP(B110,'[1]26MY_PILOT_DATA'!B:V,7,FALSE) -> 0.2 | H110: =VLOOKUP(B110,'[1]26MY_PILOT_DATA'!B:V,11,FALSE) -> 1365 | I110: =VLOOKUP($B110,'[1]26MY_PILOT_DATA'!B:V,12,FALSE) -> 0 | J110: =VLOOKUP($B110,'[1]26MY_PILOT_DATA'!B:V,13,FALSE) -> 0 | K110: =VLOOKUP($B110,'[1]26MY_PILOT_DATA'!B:V,14,FALSE) -> 0 | L110: =VLOOKUP(B110,'[1]26MY_PILOT_DATA'!B:V,15,FALSE) -> • | M110: =VLOOKUP(B110,'[1]26MY_PILOT_DATA'!B:V,16,FALSE) -> • | N110: =VLOOKUP(B110,'[1]26MY_PILOT_DATA'!B:V,17,FALSE) -> • | O110: =VLOOKUP(B110,'[1]26MY_PILOT_DATA'!B:V,18,FALSE) -> • | P110: =VLOOKUP(B110,'[1]26MY_PILOT_DATA'!B:V,19,FALSE) -> •
B111: 08L20-E09-300A | C111: =VLOOKUP(B111,'[1]26MY_PILOT_DATA'!B:V,3,FALSE) -> Roof Box, Long | D111: =B111 -> 08L20-E09-300A | E111: =VLOOKUP($B111,'[1]26MY_PILOT_DATA'!B:V,9,FALSE) -> 875 | F111: =VLOOKUP(B111,'[1]26MY_PILOT_DATA'!B:V,10,FALSE) -> 1458 | G111: =VLOOKUP(B111,'[1]26MY_PILOT_DATA'!B:V,7,FALSE) -> 0.2 | H111: =VLOOKUP(B111,'[1]26MY_PILOT_DATA'!B:V,11,FALSE) -> 1491 | I111: =VLOOKUP($B111,'[1]26MY_PILOT_DATA'!B:V,12,FALSE) -> 0 | J111: =VLOOKUP($B111,'[1]26MY_PILOT_DATA'!B:V,13,FALSE) -> 0 | K111: =VLOOKUP($B111,'[1]26MY_PILOT_DATA'!B:V,14,FALSE) -> 0 | L111: =VLOOKUP(B111,'[1]26MY_PILOT_DATA'!B:V,15,FALSE) -> • | M111: =VLOOKUP(B111,'[1]26MY_PILOT_DATA'!B:V,16,FALSE) -> • | N111: =VLOOKUP(B111,'[1]26MY_PILOT_DATA'!B:V,17,FALSE) -> • | O111: =VLOOKUP(B111,'[1]26MY_PILOT_DATA'!B:V,18,FALSE) -> • | P111: =VLOOKUP(B111,'[1]26MY_PILOT_DATA'!B:V,19,FALSE) -> •
B112: 08L20-E09-101C | C112: =VLOOKUP(B112,'[1]26MY_PILOT_DATA'!B:V,3,FALSE) -> Roof Basket | D112: =B112 -> 08L20-E09-101C | E112: =VLOOKUP($B112,'[1]26MY_PILOT_DATA'!B:V,9,FALSE) -> 571 | F112: =VLOOKUP(B112,'[1]26MY_PILOT_DATA'!B:V,10,FALSE) -> 952 | G112: =VLOOKUP(B112,'[1]26MY_PILOT_DATA'!B:V,7,FALSE) -> 0.4 | H112: =VLOOKUP(B112,'[1]26MY_PILOT_DATA'!B:V,11,FALSE) -> 1018 | I112: =VLOOKUP($B112,'[1]26MY_PILOT_DATA'!B:V,12,FALSE) -> 0 | J112: =VLOOKUP($B112,'[1]26MY_PILOT_DATA'!B:V,13,FALSE) -> 0 | K112: =VLOOKUP($B112,'[1]26MY_PILOT_DATA'!B:V,14,FALSE) -> 0 | L112: =VLOOKUP(B112,'[1]26MY_PILOT_DATA'!B:V,15,FALSE) -> • | M112: =VLOOKUP(B112,'[1]26MY_PILOT_DATA'!B:V,16,FALSE) -> • | N112: =VLOOKUP(B112,'[1]26MY_PILOT_DATA'!B:V,17,FALSE) -> • | O112: =VLOOKUP(B112,'[1]26MY_PILOT_DATA'!B:V,18,FALSE) -> • | P112: =VLOOKUP(B112,'[1]26MY_PILOT_DATA'!B:V,19,FALSE) -> •
B113: 08L09-E09-101 | C113: =VLOOKUP(B113,'[1]26MY_PILOT_DATA'!B:V,3,FALSE) -> Roof Kayak Attachment | D113: =B113 -> 08L09-E09-101 | E113: =VLOOKUP($B113,'[1]26MY_PILOT_DATA'!B:V,9,FALSE) -> 430 | F113: =VLOOKUP(B113,'[1]26MY_PILOT_DATA'!B:V,10,FALSE) -> 717 | G113: =VLOOKUP(B113,'[1]26MY_PILOT_DATA'!B:V,7,FALSE) -> 0.4 | H113: =VLOOKUP(B113,'[1]26MY_PILOT_DATA'!B:V,11,FALSE) -> 783 | I113: =VLOOKUP($B113,'[1]26MY_PILOT_DATA'!B:V,12,FALSE) -> 0 | J113: =VLOOKUP($B113,'[1]26MY_PILOT_DATA'!B:V,13,FALSE) -> 0 | K113: =VLOOKUP($B113,'[1]26MY_PILOT_DATA'!B:V,14,FALSE) -> 0 | L113: =VLOOKUP(B113,'[1]26MY_PILOT_DATA'!B:V,15,FALSE) -> • | M113: =VLOOKUP(B113,'[1]26MY_PILOT_DATA'!B:V,16,FALSE) -> • | N113: =VLOOKUP(B113,'[1]26MY_PILOT_DATA'!B:V,17,FALSE) -> • | O113: =VLOOKUP(B113,'[1]26MY_PILOT_DATA'!B:V,18,FALSE) -> • | P113: =VLOOKUP(B113,'[1]26MY_PILOT_DATA'!B:V,19,FALSE) -> •
...

Sheet 26MY_Pilot_SELL_EN
B3: 26MY Honda Pilot
B4: 200
B6: POPULAR ACCESSORIES
B7: 20
B8: 150
B10: 20 | C10: ='26MY_Pilot_APP_EN'!$C$133 -> All Season Floor Mats | H10: ='26MY_Pilot_APP_EN'!$C$135 -> Cargo Tray | M10: ='26MY_Pilot_APP_EN'!$C$155 -> Illuminated Door Sill
B11: 20 | C11: ='26MY_Pilot_APP_EN'!$H$133 -> 374.5 | D11: =-PMT($D$29/52,5*52,C11) -> 1.7076821 | E11: /wk * | F11: =$C$29 -> (6.99%) | H11: ='26MY_Pilot_APP_EN'!$H$135 -> 211.5 | I11: =-PMT($D$29/52,5*52,H11) -> 0.9644186 | J11: /wk * | K11: =$C$29 -> (6.99%) | M11: ='26MY_Pilot_APP_EN'!$H$155 -> 802.5 | N11: =-PMT($D$29/52,5*52,M11) -> 3.6593188 | O11: /wk * | P11: =$C$29 -> (6.99%)
B13: 150
B15: 20 | C15: ='26MY_Pilot_APP_EN'!$C$105 -> Crossbars | H15: ='26MY_Pilot_APP_EN'!$C$94 -> Door Visor | M15: Black Emblems -"H" Mark & AWD
B16: 50 | C16: ='26MY_Pilot_APP_EN'!$H$105 -> 443 | D16: =-PMT($D$29/52,5*52,C16) -> 2.0200352 | E16: /wk * | F16: =$C$29 -> (6.99%) | H16: ='26MY_Pilot_APP_EN'!$H$94 -> 529 | I16: =-PMT($D$29/52,5*52,H16) -> 2.4121865 | J16: /wk * | K16: =$C$29 -> (6.99%) | M16: =SUM('26MY_Pilot_APP_EN'!$H$87+'26MY_Pilot_APP_EN'!$H$88) -> 192 | N16: =-PMT($D$29/52,5*52,M16) -> 0.87550058 | O16: /wk * | P16: =$C$29 -> (6.99%)
B18: 150
B20: 20 | C20: ='26MY_Pilot_APP_EN'!$C$92 -> Running Boards Rugged | H20: Towing Package - Touring Trim | M20: ='26MY_Pilot_APP_EN'!$C$145 -> Separation Barrier
B21: 50 | C21: ='26MY_Pilot_APP_EN'!$H$92 -> 1452.5 | D21: =-PMT($D$29/52,5*52,C21) -> 6.623253 | E21: /wk * | F21: =$C$29 -> (6.99%) | H21: =SUM('26MY_Pilot_APP_EN'!$H$40:$H$47) -> 2385.3 | I21: =-PMT($D$29/52,5*52,H21) -> 10.876727 | J21: /wk * | K21: =$C$29 -> (6.99%) | M21: ='26MY_Pilot_APP_EN'!$H$145 -> 1159 | N21: =-PMT($D$29/52,5*52,M21) -> 5.2849227 | O21: /wk * | P21: =$C$29 -> (6.99%)
C23: Genuine Honda Accessories purchased with a new Honda vehicle include a 3 year / 60,000 km manufacturer's warranty.
C24: Vehicle accessories purchased after vehicle sale include a 1 year / 20,000km manufacturer's warranty.
B25: 20 | C25: *Prices shown include the cost of installation.
B26: 60 | C26: *For informational purposes only. Weekly amounts shown are estimated payments based on a 60 month finance contract at 6.99% APR (including the cost of installation). Applicable taxes and fees are extra. Accessories cannot be financed on their own and must be financed through Honda Canada Finance Inc., on approved credit, in conjunction with a Honda vehicle. Representative finance example: $350.00 financed at 6.99% APR equals $1.60 weekly for 60 months. 260 weekly payments required. Cost of borrowing is $64.80 for a total obligation of $414.80. Actual payment amounts will vary based on APR, finance contract term and cost of the applicable accessories. Conditions apply. See your Honda dealer for full details.
C27: *More customized weekly payment options & accessories can be seen on Honda.ca - Build & Price
B28: 20
B29: 18 | C29: (6.99%) | D29: 0.0699
B30: 7.5 | C30: 12 | D30: 8 | E30: 8 | F30: 10 | G30: 8.5 | H30: 12 | I30: 8 | J30: 8 | K30: 10 | L30: 8.5 | M30: 12 | N30: 8 | O30: 8 | P30: 10 | Q30: 7.5
B31: Publication Date: | C31: ='[1]26MY_PILOT_DATA'!$C$4 -> 46076 | D31: ='SELECT PROVINCE'!$A$23 -> All published prices, trim specifications, and availability are subject to change without prior notice. | P31: Province | Q31: ='[1]26MY_PILOT_DATA'!L6 -> YT

Sheet 26MY_Pilot_APP_FR
C2: Accessoires Honda
C3: Nom du modèle | D3: ='[1]26MY_PILOT_DATA'!$C$2 -> Pilot
C4: Année modèle | D4: ='26MY_Pilot_APP_EN'!D4 -> 2026
C5: S = De série (accessoire de série sur cette version).
C6: T = Taille des pneus (la taille de la jante accessoire diffère de la jante d’origine. Le client aura besoin de nouveaux pneus pour ces jantes).
C7: E = Échange d’équipement de série (la taille de la jante accessoire est la même que celle de la jante d’origine. Le client peut utiliser les pneus d’origine).
C8: N/A = Sans objet (l’accessoire ne peut être utilisé pour cette version).
H10: Province
C11: 1.0 Groupes et ensembles | H11: =prov_cd -> YT
C12: La description | D12: Numéro de pièce | E12: Prix net | F12: Prix de liste | G12: T.F.F. | H12: Prix installé | I12: Application | Q12: Commentaires
I13: ='[1]26MY_PILOT_DATA'!$M$6 -> 0 | J13: ='[1]26MY_PILOT_DATA'!$M$6 -> 0 | K13: ='[1]26MY_PILOT_DATA'!$M$6 -> 0 | L13: ='[1]26MY_PILOT_DATA'!$P$6 -> Sport | M13: ='[1]26MY_PILOT_DATA'!$Q$6 -> EX-L | N13: ='[1]26MY_PILOT_DATA'!$R$6 -> TrailSport | O13: ='[1]26MY_PILOT_DATA'!$S$6 -> Touring | P13: ='[1]26MY_PILOT_DATA'!$T$6 -> Black Edition
B14: 23PIL-PRO-PK1 ou 23PIL-PRO-PK2 | C14: =VLOOKUP(B14,'[1]26MY_PILOT_DATA'!B:V,4,FALSE) -> Ensemble de protection | D14: =B14 -> 23PIL-PRO-PK1 ou 23PIL-PRO-PK2 | E14: =VLOOKUP($B14,'[1]26MY_PILOT_DATA'!B:V,9,FALSE) -> 298.8 | F14: =VLOOKUP(B14,'[1]26MY_PILOT_DATA'!B:V,10,FALSE) -> 553 | G14: =VLOOKUP(B14,'[1]26MY_PILOT_DATA'!B:V,7,FALSE) -> 0.2 | H14: =VLOOKUP(B14,'[1]26MY_PILOT_DATA'!B:V,11,FALSE) -> 586 | I14: =VLOOKUP($B14,'[1]26MY_PILOT_DATA'!B:V,12,FALSE) -> 0 | J14: =VLOOKUP($B14,'[1]26MY_PILOT_DATA'!B:V,13,FALSE) -> 0 | K14: =VLOOKUP($B14,'[1]26MY_PILOT_DATA'!B:V,14,FALSE) -> 0 | L14: =VLOOKUP(B14,'[1]26MY_PILOT_DATA'!B:V,15,FALSE) -> • | M14: =VLOOKUP(B14,'[1]26MY_PILOT_DATA'!B:V,16,FALSE) -> • | N14: =VLOOKUP(B14,'[1]26MY_PILOT_DATA'!B:V,17,FALSE) -> • | O14: =VLOOKUP(B14,'[1]26MY_PILOT_DATA'!B:V,18,FALSE) -> • | P14: =VLOOKUP(B14,'[1]26MY_PILOT_DATA'!B:V,19,FALSE) -> • | Q14: =IF(VLOOKUP(B14,'[1]26MY_PILOT_DATA'!B:V,21,FALSE)="","",VLOOKUP(B14,'[1]26MY_PILOT_DATA'!B:V,21,FALSE)) -> 23PIL-PRO-PK1: s'applique aux versions Sport, EX-L, Touring, Black Edition 23PIL-PRO-PK2: s'applique aux version TrailSport
B15: 08P17-T90-110 ou 08P17-T90-300C | C15: =VLOOKUP(B15,'[1]26MY_PILOT_DATA'!B:V,4,FALSE) -> Protège-tapis toutes saisons | D15: =B15 -> 08P17-T90-110 ou 08P17-T90-300C
B16: 08U45-T90-100 | C16: =VLOOKUP(B16,'[1]26MY_PILOT_DATA'!B:V,4,FALSE) -> Plateau de compartiment à bagages | D16: =B16 -> 08U45-T90-100
B18: 23PIL-PRO-PKA1 | C18: =VLOOKUP(B18,'[1]26MY_PILOT_DATA'!B:V,4,FALSE) -> Ensemble de protection Avance | D18: =B18 -> 23PIL-PRO-PKA1 | E18: =VLOOKUP($B18,'[1]26MY_PILOT_DATA'!B:V,9,FALSE) -> 791.1 | F18: =VLOOKUP(B18,'[1]26MY_PILOT_DATA'!B:V,10,FALSE) -> 1318.5 | G18: =VLOOKUP(B18,'[1]26MY_PILOT_DATA'!B:V,7,FALSE) -> 1.2 | H18: =VLOOKUP(B18,'[1]26MY_PILOT_DATA'!B:V,11,FALSE) -> 1516.5 | I18: =VLOOKUP($B18,'[1]26MY_PILOT_DATA'!B:V,12,FALSE) -> 0 | J18: =VLOOKUP($B18,'[1]26MY_PILOT_DATA'!B:V,13,FALSE) -> 0 | K18: =VLOOKUP($B18,'[1]26MY_PILOT_DATA'!B:V,14,FALSE) -> 0 | L18: =VLOOKUP(B18,'[1]26MY_PILOT_DATA'!B:V,15,FALSE) -> • | M18: =VLOOKUP(B18,'[1]26MY_PILOT_DATA'!B:V,16,FALSE) -> • | N18: =VLOOKUP(B18,'[1]26MY_PILOT_DATA'!B:V,17,FALSE) -> N/A | O18: =VLOOKUP(B18,'[1]26MY_PILOT_DATA'!B:V,18,FALSE) -> • | P18: =VLOOKUP(B18,'[1]26MY_PILOT_DATA'!B:V,19,FALSE) -> • | Q18: =IF(VLOOKUP(B18,'[1]26MY_PILOT_DATA'!B:V,21,FALSE)="","",VLOOKUP(B18,'[1]26MY_PILOT_DATA'!B:V,21,FALSE)) -> Rabais de 10 % est appliqué 23PIL-PRO-PKA1: s'applique aux versions Sport, EX-L, Touring, Black Edition 23PIL-PRO-PKA2: s'applique aux version TrailSport
B19: 08P17-T90-110 | C19: =VLOOKUP(B19,'[1]26MY_PILOT_DATA'!B:V,4,FALSE) -> Protège-tapis toutes saisons | D19: =B19 -> 08P17-T90-110
B20: 08U45-T90-100 | C20: =VLOOKUP(B20,'[1]26MY_PILOT_DATA'!B:V,4,FALSE) -> Plateau de compartiment à bagages | D20: =B20 -> 08U45-T90-100
B21: 08U35-T90-110 | C21: =VLOOKUP(B21,'[1]26MY_PILOT_DATA'!B:V,4,FALSE) -> Couvercle de compartiment à bagages | D21: =B21 -> 08U35-T90-110
B22: 08P42-T90-100B | C22: =VLOOKUP(B22,'[1]26MY_PILOT_DATA'!B:V,4,FALSE) -> Protecteur de dossier de siège arrière | D22: =B22 -> 08P42-T90-100B
B23: 08P42-T90-100A | C23: =VLOOKUP(B23,'[1]26MY_PILOT_DATA'!B:V,4,FALSE) -> Protecteurs de doublure latérale | D23: =B23 -> 08P42-T90-100A
B25: 23PIL-PRO-PKA2 | C25: =VLOOKUP(B25,'[1]26MY_PILOT_DATA'!B:V,4,FALSE) -> Ensemble de protection Avance | D25: =B25 -> 23PIL-PRO-PKA2 | E25: =VLOOKUP($B25,'[1]26MY_PILOT_DATA'!B:V,9,FALSE) -> 776.7 | F25: =VLOOKUP(B25,'[1]26MY_PILOT_DATA'!B:V,10,FALSE) -> 1284.3 | G25: =VLOOKUP(B25,'[1]26MY_PILOT_DATA'!B:V,7,FALSE) -> 1.1 | H25: =VLOOKUP(B25,'[1]26MY_PILOT_DATA'!B:V,11,FALSE) -> 1465.8 | I25: =VLOOKUP($B25,'[1]26MY_PILOT_DATA'!B:V,12,FALSE) -> 0 | J25: =VLOOKUP($B25,'[1]26MY_PILOT_DATA'!B:V,13,FALSE) -> 0 | K25: =VLOOKUP($B25,'[1]26MY_PILOT_DATA'!B:V,14,FALSE) -> 0 | L25: =VLOOKUP(B25,'[1]26MY_PILOT_DATA'!B:V,15,FALSE) -> N/A | M25: =VLOOKUP(B25,'[1]26MY_PILOT_DATA'!B:V,16,FALSE) -> N/A | N25: =VLOOKUP(B25,'[1]26MY_PILOT_DATA'!B:V,17,FALSE) -> • | O25: =VLOOKUP(B25,'[1]26MY_PILOT_DATA'!B:V,18,FALSE) -> N/A | P25: =VLOOKUP(B25,'[1]26MY_PILOT_DATA'!B:V,19,FALSE) -> N/A
B26: 08P17-T90-310C | C26: =VLOOKUP(B26,'[1]26MY_PILOT_DATA'!B:V,4,FALSE) -> Protège-tapis toutes saisons, TrailSport | D26: =B26 -> 08P17-T90-310C
B27: 08U45-T90-100 | C27: =VLOOKUP(B27,'[1]26MY_PILOT_DATA'!B:V,4,FALSE) -> Plateau de compartiment à bagages | D27: =B27 -> 08U45-T90-100
B28: 08U35-T90-110 | C28: =VLOOKUP(B28,'[1]26MY_PILOT_DATA'!B:V,4,FALSE) -> Couvercle de compartiment à bagages | D28: =B28 -> 08U35-T90-110
B29: 08P42-T90-100C | C29: =VLOOKUP(B29,'[1]26MY_PILOT_DATA'!B:V,4,FALSE) -> Protecteur de dossier de siège arrière | D29: =B29 -> 08P42-T90-100C
B30: 08P42-T90-100A | C30: =VLOOKUP(B30,'[1]26MY_PILOT_DATA'!B:V,4,FALSE) -> Protecteurs de doublure latérale | D30: =B30 -> 08P42-T90-100A
B32: 26PIL-TOW-B1 ou 26PIL-TOW-B2 | C32: =VLOOKUP(B32,'[1]26MY_PILOT_DATA'!B:V,4,FALSE) -> Ensemble de remorquage | D32: Voir les commentaires | E32: =VLOOKUP($B32,'[1]26MY_PILOT_DATA'!B:V,9,FALSE) -> 998.1 | F32: =VLOOKUP(B32,'[1]26MY_PILOT_DATA'!B:V,10,FALSE) -> 1651.5 | G32: =VLOOKUP(B32,'[1]26MY_PILOT_DATA'!B:V,7,FALSE) -> 1.8 | H32: =VLOOKUP(B32,'[1]26MY_PILOT_DATA'!B:V,11,FALSE) -> 1948.5 | I32: =VLOOKUP($B32,'[1]26MY_PILOT_DATA'!B:V,12,FALSE) -> 0 | J32: =VLOOKUP($B32,'[1]26MY_PILOT_DATA'!B:V,13,FALSE) -> 0 | K32: =VLOOKUP($B32,'[1]26MY_PILOT_DATA'!B:V,14,FALSE) -> 0 | L32: =VLOOKUP(B32,'[1]26MY_PILOT_DATA'!B:V,15,FALSE) -> • | M32: =VLOOKUP(B32,'[1]26MY_PILOT_DATA'!B:V,16,FALSE) -> • | N32: =VLOOKUP(B32,'[1]26MY_PILOT_DATA'!B:V,17,FALSE) -> N/A | O32: =VLOOKUP(B32,'[1]26MY_PILOT_DATA'!B:V,18,FALSE) -> N/A | P32: =VLOOKUP(B32,'[1]26MY_PILOT_DATA'!B:V,19,FALSE) -> N/A | Q32: =IF(VLOOKUP(B32,'[1]26MY_PILOT_DATA'!B:V,21,FALSE)="","",VLOOKUP(B32,'[1]26MY_PILOT_DATA'!B:V,21,FALSE)) -> Rabais de 10 % est appliqué Refroidisseur de transmission non requis pour le Pilot 2023. La capacité de remorquage est de 5000 livres. Sport version(Capuchon d’attelage de remorque noir): 26PIL-TOW-B1: comprend un attelage de remorque de 1 7/8 po boule. 26PIL-TOW-B2: comprend attelage de remorque de 2 po boule. EX-L version(Capuchon d’attelage de remorque argent): 26PIL-TOW-S1: comprend un attelage de remorque de 1 7/8 po boule. 26PIL-TOW-S2: comprend attelage de remorque de 2 po boule. Touring version**(Capuchon d’attelage de remorque argent): 26PIL-TOW-SA1: comprend un attelage de remorque de 1 7/8 po boule. 26PIL-TOW-SA2: comprend attelage de remorque de 2 po boule. Black Edition version**(Capuchon d’attelage de remorque noir): 26PIL-TOW-BA1: comprend un attelage de remorque de 1 7/8 po boule. 26PIL-TOW-BA2: comprend attelage de remorque de 2 po boule. **Touring et Black Edition nécessitent un adaptateur d’accès mains libres pour attelage de remorque - 08L91-T90-300A
B33: 08L92-T90-100 | C33: =VLOOKUP(B33,'[1]26MY_PILOT_DATA'!B:V,4,FALSE) -> Attelage de remorque | D33: =B33 -> 08L92-T90-100
B34: 08L91-T90-300B | C34: =VLOOKUP(B34,'[1]26MY_PILOT_DATA'!B:V,4,FALSE) -> Faisceau de remorque | D34: =B34 -> 08L91-T90-300B
B35: 08L92-T90-300D ou 08L92-T90-300E | C35: =VLOOKUP(B35,'[1]26MY_PILOT_DATA'!B:V,4,FALSE) -> Capuchon d’attelage de remorque noir ou argent | D35: =B35 -> 08L92-T90-300D ou 08L92-T90-300E
B36: 08L92-T90-100A | C36: =VLOOKUP(B36,'[1]26MY_PILOT_DATA'!B:V,4,FALSE) -> Attelage de remorque - montage sur boule | D36: =B36 -> 08L92-T90-100A
B37: 08L92-S9V-300G ou 08L92-S9V-300H | C37: =VLOOKUP(B37,'[1]26MY_PILOT_DATA'!B:V,4,FALSE) -> Rotule d'attelage de 1 7/8 po ou 2 po | D37: =B37 -> 08L92-S9V-300G ou 08L92-S9V-300H
B38: 08L92-SJC-300A | C38: =VLOOKUP(B38,'[1]26MY_PILOT_DATA'!B:V,4,FALSE) -> Attelage de remorque - goupille de verrouillage | D38: =B38 -> 08L92-SJC-300A
B40: 26PIL-TOW-SA1 or 26PIL-TOW-SA2 | C40: =VLOOKUP(B40,'[1]26MY_PILOT_DATA'!B:V,4,FALSE) -> Ensemble de remorquage | D40: Voir les commentaires | E40: =VLOOKUP($B40,'[1]26MY_PILOT_DATA'!B:V,9,FALSE) -> 1292.4 | F40: =VLOOKUP(B40,'[1]26MY_PILOT_DATA'!B:V,10,FALSE) -> 2071.8 | G40: =VLOOKUP(B40,'[1]26MY_PILOT_DATA'!B:V,7,FALSE) -> 1.9 | H40: =VLOOKUP(B40,'[1]26MY_PILOT_DATA'!B:V,11,FALSE) -> 2385.3 | I40: =VLOOKUP($B40,'[1]26MY_PILOT_DATA'!B:V,12,FALSE) -> 0 | J40: =VLOOKUP($B40,'[1]26MY_PILOT_DATA'!B:V,13,FALSE) -> 0 | K40: =VLOOKUP($B40,'[1]26MY_PILOT_DATA'!B:V,14,FALSE) -> 0 | L40: =VLOOKUP(B40,'[1]26MY_PILOT_DATA'!B:V,15,FALSE) -> N/A | M40: =VLOOKUP(B40,'[1]26MY_PILOT_DATA'!B:V,16,FALSE) -> N/A | N40: =VLOOKUP(B40,'[1]26MY_PILOT_DATA'!B:V,17,FALSE) -> N/A | O40: =VLOOKUP(B40,'[1]26MY_PILOT_DATA'!B:V,18,FALSE) -> • | P40: =VLOOKUP(B40,'[1]26MY_PILOT_DATA'!B:V,19,FALSE) -> •
B41: 08L92-T90-100 | C41: =VLOOKUP(B41,'[1]26MY_PILOT_DATA'!B:V,4,FALSE) -> Attelage de remorque | D41: =B41 -> 08L92-T90-100
B42: 08L91-T90-300B | C42: =VLOOKUP(B42,'[1]26MY_PILOT_DATA'!B:V,4,FALSE) -> Faisceau de remorque | D42: =B42 -> 08L91-T90-300B
B43: 08L92-T90-300D ou 08L92-T90-300E | C43: =VLOOKUP(B43,'[1]26MY_PILOT_DATA'!B:V,4,FALSE) -> Capuchon d’attelage de remorque noir ou argent | D43: =B43 -> 08L92-T90-300D ou 08L92-T90-300E
B44: 08L92-T90-100A | C44: =VLOOKUP(B44,'[1]26MY_PILOT_DATA'!B:V,4,FALSE) -> Attelage de remorque - montage sur boule | D44: =B44 -> 08L92-T90-100A
B45: 08L92-S9V-300G ou 08L92-S9V-300H | C45: =VLOOKUP(B45,'[1]26MY_PILOT_DATA'!B:V,4,FALSE) -> Rotule d'attelage de 1 7/8 po ou 2 po | D45: =B45 -> 08L92-S9V-300G ou 08L92-S9V-300H
B46: 08L92-SJC-300A | C46: =VLOOKUP(B46,'[1]26MY_PILOT_DATA'!B:V,4,FALSE) -> Attelage de remorque - goupille de verrouillage | D46: =B46 -> 08L92-SJC-300A
B48: 26PIL-TOW-TS1 or 26PIL-TOW-TS2 | C48: =VLOOKUP(B48,'[1]26MY_PILOT_DATA'!B:V,4,FALSE) -> Ensemble de remorquage - TrailSport | D48: =B48 -> 26PIL-TOW-TS1 or 26PIL-TOW-TS2 | E48: =VLOOKUP(B48,'[1]26MY_PILOT_DATA'!B:V,9,FALSE) -> 500.65 | F48: =VLOOKUP(B48,'[1]26MY_PILOT_DATA'!B:V,10,FALSE) -> 821.75 | G48: =VLOOKUP(B48,'[1]26MY_PILOT_DATA'!B:V,7,FALSE) -> 1.2 | H48: =VLOOKUP(B48,'[1]26MY_PILOT_DATA'!B:V,11,FALSE) -> 1019.75 | I48: =VLOOKUP($B49,'[1]26MY_PILOT_DATA'!B:V,12,FALSE) -> 0 | J48: =VLOOKUP($B49,'[1]26MY_PILOT_DATA'!B:V,13,FALSE) -> 0 | K48: =VLOOKUP($B49,'[1]26MY_PILOT_DATA'!B:V,14,FALSE) -> 0 | L48: =VLOOKUP(B48,'[1]26MY_PILOT_DATA'!B:V,15,FALSE) -> N/A | M48: =VLOOKUP(B48,'[1]26MY_PILOT_DATA'!B:V,16,FALSE) -> N/A | N48: =VLOOKUP(B48,'[1]26MY_PILOT_DATA'!B:V,17,FALSE) -> • | O48: =VLOOKUP(B48,'[1]26MY_PILOT_DATA'!B:V,18,FALSE) -> N/A | P48: =VLOOKUP(B48,'[1]26MY_PILOT_DATA'!B:V,19,FALSE) -> N/A | Q48: =IF(VLOOKUP(B48,'[1]26MY_PILOT_DATA'!B:V,21,FALSE)="","",VLOOKUP(B48,'[1]26MY_PILOT_DATA'!B:V,21,FALSE)) -> Rabais de 5 % est appliqué Refroidisseur de transmission non requis pour le Pilot 2026. La capacité de remorquage est de 5000 livres. 26PIL-TOW-TS1: 1-7/8" Trailer Hitch Ball 26PIL-TOW-TS2: 2" Trailer Hitch Ball
B49: 08L91-T90-300-TS | C49: =VLOOKUP(B49,'[1]26MY_PILOT_DATA'!B:V,4,FALSE) -> Faisceau de remorque - TrailSport | D49: =D42 -> 08L91-T90-300B
B50: 08L92-T90-100A | C50: =VLOOKUP(B50,'[1]26MY_PILOT_DATA'!B:V,4,FALSE) -> Attelage de remorque - montage sur boule | D50: =B50 -> 08L92-T90-100A
B51: 08L92-S9V-300G ou 08L92-S9V-300H | C51: =VLOOKUP(B51,'[1]26MY_PILOT_DATA'!B:V,4,FALSE) -> Rotule d'attelage de 1 7/8 po ou 2 po | D51: =B51 -> 08L92-S9V-300G ou 08L92-S9V-300H
B52: 08L92-SJC-300A | C52: =VLOOKUP(B52,'[1]26MY_PILOT_DATA'!B:V,4,FALSE) -> Attelage de remorque - goupille de verrouillage | D52: =B52 -> 08L92-SJC-300A
B54: 23PIL-COLD-PK | C54: =VLOOKUP(B54,'[1]26MY_PILOT_DATA'!B:V,4,FALSE) -> Ensemble de temps froid | D54: =B54 -> 23PIL-COLD-PK | E54: =VLOOKUP($B54,'[1]26MY_PILOT_DATA'!B:V,9,FALSE) -> 224.2 | F54: =VLOOKUP(B54,'[1]26MY_PILOT_DATA'!B:V,10,FALSE) -> 374.3 | G54: =VLOOKUP(B54,'[1]26MY_PILOT_DATA'!B:V,7,FALSE) -> 1.4 | H54: =VLOOKUP(B54,'[1]26MY_PILOT_DATA'!B:V,11,FALSE) -> 605.3 | I54: =VLOOKUP($B54,'[1]26MY_PILOT_DATA'!B:V,12,FALSE) -> 0 | J54: =VLOOKUP($B54,'[1]26MY_PILOT_DATA'!B:V,13,FALSE) -> 0 | K54: =VLOOKUP($B54,'[1]26MY_PILOT_DATA'!B:V,14,FALSE) -> 0 | L54: =VLOOKUP(B54,'[1]26MY_PILOT_DATA'!B:V,15,FALSE) -> • | M54: =VLOOKUP(B54,'[1]26MY_PILOT_DATA'!B:V,16,FALSE) -> • | N54: =VLOOKUP(B54,'[1]26MY_PILOT_DATA'!B:V,17,FALSE) -> • | O54: =VLOOKUP(B54,'[1]26MY_PILOT_DATA'!B:V,18,FALSE) -> • | P54: =VLOOKUP(B54,'[1]26MY_PILOT_DATA'!B:V,19,FALSE) -> • | Q54: =IF(VLOOKUP(B54,'[1]26MY_PILOT_DATA'!B:V,21,FALSE)="","",VLOOKUP(B54,'[1]26MY_PILOT_DATA'!B:V,21,FALSE)) -> Rabais de 5% est appliqué
B55: 08T44-SNA-302 | C55: =VLOOKUP(B55,'[1]26MY_PILOT_DATA'!B:V,4,FALSE) -> Chauffe-moteur | D55: =B55 -> 08T44-SNA-302
B56: 31670-BMS-004H | C56: =VLOOKUP(B56,'[1]26MY_PILOT_DATA'!B:V,4,FALSE) -> Chargeur/mainteneur de batterie automobile 12 V Optimate | D56: =B56 -> 31670-BMS-004H
B58: 25PIL-BLK-EM1 | C58: =VLOOKUP(B58,'[1]26MY_PILOT_DATA'!B:V,4,FALSE) -> Ensemble d’emblèmes noirs | D58: =B58 -> 25PIL-BLK-EM1 | E58: =VLOOKUP($B58,'[1]26MY_PILOT_DATA'!B:V,9,FALSE) -> 106.2 | F58: =VLOOKUP(B58,'[1]26MY_PILOT_DATA'!B:V,10,FALSE) -> 176.4 | G58: =VLOOKUP(B58,'[1]26MY_PILOT_DATA'!B:V,7,FALSE) -> 0.6 | H58: =VLOOKUP(B58,'[1]26MY_PILOT_DATA'!B:V,11,FALSE) -> 275.4 | I58: =VLOOKUP($B58,'[1]26MY_PILOT_DATA'!B:V,12,FALSE) -> 0 | J58: =VLOOKUP($B58,'[1]26MY_PILOT_DATA'!B:V,13,FALSE) -> 0 | K58: =VLOOKUP($B58,'[1]26MY_PILOT_DATA'!B:V,14,FALSE) -> 0 | L58: =VLOOKUP(B58,'[1]26MY_PILOT_DATA'!B:V,15,FALSE) -> N/A | M58: =VLOOKUP(B58,'[1]26MY_PILOT_DATA'!B:V,16,FALSE) -> N/A | N58: =VLOOKUP(B58,'[1]26MY_PILOT_DATA'!B:V,17,FALSE) -> N/A | O58: =VLOOKUP(B58,'[1]26MY_PILOT_DATA'!B:V,18,FALSE) -> N/A | P58: =VLOOKUP(B58,'[1]26MY_PILOT_DATA'!B:V,19,FALSE) -> N/A | Q58: =IF(VLOOKUP(B58,'[1]26MY_PILOT_DATA'!B:V,21,FALSE)="","",VLOOKUP(B58,'[1]26MY_PILOT_DATA'!B:V,21,FALSE)) -> Rabais de 10 % est appliqué
B59: 08F20-T90-100 | C59: =VLOOKUP(B59,'[1]26MY_PILOT_DATA'!B:V,4,FALSE) -> Emblème, noirs lustré - Logo « H » | D59: =B59 -> 08F20-T90-100
B60: 08F20-T90-100D | C60: =VLOOKUP(B60,'[1]26MY_PILOT_DATA'!B:V,4,FALSE) -> Emblème, noirs lustré « Pilot » | D60: =B60 -> 08F20-T90-100D
B61: 08F20-T90-100A | C61: =VLOOKUP(B61,'[1]26MY_PILOT_DATA'!B:V,4,FALSE) -> Emblème, noirs lustré « AWD » | D61: =B61 -> 08F20-T90-100A
B63: 25PIL-BLK-EM2 | C63: =VLOOKUP(B63,'[1]26MY_PILOT_DATA'!B:V,4,FALSE) -> Ensemble d’emblèmes noirs | D63: =B63 -> 25PIL-BLK-EM2 | E63: =VLOOKUP($B63,'[1]26MY_PILOT_DATA'!B:V,9,FALSE) -> 68.4 | F63: =VLOOKUP(B63,'[1]26MY_PILOT_DATA'!B:V,10,FALSE) -> 113.4 | G63: =VLOOKUP(B63,'[1]26MY_PILOT_DATA'!B:V,7,FALSE) -> 0.4 | H63: =VLOOKUP(B63,'[1]26MY_PILOT_DATA'!B:V,11,FALSE) -> 179.4 | I63: =VLOOKUP($B63,'[1]26MY_PILOT_DATA'!B:V,12,FALSE) -> 0 | J63: =VLOOKUP($B63,'[1]26MY_PILOT_DATA'!B:V,13,FALSE) -> 0 | K63: =VLOOKUP($B63,'[1]26MY_PILOT_DATA'!B:V,14,FALSE) -> 0 | L63: =VLOOKUP(B63,'[1]26MY_PILOT_DATA'!B:V,15,FALSE) -> N/A | M63: =VLOOKUP(B63,'[1]26MY_PILOT_DATA'!B:V,16,FALSE) -> • | N63: =VLOOKUP(B63,'[1]26MY_PILOT_DATA'!B:V,17,FALSE) -> • | O63: =VLOOKUP(B63,'[1]26MY_PILOT_DATA'!B:V,18,FALSE) -> • | P63: =VLOOKUP(B63,'[1]26MY_PILOT_DATA'!B:V,19,FALSE) -> • | Q63: =IF(VLOOKUP(B63,'[1]26MY_PILOT_DATA'!B:V,21,FALSE)="","",VLOOKUP(B63,'[1]26MY_PILOT_DATA'!B:V,21,FALSE)) -> Rabais de 10 % est appliqué
B64: 08F20-T90-100 | C64: =VLOOKUP(B64,'[1]26MY_PILOT_DATA'!B:V,4,FALSE) -> Emblème, noirs lustré - Logo « H » | D64: =B64 -> 08F20-T90-100
B65: 08F20-T90-100A | C65: =VLOOKUP(B65,'[1]26MY_PILOT_DATA'!B:V,4,FALSE) -> Emblème, noirs lustré « AWD » | D65: =B65 -> 08F20-T90-100A
B66: 08F20-T90-100D | C66: =VLOOKUP(B66,'[1]26MY_PILOT_DATA'!B:V,4,FALSE) -> Emblème, noirs lustré « Pilot » | D66: =B66 -> 08F20-T90-100D
B67: 08F20-PS2-100A | C67: =VLOOKUP(B67,'[1]26MY_PILOT_DATA'!B:V,4,FALSE) -> Emblème, noirs lustré « Touring » | D67: =B67 -> 08F20-PS2-100A
C69: 2.0 Jantes et accessoires de jantes
C70: La description | D70: Numéro de pièce | E70: Prix net | F70: Prix de liste | G70: T.F.F. | H70: Prix installé | I70: Application | Q70: Commentaires
I71: ='[1]26MY_PILOT_DATA'!$M$6 -> 0 | J71: ='[1]26MY_PILOT_DATA'!$M$6 -> 0 | K71: ='[1]26MY_PILOT_DATA'!$M$6 -> 0 | L71: ='[1]26MY_PILOT_DATA'!$P$6 -> Sport | M71: ='[1]26MY_PILOT_DATA'!$Q$6 -> EX-L | N71: ='[1]26MY_PILOT_DATA'!$R$6 -> TrailSport | O71: ='[1]26MY_PILOT_DATA'!$S$6 -> Touring | P71: ='[1]26MY_PILOT_DATA'!$T$6 -> Black Edition
B72: 08W18-T90-100D | C72: =VLOOKUP(B72,'[1]26MY_PILOT_DATA'!B:V,4,FALSE) -> Jante en alliage de 18 pouces | D72: =B72 -> 08W18-T90-100D | E72: =VLOOKUP($B72,'[1]26MY_PILOT_DATA'!B:V,9,FALSE) -> 1160 | F72: =VLOOKUP(B72,'[1]26MY_PILOT_DATA'!B:V,10,FALSE) -> 1920 | G72: =VLOOKUP(B72,'[1]26MY_PILOT_DATA'!B:V,7,FALSE) -> 1.6 | H72: =VLOOKUP(B72,'[1]26MY_PILOT_DATA'!B:V,11,FALSE) -> 2184 | I72: =VLOOKUP($B72,'[1]26MY_PILOT_DATA'!B:V,12,FALSE) -> 0 | J72: =VLOOKUP($B72,'[1]26MY_PILOT_DATA'!B:V,13,FALSE) -> 0 | K72: =VLOOKUP($B72,'[1]26MY_PILOT_DATA'!B:V,14,FALSE) -> 0 | L72: =VLOOKUP(B72,'[1]26MY_PILOT_DATA'!B:V,15,FALSE) -> T | M72: =VLOOKUP(B72,'[1]26MY_PILOT_DATA'!B:V,16,FALSE) -> E | N72: =VLOOKUP(B72,'[1]26MY_PILOT_DATA'!B:V,17,FALSE) -> E | O72: =VLOOKUP(B72,'[1]26MY_PILOT_DATA'!B:V,18,FALSE) -> T | P72: =VLOOKUP(B72,'[1]26MY_PILOT_DATA'!B:V,19,FALSE) -> T | Q72: =IF(VLOOKUP(B72,'[1]26MY_PILOT_DATA'!B:V,21,FALSE)="","",VLOOKUP(B72,'[1]26MY_PILOT_DATA'!B:V,21,FALSE))
B73: 08W20-T90-100C | C73: =VLOOKUP(B73,'[1]26MY_PILOT_DATA'!B:V,4,FALSE) -> Jante en alliage de 20 pouces – noir brillant | D73: =B73 -> 08W20-T90-100C | E73: =VLOOKUP($B73,'[1]26MY_PILOT_DATA'!B:V,9,FALSE) -> 1596 | F73: =VLOOKUP(B73,'[1]26MY_PILOT_DATA'!B:V,10,FALSE) -> 2660 | G73: =VLOOKUP(B73,'[1]26MY_PILOT_DATA'!B:V,7,FALSE) -> 1.6 | H73: =VLOOKUP(B73,'[1]26MY_PILOT_DATA'!B:V,11,FALSE) -> 2924 | I73: =VLOOKUP($B73,'[1]26MY_PILOT_DATA'!B:V,12,FALSE) -> 0 | J73: =VLOOKUP($B73,'[1]26MY_PILOT_DATA'!B:V,13,FALSE) -> 0 | K73: =VLOOKUP($B73,'[1]26MY_PILOT_DATA'!B:V,14,FALSE) -> 0 | L73: =VLOOKUP(B73,'[1]26MY_PILOT_DATA'!B:V,15,FALSE) -> E | M73: =VLOOKUP(B73,'[1]26MY_PILOT_DATA'!B:V,16,FALSE) -> T | N73: =VLOOKUP(B73,'[1]26MY_PILOT_DATA'!B:V,17,FALSE) -> T | O73: =VLOOKUP(B73,'[1]26MY_PILOT_DATA'!B:V,18,FALSE) -> E | P73: =VLOOKUP(B73,'[1]26MY_PILOT_DATA'!B:V,19,FALSE) -> E | Q73: =IF(VLOOKUP(B73,'[1]26MY_PILOT_DATA'!B:V,21,FALSE)="","",VLOOKUP(B73,'[1]26MY_PILOT_DATA'!B:V,21,FALSE))
B74: 08W20-T90-300E | C74: =VLOOKUP(B74,'[1]26MY_PILOT_DATA'!B:V,4,FALSE) -> Jante en alliage de 20 pouces – noir mat | D74: =B74 -> 08W20-T90-300E | E74: =VLOOKUP($B74,'[1]26MY_PILOT_DATA'!B:V,9,FALSE) -> 1596 | F74: =VLOOKUP(B74,'[1]26MY_PILOT_DATA'!B:V,10,FALSE) -> 2660 | G74: =VLOOKUP(B74,'[1]26MY_PILOT_DATA'!B:V,7,FALSE) -> 1.6 | H74: =VLOOKUP(B74,'[1]26MY_PILOT_DATA'!B:V,11,FALSE) -> 2924 | I74: =VLOOKUP($B74,'[1]26MY_PILOT_DATA'!B:V,12,FALSE) -> 0 | J74: =VLOOKUP($B74,'[1]26MY_PILOT_DATA'!B:V,13,FALSE) -> 0 | K74: =VLOOKUP($B74,'[1]26MY_PILOT_DATA'!B:V,14,FALSE) -> 0 | L74: =VLOOKUP(B74,'[1]26MY_PILOT_DATA'!B:V,15,FALSE) -> E | M74: =VLOOKUP(B74,'[1]26MY_PILOT_DATA'!B:V,16,FALSE) -> T | N74: =VLOOKUP(B74,'[1]26MY_PILOT_DATA'!B:V,17,FALSE) -> T | O74: =VLOOKUP(B74,'[1]26MY_PILOT_DATA'!B:V,18,FALSE) -> E | P74: =VLOOKUP(B74,'[1]26MY_PILOT_DATA'!B:V,19,FALSE) -> E | Q74: =IF(VLOOKUP(B74,'[1]26MY_PILOT_DATA'!B:V,21,FALSE)="","",VLOOKUP(B74,'[1]26MY_PILOT_DATA'!B:V,21,FALSE))
B75: 08W42-TK4-301 | C75: =VLOOKUP(B75,'[1]26MY_PILOT_DATA'!B:V,4,FALSE) -> Écrous de roue antivols - Chromés | D75: =B75 -> 08W42-TK4-301 | E75: =VLOOKUP($B75,'[1]26MY_PILOT_DATA'!B:V,9,FALSE) -> 91 | F75: =VLOOKUP(B75,'[1]26MY_PILOT_DATA'!B:V,10,FALSE) -> 152 | G75: =VLOOKUP(B75,'[1]26MY_PILOT_DATA'!B:V,7,FALSE) -> 0.2 | H75: =VLOOKUP(B75,'[1]26MY_PILOT_DATA'!B:V,11,FALSE) -> 185 | I75: =VLOOKUP($B75,'[1]26MY_PILOT_DATA'!B:V,12,FALSE) -> 0 | J75: =VLOOKUP($B75,'[1]26MY_PILOT_DATA'!B:V,13,FALSE) -> 0 | K75: =VLOOKUP($B75,'[1]26MY_PILOT_DATA'!B:V,14,FALSE) -> 0 | L75: =VLOOKUP(B75,'[1]26MY_PILOT_DATA'!B:V,15,FALSE) -> N/A | M75: =VLOOKUP(B75,'[1]26MY_PILOT_DATA'!B:V,16,FALSE) -> • | N75: =VLOOKUP(B75,'[1]26MY_PILOT_DATA'!B:V,17,FALSE) -> N/A | O75: =VLOOKUP(B75,'[1]26MY_PILOT_DATA'!B:V,18,FALSE) -> N/A | P75: =VLOOKUP(B75,'[1]26MY_PILOT_DATA'!B:V,19,FALSE) -> N/A | Q75: =IF(VLOOKUP(B75,'[1]26MY_PILOT_DATA'!B:V,21,FALSE)="","",VLOOKUP(B75,'[1]26MY_PILOT_DATA'!B:V,21,FALSE))
B76: 08W42-TG7-301A | C76: =VLOOKUP(B76,'[1]26MY_PILOT_DATA'!B:V,4,FALSE) -> Écrous de roue antivols - Noirs | D76: =B76 -> 08W42-TG7-301A | E76: =VLOOKUP($B76,'[1]26MY_PILOT_DATA'!B:V,9,FALSE) -> 85 | F76: =VLOOKUP(B76,'[1]26MY_PILOT_DATA'!B:V,10,FALSE) -> 140 | G76: =VLOOKUP(B76,'[1]26MY_PILOT_DATA'!B:V,7,FALSE) -> 0.2 | H76: =VLOOKUP(B76,'[1]26MY_PILOT_DATA'!B:V,11,FALSE) -> 173 | I76: =VLOOKUP($B76,'[1]26MY_PILOT_DATA'!B:V,12,FALSE) -> 0 | J76: =VLOOKUP($B76,'[1]26MY_PILOT_DATA'!B:V,13,FALSE) -> 0 | K76: =VLOOKUP($B76,'[1]26MY_PILOT_DATA'!B:V,14,FALSE) -> 0 | L76: =VLOOKUP(B76,'[1]26MY_PILOT_DATA'!B:V,15,FALSE) -> • | M76: =VLOOKUP(B76,'[1]26MY_PILOT_DATA'!B:V,16,FALSE) -> • | N76: =VLOOKUP(B76,'[1]26MY_PILOT_DATA'!B:V,17,FALSE) -> • | O76: =VLOOKUP(B76,'[1]26MY_PILOT_DATA'!B:V,18,FALSE) -> • | P76: =VLOOKUP(B76,'[1]26MY_PILOT_DATA'!B:V,19,FALSE) -> • | Q76: =IF(VLOOKUP(B76,'[1]26MY_PILOT_DATA'!B:V,21,FALSE)="","",VLOOKUP(B76,'[1]26MY_PILOT_DATA'!B:V,21,FALSE))
B77: 08W42-PL4-100A | C77: =VLOOKUP(B77,'[1]26MY_PILOT_DATA'!B:V,4,FALSE) -> Écrous de roue - Noir | D77: =B77 -> 08W42-PL4-100A | E77: =VLOOKUP($B77,'[1]26MY_PILOT_DATA'!B:V,9,FALSE) -> 165 | F77: =VLOOKUP(B77,'[1]26MY_PILOT_DATA'!B:V,10,FALSE) -> 275 | G77: =VLOOKUP(B77,'[1]26MY_PILOT_DATA'!B:V,7,FALSE) -> 0.4 | H77: =VLOOKUP(B77,'[1]26MY_PILOT_DATA'!B:V,11,FALSE) -> 341 | I77: =VLOOKUP($B77,'[1]26MY_PILOT_DATA'!B:V,12,FALSE) -> 0 | J77: =VLOOKUP($B77,'[1]26MY_PILOT_DATA'!B:V,13,FALSE) -> 0 | K77: =VLOOKUP($B77,'[1]26MY_PILOT_DATA'!B:V,14,FALSE) -> 0 | L77: =VLOOKUP(B77,'[1]26MY_PILOT_DATA'!B:V,15,FALSE) -> S | M77: =VLOOKUP(B77,'[1]26MY_PILOT_DATA'!B:V,16,FALSE) -> • | N77: =VLOOKUP(B77,'[1]26MY_PILOT_DATA'!B:V,17,FALSE) -> S | O77: =VLOOKUP(B77,'[1]26MY_PILOT_DATA'!B:V,18,FALSE) -> S | P77: =VLOOKUP(B77,'[1]26MY_PILOT_DATA'!B:V,19,FALSE) -> S | Q77: =IF(VLOOKUP(B77,'[1]26MY_PILOT_DATA'!B:V,21,FALSE)="","",VLOOKUP(B77,'[1]26MY_PILOT_DATA'!B:V,21,FALSE)) -> Ensemble de 20 écrous de roue.
C79: 3.0 Extérieur
C80: La description | D80: Numéro de pièce | E80: Prix net | F80: Prix de liste | G80: T.F.F. | H80: Prix installé | I80: Application | Q80: Commentaires
I81: ='[1]26MY_PILOT_DATA'!$M$6 -> 0 | J81: ='[1]26MY_PILOT_DATA'!$M$6 -> 0 | K81: ='[1]26MY_PILOT_DATA'!$M$6 -> 0 | L81: ='[1]26MY_PILOT_DATA'!$P$6 -> Sport | M81: ='[1]26MY_PILOT_DATA'!$Q$6 -> EX-L | N81: ='[1]26MY_PILOT_DATA'!$R$6 -> TrailSport | O81: ='[1]26MY_PILOT_DATA'!$S$6 -> Touring | P81: ='[1]26MY_PILOT_DATA'!$T$6 -> Black Edition
B82: 08F04-T90-100 | C82: =VLOOKUP(B82,'[1]26MY_PILOT_DATA'!B:V,4,FALSE) -> Garnitures de plaques de protection latérales | D82: =B82 -> 08F04-T90-100 | E82: =VLOOKUP($B82,'[1]26MY_PILOT_DATA'!B:V,9,FALSE) -> 324 | F82: =VLOOKUP(B82,'[1]26MY_PILOT_DATA'!B:V,10,FALSE) -> 540 | G82: =VLOOKUP(B82,'[1]26MY_PILOT_DATA'!B:V,7,FALSE) -> 0.6 | H82: =VLOOKUP(B82,'[1]26MY_PILOT_DATA'!B:V,11,FALSE) -> 639 | I82: =VLOOKUP($B82,'[1]26MY_PILOT_DATA'!B:V,12,FALSE) -> 0 | J82: =VLOOKUP($B82,'[1]26MY_PILOT_DATA'!B:V,13,FALSE) -> 0 | K82: =VLOOKUP($B82,'[1]26MY_PILOT_DATA'!B:V,14,FALSE) -> 0 | L82: =VLOOKUP(B82,'[1]26MY_PILOT_DATA'!B:V,15,FALSE) -> • | M82: =VLOOKUP(B82,'[1]26MY_PILOT_DATA'!B:V,16,FALSE) -> • | N82: =VLOOKUP(B82,'[1]26MY_PILOT_DATA'!B:V,17,FALSE) -> • | O82: =VLOOKUP(B82,'[1]26MY_PILOT_DATA'!B:V,18,FALSE) -> • | P82: =VLOOKUP(B82,'[1]26MY_PILOT_DATA'!B:V,19,FALSE) -> • | Q82: =IF(VLOOKUP(B82,'[1]26MY_PILOT_DATA'!B:V,21,FALSE)="","",VLOOKUP(B82,'[1]26MY_PILOT_DATA'!B:V,21,FALSE))
B83: 08F21-T90-100A | C83: =VLOOKUP(B83,'[1]26MY_PILOT_DATA'!B:V,4,FALSE) -> Garniture de calandre | D83: =B83 -> 08F21-T90-100A | E83: =VLOOKUP($B83,'[1]26MY_PILOT_DATA'!B:V,9,FALSE) -> 247 | F83: =VLOOKUP(B83,'[1]26MY_PILOT_DATA'!B:V,10,FALSE) -> 412 | G83: =VLOOKUP(B83,'[1]26MY_PILOT_DATA'!B:V,7,FALSE) -> 0.2 | H83: =VLOOKUP(B83,'[1]26MY_PILOT_DATA'!B:V,11,FALSE) -> 445 | I83: =VLOOKUP($B83,'[1]26MY_PILOT_DATA'!B:V,12,FALSE) -> 0 | J83: =VLOOKUP($B83,'[1]26MY_PILOT_DATA'!B:V,13,FALSE) -> 0 | K83: =VLOOKUP($B83,'[1]26MY_PILOT_DATA'!B:V,14,FALSE) -> 0 | L83: =VLOOKUP(B83,'[1]26MY_PILOT_DATA'!B:V,15,FALSE) -> S | M83: =VLOOKUP(B83,'[1]26MY_PILOT_DATA'!B:V,16,FALSE) -> • | N83: =VLOOKUP(B83,'[1]26MY_PILOT_DATA'!B:V,17,FALSE) -> S | O83: =VLOOKUP(B83,'[1]26MY_PILOT_DATA'!B:V,18,FALSE) -> • | P83: =VLOOKUP(B83,'[1]26MY_PILOT_DATA'!B:V,19,FALSE) -> S | Q83: =IF(VLOOKUP(B83,'[1]26MY_PILOT_DATA'!B:V,21,FALSE)="","",VLOOKUP(B83,'[1]26MY_PILOT_DATA'!B:V,21,FALSE))
B84: PILOTEMBLEM | C84: =VLOOKUP(B84,'[1]26MY_PILOT_DATA'!B:V,4,FALSE) -> Emblèmes, noirs
B85: 08F20-T90-100 | C85: =VLOOKUP(B85,'[1]26MY_PILOT_DATA'!B:V,4,FALSE) -> Emblème, noirs lustré - Logo « H » | D85: =B85 -> 08F20-T90-100 | E85: =VLOOKUP($B85,'[1]26MY_PILOT_DATA'!B:V,9,FALSE) -> 41 | F85: =VLOOKUP(B85,'[1]26MY_PILOT_DATA'!B:V,10,FALSE) -> 68 | G85: =VLOOKUP(B85,'[1]26MY_PILOT_DATA'!B:V,7,FALSE) -> 0.2 | H85: =VLOOKUP(B85,'[1]26MY_PILOT_DATA'!B:V,11,FALSE) -> 101 | I85: =VLOOKUP($B85,'[1]26MY_PILOT_DATA'!B:V,12,FALSE) -> 0 | J85: =VLOOKUP($B85,'[1]26MY_PILOT_DATA'!B:V,13,FALSE) -> 0 | K85: =VLOOKUP($B85,'[1]26MY_PILOT_DATA'!B:V,14,FALSE) -> 0 | L85: =VLOOKUP(B85,'[1]26MY_PILOT_DATA'!B:V,15,FALSE) -> • | M85: =VLOOKUP(B85,'[1]26MY_PILOT_DATA'!B:V,16,FALSE) -> • | N85: =VLOOKUP(B85,'[1]26MY_PILOT_DATA'!B:V,17,FALSE) -> • | O85: =VLOOKUP(B85,'[1]26MY_PILOT_DATA'!B:V,18,FALSE) -> • | P85: =VLOOKUP(B85,'[1]26MY_PILOT_DATA'!B:V,19,FALSE) -> • | Q85: =IF(VLOOKUP(B85,'[1]26MY_PILOT_DATA'!B:V,21,FALSE)="","",VLOOKUP(B85,'[1]26MY_PILOT_DATA'!B:V,21,FALSE))
B86: 08F20-T90-100A | C86: =VLOOKUP(B86,'[1]26MY_PILOT_DATA'!B:V,4,FALSE) -> Emblème, noirs lustré « AWD » | D86: =B86 -> 08F20-T90-100A | E86: =VLOOKUP($B86,'[1]26MY_PILOT_DATA'!B:V,9,FALSE) -> 35 | F86: =VLOOKUP(B86,'[1]26MY_PILOT_DATA'!B:V,10,FALSE) -> 58 | G86: =VLOOKUP(B86,'[1]26MY_PILOT_DATA'!B:V,7,FALSE) -> 0.2 | H86: =VLOOKUP(B86,'[1]26MY_PILOT_DATA'!B:V,11,FALSE) -> 91 | I86: =VLOOKUP($B86,'[1]26MY_PILOT_DATA'!B:V,12,FALSE) -> 0 | J86: =VLOOKUP($B86,'[1]26MY_PILOT_DATA'!B:V,13,FALSE) -> 0 | K86: =VLOOKUP($B86,'[1]26MY_PILOT_DATA'!B:V,14,FALSE) -> 0 | L86: =VLOOKUP(B86,'[1]26MY_PILOT_DATA'!B:V,15,FALSE) -> N/A | M86: =VLOOKUP(B86,'[1]26MY_PILOT_DATA'!B:V,16,FALSE) -> • | N86: =VLOOKUP(B86,'[1]26MY_PILOT_DATA'!B:V,17,FALSE) -> • | O86: =VLOOKUP(B86,'[1]26MY_PILOT_DATA'!B:V,18,FALSE) -> • | P86: =VLOOKUP(B86,'[1]26MY_PILOT_DATA'!B:V,19,FALSE) -> • | Q86: =IF(VLOOKUP(B86,'[1]26MY_PILOT_DATA'!B:V,21,FALSE)="","",VLOOKUP(B86,'[1]26MY_PILOT_DATA'!B:V,21,FALSE))
B87: 08F20-T90-100D | C87: =VLOOKUP(B87,'[1]26MY_PILOT_DATA'!B:V,4,FALSE) -> Emblème, noirs lustré « Pilot » | D87: =B87 -> 08F20-T90-100D | E87: =VLOOKUP($B87,'[1]26MY_PILOT_DATA'!B:V,9,FALSE) -> 73 | F87: =VLOOKUP(B87,'[1]26MY_PILOT_DATA'!B:V,10,FALSE) -> 122 | G87: =VLOOKUP(B87,'[1]26MY_PILOT_DATA'!B:V,7,FALSE) -> 0.3 | H87: =VLOOKUP(B87,'[1]26MY_PILOT_DATA'!B:V,11,FALSE) -> 171.5 | I87: =VLOOKUP($B87,'[1]26MY_PILOT_DATA'!B:V,12,FALSE) -> 0 | J87: =VLOOKUP($B87,'[1]26MY_PILOT_DATA'!B:V,13,FALSE) -> 0 | K87: =VLOOKUP($B87,'[1]26MY_PILOT_DATA'!B:V,14,FALSE) -> 0 | L87: =VLOOKUP(B87,'[1]26MY_PILOT_DATA'!B:V,15,FALSE) -> • | M87: =VLOOKUP(B87,'[1]26MY_PILOT_DATA'!B:V,16,FALSE) -> • | N87: =VLOOKUP(B87,'[1]26MY_PILOT_DATA'!B:V,17,FALSE) -> • | O87: =VLOOKUP(B87,'[1]26MY_PILOT_DATA'!B:V,18,FALSE) -> • | P87: =VLOOKUP(B87,'[1]26MY_PILOT_DATA'!B:V,19,FALSE) -> • | Q87: =IF(VLOOKUP(B87,'[1]26MY_PILOT_DATA'!B:V,21,FALSE)="","",VLOOKUP(B87,'[1]26MY_PILOT_DATA'!B:V,21,FALSE))
B88: 08F20-PS2-100A | C88: =VLOOKUP(B88,'[1]26MY_PILOT_DATA'!B:V,4,FALSE) -> Emblème, noirs lustré « Touring » | D88: =B88 -> 08F20-PS2-100A | E88: =VLOOKUP($B88,'[1]26MY_PILOT_DATA'!B:V,9,FALSE) -> 47 | F88: =VLOOKUP(B88,'[1]26MY_PILOT_DATA'!B:V,10,FALSE) -> 78 | G88: =VLOOKUP(B88,'[1]26MY_PILOT_DATA'!B:V,7,FALSE) -> 0.1 | H88: =VLOOKUP(B88,'[1]26MY_PILOT_DATA'!B:V,11,FALSE) -> 94.5 | I88: =VLOOKUP($B88,'[1]26MY_PILOT_DATA'!B:V,12,FALSE) -> 0 | J88: =VLOOKUP($B88,'[1]26MY_PILOT_DATA'!B:V,13,FALSE) -> 0 | K88: =VLOOKUP($B88,'[1]26MY_PILOT_DATA'!B:V,14,FALSE) -> 0 | L88: =VLOOKUP(B88,'[1]26MY_PILOT_DATA'!B:V,15,FALSE) -> N/A | M88: =VLOOKUP(B88,'[1]26MY_PILOT_DATA'!B:V,16,FALSE) -> N/A | N88: =VLOOKUP(B88,'[1]26MY_PILOT_DATA'!B:V,17,FALSE) -> N/A | O88: =VLOOKUP(B88,'[1]26MY_PILOT_DATA'!B:V,18,FALSE) -> • | P88: =VLOOKUP(B88,'[1]26MY_PILOT_DATA'!B:V,19,FALSE) -> N/A | Q88: =IF(VLOOKUP(B88,'[1]26MY_PILOT_DATA'!B:V,21,FALSE)="","",VLOOKUP(B88,'[1]26MY_PILOT_DATA'!B:V,21,FALSE))
B89: 08L33-T90-100 | C89: =VLOOKUP(B89,'[1]26MY_PILOT_DATA'!B:V,4,FALSE) -> Marchepieds traditionnels | D89: =B89 -> 08L33-T90-100 | E89: =VLOOKUP($B89,'[1]26MY_PILOT_DATA'!B:V,9,FALSE) -> 743 | F89: =VLOOKUP(B89,'[1]26MY_PILOT_DATA'!B:V,10,FALSE) -> 1061 | G89: =VLOOKUP(B89,'[1]26MY_PILOT_DATA'!B:V,7,FALSE) -> 0.7 | H89: =VLOOKUP(B89,'[1]26MY_PILOT_DATA'!B:V,11,FALSE) -> 1176.5 | I89: =VLOOKUP($B89,'[1]26MY_PILOT_DATA'!B:V,12,FALSE) -> 0 | J89: =VLOOKUP($B89,'[1]26MY_PILOT_DATA'!B:V,13,FALSE) -> 0 | K89: =VLOOKUP($B89,'[1]26MY_PILOT_DATA'!B:V,14,FALSE) -> 0 | L89: =VLOOKUP(B89,'[1]26MY_PILOT_DATA'!B:V,15,FALSE) -> • | M89: =VLOOKUP(B89,'[1]26MY_PILOT_DATA'!B:V,16,FALSE) -> • | N89: =VLOOKUP(B89,'[1]26MY_PILOT_DATA'!B:V,17,FALSE) -> • | O89: =VLOOKUP(B89,'[1]26MY_PILOT_DATA'!B:V,18,FALSE) -> • | P89: =VLOOKUP(B89,'[1]26MY_PILOT_DATA'!B:V,19,FALSE) -> • | Q89: =IF(VLOOKUP(B89,'[1]26MY_PILOT_DATA'!B:V,21,FALSE)="","",VLOOKUP(B89,'[1]26MY_PILOT_DATA'!B:V,21,FALSE))
B90: 08L33-T90-100B | C90: =VLOOKUP(B90,'[1]26MY_PILOT_DATA'!B:V,4,FALSE) -> Marchepieds robustes | D90: =B90 -> 08L33-T90-100B | E90: =VLOOKUP($B90,'[1]26MY_PILOT_DATA'!B:V,9,FALSE) -> 936 | F90: =VLOOKUP(B90,'[1]26MY_PILOT_DATA'!B:V,10,FALSE) -> 1337 | G90: =VLOOKUP(B90,'[1]26MY_PILOT_DATA'!B:V,7,FALSE) -> 0.7 | H90: =VLOOKUP(B90,'[1]26MY_PILOT_DATA'!B:V,11,FALSE) -> 1452.5 | I90: =VLOOKUP($B90,'[1]26MY_PILOT_DATA'!B:V,12,FALSE) -> 0 | J90: =VLOOKUP($B90,'[1]26MY_PILOT_DATA'!B:V,13,FALSE) -> 0 | K90: =VLOOKUP($B90,'[1]26MY_PILOT_DATA'!B:V,14,FALSE) -> 0 | L90: =VLOOKUP(B90,'[1]26MY_PILOT_DATA'!B:V,15,FALSE) -> • | M90: =VLOOKUP(B90,'[1]26MY_PILOT_DATA'!B:V,16,FALSE) -> • | N90: =VLOOKUP(B90,'[1]26MY_PILOT_DATA'!B:V,17,FALSE) -> • | O90: =VLOOKUP(B90,'[1]26MY_PILOT_DATA'!B:V,18,FALSE) -> • | P90: =VLOOKUP(B90,'[1]26MY_PILOT_DATA'!B:V,19,FALSE) -> • | Q90: =IF(VLOOKUP(B90,'[1]26MY_PILOT_DATA'!B:V,21,FALSE)="","",VLOOKUP(B90,'[1]26MY_PILOT_DATA'!B:V,21,FALSE))
B91: 08P21-T90-100 | C91: =VLOOKUP(B91,'[1]26MY_PILOT_DATA'!B:V,4,FALSE) -> Élargisseurs d’ailes | D91: =B91 -> 08P21-T90-100 | E91: =VLOOKUP($B91,'[1]26MY_PILOT_DATA'!B:V,9,FALSE) -> 550 | F91: =VLOOKUP(B91,'[1]26MY_PILOT_DATA'!B:V,10,FALSE) -> 917 | G91: =VLOOKUP(B91,'[1]26MY_PILOT_DATA'!B:V,7,FALSE) -> 1 | H91: =VLOOKUP(B91,'[1]26MY_PILOT_DATA'!B:V,11,FALSE) -> 1082 | I91: =VLOOKUP($B91,'[1]26MY_PILOT_DATA'!B:V,12,FALSE) -> 0 | J91: =VLOOKUP($B91,'[1]26MY_PILOT_DATA'!B:V,13,FALSE) -> 0 | K91: =VLOOKUP($B91,'[1]26MY_PILOT_DATA'!B:V,14,FALSE) -> 0 | L91: =VLOOKUP(B91,'[1]26MY_PILOT_DATA'!B:V,15,FALSE) -> • | M91: =VLOOKUP(B91,'[1]26MY_PILOT_DATA'!B:V,16,FALSE) -> • | N91: =VLOOKUP(B91,'[1]26MY_PILOT_DATA'!B:V,17,FALSE) -> • | O91: =VLOOKUP(B91,'[1]26MY_PILOT_DATA'!B:V,18,FALSE) -> • | P91: =VLOOKUP(B91,'[1]26MY_PILOT_DATA'!B:V,19,FALSE) -> • | Q91: =IF(VLOOKUP(B91,'[1]26MY_PILOT_DATA'!B:V,21,FALSE)="","",VLOOKUP(B91,'[1]26MY_PILOT_DATA'!B:V,21,FALSE)) -> Remplacent les garde-boue avant et arrière. Ne peut être installé simultanément avec pellicule pour rebord de portière
B92: 08R04-T90-100 | C92: =VLOOKUP(B92,'[1]26MY_PILOT_DATA'!B:V,4,FALSE) -> Visières de portière | D92: =B92 -> 08R04-T90-100 | E92: =VLOOKUP($B92,'[1]26MY_PILOT_DATA'!B:V,9,FALSE) -> 258 | F92: =VLOOKUP(B92,'[1]26MY_PILOT_DATA'!B:V,10,FALSE) -> 430 | G92: =VLOOKUP(B92,'[1]26MY_PILOT_DATA'!B:V,7,FALSE) -> 0.6 | H92: =VLOOKUP(B92,'[1]26MY_PILOT_DATA'!B:V,11,FALSE) -> 529 | I92: =VLOOKUP($B92,'[1]26MY_PILOT_DATA'!B:V,12,FALSE) -> 0 | J92: =VLOOKUP($B92,'[1]26MY_PILOT_DATA'!B:V,13,FALSE) -> 0 | K92: =VLOOKUP($B92,'[1]26MY_PILOT_DATA'!B:V,14,FALSE) -> 0 | L92: =VLOOKUP(B92,'[1]26MY_PILOT_DATA'!B:V,15,FALSE) -> • | M92: =VLOOKUP(B92,'[1]26MY_PILOT_DATA'!B:V,16,FALSE) -> • | N92: =VLOOKUP(B92,'[1]26MY_PILOT_DATA'!B:V,17,FALSE) -> • | O92: =VLOOKUP(B92,'[1]26MY_PILOT_DATA'!B:V,18,FALSE) -> • | P92: =VLOOKUP(B92,'[1]26MY_PILOT_DATA'!B:V,19,FALSE) -> • | Q92: =IF(VLOOKUP(B92,'[1]26MY_PILOT_DATA'!B:V,21,FALSE)="","",VLOOKUP(B92,'[1]26MY_PILOT_DATA'!B:V,21,FALSE))
B93: 08L91-T90-XXXX | C93: =VLOOKUP(B93,'[1]26MY_PILOT_DATA'!B:V,4,FALSE) -> Pièces d’attelage de remorque
B94: 08L92-T90-100 | C94: =VLOOKUP(B94,'[1]26MY_PILOT_DATA'!B:V,4,FALSE) -> Attelage de remorque | D94: =B94 -> 08L92-T90-100 | E94: =VLOOKUP($B94,'[1]26MY_PILOT_DATA'!B:V,9,FALSE) -> 432 | F94: =VLOOKUP(B94,'[1]26MY_PILOT_DATA'!B:V,10,FALSE) -> 720 | G94: =VLOOKUP(B94,'[1]26MY_PILOT_DATA'!B:V,7,FALSE) -> 1.2 | H94: =VLOOKUP(B94,'[1]26MY_PILOT_DATA'!B:V,11,FALSE) -> 918 | I94: =VLOOKUP($B94,'[1]26MY_PILOT_DATA'!B:V,12,FALSE) -> 0 | J94: =VLOOKUP($B94,'[1]26MY_PILOT_DATA'!B:V,13,FALSE) -> 0 | K94: =VLOOKUP($B94,'[1]26MY_PILOT_DATA'!B:V,14,FALSE) -> 0 | L94: =VLOOKUP(B94,'[1]26MY_PILOT_DATA'!B:V,15,FALSE) -> • | M94: =VLOOKUP(B94,'[1]26MY_PILOT_DATA'!B:V,16,FALSE) -> • | N94: =VLOOKUP(B94,'[1]26MY_PILOT_DATA'!B:V,17,FALSE) -> S | O94: =VLOOKUP(B94,'[1]26MY_PILOT_DATA'!B:V,18,FALSE) -> • | P94: =VLOOKUP(B94,'[1]26MY_PILOT_DATA'!B:V,19,FALSE) -> • | Q94: =IF(VLOOKUP(B94,'[1]26MY_PILOT_DATA'!B:V,21,FALSE)="","",VLOOKUP(B94,'[1]26MY_PILOT_DATA'!B:V,21,FALSE)) -> Refroidisseur de transmission non requis pour le Pilot 2023. La capacité de remorquage est de 5000 livres. un capuchon d’attelage de remorque - 08L92-T90-300B/C **Touring et Black Edition nécessitent un adaptateur d’accès mains libres pour attelage de remorque - 08L91-T90-300A
B95: 08L91-T90-300B | C95: =VLOOKUP(B95,'[1]26MY_PILOT_DATA'!B:V,4,FALSE) -> Faisceau de remorque | D95: =B95 -> 08L91-T90-300B | E95: =VLOOKUP($B95,'[1]26MY_PILOT_DATA'!B:V,9,FALSE) -> 336 | F95: =VLOOKUP(B95,'[1]26MY_PILOT_DATA'!B:V,10,FALSE) -> 560 | G95: =VLOOKUP(B95,'[1]26MY_PILOT_DATA'!B:V,7,FALSE) -> 0.6 | H95: =VLOOKUP(B95,'[1]26MY_PILOT_DATA'!B:V,11,FALSE) -> 659 | I95: =VLOOKUP($B95,'[1]26MY_PILOT_DATA'!B:V,12,FALSE) -> 0 | J95: =VLOOKUP($B95,'[1]26MY_PILOT_DATA'!B:V,13,FALSE) -> 0 | K95: =VLOOKUP($B95,'[1]26MY_PILOT_DATA'!B:V,14,FALSE) -> 0 | L95: =VLOOKUP(B95,'[1]26MY_PILOT_DATA'!B:V,15,FALSE) -> • | M95: =VLOOKUP(B95,'[1]26MY_PILOT_DATA'!B:V,16,FALSE) -> • | N95: =VLOOKUP(B95,'[1]26MY_PILOT_DATA'!B:V,17,FALSE) -> • | O95: =VLOOKUP(B95,'[1]26MY_PILOT_DATA'!B:V,18,FALSE) -> • | P95: =VLOOKUP(B95,'[1]26MY_PILOT_DATA'!B:V,19,FALSE) -> • | Q95: =IF(VLOOKUP(B95,'[1]26MY_PILOT_DATA'!B:V,21,FALSE)="","",VLOOKUP(B95,'[1]26MY_PILOT_DATA'!B:V,21,FALSE))
B96: 08L91-T90-300-TS | C96: =VLOOKUP(B96,'[1]26MY_PILOT_DATA'!B:V,4,FALSE) -> Faisceau de remorque - TrailSport | D96: =D95 -> 08L91-T90-300B | E96: =VLOOKUP($B96,'[1]26MY_PILOT_DATA'!B:V,9,FALSE) -> 336 | F96: =VLOOKUP(B96,'[1]26MY_PILOT_DATA'!B:V,10,FALSE) -> 560 | G96: =VLOOKUP(B96,'[1]26MY_PILOT_DATA'!B:V,7,FALSE) -> 1.2 | H96: =VLOOKUP(B96,'[1]26MY_PILOT_DATA'!B:V,11,FALSE) -> 758 | I96: =VLOOKUP($B96,'[1]26MY_PILOT_DATA'!B:V,12,FALSE) -> 0 | J96: =VLOOKUP($B96,'[1]26MY_PILOT_DATA'!B:V,13,FALSE) -> 0 | K96: =VLOOKUP($B96,'[1]26MY_PILOT_DATA'!B:V,14,FALSE) -> 0 | L96: =VLOOKUP(B96,'[1]26MY_PILOT_DATA'!B:V,15,FALSE) -> N/A | M96: =VLOOKUP(B96,'[1]26MY_PILOT_DATA'!B:V,16,FALSE) -> N/A | N96: =VLOOKUP(B96,'[1]26MY_PILOT_DATA'!B:V,17,FALSE) -> • | O96: =VLOOKUP(B96,'[1]26MY_PILOT_DATA'!B:V,18,FALSE) -> N/A | P96: =VLOOKUP(B96,'[1]26MY_PILOT_DATA'!B:V,19,FALSE) -> N/A | Q96: =IF(VLOOKUP(B96,'[1]26MY_PILOT_DATA'!B:V,21,FALSE)="","",VLOOKUP(B96,'[1]26MY_PILOT_DATA'!B:V,21,FALSE)) -> Temps d’installation plus long pour la version TrailSport en raison de l’attelage de remorque de série.
B97: 08L92-T90-300D | C97: =VLOOKUP(B97,'[1]26MY_PILOT_DATA'!B:V,4,FALSE) -> Capuchon d’attelage de remorque noir | D97: =B97 -> 08L92-T90-300D | E97: =VLOOKUP($B97,'[1]26MY_PILOT_DATA'!B:V,9,FALSE) -> 150 | F97: =VLOOKUP(B97,'[1]26MY_PILOT_DATA'!B:V,10,FALSE) -> 250 | G97: =VLOOKUP(B97,'[1]26MY_PILOT_DATA'!B:V,7,FALSE) -> 0 | H97: =VLOOKUP(B97,'[1]26MY_PILOT_DATA'!B:V,11,FALSE) -> 250 | I97: =VLOOKUP($B97,'[1]26MY_PILOT_DATA'!B:V,12,FALSE) -> 0 | J97: =VLOOKUP($B97,'[1]26MY_PILOT_DATA'!B:V,13,FALSE) -> 0 | K97: =VLOOKUP($B97,'[1]26MY_PILOT_DATA'!B:V,14,FALSE) -> 0 | L97: =VLOOKUP(B97,'[1]26MY_PILOT_DATA'!B:V,15,FALSE) -> • | M97: =VLOOKUP(B97,'[1]26MY_PILOT_DATA'!B:V,16,FALSE) -> N/A | N97: =VLOOKUP(B97,'[1]26MY_PILOT_DATA'!B:V,17,FALSE) -> S | O97: =VLOOKUP(B97,'[1]26MY_PILOT_DATA'!B:V,18,FALSE) -> N/A | P97: =VLOOKUP(B97,'[1]26MY_PILOT_DATA'!B:V,19,FALSE) -> • | Q97: =IF(VLOOKUP(B97,'[1]26MY_PILOT_DATA'!B:V,21,FALSE)="","",VLOOKUP(B97,'[1]26MY_PILOT_DATA'!B:V,21,FALSE)) -> Nécessite pour l'attelage de remorque - 08L92-T90-100
B98: 08L92-T90-300E | C98: =VLOOKUP(B98,'[1]26MY_PILOT_DATA'!B:V,4,FALSE) -> Capuchon d’attelage de remorque argent | D98: =B98 -> 08L92-T90-300E | E98: =VLOOKUP($B98,'[1]26MY_PILOT_DATA'!B:V,9,FALSE) -> 150 | F98: =VLOOKUP(B98,'[1]26MY_PILOT_DATA'!B:V,10,FALSE) -> 250 | G98: =VLOOKUP(B98,'[1]26MY_PILOT_DATA'!B:V,7,FALSE) -> 0 | H98: =VLOOKUP(B98,'[1]26MY_PILOT_DATA'!B:V,11,FALSE) -> 250 | I98: =VLOOKUP($B98,'[1]26MY_PILOT_DATA'!B:V,12,FALSE) -> 0 | J98: =VLOOKUP($B98,'[1]26MY_PILOT_DATA'!B:V,13,FALSE) -> 0 | K98: =VLOOKUP($B98,'[1]26MY_PILOT_DATA'!B:V,14,FALSE) -> 0 | L98: =VLOOKUP(B98,'[1]26MY_PILOT_DATA'!B:V,15,FALSE) -> N/A | M98: =VLOOKUP(B98,'[1]26MY_PILOT_DATA'!B:V,16,FALSE) -> • | N98: =VLOOKUP(B98,'[1]26MY_PILOT_DATA'!B:V,17,FALSE) -> S | O98: =VLOOKUP(B98,'[1]26MY_PILOT_DATA'!B:V,18,FALSE) -> • | P98: =VLOOKUP(B98,'[1]26MY_PILOT_DATA'!B:V,19,FALSE) -> N/A | Q98: =IF(VLOOKUP(B98,'[1]26MY_PILOT_DATA'!B:V,21,FALSE)="","",VLOOKUP(B98,'[1]26MY_PILOT_DATA'!B:V,21,FALSE))
B99: 08L92-T90-100A | C99: =VLOOKUP(B99,'[1]26MY_PILOT_DATA'!B:V,4,FALSE) -> Attelage de remorque - montage sur boule | D99: =B99 -> 08L92-T90-100A | E99: =VLOOKUP($B99,'[1]26MY_PILOT_DATA'!B:V,9,FALSE) -> 57 | F99: =VLOOKUP(B99,'[1]26MY_PILOT_DATA'!B:V,10,FALSE) -> 95 | G99: =VLOOKUP(B99,'[1]26MY_PILOT_DATA'!B:V,7,FALSE) -> 0 | H99: =VLOOKUP(B99,'[1]26MY_PILOT_DATA'!B:V,11,FALSE) -> 95 | I99: =VLOOKUP($B99,'[1]26MY_PILOT_DATA'!B:V,12,FALSE) -> 0 | J99: =VLOOKUP($B99,'[1]26MY_PILOT_DATA'!B:V,13,FALSE) -> 0 | K99: =VLOOKUP($B99,'[1]26MY_PILOT_DATA'!B:V,14,FALSE) -> 0 | L99: =VLOOKUP(B99,'[1]26MY_PILOT_DATA'!B:V,15,FALSE) -> • | M99: =VLOOKUP(B99,'[1]26MY_PILOT_DATA'!B:V,16,FALSE) -> • | N99: =VLOOKUP(B99,'[1]26MY_PILOT_DATA'!B:V,17,FALSE) -> • | O99: =VLOOKUP(B99,'[1]26MY_PILOT_DATA'!B:V,18,FALSE) -> • | P99: =VLOOKUP(B99,'[1]26MY_PILOT_DATA'!B:V,19,FALSE) -> • | Q99: =IF(VLOOKUP(B99,'[1]26MY_PILOT_DATA'!B:V,21,FALSE)="","",VLOOKUP(B99,'[1]26MY_PILOT_DATA'!B:V,21,FALSE))
B100: 08L92-S9V-300G | C100: =VLOOKUP(B100,'[1]26MY_PILOT_DATA'!B:V,4,FALSE) -> Rotule d'attelage de 1 7/8 po | D100: =B100 -> 08L92-S9V-300G | E100: =VLOOKUP($B100,'[1]26MY_PILOT_DATA'!B:V,9,FALSE) -> 28 | F100: =VLOOKUP(B100,'[1]26MY_PILOT_DATA'!B:V,10,FALSE) -> 47 | G100: =VLOOKUP(B100,'[1]26MY_PILOT_DATA'!B:V,7,FALSE) -> 0 | H100: =VLOOKUP(B100,'[1]26MY_PILOT_DATA'!B:V,11,FALSE) -> 47 | I100: =VLOOKUP($B100,'[1]26MY_PILOT_DATA'!B:V,12,FALSE) -> 0 | J100: =VLOOKUP($B100,'[1]26MY_PILOT_DATA'!B:V,13,FALSE) -> 0 | K100: =VLOOKUP($B100,'[1]26MY_PILOT_DATA'!B:V,14,FALSE) -> 0 | L100: =VLOOKUP(B100,'[1]26MY_PILOT_DATA'!B:V,15,FALSE) -> • | M100: =VLOOKUP(B100,'[1]26MY_PILOT_DATA'!B:V,16,FALSE) -> • | N100: =VLOOKUP(B100,'[1]26MY_PILOT_DATA'!B:V,17,FALSE) -> • | O100: =VLOOKUP(B100,'[1]26MY_PILOT_DATA'!B:V,18,FALSE) -> • | P100: =VLOOKUP(B100,'[1]26MY_PILOT_DATA'!B:V,19,FALSE) -> • | Q100: =IF(VLOOKUP(B100,'[1]26MY_PILOT_DATA'!B:V,21,FALSE)="","",VLOOKUP(B100,'[1]26MY_PILOT_DATA'!B:V,21,FALSE))
B101: 08L92-S9V-300H | C101: =VLOOKUP(B101,'[1]26MY_PILOT_DATA'!B:V,4,FALSE) -> Rotule d'attelage de 2 po | D101: =B101 -> 08L92-S9V-300H | E101: =VLOOKUP($B101,'[1]26MY_PILOT_DATA'!B:V,9,FALSE) -> 28 | F101: =VLOOKUP(B101,'[1]26MY_PILOT_DATA'!B:V,10,FALSE) -> 47 | G101: =VLOOKUP(B101,'[1]26MY_PILOT_DATA'!B:V,7,FALSE) -> 0 | H101: =VLOOKUP(B101,'[1]26MY_PILOT_DATA'!B:V,11,FALSE) -> 47 | I101: =VLOOKUP($B101,'[1]26MY_PILOT_DATA'!B:V,12,FALSE) -> 0 | J101: =VLOOKUP($B101,'[1]26MY_PILOT_DATA'!B:V,13,FALSE) -> 0 | K101: =VLOOKUP($B101,'[1]26MY_PILOT_DATA'!B:V,14,FALSE) -> 0 | L101: =VLOOKUP(B101,'[1]26MY_PILOT_DATA'!B:V,15,FALSE) -> • | M101: =VLOOKUP(B101,'[1]26MY_PILOT_DATA'!B:V,16,FALSE) -> • | N101: =VLOOKUP(B101,'[1]26MY_PILOT_DATA'!B:V,17,FALSE) -> • | O101: =VLOOKUP(B101,'[1]26MY_PILOT_DATA'!B:V,18,FALSE) -> • | P101: =VLOOKUP(B101,'[1]26MY_PILOT_DATA'!B:V,19,FALSE) -> • | Q101: =IF(VLOOKUP(B101,'[1]26MY_PILOT_DATA'!B:V,21,FALSE)="","",VLOOKUP(B101,'[1]26MY_PILOT_DATA'!B:V,21,FALSE))
B102: 08L92-SJC-300A | C102: =VLOOKUP(B102,'[1]26MY_PILOT_DATA'!B:V,4,FALSE) -> Attelage de remorque - goupille de verrouillage | D102: =B102 -> 08L92-SJC-300A | E102: =VLOOKUP($B102,'[1]26MY_PILOT_DATA'!B:V,9,FALSE) -> 106 | F102: =VLOOKUP(B102,'[1]26MY_PILOT_DATA'!B:V,10,FALSE) -> 163 | G102: =VLOOKUP(B102,'[1]26MY_PILOT_DATA'!B:V,7,FALSE) -> 0 | H102: =VLOOKUP(B102,'[1]26MY_PILOT_DATA'!B:V,11,FALSE) -> 163 | I102: =VLOOKUP($B102,'[1]26MY_PILOT_DATA'!B:V,12,FALSE) -> 0 | J102: =VLOOKUP($B102,'[1]26MY_PILOT_DATA'!B:V,13,FALSE) -> 0 | K102: =VLOOKUP($B102,'[1]26MY_PILOT_DATA'!B:V,14,FALSE) -> 0 | L102: =VLOOKUP(B102,'[1]26MY_PILOT_DATA'!B:V,15,FALSE) -> • | M102: =VLOOKUP(B102,'[1]26MY_PILOT_DATA'!B:V,16,FALSE) -> • | N102: =VLOOKUP(B102,'[1]26MY_PILOT_DATA'!B:V,17,FALSE) -> • | O102: =VLOOKUP(B102,'[1]26MY_PILOT_DATA'!B:V,18,FALSE) -> • | P102: =VLOOKUP(B102,'[1]26MY_PILOT_DATA'!B:V,19,FALSE) -> • | Q102: =IF(VLOOKUP(B102,'[1]26MY_PILOT_DATA'!B:V,21,FALSE)="","",VLOOKUP(B102,'[1]26MY_PILOT_DATA'!B:V,21,FALSE))
B103: 08L04-T90-300 | C103: =VLOOKUP(B103,'[1]26MY_PILOT_DATA'!B:V,4,FALSE) -> Porte-bagages de toit | D103: =B103 -> 08L04-T90-300 | E103: =VLOOKUP($B103,'[1]26MY_PILOT_DATA'!B:V,9,FALSE) -> 246 | F103: =VLOOKUP(B103,'[1]26MY_PILOT_DATA'!B:V,10,FALSE) -> 410 | G103: =VLOOKUP(B103,'[1]26MY_PILOT_DATA'!B:V,7,FALSE) -> 0.2 | H103: =VLOOKUP(B103,'[1]26MY_PILOT_DATA'!B:V,11,FALSE) -> 443 | I103: =VLOOKUP($B103,'[1]26MY_PILOT_DATA'!B:V,12,FALSE) -> 0 | J103: =VLOOKUP($B103,'[1]26MY_PILOT_DATA'!B:V,13,FALSE) -> 0 | K103: =VLOOKUP($B103,'[1]26MY_PILOT_DATA'!B:V,14,FALSE) -> 0 | L103: =VLOOKUP(B103,'[1]26MY_PILOT_DATA'!B:V,15,FALSE) -> • | M103: =VLOOKUP(B103,'[1]26MY_PILOT_DATA'!B:V,16,FALSE) -> • | N103: =VLOOKUP(B103,'[1]26MY_PILOT_DATA'!B:V,17,FALSE) -> • | O103: =VLOOKUP(B103,'[1]26MY_PILOT_DATA'!B:V,18,FALSE) -> • | P103: =VLOOKUP(B103,'[1]26MY_PILOT_DATA'!B:V,19,FALSE) -> • | Q103: =IF(VLOOKUP(B103,'[1]26MY_PILOT_DATA'!B:V,21,FALSE)="","",VLOOKUP(B103,'[1]26MY_PILOT_DATA'!B:V,21,FALSE))
B104: 08LXX-E09-XXXX | C104: =VLOOKUP(B104,'[1]26MY_PILOT_DATA'!B:V,4,FALSE) -> Accessoires de toit
B105: 08L03-E09-300C | C105: =VLOOKUP(B105,'[1]26MY_PILOT_DATA'!B:V,4,FALSE) -> Galerie de toit, Fixation pour skis/planche à neige | D105: =B105 -> 08L03-E09-300C | E105: =VLOOKUP($B105,'[1]26MY_PILOT_DATA'!B:V,9,FALSE) -> 415 | F105: =VLOOKUP(B105,'[1]26MY_PILOT_DATA'!B:V,10,FALSE) -> 692 | G105: =VLOOKUP(B105,'[1]26MY_PILOT_DATA'!B:V,7,FALSE) -> 0.2 | H105: =VLOOKUP(B105,'[1]26MY_PILOT_DATA'!B:V,11,FALSE) -> 725 | I105: =VLOOKUP($B105,'[1]26MY_PILOT_DATA'!B:V,12,FALSE) -> 0 | J105: =VLOOKUP($B105,'[1]26MY_PILOT_DATA'!B:V,13,FALSE) -> 0 | K105: =VLOOKUP($B105,'[1]26MY_PILOT_DATA'!B:V,14,FALSE) -> 0 | L105: =VLOOKUP(B105,'[1]26MY_PILOT_DATA'!B:V,15,FALSE) -> • | M105: =VLOOKUP(B105,'[1]26MY_PILOT_DATA'!B:V,16,FALSE) -> • | N105: =VLOOKUP(B105,'[1]26MY_PILOT_DATA'!B:V,17,FALSE) -> • | O105: =VLOOKUP(B105,'[1]26MY_PILOT_DATA'!B:V,18,FALSE) -> • | P105: =VLOOKUP(B105,'[1]26MY_PILOT_DATA'!B:V,19,FALSE) -> • | Q105: =IF(VLOOKUP(B105,'[1]26MY_PILOT_DATA'!B:V,21,FALSE)="","",VLOOKUP(B105,'[1]26MY_PILOT_DATA'!B:V,21,FALSE)) -> Nécessite des barres de toit et des barres transversales.
B106: 08L07-E09-101 | C106: =VLOOKUP(B106,'[1]26MY_PILOT_DATA'!B:V,4,FALSE) -> Support à vélo vertical pour porte-bagages de toit | D106: =B106 -> 08L07-E09-101 | E106: =VLOOKUP($B106,'[1]26MY_PILOT_DATA'!B:V,9,FALSE) -> 383 | F106: =VLOOKUP(B106,'[1]26MY_PILOT_DATA'!B:V,10,FALSE) -> 547 | G106: =VLOOKUP(B106,'[1]26MY_PILOT_DATA'!B:V,7,FALSE) -> 0.4 | H106: =VLOOKUP(B106,'[1]26MY_PILOT_DATA'!B:V,11,FALSE) -> 613 | I106: =VLOOKUP($B106,'[1]26MY_PILOT_DATA'!B:V,12,FALSE) -> 0 | J106: =VLOOKUP($B106,'[1]26MY_PILOT_DATA'!B:V,13,FALSE) -> 0 | K106: =VLOOKUP($B106,'[1]26MY_PILOT_DATA'!B:V,14,FALSE) -> 0 | L106: =VLOOKUP(B106,'[1]26MY_PILOT_DATA'!B:V,15,FALSE) -> • | M106: =VLOOKUP(B106,'[1]26MY_PILOT_DATA'!B:V,16,FALSE) -> • | N106: =VLOOKUP(B106,'[1]26MY_PILOT_DATA'!B:V,17,FALSE) -> • | O106: =VLOOKUP(B106,'[1]26MY_PILOT_DATA'!B:V,18,FALSE) -> • | P106: =VLOOKUP(B106,'[1]26MY_PILOT_DATA'!B:V,19,FALSE) -> •
B107: 08L07-E09-300A | C107: =VLOOKUP(B107,'[1]26MY_PILOT_DATA'!B:V,4,FALSE) -> Fixation pour bicyclette – Ancrage de fourche | D107: =B107 -> 08L07-E09-300A | E107: =VLOOKUP($B107,'[1]26MY_PILOT_DATA'!B:V,9,FALSE) -> 292 | F107: =VLOOKUP(B107,'[1]26MY_PILOT_DATA'!B:V,10,FALSE) -> 487 | G107: =VLOOKUP(B107,'[1]26MY_PILOT_DATA'!B:V,7,FALSE) -> 0.4 | H107: =VLOOKUP(B107,'[1]26MY_PILOT_DATA'!B:V,11,FALSE) -> 553 | I107: =VLOOKUP($B107,'[1]26MY_PILOT_DATA'!B:V,12,FALSE) -> 0 | J107: =VLOOKUP($B107,'[1]26MY_PILOT_DATA'!B:V,13,FALSE) -> 0 | K107: =VLOOKUP($B107,'[1]26MY_PILOT_DATA'!B:V,14,FALSE) -> 0 | L107: =VLOOKUP(B107,'[1]26MY_PILOT_DATA'!B:V,15,FALSE) -> • | M107: =VLOOKUP(B107,'[1]26MY_PILOT_DATA'!B:V,16,FALSE) -> • | N107: =VLOOKUP(B107,'[1]26MY_PILOT_DATA'!B:V,17,FALSE) -> • | O107: =VLOOKUP(B107,'[1]26MY_PILOT_DATA'!B:V,18,FALSE) -> • | P107: =VLOOKUP(B107,'[1]26MY_PILOT_DATA'!B:V,19,FALSE) -> •
B108: 08L20-E09-300B | C108: =VLOOKUP(B108,'[1]26MY_PILOT_DATA'!B:V,4,FALSE) -> Boîte de toit courte | D108: =B108 -> 08L20-E09-300B | E108: =VLOOKUP($B108,'[1]26MY_PILOT_DATA'!B:V,9,FALSE) -> 799 | F108: =VLOOKUP(B108,'[1]26MY_PILOT_DATA'!B:V,10,FALSE) -> 1332 | G108: =VLOOKUP(B108,'[1]26MY_PILOT_DATA'!B:V,7,FALSE) -> 0.2 | H108: =VLOOKUP(B108,'[1]26MY_PILOT_DATA'!B:V,11,FALSE) -> 1365 | I108: =VLOOKUP($B108,'[1]26MY_PILOT_DATA'!B:V,12,FALSE) -> 0 | J108: =VLOOKUP($B108,'[1]26MY_PILOT_DATA'!B:V,13,FALSE) -> 0 | K108: =VLOOKUP($B108,'[1]26MY_PILOT_DATA'!B:V,14,FALSE) -> 0 | L108: =VLOOKUP(B108,'[1]26MY_PILOT_DATA'!B:V,15,FALSE) -> • | M108: =VLOOKUP(B108,'[1]26MY_PILOT_DATA'!B:V,16,FALSE) -> • | N108: =VLOOKUP(B108,'[1]26MY_PILOT_DATA'!B:V,17,FALSE) -> • | O108: =VLOOKUP(B108,'[1]26MY_PILOT_DATA'!B:V,18,FALSE) -> • | P108: =VLOOKUP(B108,'[1]26MY_PILOT_DATA'!B:V,19,FALSE) -> •
B109: 08L20-E09-300A | C109: =VLOOKUP(B109,'[1]26MY_PILOT_DATA'!B:V,4,FALSE) -> Boîte de toit – longue | D109: =B109 -> 08L20-E09-300A | E109: =VLOOKUP($B109,'[1]26MY_PILOT_DATA'!B:V,9,FALSE) -> 875 | F109: =VLOOKUP(B109,'[1]26MY_PILOT_DATA'!B:V,10,FALSE) -> 1458 | G109: =VLOOKUP(B109,'[1]26MY_PILOT_DATA'!B:V,7,FALSE) -> 0.2 | H109: =VLOOKUP(B109,'[1]26MY_PILOT_DATA'!B:V,11,FALSE) -> 1491 | I109: =VLOOKUP($B109,'[1]26MY_PILOT_DATA'!B:V,12,FALSE) -> 0 | J109: =VLOOKUP($B109,'[1]26MY_PILOT_DATA'!B:V,13,FALSE) -> 0 | K109: =VLOOKUP($B109,'[1]26MY_PILOT_DATA'!B:V,14,FALSE) -> 0 | L109: =VLOOKUP(B109,'[1]26MY_PILOT_DATA'!B:V,15,FALSE) -> • | M109: =VLOOKUP(B109,'[1]26MY_PILOT_DATA'!B:V,16,FALSE) -> • | N109: =VLOOKUP(B109,'[1]26MY_PILOT_DATA'!B:V,17,FALSE) -> • | O109: =VLOOKUP(B109,'[1]26MY_PILOT_DATA'!B:V,18,FALSE) -> • | P109: =VLOOKUP(B109,'[1]26MY_PILOT_DATA'!B:V,19,FALSE) -> •
B110: 08L20-E09-101C | C110: =VLOOKUP(B110,'[1]26MY_PILOT_DATA'!B:V,4,FALSE) -> Panier de toit | D110: =B110 -> 08L20-E09-101C | E110: =VLOOKUP($B110,'[1]26MY_PILOT_DATA'!B:V,9,FALSE) -> 571 | F110: =VLOOKUP(B110,'[1]26MY_PILOT_DATA'!B:V,10,FALSE) -> 952 | G110: =VLOOKUP(B110,'[1]26MY_PILOT_DATA'!B:V,7,FALSE) -> 0.4 | H110: =VLOOKUP(B110,'[1]26MY_PILOT_DATA'!B:V,11,FALSE) -> 1018 | I110: =VLOOKUP($B110,'[1]26MY_PILOT_DATA'!B:V,12,FALSE) -> 0 | J110: =VLOOKUP($B110,'[1]26MY_PILOT_DATA'!B:V,13,FALSE) -> 0 | K110: =VLOOKUP($B110,'[1]26MY_PILOT_DATA'!B:V,14,FALSE) -> 0 | L110: =VLOOKUP(B110,'[1]26MY_PILOT_DATA'!B:V,15,FALSE) -> • | M110: =VLOOKUP(B110,'[1]26MY_PILOT_DATA'!B:V,16,FALSE) -> • | N110: =VLOOKUP(B110,'[1]26MY_PILOT_DATA'!B:V,17,FALSE) -> • | O110: =VLOOKUP(B110,'[1]26MY_PILOT_DATA'!B:V,18,FALSE) -> • | P110: =VLOOKUP(B110,'[1]26MY_PILOT_DATA'!B:V,19,FALSE) -> •
B111: 08L09-E09-101 | C111: =VLOOKUP(B111,'[1]26MY_PILOT_DATA'!B:V,4,FALSE) -> Galerie de toit, fixation pour kayak | D111: =B111 -> 08L09-E09-101 | E111: =VLOOKUP($B111,'[1]26MY_PILOT_DATA'!B:V,9,FALSE) -> 430 | F111: =VLOOKUP(B111,'[1]26MY_PILOT_DATA'!B:V,10,FALSE) -> 717 | G111: =VLOOKUP(B111,'[1]26MY_PILOT_DATA'!B:V,7,FALSE) -> 0.4 | H111: =VLOOKUP(B111,'[1]26MY_PILOT_DATA'!B:V,11,FALSE) -> 783 | I111: =VLOOKUP($B111,'[1]26MY_PILOT_DATA'!B:V,12,FALSE) -> 0 | J111: =VLOOKUP($B111,'[1]26MY_PILOT_DATA'!B:V,13,FALSE) -> 0 | K111: =VLOOKUP($B111,'[1]26MY_PILOT_DATA'!B:V,14,FALSE) -> 0 | L111: =VLOOKUP(B111,'[1]26MY_PILOT_DATA'!B:V,15,FALSE) -> • | M111: =VLOOKUP(B111,'[1]26MY_PILOT_DATA'!B:V,16,FALSE) -> • | N111: =VLOOKUP(B111,'[1]26MY_PILOT_DATA'!B:V,17,FALSE) -> • | O111: =VLOOKUP(B111,'[1]26MY_PILOT_DATA'!B:V,18,FALSE) -> • | P111: =VLOOKUP(B111,'[1]26MY_PILOT_DATA'!B:V,19,FALSE) -> •
B112: 08L08-T90-300 | C112: =VLOOKUP(B112,'[1]26MY_PILOT_DATA'!B:V,4,FALSE) -> Plateforme de toit | D112: =B112 -> 08L08-T90-300 | E112: =VLOOKUP($B112,'[1]26MY_PILOT_DATA'!B:V,9,FALSE) -> 849 | F112: =VLOOKUP(B112,'[1]26MY_PILOT_DATA'!B:V,10,FALSE) -> 1369 | G112: =VLOOKUP(B112,'[1]26MY_PILOT_DATA'!B:V,7,FALSE) -> 0.6 | H112: =VLOOKUP(B112,'[1]26MY_PILOT_DATA'!B:V,11,FALSE) -> 1468 | I112: =VLOOKUP($B112,'[1]26MY_PILOT_DATA'!B:V,12,FALSE) -> 0 | J112: =VLOOKUP($B112,'[1]26MY_PILOT_DATA'!B:V,13,FALSE) -> 0 | K112: =VLOOKUP($B112,'[1]26MY_PILOT_DATA'!B:V,14,FALSE) -> 0 | L112: =VLOOKUP(B112,'[1]26MY_PILOT_DATA'!B:V,15,FALSE) -> • | M112: =VLOOKUP(B112,'[1]26MY_PILOT_DATA'!B:V,16,FALSE) -> • | N112: =VLOOKUP(B112,'[1]26MY_PILOT_DATA'!B:V,17,FALSE) -> • | O112: =VLOOKUP(B112,'[1]26MY_PILOT_DATA'!B:V,18,FALSE) -> • | P112: =VLOOKUP(B112,'[1]26MY_PILOT_DATA'!B:V,19,FALSE) -> •
...

Sheet 26MY_Pilot_SELL_FR
B3: 26MY Honda Pilot
B4: 200
B6: ACCESSOIRES POPULAIRES
B7: 20
B8: 150
B10: 20 | C10: ='26MY_Pilot_APP_FR'!$C$131 -> Protège-tapis toutes saisons | H10: ='26MY_Pilot_APP_FR'!$C$133 -> Plateau de compartiment à bagages | M10: ='26MY_Pilot_APP_FR'!$C$153 -> Garniture lumineuses de bas de portière
B11: 20 | C11: ='26MY_Pilot_APP_FR'!$H$131 -> 374.5 | D11: =-PMT($D$29/52,5*52,C11) -> 1.7076821 | E11: /wk * | F11: =$C$29 -> (6.99%) | H11: ='26MY_Pilot_APP_FR'!$H$133 -> 211.5 | I11: =-PMT($D$29/52,5*52,H11) -> 0.9644186 | J11: /wk * | K11: =$C$29 -> (6.99%) | M11: ='26MY_Pilot_APP_FR'!$H$153 -> 802.5 | N11: =-PMT($D$29/52,5*52,M11) -> 3.6593188 | O11: /wk * | P11: =$C$29 -> (6.99%)
B13: 150
B15: 20 | C15: ='26MY_Pilot_APP_FR'!$C$103 -> Porte-bagages de toit | H15: ='26MY_Pilot_APP_FR'!$C$92 -> Visières de portière | M15: Emblème, noirs lustré - Logo « H » & « AWD »
B16: 50 | C16: ='26MY_Pilot_APP_FR'!$H$103 -> 443 | D16: =-PMT($D$29/52,5*52,C16) -> 2.0200352 | E16: /wk * | F16: =$C$29 -> (6.99%) | H16: ='26MY_Pilot_APP_FR'!$H$92 -> 529 | I16: =-PMT($D$29/52,5*52,H16) -> 2.4121865 | J16: /wk * | K16: =$C$29 -> (6.99%) | M16: =SUM('26MY_Pilot_APP_FR'!$H$85+'26MY_Pilot_APP_FR'!$H$86) -> 192 | N16: =-PMT($D$29/52,5*52,M16) -> 0.87550058 | O16: /wk * | P16: =$C$29 -> (6.99%)
B18: 150
B20: 20 | C20: ='26MY_Pilot_APP_FR'!$C$90 -> Marchepieds robustes | H20: Ensemble de remorquage touring version | M20: ='26MY_Pilot_APP_FR'!$C$143 -> Barrière de séparation
B21: 50 | C21: ='26MY_Pilot_APP_FR'!$H$90 -> 1452.5 | D21: =-PMT($D$29/52,5*52,C21) -> 6.623253 | E21: /wk * | F21: =$C$29 -> (6.99%) | H21: =SUM('26MY_Pilot_APP_FR'!$H$40:$H$46) -> 2385.3 | I21: =-PMT($D$29/52,5*52,H21) -> 10.876727 | J21: /wk * | K21: =$C$29 -> (6.99%) | M21: ='26MY_Pilot_APP_FR'!$H$143 -> 1159 | N21: =-PMT($D$29/52,5*52,M21) -> 5.2849227 | O21: /wk * | P21: =$C$29 -> (6.99%)
C23: Les accessoires Honda d’origine achetés avec un véhicule Honda neuf incluent une garantie du fabricant de 3 ans ou 60 000 km.
C24: Les accessoires de véhicule achetés après la vente du véhicule incluent une garantie du fabricant de 1 an ou 20 000 km.
B25: 20 | C25: *Les prix indiqués incluent le coût d'installation.
B26: 60 | C26: *À titre d’information seulement. Les montants hebdomadaires indiqués sont des paiements estimés basés sur un contrat de financement de 60 mois à un taux annuel en pourcentage (TAP) de 6,99 % (coût d’installation compris). Taxes et frais applicables en sus. Les accessoires ne peuvent être financés seuls et doivent être financés par l’entremise de Honda Canada Finance Inc., sur approbation de crédit, conjointement avec un véhicule Honda. Exemple de financement représentatif : Un montant de 350,00 $ financé à un TAP de 6,99 % équivaut à un paiement hebdomadaire de 1,60 $ pendant 60 mois. 260 paiements hebdomadaires sont requis. Le coût d’emprunt est de 64,80 $, pour une obligation totale de 414,80 $. Le montant réel des paiements variera en fonction du TAP, de la période du contrat de financement et du coût des accessoires applicables. Certaines conditions s’appliquent. Veuillez visiter votre concessionnaire Honda pour obtenir tous les détails.
C27: *Vous pouvez voir d’autres options de paiements hebdomadaires personnalisés ainsi que des accessoires sur le site Honda.ca – Configuration et prix.
B28: 20
B29: 18 | C29: (6.99%) | D29: 0.0699
B30: 7.5 | C30: 12 | D30: 8 | E30: 8 | F30: 10 | G30: 8.5 | H30: 12 | I30: 8 | J30: 8 | K30: 10 | L30: 8.5 | M30: 12 | N30: 8 | O30: 8 | P30: 10 | Q30: 7.5
B31: Date de publication: | C31: ='[1]26MY_PILOT_DATA'!$C$4 -> 46076 | D31: Tout prix, spécifications de versions et disponibilté d'accessoires publiés sont sujets à changer sans pré-avis. | P31: Province | Q31: ='[1]26MY_PILOT_DATA'!L6 -> YT
